{
  "type": "Feature",
  "properties": {
    "gn:admin1_code":"1.0",
    "gn:asciiname":"Hayfa",
    "gn:country_code":"SY",
    "gn:dem":365,
    "gn:feature_class":"P",
    "gn:feature_code":"PPL",
    "gn:name":"\u1e28ayf\u0101",
    "gn:population":0,
    "gn:timezone":"Asia/Damascus",
    "iso:country":"SY",
    "name:ara_x_preferred":[
        "\u062d\u064a\u0641\u0627"
    ],
    "name:ara_x_variant":[
        "\u062e\u0631\u0627\u0628 \u0631\u0643\u0627\u0628\u0629"
    ],
    "name:kur_x_preferred":[
        "\u0631\u06ce\u0643 \u0626\u0627\u06a4\u0627"
    ],
    "name:und_x_variant":[
        "\u1e28ayf\u0101"
    ],
    "wof:name":"Hayfa",
    "wof:placetype":"locality"
},
  "geometry": {"coordinates":[42.29361,37.15583],"type":"Point"}
}