{
  "type": "Feature",
  "properties": {
    "gn:admin1_code":"1.0",
    "gn:asciiname":"Hayfa",
    "gn:country_code":"SY",
    "gn:dem":365,
    "gn:feature_class":"P",
    "gn:feature_code":"PPL",
    "gn:name":"\u1e28ayf\u0101",
    "gn:population":0,
    "gn:timezone":"Asia/Damascus",
    "iso:country":"SY",
    "name:und_x_variant":[
        "\u1e28ayf\u0101"
    ],
    "wof:name":"Hayfa",
    "wof:placetype":"locality"
},
  "geometry": {"coordinates":[42.29361,37.15583],"type":"Point"}
}