{
  "type": "Feature",
  "properties": {
    "gn:admin1_code":"9.0",
    "gn:asciiname":"Sanjaq",
    "gn:country_code":"SY",
    "gn:dem":538,
    "gn:feature_class":"P",
    "gn:feature_code":"PPL",
    "gn:name":"Sanjaq",
    "gn:population":0,
    "gn:timezone":"Asia/Damascus",
    "iso:country":"SY",
    "name:ara_x_preferred":[
        "\u0633\u0646\u062c\u0642"
    ],
    "name:und_x_variant":[
        "Sanndjaq",
        "Sanjaq"
    ],
    "wof:name":"Sanjaq",
    "wof:placetype":"locality"
},
  "geometry": {"coordinates":[38.32664000000001,36.78189],"type":"Point"}
}