{
  "type": "Feature",
  "properties": {
    "gn:admin1_code":"14.0",
    "gn:asciiname":"Ad Duwayliyah",
    "gn:country_code":"SY",
    "gn:dem":826,
    "gn:feature_class":"P",
    "gn:feature_code":"PPL",
    "gn:name":"Ad Duwayl\u012byah",
    "gn:population":0,
    "gn:timezone":"Asia/Damascus",
    "iso:country":"SY",
    "name:ara_x_preferred":[
        "\u0627\u0644\u062f\u0648\u064a\u0644\u064a\u0629"
    ],
    "name:und_x_variant":[
        "Ed Doua\u00efl\u00eey\u00e9",
        "Ad Duwayl\u012byah"
    ],
    "wof:name":"Ad Duwayliyah",
    "wof:placetype":"locality"
},
  "geometry": {"coordinates":[36.13995,35.13479],"type":"Point"}
}