{
  "type": "Feature",
  "properties": {
    "gn:admin1_code":"9.0",
    "gn:asciiname":"Murabba`at Sallum",
    "gn:country_code":"SY",
    "gn:dem":422,
    "gn:feature_class":"P",
    "gn:feature_code":"PPL",
    "gn:name":"Murabba\u2018at Sall\u016bm",
    "gn:population":0,
    "gn:timezone":"Asia/Damascus",
    "iso:country":"SY",
    "name:ara_x_preferred":[
        "\u0645\u0631\u0628\u0639\u0629 \u0633\u0644\u0648\u0645"
    ],
    "name:und_x_variant":[
        "Mourabbaet Sallo\u00fbm",
        "Murabba\u2018at Sall\u016bm"
    ],
    "wof:name":"Murabba`at Sallum",
    "wof:placetype":"locality"
},
  "geometry": {"coordinates":[37.39154,35.79306],"type":"Point"}
}