{
  "type": "Feature",
  "properties": {
    "gn:admin1_code":"12.0",
    "gn:asciiname":"Tall at Tawil",
    "gn:country_code":"SY",
    "gn:dem":404,
    "gn:feature_class":"P",
    "gn:feature_code":"PPL",
    "gn:name":"Tall a\u0163 \u0162aw\u012bl",
    "gn:population":0,
    "gn:timezone":"Asia/Damascus",
    "iso:country":"SY",
    "wof:name":"Tall at Tawil",
    "wof:placetype":"locality"
},
  "geometry": {"coordinates":[36.8125,35.54167],"type":"Point"}
}