{
  "type": "Feature",
  "properties": {
    "gn:admin1_code":"11.0",
    "gn:asciiname":"Al Bayda",
    "gn:country_code":"SY",
    "gn:dem":476,
    "gn:feature_class":"P",
    "gn:feature_code":"PPLL",
    "gn:name":"Al Bay\u1e11\u0101",
    "gn:population":0,
    "gn:timezone":"Asia/Damascus",
    "iso:country":"SY",
    "name:ara_x_preferred":[
        "\u0627\u0644\u0628\u064a\u0636\u0627"
    ],
    "name:ben_x_preferred":[
        "\u0986\u09b2 \u09ac\u09be\u0987\u09a6\u09be"
    ],
    "name:deu_x_preferred":[
        "Al Bayda"
    ],
    "name:ell_x_preferred":[
        "\u0391\u03bb \u039c\u03c0\u03ac\u03b9\u03bd\u03c4\u03b1"
    ],
    "name:hin_x_preferred":[
        "\u0905\u0932 \u092c\u093e\u092f\u0926\u093e"
    ],
    "name:hun_x_preferred":[
        "Al Bayda"
    ],
    "name:ind_x_preferred":[
        "Al Bayda"
    ],
    "name:kor_x_preferred":[
        "\uc54c \ubc14\uc774\ub2e4"
    ],
    "name:spa_x_preferred":[
        "Al Baida"
    ],
    "name:tur_x_preferred":[
        "Al Bayda"
    ],
    "name:und_x_variant":[
        "Al Bay\u1e11\u0101"
    ],
    "name:vie_x_preferred":[
        "Al Bayda"
    ],
    "wof:name":"Al Bayda",
    "wof:placetype":"locality"
},
  "geometry": {"coordinates":[37.95734,34.51237],"type":"Point"}
}