{
  "type": "Feature",
  "properties": {
    "gn:admin1_code":"11.0",
    "gn:asciiname":"Al Bayda",
    "gn:country_code":"SY",
    "gn:dem":476,
    "gn:feature_class":"P",
    "gn:feature_code":"PPLL",
    "gn:name":"Al Bay\u1e11\u0101",
    "gn:population":0,
    "gn:timezone":"Asia/Damascus",
    "iso:country":"SY",
    "name:ara_x_preferred":[
        "\u0627\u0644\u0628\u064a\u0636\u0627"
    ],
    "name:und_x_variant":[
        "Al Bay\u1e11\u0101"
    ],
    "wof:name":"Al Bayda",
    "wof:placetype":"locality"
},
  "geometry": {"coordinates":[37.95734,34.51237],"type":"Point"}
}