{
  "type": "Feature",
  "properties": {
    "gn:admin1_code":"9.0",
    "gn:asciiname":"`Ashunah",
    "gn:country_code":"SY",
    "gn:dem":637,
    "gn:feature_class":"P",
    "gn:feature_code":"PPL",
    "gn:name":"\u2018Ash\u016bnah",
    "gn:population":0,
    "gn:timezone":"Asia/Damascus",
    "iso:country":"SY",
    "name:ara_x_preferred":[
        "\u0639\u0634\u0648\u0634\u0629"
    ],
    "name:ara_x_variant":[
        "\u0639\u0634\u0648\u0646\u0629"
    ],
    "name:und_x_variant":[
        "\u2018Ash\u016bshah",
        "\u2018Ash\u016bnah"
    ],
    "wof:name":"`Ashunah",
    "wof:placetype":"locality"
},
  "geometry": {"coordinates":[36.78434,36.69588],"type":"Point"}
}