{
  "type": "Feature",
  "properties": {
    "gn:admin1_code":"1.0",
    "gn:asciiname":"Jabal ar Ra'is Juraynas",
    "gn:country_code":"SY",
    "gn:dem":352,
    "gn:feature_class":"P",
    "gn:feature_code":"PPL",
    "gn:name":"Jabal ar Ra\u2019\u012bs Jurayn\u0101s",
    "gn:population":0,
    "gn:timezone":"Asia/Damascus",
    "iso:country":"SY",
    "name:ara_x_preferred":[
        "\u062c\u0628\u0644 \u0627\u0644\u0631\u0626\u064a\u0633 \u062c\u0631\u064a\u0646\u0627\u0633"
    ],
    "name:und_x_variant":[
        "Jabal ar Ra\u2019\u012bs Jurayn\u0101s"
    ],
    "wof:name":"Jabal ar Ra'is Juraynas",
    "wof:placetype":"locality"
},
  "geometry": {"coordinates":[40.24684,36.68054],"type":"Point"}
}