{
  "type": "Feature",
  "properties": {
    "gn:admin1_code":"4.0",
    "gn:asciiname":"Dij",
    "gn:country_code":"SY",
    "gn:dem":367,
    "gn:feature_class":"P",
    "gn:feature_code":"PPL",
    "gn:name":"D\u012bj",
    "gn:population":0,
    "gn:timezone":"Asia/Damascus",
    "iso:country":"SY",
    "name:ara_x_preferred":[
        "D\u012bk"
    ],
    "name:ara_x_variant":[
        "D\u012bj",
        "\u062f\u064a\u062c"
    ],
    "name:und_x_variant":[
        "D\u00eetch",
        "D\u012btsh"
    ],
    "wof:name":"Dij",
    "wof:placetype":"locality"
},
  "geometry": {"coordinates":[38.84122,36.64337],"type":"Point"}
}