{
  "type": "Feature",
  "properties": {
    "gn:admin1_code":"14.0",
    "gn:asciiname":"Ard al Kurum",
    "gn:country_code":"SY",
    "gn:dem":41,
    "gn:feature_class":"P",
    "gn:feature_code":"PPLL",
    "gn:name":"Ar\u1e11 al Kur\u016bm",
    "gn:population":0,
    "gn:timezone":"Asia/Damascus",
    "iso:country":"SY",
    "name:ara_x_preferred":[
        "\u0623\u0631\u0636 \u0627\u0644\u0643\u0631\u0648\u0645"
    ],
    "name:und_x_variant":[
        "Ar\u1e11 al Kur\u016bm"
    ],
    "wof:name":"Ard al Kurum",
    "wof:placetype":"locality"
},
  "geometry": {"coordinates":[35.97065999999999,34.7944],"type":"Point"}
}