{
  "type": "Feature",
  "properties": {
    "gn:admin1_code":"10.0",
    "gn:asciiname":"Al Jammasiyah",
    "gn:country_code":"SY",
    "gn:dem":172,
    "gn:feature_class":"P",
    "gn:feature_code":"PPL",
    "gn:name":"Al Jamm\u0101s\u012byah",
    "gn:population":0,
    "gn:timezone":"Asia/Damascus",
    "iso:country":"SY",
    "name:ara_x_preferred":[
        "\u0627\u0644\u062c\u0645\u0627\u0633\u064a\u0629"
    ],
    "name:und_x_variant":[
        "Ej Jamm\u00e2ss\u00eey\u00e9",
        "Al Jamm\u0101s\u012byah"
    ],
    "wof:name":"Al Jammasiyah",
    "wof:placetype":"locality"
},
  "geometry": {"coordinates":[36.35915,35.44108],"type":"Point"}
}