{
  "type": "Feature",
  "properties": {
    "gn:admin1_code":"11.0",
    "gn:asciiname":"Umm Jami'",
    "gn:country_code":"SY",
    "gn:dem":764,
    "gn:feature_class":"P",
    "gn:feature_code":"PPL",
    "gn:name":"Umm J\u0101mi\u2019",
    "gn:population":0,
    "gn:timezone":"Asia/Damascus",
    "iso:country":"SY",
    "name:ara_x_preferred":[
        "\u0623\u0645 \u062d\u0627\u0645\u0629"
    ],
    "name:ara_x_variant":[
        "\u0623\u0645 \u062c\u0627\u0645\u0639"
    ],
    "name:und_x_variant":[
        "Umm J\u0101mah",
        "Umm \u1e28\u0101mah",
        "Umm J\u0101mi\u2019",
        "Umm Jurn"
    ],
    "wof:name":"Umm Jami'",
    "wof:placetype":"locality"
},
  "geometry": {"coordinates":[37.17004,34.74056],"type":"Point"}
}