{
  "type": "Feature",
  "properties": {
    "gn:admin1_code":"9.0",
    "gn:asciiname":"Rujaylah",
    "gn:country_code":"SY",
    "gn:dem":306,
    "gn:feature_class":"P",
    "gn:feature_code":"PPL",
    "gn:name":"Rujaylah",
    "gn:population":0,
    "gn:timezone":"Asia/Damascus",
    "iso:country":"SY",
    "name:ara_x_preferred":[
        "\u0631\u062c\u064a\u0644\u0629"
    ],
    "name:und_x_variant":[
        "Erdjil\u00e9",
        "Arje\u00efl\u00e9",
        "Urjaylah",
        "Rujaylah"
    ],
    "wof:name":"Rujaylah",
    "wof:placetype":"locality"
},
  "geometry": {"coordinates":[37.23074,35.86602],"type":"Point"}
}