{
  "type": "Feature",
  "properties": {
    "gn:admin1_code":"11.0",
    "gn:asciiname":"An Nazimiyah",
    "gn:country_code":"SY",
    "gn:dem":485,
    "gn:feature_class":"P",
    "gn:feature_code":"PPL",
    "gn:name":"An N\u0101z\u0327im\u012byah",
    "gn:population":0,
    "gn:timezone":"Asia/Damascus",
    "iso:country":"SY",
    "name:ara_x_preferred":[
        "\u0627\u0644\u0646\u0627\u0638\u0645\u064a\u0629"
    ],
    "name:und_x_variant":[
        "An N\u0101z\u0327im\u012byah"
    ],
    "wof:name":"An Nazimiyah",
    "wof:placetype":"locality"
},
  "geometry": {"coordinates":[36.77805,34.85123],"type":"Point"}
}