{
  "type": "Feature",
  "properties": {
    "gn:admin1_code":"2.0",
    "gn:asciiname":"At Turbah",
    "gn:country_code":"SY",
    "gn:dem":231,
    "gn:feature_class":"P",
    "gn:feature_code":"PPL",
    "gn:name":"At Turbah",
    "gn:population":0,
    "gn:timezone":"Asia/Damascus",
    "iso:country":"SY",
    "name:ara_x_preferred":[
        "\u062a\u0631\u0628\u0629"
    ],
    "name:ara_x_variant":[
        "\u0627\u0644\u062a\u0631\u0628\u0629"
    ],
    "name:nno_x_preferred":[
        "At Turbah"
    ],
    "name:rus_x_preferred":[
        "\u042d\u0442-\u0422\u0443\u0440\u0431\u0430"
    ],
    "name:und_x_variant":[
        "Tirbah",
        "Terb\u00e9",
        "Turbah",
        "Turbeh"
    ],
    "wof:name":"At Turbah",
    "wof:placetype":"locality"
},
  "geometry": {"coordinates":[35.8923,35.66245],"type":"Point"}
}