{
  "type": "Feature",
  "properties": {
    "gn:admin1_code":"1.0",
    "gn:asciiname":"Muzayri`ah",
    "gn:country_code":"SY",
    "gn:dem":415,
    "gn:feature_class":"P",
    "gn:feature_code":"PPL",
    "gn:name":"Muzayri\u2018ah",
    "gn:population":0,
    "gn:timezone":"Asia/Damascus",
    "iso:country":"SY",
    "name:ara_x_preferred":[
        "\u0645\u0632\u064a\u0631\u0639\u0629"
    ],
    "name:tur_x_preferred":[
        "Muzayri\u2018ah"
    ],
    "name:und_x_variant":[
        "Mza\u00efra\u00e2"
    ],
    "wof:name":"Muzayri`ah",
    "wof:placetype":"locality"
},
  "geometry": {"coordinates":[40.70249,36.86183],"type":"Point"}
}