{
  "type": "Feature",
  "properties": {
    "gn:admin1_code":"4.0",
    "gn:asciiname":"Mazra`at Ja`bar",
    "gn:country_code":"SY",
    "gn:dem":302,
    "gn:feature_class":"P",
    "gn:feature_code":"PPL",
    "gn:name":"Mazra\u2018at Ja\u2018b\u0101r",
    "gn:population":0,
    "gn:timezone":"Asia/Damascus",
    "iso:country":"SY",
    "name:ara_x_preferred":[
        "\u0645\u0632\u0631\u0639\u0629 \u062c\u0639\u0628\u0627\u0631"
    ],
    "name:und_x_variant":[
        "Mazra\u2018at Ja\u2018b\u0101r"
    ],
    "wof:name":"Mazra`at Ja`bar",
    "wof:placetype":"locality"
},
  "geometry": {"coordinates":[38.48495,35.90392999999999],"type":"Point"}
}