{
  "type": "Feature",
  "properties": {
    "gn:admin1_code":"1.0",
    "gn:asciiname":"Umm Hajarah",
    "gn:country_code":"SY",
    "gn:dem":272,
    "gn:feature_class":"P",
    "gn:feature_code":"PPL",
    "gn:name":"Umm \u1e28ajarah",
    "gn:population":0,
    "gn:timezone":"Asia/Damascus",
    "iso:country":"SY",
    "name:ara_x_preferred":[
        "\u0623\u0645 \u062d\u062c\u0631\u0629"
    ],
    "name:und_x_variant":[
        "Umm \u1e28ajarah"
    ],
    "wof:name":"Umm Hajarah",
    "wof:placetype":"locality"
},
  "geometry": {"coordinates":[40.82265,36.05941],"type":"Point"}
}