{
  "type": "Feature",
  "properties": {
    "gn:admin1_code":"9.0",
    "gn:asciiname":"Suraysirah",
    "gn:country_code":"SY",
    "gn:dem":478,
    "gn:feature_class":"P",
    "gn:feature_code":"PPL",
    "gn:name":"\u015euray\u015f\u012brah",
    "gn:population":0,
    "gn:timezone":"Asia/Damascus",
    "iso:country":"SY",
    "name:ara_x_preferred":[
        "Sr\u00e9s\u00e0re"
    ],
    "name:ara_x_variant":[
        "\u0635\u0631\u064a\u0635\u064a\u0631\u0629"
    ],
    "name:und_x_variant":[
        "Sr\u00e9ss\u00eer\u00e9",
        "Sreser",
        "\u015euray\u015f\u012brah"
    ],
    "wof:name":"Suraysirah",
    "wof:placetype":"locality"
},
  "geometry": {"coordinates":[36.85733,36.23998],"type":"Point"}
}