{
  "type": "Feature",
  "properties": {
    "gn:admin1_code":"9.0",
    "gn:asciiname":"Talatinah",
    "gn:country_code":"SY",
    "gn:dem":499,
    "gn:feature_class":"P",
    "gn:feature_code":"PPL",
    "gn:name":"Tal\u0101t\u012bnah",
    "gn:population":0,
    "gn:timezone":"Asia/Damascus",
    "iso:country":"SY",
    "name:ara_x_preferred":[
        "\u062a\u0644\u0627\u062a\u064a\u0646\u0629"
    ],
    "name:und_x_variant":[
        "Tal\u0101t\u012bnah"
    ],
    "wof:name":"Talatinah",
    "wof:placetype":"locality"
},
  "geometry": {"coordinates":[37.33988,36.46457],"type":"Point"}
}