{
  "type": "Feature",
  "properties": {
    "gn:admin1_code":"7.0",
    "gn:asciiname":"Al Jurdi al Gharbi",
    "gn:country_code":"SY",
    "gn:dem":184,
    "gn:feature_class":"P",
    "gn:feature_code":"PPL",
    "gn:name":"Al Jurd\u012b al Gharb\u012b",
    "gn:population":0,
    "gn:timezone":"Asia/Damascus",
    "iso:country":"SY",
    "name:ara_x_preferred":[
        "\u0627\u0644\u062c\u0631\u062f\u064a \u0627\u0644\u063a\u0631\u0628\u064a"
    ],
    "name:und_x_variant":[
        "Jaraz\u012b",
        "Al Jurd\u012b Gharb\u012b",
        "Jerdi",
        "Jirz\u012b",
        "Jerzi",
        "Jirdh\u012b",
        "Al Jurd\u012b al Gharb\u012b"
    ],
    "wof:name":"Al Jurdi al Gharbi",
    "wof:placetype":"locality"
},
  "geometry": {"coordinates":[40.60273,34.8836],"type":"Point"}
}