{
  "type": "Feature",
  "properties": {
    "gn:admin1_code":"9.0",
    "gn:asciiname":"Murayghil",
    "gn:country_code":"SY",
    "gn:dem":467,
    "gn:feature_class":"P",
    "gn:feature_code":"PPL",
    "gn:name":"Murayghil",
    "gn:population":0,
    "gn:timezone":"Asia/Damascus",
    "iso:country":"SY",
    "name:ara_x_preferred":[
        "\u0645\u0631\u064a\u063a\u0644"
    ],
    "name:fas_x_preferred":[
        "\u0645\u0631\u06cc\u063a\u0644"
    ],
    "name:pol_x_preferred":[
        "Murajghil"
    ],
    "name:und_x_variant":[
        "Mra\u00efrhel",
        "Murayghil"
    ],
    "name:vie_x_preferred":[
        "Murayghil"
    ],
    "wof:name":"Murayghil",
    "wof:placetype":"locality"
},
  "geometry": {"coordinates":[37.25608,36.60269],"type":"Point"}
}