{
  "type": "Feature",
  "properties": {
    "gn:admin1_code":"7.0",
    "gn:asciiname":"Al Kharijiyah",
    "gn:country_code":"SY",
    "gn:dem":218,
    "gn:feature_class":"P",
    "gn:feature_code":"PPL",
    "gn:name":"Al Khar\u012bj\u012byah",
    "gn:population":0,
    "gn:timezone":"Asia/Damascus",
    "iso:country":"SY",
    "name:ara_x_preferred":[
        "\u0627\u0644\u062e\u0631\u064a\u062c\u064a\u0629"
    ],
    "name:und_x_variant":[
        "Al Khar\u012bj\u012byah"
    ],
    "wof:name":"Al Kharijiyah",
    "wof:placetype":"locality"
},
  "geometry": {"coordinates":[40.61214,35.38273],"type":"Point"}
}