{
  "type": "Feature",
  "properties": {
    "gn:admin1_code":"9.0",
    "gn:asciiname":"Bayt Hasan Agha",
    "gn:country_code":"SY",
    "gn:dem":365,
    "gn:feature_class":"P",
    "gn:feature_code":"PPLL",
    "gn:name":"Bayt \u1e28asan \u0100gh\u0101",
    "gn:population":0,
    "gn:timezone":"Asia/Damascus",
    "iso:country":"SY",
    "name:ara_x_preferred":[
        "\u0628\u064a\u062a \u062d\u0633\u0646 \u0627\u0642\u0627"
    ],
    "name:ara_x_variant":[
        "\u0628\u064a\u062a \u062d\u0633\u0646 \u0622\u063a\u0627"
    ],
    "name:und_x_variant":[
        "Bayt \u1e28asan Aq\u0101",
        "Bayt \u1e28asan \u0100gh\u0101"
    ],
    "wof:name":"Bayt Hasan Agha",
    "wof:placetype":"locality"
},
  "geometry": {"coordinates":[37.36993,36.17041],"type":"Point"}
}