{
  "type": "Feature",
  "properties": {
    "gn:admin1_code":"9.0",
    "gn:asciiname":"Kurtik Siruj",
    "gn:country_code":"SY",
    "gn:dem":466,
    "gn:feature_class":"P",
    "gn:feature_code":"PPL",
    "gn:name":"K\u016brtik Sir\u016bj",
    "gn:population":0,
    "gn:timezone":"Asia/Damascus",
    "iso:country":"SY",
    "name:ara_x_preferred":[
        "\u0643\u0648\u0631\u062a\u0643"
    ],
    "name:ara_x_variant":[
        "\u0643\u0648\u0631\u062a\u0643 \u0633\u0631\u0648\u062c",
        "K\u016brtuk",
        "Sur\u016bj",
        "\u0633\u0631\u0648\u062c",
        "\u0627\u0644\u0632\u064a\u0646\u0629"
    ],
    "name:kur_x_preferred":[
        "Kurtika Siruc"
    ],
    "name:kur_x_variant":[
        "Kortika Siroc",
        "Kortika Siruc",
        "\u0643\u0648\u0631\u062a\u0643\u0627 \u0633\u0631\u0648\u062c",
        "\u0643\u06c6\u0631\u062a\u0643\u0627 \u0633\u0631\u06c6\u062c",
        "\u0643\u06c6\u0631\u062a\u0643\u0627 \u0633\u0631\u0648\u062c"
    ],
    "name:und_x_variant":[
        "K\u016brtak",
        "K\u016brtik Sir\u016bj",
        "Kurtuk",
        "Az Z\u012bnah",
        "Az Z\u012bna",
        "Z\u012bnah",
        "El Z\u00eena"
    ],
    "wof:name":"Kurtik Siruj",
    "wof:placetype":"locality"
},
  "geometry": {"coordinates":[38.47967,36.85119],"type":"Point"}
}