{
  "type": "Feature",
  "properties": {
    "gn:admin1_code":"9.0",
    "gn:asciiname":"Harjalah",
    "gn:country_code":"SY",
    "gn:dem":495,
    "gn:feature_class":"P",
    "gn:feature_code":"PPL",
    "gn:name":"\u1e28arjalah",
    "gn:population":0,
    "gn:timezone":"Asia/Damascus",
    "iso:country":"SY",
    "name:ara_x_preferred":[
        "\u062d\u0631\u062c\u0644\u0629"
    ],
    "name:und_x_variant":[
        "Al \u1e28arjalah",
        "Harjal\u00e9",
        "\u1e28arjalah"
    ],
    "wof:name":"Harjalah",
    "wof:placetype":"locality"
},
  "geometry": {"coordinates":[37.24074,36.66159],"type":"Point"}
}