{
  "type": "Feature",
  "properties": {
    "gn:admin1_code":"14.0",
    "gn:asciiname":"Hamush as Siraksi",
    "gn:country_code":"SY",
    "gn:dem":125,
    "gn:feature_class":"P",
    "gn:feature_code":"PPL",
    "gn:name":"\u1e28\u0101m\u016bsh as Siraks\u012b",
    "gn:population":0,
    "gn:timezone":"Asia/Damascus",
    "iso:country":"SY",
    "name:ara_x_preferred":[
        "\u062d\u0627\u0645\u0648\u0634 \u0627\u0644\u0633\u0631\u0627\u0633\u0643\u0629"
    ],
    "name:ara_x_variant":[
        "\u062d\u0627\u0645\u0648\u0634 \u0627\u0644\u0633\u0631\u0643\u0633\u064a"
    ],
    "name:und_x_variant":[
        "H\u00e2mmo\u00fbch Srask\u00e9",
        "H\u00e2mo\u00fbch Srask\u00e9",
        "\u1e28\u0101m\u016bsh Srask\u012b",
        "\u1e28\u0101m\u016bsh as Sir\u0101skah",
        "\u1e28\u0101m\u016bsh as Siraks\u012b"
    ],
    "wof:name":"Hamush as Siraksi",
    "wof:placetype":"locality"
},
  "geometry": {"coordinates":[35.95274000000001,34.88806],"type":"Point"}
}