{
  "type": "Feature",
  "properties": {
    "gn:admin1_code":"1.0",
    "gn:asciiname":"Hallaq",
    "gn:country_code":"SY",
    "gn:dem":476,
    "gn:feature_class":"P",
    "gn:feature_code":"PPL",
    "gn:name":"\u1e28all\u0101q",
    "gn:population":0,
    "gn:timezone":"Asia/Damascus",
    "iso:country":"SY",
    "name:ara_x_preferred":[
        "\u062d\u0644\u0627\u0642"
    ],
    "name:und_x_variant":[
        "\u1e28all\u0101qah",
        "Hall\u00e2qa",
        "\u1e28all\u0101q"
    ],
    "wof:name":"Hallaq",
    "wof:placetype":"locality"
},
  "geometry": {"coordinates":[41.89625,37.07787],"type":"Point"}
}