{
  "type": "Feature",
  "properties": {
    "gn:admin1_code":"10.0",
    "gn:asciiname":"`Abr Bayt Sayf",
    "gn:country_code":"SY",
    "gn:dem":170,
    "gn:feature_class":"P",
    "gn:feature_code":"PPL",
    "gn:name":"\u2018Abr Bayt Sayf",
    "gn:population":0,
    "gn:timezone":"Asia/Damascus",
    "iso:country":"SY",
    "name:ara_x_preferred":[
        "\u0639\u0628\u0631 \u0628\u064a\u062a \u0634\u064a\u0641"
    ],
    "name:und_x_variant":[
        "A\u00e2ber Be\u00eft S\u00eef",
        "\u2018Abr Bayt Sayf"
    ],
    "wof:name":"`Abr Bayt Sayf",
    "wof:placetype":"locality"
},
  "geometry": {"coordinates":[36.31691,35.37826],"type":"Point"}
}