{
  "type": "Feature",
  "properties": {
    "gn:admin1_code":"11.0",
    "gn:asciiname":"Mazra`at al Jandali",
    "gn:country_code":"SY",
    "gn:dem":489,
    "gn:feature_class":"P",
    "gn:feature_code":"PPLL",
    "gn:name":"Mazra\u2018at al Jandal\u012b",
    "gn:population":0,
    "gn:timezone":"Asia/Damascus",
    "iso:country":"SY",
    "name:ara_x_preferred":[
        "\u0645\u0632\u0631\u0639\u0629 \u0627\u0644\u062c\u0646\u062f\u0644\u064a"
    ],
    "name:und_x_variant":[
        "Mazra\u2018at al Jandal\u012b"
    ],
    "wof:name":"Mazra`at al Jandali",
    "wof:placetype":"locality"
},
  "geometry": {"coordinates":[36.67407,34.72181],"type":"Point"}
}