{
  "type": "Feature",
  "properties": {
    "gn:admin1_code":"2.0",
    "gn:asciiname":"Bayt al Bustan",
    "gn:country_code":"SY",
    "gn:dem":329,
    "gn:feature_class":"P",
    "gn:feature_code":"PPL",
    "gn:name":"Bayt al Bust\u0101n",
    "gn:population":0,
    "gn:timezone":"Asia/Damascus",
    "iso:country":"SY",
    "name:und_x_variant":[
        "Be\u00eft el Boust\u00e2ne",
        "Bayt al Bust\u0101n"
    ],
    "wof:name":"Bayt al Bustan",
    "wof:placetype":"locality"
},
  "geometry": {"coordinates":[36.12177,35.74306],"type":"Point"}
}