{
  "type": "Feature",
  "properties": {
    "gn:admin1_code":"10.0",
    "gn:asciiname":"Muwaylih as Suwaranah",
    "gn:country_code":"SY",
    "gn:dem":386,
    "gn:feature_class":"P",
    "gn:feature_code":"PPL",
    "gn:name":"Muwayli\u1e29 a\u015f \u015euw\u0101ranah",
    "gn:population":0,
    "gn:timezone":"Asia/Damascus",
    "iso:country":"SY",
    "name:ara_x_preferred":[
        "\u0645\u0648\u064a\u0644\u062d \u0627\u0644\u0635\u0648\u0627\u0631\u0646\u0629"
    ],
    "name:und_x_variant":[
        "Moua\u00efleh es Saou\u00e2r",
        "Muwayli\u1e29 as Saou\u00e2r",
        "Muwayli\u1e29 a\u015f \u015euw\u0101ranah"
    ],
    "wof:name":"Muwaylih as Suwaranah",
    "wof:placetype":"locality"
},
  "geometry": {"coordinates":[37.14377,35.33957],"type":"Point"}
}