{
  "type": "Feature",
  "properties": {
    "gn:admin1_code":"9.0",
    "gn:asciiname":"Daybarak Kaytikan",
    "gn:country_code":"SY",
    "gn:dem":558,
    "gn:feature_class":"P",
    "gn:feature_code":"PPL",
    "gn:name":"Daybarak Kaytik\u0101n",
    "gn:population":0,
    "gn:timezone":"Asia/Damascus",
    "iso:country":"SY",
    "name:und_x_variant":[
        "Daybarak Kaytik\u0101n"
    ],
    "wof:name":"Daybarak Kaytikan",
    "wof:placetype":"locality"
},
  "geometry": {"coordinates":[38.4125,36.7875],"type":"Point"}
}