{
  "type": "Feature",
  "properties": {
    "gn:admin1_code":"2.0",
    "gn:asciiname":"Qarah `Umar Dagh",
    "gn:country_code":"SY",
    "gn:dem":538,
    "gn:feature_class":"P",
    "gn:feature_code":"PPL",
    "gn:name":"Qarah \u2018Umar D\u0101gh",
    "gn:population":0,
    "gn:timezone":"Asia/Damascus",
    "iso:country":"SY",
    "name:ara_x_preferred":[
        "\u0642\u0631\u0647 \u0639\u0645\u0631 \u062f\u0627\u063a"
    ],
    "name:und_x_variant":[
        "Darheu Qara Omar",
        "Qara Omar D\u00e2rheu",
        "Qarah \u2018Umar D\u0101gh\u012b",
        "Qarah \u2018Umar D\u0101gh"
    ],
    "wof:name":"Qarah `Umar Dagh",
    "wof:placetype":"locality"
},
  "geometry": {"coordinates":[36.12416,35.83874],"type":"Point"}
}