{
  "type": "Feature",
  "properties": {
    "gn:admin1_code":"9.0",
    "gn:asciiname":"Rasm al Falih",
    "gn:country_code":"SY",
    "gn:dem":359,
    "gn:feature_class":"P",
    "gn:feature_code":"PPL",
    "gn:name":"Rasm al F\u0101li\u1e29",
    "gn:population":0,
    "gn:timezone":"Asia/Damascus",
    "iso:country":"SY",
    "name:ara_x_preferred":[
        "\u0631\u0633\u0645 \u0627\u0644\u0641\u0627\u0644\u062d"
    ],
    "name:und_x_variant":[
        "Rasm Falah",
        "Rasm F\u00e2leh",
        "Rasm al F\u0101li\u1e29"
    ],
    "wof:name":"Rasm al Falih",
    "wof:placetype":"locality"
},
  "geometry": {"coordinates":[37.79683,36.15582],"type":"Point"}
}