{
  "type": "Feature",
  "properties": {
    "gn:admin1_code":"11.0",
    "gn:asciiname":"Al Basiri",
    "gn:country_code":"SY",
    "gn:dem":763,
    "gn:feature_class":"P",
    "gn:feature_code":"PPL",
    "gn:name":"Al Ba\u015f\u012br\u012b",
    "gn:population":0,
    "gn:timezone":"Asia/Damascus",
    "iso:country":"SY",
    "name:ara_x_preferred":[
        "\u0627\u0644\u0628\u0635\u064a\u0631\u064a"
    ],
    "name:und_x_variant":[
        "Al Ba\u015f\u012br\u012b"
    ],
    "wof:name":"Al Basiri",
    "wof:placetype":"locality"
},
  "geometry": {"coordinates":[37.59079000000001,34.15756],"type":"Point"}
}