{
  "type": "Feature",
  "properties": {
    "gn:admin1_code":"8.0",
    "gn:asciiname":"Dayr al 'Asafir",
    "gn:country_code":"SY",
    "gn:dem":638,
    "gn:feature_class":"P",
    "gn:feature_code":"PPL",
    "gn:name":"Dayr al \u2018A\u015f\u0101f\u012br",
    "gn:population":6209,
    "gn:timezone":"Asia/Damascus",
    "iso:country":"SY",
    "name:ara_x_preferred":[
        "\u062f\u064a\u0631 \u0627\u0644\u0639\u0635\u0627\u0641\u064a\u0631"
    ],
    "name:fas_x_preferred":[
        "\u062f\u06cc\u0631 \u0627\u0644\u0639\u0635\u0627\u0641\u06cc\u0631"
    ],
    "name:nld_x_preferred":[
        "Deir al-Asafir"
    ],
    "name:pol_x_preferred":[
        "Dajr al-Asafir"
    ],
    "name:sco_x_preferred":[
        "Deir al-Asafir"
    ],
    "name:und_x_variant":[
        "De\u00efr el Assifir",
        "De\u00efr el Aass\u00e2f\u00eer",
        "Dayr al \u2018A\u015f\u0101f\u012br",
        "Dayr al-Assafir",
        "Deir Al-Asaffir"
    ],
    "name:vie_x_preferred":[
        "Deir al-Asafir"
    ],
    "wof:name":"Dayr al 'Asafir",
    "wof:placetype":"locality",
    "wof:population":6209
},
  "geometry": {"coordinates":[36.42044,33.46585],"type":"Point"}
}