{
  "type": "Feature",
  "properties": {
    "gn:admin1_code":"3.0",
    "gn:asciiname":"At Tawilah",
    "gn:country_code":"SY",
    "gn:dem":940,
    "gn:feature_class":"P",
    "gn:feature_code":"PPLL",
    "gn:name":"A\u0163 \u0162aw\u012blah",
    "gn:population":0,
    "gn:timezone":"Asia/Damascus",
    "iso:country":"SY",
    "name:ara_x_preferred":[
        "\u0627\u0644\u0637\u0648\u064a\u0644\u0629"
    ],
    "name:cat_x_preferred":[
        "Al-Tawila"
    ],
    "name:ceb_x_preferred":[
        "A\u0163 \u0162aw\u012blah"
    ],
    "name:deu_x_preferred":[
        "At-Taw\u012bla"
    ],
    "name:fas_x_preferred":[
        "\u0627\u0644\u0637\u0648\u06cc\u0644\u0647"
    ],
    "name:nno_x_preferred":[
        "At Tawilah"
    ],
    "name:rus_x_preferred":[
        "\u0410\u0442-\u0422\u0430\u0432\u0438\u043b\u0430"
    ],
    "wof:name":"At Tawilah",
    "wof:placetype":"locality"
},
  "geometry": {"coordinates":[35.88253,33.1695],"type":"Point"}
}