{
  "type": "Feature",
  "properties": {
    "gn:admin1_code":"8.0",
    "gn:asciiname":"Ard az Zurayqiyah",
    "gn:country_code":"SY",
    "gn:dem":610,
    "gn:feature_class":"P",
    "gn:feature_code":"PPLL",
    "gn:name":"Ar\u1e11 az Zurayq\u012byah",
    "gn:population":0,
    "gn:timezone":"Asia/Damascus",
    "iso:country":"SY",
    "name:ara_x_preferred":[
        "\u0623\u0631\u0636 \u0627\u0644\u0632\u0631\u064a\u0642\u064a\u0629"
    ],
    "name:und_x_variant":[
        "Ar\u1e11 az Zurayq\u012byah"
    ],
    "wof:name":"Ard az Zurayqiyah",
    "wof:placetype":"locality"
},
  "geometry": {"coordinates":[36.50535,33.55374],"type":"Point"}
}