{
  "type": "Feature",
  "properties": {
    "gn:admin1_code":"4.0",
    "gn:asciiname":"Jurn Aswad",
    "gn:country_code":"SY",
    "gn:dem":385,
    "gn:feature_class":"P",
    "gn:feature_code":"PPL",
    "gn:name":"Jurn Aswad",
    "gn:population":0,
    "gn:timezone":"Asia/Damascus",
    "iso:country":"SY",
    "name:ara_x_preferred":[
        "\u062c\u0631\u0646 \u0623\u0633\u0648\u062f"
    ],
    "name:und_x_variant":[
        "Jar\u00e2ne Assouad",
        "Journ Assouad",
        "Jurn al Aswad",
        "Jurn Aswad"
    ],
    "wof:name":"Jurn Aswad",
    "wof:placetype":"locality"
},
  "geometry": {"coordinates":[38.71922,36.67976],"type":"Point"}
}