{
  "type": "Feature",
  "properties": {
    "gn:admin1_code":"11.0",
    "gn:asciiname":"Khirbat Tin Mahmud",
    "gn:country_code":"SY",
    "gn:dem":487,
    "gn:feature_class":"P",
    "gn:feature_code":"PPL",
    "gn:name":"Khirbat T\u012bn Ma\u1e29m\u016bd",
    "gn:population":0,
    "gn:timezone":"Asia/Damascus",
    "iso:country":"SY",
    "name:ara_x_preferred":[
        "\u062e\u0631\u0628\u0629 \u062a\u064a\u0646 \u0645\u062d\u0645\u0648\u062f"
    ],
    "name:und_x_variant":[
        "Kheurbet T\u00eene Mahmo\u00fbd",
        "Kheurbet et Tin Mahmoud",
        "Khirbat T\u012bn Ma\u1e29m\u016bd"
    ],
    "wof:name":"Khirbat Tin Mahmud",
    "wof:placetype":"locality"
},
  "geometry": {"coordinates":[36.56806,34.77335],"type":"Point"}
}