{
  "type": "Feature",
  "properties": {
    "gn:admin1_code":"9.0",
    "gn:asciiname":"Al Khafsah",
    "gn:country_code":"SY",
    "gn:dem":355,
    "gn:feature_class":"P",
    "gn:feature_code":"PPLA3",
    "gn:name":"Al Khafsah",
    "gn:population":0,
    "gn:timezone":"Asia/Damascus",
    "iso:country":"SY",
    "name:ara_x_preferred":[
        "\u062e\u0641\u0633\u0629"
    ],
    "name:ara_x_variant":[
        "\u0627\u0644\u062e\u0641\u0633\u0629"
    ],
    "name:und_x_variant":[
        "Khafsah",
        "Khafs\u00e9",
        "Khafs\u00e9 el K\u00e9b\u00eer\u00e9",
        "Khafr\u00e9 K\u00e9bir\u00e9",
        "Khafsah Kab\u012br",
        "Hafse Keb\u012br",
        "Al Khafsah"
    ],
    "wof:name":"Al Khafsah",
    "wof:placetype":"locality"
},
  "geometry": {"coordinates":[38.02172,36.2311],"type":"Point"}
}