{
  "type": "Feature",
  "properties": {
    "gn:admin1_code":"9.0",
    "gn:asciiname":"Zarik",
    "gn:country_code":"SY",
    "gn:dem":373,
    "gn:feature_class":"P",
    "gn:feature_code":"PPL",
    "gn:name":"Zar\u012bk",
    "gn:population":0,
    "gn:timezone":"Asia/Damascus",
    "iso:country":"SY",
    "name:ara_x_preferred":[
        "Z\u00e9rik"
    ],
    "name:ara_x_variant":[
        "\u0632\u0631\u064a\u0643",
        "\u0632\u0631\u0643",
        "\u0632\u0631"
    ],
    "name:kur_x_preferred":[
        "Zirik"
    ],
    "name:kur_x_variant":[
        "Zerik",
        "\u0632\u06d5\u0631\u0643"
    ],
    "name:und_x_variant":[
        "Zar\u012bk",
        "Zarik",
        "Zir",
        "Zerk"
    ],
    "wof:name":"Zarik",
    "wof:placetype":"locality"
},
  "geometry": {"coordinates":[38.11668,36.77056],"type":"Point"}
}