{
  "type": "Feature",
  "properties": {
    "gn:admin1_code":"10.0",
    "gn:asciiname":"Huwaysah al Qibli",
    "gn:country_code":"SY",
    "gn:dem":359,
    "gn:feature_class":"P",
    "gn:feature_code":"PPL",
    "gn:name":"\u1e28uwaysah al Qibl\u012b",
    "gn:population":0,
    "gn:timezone":"Asia/Damascus",
    "iso:country":"SY",
    "name:ara_x_preferred":[
        "\u062d\u0648\u064a\u0633\u0629 \u0627\u0644\u0642\u0628\u0644\u064a"
    ],
    "name:und_x_variant":[
        "Houa\u00efss\u00e9 ett Taht\u00e2ni",
        "\u1e28uway\u015fah at Ta\u1e29t\u0101n\u012b",
        "\u1e28uwaysah al Qibl\u012b"
    ],
    "wof:name":"Huwaysah al Qibli",
    "wof:placetype":"locality"
},
  "geometry": {"coordinates":[37.12638,35.40295],"type":"Point"}
}