{
  "type": "Feature",
  "properties": {
    "gn:admin1_code":"9.0",
    "gn:asciiname":"Zayzafun",
    "gn:country_code":"SY",
    "gn:dem":512,
    "gn:feature_class":"P",
    "gn:feature_code":"PPL",
    "gn:name":"Zayzaf\u016bn",
    "gn:population":0,
    "gn:timezone":"Asia/Damascus",
    "iso:country":"SY",
    "name:ara_x_preferred":[
        "\u0627\u064a\u0643\u062f\u0629"
    ],
    "name:ara_x_variant":[
        "\u0632\u064a\u0632\u0641\u0648\u0646",
        "\u0627\u0644\u0632\u064a\u0632\u0641\u0648\u0646"
    ],
    "name:fas_x_preferred":[
        "\u0632\u06cc\u0632\u0641\u0648\u0646"
    ],
    "name:pol_x_preferred":[
        "Az-Zajzafun"
    ],
    "name:tur_x_preferred":[
        "\u0130\u011fde"
    ],
    "name:und_x_variant":[
        "\u012akdah",
        "Aykadah",
        "\u012akidah",
        "Zayzaf\u016bn"
    ],
    "name:vie_x_preferred":[
        "Zayzafun"
    ],
    "wof:name":"Zayzafun",
    "wof:placetype":"locality"
},
  "geometry": {"coordinates":[37.18092,36.6497],"type":"Point"}
}