{
  "type": "Feature",
  "properties": {
    "gn:admin1_code":"14.0",
    "gn:asciiname":"Shafi Ruh",
    "gn:country_code":"SY",
    "gn:dem":330,
    "gn:feature_class":"P",
    "gn:feature_code":"PPL",
    "gn:name":"Sh\u0101f\u012b R\u016b\u1e29",
    "gn:population":0,
    "gn:timezone":"Asia/Damascus",
    "iso:country":"SY",
    "name:ara_x_preferred":[
        "\u0634\u0627\u0641\u064a \u0631\u0648\u062d"
    ],
    "name:und_x_variant":[
        "Sh\u0101f\u012b R\u016b\u1e29"
    ],
    "wof:name":"Shafi Ruh",
    "wof:placetype":"locality"
},
  "geometry": {"coordinates":[36.02707,35.22032],"type":"Point"}
}