{
  "type": "Feature",
  "properties": {
    "gn:admin1_code":"12.0",
    "gn:asciiname":"Bayt Dabayq",
    "gn:country_code":"SY",
    "gn:dem":464,
    "gn:feature_class":"P",
    "gn:feature_code":"PPL",
    "gn:name":"Bayt Dabayq",
    "gn:population":0,
    "gn:timezone":"Asia/Damascus",
    "iso:country":"SY",
    "name:ara_x_preferred":[
        "\u0628\u064a\u062a \u062f\u0628\u064a\u0642"
    ],
    "name:und_x_variant":[
        "Be\u00eft Debbe\u00efq"
    ],
    "wof:name":"Bayt Dabayq",
    "wof:placetype":"locality"
},
  "geometry": {"coordinates":[36.15478,35.79006],"type":"Point"}
}