{
  "type": "Feature",
  "properties": {
    "gn:admin1_code":"14.0",
    "gn:asciiname":"`Ayn al Karm",
    "gn:country_code":"SY",
    "gn:dem":790,
    "gn:feature_class":"P",
    "gn:feature_code":"PPL",
    "gn:name":"\u2018Ayn al Karm",
    "gn:population":0,
    "gn:timezone":"Asia/Damascus",
    "iso:country":"SY",
    "name:und_x_variant":[
        "A\u00efn el Karm",
        "\u2018Ayn al Karm"
    ],
    "wof:name":"`Ayn al Karm",
    "wof:placetype":"locality"
},
  "geometry": {"coordinates":[36.22416,35.01791],"type":"Point"}
}