{
  "type": "Feature",
  "properties": {
    "gn:admin1_code":"1.0",
    "gn:asciiname":"Al Mahmudiyah",
    "gn:country_code":"SY",
    "gn:dem":400,
    "gn:feature_class":"P",
    "gn:feature_code":"PPL",
    "gn:name":"Al Ma\u1e29m\u016bd\u012byah",
    "gn:population":0,
    "gn:timezone":"Asia/Damascus",
    "iso:country":"SY",
    "name:ara_x_preferred":[
        "\u0627\u0644\u0645\u062d\u0645\u0648\u062f\u064a\u0629"
    ],
    "name:kur_x_preferred":[
        "Baba Me\u1e27mud"
    ],
    "name:kur_x_variant":[
        "\u0628\u0627\u0628\u0627 \u0645\u06d5\u062d\u0645\u0648\u062f"
    ],
    "name:und_x_variant":[
        "Al Ma\u1e29m\u016bd\u012byah",
        "B\u0101b\u0101 Ma\u1e29m\u016bd",
        "\u0628\u0627\u0628\u0627 \u0645\u062d\u0645\u0648\u062f"
    ],
    "wof:name":"Al Mahmudiyah",
    "wof:placetype":"locality"
},
  "geometry": {"coordinates":[42.07739,36.82755],"type":"Point"}
}