{
  "type": "Feature",
  "properties": {
    "gn:admin1_code":"14.0",
    "gn:asciiname":"Al Juwaymisiyah",
    "gn:country_code":"SY",
    "gn:dem":10,
    "gn:feature_class":"P",
    "gn:feature_code":"PPL",
    "gn:name":"Al Juwaym\u012bs\u012byah",
    "gn:population":0,
    "gn:timezone":"Asia/Damascus",
    "iso:country":"SY",
    "name:und_x_variant":[
        "Jou\u00e2m\u00eess\u00e9",
        "Jouamisseh",
        "Jaw\u0101m\u012bs\u012byah",
        "Al Juwaym\u012bs\u012byah",
        "\u0627\u0644\u062c\u0648\u064a\u0645\u064a\u0633\u064a\u0629"
    ],
    "wof:name":"Al Juwaymisiyah",
    "wof:placetype":"locality"
},
  "geometry": {"coordinates":[35.99781,34.66147],"type":"Point"}
}