{
  "type": "Feature",
  "properties": {
    "gn:admin1_code":"11.0",
    "gn:asciiname":"Ar Razzuqiyah",
    "gn:country_code":"SY",
    "gn:dem":664,
    "gn:feature_class":"P",
    "gn:feature_code":"PPL",
    "gn:name":"Ar Razz\u016bq\u012byah",
    "gn:population":0,
    "gn:timezone":"Asia/Damascus",
    "iso:country":"SY",
    "name:ara_x_preferred":[
        "\u0631\u0632\u0648\u0642\u064a\u0629"
    ],
    "name:ara_x_variant":[
        "\u0627\u0644\u0631\u0632\u0648\u0642\u064a\u0629"
    ],
    "name:und_x_variant":[
        "Razz\u016bq\u012byah",
        "Ar Razz\u016bq\u012byah"
    ],
    "wof:name":"Ar Razzuqiyah",
    "wof:placetype":"locality"
},
  "geometry": {"coordinates":[37.04926,34.70338],"type":"Point"}
}