{
  "type": "Feature",
  "properties": {
    "gn:admin1_code":"2.0",
    "gn:asciiname":"Al Maran",
    "gn:country_code":"SY",
    "gn:dem":462,
    "gn:feature_class":"P",
    "gn:feature_code":"PPL",
    "gn:name":"Al Mar\u0101n",
    "gn:population":0,
    "gn:timezone":"Asia/Damascus",
    "iso:country":"SY",
    "name:ara_x_preferred":[
        "\u0627\u0644\u0645\u0631\u0627\u0646"
    ],
    "name:ara_x_variant":[
        "\u0645\u0631\u0627\u0646"
    ],
    "name:und_x_variant":[
        "Al Mar\u0101n",
        "Merr\u00e2n\u00e9",
        "Marr\u0101nah",
        "Mar\u0101n"
    ],
    "wof:name":"Al Maran",
    "wof:placetype":"locality"
},
  "geometry": {"coordinates":[36.00334,35.76721],"type":"Point"}
}