{
  "type": "Feature",
  "properties": {
    "gn:admin1_code":"4.0",
    "gn:asciiname":"Shawk",
    "gn:country_code":"SY",
    "gn:dem":381,
    "gn:feature_class":"P",
    "gn:feature_code":"PPL",
    "gn:name":"Shawk",
    "gn:population":0,
    "gn:timezone":"Asia/Damascus",
    "iso:country":"SY",
    "name:ara_x_preferred":[
        "\u0634\u0648\u0643"
    ],
    "name:und_x_variant":[
        "Chaouk",
        "Tchao\u00fbk",
        "Shawk"
    ],
    "wof:name":"Shawk",
    "wof:placetype":"locality"
},
  "geometry": {"coordinates":[38.7008,36.62203],"type":"Point"}
}