{
  "type": "Feature",
  "properties": {
    "gn:admin1_code":"1.0",
    "gn:asciiname":"Nasib",
    "gn:country_code":"SY",
    "gn:dem":300,
    "gn:feature_class":"P",
    "gn:feature_code":"PPL",
    "gn:name":"Na\u015f\u012bb",
    "gn:population":0,
    "gn:timezone":"Asia/Damascus",
    "iso:country":"SY",
    "name:ara_x_preferred":[
        "\u0646\u0635\u064a\u0628"
    ],
    "name:und_x_variant":[
        "Na\u015f\u012bb"
    ],
    "wof:name":"Nasib",
    "wof:placetype":"locality"
},
  "geometry": {"coordinates":[40.99292,36.0401],"type":"Point"}
}