{
  "type": "Feature",
  "properties": {
    "gn:admin1_code":"2.0",
    "gn:asciiname":"Gharnatah",
    "gn:country_code":"SY",
    "gn:dem":252,
    "gn:feature_class":"P",
    "gn:feature_code":"PPL",
    "gn:name":"Gharn\u0101\u0163ah",
    "gn:population":0,
    "gn:timezone":"Asia/Damascus",
    "iso:country":"SY",
    "name:ara_x_preferred":[
        "\u063a\u0631\u0646\u0627\u0637\u0629"
    ],
    "name:und_x_variant":[
        "Gharn\u0101\u0163ah"
    ],
    "wof:name":"Gharnatah",
    "wof:placetype":"locality"
},
  "geometry": {"coordinates":[35.99763,35.56287000000001],"type":"Point"}
}