{
  "type": "Feature",
  "properties": {
    "gn:admin1_code":"11.0",
    "gn:asciiname":"Al Faruqiyah",
    "gn:country_code":"SY",
    "gn:dem":523,
    "gn:feature_class":"P",
    "gn:feature_code":"PPL",
    "gn:name":"Al F\u0101r\u016bq\u012byah",
    "gn:population":0,
    "gn:timezone":"Asia/Damascus",
    "iso:country":"SY",
    "name:ara_x_preferred":[
        "\u0627\u0644\u0641\u0627\u0631\u0648\u0642\u064a\u0629"
    ],
    "name:und_x_variant":[
        "Al F\u0101r\u016bq\u012byah"
    ],
    "wof:name":"Al Faruqiyah",
    "wof:placetype":"locality"
},
  "geometry": {"coordinates":[36.48634000000001,34.5011],"type":"Point"}
}