{
  "type": "Feature",
  "properties": {
    "gn:admin1_code":"9.0",
    "gn:asciiname":"Bayt Mustafa al Hassun",
    "gn:country_code":"SY",
    "gn:dem":449,
    "gn:feature_class":"P",
    "gn:feature_code":"PPL",
    "gn:name":"Bayt Mu\u015f\u0163af\u00e1 al \u1e28ass\u016bn",
    "gn:population":0,
    "gn:timezone":"Asia/Damascus",
    "iso:country":"SY",
    "name:ara_x_preferred":[
        "\u0628\u064a\u062a \u0645\u0635\u0637\u0641\u0649 \u0627\u0644\u062d\u0633\u0648\u0646"
    ],
    "name:und_x_variant":[
        "Bayt Mu\u015f\u0163af\u00e1 al \u1e28ass\u016bn"
    ],
    "wof:name":"Bayt Mustafa al Hassun",
    "wof:placetype":"locality"
},
  "geometry": {"coordinates":[37.2696,36.48447],"type":"Point"}
}