{
  "type": "Feature",
  "properties": {
    "gn:admin1_code":"1.0",
    "gn:asciiname":"Ma`ish",
    "gn:country_code":"SY",
    "gn:dem":305,
    "gn:feature_class":"P",
    "gn:feature_code":"PPL",
    "gn:name":"Ma\u2018\u012bsh",
    "gn:population":0,
    "gn:timezone":"Asia/Damascus",
    "iso:country":"SY",
    "name:ara_x_preferred":[
        "\u0645\u0639\u064a\u0634"
    ],
    "name:und_x_variant":[
        "Ma\u2018\u012bsh"
    ],
    "wof:name":"Ma`ish",
    "wof:placetype":"locality"
},
  "geometry": {"coordinates":[41.04351,35.83854],"type":"Point"}
}