{
  "type": "Feature",
  "properties": {
    "gn:admin1_code":"9.0",
    "gn:asciiname":"Shuqaydilah",
    "gn:country_code":"SY",
    "gn:dem":331,
    "gn:feature_class":"P",
    "gn:feature_code":"PPL",
    "gn:name":"Shuqaydilah",
    "gn:population":0,
    "gn:timezone":"Asia/Damascus",
    "iso:country":"SY",
    "name:ara_x_preferred":[
        "\u0634\u063a\u064a\u062f\u0644\u0629"
    ],
    "name:ara_x_variant":[
        "\u0634\u0642\u064a\u062f\u0644\u0629"
    ],
    "name:und_x_variant":[
        "Charhedle",
        "Chaghedle",
        "Chrha\u00efdl\u00e9",
        "Shughaydilah",
        "Shuqaydilah"
    ],
    "wof:name":"Shuqaydilah",
    "wof:placetype":"locality"
},
  "geometry": {"coordinates":[37.08915,36.01907999999999],"type":"Point"}
}