{
  "type": "Feature",
  "properties": {
    "gn:admin1_code":"4.0",
    "gn:asciiname":"Rasm al Ghazal",
    "gn:country_code":"SY",
    "gn:dem":340,
    "gn:feature_class":"P",
    "gn:feature_code":"PPL",
    "gn:name":"Rasm al Ghaz\u0101l",
    "gn:population":0,
    "gn:timezone":"Asia/Damascus",
    "iso:country":"SY",
    "name:ara_x_preferred":[
        "\u0631\u0633\u0645 \u0627\u0644\u063a\u0632\u0627\u0644"
    ],
    "name:und_x_variant":[
        "Rasm el Rhaz\u00e2l",
        "Rasm al Ghaz\u0101l"
    ],
    "wof:name":"Rasm al Ghazal",
    "wof:placetype":"locality"
},
  "geometry": {"coordinates":[38.92002,36.59897],"type":"Point"}
}