{
  "type": "Feature",
  "properties": {
    "gn:admin1_code":"11.0",
    "gn:asciiname":"Khirbat Nawfal",
    "gn:country_code":"SY",
    "gn:dem":523,
    "gn:feature_class":"P",
    "gn:feature_code":"PPL",
    "gn:name":"Khirbat Nawfal",
    "gn:population":0,
    "gn:timezone":"Asia/Damascus",
    "iso:country":"SY",
    "name:ara_x_preferred":[
        "\u062e\u0631\u0628\u0629 \u0646\u0648\u0641\u0644"
    ],
    "wof:name":"Khirbat Nawfal",
    "wof:placetype":"locality"
},
  "geometry": {"coordinates":[36.82625,34.81154],"type":"Point"}
}