{
  "type": "Feature",
  "properties": {
    "gn:admin1_code":"1.0",
    "gn:asciiname":"Arzanah",
    "gn:country_code":"SY",
    "gn:dem":367,
    "gn:feature_class":"P",
    "gn:feature_code":"PPL",
    "gn:name":"Arz\u0101nah",
    "gn:population":0,
    "gn:timezone":"Asia/Damascus",
    "iso:country":"SY",
    "name:ara_x_preferred":[
        "\u0623\u0631\u0632\u0627\u0646\u0629"
    ],
    "name:tur_x_preferred":[
        "Arz\u0101nah"
    ],
    "name:und_x_variant":[
        "Arz\u00e2na"
    ],
    "wof:name":"Arzanah",
    "wof:placetype":"locality"
},
  "geometry": {"coordinates":[41.46547,36.88752],"type":"Point"}
}