{
  "type": "Feature",
  "properties": {
    "gn:admin1_code":"1.0",
    "gn:asciiname":"As`ad ad Dahir",
    "gn:country_code":"SY",
    "gn:dem":350,
    "gn:feature_class":"P",
    "gn:feature_code":"PPL",
    "gn:name":"As\u2018ad a\u1e11 \u1e10\u0101hir",
    "gn:population":0,
    "gn:timezone":"Asia/Damascus",
    "iso:country":"SY",
    "name:ara_x_preferred":[
        "\u0623\u0633\u0639\u062f \u0627\u0644\u0636\u0627\u0647\u0631"
    ],
    "name:und_x_variant":[
        "As\u2018ad a\u1e11 \u1e10\u0101hir"
    ],
    "wof:name":"As`ad ad Dahir",
    "wof:placetype":"locality"
},
  "geometry": {"coordinates":[41.01569,36.23747],"type":"Point"}
}