{
  "type": "Feature",
  "properties": {
    "gn:admin1_code":"11.0",
    "gn:asciiname":"Ar Ruhaybah",
    "gn:country_code":"SY",
    "gn:dem":943,
    "gn:feature_class":"P",
    "gn:feature_code":"PPL",
    "gn:name":"Ar Ru\u1e29aybah",
    "gn:population":0,
    "gn:timezone":"Asia/Damascus",
    "iso:country":"SY",
    "name:ara_x_preferred":[
        "\u0627\u0644\u0631\u062d\u064a\u0628\u0629"
    ],
    "name:und_x_variant":[
        "R\u2019ha\u00efb\u00e9",
        "Ru\u1e29aybah",
        "Ar Ru\u1e29aybah"
    ],
    "wof:name":"Ar Ruhaybah",
    "wof:placetype":"locality"
},
  "geometry": {"coordinates":[36.93084,34.27895],"type":"Point"}
}