{
  "type": "Feature",
  "properties": {
    "gn:admin1_code":"11.0",
    "gn:asciiname":"Mizallat Rasm Kassar",
    "gn:country_code":"SY",
    "gn:dem":847,
    "gn:feature_class":"P",
    "gn:feature_code":"PPL",
    "gn:name":"Miz\u0327allat Rasm Kass\u0101r",
    "gn:population":0,
    "gn:timezone":"Asia/Damascus",
    "iso:country":"SY",
    "name:ara_x_preferred":[
        "\u0645\u0638\u0644\u0629 \u0631\u0633\u0645 \u0643\u0633\u0627\u0631"
    ],
    "name:und_x_variant":[
        "Muthallath Rashsh Kass\u0101r",
        "Miz\u0327allat Rasm Kass\u0101r",
        "Ma\u0163allat Rasm Kas\u0101d"
    ],
    "wof:name":"Mizallat Rasm Kassar",
    "wof:placetype":"locality"
},
  "geometry": {"coordinates":[37.34108,34.68869],"type":"Point"}
}