{
  "type": "Feature",
  "properties": {
    "gn:admin1_code":"11.0",
    "gn:asciiname":"Balat",
    "gn:country_code":"SY",
    "gn:dem":515,
    "gn:feature_class":"P",
    "gn:feature_code":"PPL",
    "gn:name":"Bal\u0101\u0163",
    "gn:population":0,
    "gn:timezone":"Asia/Damascus",
    "iso:country":"SY",
    "name:ara_x_preferred":[
        "\u0628\u0644\u0627\u0637"
    ],
    "name:cat_x_preferred":[
        "Balat"
    ],
    "name:ceb_x_preferred":[
        "Balat"
    ],
    "name:deu_x_preferred":[
        "Balat"
    ],
    "name:fra_x_preferred":[
        "Balat"
    ],
    "name:pol_x_preferred":[
        "Balat"
    ],
    "name:swe_x_preferred":[
        "Balat"
    ],
    "name:tgl_x_preferred":[
        "Balat"
    ],
    "name:tur_x_preferred":[
        "Balat"
    ],
    "name:und_x_variant":[
        "Bal\u0101\u0163"
    ],
    "wof:name":"Balat",
    "wof:placetype":"locality"
},
  "geometry": {"coordinates":[36.34885,34.79234],"type":"Point"}
}