{
  "type": "Feature",
  "properties": {
    "gn:admin1_code":"9.0",
    "gn:asciiname":"Hama Kabir",
    "gn:country_code":"SY",
    "gn:dem":338,
    "gn:feature_class":"P",
    "gn:feature_code":"PPL",
    "gn:name":"\u1e28am\u0101 Kab\u012br",
    "gn:population":0,
    "gn:timezone":"Asia/Damascus",
    "iso:country":"SY",
    "name:ara_x_preferred":[
        "\u062d\u0645\u0627 \u0643\u0628\u064a\u0631"
    ],
    "name:und_x_variant":[
        "\u1e28am\u0101 Kab\u012br",
        "Hama el K\u00e9b\u00eer",
        "Hama K\u00e9b\u00eer",
        "\u1e28am\u0101h al Kab\u012br"
    ],
    "wof:name":"Hama Kabir",
    "wof:placetype":"locality"
},
  "geometry": {"coordinates":[38.21932,36.4993],"type":"Point"}
}