{
  "type": "Feature",
  "properties": {
    "gn:admin1_code":"10.0",
    "gn:asciiname":"Al Ashrafiyah",
    "gn:country_code":"SY",
    "gn:dem":749,
    "gn:feature_class":"P",
    "gn:feature_code":"PPL",
    "gn:name":"Al Ashraf\u012byah",
    "gn:population":0,
    "gn:timezone":"Asia/Damascus",
    "iso:country":"SY",
    "name:ara_x_preferred":[
        "\u062e\u0646\u0627\u0632\u064a\u0631"
    ],
    "name:ara_x_variant":[
        "\u0627\u0644\u0623\u0634\u0631\u0641\u064a\u0629"
    ],
    "name:und_x_variant":[
        "Khan\u0101z\u012br",
        "Khan\u00e2z\u00eer",
        "Al Ashraf\u012byah"
    ],
    "wof:name":"Al Ashrafiyah",
    "wof:placetype":"locality"
},
  "geometry": {"coordinates":[36.39055,34.87417],"type":"Point"}
}