{
  "type": "Feature",
  "properties": {
    "gn:admin1_code":"4.0",
    "gn:asciiname":"Kharriyah",
    "gn:country_code":"SY",
    "gn:dem":322,
    "gn:feature_class":"P",
    "gn:feature_code":"PPL",
    "gn:name":"Kharr\u012byah",
    "gn:population":0,
    "gn:timezone":"Asia/Damascus",
    "iso:country":"SY",
    "name:ara_x_preferred":[
        "\u062e\u0631\u0651\u064a\u0629"
    ],
    "name:und_x_variant":[
        "Rhar\u00eej\u00e9",
        "Khar\u00eey\u00e9",
        "Khar\u00eej\u00e9",
        "Khar\u012bjah",
        "Kharr\u012byah"
    ],
    "wof:name":"Kharriyah",
    "wof:placetype":"locality"
},
  "geometry": {"coordinates":[38.94737,36.41886],"type":"Point"}
}