{
  "type": "Feature",
  "properties": {
    "gn:admin1_code":"12.0",
    "gn:asciiname":"Istabalat",
    "gn:country_code":"SY",
    "gn:dem":370,
    "gn:feature_class":"P",
    "gn:feature_code":"PPL",
    "gn:name":"I\u015f\u0163abal\u0101t",
    "gn:population":0,
    "gn:timezone":"Asia/Damascus",
    "iso:country":"SY",
    "name:ara_x_preferred":[
        "\u0627\u0635\u0637\u0628\u0644\u0627\u062a"
    ],
    "name:und_x_variant":[
        "Istabl\u00e2te",
        "Istabl\u0101t",
        "I\u015f\u0163abal\u0101t"
    ],
    "wof:name":"Istabalat",
    "wof:placetype":"locality"
},
  "geometry": {"coordinates":[36.96811,35.68728],"type":"Point"}
}