{
  "type": "Feature",
  "properties": {
    "gn:admin1_code":"2.0",
    "gn:asciiname":"Shir al Qaq",
    "gn:country_code":"SY",
    "gn:dem":381,
    "gn:feature_class":"P",
    "gn:feature_code":"PPL",
    "gn:name":"Sh\u012br al Q\u0101q",
    "gn:population":0,
    "gn:timezone":"Asia/Damascus",
    "iso:country":"SY",
    "name:ara_x_preferred":[
        "\u0634\u064a\u0631 \u0627\u0644\u0642\u0627\u0642"
    ],
    "name:und_x_variant":[
        "Ch\u00eer el Q\u00e2q",
        "Sh\u012br al Q\u0101q"
    ],
    "wof:name":"Shir al Qaq",
    "wof:placetype":"locality"
},
  "geometry": {"coordinates":[36.04275,35.59393],"type":"Point"}
}