{
  "type": "Feature",
  "properties": {
    "gn:admin1_code":"2.0",
    "gn:asciiname":"Qabw al `Awwamiyah",
    "gn:country_code":"SY",
    "gn:dem":31,
    "gn:feature_class":"P",
    "gn:feature_code":"PPL",
    "gn:name":"Qabw al \u2018Aww\u0101m\u012byah",
    "gn:population":0,
    "gn:timezone":"Asia/Damascus",
    "iso:country":"SY",
    "name:ara_x_preferred":[
        "\u0642\u0628\u0648 \u0627\u0644\u0639\u0648\u0627\u0645\u064a\u0629"
    ],
    "name:ara_x_variant":[
        "\u0642\u0628\u0648 \u0628\u064a\u062a \u0645\u0631\u0642\u0635",
        "\u0627\u0644\u0642\u0628\u0648"
    ],
    "name:und_x_variant":[
        "Qabou el Aaou\u00e2m\u00eey\u00e9",
        "Qabou el Aadou\u00e2n\u00eey\u00e9",
        "Qabw al \u2018Aww\u0101m\u012byah",
        "Qabw Bayt Murqu\u015f",
        "Qabw Bayt Marqa\u015f",
        "Qabu",
        "Al Qabw"
    ],
    "wof:name":"Qabw al `Awwamiyah",
    "wof:placetype":"locality"
},
  "geometry": {"coordinates":[35.91723,35.44175999999999],"type":"Point"}
}