{
  "type": "Feature",
  "properties": {
    "gn:admin1_code":"4.0",
    "gn:asciiname":"Sweilam",
    "gn:country_code":"SY",
    "gn:dem":295,
    "gn:feature_class":"P",
    "gn:feature_code":"PPL",
    "gn:name":"Sweilam",
    "gn:population":0,
    "gn:timezone":"Asia/Damascus",
    "iso:country":"SY",
    "wof:name":"Sweilam",
    "wof:placetype":"locality"
},
  "geometry": {"coordinates":[38.84731,36.20446],"type":"Point"}
}