{
  "type": "Feature",
  "properties": {
    "gn:admin1_code":"14.0",
    "gn:asciiname":"Bayt ash Shaykh Salamah",
    "gn:country_code":"SY",
    "gn:dem":54,
    "gn:feature_class":"P",
    "gn:feature_code":"PPL",
    "gn:name":"Bayt ash Shaykh Sal\u0101mah",
    "gn:population":0,
    "gn:timezone":"Asia/Damascus",
    "iso:country":"SY",
    "name:ara_x_preferred":[
        "\u0628\u064a\u062a \u0627\u0644\u0634\u064a\u062e \u0633\u0644\u0627\u0645\u0629"
    ],
    "name:und_x_variant":[
        "Bayt ash Shaykh Sal\u0101mah"
    ],
    "wof:name":"Bayt ash Shaykh Salamah",
    "wof:placetype":"locality"
},
  "geometry": {"coordinates":[35.95518,34.81144],"type":"Point"}
}