{
  "type": "Feature",
  "properties": {
    "gn:admin1_code":"9.0",
    "gn:asciiname":"Qabajiq Saghir",
    "gn:country_code":"SY",
    "gn:dem":477,
    "gn:feature_class":"P",
    "gn:feature_code":"PPL",
    "gn:name":"Qab\u0101jiq \u015eagh\u012br",
    "gn:population":0,
    "gn:timezone":"Asia/Damascus",
    "iso:country":"SY",
    "name:ara_x_preferred":[
        "\u0642\u0628\u0627\u062c\u0642 \u0635\u063a\u064a\u0631"
    ],
    "name:ara_x_variant":[
        "\u062f\u0648\u062d\u0629 \u0635\u063a\u064a\u0631\u0629"
    ],
    "name:kur_x_preferred":[
        "Qibaciq Bicuk"
    ],
    "name:kur_x_variant":[
        "Qebaciq Bichuk",
        "Qebaciq Bich\u00fbk",
        "\u0642\u0628\u0627\u062c\u0642 \u0628\u062c\u0648\u0643",
        "\u0642\u06d5\u0628\u0627\u062c\u0642 \u0628\u0686\u0648\u0643",
        "\u0642\u06d5\u0628\u0627\u062c\u0642 \u0628\u0686\u0648\u0648\u0643"
    ],
    "name:und_x_variant":[
        "Qab\u00e2djiq S\u00e9rh\u00eer",
        "Qab\u0101jiq \u015eagh\u012br",
        "Daw\u1e29ah \u015eagh\u012brah",
        "Daw\u1e29at \u015eagh\u012brah",
        "Dewha Sex\u00eera",
        "Qibajiq Bijuk",
        "Dawha Saghira",
        "Qbaciq Bi\u00e7\u00fbk",
        "Qabajiq Saghir",
        "Kabacuxe Picuk",
        "Kabacoxe Picuk"
    ],
    "wof:name":"Qabajiq Saghir",
    "wof:placetype":"locality"
},
  "geometry": {"coordinates":[38.48422,36.80396],"type":"Point"}
}