{
  "type": "Feature",
  "properties": {
    "gn:admin1_code":"8.0",
    "gn:asciiname":"Al Buraysah",
    "gn:country_code":"SY",
    "gn:dem":783,
    "gn:feature_class":"P",
    "gn:feature_code":"PPLL",
    "gn:name":"Al Buray\u015fah",
    "gn:population":0,
    "gn:timezone":"Asia/Damascus",
    "iso:country":"SY",
    "name:ara_x_preferred":[
        "\u0627\u0644\u0628\u0631\u064a\u0635\u0629"
    ],
    "name:und_x_variant":[
        "Al Buray\u015fah"
    ],
    "wof:name":"Al Buraysah",
    "wof:placetype":"locality"
},
  "geometry": {"coordinates":[36.21161,33.38275],"type":"Point"}
}