{
  "type": "Feature",
  "properties": {
    "gn:admin1_code":"2.0",
    "gn:asciiname":"Dayrutan Mahalibah",
    "gn:country_code":"SY",
    "gn:dem":495,
    "gn:feature_class":"P",
    "gn:feature_code":"PPL",
    "gn:name":"Dayr\u016bt\u0101n Ma\u1e29\u0101libah",
    "gn:population":0,
    "gn:timezone":"Asia/Damascus",
    "iso:country":"SY",
    "name:ara_x_preferred":[
        "\u062f\u064a\u0631\u0648\u062a\u0627\u0646 \u0645\u062d\u0627\u0644\u0628\u0629"
    ],
    "name:und_x_variant":[
        "De\u00efroutane Mh\u00e2lb\u00e9",
        "Dairutan Mhalb\u00e9",
        "Dayr\u016bt\u0101n al Ma\u1e29\u0101libah",
        "Dayr\u016bt\u0101n Ma\u1e29\u0101libah",
        "Ma\u1e29\u0101libah"
    ],
    "wof:name":"Dayrutan Mahalibah",
    "wof:placetype":"locality"
},
  "geometry": {"coordinates":[36.08778,35.48417],"type":"Point"}
}