{
  "type": "Feature",
  "properties": {
    "gn:admin1_code":"8.0",
    "gn:asciiname":"Batrunah",
    "gn:country_code":"SY",
    "gn:dem":1252,
    "gn:feature_class":"P",
    "gn:feature_code":"PPL",
    "gn:name":"Ba\u0163r\u016bnah",
    "gn:population":0,
    "gn:timezone":"Asia/Damascus",
    "iso:country":"SY",
    "name:ara_x_preferred":[
        "\u0628\u0637\u0631\u0648\u0646\u0629"
    ],
    "name:ara_x_variant":[
        "\u0627\u0644\u0628\u0637\u0631\u0648\u0646\u0629",
        "\u0627\u0644\u0631\u0648\u0636\u0629"
    ],
    "name:und_x_variant":[
        "Batr\u016bnih",
        "Batr\u016bnah",
        "Batro\u00fbn\u00e9",
        "Al Ba\u0163r\u016bnah",
        "Ba\u0163r\u016bnah",
        "Ar Raw\u1e11ah"
    ],
    "wof:name":"Batrunah",
    "wof:placetype":"locality"
},
  "geometry": {"coordinates":[36.02214,33.65252],"type":"Point"}
}