{
  "type": "Feature",
  "properties": {
    "gn:admin1_code":"11.0",
    "gn:asciiname":"Shayha",
    "gn:country_code":"SY",
    "gn:dem":771,
    "gn:feature_class":"P",
    "gn:feature_code":"PPL",
    "gn:name":"Shay\u1e29\u0101",
    "gn:population":0,
    "gn:timezone":"Asia/Damascus",
    "iso:country":"SY",
    "name:ara_x_preferred":[
        "\u0634\u064a\u062d\u0627"
    ],
    "name:und_x_variant":[
        "Choua\u00efha",
        "Shuway\u1e29ah",
        "Shay\u1e29\u0101"
    ],
    "wof:name":"Shayha",
    "wof:placetype":"locality"
},
  "geometry": {"coordinates":[37.41017,34.89265],"type":"Point"}
}