{
  "type": "Feature",
  "properties": {
    "gn:admin1_code":"2.0",
    "gn:asciiname":"Jufin",
    "gn:country_code":"SY",
    "gn:dem":380,
    "gn:feature_class":"P",
    "gn:feature_code":"PPL",
    "gn:name":"J\u016bf\u012bn",
    "gn:population":0,
    "gn:timezone":"Asia/Damascus",
    "iso:country":"SY",
    "name:ara_x_preferred":[
        "J\u016bf\u012bn"
    ],
    "name:ara_x_variant":[
        "\u062c\u0648\u0641\u064a\u0646"
    ],
    "name:und_x_variant":[
        "Jo\u00fbf\u00eene"
    ],
    "wof:name":"Jufin",
    "wof:placetype":"locality"
},
  "geometry": {"coordinates":[36.09556,35.32249],"type":"Point"}
}