{
  "type": "Feature",
  "properties": {
    "gn:admin1_code":"12.0",
    "gn:asciiname":"Al Mashhad",
    "gn:country_code":"SY",
    "gn:dem":366,
    "gn:feature_class":"P",
    "gn:feature_code":"PPL",
    "gn:name":"Al Mashhad",
    "gn:population":0,
    "gn:timezone":"Asia/Damascus",
    "iso:country":"SY",
    "name:ara_x_preferred":[
        "\u0627\u0644\u0645\u0634\u0647\u062f"
    ],
    "wof:name":"Al Mashhad",
    "wof:placetype":"locality"
},
  "geometry": {"coordinates":[37.01697,35.44622000000001],"type":"Point"}
}