{
  "type": "Feature",
  "properties": {
    "gn:admin1_code":"8.0",
    "gn:asciiname":"Al Burghuliyah",
    "gn:country_code":"SY",
    "gn:dem":993,
    "gn:feature_class":"P",
    "gn:feature_code":"PPL",
    "gn:name":"Al Burghul\u012byah",
    "gn:population":0,
    "gn:timezone":"Asia/Damascus",
    "iso:country":"SY",
    "name:ara_x_preferred":[
        "\u0627\u0644\u0628\u0631\u0647\u0644\u0629"
    ],
    "name:ara_x_variant":[
        "\u0627\u0644\u0628\u0631\u063a\u0644\u064a\u0629"
    ],
    "name:und_x_variant":[
        "Al Barhalah",
        "Al Burghul\u012byah"
    ],
    "wof:name":"Al Burghuliyah",
    "wof:placetype":"locality"
},
  "geometry": {"coordinates":[36.11569,33.62541],"type":"Point"}
}