{
  "type": "Feature",
  "properties": {
    "gn:admin1_code":"14.0",
    "gn:asciiname":"Antuz",
    "gn:country_code":"SY",
    "gn:dem":284,
    "gn:feature_class":"P",
    "gn:feature_code":"PPL",
    "gn:name":"An\u0163\u016bz",
    "gn:population":0,
    "gn:timezone":"Asia/Damascus",
    "iso:country":"SY",
    "name:ara_x_preferred":[
        "Ant\u016bz"
    ],
    "name:ara_x_variant":[
        "An\u0163\u016bz",
        "\u0627\u0646\u0637\u0648\u0632"
    ],
    "name:und_x_variant":[
        "Annto\u00fbz"
    ],
    "wof:name":"Antuz",
    "wof:placetype":"locality"
},
  "geometry": {"coordinates":[35.96456,35.11844],"type":"Point"}
}