{
  "type": "Feature",
  "properties": {
    "gn:admin1_code":"12.0",
    "gn:asciiname":"Mantaf",
    "gn:country_code":"SY",
    "gn:dem":565,
    "gn:feature_class":"P",
    "gn:feature_code":"PPL",
    "gn:name":"Man\u0163af",
    "gn:population":0,
    "gn:timezone":"Asia/Damascus",
    "iso:country":"SY",
    "name:ara_x_preferred":[
        "\u0645\u0646\u0637\u0641"
    ],
    "name:und_x_variant":[
        "Manntaf",
        "Man\u0163af"
    ],
    "wof:name":"Mantaf",
    "wof:placetype":"locality"
},
  "geometry": {"coordinates":[36.65181,35.7784],"type":"Point"}
}