{
  "type": "Feature",
  "properties": {
    "gn:admin1_code":"11.0",
    "gn:asciiname":"`Ayn Husayn Gharbiyah",
    "gn:country_code":"SY",
    "gn:dem":496,
    "gn:feature_class":"P",
    "gn:feature_code":"PPL",
    "gn:name":"\u2018Ayn \u1e28usayn Gharb\u012byah",
    "gn:population":0,
    "gn:timezone":"Asia/Damascus",
    "iso:country":"SY",
    "name:ara_x_preferred":[
        "\u0639\u064a\u0646 \u062d\u0635\u064a\u0646 \u063a\u0631\u0628\u064a\u0629"
    ],
    "name:und_x_variant":[
        "\u2018Ayn \u1e28usayn Gharb\u012byah"
    ],
    "wof:name":"`Ayn Husayn Gharbiyah",
    "wof:placetype":"locality"
},
  "geometry": {"coordinates":[36.88077,34.86027],"type":"Point"}
}