{
  "type": "Feature",
  "properties": {
    "gn:admin1_code":"9.0",
    "gn:asciiname":"Qulsuruj",
    "gn:country_code":"SY",
    "gn:dem":451,
    "gn:feature_class":"P",
    "gn:feature_code":"PPL",
    "gn:name":"Q\u016blsur\u016bj",
    "gn:population":0,
    "gn:timezone":"Asia/Damascus",
    "iso:country":"SY",
    "name:ara_x_preferred":[
        "Qulsur\u016bj"
    ],
    "name:ara_x_variant":[
        "\u0642\u0644\u0633\u0631\u0648\u062c",
        "Q\u016blsur\u016bj",
        "\u0642\u0648\u0644\u0633\u0631\u0648\u062c"
    ],
    "name:und_x_variant":[
        "El Koute",
        "Qul Saruj",
        "Kol Sroudj",
        "Q\u00f4l Sro\u016bj",
        "Ku\u2018l as Sur\u016bj",
        "Qawl Sur\u016bj"
    ],
    "wof:name":"Qulsuruj",
    "wof:placetype":"locality"
},
  "geometry": {"coordinates":[37.26117,36.41746],"type":"Point"}
}