{
  "type": "Feature",
  "properties": {
    "gn:admin1_code":"8.0",
    "gn:asciiname":"Ard ash Shuwarit",
    "gn:country_code":"SY",
    "gn:dem":605,
    "gn:feature_class":"P",
    "gn:feature_code":"PPLL",
    "gn:name":"Ar\u1e11 ash Shuwar\u012b\u0163",
    "gn:population":0,
    "gn:timezone":"Asia/Damascus",
    "iso:country":"SY",
    "name:ara_x_preferred":[
        "\u0623\u0631\u0636 \u0627\u0644\u0634\u0648\u0627\u0631\u064a\u0637"
    ],
    "name:und_x_variant":[
        "Ar\u1e11 ash Shuwar\u012b\u0163"
    ],
    "wof:name":"Ard ash Shuwarit",
    "wof:placetype":"locality"
},
  "geometry": {"coordinates":[36.58223,33.51019],"type":"Point"}
}