{
  "type": "Feature",
  "properties": {
    "gn:admin1_code":"2.0",
    "gn:asciiname":"Raqiq",
    "gn:country_code":"SY",
    "gn:dem":195,
    "gn:feature_class":"P",
    "gn:feature_code":"PPL",
    "gn:name":"Raq\u012bq",
    "gn:population":0,
    "gn:timezone":"Asia/Damascus",
    "iso:country":"SY",
    "name:ara_x_preferred":[
        "\u0631\u0642\u064a\u0642"
    ],
    "name:und_x_variant":[
        "Rq\u00eeq",
        "Raq\u012bq"
    ],
    "wof:name":"Raqiq",
    "wof:placetype":"locality"
},
  "geometry": {"coordinates":[36.01076,35.61323],"type":"Point"}
}