{
  "type": "Feature",
  "properties": {
    "gn:admin1_code":"10.0",
    "gn:asciiname":"`Ashiq `Umar",
    "gn:country_code":"SY",
    "gn:dem":587,
    "gn:feature_class":"P",
    "gn:feature_code":"PPL",
    "gn:name":"\u2018\u0100shiq \u2018Umar",
    "gn:population":0,
    "gn:timezone":"Asia/Damascus",
    "iso:country":"SY",
    "name:ara_x_preferred":[
        "\u0639\u0627\u0634\u0642 \u0639\u0645\u0631"
    ],
    "name:und_x_variant":[
        "A\u00e2cheq Omar",
        "\u2018\u0100shiq \u2018Umar"
    ],
    "wof:name":"`Ashiq `Umar",
    "wof:placetype":"locality"
},
  "geometry": {"coordinates":[36.32492,34.95187],"type":"Point"}
}