{
  "type": "Feature",
  "properties": {
    "gn:admin1_code":"2.0",
    "gn:asciiname":"Sitamu",
    "gn:country_code":"SY",
    "gn:dem":98,
    "gn:feature_class":"P",
    "gn:feature_code":"PPL",
    "gn:name":"\u015ei\u0163\u0101m\u016b",
    "gn:population":0,
    "gn:timezone":"Asia/Damascus",
    "iso:country":"SY",
    "name:ara_x_preferred":[
        "S\u0163\u0101m\u016b"
    ],
    "name:ara_x_variant":[
        "Si\u0163\u0101m\u016b",
        "\u0633\u0637\u0627\u0645\u0648",
        "\u015ei\u0163\u0101m\u016b",
        "\u0635\u0637\u0627\u0645\u0648"
    ],
    "name:und_x_variant":[
        "St\u00e2mo",
        "\u015ea\u0163\u0101m\u016b"
    ],
    "wof:name":"Sitamu",
    "wof:placetype":"locality"
},
  "geometry": {"coordinates":[35.92287,35.48025999999999],"type":"Point"}
}