{
  "type": "Feature",
  "properties": {
    "gn:admin1_code":"8.0",
    "gn:asciiname":"Ard Umm at Tum",
    "gn:country_code":"SY",
    "gn:dem":608,
    "gn:feature_class":"P",
    "gn:feature_code":"PPLL",
    "gn:name":"Ar\u1e11 Umm at T\u016bm",
    "gn:population":0,
    "gn:timezone":"Asia/Damascus",
    "iso:country":"SY",
    "name:ara_x_preferred":[
        "\u0623\u0631\u0636 \u0623\u0645 \u0627\u0644\u062a\u0648\u0645"
    ],
    "name:und_x_variant":[
        "Ar\u1e11 Umm at T\u016bm"
    ],
    "wof:name":"Ard Umm at Tum",
    "wof:placetype":"locality"
},
  "geometry": {"coordinates":[36.51708,33.56342],"type":"Point"}
}