{
  "type": "Feature",
  "properties": {
    "iso:country":"SY",
    "name:ara_x_preferred":[
        "\u0627\u0644\u0631\u0645\u0644"
    ],
    "qs:gn_country":"SY",
    "qs:gn_fcode":"PPL",
    "qs:gn_pop":0,
    "qs:name":"Ar Raml",
    "qs:name_adm0":"\u0633\u0648\u0631\u064a\u0627",
    "qs:name_adm1":"H'ims",
    "qs:photos":4,
    "qs:photos_1k":1,
    "qs:photos_9k":1,
    "qs:photos_9r":1,
    "qs:photos_all":4,
    "qs:photos_sr":1,
    "qs:placetype":"Town",
    "qs:pop_sr":"0",
    "qs:woe_adm0":23424956,
    "wof:name":"Ar Raml",
    "wof:placetype":"locality"
},
  "geometry": {"coordinates":[37.96294,34.51936],"type":"Point"}
}