{
  "type": "Feature",
  "properties": {
    "gn:admin1_code":"1.0",
    "gn:asciiname":"Maqrinat",
    "gn:country_code":"SY",
    "gn:dem":340,
    "gn:feature_class":"P",
    "gn:feature_code":"PPL",
    "gn:name":"Maqr\u012bn\u0101t",
    "gn:population":0,
    "gn:timezone":"Asia/Damascus",
    "iso:country":"SY",
    "name:ara_x_preferred":[
        "\u0645\u0642\u0631\u064a\u0646\u0627\u062a"
    ],
    "name:und_x_variant":[
        "Magre\u00efn\u00e2te",
        "Maqre\u00efn\u00e2te",
        "Maqr\u012bn\u0101t",
        "Muqr\u012bn\u0101t"
    ],
    "wof:name":"Maqrinat",
    "wof:placetype":"locality"
},
  "geometry": {"coordinates":[41.36455,36.72638],"type":"Point"}
}