{
  "type": "Feature",
  "properties": {
    "gn:admin1_code":"8.0",
    "gn:asciiname":"Ar Rab` ash Sharqi",
    "gn:country_code":"SY",
    "gn:dem":774,
    "gn:feature_class":"P",
    "gn:feature_code":"PPLL",
    "gn:name":"Ar Rab\u2018 ash Sharq\u012b",
    "gn:population":0,
    "gn:timezone":"Asia/Damascus",
    "iso:country":"SY",
    "name:ara_x_preferred":[
        "\u0627\u0644\u0631\u0628\u0639 \u0627\u0644\u0634\u0631\u0642\u064a"
    ],
    "name:und_x_variant":[
        "Ar Rab\u2018 ash Sharq\u012b"
    ],
    "wof:name":"Ar Rab` ash Sharqi",
    "wof:placetype":"locality"
},
  "geometry": {"coordinates":[36.17318,33.45864],"type":"Point"}
}