{
  "type": "Feature",
  "properties": {
    "gn:admin1_code":"8.0",
    "gn:asciiname":"Khirbat Maqam",
    "gn:country_code":"SY",
    "gn:dem":797,
    "gn:feature_class":"P",
    "gn:feature_code":"PPL",
    "gn:name":"Khirbat Maq\u0101m",
    "gn:population":0,
    "gn:timezone":"Asia/Damascus",
    "iso:country":"SY",
    "name:ara_x_preferred":[
        "\u062e\u0631\u0628\u0629 \u0645\u0642\u0627\u0645"
    ],
    "name:und_x_variant":[
        "Khirbat Maq\u0101m"
    ],
    "wof:name":"Khirbat Maqam",
    "wof:placetype":"locality"
},
  "geometry": {"coordinates":[36.11987,33.30665],"type":"Point"}
}