{
  "type": "Feature",
  "properties": {
    "gn:admin1_code":"7.0",
    "gn:asciiname":"Tayyani",
    "gn:country_code":"SY",
    "gn:dem":191,
    "gn:feature_class":"P",
    "gn:feature_code":"PPL",
    "gn:name":"\u0162ayy\u0101n\u012b",
    "gn:population":0,
    "gn:timezone":"Asia/Damascus",
    "iso:country":"SY",
    "name:ara_x_preferred":[
        "\u0637\u064a\u0627\u0646\u064a"
    ],
    "name:und_x_variant":[
        "Ta\u00efy\u00e2n\u00e9",
        "Tayy\u0101nah",
        "\u0162ayy\u0101n\u012b"
    ],
    "wof:name":"Tayyani",
    "wof:placetype":"locality"
},
  "geometry": {"coordinates":[40.54149,34.97839],"type":"Point"}
}