{
  "type": "Feature",
  "properties": {
    "gn:admin1_code":"10.0",
    "gn:asciiname":"Qal`at `Ulyan",
    "gn:country_code":"SY",
    "gn:dem":691,
    "gn:feature_class":"P",
    "gn:feature_code":"PPL",
    "gn:name":"Qal\u2018at \u2018Uly\u0101n",
    "gn:population":0,
    "gn:timezone":"Asia/Damascus",
    "iso:country":"SY",
    "name:ara_x_preferred":[
        "\u0642\u0644\u0639\u0629 \u0639\u0644\u064a\u0627\u0646"
    ],
    "name:und_x_variant":[
        "Qal\u2018at \u2018Uly\u0101n"
    ],
    "wof:name":"Qal`at `Ulyan",
    "wof:placetype":"locality"
},
  "geometry": {"coordinates":[36.32802,34.92085],"type":"Point"}
}