{
  "type": "Feature",
  "properties": {
    "gn:admin1_code":"1.0",
    "gn:asciiname":"Huwayziyah",
    "gn:country_code":"SY",
    "gn:dem":339,
    "gn:feature_class":"P",
    "gn:feature_code":"PPL",
    "gn:name":"\u1e28uwayz\u012byah",
    "gn:population":0,
    "gn:timezone":"Asia/Damascus",
    "iso:country":"SY",
    "name:ara_x_preferred":[
        "\u062d\u0648\u064a\u0632\u064a\u0629"
    ],
    "name:und_x_variant":[
        "\u1e28uwayz\u012byah"
    ],
    "wof:name":"Huwayziyah",
    "wof:placetype":"locality"
},
  "geometry": {"coordinates":[41.00417,36.16525],"type":"Point"}
}