{
  "type": "Feature",
  "properties": {
    "gn:admin1_code":"9.0",
    "gn:asciiname":"`Arab Hasan Saghir",
    "gn:country_code":"SY",
    "gn:dem":419,
    "gn:feature_class":"P",
    "gn:feature_code":"PPL",
    "gn:name":"\u2018Arab \u1e28asan \u015eagh\u012br",
    "gn:population":0,
    "gn:timezone":"Asia/Damascus",
    "iso:country":"SY",
    "name:ara_x_preferred":[
        "\u0639\u0631\u0628 \u062d\u0633\u0646 \u0635\u063a\u064a\u0631"
    ],
    "name:und_x_variant":[
        "Aarab Hassane S\u00e9rhir",
        "\u2018Arab \u1e28asan a\u015f \u015eagh\u012br",
        "\u2018Arab \u1e28asan \u015eagh\u012br"
    ],
    "wof:name":"`Arab Hasan Saghir",
    "wof:placetype":"locality"
},
  "geometry": {"coordinates":[37.85048,36.65682],"type":"Point"}
}