{
  "type": "Feature",
  "properties": {
    "gn:admin1_code":"9.0",
    "gn:asciiname":"Waqah",
    "gn:country_code":"SY",
    "gn:dem":519,
    "gn:feature_class":"P",
    "gn:feature_code":"PPL",
    "gn:name":"Waq\u0101\u1e29",
    "gn:population":0,
    "gn:timezone":"Asia/Damascus",
    "iso:country":"SY",
    "name:ara_x_preferred":[
        "Wiq\u0101\u1e29"
    ],
    "name:ara_x_variant":[
        "\u0648\u0642\u0627\u062d"
    ],
    "name:und_x_variant":[
        "Waq\u0101\u1e29",
        "Waqah"
    ],
    "wof:name":"Waqah",
    "wof:placetype":"locality"
},
  "geometry": {"coordinates":[37.43174000000001,36.40372],"type":"Point"}
}