{
  "type": "Feature",
  "properties": {
    "gn:admin1_code":"12.0",
    "gn:asciiname":"Rasm al Barjis",
    "gn:country_code":"SY",
    "gn:dem":294,
    "gn:feature_class":"P",
    "gn:feature_code":"PPL",
    "gn:name":"Rasm al Barjis",
    "gn:population":0,
    "gn:timezone":"Asia/Damascus",
    "iso:country":"SY",
    "name:ara_x_preferred":[
        "\u0631\u0633\u0645 \u0627\u0644\u0628\u0631\u062c\u0633"
    ],
    "wof:name":"Rasm al Barjis",
    "wof:placetype":"locality"
},
  "geometry": {"coordinates":[37.17648,35.52976],"type":"Point"}
}