{
  "type": "Feature",
  "properties": {
    "gn:admin1_code":"10.0",
    "gn:asciiname":"Huwayr as Sulayb",
    "gn:country_code":"SY",
    "gn:dem":416,
    "gn:feature_class":"P",
    "gn:feature_code":"PPL",
    "gn:name":"\u1e28uwayr a\u015f \u015eulayb",
    "gn:population":0,
    "gn:timezone":"Asia/Damascus",
    "iso:country":"SY",
    "name:ara_x_preferred":[
        "\u062d\u0648\u064a\u0631 \u0627\u0644\u0635\u0644\u064a\u0628"
    ],
    "name:und_x_variant":[
        "Hou\u00e9r\u00e9",
        "Houa\u00efr es Sla\u00efb",
        "\u1e28uwayr a\u015f \u015eulayb"
    ],
    "wof:name":"Huwayr as Sulayb",
    "wof:placetype":"locality"
},
  "geometry": {"coordinates":[36.54468,35.05439000000001],"type":"Point"}
}