{
  "type": "Feature",
  "properties": {
    "gn:admin1_code":"9.0",
    "gn:asciiname":"At Tulaylah",
    "gn:country_code":"SY",
    "gn:dem":811,
    "gn:feature_class":"P",
    "gn:feature_code":"PPL",
    "gn:name":"At Tulaylah",
    "gn:population":0,
    "gn:timezone":"Asia/Damascus",
    "iso:country":"SY",
    "name:ara_x_preferred":[
        "\u062a\u0628\u0647 \u0643\u0648\u064a"
    ],
    "name:ara_x_variant":[
        "\u0627\u0644\u062a\u0644\u064a\u0644\u0629"
    ],
    "name:kur_x_preferred":[
        "Gaz\u00ea"
    ],
    "name:und_x_variant":[
        "T\u00e9p\u00e9 Keuy",
        "Tabah K\u016by",
        "At Tulaylah"
    ],
    "wof:name":"At Tulaylah",
    "wof:placetype":"locality"
},
  "geometry": {"coordinates":[36.70717,36.79423],"type":"Point"}
}