{
  "type": "Feature",
  "properties": {
    "gn:admin1_code":"10.0",
    "gn:asciiname":"Mushayrifat al Muwaylih",
    "gn:country_code":"SY",
    "gn:dem":429,
    "gn:feature_class":"P",
    "gn:feature_code":"PPL",
    "gn:name":"Mushayrifat al Muwayli\u1e29",
    "gn:population":0,
    "gn:timezone":"Asia/Damascus",
    "iso:country":"SY",
    "name:ara_x_preferred":[
        "\u0645\u0634\u064a\u0631\u0641\u0629 \u0627\u0644\u0645\u0648\u064a\u0644\u062d"
    ],
    "name:und_x_variant":[
        "M\u00e9cherfet el Mo\u00fba\u00efleh",
        "Mashrafat al Muwayli\u1e29",
        "Mushayrifat al Muwayli\u1e29"
    ],
    "wof:name":"Mushayrifat al Muwaylih",
    "wof:placetype":"locality"
},
  "geometry": {"coordinates":[37.4695,35.26888],"type":"Point"}
}