{
  "type": "Feature",
  "properties": {
    "gn:admin1_code":"6.0",
    "gn:asciiname":"Shaqrah",
    "gn:country_code":"SY",
    "gn:dem":580,
    "gn:feature_class":"P",
    "gn:feature_code":"PPL",
    "gn:name":"Shaqrah",
    "gn:population":0,
    "gn:timezone":"Asia/Damascus",
    "iso:country":"SY",
    "name:ara_x_preferred":[
        "\u0634\u0642\u0631\u0629"
    ],
    "name:und_x_variant":[
        "Chakra",
        "Shakra",
        "Chaqra",
        "Shaqrah",
        "Shaqr\u0101\u2019"
    ],
    "wof:name":"Shaqrah",
    "wof:placetype":"locality"
},
  "geometry": {"coordinates":[36.2375,32.90691],"type":"Point"}
}