{
  "type": "Feature",
  "properties": {
    "gn:admin1_code":"1.0",
    "gn:asciiname":"Tall Khurnub Rashid",
    "gn:country_code":"SY",
    "gn:dem":343,
    "gn:feature_class":"P",
    "gn:feature_code":"PPL",
    "gn:name":"Tall Khurn\u016bb Rash\u012bd",
    "gn:population":0,
    "gn:timezone":"Asia/Damascus",
    "iso:country":"SY",
    "name:ara_x_preferred":[
        "\u062a\u0644 \u062e\u0631\u0646\u0648\u0628 \u0631\u0634\u064a\u062f"
    ],
    "name:tur_x_preferred":[
        "Tall Khurn\u016bb Rash\u012bd"
    ],
    "name:und_x_variant":[
        "Tell Kharno\u00fbb Rach\u00eed"
    ],
    "wof:name":"Tall Khurnub Rashid",
    "wof:placetype":"locality"
},
  "geometry": {"coordinates":[41.32559000000001,36.74902],"type":"Point"}
}