{
  "type": "Feature",
  "properties": {
    "gn:admin1_code":"9.0",
    "gn:asciiname":"Al Muwaylah",
    "gn:country_code":"SY",
    "gn:dem":347,
    "gn:feature_class":"P",
    "gn:feature_code":"PPL",
    "gn:name":"Al Muwaylah",
    "gn:population":0,
    "gn:timezone":"Asia/Damascus",
    "iso:country":"SY",
    "name:ara_x_preferred":[
        "\u0627\u0644\u0645\u0648\u064a\u0644\u0629"
    ],
    "wof:name":"Al Muwaylah",
    "wof:placetype":"locality"
},
  "geometry": {"coordinates":[38.15834,35.76787],"type":"Point"}
}