{
  "type": "Feature",
  "properties": {
    "gn:admin1_code":"1.0",
    "gn:asciiname":"Jarwan",
    "gn:country_code":"SY",
    "gn:dem":306,
    "gn:feature_class":"P",
    "gn:feature_code":"PPL",
    "gn:name":"Jarw\u0101n",
    "gn:population":0,
    "gn:timezone":"Asia/Damascus",
    "iso:country":"SY",
    "name:ara_x_preferred":[
        "\u062c\u0631\u0648\u0627\u0646"
    ],
    "name:und_x_variant":[
        "Jarw\u0101n"
    ],
    "wof:name":"Jarwan",
    "wof:placetype":"locality"
},
  "geometry": {"coordinates":[40.43725,36.00487000000001],"type":"Point"}
}