{
  "type": "Feature",
  "properties": {
    "gn:admin1_code":"11.0",
    "gn:asciiname":"Al Buwayt",
    "gn:country_code":"SY",
    "gn:dem":552,
    "gn:feature_class":"P",
    "gn:feature_code":"PPL",
    "gn:name":"Al Buwayt",
    "gn:population":0,
    "gn:timezone":"Asia/Damascus",
    "iso:country":"SY",
    "name:ara_x_preferred":[
        "\u0627\u0644\u0628\u0648\u064a\u062a"
    ],
    "name:und_x_variant":[
        "El Bouite",
        "El Boua\u00efte",
        "Al Buwayt"
    ],
    "wof:name":"Al Buwayt",
    "wof:placetype":"locality"
},
  "geometry": {"coordinates":[36.41656,34.59990999999999],"type":"Point"}
}