{
  "type": "Feature",
  "properties": {
    "gn:admin1_code":"11.0",
    "gn:asciiname":"Summaqiyat al Gharbiyah",
    "gn:country_code":"SY",
    "gn:dem":549,
    "gn:feature_class":"P",
    "gn:feature_code":"PPL",
    "gn:name":"Summ\u0101q\u012by\u0101t al Gharb\u012byah",
    "gn:population":0,
    "gn:timezone":"Asia/Damascus",
    "iso:country":"SY",
    "name:ara_x_preferred":[
        "\u0633\u0645\u0627\u0642\u064a\u0627\u062a \u0627\u0644\u063a\u0631\u0628\u064a\u0629"
    ],
    "name:ara_x_variant":[
        "\u0627\u0644\u0633\u0645\u0627\u0642\u064a\u0627\u062a \u0627\u0644\u063a\u0631\u0628\u064a\u0629"
    ],
    "name:und_x_variant":[
        "Gharbi\u00e9",
        "Soum\u00e2qiy\u00e2te Rhaybiyi",
        "Soum\u00e2qiy\u00e2te el Rharb\u00eey\u00e9",
        "Summ\u0101q\u012by\u0101t al Gharb\u012byah",
        "As Summ\u0101q\u012by\u0101t al Gharb\u012byah"
    ],
    "wof:name":"Summaqiyat al Gharbiyah",
    "wof:placetype":"locality"
},
  "geometry": {"coordinates":[36.44852,34.5715],"type":"Point"}
}