{
  "type": "Feature",
  "properties": {
    "gn:admin1_code":"1.0",
    "gn:asciiname":"Salihiyah",
    "gn:country_code":"SY",
    "gn:dem":299,
    "gn:feature_class":"P",
    "gn:feature_code":"PPL",
    "gn:name":"\u015e\u0101li\u1e29\u012byah",
    "gn:population":0,
    "gn:timezone":"Asia/Damascus",
    "iso:country":"SY",
    "name:ara_x_preferred":[
        "\u0635\u0627\u0644\u062d\u064a\u0629"
    ],
    "name:und_x_variant":[
        "\u015e\u0101li\u1e29\u012byah"
    ],
    "wof:name":"Salihiyah",
    "wof:placetype":"locality"
},
  "geometry": {"coordinates":[40.66323,36.06448],"type":"Point"}
}