{
  "type": "Feature",
  "properties": {
    "gn:admin1_code":"5.0",
    "gn:asciiname":"Dhakir",
    "gn:country_code":"SY",
    "gn:dem":725,
    "gn:feature_class":"P",
    "gn:feature_code":"PPL",
    "gn:name":"Dhak\u012br",
    "gn:population":0,
    "gn:timezone":"Asia/Damascus",
    "iso:country":"SY",
    "name:ara_x_preferred":[
        "\u0630\u0643\u064a\u0631"
    ],
    "name:und_x_variant":[
        "Dhak\u012br",
        "Dek\u012br",
        "Dak\u012br",
        "Dhukayr"
    ],
    "wof:name":"Dhakir",
    "wof:placetype":"locality"
},
  "geometry": {"coordinates":[36.5498,33.04539],"type":"Point"}
}