{
  "type": "Feature",
  "properties": {
    "gn:admin1_code":"8.0",
    "gn:asciiname":"Ash Shu`aybat",
    "gn:country_code":"SY",
    "gn:dem":1114,
    "gn:feature_class":"P",
    "gn:feature_code":"PPLL",
    "gn:name":"Ash Shu\u2018ayb\u0101t",
    "gn:population":0,
    "gn:timezone":"Asia/Damascus",
    "iso:country":"SY",
    "name:ara_x_preferred":[
        "\u0627\u0644\u0634\u0639\u064a\u0628\u0627\u062a"
    ],
    "name:und_x_variant":[
        "Ash Shu\u2018ayb\u0101t"
    ],
    "wof:name":"Ash Shu`aybat",
    "wof:placetype":"locality"
},
  "geometry": {"coordinates":[36.05831,33.6688],"type":"Point"}
}