{
  "type": "Feature",
  "properties": {
    "gn:admin1_code":"8.0",
    "gn:asciiname":"Ard ash Shayyah",
    "gn:country_code":"SY",
    "gn:dem":604,
    "gn:feature_class":"P",
    "gn:feature_code":"PPLL",
    "gn:name":"Ar\u1e11 ash Shayy\u0101\u1e29",
    "gn:population":0,
    "gn:timezone":"Asia/Damascus",
    "iso:country":"SY",
    "name:ara_x_preferred":[
        "\u0623\u0631\u0636 \u0627\u0644\u0634\u064a\u0627\u062d"
    ],
    "name:und_x_variant":[
        "Ar\u1e11 ash Shayy\u0101\u1e29"
    ],
    "wof:name":"Ard ash Shayyah",
    "wof:placetype":"locality"
},
  "geometry": {"coordinates":[36.55828,33.43473],"type":"Point"}
}