{
  "type": "Feature",
  "properties": {
    "gn:admin1_code":"1.0",
    "gn:asciiname":"Al `Unayzah",
    "gn:country_code":"SY",
    "gn:dem":385,
    "gn:feature_class":"P",
    "gn:feature_code":"PPL",
    "gn:name":"Al \u2018Unayzah",
    "gn:population":0,
    "gn:timezone":"Asia/Damascus",
    "iso:country":"SY",
    "name:ara_x_preferred":[
        "\u0627\u0644\u0639\u0646\u064a\u0632\u0629"
    ],
    "name:und_x_variant":[
        "El Aan\u00e9z\u00e9",
        "Al \u2018Anazah",
        "\u2018Unayzah",
        "Al \u2018Unayzah"
    ],
    "wof:name":"Al `Unayzah",
    "wof:placetype":"locality"
},
  "geometry": {"coordinates":[41.76685,36.89448],"type":"Point"}
}