{
  "type": "Feature",
  "properties": {
    "gn:admin1_code":"7.0",
    "gn:asciiname":"Al Khajjah",
    "gn:country_code":"SY",
    "gn:dem":211,
    "gn:feature_class":"P",
    "gn:feature_code":"PPL",
    "gn:name":"Al Khajjah",
    "gn:population":0,
    "gn:timezone":"Asia/Damascus",
    "iso:country":"SY",
    "name:ara_x_preferred":[
        "\u0627\u0644\u062e\u062c\u0629"
    ],
    "wof:name":"Al Khajjah",
    "wof:placetype":"locality"
},
  "geometry": {"coordinates":[40.54494,35.27225],"type":"Point"}
}