{
  "type": "Feature",
  "properties": {
    "gn:admin1_code":"2.0",
    "gn:asciiname":"Al Qalluf",
    "gn:country_code":"SY",
    "gn:dem":228,
    "gn:feature_class":"P",
    "gn:feature_code":"PPL",
    "gn:name":"Al Qall\u016bf",
    "gn:population":0,
    "gn:timezone":"Asia/Damascus",
    "iso:country":"SY",
    "name:ara_x_preferred":[
        "\u0627\u0644\u0642\u0644\u0648\u0641"
    ],
    "name:und_x_variant":[
        "Qallo\u00fbf",
        "Kallouf",
        "Al Qall\u016bf",
        "Qluf"
    ],
    "wof:name":"Al Qalluf",
    "wof:placetype":"locality"
},
  "geometry": {"coordinates":[35.88365,35.64488],"type":"Point"}
}