{
  "type": "Feature",
  "properties": {
    "gn:admin1_code":"11.0",
    "gn:asciiname":"Bsas",
    "gn:country_code":"SY",
    "gn:dem":293,
    "gn:feature_class":"P",
    "gn:feature_code":"PPL",
    "gn:name":"Bs\u0101s",
    "gn:population":0,
    "gn:timezone":"Asia/Damascus",
    "iso:country":"SY",
    "name:ara_x_preferred":[
        "Bs\u0101s"
    ],
    "name:ara_x_variant":[
        "Bis\u0101s",
        "\u0628\u0633\u0627\u0633",
        "\u0628\u0633\u0627\u0633 \u0627\u0644\u0642\u062f\u064a\u0645\u0629",
        "\u0628\u0633\u0627\u0633 \u0627\u0644\u062c\u062f\u064a\u062f\u0629"
    ],
    "name:pol_x_preferred":[
        "Bisas"
    ],
    "name:und_x_variant":[
        "Bs\u0101s",
        "Bs\u0101s al Qad\u012bmah",
        "Bs\u0101s al Jad\u012bdah",
        "Bis\u0101s al Qad\u012bmah",
        "Bis\u0101s al Jad\u012bdah"
    ],
    "name:vie_x_preferred":[
        "Bisas"
    ],
    "wof:name":"Bsas",
    "wof:placetype":"locality"
},
  "geometry": {"coordinates":[36.306,34.73083],"type":"Point"}
}