{
  "type": "Feature",
  "properties": {
    "iso:country":"SY",
    "name:ara_x_preferred":[
        "\u0628\u0627\u0631\u0627\u0642"
    ],
    "name:ara_x_variant":[
        "\u0628\u0631\u0643\u0629",
        "\u0628\u0631\u0643\u0627"
    ],
    "name:bre_x_preferred":[
        "Barak"
    ],
    "name:ces_x_preferred":[
        "B\u00e1rak"
    ],
    "name:deu_x_preferred":[
        "Barak"
    ],
    "name:ell_x_preferred":[
        "\u0392\u03b1\u03c1\u03ac\u03ba"
    ],
    "name:eng_x_preferred":[
        "Barak"
    ],
    "name:epo_x_preferred":[
        "Barak"
    ],
    "name:fas_x_preferred":[
        "\u0628\u0627\u0631\u0627\u06a9"
    ],
    "name:fin_x_preferred":[
        "Barak"
    ],
    "name:fra_x_preferred":[
        "Barac"
    ],
    "name:hbs_x_preferred":[
        "Barak"
    ],
    "name:heb_x_preferred":[
        "\u05d1\u05e8\u05e7 \u05d1\u05df \u05d0\u05d1\u05d9\u05e0\u05e2\u05dd"
    ],
    "name:ind_x_preferred":[
        "Barak"
    ],
    "name:ita_x_preferred":[
        "Barac"
    ],
    "name:jpn_x_preferred":[
        "\u30d0\u30e9\u30af"
    ],
    "name:nld_x_preferred":[
        "Barak"
    ],
    "name:nob_x_preferred":[
        "Barak"
    ],
    "name:nor_x_preferred":[
        "Barak"
    ],
    "name:pnb_x_preferred":[
        "\u0628\u0627\u0631\u0627\u06a9"
    ],
    "name:pol_x_preferred":[
        "Barak"
    ],
    "name:por_x_preferred":[
        "Barac"
    ],
    "name:rus_x_preferred":[
        "\u0412\u0430\u0440\u0430\u043a"
    ],
    "name:spa_x_preferred":[
        "Barak"
    ],
    "name:swa_x_preferred":[
        "Barak"
    ],
    "name:swe_x_preferred":[
        "Barak"
    ],
    "name:tur_x_preferred":[
        "Barak"
    ],
    "name:ukr_x_preferred":[
        "\u0411\u0430\u0440\u0430\u043a"
    ],
    "name:unk_x_variant":[
        "Barakah"
    ],
    "name:urd_x_preferred":[
        "\u0628\u0627\u0631\u0627\u06a9"
    ],
    "name:wol_x_preferred":[
        "Barag"
    ],
    "qs:gn_country":"SY",
    "qs:gn_fcode":"PPL",
    "qs:gn_pop":0,
    "qs:name":"Barak",
    "qs:name_adm0":"Turkey",
    "qs:name_adm1":"Gaziantep",
    "qs:photos":5,
    "qs:photos_1k":1,
    "qs:photos_9k":1,
    "qs:photos_9r":1,
    "qs:photos_all":5,
    "qs:photos_sr":1,
    "qs:placetype":"Suburb",
    "qs:pop_sr":"0",
    "qs:woe_adm0":23424969,
    "wd:wordcount":371,
    "wof:name":"Barak",
    "wof:placetype":"neighbourhood"
},
  "geometry": {"coordinates":[36.68545,36.5461],"type":"Point"}
}