{
  "type": "Feature",
  "properties": {
    "gn:admin1_code":"4.0",
    "gn:asciiname":"Ath Thadyayn",
    "gn:country_code":"SY",
    "gn:dem":285,
    "gn:feature_class":"P",
    "gn:feature_code":"PPL",
    "gn:name":"Ath Thadyayn",
    "gn:population":0,
    "gn:timezone":"Asia/Damascus",
    "iso:country":"SY",
    "name:ara_x_preferred":[
        "\u0627\u0644\u062b\u062f\u064a\u064a\u0646"
    ],
    "name:und_x_variant":[
        "As Saddayn",
        "Ath Thadyayn"
    ],
    "wof:name":"Ath Thadyayn",
    "wof:placetype":"locality"
},
  "geometry": {"coordinates":[38.71853,35.83728],"type":"Point"}
}