{
  "type": "Feature",
  "properties": {
    "gn:admin1_code":"8.0",
    "gn:asciiname":"Ash Sharqi",
    "gn:country_code":"SY",
    "gn:dem":808,
    "gn:feature_class":"P",
    "gn:feature_code":"PPLL",
    "gn:name":"Ash Sharq\u012b",
    "gn:population":0,
    "gn:timezone":"Asia/Damascus",
    "iso:country":"SY",
    "name:ara_x_preferred":[
        "\u0627\u0644\u0634\u0631\u0642\u064a"
    ],
    "name:und_x_variant":[
        "Ash Sharq\u012b"
    ],
    "wof:name":"Ash Sharqi",
    "wof:placetype":"locality"
},
  "geometry": {"coordinates":[36.72214,33.7304],"type":"Point"}
}