{
  "type": "Feature",
  "properties": {
    "gn:admin1_code":"1.0",
    "gn:asciiname":"Mahbaliyah",
    "gn:country_code":"SY",
    "gn:dem":359,
    "gn:feature_class":"P",
    "gn:feature_code":"PPL",
    "gn:name":"Mahb\u0101l\u012byah",
    "gn:population":0,
    "gn:timezone":"Asia/Damascus",
    "iso:country":"SY",
    "name:ara_x_preferred":[
        "\u0645\u0647\u0628\u0627\u0644\u064a\u0629"
    ],
    "name:und_x_variant":[
        "Mahb\u0101l\u012byah"
    ],
    "wof:name":"Mahbaliyah",
    "wof:placetype":"locality"
},
  "geometry": {"coordinates":[41.05113,36.21592],"type":"Point"}
}