{
  "type": "Feature",
  "properties": {
    "gn:admin1_code":"11.0",
    "gn:asciiname":"Umm Haratayn ash Sharqiyah",
    "gn:country_code":"SY",
    "gn:dem":714,
    "gn:feature_class":"P",
    "gn:feature_code":"PPL",
    "gn:name":"Umm \u1e28\u0101ratayn ash Sharq\u012byah",
    "gn:population":0,
    "gn:timezone":"Asia/Damascus",
    "iso:country":"SY",
    "name:ara_x_preferred":[
        "\u0623\u0645 \u062d\u0627\u0631\u062a\u064a\u0646 \u0627\u0644\u0634\u0631\u0642\u064a\u0629"
    ],
    "name:und_x_variant":[
        "Oum H\u00e2rta\u00efne Charq\u00eey\u00e9",
        "Umm \u1e28\u0101ratayn ash Sharq\u012byah"
    ],
    "wof:name":"Umm Haratayn ash Sharqiyah",
    "wof:placetype":"locality"
},
  "geometry": {"coordinates":[37.29671,34.89094],"type":"Point"}
}