{
  "type": "Feature",
  "properties": {
    "gn:admin1_code":"1.0",
    "gn:asciiname":"Khirbat al Bi'r",
    "gn:country_code":"SY",
    "gn:dem":352,
    "gn:feature_class":"P",
    "gn:feature_code":"PPL",
    "gn:name":"Khirbat al Bi\u2019r",
    "gn:population":0,
    "gn:timezone":"Asia/Damascus",
    "iso:country":"SY",
    "name:ara_x_preferred":[
        "\u062e\u0631\u0628\u0629 \u0627\u0644\u0628\u064a\u0631"
    ],
    "name:und_x_variant":[
        "Khirbat al Bi\u2019r"
    ],
    "wof:name":"Khirbat al Bi'r",
    "wof:placetype":"locality"
},
  "geometry": {"coordinates":[40.28333,36.08833],"type":"Point"}
}