{
  "type": "Feature",
  "properties": {
    "gn:admin1_code":"14.0",
    "gn:asciiname":"`Aqrab",
    "gn:country_code":"SY",
    "gn:dem":386,
    "gn:feature_class":"P",
    "gn:feature_code":"PPL",
    "gn:name":"\u2018Aqrab",
    "gn:population":0,
    "gn:timezone":"Asia/Damascus",
    "iso:country":"SY",
    "name:ara_x_preferred":[
        "\u2018Ak\u0101k\u012br"
    ],
    "name:ara_x_variant":[
        "\u0639\u0643\u0627\u0643\u064a\u0631",
        "\u0639\u0642\u0631\u0628"
    ],
    "name:und_x_variant":[
        "Aak\u00e2k\u00eer",
        "\u2018Aqrab"
    ],
    "wof:name":"`Aqrab",
    "wof:placetype":"locality"
},
  "geometry": {"coordinates":[36.45718,34.9368],"type":"Point"}
}