{
  "type": "Feature",
  "properties": {
    "gn:admin1_code":"12.0",
    "gn:asciiname":"Ma`arrat Matir",
    "gn:country_code":"SY",
    "gn:dem":520,
    "gn:feature_class":"P",
    "gn:feature_code":"PPL",
    "gn:name":"Ma\u2018arrat M\u0101tir",
    "gn:population":0,
    "gn:timezone":"Asia/Damascus",
    "iso:country":"SY",
    "name:ara_x_preferred":[
        "\u0645\u0639\u0631\u0629 \u0645\u0627\u062a\u0631"
    ],
    "name:und_x_variant":[
        "Ma\u2018arrat M\u0101tir"
    ],
    "wof:name":"Ma`arrat Matir",
    "wof:placetype":"locality"
},
  "geometry": {"coordinates":[36.55313,35.56962],"type":"Point"}
}