{
  "type": "Feature",
  "properties": {
    "gn:admin1_code":"1.0",
    "gn:asciiname":"Khirbat ash Shawk",
    "gn:country_code":"SY",
    "gn:dem":292,
    "gn:feature_class":"P",
    "gn:feature_code":"PPL",
    "gn:name":"Khirbat ash Shawk",
    "gn:population":0,
    "gn:timezone":"Asia/Damascus",
    "iso:country":"SY",
    "name:ara_x_preferred":[
        "\u062e\u0631\u0628\u0629 \u0627\u0644\u0634\u0648\u0643"
    ],
    "wof:name":"Khirbat ash Shawk",
    "wof:placetype":"locality"
},
  "geometry": {"coordinates":[40.63279,36.15094000000001],"type":"Point"}
}