{
  "type": "Feature",
  "properties": {
    "gn:admin1_code":"11.0",
    "gn:asciiname":"Sadad",
    "gn:country_code":"SY",
    "gn:dem":919,
    "gn:feature_class":"P",
    "gn:feature_code":"PPLA3",
    "gn:name":"\u015eadad",
    "gn:population":0,
    "gn:timezone":"Asia/Damascus",
    "iso:country":"SY",
    "name:ara_x_preferred":[
        "\u0635\u062f\u062f"
    ],
    "name:arc_x_preferred":[
        "\u0728\u0715\u0715"
    ],
    "name:ceb_x_preferred":[
        "\u015eadad"
    ],
    "name:fas_x_preferred":[
        "\u0635\u062f\u062f"
    ],
    "name:fra_x_preferred":[
        "Sadad"
    ],
    "name:kab_x_preferred":[
        "\u1e62adad"
    ],
    "name:mkd_x_preferred":[
        "\u0421\u0430\u0434\u0430\u0434"
    ],
    "name:pol_x_preferred":[
        "Sadad"
    ],
    "name:rus_x_preferred":[
        "\u0421\u0430\u0434\u0430\u0434"
    ],
    "name:spa_x_preferred":[
        "Sadad"
    ],
    "name:urd_x_preferred":[
        "\u0633\u062f\u0627\u062f"
    ],
    "name:vie_x_preferred":[
        "Sadad"
    ],
    "wof:name":"Sadad",
    "wof:placetype":"locality"
},
  "geometry": {"coordinates":[36.92562,34.31248],"type":"Point"}
}