{
  "type": "Feature",
  "properties": {
    "gn:admin1_code":"11.0",
    "gn:asciiname":"Sadad",
    "gn:country_code":"SY",
    "gn:dem":919,
    "gn:feature_class":"P",
    "gn:feature_code":"PPLA3",
    "gn:name":"\u015eadad",
    "gn:population":0,
    "gn:timezone":"Asia/Damascus",
    "iso:country":"SY",
    "name:ara_x_preferred":[
        "\u0635\u062f\u062f"
    ],
    "name:und_x_variant":[
        "\u015eadad"
    ],
    "wof:name":"Sadad",
    "wof:placetype":"locality"
},
  "geometry": {"coordinates":[36.92562,34.31248],"type":"Point"}
}