{
  "type": "Feature",
  "properties": {
    "gn:admin1_code":"9.0",
    "gn:asciiname":"Kafr Shil",
    "gn:country_code":"SY",
    "gn:dem":312,
    "gn:feature_class":"P",
    "gn:feature_code":"PPL",
    "gn:name":"Kafr Sh\u012bl",
    "gn:population":0,
    "gn:timezone":"Asia/Damascus",
    "iso:country":"SY",
    "name:ara_x_preferred":[
        "\u0643\u0641\u0631 \u0634\u064a\u0644"
    ],
    "name:und_x_variant":[
        "Kafer Ch\u00eel",
        "Kafr Sh\u012bl"
    ],
    "wof:name":"Kafr Shil",
    "wof:placetype":"locality"
},
  "geometry": {"coordinates":[36.83223,36.51019],"type":"Point"}
}