{
  "type": "Feature",
  "properties": {
    "gn:admin1_code":"1.0",
    "gn:asciiname":"Tall Ahmad",
    "gn:country_code":"SY",
    "gn:dem":339,
    "gn:feature_class":"P",
    "gn:feature_code":"PPL",
    "gn:name":"Tall A\u1e29mad",
    "gn:population":0,
    "gn:timezone":"Asia/Damascus",
    "iso:country":"SY",
    "name:ara_x_preferred":[
        "\u062a\u0644 \u0623\u062d\u0645\u062f"
    ],
    "name:und_x_variant":[
        "Tell Ahmed",
        "Tall A\u1e29mad"
    ],
    "wof:name":"Tall Ahmad",
    "wof:placetype":"locality"
},
  "geometry": {"coordinates":[41.29946,36.71933],"type":"Point"}
}