{
  "type": "Feature",
  "properties": {
    "gn:admin1_code":"6.0",
    "gn:asciiname":"Ad Dusah",
    "gn:country_code":"SY",
    "gn:dem":663,
    "gn:feature_class":"P",
    "gn:feature_code":"PPL",
    "gn:name":"Ad D\u016bsah",
    "gn:population":0,
    "gn:timezone":"Asia/Damascus",
    "iso:country":"SY",
    "name:ara_x_preferred":[
        "\u0627\u0644\u062f\u0648\u0633\u0629"
    ],
    "name:und_x_variant":[
        "Ad D\u016bsah"
    ],
    "wof:name":"Ad Dusah",
    "wof:placetype":"locality"
},
  "geometry": {"coordinates":[36.44238,33.07576],"type":"Point"}
}