{
  "type": "Feature",
  "properties": {
    "gn:admin1_code":"9.0",
    "gn:asciiname":"Kafr Nasih",
    "gn:country_code":"SY",
    "gn:dem":310,
    "gn:feature_class":"P",
    "gn:feature_code":"PPL",
    "gn:name":"Kafr N\u0101\u015fi\u1e29",
    "gn:population":0,
    "gn:timezone":"Asia/Damascus",
    "iso:country":"SY",
    "name:ara_x_preferred":[
        "\u0643\u0641\u0631 \u0646\u0627\u0635\u062d"
    ],
    "name:und_x_variant":[
        "Kafer N\u00e2sseh",
        "Kafer Nassih",
        "Kafr N\u0101\u015fi\u1e29"
    ],
    "wof:name":"Kafr Nasih",
    "wof:placetype":"locality"
},
  "geometry": {"coordinates":[36.78828,36.1353],"type":"Point"}
}