{
  "type": "Feature",
  "properties": {
    "gn:admin1_code":"9.0",
    "gn:asciiname":"Maryamayn",
    "gn:country_code":"SY",
    "gn:dem":321,
    "gn:feature_class":"P",
    "gn:feature_code":"PPL",
    "gn:name":"Maryamayn",
    "gn:population":0,
    "gn:timezone":"Asia/Damascus",
    "iso:country":"SY",
    "name:ara_x_preferred":[
        "\u0645\u0631\u064a\u0645\u064a\u0646"
    ],
    "name:und_x_variant":[
        "Merimin",
        "Marymayn",
        "Mariamine",
        "Mariama\u00efne",
        "Maryamayn"
    ],
    "wof:name":"Maryamayn",
    "wof:placetype":"locality"
},
  "geometry": {"coordinates":[37.12378,35.98361],"type":"Point"}
}