{
  "type": "Feature",
  "properties": {
    "gn:admin1_code":"9.0",
    "gn:asciiname":"Al Khafiyah",
    "gn:country_code":"SY",
    "gn:dem":373,
    "gn:feature_class":"P",
    "gn:feature_code":"PPL",
    "gn:name":"Al Kh\u0101f\u012byah",
    "gn:population":0,
    "gn:timezone":"Asia/Damascus",
    "iso:country":"SY",
    "name:ara_x_preferred":[
        "\u0627\u0644\u062e\u0627\u0641\u064a\u0629"
    ],
    "name:und_x_variant":[
        "Al Kh\u0101f\u012byah"
    ],
    "wof:name":"Al Khafiyah",
    "wof:placetype":"locality"
},
  "geometry": {"coordinates":[37.78663,35.64194000000001],"type":"Point"}
}