{
  "type": "Feature",
  "properties": {
    "gn:admin1_code":"8.0",
    "gn:asciiname":"At Tuwal",
    "gn:country_code":"SY",
    "gn:dem":709,
    "gn:feature_class":"P",
    "gn:feature_code":"PPLL",
    "gn:name":"A\u0163 \u0162uw\u0101l",
    "gn:population":0,
    "gn:timezone":"Asia/Damascus",
    "iso:country":"SY",
    "name:ara_x_preferred":[
        "A\u0163 \u0162uw\u0101l"
    ],
    "name:ara_x_variant":[
        "\u0627\u0644\u0637\u0648\u0627\u0644",
        "\u0645\u062d\u0627\u0641\u0638\u0629 \u0627\u0644\u0637\u0648\u0627\u0644"
    ],
    "name:fas_x_preferred":[
        "\u0627\u0644\u0637\u0648\u0627\u0644"
    ],
    "name:nno_x_preferred":[
        "At Tuwal"
    ],
    "wof:name":"At Tuwal",
    "wof:placetype":"locality"
},
  "geometry": {"coordinates":[36.22278,33.41537],"type":"Point"}
}