{
  "type": "Feature",
  "properties": {
    "gn:admin1_code":"9.0",
    "gn:asciiname":"Jafirah",
    "gn:country_code":"SY",
    "gn:dem":336,
    "gn:feature_class":"P",
    "gn:feature_code":"PPL",
    "gn:name":"Jaf\u012brah",
    "gn:population":0,
    "gn:timezone":"Asia/Damascus",
    "iso:country":"SY",
    "name:ara_x_preferred":[
        "\u062c\u0641\u064a\u0631\u0629"
    ],
    "name:und_x_variant":[
        "Ej Djoufe\u00efr\u00e9",
        "Jaf\u00eeret el Rhaz\u00e2l",
        "Jafir\u00e9t",
        "Jaf\u012brah"
    ],
    "wof:name":"Jafirah",
    "wof:placetype":"locality"
},
  "geometry": {"coordinates":[37.78022,36.11306],"type":"Point"}
}