{
  "type": "Feature",
  "properties": {
    "gn:admin1_code":"8.0",
    "gn:asciiname":"Ghurayfah",
    "gn:country_code":"SY",
    "gn:dem":614,
    "gn:feature_class":"P",
    "gn:feature_code":"PPL",
    "gn:name":"Ghurayfah",
    "gn:population":0,
    "gn:timezone":"Asia/Damascus",
    "iso:country":"SY",
    "name:ara_x_preferred":[
        "\u063a\u0631\u064a\u0641\u0629"
    ],
    "name:und_x_variant":[
        "Rhoura\u00eff\u00e9",
        "Ghurayfah"
    ],
    "wof:name":"Ghurayfah",
    "wof:placetype":"locality"
},
  "geometry": {"coordinates":[36.5479,33.50627],"type":"Point"}
}