{
  "type": "Feature",
  "properties": {
    "gn:admin1_code":"10.0",
    "gn:asciiname":"Jubb al `Uthman",
    "gn:country_code":"SY",
    "gn:dem":297,
    "gn:feature_class":"P",
    "gn:feature_code":"PPL",
    "gn:name":"Jubb al \u2018Uthm\u0101n",
    "gn:population":0,
    "gn:timezone":"Asia/Damascus",
    "iso:country":"SY",
    "name:ara_x_preferred":[
        "Jubb \u2018Uthm\u0101n"
    ],
    "name:ara_x_variant":[
        "\u062c\u0628 \u0627\u0644\u0639\u062b\u0645\u0627\u0646"
    ],
    "name:und_x_variant":[
        "Joubb Osm\u00e2ne",
        "Jubb al \u2018Uthm\u0101n"
    ],
    "wof:name":"Jubb al `Uthman",
    "wof:placetype":"locality"
},
  "geometry": {"coordinates":[37.23477000000001,35.50623],"type":"Point"}
}