{
  "type": "Feature",
  "properties": {
    "gn:admin1_code":"2.0",
    "gn:asciiname":"Baldir",
    "gn:country_code":"SY",
    "gn:dem":423,
    "gn:feature_class":"P",
    "gn:feature_code":"PPL",
    "gn:name":"Baldir",
    "gn:population":0,
    "gn:timezone":"Asia/Damascus",
    "iso:country":"SY",
    "name:ara_x_preferred":[
        "\u0628\u0644\u062f\u0631"
    ],
    "name:und_x_variant":[
        "Be\u00eft Baldeur",
        "Bayt B\u0101ld\u012br",
        "Baldir"
    ],
    "wof:name":"Baldir",
    "wof:placetype":"locality"
},
  "geometry": {"coordinates":[35.99310999999999,35.795],"type":"Point"}
}