{
  "type": "Feature",
  "properties": {
    "gn:admin1_code":"4.0",
    "gn:asciiname":"Ilalah",
    "gn:country_code":"SY",
    "gn:dem":345,
    "gn:feature_class":"P",
    "gn:feature_code":"PPL",
    "gn:name":"Ilalah",
    "gn:population":0,
    "gn:timezone":"Asia/Damascus",
    "iso:country":"SY",
    "name:ara_x_preferred":[
        "\u0627\u0644\u0644\u0629"
    ],
    "name:und_x_variant":[
        "Ill\u00e9",
        "Illah",
        "Ilalah"
    ],
    "wof:name":"Ilalah",
    "wof:placetype":"locality"
},
  "geometry": {"coordinates":[38.85524,36.61065],"type":"Point"}
}