{
  "type": "Feature",
  "properties": {
    "gn:admin1_code":"10.0",
    "gn:asciiname":"Fayruzah",
    "gn:country_code":"SY",
    "gn:dem":514,
    "gn:feature_class":"P",
    "gn:feature_code":"PPL",
    "gn:name":"Fayr\u016bzah",
    "gn:population":0,
    "gn:timezone":"Asia/Damascus",
    "iso:country":"SY",
    "name:ara_x_preferred":[
        "\u0641\u064a\u0631\u0648\u0632\u0629"
    ],
    "name:und_x_variant":[
        "Fayr\u016bzah"
    ],
    "wof:name":"Fayruzah",
    "wof:placetype":"locality"
},
  "geometry": {"coordinates":[37.12564,34.96405],"type":"Point"}
}