{
  "type": "Feature",
  "properties": {
    "gn:admin1_code":"10.0",
    "gn:asciiname":"Dayr Huwayt",
    "gn:country_code":"SY",
    "gn:dem":436,
    "gn:feature_class":"P",
    "gn:feature_code":"PPL",
    "gn:name":"Dayr \u1e28uwayt",
    "gn:population":0,
    "gn:timezone":"Asia/Damascus",
    "iso:country":"SY",
    "name:ara_x_preferred":[
        "\u062f\u064a\u0631 \u062d\u0648\u064a\u062a"
    ],
    "name:ara_x_variant":[
        "\u062d\u0648\u064a\u062a"
    ],
    "name:und_x_variant":[
        "Houe\u00efte",
        "\u1e28uway\u0163ah",
        "Dayr \u1e28uwayt",
        "\u1e28uwayt"
    ],
    "wof:name":"Dayr Huwayt",
    "wof:placetype":"locality"
},
  "geometry": {"coordinates":[36.44534,34.99414],"type":"Point"}
}