{
  "type": "Feature",
  "properties": {
    "gn:admin1_code":"10.0",
    "gn:asciiname":"Zawr al Jirabiyat",
    "gn:country_code":"SY",
    "gn:dem":254,
    "gn:feature_class":"P",
    "gn:feature_code":"PPL",
    "gn:name":"Zawr al Jir\u0101b\u012by\u0101t",
    "gn:population":0,
    "gn:timezone":"Asia/Damascus",
    "iso:country":"SY",
    "name:ara_x_preferred":[
        "Al Jir\u0101b\u012by\u0101t"
    ],
    "name:ara_x_variant":[
        "\u0632\u0648\u0631 \u0627\u0644\u062c\u0631\u0627\u0628\u064a\u0627\u062a"
    ],
    "name:und_x_variant":[
        "El Jirabyat",
        "Ej Jr\u00e2biy\u00e2te",
        "Zawr al Jir\u0101b\u012by\u0101t"
    ],
    "wof:name":"Zawr al Jirabiyat",
    "wof:placetype":"locality"
},
  "geometry": {"coordinates":[36.68193,35.19345],"type":"Point"}
}