{
  "type": "Feature",
  "properties": {
    "gn:admin1_code":"6.0",
    "gn:asciiname":"Da`il",
    "gn:country_code":"SY",
    "gn:dem":525,
    "gn:feature_class":"P",
    "gn:feature_code":"PPLA3",
    "gn:name":"D\u0101\u2018il",
    "gn:population":0,
    "gn:timezone":"Asia/Damascus",
    "iso:country":"SY",
    "name:ara_x_preferred":[
        "D\u0101\u2018il"
    ],
    "name:ara_x_variant":[
        "\u062f\u0627\u0639\u0644"
    ],
    "name:rus_x_preferred":[
        "\u0414\u0430\u0438\u043b\u044c"
    ],
    "name:und_x_variant":[
        "D\u00e2ail",
        "Da\u00e9l",
        "Daal"
    ],
    "wof:name":"Da`il",
    "wof:placetype":"locality"
},
  "geometry": {"coordinates":[36.12958,32.75466],"type":"Point"}
}