{
  "type": "Feature",
  "properties": {
    "gn:admin1_code":"14.0",
    "gn:asciiname":"Busaysah",
    "gn:country_code":"SY",
    "gn:dem":19,
    "gn:feature_class":"P",
    "gn:feature_code":"PPL",
    "gn:name":"Bu\u015fay\u015fah",
    "gn:population":0,
    "gn:timezone":"Asia/Damascus",
    "iso:country":"SY",
    "name:ara_x_preferred":[
        "\u0628\u0635\u064a\u0635\u0629"
    ],
    "name:und_x_variant":[
        "Bsa\u012bssa",
        "Al Bu\u015fay\u015fah",
        "Bu\u015fay\u015fah"
    ],
    "wof:name":"Busaysah",
    "wof:placetype":"locality"
},
  "geometry": {"coordinates":[36.02556,34.66390999999999],"type":"Point"}
}