{
  "type": "Feature",
  "properties": {
    "gn:admin1_code":"1.0",
    "gn:asciiname":"Diwar",
    "gn:country_code":"SY",
    "gn:dem":451,
    "gn:feature_class":"P",
    "gn:feature_code":"PPL",
    "gn:name":"D\u012bw\u0101r",
    "gn:population":0,
    "gn:timezone":"Asia/Damascus",
    "iso:country":"SY",
    "name:ara_x_preferred":[
        "D\u012bw\u0101r"
    ],
    "name:ara_x_variant":[
        "\u062f\u064a\u0648\u0627\u0631",
        "\u0639\u064a\u0646 \u062f\u064a\u0648\u0627\u0631"
    ],
    "name:und_x_variant":[
        "\u2018Ayn D\u012bw\u0101r",
        "Endivar",
        "Andivar",
        "\u2018Ayn Dayw\u0101r",
        "A\u00efn Div\u00e2r"
    ],
    "wof:name":"Diwar",
    "wof:placetype":"locality"
},
  "geometry": {"coordinates":[42.19201,37.28161],"type":"Point"}
}