{
  "type": "Feature",
  "properties": {
    "gn:admin1_code":"9.0",
    "gn:asciiname":"Al `Urubah",
    "gn:country_code":"SY",
    "gn:dem":510,
    "gn:feature_class":"P",
    "gn:feature_code":"PPL",
    "gn:name":"Al \u2018Ur\u016bbah",
    "gn:population":0,
    "gn:timezone":"Asia/Damascus",
    "iso:country":"SY",
    "name:ara_x_preferred":[
        "\u0639\u0631\u0628 \u0648\u064a\u0631\u0627\u0646"
    ],
    "name:ara_x_variant":[
        "\u0627\u0644\u0639\u0631\u0648\u0628\u0629"
    ],
    "name:und_x_variant":[
        "Kab Virane",
        "Aarab Vir\u00e2ne",
        "\u2018Arab W\u012br\u0101n",
        "Al \u2018Ur\u016bbah",
        "\u2018Arab Wayr\u0101n"
    ],
    "wof:name":"Al `Urubah",
    "wof:placetype":"locality"
},
  "geometry": {"coordinates":[37.58125,36.51962],"type":"Point"}
}