{
  "type": "Feature",
  "properties": {
    "gn:admin1_code":"9.0",
    "gn:asciiname":"Hamidiyat ash Shadad",
    "gn:country_code":"SY",
    "gn:dem":264,
    "gn:feature_class":"P",
    "gn:feature_code":"PPL",
    "gn:name":"\u1e28am\u012bd\u012byat ash Shad\u0101d",
    "gn:population":0,
    "gn:timezone":"Asia/Damascus",
    "iso:country":"SY",
    "name:ara_x_preferred":[
        "\u062d\u0645\u064a\u062f\u064a\u0629 \u0627\u0644\u0634\u062f\u0627\u062f"
    ],
    "name:und_x_variant":[
        "Ham\u00eed\u00eey\u00e9",
        "\u1e28am\u012bd\u012byah",
        "\u1e28am\u012bd\u012byat ash Shad\u0101d"
    ],
    "wof:name":"Hamidiyat ash Shadad",
    "wof:placetype":"locality"
},
  "geometry": {"coordinates":[37.14733,35.7275],"type":"Point"}
}