{
  "type": "Feature",
  "properties": {
    "gn:admin1_code":"11.0",
    "gn:asciiname":"Muntar al Abl",
    "gn:country_code":"SY",
    "gn:dem":723,
    "gn:feature_class":"P",
    "gn:feature_code":"PPL",
    "gn:name":"Mun\u0163\u0101r al Abl",
    "gn:population":0,
    "gn:timezone":"Asia/Damascus",
    "iso:country":"SY",
    "name:ara_x_preferred":[
        "\u0645\u0646\u0637\u0627\u0631 \u0627\u0644\u0623\u0628\u0644"
    ],
    "name:und_x_variant":[
        "Mount\u00e2r el Aabel",
        "Mun\u0163\u0101r al \u2018Abl",
        "Mun\u0163\u0101r al Abl"
    ],
    "wof:name":"Muntar al Abl",
    "wof:placetype":"locality"
},
  "geometry": {"coordinates":[37.24948,34.84594],"type":"Point"}
}