{
  "type": "Feature",
  "properties": {
    "gn:admin1_code":"1.0",
    "gn:asciiname":"Khirbat `Adhban",
    "gn:country_code":"SY",
    "gn:dem":497,
    "gn:feature_class":"P",
    "gn:feature_code":"PPL",
    "gn:name":"Khirbat \u2018Adhb\u0101n",
    "gn:population":0,
    "gn:timezone":"Asia/Damascus",
    "iso:country":"SY",
    "name:ara_x_preferred":[
        "\u062e\u0631\u0628\u0629 \u0639\u0630\u0628\u0627\u0646"
    ],
    "name:kur_x_preferred":[
        "\u06af\u0631\u06ce \u0643\u06d5\u0631\u0627"
    ],
    "name:und_x_variant":[
        "Guiri Kar\u00e2ne",
        "Kirigera",
        "K\u012br\u012b Khar\u0101n",
        "K\u012br\u012b Q\u0101r\u0101n",
        "Khirbat \u2018Adn\u0101n",
        "Khirbat \u2018Adhb\u0101n",
        "Gir\u00ea Kera",
        "\u0643\u0631\u064a \u0643\u0631\u0627"
    ],
    "wof:name":"Khirbat `Adhban",
    "wof:placetype":"locality"
},
  "geometry": {"coordinates":[42.15473,37.15651],"type":"Point"}
}