{
  "type": "Feature",
  "properties": {
    "gn:admin1_code":"2.0",
    "gn:asciiname":"Ar Ruwas",
    "gn:country_code":"SY",
    "gn:dem":210,
    "gn:feature_class":"P",
    "gn:feature_code":"PPL",
    "gn:name":"Ar Ruw\u0101s",
    "gn:population":0,
    "gn:timezone":"Asia/Damascus",
    "iso:country":"SY",
    "name:ara_x_preferred":[
        "Ar Ruw\u0101s"
    ],
    "name:ara_x_variant":[
        "\u0627\u0644\u0631\u0648\u0627\u0633"
    ],
    "name:und_x_variant":[
        "Rouasse",
        "Rou\u00e2s",
        "Roue\u00efsset Qasm\u00eene",
        "Ru\u2019aysat Qasm\u012bn"
    ],
    "wof:name":"Ar Ruwas",
    "wof:placetype":"locality"
},
  "geometry": {"coordinates":[35.88160999999999,35.63347],"type":"Point"}
}