{
  "type": "Feature",
  "properties": {
    "gn:admin1_code":"2.0",
    "gn:asciiname":"Ard al Khamakhimah",
    "gn:country_code":"SY",
    "gn:dem":39,
    "gn:feature_class":"P",
    "gn:feature_code":"PPLL",
    "gn:name":"Ar\u1e11 al Kham\u0101khimah",
    "gn:population":0,
    "gn:timezone":"Asia/Damascus",
    "iso:country":"SY",
    "name:ara_x_preferred":[
        "\u0627\u0631\u0636 \u0627\u0644\u062e\u0645\u0627\u062e\u0645\u0629"
    ],
    "name:und_x_variant":[
        "Ar\u1e11 al Kham\u0101khimah"
    ],
    "wof:name":"Ard al Khamakhimah",
    "wof:placetype":"locality"
},
  "geometry": {"coordinates":[35.90123,35.46717],"type":"Point"}
}