{
  "type": "Feature",
  "properties": {
    "gn:admin1_code":"2.0",
    "gn:asciiname":"Al Murayjat",
    "gn:country_code":"SY",
    "gn:dem":223,
    "gn:feature_class":"P",
    "gn:feature_code":"PPL",
    "gn:name":"Al Murayj\u0101t",
    "gn:population":0,
    "gn:timezone":"Asia/Damascus",
    "iso:country":"SY",
    "name:ara_x_preferred":[
        "\u0627\u0644\u0645\u0631\u064a\u062c\u0627\u062a"
    ],
    "name:und_x_variant":[
        "Al Murayj\u0101t"
    ],
    "wof:name":"Al Murayjat",
    "wof:placetype":"locality"
},
  "geometry": {"coordinates":[36.00234000000001,35.54492],"type":"Point"}
}