{
  "type": "Feature",
  "properties": {
    "gn:admin1_code":"1.0",
    "gn:asciiname":"`Uwaynik",
    "gn:country_code":"SY",
    "gn:dem":461,
    "gn:feature_class":"P",
    "gn:feature_code":"PPL",
    "gn:name":"\u2018Uwayn\u012bk",
    "gn:population":0,
    "gn:timezone":"Asia/Damascus",
    "iso:country":"SY",
    "name:ara_x_preferred":[
        "\u0639\u0648\u064a\u0646\u064a\u0643"
    ],
    "name:tur_x_preferred":[
        "\u2018Uwaynik"
    ],
    "name:und_x_variant":[
        "Aoue\u00efnik",
        "\u2018Uwayn\u012bk"
    ],
    "wof:name":"`Uwaynik",
    "wof:placetype":"locality"
},
  "geometry": {"coordinates":[40.84433,37.09322],"type":"Point"}
}