{
  "type": "Feature",
  "properties": {
    "gn:admin1_code":"6.0",
    "gn:asciiname":"Ash Shar`ah Jamlan",
    "gn:country_code":"SY",
    "gn:dem":607,
    "gn:feature_class":"P",
    "gn:feature_code":"PPL",
    "gn:name":"Ash Shar\u2018ah Jaml\u0101n",
    "gn:population":0,
    "gn:timezone":"Asia/Damascus",
    "iso:country":"SY",
    "name:ara_x_preferred":[
        "\u0627\u0644\u0634\u0631\u0639\u0629 \u062c\u0645\u0644\u0627\u0646"
    ],
    "name:und_x_variant":[
        "Ash Shar\u2018ah Jaml\u0101n"
    ],
    "wof:name":"Ash Shar`ah Jamlan",
    "wof:placetype":"locality"
},
  "geometry": {"coordinates":[36.52751,33.21768],"type":"Point"}
}