{
  "type": "Feature",
  "properties": {
    "gn:admin1_code":"8.0",
    "gn:asciiname":"Ard al Hamra'",
    "gn:country_code":"SY",
    "gn:dem":633,
    "gn:feature_class":"P",
    "gn:feature_code":"PPLL",
    "gn:name":"Ar\u1e11 al \u1e28amr\u0101\u2019",
    "gn:population":0,
    "gn:timezone":"Asia/Damascus",
    "iso:country":"SY",
    "name:ara_x_preferred":[
        "\u0623\u0631\u0636 \u0627\u0644\u062d\u0645\u0631\u0627\u0621"
    ],
    "name:und_x_variant":[
        "Ar\u1e11 al \u1e28amr\u0101\u2019"
    ],
    "wof:name":"Ard al Hamra'",
    "wof:placetype":"locality"
},
  "geometry": {"coordinates":[36.42184,33.43075],"type":"Point"}
}