{
  "type": "Feature",
  "properties": {
    "gn:admin1_code":"8.0",
    "gn:asciiname":"Hawsh al Quwayl",
    "gn:country_code":"SY",
    "gn:dem":654,
    "gn:feature_class":"P",
    "gn:feature_code":"PPL",
    "gn:name":"\u1e28awsh al Quwayl",
    "gn:population":0,
    "gn:timezone":"Asia/Damascus",
    "iso:country":"SY",
    "name:ara_x_preferred":[
        "\u062d\u0648\u0634 \u0642\u0648\u064a\u0644"
    ],
    "name:ara_x_variant":[
        "\u062d\u0648\u0634 \u0627\u0644\u0642\u0648\u064a\u0644"
    ],
    "name:und_x_variant":[
        "Haouch Goue\u00efl",
        "Haouch Qoua\u00efl",
        "Haouch el Qoua\u00efl",
        "\u1e28awsh al Quwayl",
        "\u1e28awsh Quwayl"
    ],
    "wof:name":"Hawsh al Quwayl",
    "wof:placetype":"locality"
},
  "geometry": {"coordinates":[36.35329,33.42009],"type":"Point"}
}