{
  "type": "Feature",
  "properties": {
    "gn:admin1_code":"6.0",
    "gn:asciiname":"Tibnah",
    "gn:country_code":"SY",
    "gn:dem":596,
    "gn:feature_class":"P",
    "gn:feature_code":"PPL",
    "gn:name":"Tibnah",
    "gn:population":0,
    "gn:timezone":"Asia/Damascus",
    "iso:country":"SY",
    "name:ara_x_preferred":[
        "\u062a\u0628\u0646\u0629"
    ],
    "name:und_x_variant":[
        "Tibni",
        "Tibn\u00e9",
        "Tibnah"
    ],
    "wof:name":"Tibnah",
    "wof:placetype":"locality"
},
  "geometry": {"coordinates":[36.21966,32.99124],"type":"Point"}
}