{
  "type": "Feature",
  "properties": {
    "gn:admin1_code":"2.0",
    "gn:asciiname":"Gharu",
    "gn:country_code":"SY",
    "gn:dem":204,
    "gn:feature_class":"P",
    "gn:feature_code":"PPL",
    "gn:name":"Gh\u0101r\u016b",
    "gn:population":0,
    "gn:timezone":"Asia/Damascus",
    "iso:country":"SY",
    "name:ara_x_preferred":[
        "Gh\u0101r\u016b"
    ],
    "wof:name":"Gharu",
    "wof:placetype":"locality"
},
  "geometry": {"coordinates":[35.9875,35.6875],"type":"Point"}
}