{
  "type": "Feature",
  "properties": {
    "gn:admin1_code":"4.0",
    "gn:asciiname":"Turkiyah",
    "gn:country_code":"SY",
    "gn:dem":303,
    "gn:feature_class":"P",
    "gn:feature_code":"PPL",
    "gn:name":"Turk\u012byah",
    "gn:population":0,
    "gn:timezone":"Asia/Damascus",
    "iso:country":"SY",
    "name:ara_x_preferred":[
        "\u062a\u0631\u0643\u064a\u0629"
    ],
    "name:und_x_variant":[
        "Turk\u012byah",
        "Tarikia"
    ],
    "wof:name":"Turkiyah",
    "wof:placetype":"locality"
},
  "geometry": {"coordinates":[38.67461,35.93935],"type":"Point"}
}