{
  "type": "Feature",
  "properties": {
    "gn:admin1_code":"8.0",
    "gn:asciiname":"Al Hamah",
    "gn:country_code":"SY",
    "gn:dem":790,
    "gn:feature_class":"P",
    "gn:feature_code":"PPL",
    "gn:name":"Al H\u0101mah",
    "gn:population":0,
    "gn:timezone":"Asia/Damascus",
    "iso:country":"SY",
    "name:ara_x_preferred":[
        "\u0627\u0644\u0647\u0627\u0645\u0629"
    ],
    "name:und_x_variant":[
        "Al H\u0101mah"
    ],
    "wof:name":"Al Hamah",
    "wof:placetype":"locality"
},
  "geometry": {"coordinates":[36.2206,33.5607],"type":"Point"}
}