{
  "type": "Feature",
  "properties": {
    "gn:admin1_code":"12.0",
    "gn:asciiname":"Umm Nir",
    "gn:country_code":"SY",
    "gn:dem":604,
    "gn:feature_class":"P",
    "gn:feature_code":"PPL",
    "gn:name":"Umm N\u012br",
    "gn:population":0,
    "gn:timezone":"Asia/Damascus",
    "iso:country":"SY",
    "name:ara_x_preferred":[
        "\u0623\u0645 \u0646\u064a\u0631"
    ],
    "name:fas_x_preferred":[
        "\u0627\u0645 \u0646\u06cc\u0631"
    ],
    "name:pol_x_preferred":[
        "Umm Nir"
    ],
    "name:und_x_variant":[
        "Umm N\u012br"
    ],
    "name:vie_x_preferred":[
        "Umm Nir"
    ],
    "wof:name":"Umm Nir",
    "wof:placetype":"locality"
},
  "geometry": {"coordinates":[36.43346,35.53502],"type":"Point"}
}