{
  "type": "Feature",
  "properties": {
    "gn:admin1_code":"9.0",
    "gn:asciiname":"Zahir al Ward",
    "gn:country_code":"SY",
    "gn:dem":528,
    "gn:feature_class":"P",
    "gn:feature_code":"PPL",
    "gn:name":"Zah\u012br al Ward",
    "gn:population":0,
    "gn:timezone":"Asia/Damascus",
    "iso:country":"SY",
    "name:ara_x_preferred":[
        "\u0632\u0647\u064a\u0631 \u0627\u0644\u0648\u0631\u062f"
    ],
    "name:und_x_variant":[
        "Zah\u012br al Ward"
    ],
    "wof:name":"Zahir al Ward",
    "wof:placetype":"locality"
},
  "geometry": {"coordinates":[37.27437000000001,35.98422],"type":"Point"}
}