{
  "type": "Feature",
  "properties": {
    "gn:admin1_code":"9.0",
    "gn:asciiname":"Bi'r Bakar",
    "gn:country_code":"SY",
    "gn:dem":408,
    "gn:feature_class":"P",
    "gn:feature_code":"PPL",
    "gn:name":"Bi\u2019r Bak\u0101r",
    "gn:population":0,
    "gn:timezone":"Asia/Damascus",
    "iso:country":"SY",
    "name:ara_x_preferred":[
        "\u0628\u0626\u0631 \u0628\u0643\u0627\u0631"
    ],
    "name:und_x_variant":[
        "B\u00eer el Bak\u00e2r",
        "Bi\u2019r Bak\u00e2r",
        "Bi\u2019r Bak\u0101r"
    ],
    "wof:name":"Bi'r Bakar",
    "wof:placetype":"locality"
},
  "geometry": {"coordinates":[38.3203,36.41246],"type":"Point"}
}