{
  "type": "Feature",
  "properties": {
    "gn:admin1_code":"2.0",
    "gn:asciiname":"Kharab Shurayqi",
    "gn:country_code":"SY",
    "gn:dem":199,
    "gn:feature_class":"P",
    "gn:feature_code":"PPL",
    "gn:name":"Khar\u0101b Shurayq\u012b",
    "gn:population":0,
    "gn:timezone":"Asia/Damascus",
    "iso:country":"SY",
    "name:und_x_variant":[
        "Khar\u00e2b Chra\u00efqi",
        "Khar\u0101b Shurayq\u012b"
    ],
    "wof:name":"Kharab Shurayqi",
    "wof:placetype":"locality"
},
  "geometry": {"coordinates":[36.00723,35.59156],"type":"Point"}
}