{
  "type": "Feature",
  "properties": {
    "gn:admin1_code":"14.0",
    "gn:asciiname":"Basirah",
    "gn:country_code":"SY",
    "gn:dem":6,
    "gn:feature_class":"P",
    "gn:feature_code":"PPL",
    "gn:name":"Ba\u015f\u012brah",
    "gn:population":0,
    "gn:timezone":"Asia/Damascus",
    "iso:country":"SY",
    "name:ara_x_preferred":[
        "\u0628\u0635\u064a\u0631\u0629"
    ],
    "name:und_x_variant":[
        "Tell Bs\u00eer\u00e9",
        "Tall Ba\u015f\u012brah",
        "Ba\u015f\u012brah"
    ],
    "wof:name":"Basirah",
    "wof:placetype":"locality"
},
  "geometry": {"coordinates":[35.88251,34.99132],"type":"Point"}
}