{
  "type": "Feature",
  "properties": {
    "gn:admin1_code":"8.0",
    "gn:asciiname":"Nahiyat as Sab` Biyar",
    "gn:country_code":"SY",
    "gn:dem":749,
    "gn:feature_class":"P",
    "gn:feature_code":"PPLA3",
    "gn:name":"N\u0101\u1e29iyat as Sab\u2018 Biy\u0101r",
    "gn:population":0,
    "gn:timezone":"Asia/Damascus",
    "iso:country":"SY",
    "name:ara_x_preferred":[
        "\u0646\u0627\u062d\u064a\u0629 \u0627\u0644\u0633\u0628\u0639 \u0628\u064a\u0627\u0631"
    ],
    "name:und_x_variant":[
        "N\u0101\u1e29iyat as Sab\u2018 Biy\u0101r"
    ],
    "wof:name":"Nahiyat as Sab` Biyar",
    "wof:placetype":"locality"
},
  "geometry": {"coordinates":[38.00818,33.53228],"type":"Point"}
}