{
  "type": "Feature",
  "properties": {
    "gn:admin1_code":"1.0",
    "gn:asciiname":"Khirbat an Na`j",
    "gn:country_code":"SY",
    "gn:dem":363,
    "gn:feature_class":"P",
    "gn:feature_code":"PPL",
    "gn:name":"Khirbat an Na\u2018j",
    "gn:population":0,
    "gn:timezone":"Asia/Damascus",
    "iso:country":"SY",
    "name:ara_x_preferred":[
        "\u062e\u0631\u0628\u0629 \u0627\u0644\u0646\u0639\u062c"
    ],
    "name:tur_x_preferred":[
        "Khirbat an Na\u2018j"
    ],
    "name:und_x_variant":[
        "Kheurbet enn Naaj"
    ],
    "wof:name":"Khirbat an Na`j",
    "wof:placetype":"locality"
},
  "geometry": {"coordinates":[41.47152,36.86912],"type":"Point"}
}