{
  "type": "Feature",
  "properties": {
    "gn:admin1_code":"12.0",
    "gn:asciiname":"Az Zahr",
    "gn:country_code":"SY",
    "gn:dem":440,
    "gn:feature_class":"P",
    "gn:feature_code":"PPL",
    "gn:name":"Az\u0327 Z\u0327ahr",
    "gn:population":0,
    "gn:timezone":"Asia/Damascus",
    "iso:country":"SY",
    "name:und_x_variant":[
        "Az\u0327 Z\u0327ahr"
    ],
    "wof:name":"Az Zahr",
    "wof:placetype":"locality"
},
  "geometry": {"coordinates":[36.44167,35.97083],"type":"Point"}
}