{
  "type": "Feature",
  "properties": {
    "gn:admin1_code":"12.0",
    "gn:asciiname":"Burj an Nimrah",
    "gn:country_code":"SY",
    "gn:dem":360,
    "gn:feature_class":"P",
    "gn:feature_code":"PPL",
    "gn:name":"Burj an Nimrah",
    "gn:population":0,
    "gn:timezone":"Asia/Damascus",
    "iso:country":"SY",
    "name:und_x_variant":[
        "\u0628\u0631\u062c \u0627\u0644\u0646\u0645\u0631\u0629"
    ],
    "wof:name":"Burj an Nimrah",
    "wof:placetype":"locality"
},
  "geometry": {"coordinates":[36.73037,36.15955],"type":"Point"}
}