{
  "type": "Feature",
  "properties": {
    "gn:admin1_code":"9.0",
    "gn:asciiname":"Khirbat Halimiyah",
    "gn:country_code":"SY",
    "gn:dem":526,
    "gn:feature_class":"P",
    "gn:feature_code":"PPL",
    "gn:name":"Khirbat \u1e28al\u012bm\u012byah",
    "gn:population":0,
    "gn:timezone":"Asia/Damascus",
    "iso:country":"SY",
    "name:ara_x_preferred":[
        "\u062e\u0631\u0628\u0629 \u062d\u0644\u064a\u0645\u064a\u0629"
    ],
    "name:und_x_variant":[
        "Khirbat \u1e28al\u012bm\u012byah"
    ],
    "wof:name":"Khirbat Halimiyah",
    "wof:placetype":"locality"
},
  "geometry": {"coordinates":[37.44379,36.47932],"type":"Point"}
}