{
  "type": "Feature",
  "properties": {
    "gn:admin1_code":"11.0",
    "gn:asciiname":"Hawsh Ghariqu",
    "gn:country_code":"SY",
    "gn:dem":488,
    "gn:feature_class":"P",
    "gn:feature_code":"PPL",
    "gn:name":"\u1e28awsh Ghar\u012bq\u016b",
    "gn:population":0,
    "gn:timezone":"Asia/Damascus",
    "iso:country":"SY",
    "name:ara_x_preferred":[
        "\u062d\u0648\u0634 \u063a\u0631\u064a\u0642\u0648"
    ],
    "name:und_x_variant":[
        "\u1e28awsh Ghar\u012bq\u016b"
    ],
    "wof:name":"Hawsh Ghariqu",
    "wof:placetype":"locality"
},
  "geometry": {"coordinates":[36.86921,34.85219],"type":"Point"}
}