{
  "type": "Feature",
  "properties": {
    "gn:admin1_code":"12.0",
    "gn:asciiname":"Bayt Hajj Jum`ah",
    "gn:country_code":"SY",
    "gn:dem":253,
    "gn:feature_class":"P",
    "gn:feature_code":"PPL",
    "gn:name":"Bayt \u1e28\u0101jj Jum\u2018ah",
    "gn:population":0,
    "gn:timezone":"Asia/Damascus",
    "iso:country":"SY",
    "name:ara_x_preferred":[
        "\u0628\u064a\u062a \u062d\u0627\u062c \u062c\u0645\u0639\u0629"
    ],
    "name:und_x_variant":[
        "Bayt \u1e28\u0101jj Jum\u2018ah"
    ],
    "wof:name":"Bayt Hajj Jum`ah",
    "wof:placetype":"locality"
},
  "geometry": {"coordinates":[36.4681,36.00214000000001],"type":"Point"}
}