{
  "type": "Feature",
  "properties": {
    "gn:admin1_code":"8.0",
    "gn:asciiname":"At Tanf",
    "gn:country_code":"SY",
    "gn:dem":711,
    "gn:feature_class":"P",
    "gn:feature_code":"PPL",
    "gn:name":"At Tanf",
    "gn:population":0,
    "gn:timezone":"Asia/Damascus",
    "iso:country":"SY",
    "name:ara_x_preferred":[
        "\u0627\u0644\u062a\u0646\u0641"
    ],
    "wof:name":"At Tanf",
    "wof:placetype":"locality"
},
  "geometry": {"coordinates":[38.65697,33.48834],"type":"Point"}
}