{
  "type": "Feature",
  "properties": {
    "gn:admin1_code":"2.0",
    "gn:asciiname":"Abu Makkah",
    "gn:country_code":"SY",
    "gn:dem":813,
    "gn:feature_class":"P",
    "gn:feature_code":"PPL",
    "gn:name":"Ab\u016b Makkah",
    "gn:population":0,
    "gn:timezone":"Asia/Damascus",
    "iso:country":"SY",
    "name:ara_x_preferred":[
        "\u0623\u0628\u0648 \u0645\u0643\u0629"
    ],
    "name:und_x_variant":[
        "Abou Makk\u00e9",
        "Ab\u016b Makkah"
    ],
    "wof:name":"Abu Makkah",
    "wof:placetype":"locality"
},
  "geometry": {"coordinates":[36.12842,35.64334],"type":"Point"}
}