{
  "type": "Feature",
  "properties": {
    "gn:admin1_code":"9.0",
    "gn:asciiname":"Jiqur",
    "gn:country_code":"SY",
    "gn:dem":587,
    "gn:feature_class":"P",
    "gn:feature_code":"PPL",
    "gn:name":"Jiq\u016br",
    "gn:population":0,
    "gn:timezone":"Asia/Damascus",
    "iso:country":"SY",
    "name:ara_x_preferred":[
        "\u062c\u0642\u0648\u0631"
    ],
    "name:kur_x_preferred":[
        "Ciqur"
    ],
    "name:kur_x_variant":[
        "Chikuryan",
        "\u0686\u0643\u0648\u0631\u06cc\u0627\u0646"
    ],
    "name:und_x_variant":[
        "Jiq\u016br",
        "Jikur"
    ],
    "wof:name":"Jiqur",
    "wof:placetype":"locality"
},
  "geometry": {"coordinates":[38.27723,36.88636],"type":"Point"}
}