{
  "type": "Feature",
  "properties": {
    "gn:admin1_code":"9.0",
    "gn:asciiname":"Bayt Hajj Kanu",
    "gn:country_code":"SY",
    "gn:dem":501,
    "gn:feature_class":"P",
    "gn:feature_code":"PPL",
    "gn:name":"Bayt \u1e28\u0101jj Kan\u016b",
    "gn:population":0,
    "gn:timezone":"Asia/Damascus",
    "iso:country":"SY",
    "name:ara_x_preferred":[
        "\u0628\u064a\u062a \u062d\u0627\u062c \u0643\u0646\u0648"
    ],
    "name:und_x_variant":[
        "Bayt \u1e28\u0101jj Kan\u016b"
    ],
    "wof:name":"Bayt Hajj Kanu",
    "wof:placetype":"locality"
},
  "geometry": {"coordinates":[37.72628,36.71714],"type":"Point"}
}