{
  "type": "Feature",
  "properties": {
    "gn:admin1_code":"1.0",
    "gn:asciiname":"`Ali Agha",
    "gn:country_code":"SY",
    "gn:dem":395,
    "gn:feature_class":"P",
    "gn:feature_code":"PPL",
    "gn:name":"\u2018Al\u012b \u0100gh\u0101",
    "gn:population":0,
    "gn:timezone":"Asia/Damascus",
    "iso:country":"SY",
    "name:ara_x_preferred":[
        "\u2018Al\u012b \u0100gh\u0101"
    ],
    "name:ara_x_variant":[
        "\u0639\u0644\u064a \u0622\u063a\u0627"
    ],
    "name:und_x_variant":[
        "Tall \u2018Al\u012b \u0100gh\u0101",
        "Tell Aali \u00c2rha"
    ],
    "wof:name":"`Ali Agha",
    "wof:placetype":"locality"
},
  "geometry": {"coordinates":[41.89885,36.90373],"type":"Point"}
}