{
  "type": "Feature",
  "properties": {
    "gn:admin1_code":"14.0",
    "gn:asciiname":"Tall Kazal",
    "gn:country_code":"SY",
    "gn:dem":30,
    "gn:feature_class":"P",
    "gn:feature_code":"PPL",
    "gn:name":"Tall Kazal",
    "gn:population":0,
    "gn:timezone":"Asia/Damascus",
    "iso:country":"SY",
    "name:cat_x_preferred":[
        "Sumur"
    ],
    "name:glg_x_preferred":[
        "Sumur"
    ],
    "name:pol_x_preferred":[
        "Sumur"
    ],
    "name:slv_x_preferred":[
        "Tell Kazel"
    ],
    "name:und_x_variant":[
        "Tell Kazel",
        "Tall Kazel",
        "Tall Kazal",
        "\u062a\u0644 \u0643\u0632\u0644"
    ],
    "wof:name":"Tall Kazal",
    "wof:placetype":"locality"
},
  "geometry": {"coordinates":[35.98909000000001,34.7142],"type":"Point"}
}