{
  "type": "Feature",
  "properties": {
    "gn:admin1_code":"11.0",
    "gn:asciiname":"Fatim al `Arnuq",
    "gn:country_code":"SY",
    "gn:dem":705,
    "gn:feature_class":"P",
    "gn:feature_code":"PPL",
    "gn:name":"Fa\u0163\u012bm al \u2018Arn\u016bq",
    "gn:population":0,
    "gn:timezone":"Asia/Damascus",
    "iso:country":"SY",
    "name:ara_x_preferred":[
        "\u0641\u0637\u064a\u0645 \u0627\u0644\u0639\u0631\u0646\u0648\u0642"
    ],
    "name:ara_x_variant":[
        "\u0627\u0644\u062c\u0631\u0628\u0648\u0639\u0629"
    ],
    "name:und_x_variant":[
        "J\u00e9rbo\u00fbaa",
        "Jarb\u016b\u2018",
        "Fa\u0163\u012bm al \u2018Arn\u016bq",
        "Al Jarb\u016b\u2018ah",
        "Jerbo\u00fba\u00efy\u00e9",
        "Ft\u00eem el Aarno\u00fbq",
        "Ft\u00eeme el Aarnouq"
    ],
    "wof:name":"Fatim al `Arnuq",
    "wof:placetype":"locality"
},
  "geometry": {"coordinates":[36.97172,34.64855],"type":"Point"}
}