{
  "type": "Feature",
  "properties": {
    "gn:admin1_code":"8.0",
    "gn:asciiname":"Ard al Ma`radah",
    "gn:country_code":"SY",
    "gn:dem":657,
    "gn:feature_class":"P",
    "gn:feature_code":"PPLL",
    "gn:name":"Ar\u1e11 al Ma\u2018ra\u1e11ah",
    "gn:population":0,
    "gn:timezone":"Asia/Damascus",
    "iso:country":"SY",
    "name:ara_x_preferred":[
        "\u0623\u0631\u0636 \u0627\u0644\u0645\u0639\u0631\u0636\u0629"
    ],
    "name:und_x_variant":[
        "Ar\u1e11 al Ma\u2018ra\u1e11ah"
    ],
    "wof:name":"Ard al Ma`radah",
    "wof:placetype":"locality"
},
  "geometry": {"coordinates":[36.57296,33.65000999999999],"type":"Point"}
}