{
  "type": "Feature",
  "properties": {
    "gn:admin1_code":"8.0",
    "gn:asciiname":"Jad`an al Hamadah",
    "gn:country_code":"SY",
    "gn:dem":603,
    "gn:feature_class":"P",
    "gn:feature_code":"PPL",
    "gn:name":"Jad\u2018\u0101n al \u1e28am\u0101dah",
    "gn:population":0,
    "gn:timezone":"Asia/Damascus",
    "iso:country":"SY",
    "name:ara_x_preferred":[
        "\u062c\u062f\u0639\u0627\u0646 \u0627\u0644\u062d\u0645\u0627\u062f\u0629"
    ],
    "name:und_x_variant":[
        "Jad\u2018\u0101n al \u1e28am\u0101dah"
    ],
    "wof:name":"Jad`an al Hamadah",
    "wof:placetype":"locality"
},
  "geometry": {"coordinates":[36.68366,33.45023],"type":"Point"}
}