{
  "type": "Feature",
  "properties": {
    "gn:admin1_code":"1.0",
    "gn:asciiname":"Al Ya`rubiyah",
    "gn:country_code":"SY",
    "gn:dem":393,
    "gn:feature_class":"P",
    "gn:feature_code":"PPLA3",
    "gn:name":"Al Ya\u2018rub\u012byah",
    "gn:population":0,
    "gn:timezone":"Asia/Damascus",
    "iso:country":"SY",
    "name:ara_x_preferred":[
        "\u0627\u0644\u064a\u0639\u0631\u0628\u064a\u0629"
    ],
    "name:ara_x_variant":[
        "\u062a\u0644 \u0643\u0648\u0686\u0643 \u0627\u0644\u0635\u063a\u064a\u0631",
        "\u062a\u0644 \u0643\u0648\u062c\u0643 \u0635\u063a\u064a\u0631"
    ],
    "name:kur_x_preferred":[
        "Tel Kochek"
    ],
    "name:kur_x_variant":[
        "\u062a\u06d5\u0644 \u0643\u06c6\u0686\u06d5\u0643"
    ],
    "name:und_x_variant":[
        "Al Ya\u2018r\u016bb\u012byah",
        "Al Ya\u2018rub\u012byah",
        "Tell K\u016bshik",
        "Tell Kotchek",
        "Tall K\u016bjik",
        "Tall K\u016bchak",
        "Tall K\u016bchik a\u015f \u015eagh\u012br",
        "Tall K\u016bjik \u015eagh\u012br",
        "Tel Ko\u00e7ek",
        "\u062a\u0644 \u0643\u0648\u0634\u0643"
    ],
    "wof:name":"Al Ya`rubiyah",
    "wof:placetype":"locality"
},
  "geometry": {"coordinates":[42.06206,36.81138],"type":"Point"}
}