{
  "type": "Feature",
  "properties": {
    "gn:admin1_code":"11.0",
    "gn:asciiname":"As Sawram",
    "gn:country_code":"SY",
    "gn:dem":480,
    "gn:feature_class":"P",
    "gn:feature_code":"PPLL",
    "gn:name":"As Sawr\u0101m",
    "gn:population":0,
    "gn:timezone":"Asia/Damascus",
    "iso:country":"SY",
    "name:ara_x_preferred":[
        "\u0627\u0644\u0633\u0648\u0631\u0627\u0645"
    ],
    "name:und_x_variant":[
        "As Sawr\u0101m"
    ],
    "wof:name":"As Sawram",
    "wof:placetype":"locality"
},
  "geometry": {"coordinates":[36.70417,34.74259],"type":"Point"}
}