{
  "type": "Feature",
  "properties": {
    "gn:admin1_code":"1.0",
    "gn:asciiname":"Qaysariyah al Tahtani",
    "gn:country_code":"SY",
    "gn:dem":453,
    "gn:feature_class":"P",
    "gn:feature_code":"PPL",
    "gn:name":"Qay\u015far\u012byah al Ta\u1e29t\u0101n\u012b",
    "gn:population":0,
    "gn:timezone":"Asia/Damascus",
    "iso:country":"SY",
    "name:ara_x_preferred":[
        "\u0642\u064a\u0635\u0631\u064a\u0629 \u0627\u0644\u062a\u062d\u062a\u0627\u0646\u064a"
    ],
    "name:ara_x_variant":[
        "\u0645\u0639\u0645\u0634\u0648\u0631"
    ],
    "name:kur_x_preferred":[
        "Mamash\u00fbr"
    ],
    "name:kur_x_variant":[
        "\u0645\u0627\u0645\u0627\u0634\u0648\u0648\u0631"
    ],
    "name:und_x_variant":[
        "Maamachour",
        "Ma\u2018mash\u016br",
        "Qay\u015far\u012byat al Fawq\u0101n\u012b",
        "Qay\u015far\u012byah al Ta\u1e29t\u0101n\u012b",
        "Mama\u015f\u00fbr",
        "\u0645\u0627\u0645\u0627\u0634\u0648\u0631"
    ],
    "wof:name":"Qaysariyah al Tahtani",
    "wof:placetype":"locality"
},
  "geometry": {"coordinates":[42.18977,37.14722],"type":"Point"}
}