{
  "type": "Feature",
  "properties": {
    "gn:admin1_code":"9.0",
    "gn:asciiname":"Radjun",
    "gn:country_code":"SY",
    "gn:dem":579,
    "gn:feature_class":"P",
    "gn:feature_code":"PPLA3",
    "gn:name":"Radjun",
    "gn:population":0,
    "gn:timezone":"Asia/Damascus",
    "iso:country":"SY",
    "name:ara_x_preferred":[
        "R\u0101j\u016b"
    ],
    "name:ara_x_variant":[
        "\u0631\u0627\u062c\u0648"
    ],
    "name:und_x_variant":[
        "Radjou"
    ],
    "wof:name":"Radjun",
    "wof:placetype":"locality"
},
  "geometry": {"coordinates":[36.66415,36.67598],"type":"Point"}
}