{
  "type": "Feature",
  "properties": {
    "gn:admin1_code":"10.0",
    "gn:asciiname":"Abu Mahla",
    "gn:country_code":"SY",
    "gn:dem":316,
    "gn:feature_class":"P",
    "gn:feature_code":"PPL",
    "gn:name":"Ab\u016b Ma\u1e29l\u0101",
    "gn:population":0,
    "gn:timezone":"Asia/Damascus",
    "iso:country":"SY",
    "name:ara_x_preferred":[
        "\u0623\u0628\u0648 \u0645\u062d\u0644\u0627"
    ],
    "name:und_x_variant":[
        "Ab\u016b Ma\u1e29l\u0101"
    ],
    "wof:name":"Abu Mahla",
    "wof:placetype":"locality"
},
  "geometry": {"coordinates":[37.30814,35.47259000000001],"type":"Point"}
}