{
  "type": "Feature",
  "properties": {
    "gn:admin1_code":"8.0",
    "gn:asciiname":"Bayt Ahmad Fadil",
    "gn:country_code":"SY",
    "gn:dem":808,
    "gn:feature_class":"P",
    "gn:feature_code":"PPL",
    "gn:name":"Bayt A\u1e29mad F\u0101\u1e11il",
    "gn:population":0,
    "gn:timezone":"Asia/Damascus",
    "iso:country":"SY",
    "name:ara_x_preferred":[
        "\u0628\u064a\u062a \u0627\u062d\u0645\u062f \u0641\u0627\u0636\u0644"
    ],
    "name:und_x_variant":[
        "Bayt A\u1e29mad F\u0101\u1e11il"
    ],
    "wof:name":"Bayt Ahmad Fadil",
    "wof:placetype":"locality"
},
  "geometry": {"coordinates":[37.96035,33.84409],"type":"Point"}
}