{
  "type": "Feature",
  "properties": {
    "gn:admin1_code":"4.0",
    "gn:asciiname":"Umm Safa",
    "gn:country_code":"SY",
    "gn:dem":321,
    "gn:feature_class":"P",
    "gn:feature_code":"PPL",
    "gn:name":"Umm \u015eaf\u0101",
    "gn:population":0,
    "gn:timezone":"Asia/Damascus",
    "iso:country":"SY",
    "name:ara_x_preferred":[
        "\u0623\u0645 \u0635\u0641\u0627"
    ],
    "name:und_x_variant":[
        "Oum Safa",
        "Umm \u015eaf\u0101\u2019",
        "Umm \u015eaf\u0101"
    ],
    "wof:name":"Umm Safa",
    "wof:placetype":"locality"
},
  "geometry": {"coordinates":[38.9079,36.35839],"type":"Point"}
}