{
  "type": "Feature",
  "properties": {
    "gn:admin1_code":"12.0",
    "gn:asciiname":"Kafr Battikh",
    "gn:country_code":"SY",
    "gn:dem":482,
    "gn:feature_class":"P",
    "gn:feature_code":"PPL",
    "gn:name":"Kafr Ba\u0163\u0163\u012bkh",
    "gn:population":0,
    "gn:timezone":"Asia/Damascus",
    "iso:country":"SY",
    "name:ara_x_preferred":[
        "\u0643\u0641\u0631 \u0628\u0637\u064a\u062e"
    ],
    "name:und_x_variant":[
        "Kafer Batt\u00eekh",
        "Kafr Ba\u0163\u0163\u012bkh"
    ],
    "wof:name":"Kafr Battikh",
    "wof:placetype":"locality"
},
  "geometry": {"coordinates":[36.72203,35.78191],"type":"Point"}
}