{
  "type": "Feature",
  "properties": {
    "gn:admin1_code":"8.0",
    "gn:asciiname":"As Sakhrah",
    "gn:country_code":"SY",
    "gn:dem":798,
    "gn:feature_class":"P",
    "gn:feature_code":"PPL",
    "gn:name":"A\u015f \u015eakhrah",
    "gn:population":0,
    "gn:timezone":"Asia/Damascus",
    "iso:country":"SY",
    "name:ara_x_preferred":[
        "\u0627\u0644\u0635\u062e\u0631\u0629"
    ],
    "name:und_x_variant":[
        "A\u015f \u015eakhrah"
    ],
    "wof:name":"As Sakhrah",
    "wof:placetype":"locality"
},
  "geometry": {"coordinates":[36.752,33.8278],"type":"Point"}
}