{
  "type": "Feature",
  "properties": {
    "gn:admin1_code":"9.0",
    "gn:asciiname":"Umm al `Amad",
    "gn:country_code":"SY",
    "gn:dem":395,
    "gn:feature_class":"P",
    "gn:feature_code":"PPL",
    "gn:name":"Umm al \u2018Amad",
    "gn:population":0,
    "gn:timezone":"Asia/Damascus",
    "iso:country":"SY",
    "name:ara_x_preferred":[
        "\u0623\u0645 \u0627\u0644\u0639\u0645\u062f"
    ],
    "name:und_x_variant":[
        "Oum el Aamad",
        "Oum el Ahmed",
        "Oummel Ahmed",
        "Umm al \u2018Amad"
    ],
    "wof:name":"Umm al `Amad",
    "wof:placetype":"locality"
},
  "geometry": {"coordinates":[37.81119,36.23703],"type":"Point"}
}