{
  "type": "Feature",
  "properties": {
    "gn:admin1_code":"4.0",
    "gn:asciiname":"Al Qarah",
    "gn:country_code":"SY",
    "gn:dem":362,
    "gn:feature_class":"P",
    "gn:feature_code":"PPL",
    "gn:name":"Al Qarah",
    "gn:population":0,
    "gn:timezone":"Asia/Damascus",
    "iso:country":"SY",
    "name:ara_x_preferred":[
        "\u0627\u0644\u0642\u0631\u0629"
    ],
    "wof:name":"Al Qarah",
    "wof:placetype":"locality"
},
  "geometry": {"coordinates":[39.4613,36.09858],"type":"Point"}
}