{
  "type": "Feature",
  "properties": {
    "gn:admin1_code":"8.0",
    "gn:asciiname":"Shura",
    "gn:country_code":"SY",
    "gn:dem":876,
    "gn:feature_class":"P",
    "gn:feature_code":"PPL",
    "gn:name":"Sh\u016br\u00e1",
    "gn:population":0,
    "gn:timezone":"Asia/Damascus",
    "iso:country":"SY",
    "name:ara_x_preferred":[
        "Sh\u016br\u00e1"
    ],
    "name:ara_x_variant":[
        "\u0634\u0648\u0631\u0649"
    ],
    "name:deu_x_preferred":[
        "Sch\u016br\u0101"
    ],
    "name:fas_x_preferred":[
        "\u0634\u0648\u0631\u0627"
    ],
    "name:fin_x_preferred":[
        "\u0160uura"
    ],
    "name:fra_x_preferred":[
        "Choura"
    ],
    "name:ita_x_preferred":[
        "Shura"
    ],
    "name:msa_x_preferred":[
        "Syura"
    ],
    "name:nld_x_preferred":[
        "Majlis al-Shura"
    ],
    "name:rus_x_preferred":[
        "\u0428\u0443\u0440\u0430"
    ],
    "name:spa_x_preferred":[
        "Shura"
    ],
    "name:ukr_x_preferred":[
        "\u0428\u0443\u0440\u0430"
    ],
    "name:und_x_variant":[
        "Chaoura",
        "Cho\u00fbra"
    ],
    "wof:name":"Shura",
    "wof:placetype":"locality"
},
  "geometry": {"coordinates":[36.03654,33.26407],"type":"Point"}
}