{
  "type": "Feature",
  "properties": {
    "gn:admin1_code":"8.0",
    "gn:asciiname":"Shura",
    "gn:country_code":"SY",
    "gn:dem":876,
    "gn:feature_class":"P",
    "gn:feature_code":"PPL",
    "gn:name":"Sh\u016br\u00e1",
    "gn:population":0,
    "gn:timezone":"Asia/Damascus",
    "iso:country":"SY",
    "name:ara_x_preferred":[
        "Sh\u016br\u00e1"
    ],
    "name:ara_x_variant":[
        "\u0634\u0648\u0631\u0649"
    ],
    "name:und_x_variant":[
        "Chaoura",
        "Cho\u00fbra"
    ],
    "wof:name":"Shura",
    "wof:placetype":"locality"
},
  "geometry": {"coordinates":[36.03654,33.26407],"type":"Point"}
}