{
  "type": "Feature",
  "properties": {
    "gn:admin1_code":"9.0",
    "gn:asciiname":"Tall Hasil",
    "gn:country_code":"SY",
    "gn:dem":362,
    "gn:feature_class":"P",
    "gn:feature_code":"PPL",
    "gn:name":"Tall \u1e28\u0101\u015fil",
    "gn:population":0,
    "gn:timezone":"Asia/Damascus",
    "iso:country":"SY",
    "name:ara_x_preferred":[
        "\u062a\u0644 \u062d\u0627\u0635\u0644"
    ],
    "name:und_x_variant":[
        "Tell H\u00e2ssel",
        "Tall \u1e28asal",
        "Tall \u1e28\u0101\u015fil"
    ],
    "wof:name":"Tall Hasil",
    "wof:placetype":"locality"
},
  "geometry": {"coordinates":[37.31269,36.13967],"type":"Point"}
}