{
  "type": "Feature",
  "properties": {
    "gn:admin1_code":"9.0",
    "gn:asciiname":"Zabad",
    "gn:country_code":"SY",
    "gn:dem":338,
    "gn:feature_class":"P",
    "gn:feature_code":"PPL",
    "gn:name":"Zabad",
    "gn:population":0,
    "gn:timezone":"Asia/Damascus",
    "iso:country":"SY",
    "name:ara_x_preferred":[
        "\u0632\u0628\u062f"
    ],
    "name:und_x_variant":[
        "Z\u0101bid",
        "Zebed",
        "Zab\u0101d",
        "Zabad"
    ],
    "wof:name":"Zabad",
    "wof:placetype":"locality"
},
  "geometry": {"coordinates":[37.69894,35.82465999999999],"type":"Point"}
}