{
  "type": "Feature",
  "properties": {
    "gn:admin1_code":"7.0",
    "gn:asciiname":"Ma`din `Atiq",
    "gn:country_code":"SY",
    "gn:dem":222,
    "gn:feature_class":"P",
    "gn:feature_code":"PPLL",
    "gn:name":"Ma\u2018din \u2018At\u012bq",
    "gn:population":0,
    "gn:timezone":"Asia/Damascus",
    "iso:country":"SY",
    "name:ara_x_preferred":[
        "\u0645\u0639\u062f\u0646 \u0639\u062a\u064a\u0642"
    ],
    "name:und_x_variant":[
        "Ma\u2018din \u2018At\u012bq"
    ],
    "wof:name":"Ma`din `Atiq",
    "wof:placetype":"locality"
},
  "geometry": {"coordinates":[39.68382,35.75611],"type":"Point"}
}