{
  "type": "Feature",
  "properties": {
    "gn:admin1_code":"9.0",
    "gn:asciiname":"Jaqal Kabir",
    "gn:country_code":"SY",
    "gn:dem":528,
    "gn:feature_class":"P",
    "gn:feature_code":"PPL",
    "gn:name":"Jaq\u0101l Kab\u012br",
    "gn:population":0,
    "gn:timezone":"Asia/Damascus",
    "iso:country":"SY",
    "name:ara_x_preferred":[
        "\u062c\u0642\u0627\u0644 \u0643\u0628\u064a\u0631"
    ],
    "name:und_x_variant":[
        "Tchaqal K\u00e9b\u00eer",
        "Shaqal al Kab\u012br",
        "Jaq\u0101l Kab\u012br"
    ],
    "wof:name":"Jaqal Kabir",
    "wof:placetype":"locality"
},
  "geometry": {"coordinates":[37.76579,36.50833],"type":"Point"}
}