{
  "type": "Feature",
  "properties": {
    "gn:admin1_code":"14.0",
    "gn:asciiname":"Juwayti",
    "gn:country_code":"SY",
    "gn:dem":440,
    "gn:feature_class":"P",
    "gn:feature_code":"PPL",
    "gn:name":"Juwayt\u012b",
    "gn:population":0,
    "gn:timezone":"Asia/Damascus",
    "iso:country":"SY",
    "name:ara_x_preferred":[
        "\u062c\u0648\u064a\u062a\u064a"
    ],
    "name:und_x_variant":[
        "Joua\u00efti",
        "Juwayt\u012b"
    ],
    "wof:name":"Juwayti",
    "wof:placetype":"locality"
},
  "geometry": {"coordinates":[36.07092,35.05452],"type":"Point"}
}