{
  "type": "Feature",
  "properties": {
    "gn:admin1_code":"12.0",
    "gn:asciiname":"Armanaz",
    "gn:country_code":"SY",
    "gn:dem":336,
    "gn:feature_class":"P",
    "gn:feature_code":"PPLA3",
    "gn:name":"Arman\u0101z",
    "gn:population":0,
    "gn:timezone":"Asia/Damascus",
    "iso:country":"SY",
    "name:ara_x_preferred":[
        "\u0623\u0631\u0645\u0646\u0627\u0632"
    ],
    "name:und_x_variant":[
        "Arman\u0101z"
    ],
    "wof:name":"Armanaz",
    "wof:placetype":"locality"
},
  "geometry": {"coordinates":[36.5031,36.08363],"type":"Point"}
}