{
  "type": "Feature",
  "properties": {
    "gn:admin1_code":"10.0",
    "gn:asciiname":"Qastun al Gharbi",
    "gn:country_code":"SY",
    "gn:dem":181,
    "gn:feature_class":"P",
    "gn:feature_code":"PPL",
    "gn:name":"Qas\u0163\u016bn al Gharb\u012b",
    "gn:population":0,
    "gn:timezone":"Asia/Damascus",
    "iso:country":"SY",
    "name:ara_x_preferred":[
        "\u0642\u0633\u0637\u0648\u0646 \u0627\u0644\u063a\u0631\u0628\u064a"
    ],
    "name:ara_x_variant":[
        "\u0642\u0633\u0637\u0648\u0646"
    ],
    "name:fas_x_preferred":[
        "\u0642\u0633\u0637\u0648\u0646"
    ],
    "name:pol_x_preferred":[
        "Kastun"
    ],
    "name:und_x_variant":[
        "Qasto\u00fbn",
        "Qas\u0163\u016bn",
        "Qastoun el Rharbi",
        "Qas\u0163\u016bn al Gharb\u012b"
    ],
    "name:vie_x_preferred":[
        "Qastun"
    ],
    "wof:name":"Qastun al Gharbi",
    "wof:placetype":"locality"
},
  "geometry": {"coordinates":[36.38391,35.68425999999999],"type":"Point"}
}