{
  "type": "Feature",
  "properties": {
    "gn:admin1_code":"14.0",
    "gn:asciiname":"Rawm adh Dhahab",
    "gn:country_code":"SY",
    "gn:dem":46,
    "gn:feature_class":"P",
    "gn:feature_code":"PPL",
    "gn:name":"Rawm adh Dhahab",
    "gn:population":0,
    "gn:timezone":"Asia/Damascus",
    "iso:country":"SY",
    "name:ara_x_preferred":[
        "\u0631\u0648\u0627\u0645 \u0627\u0644\u0630\u0647\u0628"
    ],
    "name:ara_x_variant":[
        "\u0631\u0648\u0645 \u0627\u0644\u0630\u0647\u0628"
    ],
    "name:und_x_variant":[
        "Raww\u0101m adh Dhahab",
        "Rawm adh Dhahab"
    ],
    "wof:name":"Rawm adh Dhahab",
    "wof:placetype":"locality"
},
  "geometry": {"coordinates":[35.91739000000001,34.85284],"type":"Point"}
}