{
  "type": "Feature",
  "properties": {
    "gn:admin1_code":"2.0",
    "gn:asciiname":"Ad Daflah",
    "gn:country_code":"SY",
    "gn:dem":55,
    "gn:feature_class":"P",
    "gn:feature_code":"PPL",
    "gn:name":"Ad Daflah",
    "gn:population":0,
    "gn:timezone":"Asia/Damascus",
    "iso:country":"SY",
    "name:ara_x_preferred":[
        "\u0642\u0631\u0647 \u0637\u0627\u0637"
    ],
    "name:ara_x_variant":[
        "\u0627\u0644\u062f\u0641\u0644\u0629",
        "\u0642\u0631\u0647 \u0637\u0627\u0637\u0627"
    ],
    "name:und_x_variant":[
        "Qara T\u00e2te",
        "Qarah \u0162\u0101\u0163",
        "Ad Daflah",
        "Qarah \u0162\u0101\u0163\u0101",
        "Qorret Tata"
    ],
    "wof:name":"Ad Daflah",
    "wof:placetype":"locality"
},
  "geometry": {"coordinates":[35.86927,35.83438],"type":"Point"}
}