{
  "type": "Feature",
  "properties": {
    "gn:admin1_code":"9.0",
    "gn:asciiname":"Sirrin ash Shamaliyah",
    "gn:country_code":"SY",
    "gn:dem":353,
    "gn:feature_class":"P",
    "gn:feature_code":"PPLA3",
    "gn:name":"\u015eirr\u012bn ash Sham\u0101l\u012byah",
    "gn:population":0,
    "gn:timezone":"Asia/Damascus",
    "iso:country":"SY",
    "name:ara_x_preferred":[
        "\u0635\u0631\u064a\u0646 \u0627\u0644\u0634\u0645\u0627\u0644\u064a\u0629"
    ],
    "name:ara_x_variant":[
        "\u0633\u0631\u064a\u0646 \u0627\u0644\u0634\u0645\u0627\u0644\u064a\u0629",
        "\u0635\u0631\u064a\u0646"
    ],
    "name:cat_x_preferred":[
        "Sarrin"
    ],
    "name:deu_x_preferred":[
        "Sarrin"
    ],
    "name:fas_x_preferred":[
        "\u0635\u0631\u06cc\u0646"
    ],
    "name:fra_x_preferred":[
        "Sarrine"
    ],
    "name:hye_x_preferred":[
        "\u054d\u0561\u057c\u057c\u056b\u0576"
    ],
    "name:nld_x_preferred":[
        "Sarrin"
    ],
    "name:nno_x_preferred":[
        "Sarrin"
    ],
    "name:pol_x_preferred":[
        "Sirrin"
    ],
    "name:rus_x_preferred":[
        "\u0421\u0435\u0440\u0440\u0438\u043d-\u044d\u0448-\u0428\u0438\u043c\u0430\u043b\u0438\u044f"
    ],
    "name:spa_x_preferred":[
        "Sarrin"
    ],
    "name:und_x_variant":[
        "Sirr\u00eene ech Ch\u00e9m\u00e2l\u00eey\u00e9",
        "Sirr\u00eene ech Chim\u00e2liye",
        "Serr\u012bn",
        "\u015eirr\u012bn",
        "Sirr\u00eene",
        "\u015eirr\u012bn ash Sham\u0101l\u012byah",
        "Sirr\u012bn ash Sham\u0101l\u012byah"
    ],
    "name:vie_x_preferred":[
        "Sarrin"
    ],
    "wof:name":"Sirrin ash Shamaliyah",
    "wof:placetype":"locality"
},
  "geometry": {"coordinates":[38.29788,36.58838],"type":"Point"}
}