{
  "type": "Feature",
  "properties": {
    "gn:admin1_code":"9.0",
    "gn:asciiname":"Sirrin ash Shamaliyah",
    "gn:country_code":"SY",
    "gn:dem":353,
    "gn:feature_class":"P",
    "gn:feature_code":"PPLA3",
    "gn:name":"\u015eirr\u012bn ash Sham\u0101l\u012byah",
    "gn:population":0,
    "gn:timezone":"Asia/Damascus",
    "iso:country":"SY",
    "name:ara_x_preferred":[
        "\u0635\u0631\u064a\u0646 \u0627\u0644\u0634\u0645\u0627\u0644\u064a\u0629"
    ],
    "name:ara_x_variant":[
        "\u0633\u0631\u064a\u0646 \u0627\u0644\u0634\u0645\u0627\u0644\u064a\u0629"
    ],
    "name:und_x_variant":[
        "Sirr\u00eene ech Ch\u00e9m\u00e2l\u00eey\u00e9",
        "Sirr\u00eene ech Chim\u00e2liye",
        "Serr\u012bn",
        "\u015eirr\u012bn",
        "Sirr\u00eene",
        "\u015eirr\u012bn ash Sham\u0101l\u012byah",
        "Sirr\u012bn ash Sham\u0101l\u012byah"
    ],
    "wof:name":"Sirrin ash Shamaliyah",
    "wof:placetype":"locality"
},
  "geometry": {"coordinates":[38.29788,36.58838],"type":"Point"}
}