{
  "type": "Feature",
  "properties": {
    "gn:admin1_code":"9.0",
    "gn:asciiname":"Tall Battal ash Shamali",
    "gn:country_code":"SY",
    "gn:dem":492,
    "gn:feature_class":"P",
    "gn:feature_code":"PPL",
    "gn:name":"Tall Ba\u0163\u0163\u0101l ash Sham\u0101l\u012b",
    "gn:population":0,
    "gn:timezone":"Asia/Damascus",
    "iso:country":"SY",
    "name:ara_x_preferred":[
        "\u062a\u0644 \u0628\u0637\u0627\u0644 \u0634\u0645\u0627\u0644\u064a"
    ],
    "name:ara_x_variant":[
        "\u062a\u0644 \u0628\u0637\u0627\u0644 \u0627\u0644\u0634\u0645\u0627\u0644\u064a"
    ],
    "name:und_x_variant":[
        "Tell Battal Ch\u00e9m\u00e2li",
        "Tell Batt\u00e2l Chim\u00e2li",
        "Tall Ba\u0163\u0163\u0101l ash Sham\u0101l\u012b",
        "Tall Ba\u1e6d\u1e6d\u0101l Sham\u0101l\u012b"
    ],
    "wof:name":"Tall Battal ash Shamali",
    "wof:placetype":"locality"
},
  "geometry": {"coordinates":[37.34212,36.64541],"type":"Point"}
}