{
  "type": "Feature",
  "properties": {
    "gn:admin1_code":"2.0",
    "gn:asciiname":"Ruwaysat al Hajal",
    "gn:country_code":"SY",
    "gn:dem":118,
    "gn:feature_class":"P",
    "gn:feature_code":"PPL",
    "gn:name":"Ruwaysat al \u1e28ajal",
    "gn:population":0,
    "gn:timezone":"Asia/Damascus",
    "iso:country":"SY",
    "name:ara_x_preferred":[
        "\u0631\u0648\u064a\u0633\u0629 \u0627\u0644\u062d\u062c\u0644"
    ],
    "name:und_x_variant":[
        "Roua\u00efsset el Hajal",
        "Rouesset el Hajel",
        "Roua\u00efset Hajel",
        "Ru\u2019aysat al \u1e28ajal",
        "Ruwaysat al \u1e28ajal"
    ],
    "wof:name":"Ruwaysat al Hajal",
    "wof:placetype":"locality"
},
  "geometry": {"coordinates":[36.00134,35.34869000000001],"type":"Point"}
}