{
  "type": "Feature",
  "properties": {
    "gn:admin1_code":"12.0",
    "gn:asciiname":"Zahr al Kabir",
    "gn:country_code":"SY",
    "gn:dem":610,
    "gn:feature_class":"P",
    "gn:feature_code":"PPL",
    "gn:name":"Z\u0327ahr al Kab\u012br",
    "gn:population":0,
    "gn:timezone":"Asia/Damascus",
    "iso:country":"SY",
    "name:ara_x_preferred":[
        "\u0638\u0647\u0631 \u0627\u0644\u0643\u0628\u064a\u0631"
    ],
    "name:und_x_variant":[
        "Dahr el K\u00e9b\u00eer",
        "\u1e10ahr al Kab\u012br",
        "Z\u0327ahr al Kab\u012br"
    ],
    "wof:name":"Zahr al Kabir",
    "wof:placetype":"locality"
},
  "geometry": {"coordinates":[36.51636,35.60581],"type":"Point"}
}