{
  "type": "Feature",
  "properties": {
    "gn:admin1_code":"9.0",
    "gn:asciiname":"Hadabat",
    "gn:country_code":"SY",
    "gn:dem":519,
    "gn:feature_class":"P",
    "gn:feature_code":"PPL",
    "gn:name":"Ha\u1e11ab\u0101t",
    "gn:population":0,
    "gn:timezone":"Asia/Damascus",
    "iso:country":"SY",
    "name:ara_x_preferred":[
        "\u0647\u0636\u0628\u0627\u062a"
    ],
    "name:und_x_variant":[
        "Edalett",
        "Adab\u00e2te",
        "Adab\u0101t",
        "Ha\u1e11ab\u0101t"
    ],
    "wof:name":"Hadabat",
    "wof:placetype":"locality"
},
  "geometry": {"coordinates":[37.4906,36.62204000000001],"type":"Point"}
}