{
  "type": "Feature",
  "properties": {
    "gn:admin1_code":"9.0",
    "gn:asciiname":"Kafr Da`il",
    "gn:country_code":"SY",
    "gn:dem":399,
    "gn:feature_class":"P",
    "gn:feature_code":"PPL",
    "gn:name":"Kafr D\u0101\u2018il",
    "gn:population":0,
    "gn:timezone":"Asia/Damascus",
    "iso:country":"SY",
    "name:ara_x_preferred":[
        "\u0643\u0641\u0631 \u062f\u0627\u0639\u0644"
    ],
    "name:und_x_variant":[
        "Kafer D\u00e2a\u00efl",
        "Kafer Dahel",
        "Kafr D\u0101\u2018il"
    ],
    "wof:name":"Kafr Da`il",
    "wof:placetype":"locality"
},
  "geometry": {"coordinates":[37.02075,36.21623],"type":"Point"}
}