{
  "type": "Feature",
  "properties": {
    "gn:admin1_code":"1.0",
    "gn:asciiname":"Chulbarat Tahtani",
    "gn:country_code":"SY",
    "gn:dem":379,
    "gn:feature_class":"P",
    "gn:feature_code":"PPL",
    "gn:name":"Chulb\u0101r\u0101t Ta\u1e29t\u0101n\u012b",
    "gn:population":0,
    "gn:timezone":"Asia/Damascus",
    "iso:country":"SY",
    "name:ara_x_preferred":[
        "\u0686\u0644\u0628\u0627\u0631\u0627\u062a \u062a\u062d\u062a\u0627\u0646\u064a"
    ],
    "name:tur_x_preferred":[
        "Chulp\u0101r\u0101t Ta\u1e29t\u0101n\u012b"
    ],
    "name:und_x_variant":[
        "Sh\u016blbar\u0101t at Ta\u1e29t\u0101n\u012b",
        "Tcholp\u00e2r\u00e2te",
        "Tcholp\u00e2r\u00e2te Taht\u00e2ni",
        "Tch\u00f4par\u00e2te",
        "Chulb\u0101r\u0101t Ta\u1e29t\u0101n\u012b",
        "Tshulb\u0101r\u0101t Ta\u1e29t\u0101n\u012b"
    ],
    "wof:name":"Chulbarat Tahtani",
    "wof:placetype":"locality"
},
  "geometry": {"coordinates":[41.21699,36.86581],"type":"Point"}
}