{
  "type": "Feature",
  "properties": {
    "gn:admin1_code":"9.0",
    "gn:asciiname":"Handarat",
    "gn:country_code":"SY",
    "gn:dem":474,
    "gn:feature_class":"P",
    "gn:feature_code":"PPL",
    "gn:name":"\u1e28andar\u0101t",
    "gn:population":0,
    "gn:timezone":"Asia/Damascus",
    "iso:country":"SY",
    "name:ara_x_preferred":[
        "\u062d\u0646\u062f\u0631\u0627\u062a"
    ],
    "name:und_x_variant":[
        "Hanndr\u00e2te",
        "\u1e28andar\u0101t"
    ],
    "wof:name":"Handarat",
    "wof:placetype":"locality"
},
  "geometry": {"coordinates":[37.16086,36.28888],"type":"Point"}
}