{
  "type": "Feature",
  "properties": {
    "gn:admin1_code":"9.0",
    "gn:asciiname":"Mahfazah",
    "gn:country_code":"SY",
    "gn:dem":545,
    "gn:feature_class":"P",
    "gn:feature_code":"PPL",
    "gn:name":"Ma\u1e29faz\u0327ah",
    "gn:population":0,
    "gn:timezone":"Asia/Damascus",
    "iso:country":"SY",
    "name:ara_x_preferred":[
        "\u0645\u062d\u0641\u0638\u0629"
    ],
    "name:und_x_variant":[
        "Maf\u00e2z\u00e9",
        "Mahf\u00e2z\u00e9",
        "Ma\u1e29f\u0101z\u0327ah",
        "Ma\u1e29faz\u0327ah"
    ],
    "wof:name":"Mahfazah",
    "wof:placetype":"locality"
},
  "geometry": {"coordinates":[38.38737,36.38803],"type":"Point"}
}