{
  "type": "Feature",
  "properties": {
    "gn:admin1_code":"9.0",
    "gn:asciiname":"Duwayr al Hawtah",
    "gn:country_code":"SY",
    "gn:dem":304,
    "gn:feature_class":"P",
    "gn:feature_code":"PPL",
    "gn:name":"Duwayr al \u1e28awtah",
    "gn:population":0,
    "gn:timezone":"Asia/Damascus",
    "iso:country":"SY",
    "name:ara_x_preferred":[
        "\u062f\u0648\u064a\u0631 \u0627\u0644\u062d\u0648\u062a\u0629"
    ],
    "name:und_x_variant":[
        "Duwayr al \u1e28awtah"
    ],
    "wof:name":"Duwayr al Hawtah",
    "wof:placetype":"locality"
},
  "geometry": {"coordinates":[37.20902,35.75101],"type":"Point"}
}