{
  "type": "Feature",
  "properties": {
    "gn:admin1_code":"1.0",
    "gn:asciiname":"Masba`ah",
    "gn:country_code":"SY",
    "gn:dem":280,
    "gn:feature_class":"P",
    "gn:feature_code":"PPL",
    "gn:name":"Ma\u015fba\u2018ah",
    "gn:population":0,
    "gn:timezone":"Asia/Damascus",
    "iso:country":"SY",
    "name:ara_x_preferred":[
        "\u0645\u0635\u0628\u0639\u0629"
    ],
    "name:und_x_variant":[
        "Ma\u1e11ba\u2018ah",
        "Ma\u015fba\u2018ah"
    ],
    "wof:name":"Masba`ah",
    "wof:placetype":"locality"
},
  "geometry": {"coordinates":[40.66747,36.10542],"type":"Point"}
}