{
  "type": "Feature",
  "properties": {
    "gn:admin1_code":"2.0",
    "gn:asciiname":"Al Musaytibah",
    "gn:country_code":"SY",
    "gn:dem":172,
    "gn:feature_class":"P",
    "gn:feature_code":"PPL",
    "gn:name":"Al Mu\u015fay\u0163ibah",
    "gn:population":0,
    "gn:timezone":"Asia/Damascus",
    "iso:country":"SY",
    "name:ara_x_preferred":[
        "\u0627\u0644\u0645\u0635\u064a\u0637\u0628\u0629"
    ],
    "name:und_x_variant":[
        "Al Mu\u015fay\u0163ibah"
    ],
    "wof:name":"Al Musaytibah",
    "wof:placetype":"locality"
},
  "geometry": {"coordinates":[35.99310999999999,35.45596],"type":"Point"}
}