{
  "type": "Feature",
  "properties": {
    "gn:admin1_code":"2.0",
    "gn:asciiname":"Zaytunah",
    "gn:country_code":"SY",
    "gn:dem":255,
    "gn:feature_class":"P",
    "gn:feature_code":"PPL",
    "gn:name":"Zayt\u016bnah",
    "gn:population":0,
    "gn:timezone":"Asia/Damascus",
    "iso:country":"SY",
    "name:ara_x_preferred":[
        "\u0632\u064a\u062a\u0648\u0646\u0629"
    ],
    "name:ara_x_variant":[
        "\u0632\u064a\u062a\u0648\u0646\u062c\u0648\u0643"
    ],
    "name:und_x_variant":[
        "Za\u00efto\u00fbndjiq",
        "Zayt\u016bnjiq",
        "Zayt\u016bnah",
        "Zayt\u016bnj\u016bk",
        "Zaytuneh",
        "Zaytunjek"
    ],
    "wof:name":"Zaytunah",
    "wof:placetype":"locality"
},
  "geometry": {"coordinates":[35.89519,35.78655],"type":"Point"}
}