{
  "type": "Feature",
  "properties": {
    "gn:admin1_code":"9.0",
    "gn:asciiname":"Qentere",
    "gn:country_code":"SY",
    "gn:dem":587,
    "gn:feature_class":"P",
    "gn:feature_code":"PPLA3",
    "gn:name":"Qenter\u00ea",
    "gn:population":0,
    "gn:timezone":"Asia/Damascus",
    "iso:country":"SY",
    "wof:name":"Qentere",
    "wof:placetype":"locality"
},
  "geometry": {"coordinates":[36.72841,36.5635],"type":"Point"}
}