{
  "type": "Feature",
  "properties": {
    "gn:admin1_code":"14.0",
    "gn:asciiname":"Bayt ad Dik",
    "gn:country_code":"SY",
    "gn:dem":157,
    "gn:feature_class":"P",
    "gn:feature_code":"PPL",
    "gn:name":"Bayt ad D\u012bk",
    "gn:population":0,
    "gn:timezone":"Asia/Damascus",
    "iso:country":"SY",
    "name:ara_x_preferred":[
        "\u0628\u064a\u062a \u0627\u0644\u062f\u064a\u0643"
    ],
    "name:und_x_variant":[
        "Be\u00eft ed D\u00eek",
        "Bayt ad D\u012bk"
    ],
    "wof:name":"Bayt ad Dik",
    "wof:placetype":"locality"
},
  "geometry": {"coordinates":[36.01902000000001,34.85633],"type":"Point"}
}