{
  "type": "Feature",
  "properties": {
    "gn:admin1_code":"1.0",
    "gn:asciiname":"Tall Ba`rur",
    "gn:country_code":"SY",
    "gn:dem":378,
    "gn:feature_class":"P",
    "gn:feature_code":"PPL",
    "gn:name":"Tall Ba\u2018r\u016br",
    "gn:population":0,
    "gn:timezone":"Asia/Damascus",
    "iso:country":"SY",
    "name:ara_x_preferred":[
        "\u062a\u0644 \u0628\u0639\u0631\u0648\u0631"
    ],
    "name:tur_x_preferred":[
        "Tall Ba\u2018r\u016br"
    ],
    "name:und_x_variant":[
        "Tell Baaro\u00fbr"
    ],
    "wof:name":"Tall Ba`rur",
    "wof:placetype":"locality"
},
  "geometry": {"coordinates":[41.41895,36.90841],"type":"Point"}
}