{
  "type": "Feature",
  "properties": {
    "gn:admin1_code":"1.0",
    "gn:asciiname":"Qarat al Hajjiyah",
    "gn:country_code":"SY",
    "gn:dem":275,
    "gn:feature_class":"P",
    "gn:feature_code":"PPL",
    "gn:name":"Q\u0101rat al \u1e28ajj\u012byah",
    "gn:population":0,
    "gn:timezone":"Asia/Damascus",
    "iso:country":"SY",
    "name:ara_x_preferred":[
        "\u0642\u0627\u0631\u0629 \u0627\u0644\u062d\u062c\u064a\u0629"
    ],
    "name:und_x_variant":[
        "Q\u0101rrat al \u1e28ajj\u012byah",
        "Q\u0101rat al \u1e28ajj\u012byah"
    ],
    "wof:name":"Qarat al Hajjiyah",
    "wof:placetype":"locality"
},
  "geometry": {"coordinates":[40.70908,36.19902],"type":"Point"}
}