{
  "type": "Feature",
  "properties": {
    "gn:admin1_code":"11.0",
    "gn:asciiname":"Sindiyanah al Gharbiyah",
    "gn:country_code":"SY",
    "gn:dem":385,
    "gn:feature_class":"P",
    "gn:feature_code":"PPL",
    "gn:name":"Sindiy\u0101nah al Gharb\u012byah",
    "gn:population":0,
    "gn:timezone":"Asia/Damascus",
    "iso:country":"SY",
    "name:ara_x_preferred":[
        "\u0633\u0646\u062f\u064a\u0627\u0646\u0629 \u0627\u0644\u063a\u0631\u0628\u064a\u0629"
    ],
    "name:ara_x_variant":[
        "\u0627\u0644\u0633\u0646\u062f\u064a\u0627\u0646\u0629"
    ],
    "name:und_x_variant":[
        "Sinndi\u00e2net el Rharb\u00eey\u00e9",
        "Sindian\u00e9",
        "Sinndiane Gharbiyah",
        "Sindiy\u0101nah al Gharb\u012byah",
        "As Sindiy\u0101nah"
    ],
    "wof:name":"Sindiyanah al Gharbiyah",
    "wof:placetype":"locality"
},
  "geometry": {"coordinates":[36.29001,34.70562],"type":"Point"}
}