{
  "type": "Feature",
  "properties": {
    "gn:admin1_code":"11.0",
    "gn:asciiname":"Al Mazra`ah",
    "gn:country_code":"SY",
    "gn:dem":487,
    "gn:feature_class":"P",
    "gn:feature_code":"PPL",
    "gn:name":"Al Mazra\u2018ah",
    "gn:population":0,
    "gn:timezone":"Asia/Damascus",
    "iso:country":"SY",
    "name:ara_x_preferred":[
        "\u0627\u0644\u0645\u0632\u0631\u0639\u0629"
    ],
    "name:ara_x_variant":[
        "\u0627\u0644\u062d\u0648\u0634"
    ],
    "name:und_x_variant":[
        "Al Mazra\u2018ah",
        "Al \u1e28awsh"
    ],
    "wof:name":"Al Mazra`ah",
    "wof:placetype":"locality"
},
  "geometry": {"coordinates":[36.65622000000001,34.72758],"type":"Point"}
}