{
  "type": "Feature",
  "properties": {
    "gn:admin1_code":"10.0",
    "gn:asciiname":"Rasm Judaydah",
    "gn:country_code":"SY",
    "gn:dem":639,
    "gn:feature_class":"P",
    "gn:feature_code":"PPLL",
    "gn:name":"Rasm Judaydah",
    "gn:population":0,
    "gn:timezone":"Asia/Damascus",
    "iso:country":"SY",
    "name:ara_x_preferred":[
        "\u0631\u0633\u0645 \u062c\u062f\u064a\u062f\u0629"
    ],
    "name:und_x_variant":[
        "Rasm Jad\u012bdah",
        "Rasm Judaydah"
    ],
    "wof:name":"Rasm Judaydah",
    "wof:placetype":"locality"
},
  "geometry": {"coordinates":[37.86176,35.12962],"type":"Point"}
}