{
  "type": "Feature",
  "properties": {
    "gn:admin1_code":"1.0",
    "gn:asciiname":"Birkil Bawz",
    "gn:country_code":"SY",
    "gn:dem":350,
    "gn:feature_class":"P",
    "gn:feature_code":"PPL",
    "gn:name":"Birk\u012bl Bawz",
    "gn:population":0,
    "gn:timezone":"Asia/Damascus",
    "iso:country":"SY",
    "name:ara_x_preferred":[
        "\u0628\u0631\u0643\u064a\u0644 \u0628\u0648\u0632"
    ],
    "name:und_x_variant":[
        "Birk\u012bl Bawz"
    ],
    "wof:name":"Birkil Bawz",
    "wof:placetype":"locality"
},
  "geometry": {"coordinates":[40.70136,36.69518],"type":"Point"}
}