{
  "type": "Feature",
  "properties": {
    "gn:admin1_code":"12.0",
    "gn:asciiname":"Al Muzanbaqa",
    "gn:country_code":"SY",
    "gn:dem":102,
    "gn:feature_class":"P",
    "gn:feature_code":"PPL",
    "gn:name":"Al Muzanbaq\u00e1",
    "gn:population":0,
    "gn:timezone":"Europe/Istanbul",
    "iso:country":"SY",
    "name:ara_x_preferred":[
        "\u0627\u0644\u0645\u0632\u0646\u0628\u0642\u0649"
    ],
    "name:und_x_variant":[
        "Al Muzanbaq\u00e1"
    ],
    "wof:name":"Al Muzanbaqa",
    "wof:placetype":"locality"
},
  "geometry": {"coordinates":[36.3762,36.01016],"type":"Point"}
}