{
  "type": "Feature",
  "properties": {
    "gn:admin1_code":"6.0",
    "gn:asciiname":"Khirbat at Tayr",
    "gn:country_code":"SY",
    "gn:dem":483,
    "gn:feature_class":"P",
    "gn:feature_code":"PPL",
    "gn:name":"Khirbat a\u0163 \u0162ayr",
    "gn:population":0,
    "gn:timezone":"Asia/Damascus",
    "iso:country":"SY",
    "name:ara_x_preferred":[
        "\u062e\u0631\u0628\u0629 \u0627\u0644\u0637\u064a\u0631"
    ],
    "name:und_x_variant":[
        "Khirbat a\u0163 \u0162ayr"
    ],
    "wof:name":"Khirbat at Tayr",
    "wof:placetype":"locality"
},
  "geometry": {"coordinates":[36.0472,32.79073],"type":"Point"}
}