{
  "type": "Feature",
  "properties": {
    "gn:admin1_code":"2.0",
    "gn:asciiname":"Bayt Suhin",
    "gn:country_code":"SY",
    "gn:dem":249,
    "gn:feature_class":"P",
    "gn:feature_code":"PPL",
    "gn:name":"Bayt S\u016bh\u012bn",
    "gn:population":0,
    "gn:timezone":"Asia/Damascus",
    "iso:country":"SY",
    "name:ara_x_preferred":[
        "\u0628\u064a\u062a \u0633\u0648\u0647\u064a\u0646"
    ],
    "name:pol_x_preferred":[
        "Bajt Suhin"
    ],
    "name:und_x_variant":[
        "Be\u00eft So\u00fbhine",
        "Bayt S\u016bh\u012bn"
    ],
    "name:vie_x_preferred":[
        "Bayt Suhin"
    ],
    "wof:name":"Bayt Suhin",
    "wof:placetype":"locality"
},
  "geometry": {"coordinates":[36.01363,35.51469],"type":"Point"}
}