{
  "type": "Feature",
  "properties": {
    "gn:admin1_code":"1.0",
    "gn:asciiname":"Khirbat Jassah",
    "gn:country_code":"SY",
    "gn:dem":342,
    "gn:feature_class":"P",
    "gn:feature_code":"PPL",
    "gn:name":"Khirbat Jassah",
    "gn:population":0,
    "gn:timezone":"Asia/Damascus",
    "iso:country":"SY",
    "name:ara_x_preferred":[
        "\u062e\u0631\u0628\u0629 \u062c\u0633\u0629"
    ],
    "name:und_x_variant":[
        "Khirbat Ji\u015f\u015f\u012b",
        "Kheurbet Jessi S\u00e9rh\u00eer",
        "Kheurbet Jessi",
        "Khirbat Jassah"
    ],
    "wof:name":"Khirbat Jassah",
    "wof:placetype":"locality"
},
  "geometry": {"coordinates":[41.39872,36.71198],"type":"Point"}
}