{
  "type": "Feature",
  "properties": {
    "gn:admin1_code":"1.0",
    "gn:asciiname":"Umm Dibs",
    "gn:country_code":"SY",
    "gn:dem":352,
    "gn:feature_class":"P",
    "gn:feature_code":"PPL",
    "gn:name":"Umm Dibs",
    "gn:population":0,
    "gn:timezone":"Asia/Damascus",
    "iso:country":"SY",
    "name:ara_x_preferred":[
        "\u0623\u0645 \u062f\u0628\u0633"
    ],
    "name:tur_x_preferred":[
        "Umm Dibs"
    ],
    "name:und_x_variant":[
        "Oum Debess"
    ],
    "wof:name":"Umm Dibs",
    "wof:placetype":"locality"
},
  "geometry": {"coordinates":[40.03801,36.76684],"type":"Point"}
}