{
  "type": "Feature",
  "properties": {
    "gn:country":"SY",
    "gn:fcode":"PPL",
    "gn:population":2,
    "iso:country":"SY",
    "name:ara_x_preferred":[
        "\u0645\u064a\u0633\u0631\u0629"
    ],
    "name:ara_x_variant":[
        "\u0645\u0639\u064a\u0635\u0631\u0629"
    ],
    "name:und_x_variant":[
        "Ma\u00efsra"
    ],
    "qs:name":"Maysarah",
    "qs:photos_9r":0,
    "qs:photos_sr":0,
    "qs:pop_sr":"1",
    "wof:name":"Maysarah",
    "wof:placetype":"locality",
    "wof:population":2
},
  "geometry": {"coordinates":[37.74975,36.51578],"type":"Point"}
}