{
  "type": "Feature",
  "properties": {
    "gn:admin1_code":"1.0",
    "gn:asciiname":"Umm Wadi",
    "gn:country_code":"SY",
    "gn:dem":337,
    "gn:feature_class":"P",
    "gn:feature_code":"PPL",
    "gn:name":"Umm W\u0101d\u012b",
    "gn:population":0,
    "gn:timezone":"Asia/Damascus",
    "iso:country":"SY",
    "name:ara_x_preferred":[
        "Umm W\u0101d\u012b"
    ],
    "name:ara_x_variant":[
        "\u0627\u0645 \u0648\u0627\u062f\u064a"
    ],
    "wof:name":"Umm Wadi",
    "wof:placetype":"locality"
},
  "geometry": {"coordinates":[41.06461,36.11691],"type":"Point"}
}