{
  "type": "Feature",
  "properties": {
    "gn:admin1_code":"9.0",
    "gn:asciiname":"Murtafa` Kabir",
    "gn:country_code":"SY",
    "gn:dem":527,
    "gn:feature_class":"P",
    "gn:feature_code":"PPL",
    "gn:name":"Murtafa\u2018 Kab\u012br",
    "gn:population":0,
    "gn:timezone":"Asia/Damascus",
    "iso:country":"SY",
    "name:ara_x_preferred":[
        "\u0627\u0644\u0645\u0631\u062a\u0641\u0639 \u0627\u0644\u0643\u0628\u064a\u0631"
    ],
    "name:ara_x_variant":[
        "\u0645\u0631\u062a\u0641\u0639 \u0643\u0628\u064a\u0631",
        "\u0642\u0631\u0647 \u062c\u064a\u0648\u0643"
    ],
    "name:und_x_variant":[
        "Al Murtafa\u2018 al Kab\u012br",
        "Murtafa\u2018 Kab\u012br",
        "Qarah Juy\u016bk"
    ],
    "wof:name":"Murtafa` Kabir",
    "wof:placetype":"locality"
},
  "geometry": {"coordinates":[37.65781,36.65584000000001],"type":"Point"}
}