{
  "type": "Feature",
  "properties": {
    "gn:admin1_code":"12.0",
    "gn:asciiname":"Al `Adnaniyah",
    "gn:country_code":"SY",
    "gn:dem":354,
    "gn:feature_class":"P",
    "gn:feature_code":"PPL",
    "gn:name":"Al \u2018Adn\u0101n\u012byah",
    "gn:population":0,
    "gn:timezone":"Asia/Damascus",
    "iso:country":"SY",
    "name:ara_x_preferred":[
        "\u0627\u0644\u0639\u062f\u0646\u0627\u0646\u064a\u0629"
    ],
    "name:und_x_variant":[
        "Al \u2018Adn\u0101n\u012byah"
    ],
    "wof:name":"Al `Adnaniyah",
    "wof:placetype":"locality"
},
  "geometry": {"coordinates":[36.31078,35.96566],"type":"Point"}
}