{
  "type": "Feature",
  "properties": {
    "gn:admin1_code":"9.0",
    "gn:asciiname":"Lalat Muhammad",
    "gn:country_code":"SY",
    "gn:dem":351,
    "gn:feature_class":"P",
    "gn:feature_code":"PPL",
    "gn:name":"L\u0101lat Mu\u1e29ammad",
    "gn:population":0,
    "gn:timezone":"Asia/Damascus",
    "iso:country":"SY",
    "name:ara_x_preferred":[
        "\u0644\u0627\u0644\u0629 \u0645\u062d\u0645\u062f"
    ],
    "name:und_x_variant":[
        "Tell Lala",
        "L\u00e2let Mohammed",
        "L\u0101lat Mu\u1e29ammad"
    ],
    "wof:name":"Lalat Muhammad",
    "wof:placetype":"locality"
},
  "geometry": {"coordinates":[37.75772,36.1537],"type":"Point"}
}