{
  "type": "Feature",
  "properties": {
    "gn:admin1_code":"9.0",
    "gn:asciiname":"Blink",
    "gn:country_code":"SY",
    "gn:dem":366,
    "gn:feature_class":"P",
    "gn:feature_code":"PPL",
    "gn:name":"Blink",
    "gn:population":0,
    "gn:timezone":"Asia/Damascus",
    "iso:country":"SY",
    "name:ara_x_preferred":[
        "\u0628\u0644\u0646\u0643"
    ],
    "name:ara_x_variant":[
        "\u0641\u0647\u062f\u064a\u0629"
    ],
    "name:kur_x_preferred":[
        "Bilink"
    ],
    "name:kur_x_variant":[
        "P\u0142ing",
        "B\u0142ing",
        "\u067e\u06b5\u0646\u06af",
        "\u0628\u06b5\u0646\u06af"
    ],
    "name:und_x_variant":[
        "Fahd\u012byah",
        "Fehediye",
        "Piling",
        "Fahd\u012bya"
    ],
    "wof:name":"Blink",
    "wof:placetype":"locality"
},
  "geometry": {"coordinates":[38.14057,36.74483],"type":"Point"}
}