{
  "type": "Feature",
  "properties": {
    "gn:admin1_code":"2.0",
    "gn:asciiname":"Ard at Tuwaynah",
    "gn:country_code":"SY",
    "gn:dem":18,
    "gn:feature_class":"P",
    "gn:feature_code":"PPLL",
    "gn:name":"Ar\u1e11 at Tuwaynah",
    "gn:population":0,
    "gn:timezone":"Asia/Damascus",
    "iso:country":"SY",
    "name:ara_x_preferred":[
        "\u0623\u0631\u0636 \u0627\u0644\u062a\u0648\u064a\u0646\u0629"
    ],
    "name:und_x_variant":[
        "Ar\u1e11 at Tuwaynah"
    ],
    "wof:name":"Ard at Tuwaynah",
    "wof:placetype":"locality"
},
  "geometry": {"coordinates":[35.93498,35.36985],"type":"Point"}
}