{
  "type": "Feature",
  "properties": {
    "gn:admin1_code":"1.0",
    "gn:asciiname":"Dabshiyah",
    "gn:country_code":"SY",
    "gn:dem":391,
    "gn:feature_class":"P",
    "gn:feature_code":"PPL",
    "gn:name":"Dabsh\u012byah",
    "gn:population":0,
    "gn:timezone":"Asia/Damascus",
    "iso:country":"SY",
    "name:ara_x_preferred":[
        "\u062f\u0628\u0634\u064a\u0629"
    ],
    "name:und_x_variant":[
        "Dabsh\u012byah"
    ],
    "wof:name":"Dabshiyah",
    "wof:placetype":"locality"
},
  "geometry": {"coordinates":[40.39917,36.17389],"type":"Point"}
}