{
  "type": "Feature",
  "properties": {
    "iso:country":"SY",
    "ne:ADM0CAP":0.0,
    "ne:ADM0NAME":"Syria",
    "ne:ADM0_A3":"SYR",
    "ne:ADM1NAME":"Damascus",
    "ne:ADMIN1_COD":8,
    "ne:CAPALT":0,
    "ne:CHANGED":0,
    "ne:CHECKME":0,
    "ne:COMPARE":0,
    "ne:DIFFASCII":0,
    "ne:ELEVATION":0.0,
    "ne:FEATURECLA":"Populated place",
    "ne:FEATURE_CL":"P",
    "ne:FEATURE_CO":"PPL",
    "ne:GEONAMEID":173193,
    "ne:GEONAMESNO":"GeoNames spatial join with similar names only.",
    "ne:GN_ASCII":"An Nabk",
    "ne:GN_POP":49372,
    "ne:GTOPO30":1266.0,
    "ne:ISO_A2":"SY",
    "ne:LABELRANK":6,
    "ne:LATITUDE":34.017031,
    "ne:LONGITUDE":36.733303,
    "ne:LS_MATCH":1,
    "ne:LS_NAME":"Ad Nabk",
    "ne:MAX_AREAKM":15.0,
    "ne:MAX_AREAMI":6.0,
    "ne:MAX_BBXMAX":36.758333,
    "ne:MAX_BBXMIN":36.708333,
    "ne:MAX_BBYMAX":34.05,
    "ne:MAX_BBYMIN":34.008333,
    "ne:MAX_NATSCA":20.0,
    "ne:MAX_PERKM":20.0,
    "ne:MAX_PERMI":13.0,
    "ne:MAX_POP10":50178,
    "ne:MAX_POP20":50178,
    "ne:MAX_POP300":0,
    "ne:MAX_POP310":0,
    "ne:MAX_POP50":0,
    "ne:MEAN_BBXC":36.731944,
    "ne:MEAN_BBYC":34.028373,
    "ne:MEGACITY":0,
    "ne:MIN_AREAKM":15.0,
    "ne:MIN_AREAMI":6.0,
    "ne:MIN_BBXMAX":36.758333,
    "ne:MIN_BBXMIN":36.708333,
    "ne:MIN_BBYMAX":34.05,
    "ne:MIN_BBYMIN":34.008333,
    "ne:MIN_PERKM":20.0,
    "ne:MIN_PERMI":13.0,
    "ne:NAME":"Ad Nabk",
    "ne:NAMEASCII":"Ad Nabk",
    "ne:NAMEDIFF":0,
    "ne:NATSCALE":20,
    "ne:POP1950":0,
    "ne:POP1955":0,
    "ne:POP1960":0,
    "ne:POP1965":0,
    "ne:POP1970":0,
    "ne:POP1975":0,
    "ne:POP1980":0,
    "ne:POP1985":0,
    "ne:POP1990":0,
    "ne:POP1995":0,
    "ne:POP2000":0,
    "ne:POP2005":0,
    "ne:POP2010":0,
    "ne:POP2015":0,
    "ne:POP2020":0,
    "ne:POP2025":0,
    "ne:POP2050":0,
    "ne:POP_MAX":50178,
    "ne:POP_MIN":49372,
    "ne:POP_OTHER":50178,
    "ne:RANK_MAX":8,
    "ne:RANK_MIN":7,
    "ne:SCALERANK":7,
    "ne:SOV0NAME":"Syria",
    "ne:SOV_A3":"SYR",
    "ne:TIMEZONE":"Asia/Damascus",
    "ne:UN_FID":0,
    "ne:UN_LAT":0.0,
    "ne:UN_LONG":0.0,
    "ne:WORLDCITY":0,
    "ne:min_zoom":6.7,
    "wof:name":"Ad Nabk",
    "wof:placetype":"locality"
},
  "geometry": {"coordinates":[36.7333027737975,34.01703086245726],"type":"Point"}
}