{
  "type": "Feature",
  "properties": {
    "gn:admin1_code":"2.0",
    "gn:asciiname":"Mazra`at al Qabw",
    "gn:country_code":"SY",
    "gn:dem":100,
    "gn:feature_class":"P",
    "gn:feature_code":"PPL",
    "gn:name":"Mazra\u2018at al Qabw",
    "gn:population":0,
    "gn:timezone":"Asia/Damascus",
    "iso:country":"SY",
    "name:ara_x_preferred":[
        "\u0645\u0632\u0631\u0639\u0629 \u0627\u0644\u0642\u0628\u0648"
    ],
    "name:und_x_variant":[
        "Mazra\u2018at al Qabw"
    ],
    "wof:name":"Mazra`at al Qabw",
    "wof:placetype":"locality"
},
  "geometry": {"coordinates":[35.88894000000001,35.51802],"type":"Point"}
}