{
  "type": "Feature",
  "properties": {
    "gn:admin1_code":"12.0",
    "gn:asciiname":"Al Majalliyah",
    "gn:country_code":"SY",
    "gn:dem":677,
    "gn:feature_class":"P",
    "gn:feature_code":"PPL",
    "gn:name":"Al Majall\u012byah",
    "gn:population":0,
    "gn:timezone":"Asia/Damascus",
    "iso:country":"SY",
    "name:ara_x_preferred":[
        "\u0627\u0644\u0645\u062c\u0644\u064a\u0629"
    ],
    "name:und_x_variant":[
        "Al Majall\u012byah"
    ],
    "wof:name":"Al Majalliyah",
    "wof:placetype":"locality"
},
  "geometry": {"coordinates":[36.52542,35.66936],"type":"Point"}
}