{
  "type": "Feature",
  "properties": {
    "gn:admin1_code":"11.0",
    "gn:asciiname":"Qism al Jidyah",
    "gn:country_code":"SY",
    "gn:dem":422,
    "gn:feature_class":"P",
    "gn:feature_code":"PPL",
    "gn:name":"Qism al Jidyah",
    "gn:population":0,
    "gn:timezone":"Asia/Damascus",
    "iso:country":"SY",
    "name:ara_x_preferred":[
        "\u0642\u0633\u0645 \u0627\u0644\u062c\u062f\u064a\u0629"
    ],
    "wof:name":"Qism al Jidyah",
    "wof:placetype":"locality"
},
  "geometry": {"coordinates":[36.68166,34.87971],"type":"Point"}
}