{
  "type": "Feature",
  "properties": {
    "gn:admin1_code":"12.0",
    "gn:asciiname":"Al Kukhiyah",
    "gn:country_code":"SY",
    "gn:dem":267,
    "gn:feature_class":"P",
    "gn:feature_code":"PPL",
    "gn:name":"Al K\u016bkh\u012byah",
    "gn:population":0,
    "gn:timezone":"Asia/Damascus",
    "iso:country":"SY",
    "name:ara_x_preferred":[
        "\u0627\u0644\u0643\u0648\u062e\u064a\u0629"
    ],
    "name:und_x_variant":[
        "Al K\u016bkh\u012byah"
    ],
    "wof:name":"Al Kukhiyah",
    "wof:placetype":"locality"
},
  "geometry": {"coordinates":[36.4465,35.75701],"type":"Point"}
}