{
  "type": "Feature",
  "properties": {
    "gn:admin1_code":"1.0",
    "gn:asciiname":"As Suwaytiyah",
    "gn:country_code":"SY",
    "gn:dem":291,
    "gn:feature_class":"P",
    "gn:feature_code":"PPL",
    "gn:name":"As Suway\u0163\u012byah",
    "gn:population":0,
    "gn:timezone":"Asia/Damascus",
    "iso:country":"SY",
    "name:ara_x_preferred":[
        "\u0627\u0644\u0633\u0648\u064a\u0637\u064a\u0629"
    ],
    "name:und_x_variant":[
        "As Suway\u0163\u012byah"
    ],
    "wof:name":"As Suwaytiyah",
    "wof:placetype":"locality"
},
  "geometry": {"coordinates":[40.66107,36.04558],"type":"Point"}
}