{
  "type": "Feature",
  "properties": {
    "gn:admin1_code":"12.0",
    "gn:asciiname":"Bayt al Bakkar",
    "gn:country_code":"SY",
    "gn:dem":747,
    "gn:feature_class":"P",
    "gn:feature_code":"PPL",
    "gn:name":"Bayt al Bakk\u0101r",
    "gn:population":0,
    "gn:timezone":"Asia/Damascus",
    "iso:country":"SY",
    "name:ara_x_preferred":[
        "\u0628\u064a\u062a \u0627\u0644\u0628\u0643\u0627\u0631"
    ],
    "name:und_x_variant":[
        "Bayt al Bakk\u0101r"
    ],
    "wof:name":"Bayt al Bakkar",
    "wof:placetype":"locality"
},
  "geometry": {"coordinates":[36.45068,36.0644],"type":"Point"}
}