{
  "type": "Feature",
  "properties": {
    "gn:admin1_code":"3.0",
    "gn:asciiname":"Sayda",
    "gn:country_code":"SY",
    "gn:dem":500,
    "gn:feature_class":"P",
    "gn:feature_code":"PPL",
    "gn:name":"\u015eayd\u0101",
    "gn:population":0,
    "gn:timezone":"Asia/Damascus",
    "iso:country":"SY",
    "name:ara_x_preferred":[
        "\u0635\u064a\u062f\u0627"
    ],
    "name:ara_x_variant":[
        "\u0632\u0627\u064a\u062f\u0627"
    ],
    "name:azb_x_preferred":[
        "\u0632\u0627\u06cc\u062f\u0627"
    ],
    "name:bak_x_preferred":[
        "\u0417\u0430\u0439\u0434\u0430"
    ],
    "name:ces_x_preferred":[
        "Sayda"
    ],
    "name:deu_x_preferred":[
        "Sayda"
    ],
    "name:epo_x_preferred":[
        "Sayda"
    ],
    "name:est_x_preferred":[
        "Sayda"
    ],
    "name:fas_x_preferred":[
        "\u0632\u0627\u06cc\u062f\u0627"
    ],
    "name:fra_x_preferred":[
        "Sayda"
    ],
    "name:hsb_x_preferred":[
        "Sayda"
    ],
    "name:hun_x_preferred":[
        "Sayda"
    ],
    "name:ita_x_preferred":[
        "Sayda"
    ],
    "name:kaz_x_preferred":[
        "\u0417\u0430\u0439\u0434\u0430"
    ],
    "name:kir_x_preferred":[
        "\u0417\u0430\u0439\u0434\u0430"
    ],
    "name:lav_x_preferred":[
        "Zaida"
    ],
    "name:mkd_x_preferred":[
        "\u0417\u0430\u0458\u0434\u0430"
    ],
    "name:msa_x_preferred":[
        "Sayda"
    ],
    "name:nld_x_preferred":[
        "Sayda"
    ],
    "name:nor_x_preferred":[
        "Sayda"
    ],
    "name:pol_x_preferred":[
        "Sayda"
    ],
    "name:ron_x_preferred":[
        "Sayda"
    ],
    "name:rus_x_preferred":[
        "\u0417\u0430\u0439\u0434\u0430"
    ],
    "name:spa_x_preferred":[
        "Sayda"
    ],
    "name:srp_x_preferred":[
        "\u0417\u0430\u0458\u0434\u0430"
    ],
    "name:swe_x_preferred":[
        "Sayda"
    ],
    "name:ukr_x_preferred":[
        "\u0417\u0430\u0439\u0434\u0430"
    ],
    "name:und_x_variant":[
        "\u015eayd\u0101"
    ],
    "name:uzb_x_preferred":[
        "Sayda"
    ],
    "name:vie_x_preferred":[
        "Sayda"
    ],
    "name:vol_x_preferred":[
        "Sayda"
    ],
    "name:war_x_preferred":[
        "Sayda"
    ],
    "wof:name":"Sayda",
    "wof:placetype":"locality"
},
  "geometry": {"coordinates":[35.87609000000001,32.87622],"type":"Point"}
}