{
  "type": "Feature",
  "properties": {
    "gn:admin1_code":"3.0",
    "gn:asciiname":"Sayda",
    "gn:country_code":"SY",
    "gn:dem":500,
    "gn:feature_class":"P",
    "gn:feature_code":"PPL",
    "gn:name":"\u015eayd\u0101",
    "gn:population":0,
    "gn:timezone":"Asia/Damascus",
    "iso:country":"SY",
    "name:ara_x_preferred":[
        "\u0635\u064a\u062f\u0627"
    ],
    "name:und_x_variant":[
        "\u015eayd\u0101"
    ],
    "wof:name":"Sayda",
    "wof:placetype":"locality"
},
  "geometry": {"coordinates":[35.87609000000001,32.87622],"type":"Point"}
}