{
  "type": "Feature",
  "properties": {
    "gn:admin1_code":"12.0",
    "gn:asciiname":"Az Zanbaqi",
    "gn:country_code":"SY",
    "gn:dem":289,
    "gn:feature_class":"P",
    "gn:feature_code":"PPL",
    "gn:name":"Az Zanbaq\u012b",
    "gn:population":0,
    "gn:timezone":"Asia/Damascus",
    "iso:country":"SY",
    "name:ara_x_preferred":[
        "\u0627\u0644\u0632\u0646\u0628\u0642\u064a"
    ],
    "name:und_x_variant":[
        "Az Zanbaq\u012b"
    ],
    "wof:name":"Az Zanbaqi",
    "wof:placetype":"locality"
},
  "geometry": {"coordinates":[36.39984000000001,36.00397],"type":"Point"}
}