{
  "type": "Feature",
  "properties": {
    "gn:admin1_code":"1.0",
    "gn:asciiname":"Ash Shamiyah",
    "gn:country_code":"SY",
    "gn:dem":491,
    "gn:feature_class":"P",
    "gn:feature_code":"PPL",
    "gn:name":"Ash Sh\u0101m\u012byah",
    "gn:population":0,
    "gn:timezone":"Asia/Damascus",
    "iso:country":"SY",
    "name:ara_x_preferred":[
        "\u0627\u0644\u0634\u0627\u0645\u064a\u0629"
    ],
    "name:ara_x_variant":[
        "Ch\u0101rj\u0101n",
        "\u0686\u0627\u0631\u062c\u0627\u0646"
    ],
    "name:kur_x_preferred":[
        "Ga \u1e5eeshan\u00ea"
    ],
    "name:kur_x_variant":[
        "\u06af\u0627 \u0695\u06d5\u0634\u0627\u0646\u06ce"
    ],
    "name:nno_x_preferred":[
        "Ash Shamiyah"
    ],
    "name:und_x_variant":[
        "Ash Sh\u0101m\u012byah"
    ],
    "wof:name":"Ash Shamiyah",
    "wof:placetype":"locality"
},
  "geometry": {"coordinates":[42.13444,37.12139],"type":"Point"}
}