{
  "type": "Feature",
  "properties": {
    "gn:admin1_code":"1.0",
    "gn:asciiname":"Ash Shamiyah",
    "gn:country_code":"SY",
    "gn:dem":491,
    "gn:feature_class":"P",
    "gn:feature_code":"PPL",
    "gn:name":"Ash Sh\u0101m\u012byah",
    "gn:population":0,
    "gn:timezone":"Asia/Damascus",
    "iso:country":"SY",
    "name:ara_x_preferred":[
        "\u0627\u0644\u0634\u0627\u0645\u064a\u0629"
    ],
    "name:nno_x_preferred":[
        "Ash Shamiyah"
    ],
    "name:und_x_variant":[
        "Ash Sh\u0101m\u012byah"
    ],
    "wof:name":"Ash Shamiyah",
    "wof:placetype":"locality"
},
  "geometry": {"coordinates":[42.13444000000001,37.12139000000001],"type":"Point"}
}