{
  "type": "Feature",
  "properties": {
    "gn:admin1_code":"9.0",
    "gn:asciiname":"`Ayyashiyah",
    "gn:country_code":"SY",
    "gn:dem":394,
    "gn:feature_class":"P",
    "gn:feature_code":"PPL",
    "gn:name":"\u2018Ayy\u0101sh\u012byah",
    "gn:population":0,
    "gn:timezone":"Asia/Damascus",
    "iso:country":"SY",
    "name:ara_x_preferred":[
        "\u0639\u064a\u0627\u0634\u064a\u0629"
    ],
    "name:und_x_variant":[
        "Aay\u00e2chiy\u00e9",
        "Ayachiy\u00e9",
        "\u2018Ayy\u0101sh\u012byah"
    ],
    "wof:name":"`Ayyashiyah",
    "wof:placetype":"locality"
},
  "geometry": {"coordinates":[37.54725,36.25946],"type":"Point"}
}