{
  "type": "Feature",
  "properties": {
    "gn:admin1_code":"12.0",
    "gn:asciiname":"Jarad",
    "gn:country_code":"SY",
    "gn:dem":259,
    "gn:feature_class":"P",
    "gn:feature_code":"PPL",
    "gn:name":"Jar\u0101d",
    "gn:population":0,
    "gn:timezone":"Asia/Damascus",
    "iso:country":"SY",
    "name:ara_x_preferred":[
        "\u062c\u0631\u0627\u062f"
    ],
    "name:und_x_variant":[
        "Jar\u0101d"
    ],
    "wof:name":"Jarad",
    "wof:placetype":"locality"
},
  "geometry": {"coordinates":[36.4142,36.00624000000001],"type":"Point"}
}