{
  "type": "Feature",
  "properties": {
    "gn:admin1_code":"11.0",
    "gn:asciiname":"Al Hafar",
    "gn:country_code":"SY",
    "gn:dem":978,
    "gn:feature_class":"P",
    "gn:feature_code":"PPL",
    "gn:name":"Al \u1e28afar",
    "gn:population":0,
    "gn:timezone":"Asia/Damascus",
    "iso:country":"SY",
    "name:ara_x_preferred":[
        "\u0627\u0644\u062d\u0641\u0631"
    ],
    "name:und_x_variant":[
        "\u1e28afr",
        "Al \u1e28afr",
        "Hafar",
        "El Hafar",
        "Al \u1e28afar"
    ],
    "wof:name":"Al Hafar",
    "wof:placetype":"locality"
},
  "geometry": {"coordinates":[36.90425,34.25138],"type":"Point"}
}