{
  "type": "Feature",
  "properties": {
    "gn:admin1_code":"11.0",
    "gn:asciiname":"Kharijat as Salibah",
    "gn:country_code":"SY",
    "gn:dem":621,
    "gn:feature_class":"P",
    "gn:feature_code":"PPL",
    "gn:name":"Khar\u012bjat a\u015f \u015eal\u012bbah",
    "gn:population":0,
    "gn:timezone":"Asia/Damascus",
    "iso:country":"SY",
    "name:ara_x_preferred":[
        "\u062e\u0631\u064a\u062c\u0629 \u0627\u0644\u0635\u0644\u064a\u0628\u0629"
    ],
    "name:und_x_variant":[
        "Khar\u00eejet Sal\u00eeb\u00e9",
        "Khar\u012bjat \u015eal\u012bbah",
        "Khar\u012bjat a\u015f \u015eal\u012bbah"
    ],
    "wof:name":"Kharijat as Salibah",
    "wof:placetype":"locality"
},
  "geometry": {"coordinates":[36.91906,34.7294],"type":"Point"}
}