{
  "type": "Feature",
  "properties": {
    "gn:admin1_code":"2.0",
    "gn:asciiname":"Qarah Bibar",
    "gn:country_code":"SY",
    "gn:dem":463,
    "gn:feature_class":"P",
    "gn:feature_code":"PPL",
    "gn:name":"Qarah B\u012bb\u0101r",
    "gn:population":0,
    "gn:timezone":"Asia/Damascus",
    "iso:country":"SY",
    "name:ara_x_preferred":[
        "\u0642\u0631\u0647 \u0628\u064a\u0628\u0627\u0631"
    ],
    "name:ara_x_variant":[
        "\u0628\u064a\u062a \u0634\u0639\u064a\u0628\u0627\u0646"
    ],
    "name:und_x_variant":[
        "Be\u00eft Chaib\u00e2ne",
        "Qara B\u00eeb\u00e2r",
        "Qarah B\u012bb\u0101r",
        "Bayt Shu\u2018ayb\u0101n",
        "Be\u00eft Cha\u00efbane"
    ],
    "wof:name":"Qarah Bibar",
    "wof:placetype":"locality"
},
  "geometry": {"coordinates":[36.11125,35.85720999999999],"type":"Point"}
}