{
  "type": "Feature",
  "properties": {
    "gn:admin1_code":"2.0",
    "gn:asciiname":"Al Haffah",
    "gn:country_code":"SY",
    "gn:dem":309,
    "gn:feature_class":"P",
    "gn:feature_code":"PPLA2",
    "gn:name":"Al \u1e28affah",
    "gn:population":0,
    "gn:timezone":"Asia/Damascus",
    "iso:country":"SY",
    "name:ara_x_preferred":[
        "\u0627\u0644\u062d\u0641\u0629"
    ],
    "name:fas_x_preferred":[
        "\u0627\u0644\u0647\u0641\u0647"
    ],
    "name:nno_x_preferred":[
        "Al Haffah"
    ],
    "name:und_x_variant":[
        "Haffe",
        "Al-Hiffeh",
        "\u1e28affah",
        "Al-Haffeh",
        "Al \u1e28affah",
        "Al Jaffah"
    ],
    "wof:name":"Al Haffah",
    "wof:placetype":"locality"
},
  "geometry": {"coordinates":[36.03006,35.59824000000001],"type":"Point"}
}