{
  "type": "Feature",
  "properties": {
    "gn:admin1_code":"9.0",
    "gn:asciiname":"Rasm al Mushayrif",
    "gn:country_code":"SY",
    "gn:dem":452,
    "gn:feature_class":"P",
    "gn:feature_code":"PPL",
    "gn:name":"Rasm al Mushayrif",
    "gn:population":0,
    "gn:timezone":"Asia/Damascus",
    "iso:country":"SY",
    "name:ara_x_preferred":[
        "\u0631\u0633\u0645 \u0627\u0644\u0645\u0634\u064a\u0631\u0641"
    ],
    "wof:name":"Rasm al Mushayrif",
    "wof:placetype":"locality"
},
  "geometry": {"coordinates":[37.2832,35.90533],"type":"Point"}
}