{
  "type": "Feature",
  "properties": {
    "gn:admin1_code":"1.0",
    "gn:asciiname":"Suwaydik",
    "gn:country_code":"SY",
    "gn:dem":503,
    "gn:feature_class":"P",
    "gn:feature_code":"PPL",
    "gn:name":"Suwaydik",
    "gn:population":0,
    "gn:timezone":"Asia/Damascus",
    "iso:country":"SY",
    "name:ara_x_preferred":[
        "Y\u0101f\u0101"
    ],
    "name:ara_x_variant":[
        "\u064a\u0627\u0641\u0627",
        "\u0633\u0648\u064a\u062f\u064a\u0643"
    ],
    "name:kur_x_preferred":[
        "Siw\u00ead\u00eeka Kesh\u00ea"
    ],
    "name:kur_x_variant":[
        "\u0633\u0648\u06ce\u062f\u064a\u0643\u0627 \u0643\u06d5\u0634\u06ce"
    ],
    "name:und_x_variant":[
        "Soue\u00efdik",
        "Suwaydik",
        "Suwayd\u012bk",
        "Siw\u00ead\u00eeka Ke\u015f\u00ea",
        "\u0633\u0648\u064a\u062f\u064a\u0643\u0627 \u0643\u0634\u064a"
    ],
    "wof:name":"Suwaydik",
    "wof:placetype":"locality"
},
  "geometry": {"coordinates":[42.16716,37.11318],"type":"Point"}
}