{
  "type": "Feature",
  "properties": {
    "gn:admin1_code":"14.0",
    "gn:asciiname":"Bayt ash Shaykh Mutawwaj",
    "gn:country_code":"SY",
    "gn:dem":350,
    "gn:feature_class":"P",
    "gn:feature_code":"PPL",
    "gn:name":"Bayt ash Shaykh Mutawwaj",
    "gn:population":0,
    "gn:timezone":"Asia/Damascus",
    "iso:country":"SY",
    "name:und_x_variant":[
        "Be\u00eft ech Che\u00efkh Mtao\u00fbej",
        "Bayt ash Shaykh Mutawwaj"
    ],
    "wof:name":"Bayt ash Shaykh Mutawwaj",
    "wof:placetype":"locality"
},
  "geometry": {"coordinates":[35.95909,35.09423],"type":"Point"}
}