{
  "type": "Feature",
  "properties": {
    "gn:admin1_code":"10.0",
    "gn:asciiname":"Abu Laffah",
    "gn:country_code":"SY",
    "gn:dem":359,
    "gn:feature_class":"P",
    "gn:feature_code":"PPL",
    "gn:name":"Ab\u016b Laffah",
    "gn:population":0,
    "gn:timezone":"Asia/Damascus",
    "iso:country":"SY",
    "name:ara_x_preferred":[
        "\u0623\u0628\u0648 \u0644\u0641\u0629"
    ],
    "name:und_x_variant":[
        "Ab\u016b Laffah"
    ],
    "wof:name":"Abu Laffah",
    "wof:placetype":"locality"
},
  "geometry": {"coordinates":[37.50513,35.39924],"type":"Point"}
}