{
  "type": "Feature",
  "properties": {
    "gn:admin1_code":"8.0",
    "gn:asciiname":"Ba`lat Marah al `Arab",
    "gn:country_code":"SY",
    "gn:dem":824,
    "gn:feature_class":"P",
    "gn:feature_code":"PPLL",
    "gn:name":"Ba\u2018lat Mar\u0101\u1e29 al \u2018Arab",
    "gn:population":0,
    "gn:timezone":"Asia/Damascus",
    "iso:country":"SY",
    "name:ara_x_preferred":[
        "\u0628\u0639\u0644\u0629 \u0645\u0631\u0627\u062d \u0627\u0644\u0639\u0631\u0628"
    ],
    "name:und_x_variant":[
        "Ba\u2018lat Mar\u0101\u1e29 al \u2018Arab"
    ],
    "wof:name":"Ba`lat Marah al `Arab",
    "wof:placetype":"locality"
},
  "geometry": {"coordinates":[36.09723,33.37122],"type":"Point"}
}