{
  "type": "Feature",
  "properties": {
    "gn:admin1_code":"9.0",
    "gn:asciiname":"Umm Qurun",
    "gn:country_code":"SY",
    "gn:dem":291,
    "gn:feature_class":"P",
    "gn:feature_code":"PPL",
    "gn:name":"Umm Qur\u016bn",
    "gn:population":0,
    "gn:timezone":"Asia/Damascus",
    "iso:country":"SY",
    "name:ara_x_preferred":[
        "Umm Qur\u016bn"
    ],
    "name:ara_x_variant":[
        "\u0623\u0645 \u0642\u0631\u0648\u0646"
    ],
    "wof:name":"Umm Qurun",
    "wof:placetype":"locality"
},
  "geometry": {"coordinates":[37.32573,35.55437],"type":"Point"}
}