{
  "type": "Feature",
  "properties": {
    "gn:admin1_code":"5.0",
    "gn:admin2_code":"172409.0",
    "gn:asciiname":"Salah",
    "gn:country_code":"SY",
    "gn:dem":1541,
    "gn:feature_class":"P",
    "gn:feature_code":"PPL",
    "gn:name":"S\u0101lah",
    "gn:population":0,
    "gn:timezone":"Asia/Damascus",
    "iso:country":"SY",
    "name:ara_x_preferred":[
        "\u0633\u0627\u0644\u0629"
    ],
    "name:rus_x_preferred":[
        "\u0421\u0430\u043b\u0430"
    ],
    "name:und_x_variant":[
        "S\u0101lih",
        "Sala",
        "S\u00e2l\u00e9",
        "S\u0101lah"
    ],
    "wof:name":"Salah",
    "wof:placetype":"locality"
},
  "geometry": {"coordinates":[36.7737,32.6478],"type":"Point"}
}