{
  "type": "Feature",
  "properties": {
    "gn:admin1_code":"8.0",
    "gn:asciiname":"Ard al Jarrariyat",
    "gn:country_code":"SY",
    "gn:dem":603,
    "gn:feature_class":"P",
    "gn:feature_code":"PPLL",
    "gn:name":"Ar\u1e11 al Jarr\u0101r\u012by\u0101t",
    "gn:population":0,
    "gn:timezone":"Asia/Damascus",
    "iso:country":"SY",
    "name:ara_x_preferred":[
        "\u0627\u0631\u0636 \u0627\u0644\u062c\u0631\u0627\u0631\u064a\u0627\u062a"
    ],
    "name:und_x_variant":[
        "Ar\u1e11 al Jarr\u0101r\u012by\u0101t"
    ],
    "wof:name":"Ard al Jarrariyat",
    "wof:placetype":"locality"
},
  "geometry": {"coordinates":[36.54642,33.5481],"type":"Point"}
}