{
  "type": "Feature",
  "properties": {
    "gn:admin1_code":"9.0",
    "gn:asciiname":"Jatbu",
    "gn:country_code":"SY",
    "gn:dem":516,
    "gn:feature_class":"P",
    "gn:feature_code":"PPL",
    "gn:name":"Ja\u0163b\u016b",
    "gn:population":0,
    "gn:timezone":"Asia/Damascus",
    "iso:country":"SY",
    "name:ara_x_preferred":[
        "\u062c\u0637\u0628\u0648"
    ],
    "name:ara_x_variant":[
        "\u062c\u0644\u0628\u0644"
    ],
    "name:und_x_variant":[
        "Ja\u0163b\u016b",
        "Jalbal"
    ],
    "wof:name":"Jatbu",
    "wof:placetype":"locality"
},
  "geometry": {"coordinates":[36.96901,36.48456],"type":"Point"}
}