{
  "type": "Feature",
  "properties": {
    "gn:admin1_code":"11.0",
    "gn:asciiname":"Ash Sharaqliyah",
    "gn:country_code":"SY",
    "gn:dem":420,
    "gn:feature_class":"P",
    "gn:feature_code":"PPL",
    "gn:name":"Ash Sharaql\u012byah",
    "gn:population":0,
    "gn:timezone":"Asia/Damascus",
    "iso:country":"SY",
    "name:ara_x_preferred":[
        "\u0627\u0644\u0634\u0631\u0642\u0644\u064a\u0629"
    ],
    "name:und_x_variant":[
        "Charakli\u00e9",
        "Charaql\u00eey\u00e9",
        "Sharaql\u012byah",
        "Ash Sharaql\u012byah"
    ],
    "wof:name":"Ash Sharaqliyah",
    "wof:placetype":"locality"
},
  "geometry": {"coordinates":[36.51212,34.83574],"type":"Point"}
}