{
  "type": "Feature",
  "properties": {
    "gn:admin1_code":"2.0",
    "gn:asciiname":"Al Manzilah",
    "gn:country_code":"SY",
    "gn:dem":73,
    "gn:feature_class":"P",
    "gn:feature_code":"PPL",
    "gn:name":"Al Manzilah",
    "gn:population":0,
    "gn:timezone":"Asia/Damascus",
    "iso:country":"SY",
    "name:ara_x_preferred":[
        "\u0627\u0644\u0645\u0646\u0632\u0644\u0629"
    ],
    "wof:name":"Al Manzilah",
    "wof:placetype":"locality"
},
  "geometry": {"coordinates":[35.85985,35.71965],"type":"Point"}
}