{
  "type": "Feature",
  "properties": {
    "gn:admin1_code":"9.0",
    "gn:asciiname":"Shaykh Kilu",
    "gn:country_code":"SY",
    "gn:dem":463,
    "gn:feature_class":"P",
    "gn:feature_code":"PPL",
    "gn:name":"Shaykh K\u012bl\u016b",
    "gn:population":0,
    "gn:timezone":"Asia/Damascus",
    "iso:country":"SY",
    "name:ara_x_preferred":[
        "\u0634\u064a\u062e \u0643\u064a\u0644\u0648"
    ],
    "name:und_x_variant":[
        "Che\u00efkh K\u00eelo",
        "Shaykh K\u012bl\u016b"
    ],
    "wof:name":"Shaykh Kilu",
    "wof:placetype":"locality"
},
  "geometry": {"coordinates":[36.75708,36.61939],"type":"Point"}
}