{
  "type": "Feature",
  "properties": {
    "gn:admin1_code":"11.0",
    "gn:asciiname":"Al Khalidiyah",
    "gn:country_code":"SY",
    "gn:dem":518,
    "gn:feature_class":"P",
    "gn:feature_code":"PPL",
    "gn:name":"Al Kh\u0101lid\u012byah",
    "gn:population":0,
    "gn:timezone":"Asia/Damascus",
    "iso:country":"SY",
    "name:ara_x_preferred":[
        "\u0627\u0644\u0642\u0646\u0637\u0631\u0629"
    ],
    "name:ara_x_variant":[
        "\u0627\u0644\u062e\u0627\u0644\u062f\u064a\u0629"
    ],
    "name:und_x_variant":[
        "Al Qan\u0163arah",
        "Al Kh\u0101lid\u012byah"
    ],
    "wof:name":"Al Khalidiyah",
    "wof:placetype":"locality"
},
  "geometry": {"coordinates":[36.51145,34.50738],"type":"Point"}
}