{
  "type": "Feature",
  "properties": {
    "gn:admin1_code":"9.0",
    "gn:asciiname":"Shaykh `Aqil",
    "gn:country_code":"SY",
    "gn:dem":562,
    "gn:feature_class":"P",
    "gn:feature_code":"PPL",
    "gn:name":"Shaykh \u2018Aq\u012bl",
    "gn:population":0,
    "gn:timezone":"Asia/Damascus",
    "iso:country":"SY",
    "name:ara_x_preferred":[
        "\u0634\u064a\u062e \u0639\u0642\u064a\u0644"
    ],
    "name:und_x_variant":[
        "Che\u00efkh Akil",
        "Che\u00efkh Aaq\u00eel",
        "Ash Shaykh \u2018Aq\u012bl",
        "Shaykh \u2018Aq\u012bl"
    ],
    "wof:name":"Shaykh `Aqil",
    "wof:placetype":"locality"
},
  "geometry": {"coordinates":[36.94026,36.31184],"type":"Point"}
}