{
  "type": "Feature",
  "properties": {
    "gn:admin1_code":"2.0",
    "gn:asciiname":"Al Mushayrifah",
    "gn:country_code":"SY",
    "gn:dem":159,
    "gn:feature_class":"P",
    "gn:feature_code":"PPL",
    "gn:name":"Al Mushayrifah",
    "gn:population":0,
    "gn:timezone":"Asia/Damascus",
    "iso:country":"SY",
    "name:ara_x_preferred":[
        "\u0627\u0644\u0645\u0634\u064a\u0631\u0641\u0629"
    ],
    "name:ara_x_variant":[
        "\u0645\u0634\u064a\u0631\u0641\u0629 \u0627\u0644\u062d\u0641\u0629"
    ],
    "name:und_x_variant":[
        "El M\u00e9cherf\u00e9",
        "El Mcherfi",
        "Al Mushayrifah",
        "Mushayrifat al \u1e28iffah",
        "Msheirfet Elhiffeh"
    ],
    "wof:name":"Al Mushayrifah",
    "wof:placetype":"locality"
},
  "geometry": {"coordinates":[35.93194000000001,35.52359000000001],"type":"Point"}
}