{
  "type": "Feature",
  "properties": {
    "gn:admin1_code":"10.0",
    "gn:asciiname":"Dunaybah",
    "gn:country_code":"SY",
    "gn:dem":488,
    "gn:feature_class":"P",
    "gn:feature_code":"PPL",
    "gn:name":"Dunaybah",
    "gn:population":0,
    "gn:timezone":"Asia/Damascus",
    "iso:country":"SY",
    "name:ara_x_preferred":[
        "\u062f\u0646\u064a\u0628\u0629"
    ],
    "name:fas_x_preferred":[
        "\u062f\u0646\u06cc\u0628\u0647"
    ],
    "name:pol_x_preferred":[
        "Dunajba"
    ],
    "name:und_x_variant":[
        "Dna\u00efb\u00e9",
        "Dne\u00efbe"
    ],
    "name:vie_x_preferred":[
        "Dunaybah"
    ],
    "wof:name":"Dunaybah",
    "wof:placetype":"locality"
},
  "geometry": {"coordinates":[37.00583,34.92811],"type":"Point"}
}