{
  "type": "Feature",
  "properties": {
    "gn:admin1_code":"9.0",
    "gn:asciiname":"Khirbat Shuwaym",
    "gn:country_code":"SY",
    "gn:dem":357,
    "gn:feature_class":"P",
    "gn:feature_code":"PPL",
    "gn:name":"Khirbat Shuwaym",
    "gn:population":0,
    "gn:timezone":"Asia/Damascus",
    "iso:country":"SY",
    "name:ara_x_preferred":[
        "\u062e\u0631\u0628\u0629 \u0634\u0648\u064a\u0645"
    ],
    "wof:name":"Khirbat Shuwaym",
    "wof:placetype":"locality"
},
  "geometry": {"coordinates":[38.10771,35.8636],"type":"Point"}
}