{
  "type": "Feature",
  "properties": {
    "gn:admin1_code":"8.0",
    "gn:asciiname":"Ard al Marj",
    "gn:country_code":"SY",
    "gn:dem":606,
    "gn:feature_class":"P",
    "gn:feature_code":"PPLL",
    "gn:name":"Ar\u1e11 al Marj",
    "gn:population":0,
    "gn:timezone":"Asia/Damascus",
    "iso:country":"SY",
    "name:ara_x_preferred":[
        "\u0623\u0631\u0636 \u0627\u0644\u0645\u0631\u062c"
    ],
    "name:und_x_variant":[
        "Ar\u1e11 al Marj"
    ],
    "wof:name":"Ard al Marj",
    "wof:placetype":"locality"
},
  "geometry": {"coordinates":[36.52756,33.60562],"type":"Point"}
}