{
  "type": "Feature",
  "properties": {
    "gn:admin1_code":"8.0",
    "gn:asciiname":"Ard ar Rayhan",
    "gn:country_code":"SY",
    "gn:dem":634,
    "gn:feature_class":"P",
    "gn:feature_code":"PPLL",
    "gn:name":"Ar\u1e11 ar Ray\u1e29\u0101n",
    "gn:population":0,
    "gn:timezone":"Asia/Damascus",
    "iso:country":"SY",
    "name:ara_x_preferred":[
        "\u0627\u0631\u0636 \u0627\u0644\u0631\u064a\u062d\u0627\u0646"
    ],
    "name:und_x_variant":[
        "Ar\u1e11 ar Ray\u1e29\u0101n"
    ],
    "wof:name":"Ard ar Rayhan",
    "wof:placetype":"locality"
},
  "geometry": {"coordinates":[36.43373,33.56109],"type":"Point"}
}