{
  "type": "Feature",
  "properties": {
    "gn:admin1_code":"9.0",
    "gn:asciiname":"Tirmik Bijan",
    "gn:country_code":"SY",
    "gn:dem":544,
    "gn:feature_class":"P",
    "gn:feature_code":"PPL",
    "gn:name":"Tirm\u012bk B\u012bj\u0101n",
    "gn:population":0,
    "gn:timezone":"Asia/Damascus",
    "iso:country":"SY",
    "name:ara_x_preferred":[
        "\u062a\u0631\u0645\u064a\u0643 \u0628\u064a\u062c\u0627\u0646"
    ],
    "name:ara_x_variant":[
        "Tirm\u012bk B\u012bj\u0101n",
        "\u0628\u064a\u062c\u0627\u0646"
    ],
    "name:kur_x_preferred":[
        "Tirmik\u00ee B\u00ee Can"
    ],
    "name:kur_x_variant":[
        "Tirmik\u00ea B\u00ea Can",
        "\u062a\u0631\u0645\u0643\u064a \u0628\u064a \u062c\u0627\u0646",
        "\u062a\u0631\u0645\u0643\u06ce \u0628\u06ce \u062c\u0627\u0646"
    ],
    "name:und_x_variant":[
        "Tarm\u012bk B\u012bj\u0101n",
        "Tirm\u012bk Bayj\u0101n",
        "Tirmik Bijan",
        "B\u012bj\u0101n",
        "B\u00eecan",
        "Tirmike Be Jan",
        "Termik B\u00eacan"
    ],
    "wof:name":"Tirmik Bijan",
    "wof:placetype":"locality"
},
  "geometry": {"coordinates":[38.34712,36.87097],"type":"Point"}
}