{
  "type": "Feature",
  "properties": {
    "gn:admin1_code":"12.0",
    "gn:asciiname":"Hazzarin",
    "gn:country_code":"SY",
    "gn:dem":605,
    "gn:feature_class":"P",
    "gn:feature_code":"PPL",
    "gn:name":"\u1e28azz\u0101r\u012bn",
    "gn:population":0,
    "gn:timezone":"Asia/Damascus",
    "iso:country":"SY",
    "name:ara_x_preferred":[
        "\u062d\u0632\u0627\u0631\u064a\u0646"
    ],
    "name:und_x_variant":[
        "Hazz\u00e2r\u00eene",
        "\u1e28azz\u0101r\u012b",
        "\u1e28azz\u0101r\u012bn"
    ],
    "wof:name":"Hazzarin",
    "wof:placetype":"locality"
},
  "geometry": {"coordinates":[36.52615,35.60002],"type":"Point"}
}