{
  "type": "Feature",
  "properties": {
    "gn:admin1_code":"11.0",
    "gn:asciiname":"Umm al Mays",
    "gn:country_code":"SY",
    "gn:dem":497,
    "gn:feature_class":"P",
    "gn:feature_code":"PPL",
    "gn:name":"Umm al Mays",
    "gn:population":0,
    "gn:timezone":"Asia/Damascus",
    "iso:country":"SY",
    "name:ara_x_preferred":[
        "\u0623\u0645 \u0627\u0644\u0645\u064a\u0633"
    ],
    "name:und_x_variant":[
        "Oumm el Ma\u00efss",
        "Oumm el Me\u00efs",
        "Umm al Mays"
    ],
    "wof:name":"Umm al Mays",
    "wof:placetype":"locality"
},
  "geometry": {"coordinates":[36.43317,34.64905],"type":"Point"}
}