{
  "type": "Feature",
  "properties": {
    "gn:admin1_code":"1.0",
    "gn:asciiname":"`Ayn `Amshah Tahtani",
    "gn:country_code":"SY",
    "gn:dem":446,
    "gn:feature_class":"P",
    "gn:feature_code":"PPL",
    "gn:name":"\u2018Ayn \u2018Amshah Ta\u1e29t\u0101n\u012b",
    "gn:population":0,
    "gn:timezone":"Asia/Damascus",
    "iso:country":"SY",
    "name:ara_x_preferred":[
        "\u0639\u064a\u0646 \u0639\u0645\u0634\u0629 \u062a\u062d\u062a\u0627\u0646\u064a"
    ],
    "name:tur_x_preferred":[
        "\u2018Ayn \u2018Amsh\u0101\u2019 at Ta\u1e29t\u0101n\u012b"
    ],
    "name:und_x_variant":[
        "A\u00efn Aamcha Taht\u00e2ni",
        "\u2018Ayn \u2018Amshah Ta\u1e29t\u0101n\u012b"
    ],
    "wof:name":"`Ayn `Amshah Tahtani",
    "wof:placetype":"locality"
},
  "geometry": {"coordinates":[40.82725,37.03457],"type":"Point"}
}