{
  "type": "Feature",
  "properties": {
    "gn:admin1_code":"8.0",
    "gn:asciiname":"Manin",
    "gn:country_code":"SY",
    "gn:dem":1122,
    "gn:feature_class":"P",
    "gn:feature_code":"PPL",
    "gn:name":"Man\u012bn",
    "gn:population":0,
    "gn:timezone":"Asia/Damascus",
    "iso:country":"SY",
    "name:ara_x_preferred":[
        "\u0645\u0646\u064a\u0646"
    ],
    "name:ara_x_variant":[
        "\u0639\u064a\u0646 \u0645\u0646\u064a\u0646"
    ],
    "name:fas_x_preferred":[
        "\u0645\u0646\u06cc\u0646"
    ],
    "name:pol_x_preferred":[
        "Manin"
    ],
    "name:und_x_variant":[
        "Mn\u00eene",
        "Menin",
        "Man\u012bn",
        "Min\u012bn"
    ],
    "name:vie_x_preferred":[
        "Manin"
    ],
    "wof:name":"Manin",
    "wof:placetype":"locality"
},
  "geometry": {"coordinates":[36.29905,33.64057],"type":"Point"}
}