{
  "type": "Feature",
  "properties": {
    "gn:admin1_code":"9.0",
    "gn:asciiname":"Kuk Tabbah Sughra",
    "gn:country_code":"SY",
    "gn:dem":403,
    "gn:feature_class":"P",
    "gn:feature_code":"PPL",
    "gn:name":"K\u016bk Tabbah \u015eughr\u00e1",
    "gn:population":0,
    "gn:timezone":"Asia/Damascus",
    "iso:country":"SY",
    "name:ara_x_preferred":[
        "\u0643\u0648\u0643 \u062a\u0628\u0629 \u0643\u0628\u0631\u0649"
    ],
    "name:und_x_variant":[
        "K\u016bk Tappah \u015eughr\u00e1",
        "K\u016bk Tabbah \u015eughr\u00e1"
    ],
    "wof:name":"Kuk Tabbah Sughra",
    "wof:placetype":"locality"
},
  "geometry": {"coordinates":[38.6295,36.56439],"type":"Point"}
}