{
  "type": "Feature",
  "properties": {
    "gn:admin1_code":"11.0",
    "gn:asciiname":"Umm Sharshuh",
    "gn:country_code":"SY",
    "gn:dem":437,
    "gn:feature_class":"P",
    "gn:feature_code":"PPL",
    "gn:name":"Umm Sharsh\u016b\u1e29",
    "gn:population":0,
    "gn:timezone":"Asia/Damascus",
    "iso:country":"SY",
    "name:ara_x_preferred":[
        "\u0623\u0645 \u0634\u0631\u0634\u0648\u062d"
    ],
    "name:und_x_variant":[
        "Oum ech Cherchouch",
        "Oum Charcho\u00fbh",
        "Oumm Charchouh",
        "Oumm Charcho\u00fbch",
        "Umm Sharsh\u016b\u1e29"
    ],
    "wof:name":"Umm Sharshuh",
    "wof:placetype":"locality"
},
  "geometry": {"coordinates":[36.68765,34.87573],"type":"Point"}
}