{
  "type": "Feature",
  "properties": {
    "gn:admin1_code":"1.0",
    "gn:asciiname":"Qijlah",
    "gn:country_code":"SY",
    "gn:dem":441,
    "gn:feature_class":"P",
    "gn:feature_code":"PPL",
    "gn:name":"Qijlah",
    "gn:population":0,
    "gn:timezone":"Asia/Damascus",
    "iso:country":"SY",
    "name:ara_x_preferred":[
        "\u0642\u062c\u0644\u0629"
    ],
    "name:tur_x_preferred":[
        "Qijlah"
    ],
    "name:und_x_variant":[
        "Qijl\u00e9"
    ],
    "wof:name":"Qijlah",
    "wof:placetype":"locality"
},
  "geometry": {"coordinates":[40.84902,37.06264],"type":"Point"}
}