{
  "type": "Feature",
  "properties": {
    "gn:admin1_code":"2.0",
    "gn:asciiname":"Tartiyah",
    "gn:country_code":"SY",
    "gn:dem":901,
    "gn:feature_class":"P",
    "gn:feature_code":"PPL",
    "gn:name":"Tartiy\u0101\u1e29",
    "gn:population":0,
    "gn:timezone":"Asia/Damascus",
    "iso:country":"SY",
    "name:ara_x_preferred":[
        "\u062a\u0631\u062a\u064a\u0627\u062d"
    ],
    "name:und_x_variant":[
        "Tert\u00eey\u00e2h",
        "Tartiy\u0101\u1e29",
        "Tartiy\u0101kh"
    ],
    "wof:name":"Tartiyah",
    "wof:placetype":"locality"
},
  "geometry": {"coordinates":[36.16331,35.68402000000001],"type":"Point"}
}