{
  "type": "Feature",
  "properties": {
    "gn:admin1_code":"1.0",
    "gn:asciiname":"Rashidiyah",
    "gn:country_code":"SY",
    "gn:dem":284,
    "gn:feature_class":"P",
    "gn:feature_code":"PPL",
    "gn:name":"Rash\u012bd\u012byah",
    "gn:population":0,
    "gn:timezone":"Asia/Damascus",
    "iso:country":"SY",
    "name:ara_x_preferred":[
        "\u0631\u0634\u064a\u062f\u064a\u0629"
    ],
    "name:und_x_variant":[
        "Rach\u00eed\u00eey\u00e9",
        "Rashd\u012byah",
        "Rash\u012bd\u012byah"
    ],
    "wof:name":"Rashidiyah",
    "wof:placetype":"locality"
},
  "geometry": {"coordinates":[40.71159,36.15188],"type":"Point"}
}