{
  "type": "Feature",
  "properties": {
    "gn:admin1_code":"4.0",
    "gn:asciiname":"Shunaynah",
    "gn:country_code":"SY",
    "gn:dem":351,
    "gn:feature_class":"P",
    "gn:feature_code":"PPL",
    "gn:name":"Shunaynah",
    "gn:population":0,
    "gn:timezone":"Asia/Damascus",
    "iso:country":"SY",
    "name:ara_x_preferred":[
        "\u0634\u0646\u064a\u0646\u0629"
    ],
    "name:und_x_variant":[
        "Chene\u00efn\u00e9",
        "Shunaynah"
    ],
    "wof:name":"Shunaynah",
    "wof:placetype":"locality"
},
  "geometry": {"coordinates":[38.80107,36.57899000000001],"type":"Point"}
}