{
  "type": "Feature",
  "properties": {
    "gn:admin1_code":"1.0",
    "gn:asciiname":"`Uluk Gharbi",
    "gn:country_code":"SY",
    "gn:dem":361,
    "gn:feature_class":"P",
    "gn:feature_code":"PPL",
    "gn:name":"\u2018Ul\u016bk Gharb\u012b",
    "gn:population":0,
    "gn:timezone":"Asia/Damascus",
    "iso:country":"SY",
    "name:ara_x_preferred":[
        "\u0639\u0644\u0648\u0643 \u063a\u0631\u0628\u064a"
    ],
    "name:tur_x_preferred":[
        "\u2018Al\u016bq al Gharb\u012b"
    ],
    "name:und_x_variant":[
        "Aalo\u00fbq Rharbi",
        "\u2018Ul\u016bk Gharb\u012b"
    ],
    "wof:name":"`Uluk Gharbi",
    "wof:placetype":"locality"
},
  "geometry": {"coordinates":[40.12911,36.86361],"type":"Point"}
}