{
  "type": "Feature",
  "properties": {
    "gn:admin1_code":"9.0",
    "gn:asciiname":"Zaghra",
    "gn:country_code":"SY",
    "gn:dem":449,
    "gn:feature_class":"P",
    "gn:feature_code":"PPL",
    "gn:name":"Zaghr\u0101",
    "gn:population":0,
    "gn:timezone":"Asia/Damascus",
    "iso:country":"SY",
    "name:ara_x_preferred":[
        "\u0632\u063a\u0631\u0627"
    ],
    "name:und_x_variant":[
        "Zaghr\u0101"
    ],
    "wof:name":"Zaghra",
    "wof:placetype":"locality"
},
  "geometry": {"coordinates":[37.48378,35.75456],"type":"Point"}
}