{
  "type": "Feature",
  "properties": {
    "gn:admin1_code":"9.0",
    "gn:asciiname":"Ad Dulab",
    "gn:country_code":"SY",
    "gn:dem":320,
    "gn:feature_class":"P",
    "gn:feature_code":"PPL",
    "gn:name":"Ad D\u016bl\u0101b",
    "gn:population":0,
    "gn:timezone":"Asia/Damascus",
    "iso:country":"SY",
    "name:ara_x_preferred":[
        "D\u016bl\u0101b"
    ],
    "name:ara_x_variant":[
        "Ad D\u016bl\u0101b",
        "\u0627\u0644\u0631\u0648\u0644\u0627\u0628"
    ],
    "name:und_x_variant":[
        "Do\u00fbl\u00e2b"
    ],
    "wof:name":"Ad Dulab",
    "wof:placetype":"locality"
},
  "geometry": {"coordinates":[37.52586,36.09964],"type":"Point"}
}