{
  "type": "Feature",
  "properties": {
    "gn:admin1_code":"9.0",
    "gn:asciiname":"Khirbat al Muftahiyah",
    "gn:country_code":"SY",
    "gn:dem":348,
    "gn:feature_class":"P",
    "gn:feature_code":"PPL",
    "gn:name":"Khirbat al Muft\u0101\u1e29\u012byah",
    "gn:population":0,
    "gn:timezone":"Asia/Damascus",
    "iso:country":"SY",
    "name:ara_x_preferred":[
        "\u062e\u0631\u0628\u0629 \u0627\u0644\u0645\u0641\u062a\u0627\u062d\u064a\u0629"
    ],
    "name:und_x_variant":[
        "Khirbat al Muft\u0101\u1e29\u012byah"
    ],
    "wof:name":"Khirbat al Muftahiyah",
    "wof:placetype":"locality"
},
  "geometry": {"coordinates":[38.0513,35.85151],"type":"Point"}
}