{
  "type": "Feature",
  "properties": {
    "gn:admin1_code":"10.0",
    "gn:asciiname":"Al Bayad",
    "gn:country_code":"SY",
    "gn:dem":291,
    "gn:feature_class":"P",
    "gn:feature_code":"PPL",
    "gn:name":"Al Bay\u0101\u1e11",
    "gn:population":0,
    "gn:timezone":"Asia/Damascus",
    "iso:country":"SY",
    "name:ara_x_preferred":[
        "\u0627\u0644\u0628\u064a\u0627\u0636"
    ],
    "name:und_x_variant":[
        "Al Bay\u0101\u1e11"
    ],
    "wof:name":"Al Bayad",
    "wof:placetype":"locality"
},
  "geometry": {"coordinates":[36.56034,35.14505],"type":"Point"}
}