{
  "type": "Feature",
  "properties": {
    "gn:admin1_code":"11.0",
    "gn:asciiname":"Ash Shayyahat",
    "gn:country_code":"SY",
    "gn:dem":534,
    "gn:feature_class":"P",
    "gn:feature_code":"PPL",
    "gn:name":"Ash Shayy\u0101\u1e29\u0101t",
    "gn:population":0,
    "gn:timezone":"Asia/Damascus",
    "iso:country":"SY",
    "name:ara_x_preferred":[
        "\u0627\u0644\u0634\u064a\u0627\u062d\u0627\u062a"
    ],
    "name:und_x_variant":[
        "Ash Shayy\u0101\u1e29\u0101t"
    ],
    "wof:name":"Ash Shayyahat",
    "wof:placetype":"locality"
},
  "geometry": {"coordinates":[36.57354,34.47096],"type":"Point"}
}