{
  "type": "Feature",
  "properties": {
    "gn:admin1_code":"9.0",
    "gn:asciiname":"Tall Banin",
    "gn:cc2":"SY",
    "gn:country_code":"SY",
    "gn:dem":516,
    "gn:feature_class":"P",
    "gn:feature_code":"PPL",
    "gn:name":"Tall Ban\u012bn",
    "gn:population":0,
    "gn:timezone":"Asia/Damascus",
    "iso:country":"SY",
    "name:und_x_variant":[
        "Tell Ban\u00eene",
        "Tall Ban\u012bn"
    ],
    "wof:name":"Tall Banin",
    "wof:placetype":"locality"
},
  "geometry": {"coordinates":[37.33333,35.98333],"type":"Point"}
}