{
  "type": "Feature",
  "properties": {
    "gn:admin1_code":"9.0",
    "gn:asciiname":"Rasm al Jahsh",
    "gn:country_code":"SY",
    "gn:dem":278,
    "gn:feature_class":"P",
    "gn:feature_code":"PPL",
    "gn:name":"Rasm al Ja\u1e29sh",
    "gn:population":0,
    "gn:timezone":"Asia/Damascus",
    "iso:country":"SY",
    "name:ara_x_preferred":[
        "\u0631\u0633\u0645 \u0627\u0644\u062c\u062d\u0634"
    ],
    "name:und_x_variant":[
        "Rasm ej Jahch",
        "Rasm al Ja\u1e29sh"
    ],
    "wof:name":"Rasm al Jahsh",
    "wof:placetype":"locality"
},
  "geometry": {"coordinates":[37.1763,35.64631],"type":"Point"}
}