{
  "type": "Feature",
  "properties": {
    "gn:admin1_code":"12.0",
    "gn:asciiname":"Mashta al `Atiq",
    "gn:country_code":"SY",
    "gn:dem":252,
    "gn:feature_class":"P",
    "gn:feature_code":"PPL",
    "gn:name":"Masht\u00e1 al \u2018At\u012bq",
    "gn:population":0,
    "gn:timezone":"Asia/Damascus",
    "iso:country":"SY",
    "name:ara_x_preferred":[
        "\u0645\u0634\u062a\u0649 \u0627\u0644\u0639\u062a\u064a\u0642"
    ],
    "name:und_x_variant":[
        "Masht\u00e1 al \u2018At\u012bq"
    ],
    "wof:name":"Mashta al `Atiq",
    "wof:placetype":"locality"
},
  "geometry": {"coordinates":[36.36313,35.8852],"type":"Point"}
}