{
  "type": "Feature",
  "properties": {
    "gn:admin1_code":"9.0",
    "gn:asciiname":"Diwan Tahtani",
    "gn:country_code":"SY",
    "gn:dem":159,
    "gn:feature_class":"P",
    "gn:feature_code":"PPL",
    "gn:name":"D\u012bw\u0101n Ta\u1e29t\u0101n\u012b",
    "gn:population":0,
    "gn:timezone":"Asia/Damascus",
    "iso:country":"SY",
    "name:ara_x_preferred":[
        "\u062f\u064a\u0648\u0627\u0646 \u062a\u062d\u062a\u0627\u0646\u064a"
    ],
    "name:und_x_variant":[
        "Diouan Tahtani",
        "D\u00eeou\u00e2ne Taht\u00e2ni",
        "D\u012bw\u0101n at Ta\u1e29t\u0101n\u012b",
        "D\u012bw\u0101n Ta\u1e29t\u0101n\u012b",
        "Diou\u00e2ne Taht\u00e2ni"
    ],
    "wof:name":"Diwan Tahtani",
    "wof:placetype":"locality"
},
  "geometry": {"coordinates":[36.71661,36.35789000000001],"type":"Point"}
}