{
  "type": "Feature",
  "properties": {
    "gn:admin1_code":"4.0",
    "gn:asciiname":"Jurah",
    "gn:country_code":"SY",
    "gn:dem":339,
    "gn:feature_class":"P",
    "gn:feature_code":"PPL",
    "gn:name":"J\u016brah",
    "gn:population":0,
    "gn:timezone":"Asia/Damascus",
    "iso:country":"SY",
    "name:ara_x_preferred":[
        "\u062c\u0648\u0631\u0629"
    ],
    "name:und_x_variant":[
        "Jo\u00fbra",
        "Jourra",
        "J\u016brah"
    ],
    "wof:name":"Jurah",
    "wof:placetype":"locality"
},
  "geometry": {"coordinates":[38.90372,36.38436],"type":"Point"}
}