{
  "type": "Feature",
  "properties": {
    "gn:admin1_code":"10.0",
    "gn:asciiname":"Tall at Tut",
    "gn:country_code":"SY",
    "gn:dem":519,
    "gn:feature_class":"P",
    "gn:feature_code":"PPL",
    "gn:name":"Tall at T\u016bt",
    "gn:population":0,
    "gn:timezone":"Asia/Damascus",
    "iso:country":"SY",
    "name:ara_x_preferred":[
        "\u062a\u0644 \u0627\u0644\u062a\u0648\u062a"
    ],
    "name:und_x_variant":[
        "Tell ett To\u00fbte",
        "Tall at T\u016bt"
    ],
    "wof:name":"Tall at Tut",
    "wof:placetype":"locality"
},
  "geometry": {"coordinates":[37.16434,34.9897],"type":"Point"}
}