{
  "type": "Feature",
  "properties": {
    "gn:admin1_code":"9.0",
    "gn:asciiname":"`Ajami",
    "gn:country_code":"SY",
    "gn:dem":490,
    "gn:feature_class":"P",
    "gn:feature_code":"PPL",
    "gn:name":"\u2018Ajam\u012b",
    "gn:population":0,
    "gn:timezone":"Asia/Damascus",
    "iso:country":"SY",
    "name:ara_x_preferred":[
        "\u0639\u062c\u0645\u064a"
    ],
    "name:und_x_variant":[
        "Adjimi",
        "Aajami",
        "\u2018Ajam\u012b"
    ],
    "wof:name":"`Ajami",
    "wof:placetype":"locality"
},
  "geometry": {"coordinates":[37.6467,36.42339000000001],"type":"Point"}
}