{
  "type": "Feature",
  "properties": {
    "gn:country":"SY",
    "gn:fcode":"PPLA3",
    "gn:pop":24754,
    "iso:country":"SY",
    "name:ara_x_preferred":[
        "\u0643\u0641\u0631 \u0646\u0628\u0644"
    ],
    "name:ara_x_variant":[
        "\u0643\u0641\u0631\u0646\u0628\u0644"
    ],
    "name:deu_x_preferred":[
        "Kafranbel"
    ],
    "name:eng_x_preferred":[
        "Kafr Nabl"
    ],
    "name:fas_x_preferred":[
        "\u06a9\u0641\u0631\u0646\u0628\u0644"
    ],
    "name:nld_x_preferred":[
        "Kafr Nabl"
    ],
    "name:nno_x_preferred":[
        "Kafr Nabl"
    ],
    "name:pol_x_preferred":[
        "Kafr Nubl"
    ],
    "name:swe_x_preferred":[
        "Kafr Nubl"
    ],
    "name:ukr_x_preferred":[
        "\u041a\u0430\u0444\u0440\u0430\u043d\u0431\u0435\u043b\u044c"
    ],
    "name:unk_x_variant":[
        "Kafr nabel"
    ],
    "name:urd_x_preferred":[
        "\u06a9\u0641\u0631 \u0646\u0628\u0644"
    ],
    "qs:name":"Kafr Nabl",
    "qs:photos_9r":0,
    "qs:photos_sr":0,
    "qs:pop_sr":"7",
    "wd:wordcount":359,
    "wof:name":"Kafr Nabl",
    "wof:placetype":"locality",
    "wof:population":24754
},
  "geometry": {"coordinates":[36.56449,35.61376],"type":"Point"}
}