{
  "type": "Feature",
  "properties": {
    "gn:admin1_code":"8.0",
    "gn:asciiname":"Al Ajasah",
    "gn:country_code":"SY",
    "gn:dem":703,
    "gn:feature_class":"P",
    "gn:feature_code":"PPLL",
    "gn:name":"Al Aj\u0101\u015fah",
    "gn:population":0,
    "gn:timezone":"Asia/Damascus",
    "iso:country":"SY",
    "name:ara_x_preferred":[
        "\u0627\u0644\u0627\u062c\u0627\u0635\u0629"
    ],
    "name:und_x_variant":[
        "Al Aj\u0101\u015fah"
    ],
    "wof:name":"Al Ajasah",
    "wof:placetype":"locality"
},
  "geometry": {"coordinates":[36.2249,33.44383],"type":"Point"}
}