{
  "type": "Feature",
  "properties": {
    "gn:admin1_code":"12.0",
    "gn:asciiname":"Masadah",
    "gn:country_code":"SY",
    "gn:dem":292,
    "gn:feature_class":"P",
    "gn:feature_code":"PPL",
    "gn:name":"Mas\u0101dah",
    "gn:population":0,
    "gn:timezone":"Asia/Damascus",
    "iso:country":"SY",
    "name:ara_x_preferred":[
        "\u0645\u0633\u0627\u062f\u0629"
    ],
    "name:und_x_variant":[
        "Mas\u0101dah"
    ],
    "wof:name":"Masadah",
    "wof:placetype":"locality"
},
  "geometry": {"coordinates":[37.18355,35.52157000000001],"type":"Point"}
}