{
  "type": "Feature",
  "properties": {
    "gn:admin1_code":"8.0",
    "gn:asciiname":"Ard Sharqi al Karm",
    "gn:country_code":"SY",
    "gn:dem":613,
    "gn:feature_class":"P",
    "gn:feature_code":"PPLL",
    "gn:name":"Ar\u1e11 Sharq\u012b al Karm",
    "gn:population":0,
    "gn:timezone":"Asia/Damascus",
    "iso:country":"SY",
    "name:ara_x_preferred":[
        "\u0623\u0631\u0636 \u0634\u0631\u0642\u064a \u0627\u0644\u0643\u0631\u0645"
    ],
    "name:und_x_variant":[
        "Ar\u1e11 Sharq\u012b al Karm"
    ],
    "wof:name":"Ard Sharqi al Karm",
    "wof:placetype":"locality"
},
  "geometry": {"coordinates":[36.49079,33.44505],"type":"Point"}
}