{
  "type": "Feature",
  "properties": {
    "gn:admin1_code":"14.0",
    "gn:asciiname":"Shubat",
    "gn:country_code":"SY",
    "gn:dem":264,
    "gn:feature_class":"P",
    "gn:feature_code":"PPL",
    "gn:name":"Shub\u0101\u0163",
    "gn:population":0,
    "gn:timezone":"Asia/Damascus",
    "iso:country":"SY",
    "name:ara_x_preferred":[
        "Shub\u0101\u0163"
    ],
    "name:ara_x_variant":[
        "\u0634\u0628\u0627\u0637"
    ],
    "name:und_x_variant":[
        "Chb\u00e2te"
    ],
    "wof:name":"Shubat",
    "wof:placetype":"locality"
},
  "geometry": {"coordinates":[36.00118,34.89761],"type":"Point"}
}