{
  "type": "Feature",
  "properties": {
    "gn:admin1_code":"1.0",
    "gn:asciiname":"Tulul Matlutah",
    "gn:country_code":"SY",
    "gn:dem":365,
    "gn:feature_class":"P",
    "gn:feature_code":"PPL",
    "gn:name":"Tul\u016bl Matl\u016btah",
    "gn:population":0,
    "gn:timezone":"Asia/Damascus",
    "iso:country":"SY",
    "name:ara_x_preferred":[
        "\u062a\u0644\u0648\u0644 \u0645\u062a\u0644\u0648\u062a\u0629"
    ],
    "name:tur_x_preferred":[
        "Tul\u016bl Matl\u016btah"
    ],
    "wof:name":"Tulul Matlutah",
    "wof:placetype":"locality"
},
  "geometry": {"coordinates":[41.40013,36.85105],"type":"Point"}
}