{
  "type": "Feature",
  "properties": {
    "gn:admin1_code":"10.0",
    "gn:asciiname":"Tall Mallah",
    "gn:country_code":"SY",
    "gn:dem":196,
    "gn:feature_class":"P",
    "gn:feature_code":"PPL",
    "gn:name":"Tall Mall\u0101\u1e29",
    "gn:population":0,
    "gn:timezone":"Asia/Damascus",
    "iso:country":"SY",
    "name:ara_x_preferred":[
        "\u062a\u0644 \u0645\u0644\u0627\u062d"
    ],
    "name:ara_x_variant":[
        "\u062a\u0644 \u0645\u0644\u062d"
    ],
    "name:fas_x_preferred":[
        "\u062a\u0644 \u0645\u0644\u062d"
    ],
    "name:pol_x_preferred":[
        "Tall Mallah"
    ],
    "name:und_x_variant":[
        "Ard Tell el Mal\u00e2h",
        "Tall Mall\u0101\u1e29",
        "Tall Mala\u1e29"
    ],
    "name:vie_x_preferred":[
        "Tell Malah"
    ],
    "wof:name":"Tall Mallah",
    "wof:placetype":"locality"
},
  "geometry": {"coordinates":[36.51962,35.30566],"type":"Point"}
}