{
  "type": "Feature",
  "properties": {
    "gn:admin1_code":"1.0",
    "gn:asciiname":"Murayjat",
    "gn:country_code":"SY",
    "gn:dem":610,
    "gn:feature_class":"P",
    "gn:feature_code":"PPL",
    "gn:name":"Murayj\u0101t",
    "gn:population":0,
    "gn:timezone":"Asia/Damascus",
    "iso:country":"SY",
    "name:ara_x_preferred":[
        "\u0645\u0631\u064a\u062c\u0627\u062a"
    ],
    "name:ara_x_variant":[
        "\u0627\u0644\u0645\u0631\u062c\u0627\u0646"
    ],
    "name:kur_x_preferred":[
        "\u062f\u0644\u0627\u0648\u06ce \u0643\u06d5\u0631\u0627"
    ],
    "name:und_x_variant":[
        "Delavi Guire",
        "D\u00e9lavi Kara",
        "Dalaw\u012b Karah",
        "Dil\u0101f\u012b Qarah",
        "Delaoui Guire",
        "D\u00e9lavi Kana",
        "Al Murayj\u0101t",
        "Murayj\u0101t",
        "Al Marj\u0101n",
        "Dila\u00ea Kera",
        "\u062f\u0644\u0627\u064a\u0627 \u0643\u0631\u064a"
    ],
    "wof:name":"Murayjat",
    "wof:placetype":"locality"
},
  "geometry": {"coordinates":[41.9089,37.14446],"type":"Point"}
}