{
  "type": "Feature",
  "properties": {
    "gn:admin1_code":"12.0",
    "gn:asciiname":"Rasha ash Shamaliyah",
    "gn:country_code":"SY",
    "gn:dem":706,
    "gn:feature_class":"P",
    "gn:feature_code":"PPL",
    "gn:name":"R\u0101sh\u0101 ash Sham\u0101l\u012byah",
    "gn:population":0,
    "gn:timezone":"Asia/Damascus",
    "iso:country":"SY",
    "name:ara_x_preferred":[
        "\u0631\u0627\u0634\u0627 \u0627\u0644\u0634\u0645\u0627\u0644\u064a\u0629"
    ],
    "name:und_x_variant":[
        "R\u00e2cha ech Ch\u00e9m\u00e2l\u00eey\u00e9",
        "R\u0101sh\u0101 ash Sham\u0101l\u012byah"
    ],
    "wof:name":"Rasha ash Shamaliyah",
    "wof:placetype":"locality"
},
  "geometry": {"coordinates":[36.42246,35.55233],"type":"Point"}
}