{
  "type": "Feature",
  "properties": {
    "gn:admin1_code":"2.0",
    "gn:asciiname":"Al Qubaysiyah",
    "gn:country_code":"SY",
    "gn:dem":68,
    "gn:feature_class":"P",
    "gn:feature_code":"PPL",
    "gn:name":"Al Qubays\u012byah",
    "gn:population":0,
    "gn:timezone":"Asia/Damascus",
    "iso:country":"SY",
    "name:ara_x_preferred":[
        "\u0627\u0644\u0642\u0628\u064a\u0633\u064a\u0629"
    ],
    "name:und_x_variant":[
        "Al Qubays\u012byah",
        "Al Qubaysah"
    ],
    "wof:name":"Al Qubaysiyah",
    "wof:placetype":"locality"
},
  "geometry": {"coordinates":[35.96717,35.41820999999999],"type":"Point"}
}