{
  "type": "Feature",
  "properties": {
    "gn:admin1_code":"12.0",
    "gn:asciiname":"Bitamma",
    "gn:country_code":"SY",
    "gn:dem":106,
    "gn:feature_class":"P",
    "gn:feature_code":"PPL",
    "gn:name":"Bitamm\u0101",
    "gn:population":0,
    "gn:timezone":"Asia/Damascus",
    "iso:country":"SY",
    "name:ara_x_preferred":[
        "\u0628\u062a\u0645\u0627"
    ],
    "name:und_x_variant":[
        "Bitamm\u0101",
        "Btamm\u0101"
    ],
    "wof:name":"Bitamma",
    "wof:placetype":"locality"
},
  "geometry": {"coordinates":[36.38866,36.0757],"type":"Point"}
}