{
  "type": "Feature",
  "properties": {
    "gn:admin1_code":"9.0",
    "gn:asciiname":"Jubb al Katashli",
    "gn:country_code":"SY",
    "gn:dem":462,
    "gn:feature_class":"P",
    "gn:feature_code":"PPL",
    "gn:name":"Jubb al Katashl\u012b",
    "gn:population":0,
    "gn:timezone":"Asia/Damascus",
    "iso:country":"SY",
    "name:ara_x_preferred":[
        "\u062c\u0628 \u0627\u0644\u0643\u062a\u0634\u0644\u064a"
    ],
    "name:und_x_variant":[
        "Jubb al Katashl\u012b",
        "Joubb el Ketchli",
        "Jubb al Qa\u0163ashl\u012b"
    ],
    "wof:name":"Jubb al Katashli",
    "wof:placetype":"locality"
},
  "geometry": {"coordinates":[38.01123,36.39966],"type":"Point"}
}