{
  "type": "Feature",
  "properties": {
    "gn:admin1_code":"10.0",
    "gn:asciiname":"Fakhr",
    "gn:country_code":"SY",
    "gn:dem":700,
    "gn:feature_class":"P",
    "gn:feature_code":"PPL",
    "gn:name":"Fakhr",
    "gn:population":0,
    "gn:timezone":"Asia/Damascus",
    "iso:country":"SY",
    "name:ara_x_preferred":[
        "\u0641\u062e\u0631"
    ],
    "wof:name":"Fakhr",
    "wof:placetype":"locality"
},
  "geometry": {"coordinates":[37.54709,35.07427],"type":"Point"}
}