{
  "type": "Feature",
  "properties": {
    "gn:admin1_code":"6.0",
    "gn:asciiname":"At Tabah",
    "gn:country_code":"SY",
    "gn:dem":627,
    "gn:feature_class":"P",
    "gn:feature_code":"PPL",
    "gn:name":"At Tabah",
    "gn:population":0,
    "gn:timezone":"Asia/Damascus",
    "iso:country":"SY",
    "name:ara_x_preferred":[
        "\u0627\u0644\u062a\u0628\u0629"
    ],
    "name:und_x_variant":[
        "At Tubbah",
        "At Tabah",
        "At Tabbah"
    ],
    "wof:name":"At Tabah",
    "wof:placetype":"locality"
},
  "geometry": {"coordinates":[36.39895,33.11745],"type":"Point"}
}