{
  "type": "Feature",
  "properties": {
    "gn:admin1_code":"9.0",
    "gn:asciiname":"Maklul",
    "gn:country_code":"SY",
    "gn:dem":487,
    "gn:feature_class":"P",
    "gn:feature_code":"PPL",
    "gn:name":"Makl\u016bl",
    "gn:population":0,
    "gn:timezone":"Asia/Damascus",
    "iso:country":"SY",
    "name:ara_x_preferred":[
        "\u0645\u0643\u0644\u0648\u0644"
    ],
    "name:ara_x_variant":[
        "\u0645\u063a\u0644\u0648\u0644"
    ],
    "name:und_x_variant":[
        "Marhlo\u00fbl",
        "Maglol",
        "Maghl\u016bl",
        "Makl\u016bl"
    ],
    "wof:name":"Maklul",
    "wof:placetype":"locality"
},
  "geometry": {"coordinates":[38.38333,36.88162],"type":"Point"}
}