{
  "type": "Feature",
  "properties": {
    "gn:admin1_code":"3.0",
    "gn:asciiname":"`Ayn al Qadi",
    "gn:country_code":"SY",
    "gn:dem":563,
    "gn:feature_class":"P",
    "gn:feature_code":"PPL",
    "gn:name":"\u2018Ayn al Q\u0101\u1e11\u012b",
    "gn:population":0,
    "gn:timezone":"Asia/Damascus",
    "iso:country":"SY",
    "name:ara_x_preferred":[
        "\u0639\u064a\u0646 \u0627\u0644\u0642\u0627\u0636\u064a"
    ],
    "name:und_x_variant":[
        "\u2018Ayn al Q\u0101\u1e11\u012b"
    ],
    "wof:name":"`Ayn al Qadi",
    "wof:placetype":"locality"
},
  "geometry": {"coordinates":[35.87774,32.89987],"type":"Point"}
}