{
  "type": "Feature",
  "properties": {
    "gn:admin1_code":"9.0",
    "gn:asciiname":"Ghajar Tahtani",
    "gn:country_code":"SY",
    "gn:dem":520,
    "gn:feature_class":"P",
    "gn:feature_code":"PPL",
    "gn:name":"Ghajar Ta\u1e29t\u0101n\u012b",
    "gn:population":0,
    "gn:timezone":"Asia/Damascus",
    "iso:country":"SY",
    "name:ara_x_preferred":[
        "\u063a\u062c\u0631 \u062a\u062d\u062a\u0627\u0646\u064a"
    ],
    "name:und_x_variant":[
        "Rhajar Taht\u00e2ni",
        "Ghajar at Ta\u1e29t\u0101n\u012b",
        "Ghajar Ta\u1e29t\u0101n\u012b"
    ],
    "wof:name":"Ghajar Tahtani",
    "wof:placetype":"locality"
},
  "geometry": {"coordinates":[38.44143,36.67809000000001],"type":"Point"}
}