{
  "type": "Feature",
  "properties": {
    "gn:admin1_code":"1.0",
    "gn:asciiname":"Kahfat Saghir",
    "gn:country_code":"SY",
    "gn:dem":281,
    "gn:feature_class":"P",
    "gn:feature_code":"PPL",
    "gn:name":"Kahf\u0101t \u015eagh\u012br",
    "gn:population":0,
    "gn:timezone":"Asia/Damascus",
    "iso:country":"SY",
    "name:ara_x_preferred":[
        "\u0643\u0647\u0641\u0627\u062a \u0635\u063a\u064a\u0631"
    ],
    "name:und_x_variant":[
        "Kahf\u0101t \u015eagh\u012br"
    ],
    "wof:name":"Kahfat Saghir",
    "wof:placetype":"locality"
},
  "geometry": {"coordinates":[40.64457,36.15293],"type":"Point"}
}