{
  "type": "Feature",
  "properties": {
    "gn:admin1_code":"14.0",
    "gn:asciiname":"Wadi al Mas",
    "gn:country_code":"SY",
    "gn:dem":191,
    "gn:feature_class":"P",
    "gn:feature_code":"PPL",
    "gn:name":"W\u0101d\u012b al M\u0101s",
    "gn:population":0,
    "gn:timezone":"Asia/Damascus",
    "iso:country":"SY",
    "name:ara_x_preferred":[
        "\u0648\u0627\u062f\u064a \u0627\u0644\u0645\u0627\u0633"
    ],
    "name:ara_x_variant":[
        "\u0648\u0627\u062f\u064a \u0627\u0644\u0645\u064a\u0633"
    ],
    "name:und_x_variant":[
        "Ou\u00e2di el Me\u00efss",
        "Ou\u00e2di el Miess",
        "W\u0101d\u012b al M\u012bs",
        "W\u0101d\u012b al M\u0101s",
        "W\u0101d\u012b al Mays"
    ],
    "wof:name":"Wadi al Mas",
    "wof:placetype":"locality"
},
  "geometry": {"coordinates":[36.07729000000001,34.72724],"type":"Point"}
}