{
  "type": "Feature",
  "properties": {
    "gn:admin1_code":"10.0",
    "gn:asciiname":"Ash Shihah",
    "gn:country_code":"SY",
    "gn:dem":300,
    "gn:feature_class":"P",
    "gn:feature_code":"PPL",
    "gn:name":"Ash Sh\u012b\u1e29ah",
    "gn:population":0,
    "gn:timezone":"Asia/Damascus",
    "iso:country":"SY",
    "name:ara_x_preferred":[
        "\u0627\u0644\u0634\u064a\u062d\u0629"
    ],
    "name:und_x_variant":[
        "Ech Ch\u00eeha",
        "Chiha",
        "Ash Sh\u012b\u1e29ah"
    ],
    "wof:name":"Ash Shihah",
    "wof:placetype":"locality"
},
  "geometry": {"coordinates":[36.68449,35.15507],"type":"Point"}
}