{
  "type": "Feature",
  "properties": {
    "gn:admin1_code":"9.0",
    "gn:asciiname":"Al Ghuz",
    "gn:country_code":"SY",
    "gn:dem":477,
    "gn:feature_class":"P",
    "gn:feature_code":"PPL",
    "gn:name":"Al Gh\u016bz",
    "gn:population":0,
    "gn:timezone":"Asia/Damascus",
    "iso:country":"SY",
    "name:ara_x_preferred":[
        "Gh\u016bz"
    ],
    "name:ara_x_variant":[
        "Al Gh\u016bz",
        "\u0627\u0644\u063a\u0648\u0632"
    ],
    "name:und_x_variant":[
        "Rho\u00fbz",
        "Ghouz",
        "Gh\u016bz"
    ],
    "wof:name":"Al Ghuz",
    "wof:placetype":"locality"
},
  "geometry": {"coordinates":[37.29282,36.46587],"type":"Point"}
}