{
  "type": "Feature",
  "properties": {
    "gn:admin1_code":"2.0",
    "gn:asciiname":"Karm al Halwani",
    "gn:country_code":"SY",
    "gn:dem":687,
    "gn:feature_class":"P",
    "gn:feature_code":"PPL",
    "gn:name":"Karm al \u1e28alw\u0101n\u012b",
    "gn:population":0,
    "gn:timezone":"Asia/Damascus",
    "iso:country":"SY",
    "name:und_x_variant":[
        "Karm el H\u00e9lou\u00e2ni",
        "Karm al \u1e28alw\u0101n\u012b"
    ],
    "wof:name":"Karm al Halwani",
    "wof:placetype":"locality"
},
  "geometry": {"coordinates":[36.08333,35.512],"type":"Point"}
}