{
  "type": "Feature",
  "properties": {
    "gn:admin1_code":"2.0",
    "gn:asciiname":"Jinkil",
    "gn:country_code":"SY",
    "gn:dem":463,
    "gn:feature_class":"P",
    "gn:feature_code":"PPL",
    "gn:name":"Jink\u012bl",
    "gn:population":0,
    "gn:timezone":"Asia/Damascus",
    "iso:country":"SY",
    "name:ara_x_preferred":[
        "Jink\u012bl"
    ],
    "name:ara_x_variant":[
        "\u062c\u0646\u0643\u064a\u0644"
    ],
    "name:und_x_variant":[
        "Jinnk\u00eel"
    ],
    "wof:name":"Jinkil",
    "wof:placetype":"locality"
},
  "geometry": {"coordinates":[36.0536,35.62166],"type":"Point"}
}