{
  "type": "Feature",
  "properties": {
    "gn:admin1_code":"1.0",
    "gn:asciiname":"Khirbat `Ashur",
    "gn:country_code":"SY",
    "gn:dem":357,
    "gn:feature_class":"P",
    "gn:feature_code":"PPL",
    "gn:name":"Khirbat \u2018\u0100sh\u016br",
    "gn:population":0,
    "gn:timezone":"Asia/Damascus",
    "iso:country":"SY",
    "name:ara_x_preferred":[
        "\u062e\u0631\u0628\u0629 \u0639\u0627\u0634\u0648\u0631"
    ],
    "name:tur_x_preferred":[
        "Khirbat \u2018\u0100sh\u016br"
    ],
    "name:und_x_variant":[
        "Kheurbet Aacho\u00fbr"
    ],
    "wof:name":"Khirbat `Ashur",
    "wof:placetype":"locality"
},
  "geometry": {"coordinates":[40.74667,36.74833],"type":"Point"}
}