{
  "type": "Feature",
  "properties": {
    "gn:admin1_code":"9.0",
    "gn:asciiname":"Abu Jadhah `Atiq",
    "gn:country_code":"SY",
    "gn:dem":417,
    "gn:feature_class":"P",
    "gn:feature_code":"PPL",
    "gn:name":"Ab\u016b Jadhah \u2018At\u012bq",
    "gn:population":0,
    "gn:timezone":"Asia/Damascus",
    "iso:country":"SY",
    "name:ara_x_preferred":[
        "\u0623\u0628\u0648 \u062c\u062f\u062d\u0629 \u0639\u062a\u064a\u0642"
    ],
    "name:und_x_variant":[
        "Abou Jadha Serh\u00eer",
        "Abou Djedkha Sghire",
        "Abou Jadha Aat\u00eeq",
        "Ab\u016b Jadhah \u2018At\u012bq"
    ],
    "wof:name":"Abu Jadhah `Atiq",
    "wof:placetype":"locality"
},
  "geometry": {"coordinates":[37.85392,36.25991],"type":"Point"}
}