{
  "type": "Feature",
  "properties": {
    "gn:admin1_code":"1.0",
    "gn:asciiname":"Abu Bakr",
    "gn:country_code":"SY",
    "gn:dem":538,
    "gn:feature_class":"P",
    "gn:feature_code":"PPL",
    "gn:name":"Ab\u016b Bakr",
    "gn:population":0,
    "gn:timezone":"Asia/Damascus",
    "iso:country":"SY",
    "name:ara_x_preferred":[
        "\u0623\u0628\u0648 \u0628\u0643\u0631"
    ],
    "name:kur_x_preferred":[
        "Bekir Oghl\u00ee"
    ],
    "name:kur_x_variant":[
        "\u0628\u06d5\u0643\u0631 \u0626\u06c6\u063a\u0644\u0649"
    ],
    "name:und_x_variant":[
        "Bakar Orhlou",
        "Ab\u016b Bakr",
        "Bekir Oxl\u00ee",
        "\u0628\u0643\u0631 \u0623\u0648\u063a\u0644\u064a"
    ],
    "wof:name":"Abu Bakr",
    "wof:placetype":"locality"
},
  "geometry": {"coordinates":[41.81385,37.07538],"type":"Point"}
}