{
  "type": "Feature",
  "properties": {
    "gn:admin1_code":"10.0",
    "gn:asciiname":"Tammazah",
    "gn:country_code":"SY",
    "gn:dem":1042,
    "gn:feature_class":"P",
    "gn:feature_code":"PPL",
    "gn:name":"Tamm\u0101zah",
    "gn:population":0,
    "gn:timezone":"Asia/Damascus",
    "iso:country":"SY",
    "name:ara_x_preferred":[
        "\u062a\u0645\u0627\u0632\u0629"
    ],
    "name:und_x_variant":[
        "Ett Temm\u00e2z\u00e9",
        "Et Temm\u00e2z\u00e9",
        "At Tamm\u0101zah",
        "Tamm\u0101zah"
    ],
    "wof:name":"Tammazah",
    "wof:placetype":"locality"
},
  "geometry": {"coordinates":[36.25232000000001,35.26758],"type":"Point"}
}