{
  "type": "Feature",
  "properties": {
    "gn:admin1_code":"12.0",
    "gn:asciiname":"Batintah",
    "gn:country_code":"SY",
    "gn:dem":365,
    "gn:feature_class":"P",
    "gn:feature_code":"PPL",
    "gn:name":"B\u0101tintah",
    "gn:population":0,
    "gn:timezone":"Asia/Damascus",
    "iso:country":"SY",
    "name:und_x_variant":[
        "B\u0101tintah",
        "\u0628\u0627\u062a\u0646\u062a\u0629"
    ],
    "wof:name":"Batintah",
    "wof:placetype":"locality"
},
  "geometry": {"coordinates":[36.63322,36.0072],"type":"Point"}
}