{
  "type": "Feature",
  "properties": {
    "gn:admin1_code":"1.0",
    "gn:asciiname":"Uwayjiyan",
    "gn:country_code":"SY",
    "gn:dem":471,
    "gn:feature_class":"P",
    "gn:feature_code":"PPL",
    "gn:name":"Uwayj\u0131y\u0101n",
    "gn:population":0,
    "gn:timezone":"Asia/Damascus",
    "iso:country":"SY",
    "name:ara_x_preferred":[
        "\u0627\u0648\u064a\u062c\u064a\u0627\u0646"
    ],
    "name:tur_x_preferred":[
        "Uwayj\u0131y\u0101n"
    ],
    "wof:name":"Uwayjiyan",
    "wof:placetype":"locality"
},
  "geometry": {"coordinates":[41.02361,37.07745],"type":"Point"}
}