{
  "type": "Feature",
  "properties": {
    "gn:admin1_code":"12.0",
    "gn:asciiname":"Tall al Fukhkhar",
    "gn:country_code":"SY",
    "gn:dem":252,
    "gn:feature_class":"P",
    "gn:feature_code":"PPL",
    "gn:name":"Tall al Fukhkh\u0101r",
    "gn:population":0,
    "gn:timezone":"Asia/Damascus",
    "iso:country":"SY",
    "name:ara_x_preferred":[
        "\u062a\u0644 \u0627\u0644\u0641\u062e\u0627\u0631"
    ],
    "name:und_x_variant":[
        "Tell el Foukh\u00e2r",
        "Tall al Fukhkh\u0101r"
    ],
    "wof:name":"Tall al Fukhkhar",
    "wof:placetype":"locality"
},
  "geometry": {"coordinates":[37.0399,35.83038],"type":"Point"}
}