{
  "type": "Feature",
  "properties": {
    "gn:admin1_code":"9.0",
    "gn:asciiname":"Al Jubah",
    "gn:country_code":"SY",
    "gn:dem":552,
    "gn:feature_class":"P",
    "gn:feature_code":"PPL",
    "gn:name":"Al J\u016bbah",
    "gn:population":0,
    "gn:timezone":"Asia/Damascus",
    "iso:country":"SY",
    "name:ara_x_preferred":[
        "\u062c\u0628\u0629"
    ],
    "name:ara_x_variant":[
        "\u0627\u0644\u062c\u0648\u0628\u0629"
    ],
    "name:und_x_variant":[
        "Djoubi",
        "Jo\u00fbb\u00e9",
        "J\u016bbah",
        "Jubbah",
        "Al J\u016bbah"
    ],
    "wof:name":"Al Jubah",
    "wof:placetype":"locality"
},
  "geometry": {"coordinates":[37.33783,36.36733],"type":"Point"}
}