{
  "type": "Feature",
  "properties": {
    "gn:admin1_code":"11.0",
    "gn:asciiname":"Al Jabbat",
    "gn:country_code":"SY",
    "gn:dem":668,
    "gn:feature_class":"P",
    "gn:feature_code":"PPL",
    "gn:name":"Al Jabb\u0101t",
    "gn:population":0,
    "gn:timezone":"Asia/Damascus",
    "iso:country":"SY",
    "name:ara_x_preferred":[
        "\u0627\u0644\u062c\u0628\u0627\u062a"
    ],
    "name:und_x_variant":[
        "Al Jabb\u0101t"
    ],
    "wof:name":"Al Jabbat",
    "wof:placetype":"locality"
},
  "geometry": {"coordinates":[37.28525,34.38652],"type":"Point"}
}