{
  "type": "Feature",
  "properties": {
    "gn:admin1_code":"2.0",
    "gn:asciiname":"Hurayshah",
    "gn:cc2":"SY",
    "gn:country_code":"SY",
    "gn:dem":956,
    "gn:feature_class":"P",
    "gn:feature_code":"PPL",
    "gn:name":"\u1e28urayshah",
    "gn:population":0,
    "gn:timezone":"Asia/Damascus",
    "iso:country":"SY",
    "name:und_x_variant":[
        "Hra\u00efch\u00e9",
        "\u1e28urayshah"
    ],
    "wof:name":"Hurayshah",
    "wof:placetype":"locality"
},
  "geometry": {"coordinates":[36.16667,35.65],"type":"Point"}
}