{
  "type": "Feature",
  "properties": {
    "gn:admin1_code":"8.0",
    "gn:asciiname":"Ard al Kharut",
    "gn:country_code":"SY",
    "gn:dem":603,
    "gn:feature_class":"P",
    "gn:feature_code":"PPLL",
    "gn:name":"Ar\u1e11 al Kh\u0101r\u016b\u0163",
    "gn:population":0,
    "gn:timezone":"Asia/Damascus",
    "iso:country":"SY",
    "name:ara_x_preferred":[
        "\u0623\u0631\u0636 \u0627\u0644\u062e\u0627\u0631\u0648\u0637"
    ],
    "name:und_x_variant":[
        "Ar\u1e11 al Kh\u0101r\u016b\u0163"
    ],
    "wof:name":"Ard al Kharut",
    "wof:placetype":"locality"
},
  "geometry": {"coordinates":[36.59036,33.48971],"type":"Point"}
}