{
  "type": "Feature",
  "properties": {
    "gn:admin1_code":"13.0",
    "gn:asciiname":"Mukhayyam al Yarmuk",
    "gn:country_code":"SY",
    "gn:dem":684,
    "gn:feature_class":"P",
    "gn:feature_code":"PPL",
    "gn:name":"Mukhayyam al Yarm\u016bk",
    "gn:population":0,
    "gn:timezone":"Asia/Damascus",
    "iso:country":"SY",
    "name:ara_x_preferred":[
        "\u0645\u062e\u064a\u0645 \u0627\u0644\u064a\u0631\u0645\u0648\u0643"
    ],
    "name:ara_x_variant":[
        "\u0627\u0644\u064a\u0631\u0645\u0648\u0643"
    ],
    "name:und_x_variant":[
        "Mokhayam Al-Yarmouk Camp",
        "Mukhayam Yarmouk",
        "Mokhayam Yarmouk",
        "Mukhayyam al Yarm\u016bk",
        "Al Yarm\u016bk"
    ],
    "wof:name":"Mukhayyam al Yarmuk",
    "wof:placetype":"locality"
},
  "geometry": {"coordinates":[36.3018,33.4699],"type":"Point"}
}