{
  "type": "Feature",
  "properties": {
    "gn:admin1_code":"1.0",
    "gn:asciiname":"Dabbanah",
    "gn:country_code":"SY",
    "gn:dem":424,
    "gn:feature_class":"P",
    "gn:feature_code":"PPL",
    "gn:name":"Dabb\u0101nah",
    "gn:population":0,
    "gn:timezone":"Asia/Damascus",
    "iso:country":"SY",
    "name:ara_x_preferred":[
        "\u062f\u0628\u0627\u0646\u0629"
    ],
    "name:tur_x_preferred":[
        "Dabb\u0101nah"
    ],
    "name:und_x_variant":[
        "Dabb\u00e2n\u00e9"
    ],
    "wof:name":"Dabbanah",
    "wof:placetype":"locality"
},
  "geometry": {"coordinates":[41.26502,36.99541],"type":"Point"}
}