{
  "type": "Feature",
  "properties": {
    "gn:admin1_code":"12.0",
    "gn:asciiname":"Ash Sharafiyah",
    "gn:country_code":"SY",
    "gn:dem":92,
    "gn:feature_class":"P",
    "gn:feature_code":"PPL",
    "gn:name":"Ash Sharaf\u012byah",
    "gn:population":0,
    "gn:timezone":"Asia/Damascus",
    "iso:country":"SY",
    "name:ara_x_preferred":[
        "\u0627\u0644\u0634\u0631\u0641\u064a\u0629"
    ],
    "name:und_x_variant":[
        "Ash Sharaf\u012byah"
    ],
    "wof:name":"Ash Sharafiyah",
    "wof:placetype":"locality"
},
  "geometry": {"coordinates":[36.39087,36.21667],"type":"Point"}
}