{
  "type": "Feature",
  "properties": {
    "gn:admin1_code":"12.0",
    "gn:asciiname":"Kafr `Ayn",
    "gn:country_code":"SY",
    "gn:dem":363,
    "gn:feature_class":"P",
    "gn:feature_code":"PPL",
    "gn:name":"Kafr \u2018Ayn",
    "gn:population":0,
    "gn:timezone":"Asia/Damascus",
    "iso:country":"SY",
    "name:ara_x_preferred":[
        "\u0643\u0641\u0631 \u0639\u064a\u0646"
    ],
    "name:und_x_variant":[
        "Kafer A\u00efn",
        "Kafr \u2018Ayn"
    ],
    "wof:name":"Kafr `Ayn",
    "wof:placetype":"locality"
},
  "geometry": {"coordinates":[36.56657,35.44494],"type":"Point"}
}