{
  "type": "Feature",
  "properties": {
    "gn:admin1_code":"9.0",
    "gn:asciiname":"Jaqalli Jum",
    "gn:country_code":"SY",
    "gn:dem":413,
    "gn:feature_class":"P",
    "gn:feature_code":"PPL",
    "gn:name":"Jaq\u0101ll\u012b J\u016bm",
    "gn:population":0,
    "gn:timezone":"Asia/Damascus",
    "iso:country":"SY",
    "name:ara_x_preferred":[
        "\u062c\u0642\u0627\u0644\u0644\u0648 \u0627\u0644\u062c\u0648\u0645"
    ],
    "name:ara_x_variant":[
        "\u062c\u0642\u0627\u0644\u0644\u064a \u062c\u0648\u0645"
    ],
    "name:und_x_variant":[
        "Jaq\u0101ll\u016b al J\u016bm",
        "Jaq\u0101ll\u012b J\u016bm",
        "Tchaq\u00e2lleu ej Jo\u00fbm",
        "Jaq\u0101 Lill\u016b al J\u016bm"
    ],
    "wof:name":"Jaqalli Jum",
    "wof:placetype":"locality"
},
  "geometry": {"coordinates":[36.71285,36.45283],"type":"Point"}
}