{
  "type": "Feature",
  "properties": {
    "gn:admin1_code":"1.0",
    "gn:asciiname":"Jihad",
    "gn:country_code":"SY",
    "gn:dem":303,
    "gn:feature_class":"P",
    "gn:feature_code":"PPL",
    "gn:name":"Jih\u0101d",
    "gn:population":0,
    "gn:timezone":"Asia/Damascus",
    "iso:country":"SY",
    "name:ara_x_preferred":[
        "\u062c\u0647\u0627\u062f"
    ],
    "name:und_x_variant":[
        "Jih\u0101d"
    ],
    "wof:name":"Jihad",
    "wof:placetype":"locality"
},
  "geometry": {"coordinates":[40.54904000000001,35.89335999999999],"type":"Point"}
}