{
  "type": "Feature",
  "properties": {
    "gn:admin1_code":"10.0",
    "gn:asciiname":"Khanazir",
    "gn:country_code":"SY",
    "gn:dem":214,
    "gn:feature_class":"P",
    "gn:feature_code":"PPL",
    "gn:name":"Khan\u0101z\u012br",
    "gn:population":0,
    "gn:timezone":"Asia/Damascus",
    "iso:country":"SY",
    "name:ara_x_preferred":[
        "\u062e\u0646\u0627\u0632\u064a\u0631"
    ],
    "name:ara_x_variant":[
        "\u062e\u0631\u0628\u0629 \u062e\u0646\u0632\u064a\u0631",
        "\u062e\u0646\u0632\u064a\u0631",
        "\u0627\u0644\u0623\u0634\u0631\u0641\u064a\u0629 \u062e\u0646\u0627\u0632\u064a\u0631"
    ],
    "name:fas_x_preferred":[
        "\u0627\u0634\u0631\u0641\u06cc\u0647 \u062e\u0646\u0627\u0632\u06cc\u0631"
    ],
    "name:und_x_variant":[
        "Khan\u00e2z\u00eer",
        "Al Khan\u0101z\u012br",
        "Khan\u0101z\u012br",
        "Khirbat Khanz\u012br",
        "Khanz\u012br"
    ],
    "name:vie_x_preferred":[
        "Khanazir"
    ],
    "wof:name":"Khanazir",
    "wof:placetype":"locality"
},
  "geometry": {"coordinates":[36.53172,35.24856],"type":"Point"}
}