{
  "type": "Feature",
  "properties": {
    "gn:admin1_code":"10.0",
    "gn:asciiname":"`Amqiyah",
    "gn:country_code":"SY",
    "gn:dem":171,
    "gn:feature_class":"P",
    "gn:feature_code":"PPL",
    "gn:name":"\u2018Amq\u012byah",
    "gn:population":0,
    "gn:timezone":"Asia/Damascus",
    "iso:country":"SY",
    "name:ara_x_preferred":[
        "\u0639\u0645\u0642\u064a\u0629"
    ],
    "name:und_x_variant":[
        "\u2018Amqiya",
        "Aamqiy\u00e9",
        "Amkiy\u00e9",
        "\u2018Amq\u012bye",
        "A\u2018maq\u012byah",
        "Al \u2018Amq\u012byah",
        "\u2018Amq\u012byah"
    ],
    "wof:name":"`Amqiyah",
    "wof:placetype":"locality"
},
  "geometry": {"coordinates":[36.38226,35.57299000000001],"type":"Point"}
}