{
  "type": "Feature",
  "properties": {
    "gn:admin1_code":"9.0",
    "gn:asciiname":"Qibab Abu Qalqal",
    "gn:country_code":"SY",
    "gn:dem":449,
    "gn:feature_class":"P",
    "gn:feature_code":"PPL",
    "gn:name":"Qib\u0101b Ab\u016b Qalqal",
    "gn:population":0,
    "gn:timezone":"Asia/Damascus",
    "iso:country":"SY",
    "name:ara_x_preferred":[
        "Qib\u0101b"
    ],
    "name:ara_x_variant":[
        "\u0642\u0628\u0627\u0628 \u0623\u0628\u0648 \u0642\u0644\u0642\u0644"
    ],
    "name:und_x_variant":[
        "Qoub\u00e2b abou Qalqal",
        "Qib\u0101b Ab\u016b Qalqal"
    ],
    "wof:name":"Qibab Abu Qalqal",
    "wof:placetype":"locality"
},
  "geometry": {"coordinates":[38.04429,36.43925],"type":"Point"}
}