{
  "type": "Feature",
  "properties": {
    "gn:admin1_code":"5.0",
    "gn:asciiname":"Rimat al Luhuf",
    "gn:country_code":"SY",
    "gn:dem":861,
    "gn:feature_class":"P",
    "gn:feature_code":"PPL",
    "gn:name":"R\u012bmat al Lu\u1e29uf",
    "gn:population":0,
    "gn:timezone":"Asia/Damascus",
    "iso:country":"SY",
    "name:ara_x_preferred":[
        "\u0631\u064a\u0645\u0629 \u0627\u0644\u0644\u062d\u0641"
    ],
    "name:und_x_variant":[
        "R\u00eemet el Lof",
        "Rimet el Foukhour",
        "R\u00eemet el Fokho\u00fbr",
        "R\u012bmat al Fakh\u016br",
        "R\u012bmat al Lu\u1e29uf"
    ],
    "wof:name":"Rimat al Luhuf",
    "wof:placetype":"locality"
},
  "geometry": {"coordinates":[36.52387,32.83385],"type":"Point"}
}