{
  "type": "Feature",
  "properties": {
    "gn:admin1_code":"9.0",
    "gn:asciiname":"`Ajjurah",
    "gn:country_code":"SY",
    "gn:dem":355,
    "gn:feature_class":"P",
    "gn:feature_code":"PPL",
    "gn:name":"\u2018Ajj\u016brah",
    "gn:population":0,
    "gn:timezone":"Asia/Damascus",
    "iso:country":"SY",
    "name:ara_x_preferred":[
        "\u0639\u062c\u0648\u0631\u0629"
    ],
    "name:und_x_variant":[
        "Djerah",
        "Al Jarah",
        "Jir\u0101h",
        "Aajjo\u00fbra",
        "\u2018Ajj\u016brah"
    ],
    "wof:name":"`Ajjurah",
    "wof:placetype":"locality"
},
  "geometry": {"coordinates":[37.91875,36.09377],"type":"Point"}
}