{
  "type": "Feature",
  "properties": {
    "gn:admin1_code":"9.0",
    "gn:asciiname":"Abu Hasan",
    "gn:cc2":"SY",
    "gn:country_code":"SY",
    "gn:dem":302,
    "gn:feature_class":"P",
    "gn:feature_code":"PPL",
    "gn:name":"Ab\u016b \u1e28asan",
    "gn:population":0,
    "gn:timezone":"Asia/Damascus",
    "iso:country":"SY",
    "name:und_x_variant":[
        "Abou Hassane",
        "Ab\u016b \u1e28asan"
    ],
    "wof:name":"Abu Hasan",
    "wof:placetype":"locality"
},
  "geometry": {"coordinates":[38.15,35.95],"type":"Point"}
}