{
  "type": "Feature",
  "properties": {
    "gn:admin1_code":"12.0",
    "gn:asciiname":"Luksin",
    "gn:country_code":"SY",
    "gn:dem":459,
    "gn:feature_class":"P",
    "gn:feature_code":"PPL",
    "gn:name":"L\u016bks\u012bn",
    "gn:population":0,
    "gn:timezone":"Asia/Damascus",
    "iso:country":"SY",
    "name:ara_x_preferred":[
        "Luks\u012bn"
    ],
    "name:ara_x_variant":[
        "L\u016bks\u012bn",
        "\u0644\u0648\u0643\u0633\u064a\u0646"
    ],
    "name:und_x_variant":[
        "Louks\u00eene"
    ],
    "wof:name":"Luksin",
    "wof:placetype":"locality"
},
  "geometry": {"coordinates":[36.31432,35.94258],"type":"Point"}
}