{
  "type": "Feature",
  "properties": {
    "gn:admin1_code":"12.0",
    "gn:asciiname":"Kafr Mid",
    "gn:country_code":"SY",
    "gn:dem":243,
    "gn:feature_class":"P",
    "gn:feature_code":"PPL",
    "gn:name":"Kafr M\u012bd",
    "gn:population":0,
    "gn:timezone":"Asia/Damascus",
    "iso:country":"SY",
    "name:ara_x_preferred":[
        "\u0643\u0641\u0631 \u0645\u064a\u062f"
    ],
    "name:und_x_variant":[
        "Kafer M\u00eed",
        "Kafr M\u012bd"
    ],
    "wof:name":"Kafr Mid",
    "wof:placetype":"locality"
},
  "geometry": {"coordinates":[36.44092,35.80526],"type":"Point"}
}