{
  "type": "Feature",
  "properties": {
    "gn:admin1_code":"9.0",
    "gn:asciiname":"Al Jumrukiyah",
    "gn:country_code":"SY",
    "gn:dem":406,
    "gn:feature_class":"P",
    "gn:feature_code":"PPL",
    "gn:name":"Al Jumruk\u012byah",
    "gn:population":0,
    "gn:timezone":"Asia/Damascus",
    "iso:country":"SY",
    "name:ara_x_preferred":[
        "K\u016bj\u0101k\u012b"
    ],
    "name:ara_x_variant":[
        "\u0643\u0648\u062c\u0627\u0643\u064a",
        "\u0627\u0644\u062c\u0645\u0631\u0643\u064a\u0629"
    ],
    "name:und_x_variant":[
        "Al Jumruk\u012byah"
    ],
    "wof:name":"Al Jumrukiyah",
    "wof:placetype":"locality"
},
  "geometry": {"coordinates":[36.83846,36.61924000000001],"type":"Point"}
}