{
  "type": "Feature",
  "properties": {
    "gn:admin1_code":"1.0",
    "gn:asciiname":"Rajr",
    "gn:country_code":"SY",
    "gn:dem":312,
    "gn:feature_class":"P",
    "gn:feature_code":"PPL",
    "gn:name":"Rajr",
    "gn:population":0,
    "gn:timezone":"Asia/Damascus",
    "iso:country":"SY",
    "name:ara_x_preferred":[
        "\u0631\u062c\u0631"
    ],
    "wof:name":"Rajr",
    "wof:placetype":"locality"
},
  "geometry": {"coordinates":[40.57682,36.15614],"type":"Point"}
}