{
  "type": "Feature",
  "properties": {
    "gn:admin1_code":"11.0",
    "gn:asciiname":"Umm Haratayn",
    "gn:country_code":"SY",
    "gn:dem":531,
    "gn:feature_class":"P",
    "gn:feature_code":"PPL",
    "gn:name":"Umm \u1e28\u0101ratayn",
    "gn:population":0,
    "gn:timezone":"Asia/Damascus",
    "iso:country":"SY",
    "name:ara_x_preferred":[
        "\u0623\u0645 \u062d\u0627\u0631\u062a\u064a\u0646"
    ],
    "name:und_x_variant":[
        "Oumm Harte\u00efn",
        "Oum H\u00e2rta\u00efne",
        "Oumm H\u00e2rta\u00efne",
        "Umm \u1e28\u0101ratayn"
    ],
    "wof:name":"Umm Haratayn",
    "wof:placetype":"locality"
},
  "geometry": {"coordinates":[36.45475,34.58235],"type":"Point"}
}