{
  "type": "Feature",
  "properties": {
    "gn:admin1_code":"10.0",
    "gn:asciiname":"Bshinnin",
    "gn:country_code":"SY",
    "gn:dem":708,
    "gn:feature_class":"P",
    "gn:feature_code":"PPL",
    "gn:name":"Bshinn\u012bn",
    "gn:population":0,
    "gn:timezone":"Asia/Damascus",
    "iso:country":"SY",
    "name:ara_x_preferred":[
        "Bshinn\u012bn"
    ],
    "name:ara_x_variant":[
        "\u0628\u0634\u0646\u064a\u0646"
    ],
    "name:und_x_variant":[
        "Bchenn\u00eene",
        "Bishann\u012bn",
        "Bishinn\u012bn"
    ],
    "wof:name":"Bshinnin",
    "wof:placetype":"locality"
},
  "geometry": {"coordinates":[36.36998,34.9034],"type":"Point"}
}