{
  "type": "Feature",
  "properties": {
    "gn:admin1_code":"9.0",
    "gn:asciiname":"Houlilo",
    "gn:country_code":"SY",
    "gn:dem":717,
    "gn:feature_class":"P",
    "gn:feature_code":"PPL",
    "gn:name":"Houlilo",
    "gn:population":0,
    "gn:timezone":"Asia/Damascus",
    "iso:country":"SY",
    "name:ara_x_preferred":[
        "Hul\u012bl\u016b"
    ],
    "name:ara_x_variant":[
        "\u0647\u0648\u0644\u064a\u0644\u0648",
        "\u0647\u0644\u064a\u0644"
    ],
    "name:und_x_variant":[
        "Hol\u00eelo",
        "H\u016bl\u012bl\u016b",
        "Hul\u012bl",
        "Hal\u012bl"
    ],
    "wof:name":"Houlilo",
    "wof:placetype":"locality"
},
  "geometry": {"coordinates":[36.69456,36.69058],"type":"Point"}
}