{
  "type": "Feature",
  "properties": {
    "gn:admin1_code":"10.0",
    "gn:asciiname":"Qisraya",
    "gn:country_code":"SY",
    "gn:dem":534,
    "gn:feature_class":"P",
    "gn:feature_code":"PPL",
    "gn:name":"Qi\u015fr\u0101y\u0101",
    "gn:population":0,
    "gn:timezone":"Asia/Damascus",
    "iso:country":"SY",
    "name:ara_x_preferred":[
        "Qi\u015fr\u0101y\u0101"
    ],
    "name:ara_x_variant":[
        "\u0642\u0635\u0631\u0627\u064a\u0627"
    ],
    "name:und_x_variant":[
        "Qisr\u00e2ya"
    ],
    "wof:name":"Qisraya",
    "wof:placetype":"locality"
},
  "geometry": {"coordinates":[36.41244,34.88743],"type":"Point"}
}