{
  "type": "Feature",
  "properties": {
    "gn:admin1_code":"2.0",
    "gn:asciiname":"`Uzayrah",
    "gn:country_code":"SY",
    "gn:dem":622,
    "gn:feature_class":"P",
    "gn:feature_code":"PPL",
    "gn:name":"\u2018Uzayrah",
    "gn:population":0,
    "gn:timezone":"Asia/Damascus",
    "iso:country":"SY",
    "name:ara_x_preferred":[
        "\u0639\u0632\u064a\u0631\u0629"
    ],
    "name:und_x_variant":[
        "Aaze\u00efr\u00e9",
        "\u0100ze\u00efra",
        "Al \u2018Uzayr\u012b",
        "\u2018Uzayrah"
    ],
    "wof:name":"`Uzayrah",
    "wof:placetype":"locality"
},
  "geometry": {"coordinates":[36.10788,35.48246],"type":"Point"}
}