{
  "type": "Feature",
  "properties": {
    "gn:admin1_code":"1.0",
    "gn:asciiname":"Bilaliyah",
    "gn:country_code":"SY",
    "gn:dem":245,
    "gn:feature_class":"P",
    "gn:feature_code":"PPL",
    "gn:name":"Bil\u0101l\u012byah",
    "gn:population":0,
    "gn:timezone":"Asia/Damascus",
    "iso:country":"SY",
    "name:ara_x_preferred":[
        "\u0628\u0644\u0627\u0644\u064a\u0629"
    ],
    "name:und_x_variant":[
        "Bil\u0101l\u012byah"
    ],
    "wof:name":"Bilaliyah",
    "wof:placetype":"locality"
},
  "geometry": {"coordinates":[40.84199,35.80028],"type":"Point"}
}