{
  "type": "Feature",
  "properties": {
    "gn:admin1_code":"5.0",
    "gn:asciiname":"Al Hit",
    "gn:country_code":"SY",
    "gn:dem":1090,
    "gn:feature_class":"P",
    "gn:feature_code":"PPL",
    "gn:name":"Al \u1e28\u012bt",
    "gn:population":0,
    "gn:timezone":"Asia/Damascus",
    "iso:country":"SY",
    "name:ara_x_preferred":[
        "Al H\u012bt"
    ],
    "name:ara_x_variant":[
        "Al \u1e28\u012bt",
        "\u0627\u0644\u062d\u064a\u062a"
    ],
    "name:und_x_variant":[
        "El H\u00eet\u00e9",
        "Eithal"
    ],
    "wof:name":"Al Hit",
    "wof:placetype":"locality"
},
  "geometry": {"coordinates":[36.67181,32.92644],"type":"Point"}
}