{
  "type": "Feature",
  "properties": {
    "gn:admin1_code":"11.0",
    "gn:asciiname":"Jubb al Bustan",
    "gn:country_code":"SY",
    "gn:dem":635,
    "gn:feature_class":"P",
    "gn:feature_code":"PPL",
    "gn:name":"Jubb al Bust\u0101n",
    "gn:population":0,
    "gn:timezone":"Asia/Damascus",
    "iso:country":"SY",
    "name:ara_x_preferred":[
        "\u062c\u0628 \u0627\u0644\u0628\u0633\u062a\u0627\u0646"
    ],
    "name:und_x_variant":[
        "Joubb el Boust\u00e2ne",
        "Jubb al Bust\u0101n",
        "Joubb Boust\u00e2ne"
    ],
    "wof:name":"Jubb al Bustan",
    "wof:placetype":"locality"
},
  "geometry": {"coordinates":[36.46584,34.77357],"type":"Point"}
}