{
  "type": "Feature",
  "properties": {
    "gn:admin1_code":"1.0",
    "gn:asciiname":"Qaysariyah al Fawqani",
    "gn:country_code":"SY",
    "gn:dem":475,
    "gn:feature_class":"P",
    "gn:feature_code":"PPL",
    "gn:name":"Qay\u015far\u012byah al Fawq\u0101n\u012b",
    "gn:population":0,
    "gn:timezone":"Asia/Damascus",
    "iso:country":"SY",
    "name:ara_x_preferred":[
        "\u0642\u064a\u0635\u0631\u064a\u0629 \u0627\u0644\u0641\u0648\u0642\u0627\u0646\u064a"
    ],
    "name:ara_x_variant":[
        "\u0645\u0639\u0645\u0634\u0648\u0631"
    ],
    "name:und_x_variant":[
        "Qay\u015far\u012byat al Fawq\u0101n\u012b",
        "Qay\u015far\u012byah al Fawq\u0101n\u012b",
        "Maamachour",
        "Ma\u2018mash\u016br"
    ],
    "wof:name":"Qaysariyah al Fawqani",
    "wof:placetype":"locality"
},
  "geometry": {"coordinates":[42.17774,37.1439],"type":"Point"}
}