{
  "type": "Feature",
  "properties": {
    "gn:admin1_code":"10.0",
    "gn:asciiname":"Al Hasaw",
    "gn:country_code":"SY",
    "gn:dem":557,
    "gn:feature_class":"P",
    "gn:feature_code":"PPL",
    "gn:name":"Al \u1e28as\u0101w",
    "gn:population":0,
    "gn:timezone":"Asia/Damascus",
    "iso:country":"SY",
    "name:ara_x_preferred":[
        "\u0627\u0644\u062d\u0633\u0627\u0648"
    ],
    "name:und_x_variant":[
        "Al \u1e28as\u0101w"
    ],
    "wof:name":"Al Hasaw",
    "wof:placetype":"locality"
},
  "geometry": {"coordinates":[37.68592,35.14951],"type":"Point"}
}