{
  "type": "Feature",
  "properties": {
    "gn:admin1_code":"14.0",
    "gn:asciiname":"Bayt al Jabal",
    "gn:country_code":"SY",
    "gn:dem":267,
    "gn:feature_class":"P",
    "gn:feature_code":"PPL",
    "gn:name":"Bayt al Jabal",
    "gn:population":0,
    "gn:timezone":"Asia/Damascus",
    "iso:country":"SY",
    "name:ara_x_preferred":[
        "\u0628\u064a\u062a \u0627\u0644\u062c\u0628\u0644"
    ],
    "wof:name":"Bayt al Jabal",
    "wof:placetype":"locality"
},
  "geometry": {"coordinates":[35.92279,34.96998],"type":"Point"}
}