{
  "type": "Feature",
  "properties": {
    "gn:admin1_code":"2.0",
    "gn:asciiname":"Ad Dubayqah",
    "gn:country_code":"SY",
    "gn:dem":13,
    "gn:feature_class":"P",
    "gn:feature_code":"PPL",
    "gn:name":"Ad Dubayqah",
    "gn:population":0,
    "gn:timezone":"Asia/Damascus",
    "iso:country":"SY",
    "name:ara_x_preferred":[
        "\u0627\u0644\u062f\u0628\u064a\u0642\u0629"
    ],
    "wof:name":"Ad Dubayqah",
    "wof:placetype":"locality"
},
  "geometry": {"coordinates":[35.93197,35.29146],"type":"Point"}
}