{
  "type": "Feature",
  "properties": {
    "gn:admin1_code":"2.0",
    "gn:asciiname":"Bayt Rayhan",
    "gn:country_code":"SY",
    "gn:dem":132,
    "gn:feature_class":"P",
    "gn:feature_code":"PPL",
    "gn:name":"Bayt Ray\u1e29\u0101n",
    "gn:population":0,
    "gn:timezone":"Asia/Damascus",
    "iso:country":"SY",
    "name:ara_x_preferred":[
        "\u0628\u064a\u062a \u0631\u064a\u062d\u0627\u0646"
    ],
    "name:und_x_variant":[
        "Bait Rihan",
        "Be\u00eft R\u00eeh\u00e2ne",
        "Bayt Ray\u1e29\u0101n"
    ],
    "wof:name":"Bayt Rayhan",
    "wof:placetype":"locality"
},
  "geometry": {"coordinates":[36.00384000000001,35.3779],"type":"Point"}
}