{
  "type": "Feature",
  "properties": {
    "gn:admin1_code":"11.0",
    "gn:asciiname":"Baghliyah",
    "gn:country_code":"SY",
    "gn:dem":842,
    "gn:feature_class":"P",
    "gn:feature_code":"PPL",
    "gn:name":"Baghl\u012byah",
    "gn:population":0,
    "gn:timezone":"Asia/Damascus",
    "iso:country":"SY",
    "name:ara_x_preferred":[
        "\u0628\u063a\u0644\u064a\u0629"
    ],
    "name:und_x_variant":[
        "Baghl\u012byah"
    ],
    "wof:name":"Baghliyah",
    "wof:placetype":"locality"
},
  "geometry": {"coordinates":[37.30715,34.68129],"type":"Point"}
}