{
  "type": "Feature",
  "properties": {
    "gn:admin1_code":"14.0",
    "gn:asciiname":"Mashli",
    "gn:country_code":"SY",
    "gn:dem":891,
    "gn:feature_class":"P",
    "gn:feature_code":"PPL",
    "gn:name":"Mashl\u012b",
    "gn:population":0,
    "gn:timezone":"Asia/Damascus",
    "iso:country":"SY",
    "name:ara_x_preferred":[
        "\u0645\u064a\u0634\u0644\u064a"
    ],
    "name:ara_x_variant":[
        "\u0645\u0634\u0644\u064a"
    ],
    "name:und_x_variant":[
        "M\u00e9chl\u012b",
        "Mashl\u012b",
        "Mayshl\u012b",
        "Mechli"
    ],
    "wof:name":"Mashli",
    "wof:placetype":"locality"
},
  "geometry": {"coordinates":[36.20316,34.97598],"type":"Point"}
}