{
  "type": "Feature",
  "properties": {
    "gn:admin1_code":"12.0",
    "gn:asciiname":"Faylun",
    "gn:country_code":"SY",
    "gn:dem":515,
    "gn:feature_class":"P",
    "gn:feature_code":"PPL",
    "gn:name":"Fayl\u016bn",
    "gn:population":0,
    "gn:timezone":"Asia/Damascus",
    "iso:country":"SY",
    "name:ara_x_preferred":[
        "\u0641\u064a\u0644\u0648\u0646"
    ],
    "name:fas_x_preferred":[
        "\u0641\u06cc\u0644\u0648\u0646"
    ],
    "name:pol_x_preferred":[
        "Fajlun"
    ],
    "name:und_x_variant":[
        "Fa\u00eflo\u00fbn",
        "Fayl\u016bn"
    ],
    "name:vie_x_preferred":[
        "Faylun"
    ],
    "wof:name":"Faylun",
    "wof:placetype":"locality"
},
  "geometry": {"coordinates":[36.61254,35.88051],"type":"Point"}
}