{
  "type": "Feature",
  "properties": {
    "gn:admin1_code":"8.0",
    "gn:asciiname":"Ma`dar",
    "gn:country_code":"SY",
    "gn:dem":1470,
    "gn:feature_class":"P",
    "gn:feature_code":"PPL",
    "gn:name":"Ma\u2018dar",
    "gn:population":0,
    "gn:timezone":"Asia/Damascus",
    "iso:country":"SY",
    "name:ara_x_preferred":[
        "\u0645\u0639\u062f\u0631"
    ],
    "name:pol_x_preferred":[
        "Madar"
    ],
    "name:und_x_variant":[
        "Ma\u2018dar"
    ],
    "name:vie_x_preferred":[
        "Maadar"
    ],
    "wof:name":"Ma`dar",
    "wof:placetype":"locality"
},
  "geometry": {"coordinates":[36.0109,33.73738],"type":"Point"}
}