{
  "type": "Feature",
  "properties": {
    "gn:admin1_code":"11.0",
    "gn:asciiname":"Ard ar Ruk",
    "gn:country_code":"SY",
    "gn:dem":547,
    "gn:feature_class":"P",
    "gn:feature_code":"PPLL",
    "gn:name":"Ar\u1e11 ar R\u016bk",
    "gn:population":0,
    "gn:timezone":"Asia/Damascus",
    "iso:country":"SY",
    "name:ara_x_preferred":[
        "\u0627\u0631\u0636 \u0627\u0644\u0631\u0648\u0643"
    ],
    "name:und_x_variant":[
        "Ar\u1e11 ar R\u016bk"
    ],
    "wof:name":"Ard ar Ruk",
    "wof:placetype":"locality"
},
  "geometry": {"coordinates":[36.76249,34.70942],"type":"Point"}
}