{
  "type": "Feature",
  "properties": {
    "gn:admin1_code":"9.0",
    "gn:asciiname":"Jurunli",
    "gn:country_code":"SY",
    "gn:dem":463,
    "gn:feature_class":"P",
    "gn:feature_code":"PPL",
    "gn:name":"J\u016brunl\u012b",
    "gn:population":0,
    "gn:timezone":"Asia/Damascus",
    "iso:country":"SY",
    "name:ara_x_preferred":[
        "J\u016brunl\u012b"
    ],
    "name:ara_x_variant":[
        "\u062c\u0648\u0631\u0646\u0644\u064a"
    ],
    "name:und_x_variant":[
        "Jo\u00fbrounnli",
        "Jo\u00fbrounli"
    ],
    "wof:name":"Jurunli",
    "wof:placetype":"locality"
},
  "geometry": {"coordinates":[37.89948,36.36611],"type":"Point"}
}