{
  "type": "Feature",
  "properties": {
    "gn:admin1_code":"9.0",
    "gn:asciiname":"Rabiyat al Hanutah",
    "gn:country_code":"SY",
    "gn:dem":355,
    "gn:feature_class":"P",
    "gn:feature_code":"PPL",
    "gn:name":"Rab\u012byat al \u1e28\u0101n\u016btah",
    "gn:population":0,
    "gn:timezone":"Asia/Damascus",
    "iso:country":"SY",
    "name:ara_x_preferred":[
        "\u0631\u0628\u0633\u0629 \u0627\u0644\u062d\u0627\u0646\u0648\u062a\u0629"
    ],
    "name:und_x_variant":[
        "Rba\u00efa\u00e2",
        "Rubay\u2018ah",
        "Rab\u012byat al \u1e28\u0101n\u016btah"
    ],
    "wof:name":"Rabiyat al Hanutah",
    "wof:placetype":"locality"
},
  "geometry": {"coordinates":[37.3524,35.82793],"type":"Point"}
}