{
  "type": "Feature",
  "properties": {
    "gn:admin1_code":"12.0",
    "gn:asciiname":"Al Qamishliyah",
    "gn:country_code":"SY",
    "gn:dem":113,
    "gn:feature_class":"P",
    "gn:feature_code":"PPL",
    "gn:name":"Al Q\u0101mishl\u012byah",
    "gn:population":0,
    "gn:timezone":"Asia/Damascus",
    "iso:country":"SY",
    "name:ara_x_preferred":[
        "\u0627\u0644\u0642\u0627\u0645\u0634\u0644\u064a\u0629"
    ],
    "name:und_x_variant":[
        "Al Q\u0101mishl\u012byah"
    ],
    "wof:name":"Al Qamishliyah",
    "wof:placetype":"locality"
},
  "geometry": {"coordinates":[36.41261,36.20267],"type":"Point"}
}