{
  "type": "Feature",
  "properties": {
    "gn:admin1_code":"10.0",
    "gn:asciiname":"Tall Mabtuhah",
    "gn:country_code":"SY",
    "gn:dem":179,
    "gn:feature_class":"P",
    "gn:feature_code":"PPL",
    "gn:name":"Tall Mab\u0163\u016b\u1e29ah",
    "gn:population":0,
    "gn:timezone":"Asia/Damascus",
    "iso:country":"SY",
    "name:ara_x_preferred":[
        "\u062a\u0644 \u0645\u0628\u0637\u0648\u062d\u0629"
    ],
    "name:und_x_variant":[
        "Tell Mabtouh\u00e9",
        "Tall Mab\u0163\u016b\u1e29ah"
    ],
    "wof:name":"Tall Mabtuhah",
    "wof:placetype":"locality"
},
  "geometry": {"coordinates":[36.38671,35.63014000000001],"type":"Point"}
}