{
  "type": "Feature",
  "properties": {
    "gn:admin1_code":"9.0",
    "gn:asciiname":"Al Azraq",
    "gn:country_code":"SY",
    "gn:dem":520,
    "gn:feature_class":"P",
    "gn:feature_code":"PPL",
    "gn:name":"Al Azraq",
    "gn:population":0,
    "gn:timezone":"Asia/Damascus",
    "iso:country":"SY",
    "name:ara_x_preferred":[
        "\u0627\u0644\u0623\u0632\u0631\u0642"
    ],
    "name:und_x_variant":[
        "El Azraq",
        "Azraq",
        "Al Azraq"
    ],
    "wof:name":"Al Azraq",
    "wof:placetype":"locality"
},
  "geometry": {"coordinates":[37.44106,36.36964],"type":"Point"}
}