{
  "type": "Feature",
  "properties": {
    "gn:admin1_code":"11.0",
    "gn:asciiname":"Turayfawi",
    "gn:country_code":"SY",
    "gn:dem":457,
    "gn:feature_class":"P",
    "gn:feature_code":"PPL",
    "gn:name":"\u0162urayf\u0101w\u012b",
    "gn:population":0,
    "gn:timezone":"Asia/Damascus",
    "iso:country":"SY",
    "name:ara_x_preferred":[
        "\u0637\u0631\u064a\u0641\u0627\u0648\u064a"
    ],
    "name:und_x_variant":[
        "\u0162urayf\u0101w\u012b"
    ],
    "wof:name":"Turayfawi",
    "wof:placetype":"locality"
},
  "geometry": {"coordinates":[38.09208,34.53252],"type":"Point"}
}