{
  "type": "Feature",
  "properties": {
    "gn:admin1_code":"2.0",
    "gn:asciiname":"Ninatat al Bur",
    "gn:country_code":"SY",
    "gn:dem":482,
    "gn:feature_class":"P",
    "gn:feature_code":"PPL",
    "gn:name":"N\u012bnatat al B\u016br",
    "gn:population":0,
    "gn:timezone":"Asia/Damascus",
    "iso:country":"SY",
    "name:ara_x_preferred":[
        "\u0646\u064a\u0646\u062a\u0629 \u0627\u0644\u0628\u0648\u0631"
    ],
    "name:ara_x_variant":[
        "\u0646\u064a\u0646\u0629"
    ],
    "name:und_x_variant":[
        "Ninet el Bo\u00fbr",
        "N\u012bnat al B\u016br",
        "N\u012bnatat al B\u016br",
        "N\u012bnah"
    ],
    "wof:name":"Ninatat al Bur",
    "wof:placetype":"locality"
},
  "geometry": {"coordinates":[36.09774,35.42501],"type":"Point"}
}