{
  "type": "Feature",
  "properties": {
    "gn:admin1_code":"8.0",
    "gn:asciiname":"Rimah",
    "gn:country_code":"SY",
    "gn:dem":1480,
    "gn:feature_class":"P",
    "gn:feature_code":"PPL",
    "gn:name":"R\u012bmah",
    "gn:population":0,
    "gn:timezone":"Asia/Damascus",
    "iso:country":"SY",
    "name:ara_x_preferred":[
        "\u0631\u064a\u0645\u0629"
    ],
    "name:ara_x_variant":[
        "\u0631\u064a\u0645\u0647"
    ],
    "name:und_x_variant":[
        "Rim\u00e9",
        "R\u012bmah",
        "R\u00eem\u00e9"
    ],
    "wof:name":"Rimah",
    "wof:placetype":"locality"
},
  "geometry": {"coordinates":[35.90092999999999,33.38578],"type":"Point"}
}