{
  "type": "Feature",
  "properties": {
    "gn:admin1_code":"9.0",
    "gn:asciiname":"Assous",
    "gn:country_code":"SY",
    "gn:dem":303,
    "gn:feature_class":"P",
    "gn:feature_code":"PPL",
    "gn:name":"Assous",
    "gn:population":0,
    "gn:timezone":"Asia/Damascus",
    "iso:country":"SY",
    "name:ara_x_preferred":[
        "\u2018A\u015f\u2018\u016b\u015f"
    ],
    "name:ara_x_variant":[
        "\u2018A\u015f\u016b\u015f",
        "\u0639\u0635\u0648\u0635",
        "\u0639\u0635\u0639\u0648\u0635"
    ],
    "name:und_x_variant":[
        "Aasso\u00fbs",
        "Assous",
        "Aasso\u00fbss"
    ],
    "wof:name":"Assous",
    "wof:placetype":"locality"
},
  "geometry": {"coordinates":[36.84732,36.07767],"type":"Point"}
}