{
  "type": "Feature",
  "properties": {
    "gn:admin1_code":"9.0",
    "gn:asciiname":"Qarah Halinj",
    "gn:country_code":"SY",
    "gn:dem":486,
    "gn:feature_class":"P",
    "gn:feature_code":"PPL",
    "gn:name":"Qarah \u1e28alinj",
    "gn:population":0,
    "gn:timezone":"Asia/Damascus",
    "iso:country":"SY",
    "name:ara_x_preferred":[
        "\u0642\u0631\u0647 \u062d\u0644\u0646\u062c"
    ],
    "name:ara_x_variant":[
        "\u0642\u0631\u0647 \u062d\u0644\u0646\u062c\u0647",
        "\u0627\u0644\u063a\u0633\u0627\u0646\u064a\u0629",
        "\u0642\u0631\u0629 \u062d\u0644\u0646\u062c"
    ],
    "name:kur_x_preferred":[
        "Qere \u1e26elinc"
    ],
    "name:kur_x_variant":[
        "\u1e26elinc\u00ea",
        "Qere \u1e26ilinc",
        "\u0642\u06d5\u0631\u06d5 \u062d\u06d5\u0644\u0646\u062c",
        "\u062d\u06d5\u0644\u0646\u062c\u06ce",
        "\u0642\u06d5\u0631\u06d5 \u062d\u0644\u0646\u062c"
    ],
    "name:und_x_variant":[
        "Qara Halinndj",
        "Qarah Khal\u012bj",
        "Qarah H\u0101l\u0101nj\u0101",
        "Qara Halinndj\u00e9",
        "Qarah \u1e28\u0101lin\u1e29",
        "Qarah \u1e28alinjah",
        "Qarah \u1e28alinj",
        "Qarah Halinj",
        "Helinc",
        "Al Ghas\u0101n\u012byah",
        "Qarah \u1e28ilinj",
        "El Xezaniy\u00ea",
        "Qere Hilinc",
        "Ghasaniyeh",
        "Helinc\u00ea"
    ],
    "wof:name":"Qarah Halinj",
    "wof:placetype":"locality"
},
  "geometry": {"coordinates":[38.3799,36.85414],"type":"Point"}
}