{
  "type": "Feature",
  "properties": {
    "gn:admin1_code":"9.0",
    "gn:asciiname":"Kafr Safrah",
    "gn:country_code":"SY",
    "gn:dem":359,
    "gn:feature_class":"P",
    "gn:feature_code":"PPL",
    "gn:name":"Kafr \u015eafrah",
    "gn:population":0,
    "gn:timezone":"Asia/Damascus",
    "iso:country":"SY",
    "name:ara_x_preferred":[
        "\u0643\u0641\u0631 \u0635\u0641\u0631\u0629"
    ],
    "name:und_x_variant":[
        "Kafer Safra",
        "Kafr \u015eafr\u0101\u2019",
        "Kafr \u015eafrah"
    ],
    "wof:name":"Kafr Safrah",
    "wof:placetype":"locality"
},
  "geometry": {"coordinates":[36.66119000000001,36.42752],"type":"Point"}
}