{
  "type": "Feature",
  "properties": {
    "gn:admin1_code":"2.0",
    "gn:asciiname":"Al `Asiliyah",
    "gn:country_code":"SY",
    "gn:dem":24,
    "gn:feature_class":"P",
    "gn:feature_code":"PPL",
    "gn:name":"Al \u2018As\u012bl\u012byah",
    "gn:population":0,
    "gn:timezone":"Asia/Damascus",
    "iso:country":"SY",
    "name:ara_x_preferred":[
        "\u0627\u0644\u0639\u0633\u064a\u0644\u064a\u0629"
    ],
    "name:und_x_variant":[
        "Al \u2018As\u012bl\u012byah"
    ],
    "wof:name":"Al `Asiliyah",
    "wof:placetype":"locality"
},
  "geometry": {"coordinates":[35.92715,35.3946],"type":"Point"}
}