{
  "type": "Feature",
  "properties": {
    "gn:admin1_code":"7.0",
    "gn:asciiname":"Al Falw",
    "gn:country_code":"SY",
    "gn:dem":218,
    "gn:feature_class":"P",
    "gn:feature_code":"PPL",
    "gn:name":"Al Falw",
    "gn:population":0,
    "gn:timezone":"Asia/Damascus",
    "iso:country":"SY",
    "name:ara_x_preferred":[
        "\u0627\u0644\u0641\u0644\u0648"
    ],
    "name:und_x_variant":[
        "Al Fal\u016b Kib\u0101r",
        "Al Falw"
    ],
    "wof:name":"Al Falw",
    "wof:placetype":"locality"
},
  "geometry": {"coordinates":[39.85226,35.62631],"type":"Point"}
}