{
  "type": "Feature",
  "properties": {
    "gn:admin1_code":"1.0",
    "gn:asciiname":"Mahmudiyah",
    "gn:country_code":"SY",
    "gn:dem":387,
    "gn:feature_class":"P",
    "gn:feature_code":"PPL",
    "gn:name":"Ma\u1e29m\u016bd\u012byah",
    "gn:population":0,
    "gn:timezone":"Asia/Damascus",
    "iso:country":"SY",
    "name:ara_x_preferred":[
        "\u0645\u062d\u0645\u0648\u062f\u064a\u0629"
    ],
    "name:tur_x_preferred":[
        "Ma\u1e29m\u016bd\u012byah"
    ],
    "name:und_x_variant":[
        "Mahmo\u00fbd\u00eey\u00e9",
        "Ma\u1e29m\u016bd\u012byah"
    ],
    "wof:name":"Mahmudiyah",
    "wof:placetype":"locality"
},
  "geometry": {"coordinates":[40.72944,36.81834],"type":"Point"}
}