{
  "type": "Feature",
  "properties": {
    "gn:admin1_code":"1.0",
    "gn:asciiname":"Khirbat Jamus",
    "gn:country_code":"SY",
    "gn:dem":315,
    "gn:feature_class":"P",
    "gn:feature_code":"PPL",
    "gn:name":"Khirbat J\u0101m\u016bs",
    "gn:population":0,
    "gn:timezone":"Asia/Damascus",
    "iso:country":"SY",
    "name:ara_x_preferred":[
        "\u062e\u0631\u0628\u0629 \u062c\u0627\u0645\u0648\u0633"
    ],
    "name:und_x_variant":[
        "Khirbat J\u0101m\u016bs",
        "Khirat al J\u0101m\u016bs"
    ],
    "wof:name":"Khirbat Jamus",
    "wof:placetype":"locality"
},
  "geometry": {"coordinates":[40.78675,36.53777],"type":"Point"}
}