{
  "type": "Feature",
  "properties": {
    "gn:admin1_code":"14.0",
    "gn:asciiname":"Hanafiyah",
    "gn:country_code":"SY",
    "gn:dem":218,
    "gn:feature_class":"P",
    "gn:feature_code":"PPL",
    "gn:name":"\u1e28anaf\u012byah",
    "gn:population":0,
    "gn:timezone":"Asia/Damascus",
    "iso:country":"SY",
    "name:ara_x_preferred":[
        "\u062d\u0646\u0641\u064a\u0629"
    ],
    "name:und_x_variant":[
        "Hannf\u00eey\u00e9",
        "Al \u1e28anaf\u012byah",
        "\u1e28anaf\u012byah"
    ],
    "wof:name":"Hanafiyah",
    "wof:placetype":"locality"
},
  "geometry": {"coordinates":[35.95697,35.01328],"type":"Point"}
}