{
  "type": "Feature",
  "properties": {
    "gn:admin1_code":"9.0",
    "gn:asciiname":"Al `Anazah",
    "gn:country_code":"SY",
    "gn:dem":370,
    "gn:feature_class":"P",
    "gn:feature_code":"PPL",
    "gn:name":"Al \u2018An\u0101zah",
    "gn:population":0,
    "gn:timezone":"Asia/Damascus",
    "iso:country":"SY",
    "name:ara_x_preferred":[
        "\u0627\u0644\u0639\u0646\u0627\u0632\u0629"
    ],
    "name:und_x_variant":[
        "Aann\u00e2z\u00e9",
        "\u2018Ann\u0101zah",
        "Al \u2018An\u0101zah"
    ],
    "wof:name":"Al `Anazah",
    "wof:placetype":"locality"
},
  "geometry": {"coordinates":[37.47962,35.98699999999999],"type":"Point"}
}