{
  "type": "Feature",
  "properties": {
    "gn:admin1_code":"10.0",
    "gn:asciiname":"Saffawi",
    "gn:country_code":"SY",
    "gn:dem":496,
    "gn:feature_class":"P",
    "gn:feature_code":"PPL",
    "gn:name":"\u015eaff\u0101w\u012b",
    "gn:population":0,
    "gn:timezone":"Asia/Damascus",
    "iso:country":"SY",
    "name:ara_x_preferred":[
        "\u0635\u0641\u0627\u0648\u064a"
    ],
    "name:und_x_variant":[
        "Saff\u00e2oui",
        "\u015eaff\u0101w\u012b"
    ],
    "wof:name":"Saffawi",
    "wof:placetype":"locality"
},
  "geometry": {"coordinates":[37.09071,34.95885],"type":"Point"}
}