{
  "type": "Feature",
  "properties": {
    "gn:admin1_code":"7.0",
    "gn:asciiname":"`Annabah",
    "gn:country_code":"SY",
    "gn:dem":206,
    "gn:feature_class":"P",
    "gn:feature_code":"PPL",
    "gn:name":"\u2018Ann\u0101bah",
    "gn:population":0,
    "gn:timezone":"Asia/Damascus",
    "iso:country":"SY",
    "name:und_x_variant":[
        "Aannab\u00e9",
        "\u2018Ann\u0101bah"
    ],
    "wof:name":"`Annabah",
    "wof:placetype":"locality"
},
  "geometry": {"coordinates":[39.91667,35.51667],"type":"Point"}
}