{
  "type": "Feature",
  "properties": {
    "gn:admin1_code":"2.0",
    "gn:asciiname":"Marj az Zawiyah",
    "gn:country_code":"SY",
    "gn:dem":302,
    "gn:feature_class":"P",
    "gn:feature_code":"PPL",
    "gn:name":"Marj az Zaw\u012byah",
    "gn:population":0,
    "gn:timezone":"Asia/Damascus",
    "iso:country":"SY",
    "name:ara_x_preferred":[
        "\u0645\u0631\u062c \u0627\u0644\u0632\u0648\u064a\u0629"
    ],
    "name:ara_x_variant":[
        "\u0639\u064a\u0646 \u0627\u0644\u0632\u0631\u0642\u0627\u0621",
        "\u0645\u0631\u062c \u0627\u0644\u0632\u0627\u0648\u064a\u0629"
    ],
    "name:und_x_variant":[
        "A\u00efn ez Zarqa",
        "Marj ez Zaou\u00eey\u00e9",
        "Marj az Z\u0101wiyah",
        "Marj az Zaw\u012byah",
        "\u2018Ayn az Zarq\u0101\u2019"
    ],
    "wof:name":"Marj az Zawiyah",
    "wof:placetype":"locality"
},
  "geometry": {"coordinates":[36.12886,35.75346],"type":"Point"}
}