{
  "type": "Feature",
  "properties": {
    "gn:admin1_code":"4.0",
    "gn:asciiname":"Abu ad Duhur",
    "gn:country_code":"SY",
    "gn:dem":365,
    "gn:feature_class":"P",
    "gn:feature_code":"PPL",
    "gn:name":"Ab\u016b a\u1e11 \u1e10uh\u016br",
    "gn:population":0,
    "gn:timezone":"Asia/Damascus",
    "iso:country":"SY",
    "name:ara_x_preferred":[
        "\u0627\u0628\u0648 \u0627\u0644\u0636\u0647\u0648\u0631"
    ],
    "name:und_x_variant":[
        "Abou ed Douho\u00fbr",
        "Ab\u016b a\u1e11 \u1e10uh\u016br"
    ],
    "wof:name":"Abu ad Duhur",
    "wof:placetype":"locality"
},
  "geometry": {"coordinates":[38.77946,36.52745],"type":"Point"}
}