{
  "type": "Feature",
  "properties": {
    "gn:admin1_code":"9.0",
    "gn:asciiname":"Jubb Hasan Agha",
    "gn:country_code":"SY",
    "gn:dem":451,
    "gn:feature_class":"P",
    "gn:feature_code":"PPL",
    "gn:name":"Jubb \u1e28asan \u0100gh\u0101",
    "gn:population":0,
    "gn:timezone":"Asia/Damascus",
    "iso:country":"SY",
    "name:ara_x_preferred":[
        "\u062c\u0628 \u062c\u0633\u0646 \u0622\u063a\u0627"
    ],
    "name:und_x_variant":[
        "Joubb Hassane \u00c2rba",
        "Joubb Hassane \u00c2rha",
        "Jubb \u1e28asan \u0100gh\u0101"
    ],
    "wof:name":"Jubb Hasan Agha",
    "wof:placetype":"locality"
},
  "geometry": {"coordinates":[38.04059,36.44939],"type":"Point"}
}