{
  "type": "Feature",
  "properties": {
    "gn:admin1_code":"12.0",
    "gn:asciiname":"Al Wasita",
    "gn:country_code":"SY",
    "gn:dem":246,
    "gn:feature_class":"P",
    "gn:feature_code":"PPL",
    "gn:name":"Al Was\u012b\u0163\u00e1",
    "gn:population":0,
    "gn:timezone":"Asia/Damascus",
    "iso:country":"SY",
    "name:ara_x_preferred":[
        "\u0627\u0644\u0648\u0633\u064a\u0637\u0649"
    ],
    "name:und_x_variant":[
        "Al Was\u012b\u0163\u00e1"
    ],
    "wof:name":"Al Wasita",
    "wof:placetype":"locality"
},
  "geometry": {"coordinates":[37.04713,35.79148],"type":"Point"}
}