{
  "type": "Feature",
  "properties": {
    "gn:admin1_code":"7.0",
    "gn:asciiname":"Zalmawiyah",
    "gn:country_code":"SY",
    "gn:dem":743,
    "gn:feature_class":"P",
    "gn:feature_code":"PPL",
    "gn:name":"Zalm\u0101w\u012byah",
    "gn:population":0,
    "gn:timezone":"Asia/Damascus",
    "iso:country":"SY",
    "name:ara_x_preferred":[
        "\u0632\u0644\u0645\u0627\u0648\u064a\u0629"
    ],
    "name:und_x_variant":[
        "Zalm\u0101w\u012byah"
    ],
    "wof:name":"Zalmawiyah",
    "wof:placetype":"locality"
},
  "geometry": {"coordinates":[39.41555,35.3957],"type":"Point"}
}