{
  "type": "Feature",
  "properties": {
    "gn:admin1_code":"9.0",
    "gn:asciiname":"Jubb `Alays",
    "gn:country_code":"SY",
    "gn:dem":345,
    "gn:feature_class":"P",
    "gn:feature_code":"PPL",
    "gn:name":"Jubb \u2018Alays",
    "gn:population":0,
    "gn:timezone":"Asia/Damascus",
    "iso:country":"SY",
    "name:ara_x_preferred":[
        "\u062c\u0628 \u0639\u0644\u064a\u0633"
    ],
    "name:und_x_variant":[
        "Joubb Aala\u00efss",
        "Jubb Aalaiss",
        "Jubb \u2018Alays"
    ],
    "wof:name":"Jubb `Alays",
    "wof:placetype":"locality"
},
  "geometry": {"coordinates":[37.33754,35.80438],"type":"Point"}
}