{
  "type": "Feature",
  "properties": {
    "gn:admin1_code":"3.0",
    "gn:asciiname":"Bruchim Qela' Alon",
    "gn:country_code":"SY",
    "gn:dem":666,
    "gn:feature_class":"P",
    "gn:feature_code":"PPL",
    "gn:name":"Bruchim Qela' Alon",
    "gn:population":0,
    "gn:timezone":"Asia/Jerusalem",
    "iso:country":"SY",
    "wof:name":"Bruchim Qela' Alon",
    "wof:placetype":"locality"
},
  "geometry": {"coordinates":[35.69106,33.13187],"type":"Point"}
}