{
  "type": "Feature",
  "properties": {
    "gn:admin1_code":"11.0",
    "gn:asciiname":"Talldaww",
    "gn:country_code":"SY",
    "gn:dem":375,
    "gn:feature_class":"P",
    "gn:feature_code":"PPLA3",
    "gn:name":"Talldaww",
    "gn:population":0,
    "gn:timezone":"Asia/Damascus",
    "iso:country":"SY",
    "name:ara_x_preferred":[
        "\u062a\u0644 \u062f\u0648"
    ],
    "name:ara_x_variant":[
        "\u062a\u0644\u062f\u0648",
        "\u062e\u0631\u0628\u0629 \u0627\u0644\u0646\u0627\u0635\u0631\u064a\u0629"
    ],
    "name:und_x_variant":[
        "Tell Daou",
        "Tall Daww",
        "Talldaww",
        "Khirbat N\u0101\u015fir\u012byah",
        "Khirbat an N\u0101\u015fir\u012byah",
        "Kheurbet N\u00e2sriy\u00e9"
    ],
    "wof:name":"Talldaww",
    "wof:placetype":"locality"
},
  "geometry": {"coordinates":[36.524,34.87632],"type":"Point"}
}