{
  "type": "Feature",
  "properties": {
    "gn:admin1_code":"14.0",
    "gn:asciiname":"Barqiyah",
    "gn:country_code":"SY",
    "gn:dem":305,
    "gn:feature_class":"P",
    "gn:feature_code":"PPL",
    "gn:name":"Barq\u012byah",
    "gn:population":0,
    "gn:timezone":"Asia/Damascus",
    "iso:country":"SY",
    "name:ara_x_preferred":[
        "\u0628\u0631\u0642\u064a\u0629"
    ],
    "name:ara_x_variant":[
        "\u0628\u0627\u0631\u0642\u064a\u0647",
        "\u0627\u0644\u0635\u0627\u0641\u064a\u0629"
    ],
    "name:und_x_variant":[
        "Barq\u00eey\u00e9",
        "Barq\u012byah",
        "B\u0101riq\u012byah",
        "A\u015f \u015e\u0101fiyah"
    ],
    "wof:name":"Barqiyah",
    "wof:placetype":"locality"
},
  "geometry": {"coordinates":[36.21366,34.7925],"type":"Point"}
}