{
  "type": "Feature",
  "properties": {
    "gn:admin1_code":"1.0",
    "gn:asciiname":"Karanku",
    "gn:country_code":"SY",
    "gn:dem":443,
    "gn:feature_class":"P",
    "gn:feature_code":"PPL",
    "gn:name":"Karank\u016b",
    "gn:population":0,
    "gn:timezone":"Asia/Damascus",
    "iso:country":"SY",
    "name:ara_x_preferred":[
        "\u0643\u0631 \u0646\u0643\u0648"
    ],
    "name:tur_x_preferred":[
        "Karenngo"
    ],
    "name:und_x_variant":[
        "Karank\u016b"
    ],
    "wof:name":"Karanku",
    "wof:placetype":"locality"
},
  "geometry": {"coordinates":[40.89408,37.04785],"type":"Point"}
}