{
  "type": "Feature",
  "properties": {
    "gn:admin1_code":"9.0",
    "gn:asciiname":"Wuraydah",
    "gn:country_code":"SY",
    "gn:dem":436,
    "gn:feature_class":"P",
    "gn:feature_code":"PPL",
    "gn:name":"Wuraydah",
    "gn:population":0,
    "gn:timezone":"Asia/Damascus",
    "iso:country":"SY",
    "name:ara_x_preferred":[
        "\u0648\u0631\u064a\u0644\u0629"
    ],
    "name:ara_x_variant":[
        "\u0648\u0631\u064a\u062f\u0629"
    ],
    "name:und_x_variant":[
        "War\u012blah",
        "Wuraydah"
    ],
    "wof:name":"Wuraydah",
    "wof:placetype":"locality"
},
  "geometry": {"coordinates":[37.37125,36.25543],"type":"Point"}
}