{
  "type": "Feature",
  "properties": {
    "gn:admin1_code":"9.0",
    "gn:asciiname":"Abu Jakkah",
    "gn:country_code":"SY",
    "gn:dem":365,
    "gn:feature_class":"P",
    "gn:feature_code":"PPL",
    "gn:name":"Ab\u016b Jakkah",
    "gn:population":0,
    "gn:timezone":"Asia/Damascus",
    "iso:country":"SY",
    "name:ara_x_preferred":[
        "\u0623\u0628\u0648 \u062c\u0643\u0629"
    ],
    "name:und_x_variant":[
        "Abou Jekka",
        "Abou Jadha Salma",
        "Ab\u016b Jakkah"
    ],
    "wof:name":"Abu Jakkah",
    "wof:placetype":"locality"
},
  "geometry": {"coordinates":[37.99277,36.20898],"type":"Point"}
}