{
  "type": "Feature",
  "properties": {
    "gn:admin1_code":"1.0",
    "gn:asciiname":"`Annad",
    "gn:country_code":"SY",
    "gn:dem":294,
    "gn:feature_class":"P",
    "gn:feature_code":"PPL",
    "gn:name":"\u2018Ann\u0101d",
    "gn:population":0,
    "gn:timezone":"Asia/Damascus",
    "iso:country":"SY",
    "name:ara_x_preferred":[
        "\u2018An\u0101d"
    ],
    "name:ara_x_variant":[
        "\u0639\u0646\u0627\u062f",
        "\u2018Ann\u0101d"
    ],
    "wof:name":"`Annad",
    "wof:placetype":"locality"
},
  "geometry": {"coordinates":[41.02632,35.81095999999999],"type":"Point"}
}