{
  "type": "Feature",
  "properties": {
    "gn:admin1_code":"1.0",
    "gn:asciiname":"Karhuk",
    "gn:country_code":"SY",
    "gn:dem":401,
    "gn:feature_class":"P",
    "gn:feature_code":"PPL",
    "gn:name":"Karh\u016bk",
    "gn:population":0,
    "gn:timezone":"Asia/Damascus",
    "iso:country":"SY",
    "name:ara_x_preferred":[
        "\u0643\u0631\u0647\u0648\u0643"
    ],
    "name:und_x_variant":[
        "Karh\u016bk"
    ],
    "wof:name":"Karhuk",
    "wof:placetype":"locality"
},
  "geometry": {"coordinates":[41.88187,36.92547],"type":"Point"}
}