{
  "type": "Feature",
  "properties": {
    "gn:admin1_code":"11.0",
    "gn:asciiname":"Bir Khan `Unaybah",
    "gn:country_code":"SY",
    "gn:dem":1013,
    "gn:feature_class":"P",
    "gn:feature_code":"PPL",
    "gn:name":"B\u012br Kh\u0101n \u2018Unaybah",
    "gn:population":0,
    "gn:timezone":"Asia/Damascus",
    "iso:country":"SY",
    "name:ara_x_preferred":[
        "\u0628\u064a\u0631 \u062e\u0627\u0646 \u0639\u0646\u064a\u0628\u0629"
    ],
    "name:und_x_variant":[
        "Bi\u2019r Kh\u0101n \u2018Unaybah",
        "B\u012br Kh\u0101n \u2018Unaybah"
    ],
    "wof:name":"Bir Khan `Unaybah",
    "wof:placetype":"locality"
},
  "geometry": {"coordinates":[37.34392,34.04055],"type":"Point"}
}