{
  "type": "Feature",
  "properties": {
    "gn:admin1_code":"2.0",
    "gn:asciiname":"Zuwayk",
    "gn:country_code":"SY",
    "gn:dem":398,
    "gn:feature_class":"P",
    "gn:feature_code":"PPL",
    "gn:name":"Zuwayk",
    "gn:population":0,
    "gn:timezone":"Asia/Damascus",
    "iso:country":"SY",
    "name:ara_x_preferred":[
        "\u0632\u0648\u064a\u0643"
    ],
    "name:und_x_variant":[
        "Zoua\u00efyek",
        "Az Zuwayyik",
        "Zuwayk"
    ],
    "wof:name":"Zuwayk",
    "wof:placetype":"locality"
},
  "geometry": {"coordinates":[36.03995,35.69467],"type":"Point"}
}