{
  "type": "Feature",
  "properties": {
    "gn:admin1_code":"11.0",
    "gn:asciiname":"Khirbat an Nazra",
    "gn:cc2":"SY",
    "gn:country_code":"SY",
    "gn:dem":927,
    "gn:feature_class":"P",
    "gn:feature_code":"PPL",
    "gn:name":"Khirbat an Nazr\u0101",
    "gn:population":0,
    "gn:timezone":"Asia/Damascus",
    "iso:country":"SY",
    "name:und_x_variant":[
        "Kheurbet enn Nazra",
        "Khirbat an Nazr\u0101"
    ],
    "wof:name":"Khirbat an Nazra",
    "wof:placetype":"locality"
},
  "geometry": {"coordinates":[37.41667,34.81667],"type":"Point"}
}