{
  "type": "Feature",
  "properties": {
    "gn:admin1_code":"9.0",
    "gn:asciiname":"Bilaliku",
    "gn:country_code":"SY",
    "gn:dem":974,
    "gn:feature_class":"P",
    "gn:feature_code":"PPL",
    "gn:name":"Bil\u0101l\u012bk\u016b",
    "gn:population":0,
    "gn:timezone":"Asia/Damascus",
    "iso:country":"SY",
    "name:ara_x_preferred":[
        "Bil\u0101l\u012bk\u016b"
    ],
    "name:ara_x_variant":[
        "\u0628\u0644\u0627\u0644\u064a\u0643\u0648",
        "\u0628\u0644\u0627\u0644\u064a\u0629"
    ],
    "name:und_x_variant":[
        "Belaliko",
        "B\u00e9l\u00e2l Keuy",
        "Bal\u0101l K\u016by",
        "Bil\u0101l\u012byah"
    ],
    "wof:name":"Bilaliku",
    "wof:placetype":"locality"
},
  "geometry": {"coordinates":[36.68401,36.75032],"type":"Point"}
}