{
  "type": "Feature",
  "properties": {
    "gn:admin1_code":"9.0",
    "gn:asciiname":"Jatal Qabu",
    "gn:country_code":"SY",
    "gn:dem":747,
    "gn:feature_class":"P",
    "gn:feature_code":"PPL",
    "gn:name":"Jat\u0101l Q\u0101b\u016b",
    "gn:population":0,
    "gn:timezone":"Asia/Damascus",
    "iso:country":"SY",
    "name:ara_x_preferred":[
        "\u062c\u062a\u0627\u0644 \u0642\u0628\u0648"
    ],
    "name:ara_x_variant":[
        "\u062c\u062a\u0627\u0644 \u0642\u0627\u0628\u0648",
        "\u0627\u0644\u0628\u0626\u0631\u064a\u0646"
    ],
    "name:und_x_variant":[
        "Tchat\u00e2l Qapou",
        "Tchatal Kouyou",
        "Jat\u0101l Qab\u016b",
        "Jat\u0101l Q\u0101b\u016b",
        "Al Bi\u2019rayn"
    ],
    "wof:name":"Jatal Qabu",
    "wof:placetype":"locality"
},
  "geometry": {"coordinates":[36.74955,36.68386],"type":"Point"}
}