{
  "type": "Feature",
  "properties": {
    "gn:admin1_code":"5.0",
    "gn:asciiname":"`Arajah",
    "gn:country_code":"SY",
    "gn:dem":1166,
    "gn:feature_class":"P",
    "gn:feature_code":"PPL",
    "gn:name":"\u2018Ar\u0101jah",
    "gn:population":0,
    "gn:timezone":"Asia/Damascus",
    "iso:country":"SY",
    "name:ara_x_preferred":[
        "\u0639\u0631\u0627\u062c\u0629"
    ],
    "name:und_x_variant":[
        "\u2018Ar\u0101jah"
    ],
    "wof:name":"`Arajah",
    "wof:placetype":"locality"
},
  "geometry": {"coordinates":[36.76887,32.8683],"type":"Point"}
}