{
  "type": "Feature",
  "properties": {
    "gn:admin1_code":"8.0",
    "gn:asciiname":"Darushah",
    "gn:country_code":"SY",
    "gn:dem":803,
    "gn:feature_class":"P",
    "gn:feature_code":"PPL",
    "gn:name":"Dar\u016bshah",
    "gn:population":0,
    "gn:timezone":"Asia/Damascus",
    "iso:country":"SY",
    "name:ara_x_preferred":[
        "\u062d\u0648\u0634 \u062f\u0631\u0648\u0634\u0629"
    ],
    "name:ara_x_variant":[
        "\u062f\u0631\u0648\u0634\u0629"
    ],
    "name:und_x_variant":[
        "Dro\u00fbcha",
        "Haouch Dro\u00fbcha",
        "\u1e28awsh Dr\u016bshah",
        "\u1e28awsh Dar\u016bshah",
        "Dar\u016bshah"
    ],
    "wof:name":"Darushah",
    "wof:placetype":"locality"
},
  "geometry": {"coordinates":[36.12923,33.40037],"type":"Point"}
}