{
  "type": "Feature",
  "properties": {
    "gn:admin1_code":"9.0",
    "gn:asciiname":"Khassaf",
    "gn:country_code":"SY",
    "gn:dem":320,
    "gn:feature_class":"P",
    "gn:feature_code":"PPL",
    "gn:name":"Khass\u0101f",
    "gn:population":0,
    "gn:timezone":"Asia/Damascus",
    "iso:country":"SY",
    "name:ara_x_preferred":[
        "\u062e\u0633\u0627\u0641"
    ],
    "name:und_x_variant":[
        "Khass\u00e2t",
        "Khass\u0101f"
    ],
    "wof:name":"Khassaf",
    "wof:placetype":"locality"
},
  "geometry": {"coordinates":[37.67914,36.09732],"type":"Point"}
}