{
  "type": "Feature",
  "properties": {
    "gn:admin1_code":"9.0",
    "gn:asciiname":"Baylunah",
    "gn:country_code":"SY",
    "gn:dem":379,
    "gn:feature_class":"P",
    "gn:feature_code":"PPL",
    "gn:name":"Bayl\u016bnah",
    "gn:population":0,
    "gn:timezone":"Asia/Damascus",
    "iso:country":"SY",
    "name:ara_x_preferred":[
        "\u0628\u064a\u0644\u0648\u0646\u0629"
    ],
    "name:ara_x_variant":[
        "\u0642\u0631\u064a\u0629 \u0627\u0644\u0639\u0637\u0648"
    ],
    "name:kur_x_preferred":[
        "B\u00ealuny\u00ea"
    ],
    "name:kur_x_variant":[
        "\u0628\u06ce\u0644\u0648\u0646\u064a\u06ce"
    ],
    "name:und_x_variant":[
        "B\u00e9lo\u00fbn",
        "Be\u00eflo\u00fbn\u00e9",
        "Bayl\u016bnah",
        "Qaryat al \u2018A\u0163\u016b"
    ],
    "wof:name":"Baylunah",
    "wof:placetype":"locality"
},
  "geometry": {"coordinates":[38.05973,36.80894],"type":"Point"}
}