{
  "type": "Feature",
  "properties": {
    "gn:admin1_code":"2.0",
    "gn:asciiname":"Al `Uwa",
    "gn:country_code":"SY",
    "gn:dem":33,
    "gn:feature_class":"P",
    "gn:feature_code":"PPLL",
    "gn:name":"Al \u2018Uw\u0101",
    "gn:population":0,
    "gn:timezone":"Asia/Damascus",
    "iso:country":"SY",
    "name:ara_x_preferred":[
        "Al \u2018Uw\u0101"
    ],
    "name:ara_x_variant":[
        "\u0627\u0644\u0639\u0648\u0627"
    ],
    "wof:name":"Al `Uwa",
    "wof:placetype":"locality"
},
  "geometry": {"coordinates":[35.80117,35.57579000000001],"type":"Point"}
}