{
  "type": "Feature",
  "properties": {
    "gn:admin1_code":"12.0",
    "gn:asciiname":"Al Buq`ah",
    "gn:country_code":"SY",
    "gn:dem":464,
    "gn:feature_class":"P",
    "gn:feature_code":"PPL",
    "gn:name":"Al Buq\u2018ah",
    "gn:population":0,
    "gn:timezone":"Asia/Damascus",
    "iso:country":"SY",
    "name:ara_x_preferred":[
        "\u0627\u0644\u0628\u0642\u0639\u0629"
    ],
    "name:und_x_variant":[
        "Al Buq\u2018ah"
    ],
    "wof:name":"Al Buq`ah",
    "wof:placetype":"locality"
},
  "geometry": {"coordinates":[36.49571,35.80422],"type":"Point"}
}