{
  "type": "Feature",
  "properties": {
    "gn:admin1_code":"14.0",
    "gn:asciiname":"Ar Ruwaysah",
    "gn:country_code":"SY",
    "gn:dem":56,
    "gn:feature_class":"P",
    "gn:feature_code":"PPL",
    "gn:name":"Ar Ruwaysah",
    "gn:population":0,
    "gn:timezone":"Asia/Damascus",
    "iso:country":"SY",
    "name:ara_x_preferred":[
        "\u0627\u0644\u0631\u0648\u064a\u0633\u0629"
    ],
    "wof:name":"Ar Ruwaysah",
    "wof:placetype":"locality"
},
  "geometry": {"coordinates":[35.97855999999999,34.79221],"type":"Point"}
}