{
  "type": "Feature",
  "properties": {
    "gn:admin1_code":"1.0",
    "gn:asciiname":"Mushayrifah Kabirah",
    "gn:country_code":"SY",
    "gn:dem":380,
    "gn:feature_class":"P",
    "gn:feature_code":"PPL",
    "gn:name":"Mushayrifah Kab\u012brah",
    "gn:population":0,
    "gn:timezone":"Asia/Damascus",
    "iso:country":"SY",
    "name:ara_x_preferred":[
        "\u0645\u0634\u064a\u0631\u0641\u0629 \u0643\u0628\u064a\u0631\u0629"
    ],
    "name:tur_x_preferred":[
        "Mushayrifah al Kab\u012brah"
    ],
    "name:und_x_variant":[
        "M\u00e9cherf\u00e9 K\u00e9b\u00eer\u00e9",
        "Mushayrifah Kab\u012brah"
    ],
    "wof:name":"Mushayrifah Kabirah",
    "wof:placetype":"locality"
},
  "geometry": {"coordinates":[41.24087,36.82904],"type":"Point"}
}