{
  "type": "Feature",
  "properties": {
    "gn:admin1_code":"9.0",
    "gn:asciiname":"Kharab Kurd",
    "gn:country_code":"SY",
    "gn:dem":481,
    "gn:feature_class":"P",
    "gn:feature_code":"PPL",
    "gn:name":"Khar\u0101b K\u016brd",
    "gn:population":0,
    "gn:timezone":"Asia/Damascus",
    "iso:country":"SY",
    "name:ara_x_preferred":[
        "\u062e\u0631\u0627\u0628 \u0643\u0648\u0631\u062f"
    ],
    "name:ara_x_variant":[
        "\u062e\u0631\u0627\u0628 \u0643\u0631\u062f",
        "\u062e\u0631\u0627\u0628 \u0643\u0648\u0631\u062a"
    ],
    "name:kur_x_preferred":[
        "Xerab Kurd"
    ],
    "name:kur_x_variant":[
        "\u062e\u06d5\u0631\u0627\u0628 \u0643\u0648\u0631\u062f",
        "Xerab Kurt",
        "\u062e\u06d5\u0631\u0627\u0628 \u0643\u0648\u0631\u062a"
    ],
    "name:und_x_variant":[
        "Khar\u00e2b Kourd",
        "Khar\u0101b Kurd",
        "Khar\u0101b K\u016brd",
        "Kharab Kurd",
        "Khar\u0101b K\u016brt"
    ],
    "wof:name":"Kharab Kurd",
    "wof:placetype":"locality"
},
  "geometry": {"coordinates":[38.44859,36.81465],"type":"Point"}
}