{
  "type": "Feature",
  "properties": {
    "gn:admin1_code":"10.0",
    "gn:asciiname":"Shahlah",
    "gn:country_code":"SY",
    "gn:dem":400,
    "gn:feature_class":"P",
    "gn:feature_code":"PPL",
    "gn:name":"Sha\u1e29lah",
    "gn:population":0,
    "gn:timezone":"Asia/Damascus",
    "iso:country":"SY",
    "name:ara_x_preferred":[
        "\u0634\u062d\u0644\u0629"
    ],
    "name:und_x_variant":[
        "Chahl\u00e9",
        "Shahlah",
        "Sha\u1e29lah"
    ],
    "wof:name":"Shahlah",
    "wof:placetype":"locality"
},
  "geometry": {"coordinates":[36.93847,35.07775],"type":"Point"}
}