{
  "type": "Feature",
  "properties": {
    "gn:admin1_code":"1.0",
    "gn:asciiname":"At Tash",
    "gn:country_code":"SY",
    "gn:dem":379,
    "gn:feature_class":"P",
    "gn:feature_code":"PPL",
    "gn:name":"A\u0163 \u0162\u0101sh",
    "gn:population":0,
    "gn:timezone":"Asia/Damascus",
    "iso:country":"SY",
    "name:ara_x_preferred":[
        "A\u0163 \u0162\u0101sh"
    ],
    "name:ara_x_variant":[
        "\u0627\u0644\u0637\u0627\u0634"
    ],
    "name:und_x_variant":[
        "Ett T\u00e2ch"
    ],
    "wof:name":"At Tash",
    "wof:placetype":"locality"
},
  "geometry": {"coordinates":[41.84767,36.81026],"type":"Point"}
}