{
  "type": "Feature",
  "properties": {
    "gn:admin1_code":"9.0",
    "gn:asciiname":"Rasm es Safa",
    "gn:country_code":"SY",
    "gn:dem":475,
    "gn:feature_class":"P",
    "gn:feature_code":"PPL",
    "gn:name":"Rasm es Safa",
    "gn:population":0,
    "gn:timezone":"Asia/Damascus",
    "iso:country":"SY",
    "name:ara_x_preferred":[
        "\u0631\u0633\u0645 \u0627\u0644\u0635\u0641\u0627"
    ],
    "name:ara_x_variant":[
        "\u0627\u0644\u0635\u0641\u0627"
    ],
    "name:und_x_variant":[
        "Rasm a\u015f \u015eaf\u0101",
        "A\u015f \u015eaf\u0101"
    ],
    "wof:name":"Rasm es Safa",
    "wof:placetype":"locality"
},
  "geometry": {"coordinates":[37.27412,36.00508],"type":"Point"}
}