{
  "type": "Feature",
  "properties": {
    "gn:admin1_code":"10.0",
    "gn:asciiname":"Abu Dali",
    "gn:country_code":"SY",
    "gn:dem":677,
    "gn:feature_class":"P",
    "gn:feature_code":"PPL",
    "gn:name":"Ab\u016b D\u0101l\u012b",
    "gn:population":0,
    "gn:timezone":"Asia/Damascus",
    "iso:country":"SY",
    "name:ara_x_preferred":[
        "Ab\u016b D\u0101l\u012b"
    ],
    "name:ara_x_variant":[
        "\u0623\u0628\u0648 \u062f\u0627\u0644\u064a"
    ],
    "name:und_x_variant":[
        "Abou D\u00e2li"
    ],
    "wof:name":"Abu Dali",
    "wof:placetype":"locality"
},
  "geometry": {"coordinates":[37.39189,35.03524],"type":"Point"}
}