{
  "type": "Feature",
  "properties": {
    "gn:admin1_code":"10.0",
    "gn:asciiname":"As Salaliyah",
    "gn:country_code":"SY",
    "gn:dem":684,
    "gn:feature_class":"P",
    "gn:feature_code":"PPL",
    "gn:name":"As Sal\u0101l\u012byah",
    "gn:population":0,
    "gn:timezone":"Asia/Damascus",
    "iso:country":"SY",
    "name:ara_x_preferred":[
        "\u0627\u0644\u0633\u0644\u0627\u0644\u064a\u0629"
    ],
    "name:und_x_variant":[
        "As Sal\u0101l\u012byah"
    ],
    "wof:name":"As Salaliyah",
    "wof:placetype":"locality"
},
  "geometry": {"coordinates":[37.52038,35.06462],"type":"Point"}
}