{
  "type": "Feature",
  "properties": {
    "gn:admin1_code":"13.0",
    "gn:asciiname":"Dummar",
    "gn:country_code":"SY",
    "gn:dem":767,
    "gn:feature_class":"P",
    "gn:feature_code":"PPL",
    "gn:name":"Dummar",
    "gn:population":0,
    "gn:timezone":"Asia/Damascus",
    "iso:country":"SY",
    "name:ara_x_preferred":[
        "\u062f\u0645\u0631"
    ],
    "name:ara_x_variant":[
        "\u0636\u0627\u062d\u064a\u0629 \u062f\u0645\u0631"
    ],
    "name:und_x_variant":[
        "Doumar",
        "Doummar",
        "Dummar",
        "\u1e10\u0101\u1e29iyat Dummar"
    ],
    "wof:name":"Dummar",
    "wof:placetype":"locality"
},
  "geometry": {"coordinates":[36.2436,33.53148],"type":"Point"}
}