{
  "type": "Feature",
  "properties": {
    "gn:admin1_code":"1.0",
    "gn:asciiname":"Ghardukah",
    "gn:country_code":"SY",
    "gn:dem":387,
    "gn:feature_class":"P",
    "gn:feature_code":"PPL",
    "gn:name":"Ghard\u016bkah",
    "gn:population":0,
    "gn:timezone":"Asia/Damascus",
    "iso:country":"SY",
    "name:ara_x_preferred":[
        "\u063a\u0631\u062f\u0648\u0643\u0629"
    ],
    "name:tur_x_preferred":[
        "Ghard\u016bgah"
    ],
    "name:und_x_variant":[
        "Rhardo\u00fbga",
        "Ghard\u016bqah",
        "Ghard\u016bkah"
    ],
    "wof:name":"Ghardukah",
    "wof:placetype":"locality"
},
  "geometry": {"coordinates":[41.55395,36.9502],"type":"Point"}
}