{
  "type": "Feature",
  "properties": {
    "gn:admin1_code":"12.0",
    "gn:asciiname":"Balqah",
    "gn:country_code":"SY",
    "gn:dem":481,
    "gn:feature_class":"P",
    "gn:feature_code":"PPL",
    "gn:name":"Balqah",
    "gn:population":0,
    "gn:timezone":"Asia/Damascus",
    "iso:country":"SY",
    "name:ara_x_preferred":[
        "\u0628\u0644\u0642\u0629"
    ],
    "name:und_x_variant":[
        "Balq\u0101\u2019",
        "Balqah"
    ],
    "wof:name":"Balqah",
    "wof:placetype":"locality"
},
  "geometry": {"coordinates":[36.79589,35.66345],"type":"Point"}
}