{
  "type": "Feature",
  "properties": {
    "gn:admin1_code":"2.0",
    "gn:asciiname":"Ar Rastin",
    "gn:country_code":"SY",
    "gn:dem":190,
    "gn:feature_class":"P",
    "gn:feature_code":"PPL",
    "gn:name":"Ar Rast\u012bn",
    "gn:population":0,
    "gn:timezone":"Asia/Damascus",
    "iso:country":"SY",
    "name:ara_x_preferred":[
        "B\u0101st\u012bn"
    ],
    "name:ara_x_variant":[
        "\u0628\u0627\u0633\u062a\u064a\u0646",
        "\u0627\u0644\u0631\u0633\u062a\u064a\u0646"
    ],
    "name:und_x_variant":[
        "Rast\u00eene",
        "Ar Rast\u012bn",
        "Y\u0101st\u012bn",
        "Ra\u2019s T\u012bn"
    ],
    "wof:name":"Ar Rastin",
    "wof:placetype":"locality"
},
  "geometry": {"coordinates":[35.9455,35.63176],"type":"Point"}
}