{
  "type": "Feature",
  "properties": {
    "gn:admin1_code":"9.0",
    "gn:asciiname":"As Sakhanah",
    "gn:country_code":"SY",
    "gn:dem":322,
    "gn:feature_class":"P",
    "gn:feature_code":"PPL",
    "gn:name":"As Sakhanah",
    "gn:population":0,
    "gn:timezone":"Asia/Damascus",
    "iso:country":"SY",
    "name:ara_x_preferred":[
        "\u0627\u0644\u0633\u062e\u0646\u0629"
    ],
    "name:und_x_variant":[
        "Soukhn\u00e9",
        "\u015eukhnah",
        "As Sakhanah"
    ],
    "wof:name":"As Sakhanah",
    "wof:placetype":"locality"
},
  "geometry": {"coordinates":[38.0631,36.21578],"type":"Point"}
}