{
  "type": "Feature",
  "properties": {
    "gn:admin1_code":"10.0",
    "gn:asciiname":"Jubb al Hintah",
    "gn:country_code":"SY",
    "gn:dem":305,
    "gn:feature_class":"P",
    "gn:feature_code":"PPL",
    "gn:name":"Jubb al \u1e28in\u0163ah",
    "gn:population":0,
    "gn:timezone":"Asia/Damascus",
    "iso:country":"SY",
    "name:ara_x_preferred":[
        "\u062c\u0628 \u0627\u0644\u062d\u0646\u0637\u0629"
    ],
    "name:und_x_variant":[
        "Joubb el Hinnta",
        "Jubb al \u1e28in\u0163ah"
    ],
    "wof:name":"Jubb al Hintah",
    "wof:placetype":"locality"
},
  "geometry": {"coordinates":[37.23626,35.48719000000001],"type":"Point"}
}