{
  "type": "Feature",
  "properties": {
    "gn:admin1_code":"9.0",
    "gn:asciiname":"Al Khadra'",
    "gn:country_code":"SY",
    "gn:dem":405,
    "gn:feature_class":"P",
    "gn:feature_code":"PPL",
    "gn:name":"Al Kha\u1e11r\u0101\u2019",
    "gn:population":0,
    "gn:timezone":"Asia/Damascus",
    "iso:country":"SY",
    "name:ara_x_preferred":[
        "\u062c\u0648\u064a\u0642"
    ],
    "name:ara_x_variant":[
        "\u0627\u0644\u062e\u0636\u0631\u0627\u0621"
    ],
    "name:kur_x_preferred":[
        "Coq\u00ea"
    ],
    "name:und_x_variant":[
        "Djiouik",
        "Joua\u00efq",
        "Juwayq",
        "Al Kha\u1e11r\u0101\u2019"
    ],
    "wof:name":"Al Khadra'",
    "wof:placetype":"locality"
},
  "geometry": {"coordinates":[36.79524,36.54089000000001],"type":"Point"}
}