{
  "type": "Feature",
  "properties": {
    "gn:admin1_code":"9.0",
    "gn:asciiname":"Bandirak",
    "gn:country_code":"SY",
    "gn:dem":535,
    "gn:feature_class":"P",
    "gn:feature_code":"PPL",
    "gn:name":"Bandirak",
    "gn:population":0,
    "gn:timezone":"Asia/Damascus",
    "iso:country":"SY",
    "name:ara_x_preferred":[
        "\u0628\u0646\u062f\u0647 \u0631\u0643"
    ],
    "name:ara_x_variant":[
        "\u0628\u0646\u062f\u0631\u0643",
        "\u0627\u0644\u0642\u0644\u0645"
    ],
    "name:und_x_variant":[
        "Benndirek",
        "Bendarak",
        "Bandirak",
        "Bandah Rak",
        "Al Qalam"
    ],
    "wof:name":"Bandirak",
    "wof:placetype":"locality"
},
  "geometry": {"coordinates":[36.7243,36.81786],"type":"Point"}
}