{
  "type": "Feature",
  "properties": {
    "gn:admin1_code":"1.0",
    "gn:asciiname":"Mutaybin",
    "gn:country_code":"SY",
    "gn:dem":236,
    "gn:feature_class":"P",
    "gn:feature_code":"PPLL",
    "gn:name":"Mutaybin",
    "gn:population":0,
    "gn:timezone":"Asia/Damascus",
    "iso:country":"SY",
    "name:ara_x_preferred":[
        "\u0645\u062a\u064a\u0628\u0646"
    ],
    "wof:name":"Mutaybin",
    "wof:placetype":"locality"
},
  "geometry": {"coordinates":[40.80277,35.75742],"type":"Point"}
}