{
  "type": "Feature",
  "properties": {
    "gn:admin1_code":"11.0",
    "gn:asciiname":"Barouha",
    "gn:country_code":"SY",
    "gn:dem":318,
    "gn:feature_class":"P",
    "gn:feature_code":"PPL",
    "gn:name":"Barouha",
    "gn:population":0,
    "gn:timezone":"Asia/Damascus",
    "iso:country":"SY",
    "name:ara_x_preferred":[
        "\u0628\u0627\u0631\u0648\u062d\u0629"
    ],
    "name:und_x_variant":[
        "B\u0101r\u016b\u1e29ah"
    ],
    "wof:name":"Barouha",
    "wof:placetype":"locality"
},
  "geometry": {"coordinates":[36.28134,34.6956],"type":"Point"}
}