{
  "type": "Feature",
  "properties": {
    "gn:admin1_code":"14.0",
    "gn:asciiname":"`Anayisah",
    "gn:country_code":"SY",
    "gn:dem":16,
    "gn:feature_class":"P",
    "gn:feature_code":"PPLL",
    "gn:name":"\u2018An\u0101yisah",
    "gn:population":0,
    "gn:timezone":"Asia/Damascus",
    "iso:country":"SY",
    "name:ara_x_preferred":[
        "\u0639\u0646\u0627\u064a\u0633\u0629"
    ],
    "name:und_x_variant":[
        "\u2018An\u0101yisah"
    ],
    "wof:name":"`Anayisah",
    "wof:placetype":"locality"
},
  "geometry": {"coordinates":[35.91873,34.81645],"type":"Point"}
}