{
  "type": "Feature",
  "properties": {
    "gn:admin1_code":"12.0",
    "gn:asciiname":"Ma`arrat Sin",
    "gn:country_code":"SY",
    "gn:dem":514,
    "gn:feature_class":"P",
    "gn:feature_code":"PPL",
    "gn:name":"Ma\u2018arrat \u015e\u012bn",
    "gn:population":0,
    "gn:timezone":"Asia/Damascus",
    "iso:country":"SY",
    "name:ara_x_preferred":[
        "\u0645\u0639\u0631\u0629 \u0635\u064a\u0646"
    ],
    "name:und_x_variant":[
        "Maarret S\u00eene",
        "Ma\u2018arrat \u015e\u012bn",
        "Ma\u2018arr Ta\u015f\u012bn",
        "Ma\u2018arrat\u015f\u012bn"
    ],
    "wof:name":"Ma`arrat Sin",
    "wof:placetype":"locality"
},
  "geometry": {"coordinates":[36.51809,35.57395],"type":"Point"}
}