{
  "type": "Feature",
  "properties": {
    "gn:admin1_code":"3.0",
    "gn:asciiname":"Al Bassali",
    "gn:country_code":"SY",
    "gn:dem":529,
    "gn:feature_class":"P",
    "gn:feature_code":"PPL",
    "gn:name":"Al Ba\u015f\u015f\u0101l\u012b",
    "gn:population":0,
    "gn:timezone":"Asia/Damascus",
    "iso:country":"SY",
    "name:ara_x_preferred":[
        "\u0627\u0644\u0628\u0635\u0651\u0627\u0644\u064a"
    ],
    "name:ara_x_variant":[
        "\u0627\u0644\u0628\u0635\u0629 \u0627\u0644\u0634\u0631\u0642\u064a\u0629"
    ],
    "name:und_x_variant":[
        "El Bassa",
        "Al Ba\u015f\u015fah",
        "Al Ba\u015f\u015f\u0101l\u012b",
        "Al Ba\u015f\u015fah ash Sharq\u012byah"
    ],
    "wof:name":"Al Bassali",
    "wof:placetype":"locality"
},
  "geometry": {"coordinates":[35.88457000000001,32.88924],"type":"Point"}
}