{
  "type": "Feature",
  "properties": {
    "gn:admin1_code":"9.0",
    "gn:asciiname":"Shallalah Kabirah",
    "gn:country_code":"SY",
    "gn:dem":329,
    "gn:feature_class":"P",
    "gn:feature_code":"PPL",
    "gn:name":"Shall\u0101lah Kab\u012brah",
    "gn:population":0,
    "gn:timezone":"Asia/Damascus",
    "iso:country":"SY",
    "name:ara_x_preferred":[
        "\u0634\u0644\u0627\u0644\u0629 \u0643\u0628\u064a\u0631\u0629"
    ],
    "name:und_x_variant":[
        "Chellal\u00e9 K\u00e9b\u00eer\u00e9",
        "Chell\u00e2li K\u00e9b\u00eer\u00e9",
        "Shall\u0101lah al Kab\u012brah",
        "Shall\u0101lah Kab\u012brah"
    ],
    "wof:name":"Shallalah Kabirah",
    "wof:placetype":"locality"
},
  "geometry": {"coordinates":[37.57332,35.85892],"type":"Point"}
}