{
  "type": "Feature",
  "properties": {
    "gn:admin1_code":"10.0",
    "gn:asciiname":"Kafr Kamrah",
    "gn:country_code":"SY",
    "gn:dem":672,
    "gn:feature_class":"P",
    "gn:feature_code":"PPL",
    "gn:name":"Kafr Kamrah",
    "gn:population":0,
    "gn:timezone":"Asia/Damascus",
    "iso:country":"SY",
    "name:ara_x_preferred":[
        "\u0643\u0641\u0631 \u0643\u0645\u0631\u0629"
    ],
    "name:und_x_variant":[
        "Kafer Kamra",
        "Kafr Kamrah",
        "Kefer Kamra"
    ],
    "wof:name":"Kafr Kamrah",
    "wof:placetype":"locality"
},
  "geometry": {"coordinates":[36.39953,34.89870999999999],"type":"Point"}
}