{
  "type": "Feature",
  "properties": {
    "gn:admin1_code":"12.0",
    "gn:asciiname":"Bab al Hawa",
    "gn:country_code":"SY",
    "gn:dem":404,
    "gn:feature_class":"P",
    "gn:feature_code":"PPL",
    "gn:name":"B\u0101b al Haw\u00e1",
    "gn:population":0,
    "gn:timezone":"Asia/Damascus",
    "iso:country":"SY",
    "name:ara_x_preferred":[
        "\u0628\u0627\u0628 \u0627\u0644\u0647\u0648\u0649"
    ],
    "name:und_x_variant":[
        "B\u0101b al Haw\u00e1"
    ],
    "wof:name":"Bab al Hawa",
    "wof:placetype":"locality"
},
  "geometry": {"coordinates":[36.4707,36.15727],"type":"Point"}
}