{
  "type": "Feature",
  "properties": {
    "gn:admin1_code":"12.0",
    "gn:asciiname":"Kafr Hatah",
    "gn:country_code":"SY",
    "gn:dem":278,
    "gn:feature_class":"P",
    "gn:feature_code":"PPL",
    "gn:name":"Kafr \u1e28\u0101tah",
    "gn:population":0,
    "gn:timezone":"Asia/Damascus",
    "iso:country":"SY",
    "name:ara_x_preferred":[
        "\u0643\u0641\u0631 \u062c\u0627\u062a"
    ],
    "name:ara_x_variant":[
        "\u0643\u0641\u0631 \u062d\u0627\u062a\u0629"
    ],
    "name:und_x_variant":[
        "Kafr J\u0101t",
        "Kafr \u1e28\u0101tah"
    ],
    "wof:name":"Kafr Hatah",
    "wof:placetype":"locality"
},
  "geometry": {"coordinates":[36.44617,36.16736],"type":"Point"}
}