{
  "type": "Feature",
  "properties": {
    "gn:admin1_code":"10.0",
    "gn:asciiname":"Az Zaytunah",
    "gn:cc2":"SY",
    "gn:country_code":"SY",
    "gn:dem":658,
    "gn:feature_class":"P",
    "gn:feature_code":"PPL",
    "gn:name":"Az Zayt\u016bnah",
    "gn:population":0,
    "gn:timezone":"Asia/Damascus",
    "iso:country":"SY",
    "name:und_x_variant":[
        "Ez Za\u00efto\u00fbn\u00e9",
        "Az Zayt\u016bnah"
    ],
    "wof:name":"Az Zaytunah",
    "wof:placetype":"locality"
},
  "geometry": {"coordinates":[36.21909,35.01235],"type":"Point"}
}