{
  "type": "Feature",
  "properties": {
    "gn:admin1_code":"12.0",
    "gn:asciiname":"Al Mushayrifah",
    "gn:country_code":"SY",
    "gn:dem":392,
    "gn:feature_class":"P",
    "gn:feature_code":"PPL",
    "gn:name":"Al Mushayrifah",
    "gn:population":0,
    "gn:timezone":"Asia/Damascus",
    "iso:country":"SY",
    "name:ara_x_preferred":[
        "\u0627\u0644\u0645\u0634\u064a\u0631"
    ],
    "name:ara_x_variant":[
        "\u0627\u0644\u0645\u0634\u064a\u0631\u0641\u0629"
    ],
    "name:ceb_x_preferred":[
        "Al Mushayrifah"
    ],
    "name:swe_x_preferred":[
        "Al Mushayrifah"
    ],
    "name:und_x_variant":[
        "El Mcha\u00efr",
        "El Mcha\u00efrf\u00e9",
        "Al Mushayr",
        "Al Mush\u012br"
    ],
    "wof:name":"Al Mushayrifah",
    "wof:placetype":"locality"
},
  "geometry": {"coordinates":[36.39094,35.76376],"type":"Point"}
}