{
  "type": "Feature",
  "properties": {
    "gn:admin1_code":"1.0",
    "gn:asciiname":"Umm al Ma`z",
    "gn:country_code":"SY",
    "gn:dem":326,
    "gn:feature_class":"P",
    "gn:feature_code":"PPL",
    "gn:name":"Umm al Ma\u2018z",
    "gn:population":0,
    "gn:timezone":"Asia/Damascus",
    "iso:country":"SY",
    "name:ara_x_preferred":[
        "\u0623\u0645 \u0627\u0644\u0645\u0639\u0632"
    ],
    "name:und_x_variant":[
        "Umm al Ma\u2018z"
    ],
    "wof:name":"Umm al Ma`z",
    "wof:placetype":"locality"
},
  "geometry": {"coordinates":[40.46713,36.09667],"type":"Point"}
}