{
  "type": "Feature",
  "properties": {
    "gn:admin1_code":"9.0",
    "gn:asciiname":"Al `Afsh",
    "gn:country_code":"SY",
    "gn:dem":380,
    "gn:feature_class":"P",
    "gn:feature_code":"PPL",
    "gn:name":"Al \u2018Afsh",
    "gn:population":0,
    "gn:timezone":"Asia/Damascus",
    "iso:country":"SY",
    "name:ara_x_preferred":[
        "Al \u2018Afsh"
    ],
    "name:ara_x_variant":[
        "\u0627\u0644\u0639\u0641\u0634"
    ],
    "name:und_x_variant":[
        "El Aaf\u00e9ch",
        "Al \u2018Afish",
        "El Afch",
        "\u2018Afsh",
        "El Afech"
    ],
    "wof:name":"Al `Afsh",
    "wof:placetype":"locality"
},
  "geometry": {"coordinates":[37.46388,36.21167],"type":"Point"}
}