{
  "type": "Feature",
  "properties": {
    "gn:admin1_code":"11.0",
    "gn:asciiname":"Khirbat Sinnu al Fadil",
    "gn:country_code":"SY",
    "gn:dem":1035,
    "gn:feature_class":"P",
    "gn:feature_code":"PPL",
    "gn:name":"Khirbat Sinn\u016b al F\u0101\u1e11il",
    "gn:population":0,
    "gn:timezone":"Asia/Damascus",
    "iso:country":"SY",
    "name:ara_x_preferred":[
        "\u062e\u0631\u0628\u0629 \u0633\u0646\u0648 \u0627\u0644\u0641\u0627\u0636\u0644"
    ],
    "name:und_x_variant":[
        "Khirbat Sinn\u016b al F\u0101\u1e11il"
    ],
    "wof:name":"Khirbat Sinnu al Fadil",
    "wof:placetype":"locality"
},
  "geometry": {"coordinates":[37.5708,34.89371],"type":"Point"}
}