{
  "type": "Feature",
  "properties": {
    "gn:admin1_code":"9.0",
    "gn:asciiname":"Ar Ridwaniyah",
    "gn:country_code":"SY",
    "gn:dem":353,
    "gn:feature_class":"P",
    "gn:feature_code":"PPL",
    "gn:name":"Ar Ri\u1e11w\u0101n\u012byah",
    "gn:population":0,
    "gn:timezone":"Asia/Damascus",
    "iso:country":"SY",
    "name:ara_x_preferred":[
        "\u0631\u0636\u0648\u0627\u0646\u064a\u0629"
    ],
    "name:ara_x_variant":[
        "\u0627\u0644\u0631\u0636\u0648\u0627\u0646\u064a\u0629"
    ],
    "name:und_x_variant":[
        "Radouani\u00e9",
        "Rodou\u00e2n\u00eey\u00e9",
        "Ri\u1e11w\u0101n\u012byah",
        "Ar Ri\u1e11w\u0101n\u012byah"
    ],
    "wof:name":"Ar Ridwaniyah",
    "wof:placetype":"locality"
},
  "geometry": {"coordinates":[37.42743,36.16054000000001],"type":"Point"}
}