{
  "type": "Feature",
  "properties": {
    "gn:admin1_code":"5.0",
    "gn:asciiname":"Lahithah",
    "gn:country_code":"SY",
    "gn:dem":785,
    "gn:feature_class":"P",
    "gn:feature_code":"PPL",
    "gn:name":"L\u0101hithah",
    "gn:population":0,
    "gn:timezone":"Asia/Damascus",
    "iso:country":"SY",
    "name:ara_x_preferred":[
        "\u0644\u0627\u0647\u062b\u0629"
    ],
    "name:und_x_variant":[
        "Lah\u00eet\u00e9",
        "Lahet\u00e9",
        "La\u1e29\u012btih",
        "L\u0101hithah"
    ],
    "wof:name":"Lahithah",
    "wof:placetype":"locality"
},
  "geometry": {"coordinates":[36.58308,32.99333],"type":"Point"}
}