{
  "type": "Feature",
  "properties": {
    "gn:admin1_code":"1.0",
    "gn:asciiname":"Tall al Umara'",
    "gn:country_code":"SY",
    "gn:dem":424,
    "gn:feature_class":"P",
    "gn:feature_code":"PPL",
    "gn:name":"Tall al Umar\u0101\u2019",
    "gn:population":0,
    "gn:timezone":"Asia/Damascus",
    "iso:country":"SY",
    "name:ara_x_preferred":[
        "\u062a\u0644 \u0627\u0644\u0627\u0645\u0631\u0627\u0621"
    ],
    "name:ara_x_variant":[
        "\u0643\u064a\u0631\u0643"
    ],
    "name:kur_x_preferred":[
        "\u06af\u0631\u0643\u0627 \u0645\u064a\u0631\u06c6"
    ],
    "name:und_x_variant":[
        "Guirek",
        "K\u012brak",
        "Tall al Umar\u0101\u2019",
        "Girka M\u00eero",
        "\u0643\u0631\u0643\u064a \u0645\u064a\u0631\u0648"
    ],
    "wof:name":"Tall al Umara'",
    "wof:placetype":"locality"
},
  "geometry": {"coordinates":[42.21773,37.14364000000001],"type":"Point"}
}