{
  "type": "Feature",
  "properties": {
    "gn:admin1_code":"1.0",
    "gn:asciiname":"Turbah",
    "gn:country_code":"SY",
    "gn:dem":447,
    "gn:feature_class":"P",
    "gn:feature_code":"PPL",
    "gn:name":"Turbah",
    "gn:population":0,
    "gn:timezone":"Asia/Damascus",
    "iso:country":"SY",
    "name:ara_x_preferred":[
        "\u062a\u0631\u0628\u0629"
    ],
    "name:tur_x_preferred":[
        "Turbah"
    ],
    "name:und_x_variant":[
        "Terb\u00e9",
        "Turbah"
    ],
    "wof:name":"Turbah",
    "wof:placetype":"locality"
},
  "geometry": {"coordinates":[40.5331,36.9638],"type":"Point"}
}