{
  "type": "Feature",
  "properties": {
    "gn:admin1_code":"9.0",
    "gn:asciiname":"Jibrin",
    "gn:country_code":"SY",
    "gn:dem":389,
    "gn:feature_class":"P",
    "gn:feature_code":"PPL",
    "gn:name":"Jibr\u012bn",
    "gn:population":0,
    "gn:timezone":"Asia/Damascus",
    "iso:country":"SY",
    "name:ara_x_preferred":[
        "Jibr\u012bn"
    ],
    "name:ara_x_variant":[
        "\u062c\u0628\u0631\u064a\u0646"
    ],
    "name:fas_x_preferred":[
        "\u062c\u0628\u0631\u06cc\u0646"
    ],
    "name:pol_x_preferred":[
        "D\u017cibrin"
    ],
    "name:und_x_variant":[
        "Djibrine",
        "Jibr\u00eene",
        "Jibr\u00eer"
    ],
    "name:vie_x_preferred":[
        "Jibrin"
    ],
    "wof:name":"Jibrin",
    "wof:placetype":"locality"
},
  "geometry": {"coordinates":[37.25531,36.18292],"type":"Point"}
}