{
  "type": "Feature",
  "properties": {
    "gn:admin1_code":"9.0",
    "gn:asciiname":"Sad`aya",
    "gn:country_code":"SY",
    "gn:dem":457,
    "gn:feature_class":"P",
    "gn:feature_code":"PPL",
    "gn:name":"\u015ead\u2018\u0101y\u0101",
    "gn:population":0,
    "gn:timezone":"Asia/Damascus",
    "iso:country":"SY",
    "name:ara_x_preferred":[
        "\u0635\u062f\u0639\u0627\u064a\u0627"
    ],
    "name:und_x_variant":[
        "Seda\u00efa",
        "Sada\u00e2ya",
        "Sad\u2018\u0101y\u0101",
        "\u015ead\u2018\u0101y\u0101"
    ],
    "wof:name":"Sad`aya",
    "wof:placetype":"locality"
},
  "geometry": {"coordinates":[37.26247,36.04342000000001],"type":"Point"}
}