{
  "type": "Feature",
  "properties": {
    "gn:admin1_code":"11.0",
    "gn:asciiname":"`Ayn al Qatt",
    "gn:country_code":"SY",
    "gn:dem":817,
    "gn:feature_class":"P",
    "gn:feature_code":"PPL",
    "gn:name":"\u2018Ayn al Qa\u0163\u0163",
    "gn:population":0,
    "gn:timezone":"Asia/Damascus",
    "iso:country":"SY",
    "name:ara_x_preferred":[
        "\u0639\u064a\u0646 \u0627\u0644\u0642\u0637"
    ],
    "name:und_x_variant":[
        "A\u00efn el Qott",
        "\u2018Ayn al Qu\u0163\u0163",
        "\u2018Ayn al Qa\u0163\u0163"
    ],
    "wof:name":"`Ayn al Qatt",
    "wof:placetype":"locality"
},
  "geometry": {"coordinates":[36.38822,34.80254],"type":"Point"}
}