{
  "type": "Feature",
  "properties": {
    "gn:admin1_code":"1.0",
    "gn:asciiname":"Tall Birak",
    "gn:country_code":"SY",
    "gn:dem":334,
    "gn:feature_class":"P",
    "gn:feature_code":"PPL",
    "gn:name":"Tall Bir\u0101k",
    "gn:population":0,
    "gn:timezone":"Asia/Damascus",
    "iso:country":"SY",
    "name:ara_x_preferred":[
        "\u062a\u0644 \u0628\u0631\u0627\u0643"
    ],
    "name:und_x_variant":[
        "Tell Br\u00e2k",
        "Tall Bir\u0101k Ta\u1e29t\u0101n\u012b",
        "Tall Bir\u0101k"
    ],
    "wof:name":"Tall Birak",
    "wof:placetype":"locality"
},
  "geometry": {"coordinates":[41.08281,36.64869],"type":"Point"}
}