{
  "type": "Feature",
  "properties": {
    "gn:admin1_code":"2.0",
    "gn:asciiname":"Juwayb Qarahilah",
    "gn:country_code":"SY",
    "gn:dem":678,
    "gn:feature_class":"P",
    "gn:feature_code":"PPL",
    "gn:name":"Juwayb Qar\u0101\u1e29ilah",
    "gn:population":0,
    "gn:timezone":"Asia/Damascus",
    "iso:country":"SY",
    "name:ara_x_preferred":[
        "\u062c\u0648\u064a\u0628 \u0642\u0631\u0627\u062d\u0644\u0629"
    ],
    "name:und_x_variant":[
        "Juwa\u2019ib Qrahla",
        "Joua\u00efb Qr\u00e2hl\u00e9",
        "Juwayb Qar\u0101\u1e29ilah"
    ],
    "wof:name":"Juwayb Qarahilah",
    "wof:placetype":"locality"
},
  "geometry": {"coordinates":[36.05529,35.2644],"type":"Point"}
}