{
  "type": "Feature",
  "properties": {
    "gn:admin1_code":"2.0",
    "gn:asciiname":"`Ayn al Bayda",
    "gn:country_code":"SY",
    "gn:dem":419,
    "gn:feature_class":"P",
    "gn:feature_code":"PPL",
    "gn:name":"\u2018Ayn al Bay\u1e11\u0101",
    "gn:population":0,
    "gn:timezone":"Asia/Damascus",
    "iso:country":"SY",
    "name:ara_x_preferred":[
        "\u0639\u064a\u0646 \u0627\u0644\u0628\u064a\u0636\u0627"
    ],
    "name:und_x_variant":[
        "A\u00efn el Be\u00efda",
        "\u2018Ayn al Bay\u1e11\u0101\u2019",
        "\u2018Ayn al Bay\u1e11\u0101"
    ],
    "wof:name":"`Ayn al Bayda",
    "wof:placetype":"locality"
},
  "geometry": {"coordinates":[36.15391,35.77137000000001],"type":"Point"}
}