{
  "type": "Feature",
  "properties": {
    "gn:admin1_code":"10.0",
    "gn:asciiname":"At Turaymisah",
    "gn:country_code":"SY",
    "gn:dem":196,
    "gn:feature_class":"P",
    "gn:feature_code":"PPL",
    "gn:name":"At Turaymisah",
    "gn:population":0,
    "gn:timezone":"Asia/Damascus",
    "iso:country":"SY",
    "name:ara_x_preferred":[
        "\u0627\u0644\u062a\u0631\u064a\u0645\u0633\u0629"
    ],
    "name:und_x_variant":[
        "Ett Tra\u00efms\u00e9",
        "Ett Tra\u00efmiss\u00e9",
        "At Turaym\u012bsah",
        "At Turaymisah"
    ],
    "wof:name":"At Turaymisah",
    "wof:placetype":"locality"
},
  "geometry": {"coordinates":[36.50236,35.27187],"type":"Point"}
}