{
  "type": "Feature",
  "properties": {
    "gn:admin1_code":"2.0",
    "gn:asciiname":"Jaqruran",
    "gn:country_code":"SY",
    "gn:dem":287,
    "gn:feature_class":"P",
    "gn:feature_code":"PPL",
    "gn:name":"Jaqr\u016br\u0101n",
    "gn:population":0,
    "gn:timezone":"Asia/Damascus",
    "iso:country":"SY",
    "name:und_x_variant":[
        "Jaqr\u016br\u0101n"
    ],
    "wof:name":"Jaqruran",
    "wof:placetype":"locality"
},
  "geometry": {"coordinates":[35.9625,35.75417],"type":"Point"}
}