{
  "type": "Feature",
  "properties": {
    "gn:admin1_code":"9.0",
    "gn:asciiname":"Al Burayj",
    "gn:country_code":"SY",
    "gn:dem":453,
    "gn:feature_class":"P",
    "gn:feature_code":"PPL",
    "gn:name":"Al Burayj",
    "gn:population":0,
    "gn:timezone":"Asia/Damascus",
    "iso:country":"SY",
    "name:ara_x_preferred":[
        "\u0627\u0644\u0628\u0631\u064a\u062c"
    ],
    "name:und_x_variant":[
        "Bra\u00efj",
        "Brege",
        "Breige",
        "Burayj",
        "Al Burayj"
    ],
    "wof:name":"Al Burayj",
    "wof:placetype":"locality"
},
  "geometry": {"coordinates":[36.85209,36.25225],"type":"Point"}
}