{
  "type": "Feature",
  "properties": {
    "gn:admin1_code":"14.0",
    "gn:asciiname":"Baydar al Balat",
    "gn:country_code":"SY",
    "gn:dem":53,
    "gn:feature_class":"P",
    "gn:feature_code":"PPL",
    "gn:name":"Baydar al Bal\u0101\u0163",
    "gn:population":0,
    "gn:timezone":"Asia/Damascus",
    "iso:country":"SY",
    "name:ara_x_preferred":[
        "\u0628\u064a\u062f\u0631 \u0627\u0644\u0628\u0644\u0627\u0637"
    ],
    "name:und_x_variant":[
        "Baydar al Bal\u0101\u0163"
    ],
    "wof:name":"Baydar al Balat",
    "wof:placetype":"locality"
},
  "geometry": {"coordinates":[35.96672,34.80718],"type":"Point"}
}