{
  "type": "Feature",
  "properties": {
    "gn:admin1_code":"6.0",
    "gn:asciiname":"Judayyah",
    "gn:country_code":"SY",
    "gn:dem":684,
    "gn:feature_class":"P",
    "gn:feature_code":"PPL",
    "gn:name":"Judayyah",
    "gn:population":0,
    "gn:timezone":"Asia/Damascus",
    "iso:country":"SY",
    "name:ara_x_preferred":[
        "\u062c\u062f\u064a\u0629"
    ],
    "name:und_x_variant":[
        "Jad\u012byah",
        "Jadd\u012byah",
        "Jde\u00efy\u00e9",
        "Judayyah"
    ],
    "wof:name":"Judayyah",
    "wof:placetype":"locality"
},
  "geometry": {"coordinates":[36.10883,33.06494],"type":"Point"}
}