{
  "type": "Feature",
  "properties": {
    "gn:admin1_code":"9.0",
    "gn:asciiname":"Halwanji",
    "gn:country_code":"SY",
    "gn:dem":403,
    "gn:feature_class":"P",
    "gn:feature_code":"PPL",
    "gn:name":"\u1e28alw\u0101nj\u012b",
    "gn:population":0,
    "gn:timezone":"Asia/Damascus",
    "iso:country":"SY",
    "name:ara_x_preferred":[
        "\u062d\u0644\u0648\u0627\u0646\u062c\u064a"
    ],
    "name:und_x_variant":[
        "Halo\u00fbannji",
        "\u1e28alw\u0101nj\u012b"
    ],
    "wof:name":"Halwanji",
    "wof:placetype":"locality"
},
  "geometry": {"coordinates":[37.91023,36.64912],"type":"Point"}
}