{
  "type": "Feature",
  "properties": {
    "gn:admin1_code":"1.0",
    "gn:asciiname":"Quldman",
    "gn:country_code":"SY",
    "gn:dem":467,
    "gn:feature_class":"P",
    "gn:feature_code":"PPL",
    "gn:name":"Quldm\u0101n",
    "gn:population":0,
    "gn:timezone":"Asia/Damascus",
    "iso:country":"SY",
    "name:ara_x_preferred":[
        "Quldm\u0101n"
    ],
    "name:ara_x_variant":[
        "\u0642\u0644\u062f\u0645\u0627\u0646",
        "\u0627\u0644\u0646\u062c\u0641"
    ],
    "name:kur_x_preferred":[
        "Qul Duman"
    ],
    "name:und_x_variant":[
        "Qulduman",
        "An Najaf",
        "\u0642\u0644 \u062f\u0648\u0645\u0627\u0646"
    ],
    "wof:name":"Quldman",
    "wof:placetype":"locality"
},
  "geometry": {"coordinates":[42.18829,36.96275],"type":"Point"}
}