{
  "type": "Feature",
  "properties": {
    "gn:admin1_code":"9.0",
    "gn:asciiname":"Taftiyah",
    "gn:country_code":"SY",
    "gn:dem":432,
    "gn:feature_class":"P",
    "gn:feature_code":"PPL",
    "gn:name":"Taft\u012byah",
    "gn:population":0,
    "gn:timezone":"Asia/Damascus",
    "iso:country":"SY",
    "name:ara_x_preferred":[
        "\u062a\u0641\u062a\u064a\u0629"
    ],
    "name:und_x_variant":[
        "Taft\u012byah"
    ],
    "wof:name":"Taftiyah",
    "wof:placetype":"locality"
},
  "geometry": {"coordinates":[37.6308,36.31317],"type":"Point"}
}