{
  "type": "Feature",
  "properties": {
    "gn:admin1_code":"8.0",
    "gn:asciiname":"Khirbat Qamit",
    "gn:country_code":"SY",
    "gn:dem":724,
    "gn:feature_class":"P",
    "gn:feature_code":"PPL",
    "gn:name":"Khirbat Qam\u012b\u0163",
    "gn:population":0,
    "gn:timezone":"Asia/Damascus",
    "iso:country":"SY",
    "name:ara_x_preferred":[
        "\u062e\u0631\u0628\u0629 \u0642\u0645\u064a\u0637"
    ],
    "name:und_x_variant":[
        "Khirbat Qam\u012b\u0163"
    ],
    "wof:name":"Khirbat Qamit",
    "wof:placetype":"locality"
},
  "geometry": {"coordinates":[36.19237,33.26818],"type":"Point"}
}