{
  "type": "Feature",
  "properties": {
    "gn:admin1_code":"2.0",
    "gn:asciiname":"Qasiyah",
    "gn:country_code":"SY",
    "gn:dem":69,
    "gn:feature_class":"P",
    "gn:feature_code":"PPL",
    "gn:name":"Q\u0101\u015fiyah",
    "gn:population":0,
    "gn:timezone":"Asia/Damascus",
    "iso:country":"SY",
    "name:ara_x_preferred":[
        "\u0642\u0627\u0633\u064a\u0629"
    ],
    "name:ara_x_variant":[
        "\u0642\u0627\u0635\u064a\u0629"
    ],
    "name:und_x_variant":[
        "Q\u00e2ssi\u00e9",
        "Q\u0101siyah",
        "Q\u0101\u015fiyah"
    ],
    "wof:name":"Qasiyah",
    "wof:placetype":"locality"
},
  "geometry": {"coordinates":[35.94162,35.56318],"type":"Point"}
}