{
  "type": "Feature",
  "properties": {
    "gn:admin1_code":"1.0",
    "gn:asciiname":"Al Wa`rah",
    "gn:country_code":"SY",
    "gn:dem":395,
    "gn:feature_class":"P",
    "gn:feature_code":"PPL",
    "gn:name":"Al Wa\u2018rah",
    "gn:population":0,
    "gn:timezone":"Asia/Damascus",
    "iso:country":"SY",
    "name:ara_x_preferred":[
        "\u0627\u0644\u0648\u0639\u0631\u0629"
    ],
    "name:tur_x_preferred":[
        "Al Wa\u2018irah"
    ],
    "name:und_x_variant":[
        "Ou\u00e2ra",
        "W\u0101rah",
        "Al Wa\u2018rah"
    ],
    "wof:name":"Al Wa`rah",
    "wof:placetype":"locality"
},
  "geometry": {"coordinates":[41.63807,36.90958],"type":"Point"}
}