{
  "type": "Feature",
  "properties": {
    "gn:admin1_code":"14.0",
    "gn:asciiname":"Khirbat al Qabw",
    "gn:country_code":"SY",
    "gn:dem":655,
    "gn:feature_class":"P",
    "gn:feature_code":"PPL",
    "gn:name":"Khirbat al Qabw",
    "gn:population":0,
    "gn:timezone":"Asia/Damascus",
    "iso:country":"SY",
    "name:ara_x_preferred":[
        "\u062e\u0631\u0628\u0629 \u0627\u0644\u0642\u0628\u0648"
    ],
    "name:und_x_variant":[
        "Kheurbet el Qabou",
        "Khirbat al Qabw"
    ],
    "wof:name":"Khirbat al Qabw",
    "wof:placetype":"locality"
},
  "geometry": {"coordinates":[36.07984,35.09713],"type":"Point"}
}