{
  "type": "Feature",
  "properties": {
    "gn:admin1_code":"10.0",
    "gn:asciiname":"Abu al Qudur",
    "gn:country_code":"SY",
    "gn:dem":447,
    "gn:feature_class":"P",
    "gn:feature_code":"PPL",
    "gn:name":"Ab\u016b al Qud\u016br",
    "gn:population":0,
    "gn:timezone":"Asia/Damascus",
    "iso:country":"SY",
    "name:ara_x_preferred":[
        "\u0623\u0628\u0648 \u0627\u0644\u0642\u062f\u0648\u0631"
    ],
    "name:und_x_variant":[
        "Abou el Qdo\u00fbr",
        "Ab\u016b al Qud\u016br"
    ],
    "wof:name":"Abu al Qudur",
    "wof:placetype":"locality"
},
  "geometry": {"coordinates":[37.02385,35.28097],"type":"Point"}
}