{
  "type": "Feature",
  "properties": {
    "gn:admin1_code":"14.0",
    "gn:asciiname":"Na`lat `Ayn Saq",
    "gn:country_code":"SY",
    "gn:dem":5,
    "gn:feature_class":"P",
    "gn:feature_code":"PPL",
    "gn:name":"Na\u2018lat \u2018Ayn S\u0101q",
    "gn:population":0,
    "gn:timezone":"Asia/Damascus",
    "iso:country":"SY",
    "name:ara_x_preferred":[
        "\u0646\u0639\u0644\u0629 \u0639\u064a\u0646 \u0633\u0627\u0642"
    ],
    "name:und_x_variant":[
        "Na\u2018lat \u2018Ayn S\u0101q"
    ],
    "wof:name":"Na`lat `Ayn Saq",
    "wof:placetype":"locality"
},
  "geometry": {"coordinates":[35.91804000000001,34.80693],"type":"Point"}
}