{
  "type": "Feature",
  "properties": {
    "gn:admin1_code":"11.0",
    "gn:asciiname":"Bayt ar Rafi`ah",
    "gn:country_code":"SY",
    "gn:dem":867,
    "gn:feature_class":"P",
    "gn:feature_code":"PPL",
    "gn:name":"Bayt ar Raf\u012b\u2018ah",
    "gn:population":0,
    "gn:timezone":"Asia/Damascus",
    "iso:country":"SY",
    "name:ara_x_preferred":[
        "\u0628\u064a\u062a \u0627\u0644\u0631\u0641\u064a\u0639\u0629"
    ],
    "name:ara_x_variant":[
        "\u0628\u064a\u062f\u0631 \u0631\u0641\u064a\u0639"
    ],
    "name:und_x_variant":[
        "Be\u00eft er Raf\u00eeaa",
        "Be\u00eft al Rafi\u2019ah",
        "Bayt ar Raf\u012b\u2018ah",
        "Baydar Raf\u012b\u2018"
    ],
    "wof:name":"Bayt ar Rafi`ah",
    "wof:placetype":"locality"
},
  "geometry": {"coordinates":[36.31313,34.85777],"type":"Point"}
}