{
  "type": "Feature",
  "properties": {
    "gn:admin1_code":"1.0",
    "gn:asciiname":"Khirbat Ghadir",
    "gn:country_code":"SY",
    "gn:dem":403,
    "gn:feature_class":"P",
    "gn:feature_code":"PPL",
    "gn:name":"Khirbat Ghad\u012br",
    "gn:population":0,
    "gn:timezone":"Asia/Damascus",
    "iso:country":"SY",
    "name:ara_x_preferred":[
        "\u062e\u0631\u0628\u0629 \u063a\u062f\u064a\u0631"
    ],
    "name:tur_x_preferred":[
        "Khirbat Ghad\u012br"
    ],
    "name:und_x_variant":[
        "Kheurbet Rhad\u00eer",
        "Khirbat Ghad\u012br"
    ],
    "wof:name":"Khirbat Ghadir",
    "wof:placetype":"locality"
},
  "geometry": {"coordinates":[40.767,36.86801],"type":"Point"}
}