{
  "type": "Feature",
  "properties": {
    "gn:admin1_code":"9.0",
    "gn:asciiname":"Karbajak",
    "gn:country_code":"SY",
    "gn:dem":559,
    "gn:feature_class":"P",
    "gn:feature_code":"PPL",
    "gn:name":"Karbajak",
    "gn:population":0,
    "gn:timezone":"Asia/Damascus",
    "iso:country":"SY",
    "wof:name":"Karbajak",
    "wof:placetype":"locality"
},
  "geometry": {"coordinates":[38.2375,36.89583],"type":"Point"}
}