{
  "type": "Feature",
  "properties": {
    "gn:admin1_code":"1.0",
    "gn:asciiname":"As Safh",
    "gn:country_code":"SY",
    "gn:dem":508,
    "gn:feature_class":"P",
    "gn:feature_code":"PPL",
    "gn:name":"As Saf\u1e29",
    "gn:population":0,
    "gn:timezone":"Asia/Damascus",
    "iso:country":"SY",
    "name:ara_x_preferred":[
        "\u0627\u0644\u0633\u0641\u062d"
    ],
    "name:und_x_variant":[
        "As Saf\u1e29"
    ],
    "wof:name":"As Safh",
    "wof:placetype":"locality"
},
  "geometry": {"coordinates":[42.06094,37.14531],"type":"Point"}
}