{
  "type": "Feature",
  "properties": {
    "gn:admin1_code":"9.0",
    "gn:asciiname":"Haddadin",
    "gn:country_code":"SY",
    "gn:dem":377,
    "gn:feature_class":"P",
    "gn:feature_code":"PPL",
    "gn:name":"\u1e28add\u0101d\u012bn",
    "gn:population":0,
    "gn:timezone":"Asia/Damascus",
    "iso:country":"SY",
    "name:ara_x_preferred":[
        "\u062d\u062f\u0627\u062f\u064a\u0646"
    ],
    "name:und_x_variant":[
        "Hadd\u00e2d\u00eene",
        "\u1e28add\u0101d\u012bn"
    ],
    "wof:name":"Haddadin",
    "wof:placetype":"locality"
},
  "geometry": {"coordinates":[37.16915,36.10126],"type":"Point"}
}