{
  "type": "Feature",
  "properties": {
    "gn:admin1_code":"9.0",
    "gn:asciiname":"Umm `Amud",
    "gn:country_code":"SY",
    "gn:dem":334,
    "gn:feature_class":"P",
    "gn:feature_code":"PPL",
    "gn:name":"Umm \u2018Am\u016bd",
    "gn:population":0,
    "gn:timezone":"Asia/Damascus",
    "iso:country":"SY",
    "name:ara_x_preferred":[
        "Umm \u2018\u0100m\u016bd"
    ],
    "name:ara_x_variant":[
        "\u0623\u0645 \u0639\u0627\u0645\u0648\u062f",
        "Umm \u2018Am\u016bd",
        "\u0623\u0645 \u0639\u0645\u0648\u062f"
    ],
    "name:und_x_variant":[
        "Oum el Aamo\u00fbd",
        "Umm al \u2018\u0100m\u016bd"
    ],
    "wof:name":"Umm `Amud",
    "wof:placetype":"locality"
},
  "geometry": {"coordinates":[37.55164,35.97539000000001],"type":"Point"}
}