{
  "type": "Feature",
  "properties": {
    "gn:admin1_code":"3.0",
    "gn:asciiname":"Hadar",
    "gn:country_code":"SY",
    "gn:dem":1272,
    "gn:feature_class":"P",
    "gn:feature_code":"PPL",
    "gn:name":"\u1e28a\u1e11ar",
    "gn:population":0,
    "gn:timezone":"Asia/Damascus",
    "iso:country":"SY",
    "name:ara_x_preferred":[
        "\u062d\u0636\u0631"
    ],
    "name:fas_x_preferred":[
        "\u062d\u0636\u0631"
    ],
    "name:heb_x_preferred":[
        "\u05d7\u05d3\u05e8"
    ],
    "name:pol_x_preferred":[
        "Hadar"
    ],
    "name:und_x_variant":[
        "\u1e28a\u1e11ar"
    ],
    "name:vie_x_preferred":[
        "Hader"
    ],
    "wof:name":"Hadar",
    "wof:placetype":"locality"
},
  "geometry": {"coordinates":[35.83043,33.28098],"type":"Point"}
}