{
  "type": "Feature",
  "properties": {
    "gn:admin1_code":"7.0",
    "gn:asciiname":"Al Ghawwari",
    "gn:country_code":"SY",
    "gn:dem":216,
    "gn:feature_class":"P",
    "gn:feature_code":"PPL",
    "gn:name":"Al Ghaww\u0101r\u012b",
    "gn:population":0,
    "gn:timezone":"Asia/Damascus",
    "iso:country":"SY",
    "name:ara_x_preferred":[
        "\u0627\u0644\u063a\u0648\u0627\u0631\u064a"
    ],
    "name:und_x_variant":[
        "Al Ghaww\u0101r\u012b",
        "Al Ghaw\u0101r\u012b"
    ],
    "wof:name":"Al Ghawwari",
    "wof:placetype":"locality"
},
  "geometry": {"coordinates":[40.59468,35.36954],"type":"Point"}
}