{
  "type": "Feature",
  "properties": {
    "gn:admin1_code":"9.0",
    "gn:asciiname":"Karbalak",
    "gn:country_code":"SY",
    "gn:dem":461,
    "gn:feature_class":"P",
    "gn:feature_code":"PPL",
    "gn:name":"Karbalak",
    "gn:population":0,
    "gn:timezone":"Asia/Damascus",
    "iso:country":"SY",
    "wof:name":"Karbalak",
    "wof:placetype":"locality"
},
  "geometry": {"coordinates":[38.55278,36.73333],"type":"Point"}
}