{
  "type": "Feature",
  "properties": {
    "gn:admin1_code":"1.0",
    "gn:asciiname":"Khirbat as Suwaydiyah",
    "gn:country_code":"SY",
    "gn:dem":320,
    "gn:feature_class":"P",
    "gn:feature_code":"PPL",
    "gn:name":"Khirbat as Suwayd\u012byah",
    "gn:population":0,
    "gn:timezone":"Asia/Damascus",
    "iso:country":"SY",
    "name:ara_x_preferred":[
        "\u062e\u0631\u0628\u0629 \u0627\u0644\u0633\u0648\u064a\u062f\u064a\u0629"
    ],
    "name:und_x_variant":[
        "Khirbat as Suwayd\u012byah"
    ],
    "wof:name":"Khirbat as Suwaydiyah",
    "wof:placetype":"locality"
},
  "geometry": {"coordinates":[40.57769,36.20554],"type":"Point"}
}