{
  "type": "Feature",
  "properties": {
    "gn:admin1_code":"9.0",
    "gn:asciiname":"Abu al Kahf",
    "gn:country_code":"SY",
    "gn:dem":466,
    "gn:feature_class":"P",
    "gn:feature_code":"PPL",
    "gn:name":"Ab\u016b al Kahf",
    "gn:population":0,
    "gn:timezone":"Asia/Damascus",
    "iso:country":"SY",
    "name:ara_x_preferred":[
        "\u0623\u0628\u0648 \u0627\u0644\u0643\u0647\u0641"
    ],
    "name:und_x_variant":[
        "Abou el Kheff",
        "Abou el Kahf",
        "Abou Kahf",
        "Ab\u016b al Kahf"
    ],
    "wof:name":"Abu al Kahf",
    "wof:placetype":"locality"
},
  "geometry": {"coordinates":[37.83651,36.35775],"type":"Point"}
}