{
  "type": "Feature",
  "properties": {
    "gn:admin1_code":"10.0",
    "gn:asciiname":"Hasan al Malham",
    "gn:country_code":"SY",
    "gn:dem":550,
    "gn:feature_class":"P",
    "gn:feature_code":"PPL",
    "gn:name":"\u1e28asan al Mal\u1e29am",
    "gn:population":0,
    "gn:timezone":"Asia/Damascus",
    "iso:country":"SY",
    "name:ara_x_preferred":[
        "\u062d\u0633\u0646 \u0627\u0644\u0645\u0644\u062d\u0645"
    ],
    "name:und_x_variant":[
        "\u1e28asan al Mal\u1e29am"
    ],
    "wof:name":"Hasan al Malham",
    "wof:placetype":"locality"
},
  "geometry": {"coordinates":[37.19345,35.05584],"type":"Point"}
}