{
  "type": "Feature",
  "properties": {
    "gn:admin1_code":"9.0",
    "gn:asciiname":"Kuwayris Burayj Gharbi",
    "gn:country_code":"SY",
    "gn:dem":356,
    "gn:feature_class":"P",
    "gn:feature_code":"PPL",
    "gn:name":"Kuwayris Burayj Gharb\u012b",
    "gn:population":0,
    "gn:timezone":"Asia/Damascus",
    "iso:country":"SY",
    "name:ara_x_preferred":[
        "\u0643\u0648\u064a\u0631\u0633 \u0628\u0631\u064a\u062c \u063a\u0631\u0628\u064a"
    ],
    "name:und_x_variant":[
        "Koua\u00efres Gharbi",
        "Koua\u00efr\u00e9s Bra\u00efj Rharbi",
        "Koua\u00efr\u00e8s el Rharbi",
        "Kuwayris Burayj al Gharb\u012b",
        "Kuwayris Burayj Gharb\u012b"
    ],
    "wof:name":"Kuwayris Burayj Gharbi",
    "wof:placetype":"locality"
},
  "geometry": {"coordinates":[37.5139,36.16651],"type":"Point"}
}