{
  "type": "Feature",
  "properties": {
    "gn:admin1_code":"9.0",
    "gn:asciiname":"Jubb al Kalb al Kabir",
    "gn:country_code":"SY",
    "gn:dem":471,
    "gn:feature_class":"P",
    "gn:feature_code":"PPL",
    "gn:name":"Jubb al Kalb al Kab\u012br",
    "gn:population":0,
    "gn:timezone":"Asia/Damascus",
    "iso:country":"SY",
    "name:und_x_variant":[
        "Joubb el Kelb K\u00e9b\u00eer",
        "Jubb al Kalb al Kab\u012br"
    ],
    "wof:name":"Jubb al Kalb al Kabir",
    "wof:placetype":"locality"
},
  "geometry": {"coordinates":[38.07983,36.56484],"type":"Point"}
}