{
  "type": "Feature",
  "properties": {
    "gn:admin1_code":"2.0",
    "gn:asciiname":"Shumaysah",
    "gn:country_code":"SY",
    "gn:dem":257,
    "gn:feature_class":"P",
    "gn:feature_code":"PPL",
    "gn:name":"Shumaysah",
    "gn:population":0,
    "gn:timezone":"Asia/Damascus",
    "iso:country":"SY",
    "name:ara_x_preferred":[
        "\u0634\u0645\u064a\u0633\u0629"
    ],
    "name:und_x_variant":[
        "Chma\u00efss\u00e9",
        "Shumayyisah",
        "Shumaysah",
        "Chema\u00efsse"
    ],
    "wof:name":"Shumaysah",
    "wof:placetype":"locality"
},
  "geometry": {"coordinates":[36.14208,35.78577],"type":"Point"}
}