{
  "type": "Feature",
  "properties": {
    "gn:admin1_code":"10.0",
    "gn:asciiname":"Ma`arrin",
    "gn:country_code":"SY",
    "gn:dem":222,
    "gn:feature_class":"P",
    "gn:feature_code":"PPL",
    "gn:name":"Ma\u2018arr\u012bn",
    "gn:population":0,
    "gn:timezone":"Asia/Damascus",
    "iso:country":"SY",
    "name:ara_x_preferred":[
        "\u0645\u0639\u0631\u064a\u0646"
    ],
    "name:und_x_variant":[
        "Maarr\u00eene",
        "Ma\u2018arr\u012bn"
    ],
    "wof:name":"Ma`arrin",
    "wof:placetype":"locality"
},
  "geometry": {"coordinates":[36.44709,35.15837],"type":"Point"}
}