{
  "type": "Feature",
  "properties": {
    "gn:admin1_code":"14.0",
    "gn:asciiname":"`Aynata",
    "gn:country_code":"SY",
    "gn:dem":518,
    "gn:feature_class":"P",
    "gn:feature_code":"PPL",
    "gn:name":"\u2018Ayn\u0101t\u0101",
    "gn:population":0,
    "gn:timezone":"Asia/Damascus",
    "iso:country":"SY",
    "name:ara_x_preferred":[
        "\u0639\u064a\u0646\u0627\u062a\u0627"
    ],
    "name:und_x_variant":[
        "\u2018Ayn\u0101t\u0101"
    ],
    "wof:name":"`Aynata",
    "wof:placetype":"locality"
},
  "geometry": {"coordinates":[36.22583,34.88434],"type":"Point"}
}