{
  "type": "Feature",
  "properties": {
    "gn:admin1_code":"14.0",
    "gn:asciiname":"Bsarmun",
    "gn:country_code":"SY",
    "gn:dem":749,
    "gn:feature_class":"P",
    "gn:feature_code":"PPL",
    "gn:name":"B\u015farm\u016bn",
    "gn:population":0,
    "gn:timezone":"Asia/Damascus",
    "iso:country":"SY",
    "name:ara_x_preferred":[
        "\u0628\u0635\u0631\u0645\u0648\u0646"
    ],
    "name:und_x_variant":[
        "Bsarmo\u00fbn",
        "B\u015farm\u016bn",
        "Bi\u015farm\u016bn"
    ],
    "wof:name":"Bsarmun",
    "wof:placetype":"locality"
},
  "geometry": {"coordinates":[36.13539,35.2125],"type":"Point"}
}