{
  "type": "Feature",
  "properties": {
    "gn:admin1_code":"9.0",
    "gn:asciiname":"Jubaylah",
    "gn:country_code":"SY",
    "gn:dem":422,
    "gn:feature_class":"P",
    "gn:feature_code":"PPL",
    "gn:name":"Jubaylah",
    "gn:population":0,
    "gn:timezone":"Asia/Damascus",
    "iso:country":"SY",
    "name:ara_x_preferred":[
        "\u062d\u0628\u064a\u0644\u0629"
    ],
    "name:ara_x_variant":[
        "\u062c\u0628\u064a\u0644\u0629"
    ],
    "name:und_x_variant":[
        "\u1e28ab\u012blah",
        "Jubaylah"
    ],
    "wof:name":"Jubaylah",
    "wof:placetype":"locality"
},
  "geometry": {"coordinates":[37.19306,36.30163],"type":"Point"}
}