{
  "type": "Feature",
  "properties": {
    "gn:admin1_code":"4.0",
    "gn:asciiname":"Butayman",
    "gn:country_code":"SY",
    "gn:dem":453,
    "gn:feature_class":"P",
    "gn:feature_code":"PPL",
    "gn:name":"Bu\u0163aym\u0101n",
    "gn:population":0,
    "gn:timezone":"Asia/Damascus",
    "iso:country":"SY",
    "name:ara_x_preferred":[
        "\u0628\u0637\u064a\u0645\u0627\u0646"
    ],
    "name:und_x_variant":[
        "Bu\u0163aym\u0101n"
    ],
    "wof:name":"Butayman",
    "wof:placetype":"locality"
},
  "geometry": {"coordinates":[39.74861,36.20134],"type":"Point"}
}