{
  "type": "Feature",
  "properties": {
    "gn:admin1_code":"1.0",
    "gn:asciiname":"Sahlat ad Dubban",
    "gn:country_code":"SY",
    "gn:dem":329,
    "gn:feature_class":"P",
    "gn:feature_code":"PPL",
    "gn:name":"Sahlat ad Dubb\u0101n",
    "gn:population":0,
    "gn:timezone":"Asia/Damascus",
    "iso:country":"SY",
    "name:ara_x_preferred":[
        "\u0633\u0647\u0644\u0629 \u0627\u0644\u062f\u0628\u0627\u0646"
    ],
    "name:und_x_variant":[
        "Sahlat ad Dubb\u0101n"
    ],
    "wof:name":"Sahlat ad Dubban",
    "wof:placetype":"locality"
},
  "geometry": {"coordinates":[40.60165,36.24129],"type":"Point"}
}