{
  "type": "Feature",
  "properties": {
    "gn:admin1_code":"12.0",
    "gn:asciiname":"Kinan",
    "gn:country_code":"SY",
    "gn:dem":302,
    "gn:feature_class":"P",
    "gn:feature_code":"PPL",
    "gn:name":"K\u012bn\u0101n",
    "gn:population":0,
    "gn:timezone":"Asia/Damascus",
    "iso:country":"SY",
    "name:ara_x_preferred":[
        "K\u012bn\u0101n"
    ],
    "name:ara_x_variant":[
        "\u0643\u064a\u0646\u0627\u0646"
    ],
    "wof:name":"Kinan",
    "wof:placetype":"locality"
},
  "geometry": {"coordinates":[36.81383,36.05114],"type":"Point"}
}