{
  "type": "Feature",
  "properties": {
    "gn:admin1_code":"11.0",
    "gn:asciiname":"Ard Suray al Halabi",
    "gn:country_code":"SY",
    "gn:dem":545,
    "gn:feature_class":"P",
    "gn:feature_code":"PPLL",
    "gn:name":"Ar\u1e11 Suray al \u1e28alab\u012b",
    "gn:population":0,
    "gn:timezone":"Asia/Damascus",
    "iso:country":"SY",
    "name:ara_x_preferred":[
        "\u0623\u0631\u0636 \u0633\u0648\u0631\u064a \u0627\u0644\u062d\u0644\u0628\u064a"
    ],
    "name:und_x_variant":[
        "Ar\u1e11 Suray al \u1e28alab\u012b"
    ],
    "wof:name":"Ard Suray al Halabi",
    "wof:placetype":"locality"
},
  "geometry": {"coordinates":[36.74093,34.69645],"type":"Point"}
}