{
  "type": "Feature",
  "properties": {
    "gn:admin1_code":"11.0",
    "gn:asciiname":"Al Ma`murah",
    "gn:country_code":"SY",
    "gn:dem":479,
    "gn:feature_class":"P",
    "gn:feature_code":"PPL",
    "gn:name":"Al Ma\u2018m\u016brah",
    "gn:population":0,
    "gn:timezone":"Asia/Damascus",
    "iso:country":"SY",
    "name:ara_x_preferred":[
        "\u0627\u0644\u0645\u062d\u0645\u0648\u0631\u064a"
    ],
    "name:ara_x_variant":[
        "\u0627\u0644\u0645\u0639\u0645\u0648\u0631\u0629"
    ],
    "name:und_x_variant":[
        "El Mahmo\u00fbri",
        "Al Ma\u1e29m\u016br\u012b",
        "Al Ma\u2018m\u016brah"
    ],
    "wof:name":"Al Ma`murah",
    "wof:placetype":"locality"
},
  "geometry": {"coordinates":[36.65841,34.71217],"type":"Point"}
}