{
  "type": "Feature",
  "properties": {
    "gn:admin1_code":"9.0",
    "gn:asciiname":"Qantarat Awkhan",
    "gn:country_code":"SY",
    "gn:dem":463,
    "gn:feature_class":"P",
    "gn:feature_code":"PPL",
    "gn:name":"Qan\u0163arat Awkh\u0101n",
    "gn:population":0,
    "gn:timezone":"Asia/Damascus",
    "iso:country":"SY",
    "name:ara_x_preferred":[
        "\u0642\u0646\u0637\u0631\u0629 \u0623\u0648\u062e\u0627\u0646"
    ],
    "name:ara_x_variant":[
        "\u0627\u0644\u0642\u0646\u0637\u0631\u0629",
        "\u0642\u0646\u0637\u0631\u0629",
        "\u0642\u0646\u0637\u0631\u0627"
    ],
    "name:kur_x_preferred":[
        "Qintira Sh\u00eexan"
    ],
    "name:kur_x_variant":[
        "Qentera Sh\u00eexan",
        "Qentera Sh\u00eaxan",
        "\u0642\u0646\u062a\u0631\u0627 \u0634\u064a\u062e\u0627\u0646",
        "\u0642\u06d5\u0646\u062a\u06d5\u0631\u0627 \u0634\u064a\u062e\u0627\u0646",
        "\u0642\u06d5\u0646\u062a\u06d5\u0631\u0627 \u0634\u06ce\u062e\u0627\u0646"
    ],
    "name:und_x_variant":[
        "Qanntaret Aoukh\u00e2ne",
        "Qanntara",
        "Qaintar",
        "Qan\u0163arat Awkh\u0101n",
        "Kansarat Awkhan",
        "Al Qan\u0163arah",
        "Al Qan\u0163ara",
        "Qantara",
        "Qan\u0163arah",
        "Qan\u0163ara",
        "Qentera",
        "Qintira Shikhan",
        "Qantara Shikhan",
        "Qan\u0163ar\u0101",
        "Qantar\u0101 Shaykh\u0101n",
        "Qentera Shekhan",
        "Qentera \u015e\u00eaxan"
    ],
    "wof:name":"Qantarat Awkhan",
    "wof:placetype":"locality"
},
  "geometry": {"coordinates":[38.19503,36.83361],"type":"Point"}
}