{
  "type": "Feature",
  "properties": {
    "gn:admin1_code":"2.0",
    "gn:asciiname":"Qarah Dalak",
    "gn:country_code":"SY",
    "gn:dem":824,
    "gn:feature_class":"P",
    "gn:feature_code":"PPL",
    "gn:name":"Qarah Dalak",
    "gn:population":0,
    "gn:timezone":"Asia/Damascus",
    "iso:country":"SY",
    "wof:name":"Qarah Dalak",
    "wof:placetype":"locality"
},
  "geometry": {"coordinates":[35.96667,35.91667],"type":"Point"}
}