{
  "type": "Feature",
  "properties": {
    "gn:admin1_code":"2.0",
    "gn:asciiname":"Sefsaf",
    "gn:country_code":"SY",
    "gn:dem":111,
    "gn:feature_class":"P",
    "gn:feature_code":"PPL",
    "gn:name":"Sefsaf",
    "gn:population":0,
    "gn:timezone":"Asia/Damascus",
    "iso:country":"SY",
    "name:ara_x_preferred":[
        "\u0627\u0644\u0635\u0641\u0635\u0627\u0641"
    ],
    "name:ara_x_variant":[
        "\u0635\u0641\u0635\u0627\u0641"
    ],
    "name:cat_x_preferred":[
        "Sefsaf"
    ],
    "name:ceb_x_preferred":[
        "Sefsaf"
    ],
    "name:ita_x_preferred":[
        "Sefsaf"
    ],
    "name:swe_x_preferred":[
        "Sefsaf"
    ],
    "name:und_x_variant":[
        "Safs\u00e2f",
        "A\u015f \u015eaf\u015f\u0101f",
        "Sefsaf"
    ],
    "wof:name":"Sefsaf",
    "wof:placetype":"locality"
},
  "geometry": {"coordinates":[35.92517,35.65279],"type":"Point"}
}