{
  "type": "Feature",
  "properties": {
    "gn:admin1_code":"9.0",
    "gn:asciiname":"Qawr Dini",
    "gn:country_code":"SY",
    "gn:dem":361,
    "gn:feature_class":"P",
    "gn:feature_code":"PPL",
    "gn:name":"Qawr D\u012bn\u012b",
    "gn:population":0,
    "gn:timezone":"Asia/Damascus",
    "iso:country":"SY",
    "wof:name":"Qawr Dini",
    "wof:placetype":"locality"
},
  "geometry": {"coordinates":[38.13611,36.72222],"type":"Point"}
}