{
  "type": "Feature",
  "properties": {
    "gn:admin1_code":"11.0",
    "gn:asciiname":"Al Wardiyat",
    "gn:country_code":"SY",
    "gn:dem":218,
    "gn:feature_class":"P",
    "gn:feature_code":"PPL",
    "gn:name":"Al Ward\u012by\u0101t",
    "gn:population":0,
    "gn:timezone":"Asia/Damascus",
    "iso:country":"SY",
    "name:ara_x_preferred":[
        "\u0627\u0644\u0648\u0631\u062f\u064a\u0627\u062a"
    ],
    "name:und_x_variant":[
        "Ouard\u00eey\u00e2te",
        "Al Ward\u012by\u0101t"
    ],
    "wof:name":"Al Wardiyat",
    "wof:placetype":"locality"
},
  "geometry": {"coordinates":[36.1971,34.69187],"type":"Point"}
}