{
  "type": "Feature",
  "properties": {
    "gn:admin1_code":"14.0",
    "gn:asciiname":"Jawbat Muhmis",
    "gn:country_code":"SY",
    "gn:dem":705,
    "gn:feature_class":"P",
    "gn:feature_code":"PPL",
    "gn:name":"Jawbat Mu\u1e29mi\u015f",
    "gn:population":0,
    "gn:timezone":"Asia/Damascus",
    "iso:country":"SY",
    "name:und_x_variant":[
        "Jaoubet Mohmis",
        "Jawbat Mu\u1e29mi\u015f"
    ],
    "wof:name":"Jawbat Muhmis",
    "wof:placetype":"locality"
},
  "geometry": {"coordinates":[36.10889,35.08165],"type":"Point"}
}