{
  "type": "Feature",
  "properties": {
    "gn:admin1_code":"1.0",
    "gn:asciiname":"Umm Harmala",
    "gn:country_code":"SY",
    "gn:dem":345,
    "gn:feature_class":"P",
    "gn:feature_code":"PPL",
    "gn:name":"Umm Harmal\u0101",
    "gn:population":0,
    "gn:timezone":"Asia/Damascus",
    "iso:country":"SY",
    "name:ara_x_preferred":[
        "\u0623\u0645 \u062d\u0631\u0645\u0644\u0627"
    ],
    "name:und_x_variant":[
        "Oum Harmala",
        "Umm Harmalah",
        "Umm Harmal\u0101"
    ],
    "wof:name":"Umm Harmala",
    "wof:placetype":"locality"
},
  "geometry": {"coordinates":[40.38476,36.74905],"type":"Point"}
}