{
  "type": "Feature",
  "properties": {
    "gn:admin1_code":"12.0",
    "gn:asciiname":"Atmah",
    "gn:country_code":"SY",
    "gn:dem":227,
    "gn:feature_class":"P",
    "gn:feature_code":"PPL",
    "gn:name":"A\u0163mah",
    "gn:population":0,
    "gn:timezone":"Asia/Damascus",
    "iso:country":"SY",
    "name:ara_x_preferred":[
        "\u0623\u0637\u0645\u0629"
    ],
    "name:ara_x_variant":[
        "\u0623\u0637\u0645\u0647"
    ],
    "name:deu_x_preferred":[
        "Atmeh"
    ],
    "name:fas_x_preferred":[
        "\u0627\u0637\u0645\u0647"
    ],
    "name:pol_x_preferred":[
        "Atima"
    ],
    "name:und_x_variant":[
        "Atma",
        "Atmih",
        "Atm\u00e9",
        "\u0100\u0163imah",
        "A\u0163mah",
        "A\u0163imah"
    ],
    "name:vie_x_preferred":[
        "Atme"
    ],
    "wof:name":"Atmah",
    "wof:placetype":"locality"
},
  "geometry": {"coordinates":[36.68839000000001,36.3095],"type":"Point"}
}