{
  "type": "Feature",
  "properties": {
    "gn:admin1_code":"2.0",
    "gn:asciiname":"Al Mushaymishah",
    "gn:country_code":"SY",
    "gn:dem":202,
    "gn:feature_class":"P",
    "gn:feature_code":"PPL",
    "gn:name":"Al Mushaymishah",
    "gn:population":0,
    "gn:timezone":"Asia/Damascus",
    "iso:country":"SY",
    "name:ara_x_preferred":[
        "\u0627\u0644\u0645\u0634\u064a\u0645\u0634\u0629"
    ],
    "wof:name":"Al Mushaymishah",
    "wof:placetype":"locality"
},
  "geometry": {"coordinates":[35.97633,35.6411],"type":"Point"}
}