{
  "type": "Feature",
  "properties": {
    "gn:admin1_code":"2.0",
    "gn:asciiname":"Kaslajuk",
    "gn:country_code":"SY",
    "gn:dem":189,
    "gn:feature_class":"P",
    "gn:feature_code":"PPL",
    "gn:name":"Kaslaj\u016bk",
    "gn:population":0,
    "gn:timezone":"Asia/Damascus",
    "iso:country":"SY",
    "name:ara_x_preferred":[
        "\u0643\u0633\u0644\u062c\u0648\u0643"
    ],
    "name:und_x_variant":[
        "Kesladjo\u00fbq",
        "Kasl\u0101j\u016bq",
        "Kaslaj\u016bk"
    ],
    "wof:name":"Kaslajuk",
    "wof:placetype":"locality"
},
  "geometry": {"coordinates":[36.06626,35.73009000000001],"type":"Point"}
}