{
  "type": "Feature",
  "properties": {
    "gn:admin1_code":"10.0",
    "gn:asciiname":"Al Qanatir",
    "gn:country_code":"SY",
    "gn:dem":315,
    "gn:feature_class":"P",
    "gn:feature_code":"PPL",
    "gn:name":"Al Qan\u0101\u0163ir",
    "gn:population":0,
    "gn:timezone":"Asia/Damascus",
    "iso:country":"SY",
    "name:ara_x_preferred":[
        "\u0627\u0644\u0642\u0646\u0627\u0637\u0631"
    ],
    "name:und_x_variant":[
        "El Qan\u00e2ter",
        "Al Qan\u0101\u0163ir"
    ],
    "wof:name":"Al Qanatir",
    "wof:placetype":"locality"
},
  "geometry": {"coordinates":[37.23225,35.47101],"type":"Point"}
}