{
  "type": "Feature",
  "properties": {
    "gn:admin1_code":"1.0",
    "gn:asciiname":"`Atawiyah",
    "gn:country_code":"SY",
    "gn:dem":387,
    "gn:feature_class":"P",
    "gn:feature_code":"PPL",
    "gn:name":"\u2018A\u0163aw\u012byah",
    "gn:population":0,
    "gn:timezone":"Asia/Damascus",
    "iso:country":"SY",
    "name:ara_x_preferred":[
        "\u0639\u0637\u0648\u064a\u0629"
    ],
    "name:tur_x_preferred":[
        "\u2018A\u0163aw\u012byah"
    ],
    "name:und_x_variant":[
        "Aataou\u00eey\u00e9"
    ],
    "wof:name":"`Atawiyah",
    "wof:placetype":"locality"
},
  "geometry": {"coordinates":[41.59404,36.95072],"type":"Point"}
}