{
  "type": "Feature",
  "properties": {
    "gn:admin1_code":"2.0",
    "gn:asciiname":"Dayrunah",
    "gn:country_code":"SY",
    "gn:dem":658,
    "gn:feature_class":"P",
    "gn:feature_code":"PPL",
    "gn:name":"Dayr\u016bnah",
    "gn:population":0,
    "gn:timezone":"Asia/Damascus",
    "iso:country":"SY",
    "name:ara_x_preferred":[
        "\u062f\u064a\u0631\u0648\u0646\u0629"
    ],
    "name:ara_x_variant":[
        "\u062f\u064a\u0631\u0648\u0646\u0629 \u0627\u0644\u0623\u0643\u0631\u0627\u062f"
    ],
    "name:und_x_variant":[
        "De\u00efro\u00fbn\u00e9",
        "Dayr\u016bnah",
        "Dayr\u016bnat al Akr\u0101d"
    ],
    "wof:name":"Dayrunah",
    "wof:placetype":"locality"
},
  "geometry": {"coordinates":[36.19624,35.7464],"type":"Point"}
}