{
  "type": "Feature",
  "properties": {
    "gn:admin1_code":"12.0",
    "gn:asciiname":"Mardikh",
    "gn:country_code":"SY",
    "gn:dem":410,
    "gn:feature_class":"P",
    "gn:feature_code":"PPL",
    "gn:name":"Mard\u012bkh",
    "gn:population":0,
    "gn:timezone":"Asia/Damascus",
    "iso:country":"SY",
    "name:ara_x_preferred":[
        "\u0645\u0631\u062f\u064a\u062e"
    ],
    "name:fas_x_preferred":[
        "\u0645\u0631\u062f\u06cc\u062e"
    ],
    "name:pol_x_preferred":[
        "Mardich"
    ],
    "name:und_x_variant":[
        "Mard\u012bkh"
    ],
    "name:vie_x_preferred":[
        "Mardikh"
    ],
    "wof:name":"Mardikh",
    "wof:placetype":"locality"
},
  "geometry": {"coordinates":[36.79093,35.81117000000001],"type":"Point"}
}