{
  "type": "Feature",
  "properties": {
    "gn:admin1_code":"4.0",
    "gn:asciiname":"Al Khumaysiyah",
    "gn:country_code":"SY",
    "gn:dem":226,
    "gn:feature_class":"P",
    "gn:feature_code":"PPL",
    "gn:name":"Al Khumays\u012byah",
    "gn:population":0,
    "gn:timezone":"Asia/Damascus",
    "iso:country":"SY",
    "name:ara_x_preferred":[
        "\u0627\u0644\u062e\u0645\u064a\u0633\u064a\u0629"
    ],
    "name:und_x_variant":[
        "El Kh\u00e9ma\u00efss\u00eey\u00e9",
        "Al Khumays\u012byah"
    ],
    "wof:name":"Al Khumaysiyah",
    "wof:placetype":"locality"
},
  "geometry": {"coordinates":[39.58667,35.78323],"type":"Point"}
}