{
  "type": "Feature",
  "properties": {
    "gn:admin1_code":"4.0",
    "gn:asciiname":"Sukkariyah",
    "gn:country_code":"SY",
    "gn:dem":360,
    "gn:feature_class":"P",
    "gn:feature_code":"PPL",
    "gn:name":"Sukkar\u012byah",
    "gn:population":0,
    "gn:timezone":"Asia/Damascus",
    "iso:country":"SY",
    "name:ara_x_preferred":[
        "\u0633\u0643\u0631\u064a\u0629"
    ],
    "name:und_x_variant":[
        "Soukkar\u00eey\u00e9",
        "Soukar\u00eeya",
        "Sukkar\u012byah"
    ],
    "wof:name":"Sukkariyah",
    "wof:placetype":"locality"
},
  "geometry": {"coordinates":[38.84392,36.66096],"type":"Point"}
}