{
  "type": "Feature",
  "properties": {
    "gn:admin1_code":"14.0",
    "gn:asciiname":"Zahr Matar",
    "gn:country_code":"SY",
    "gn:dem":265,
    "gn:feature_class":"P",
    "gn:feature_code":"PPL",
    "gn:name":"Z\u0327ahr Ma\u0163ar",
    "gn:population":0,
    "gn:timezone":"Asia/Damascus",
    "iso:country":"SY",
    "name:ara_x_preferred":[
        "\u0636\u0647\u0631 \u0645\u0637\u0631"
    ],
    "name:ara_x_variant":[
        "\u0638\u0647\u0631 \u0645\u0637\u0631"
    ],
    "name:und_x_variant":[
        "\u1e10ahr Ma\u0163ar",
        "Z\u0327ahr Ma\u0163ar"
    ],
    "wof:name":"Zahr Matar",
    "wof:placetype":"locality"
},
  "geometry": {"coordinates":[35.97152,34.98784000000001],"type":"Point"}
}