{
  "type": "Feature",
  "properties": {
    "gn:admin1_code":"1.0",
    "gn:asciiname":"`Abd al Khaznah",
    "gn:country_code":"SY",
    "gn:dem":331,
    "gn:feature_class":"P",
    "gn:feature_code":"PPL",
    "gn:name":"\u2018Abd al Khaznah",
    "gn:population":0,
    "gn:timezone":"Asia/Damascus",
    "iso:country":"SY",
    "name:ara_x_preferred":[
        "\u0639\u0628\u062f \u0627\u0644\u062e\u0632\u0646\u0629"
    ],
    "name:und_x_variant":[
        "\u2018Abd al Khaznah"
    ],
    "wof:name":"`Abd al Khaznah",
    "wof:placetype":"locality"
},
  "geometry": {"coordinates":[40.93822,36.06729],"type":"Point"}
}