{
  "type": "Feature",
  "properties": {
    "gn:admin1_code":"7.0",
    "gn:asciiname":"Mu`ayjil",
    "gn:country_code":"SY",
    "gn:dem":237,
    "gn:feature_class":"P",
    "gn:feature_code":"PPL",
    "gn:name":"Mu\u2018ayj\u012bl",
    "gn:population":0,
    "gn:timezone":"Asia/Damascus",
    "iso:country":"SY",
    "name:ara_x_preferred":[
        "\u0645\u0639\u064a\u062c\u064a\u0644"
    ],
    "name:ara_x_variant":[
        "\u0645\u0639\u064a\u062c\u0644",
        "\u0645\u0639\u062c\u064a\u0644"
    ],
    "name:und_x_variant":[
        "Moue\u00efjel",
        "Mu\u2018ayj\u012bl",
        "Mu\u2018ayjil",
        "Ma\u2018aj\u012bl"
    ],
    "wof:name":"Mu`ayjil",
    "wof:placetype":"locality"
},
  "geometry": {"coordinates":[40.73477000000001,35.59757000000001],"type":"Point"}
}