{
  "type": "Feature",
  "properties": {
    "gn:admin1_code":"2.0",
    "gn:asciiname":"Al Hamidiyah",
    "gn:country_code":"SY",
    "gn:dem":218,
    "gn:feature_class":"P",
    "gn:feature_code":"PPL",
    "gn:name":"Al \u1e28am\u012bd\u012byah",
    "gn:population":0,
    "gn:timezone":"Asia/Damascus",
    "iso:country":"SY",
    "name:ara_x_preferred":[
        "\u062d\u0645\u064a\u062f\u064a\u0629"
    ],
    "name:ara_x_variant":[
        "\u0627\u0644\u062d\u0645\u064a\u062f\u064a\u0629"
    ],
    "name:und_x_variant":[
        "Ham\u00eed\u00eey\u00e9",
        "Hamidi\u00e9",
        "\u1e28am\u012bd\u012byah",
        "Al \u1e28am\u012bd\u012byah",
        "Hameidiyyeh"
    ],
    "wof:name":"Al Hamidiyah",
    "wof:placetype":"locality"
},
  "geometry": {"coordinates":[35.99082999999999,35.60602],"type":"Point"}
}