{
  "type": "Feature",
  "properties": {
    "gn:admin1_code":"14.0",
    "gn:asciiname":"Muqaybilah",
    "gn:country_code":"SY",
    "gn:dem":655,
    "gn:feature_class":"P",
    "gn:feature_code":"PPL",
    "gn:name":"Muqaybilah",
    "gn:population":0,
    "gn:timezone":"Asia/Damascus",
    "iso:country":"SY",
    "name:ara_x_preferred":[
        "\u0645\u0642\u064a\u0628\u0644\u0629"
    ],
    "wof:name":"Muqaybilah",
    "wof:placetype":"locality"
},
  "geometry": {"coordinates":[36.11733,35.09887],"type":"Point"}
}