{
  "type": "Feature",
  "properties": {
    "gn:admin1_code":"10.0",
    "gn:asciiname":"Ar Ramliyah",
    "gn:country_code":"SY",
    "gn:dem":312,
    "gn:feature_class":"P",
    "gn:feature_code":"PPL",
    "gn:name":"Ar Raml\u012byah",
    "gn:population":0,
    "gn:timezone":"Asia/Damascus",
    "iso:country":"SY",
    "name:ara_x_preferred":[
        "\u0631\u0645\u0644\u064a\u0629"
    ],
    "name:ara_x_variant":[
        "\u0627\u0644\u0631\u0645\u0644\u064a\u0629"
    ],
    "name:und_x_variant":[
        "Raml\u00eey\u00e9",
        "Raml\u012byah",
        "Ramliy\u00e9",
        "Ar Raml\u012byah"
    ],
    "wof:name":"Ar Ramliyah",
    "wof:placetype":"locality"
},
  "geometry": {"coordinates":[36.87549,35.04211],"type":"Point"}
}