{
  "type": "Feature",
  "properties": {
    "gn:admin1_code":"10.0",
    "gn:asciiname":"`Ayn ash Shams",
    "gn:country_code":"SY",
    "gn:dem":875,
    "gn:feature_class":"P",
    "gn:feature_code":"PPL",
    "gn:name":"\u2018Ayn ash Shams",
    "gn:population":0,
    "gn:timezone":"Asia/Damascus",
    "iso:country":"SY",
    "name:ara_x_preferred":[
        "\u0639\u064a\u0646 \u0627\u0644\u0634\u0645\u0633"
    ],
    "name:und_x_variant":[
        "A\u00efn ech Chams",
        "\u2018Ayn ash Shams"
    ],
    "wof:name":"`Ayn ash Shams",
    "wof:placetype":"locality"
},
  "geometry": {"coordinates":[36.27587,34.93286],"type":"Point"}
}