{
  "type": "Feature",
  "properties": {
    "gn:admin1_code":"10.0",
    "gn:asciiname":"Tuwam",
    "gn:country_code":"SY",
    "gn:dem":341,
    "gn:feature_class":"P",
    "gn:feature_code":"PPL",
    "gn:name":"Tuw\u0101m",
    "gn:population":0,
    "gn:timezone":"Asia/Damascus",
    "iso:country":"SY",
    "name:ara_x_preferred":[
        "Tuw\u0101m"
    ],
    "name:ara_x_variant":[
        "\u062a\u0648\u0627\u0645",
        "\u062a\u0648\u064a\u0645"
    ],
    "name:und_x_variant":[
        "Tou\u00e8m",
        "Tou\u00e2m",
        "Toueme",
        "At Tuwaym",
        "Tuwaym"
    ],
    "wof:name":"Tuwam",
    "wof:placetype":"locality"
},
  "geometry": {"coordinates":[36.53905,35.15737],"type":"Point"}
}