{
  "type": "Feature",
  "properties": {
    "gn:admin1_code":"9.0",
    "gn:asciiname":"Mawi Tahtani",
    "gn:country_code":"SY",
    "gn:dem":467,
    "gn:feature_class":"P",
    "gn:feature_code":"PPL",
    "gn:name":"Mawi Tahtani",
    "gn:population":0,
    "gn:timezone":"Asia/Damascus",
    "iso:country":"SY",
    "name:ara_x_preferred":[
        "\u062e\u0627\u0646 \u062a\u062d\u062a\u0627\u0646\u064a"
    ],
    "name:ara_x_variant":[
        "\u0645\u0627\u0648\u0649 \u062a\u062d\u062a\u0627\u0646\u064a",
        "\u0645\u0627\u0648\u064a \u062a\u062d\u062a\u0627\u0646\u064a",
        "\u0645\u0623\u0648\u0649 \u062a\u062d\u062a\u0627\u0646\u064a"
    ],
    "name:kur_x_preferred":[
        "Xan\u00eek Z\u00eer"
    ],
    "name:kur_x_variant":[
        "Xan\u00eek J\u00eer",
        "Xan\u00eek J\u00ear",
        "\u062e\u0627\u0646\u064a\u0643 \u0632\u064a\u0631",
        "\u062e\u0627\u0646\u064a\u0643 \u0698\u064a\u0631",
        "\u062e\u0627\u0646\u064a\u0643 \u0698\u06ce\u0631"
    ],
    "name:und_x_variant":[
        "Kh\u0101n Ta\u1e29t\u0101n\u012b",
        "M\u0101w\u00e1 Ta\u1e29t\u0101n\u012b",
        "M\u0101w\u012b Ta\u1e29t\u0101n\u012b",
        "Mawa Tehtan\u00ee",
        "Mawi Tahtani",
        "Khanik Zir",
        "Xanik Zer",
        "Ma\u2019w\u00e1 Ta\u1e29t\u0101n\u012b"
    ],
    "wof:name":"Mawi Tahtani",
    "wof:placetype":"locality"
},
  "geometry": {"coordinates":[38.19125,36.82897],"type":"Point"}
}