{
  "type": "Feature",
  "properties": {
    "gn:admin1_code":"9.0",
    "gn:asciiname":"Qasimiyah",
    "gn:country_code":"SY",
    "gn:dem":332,
    "gn:feature_class":"P",
    "gn:feature_code":"PPL",
    "gn:name":"Q\u0101sim\u012byah",
    "gn:population":0,
    "gn:timezone":"Asia/Damascus",
    "iso:country":"SY",
    "name:ara_x_preferred":[
        "\u0642\u0627\u0633\u0645\u064a\u0629"
    ],
    "name:und_x_variant":[
        "Al Q\u0101sm\u012byah",
        "Q\u00e2sm\u00eey\u00e9",
        "Q\u0101sim\u012byah"
    ],
    "wof:name":"Qasimiyah",
    "wof:placetype":"locality"
},
  "geometry": {"coordinates":[38.12273,36.70321],"type":"Point"}
}