{
  "type": "Feature",
  "properties": {
    "gn:admin1_code":"9.0",
    "gn:asciiname":"Qadimiyah",
    "gn:country_code":"SY",
    "gn:dem":385,
    "gn:feature_class":"P",
    "gn:feature_code":"PPL",
    "gn:name":"Q\u0101dim\u012byah",
    "gn:population":0,
    "gn:timezone":"Asia/Damascus",
    "iso:country":"SY",
    "name:ara_x_preferred":[
        "\u0642\u0627\u062f\u0645\u064a\u0629"
    ],
    "name:und_x_variant":[
        "Qadm\u00eey\u00e9",
        "Q\u0101dim\u012byah"
    ],
    "wof:name":"Qadimiyah",
    "wof:placetype":"locality"
},
  "geometry": {"coordinates":[37.19972,36.04668],"type":"Point"}
}