{
  "type": "Feature",
  "properties": {
    "gn:admin1_code":"11.0",
    "gn:asciiname":"Bluzah",
    "gn:country_code":"SY",
    "gn:dem":613,
    "gn:feature_class":"P",
    "gn:feature_code":"PPL",
    "gn:name":"Bl\u016bzah",
    "gn:population":0,
    "gn:timezone":"Asia/Damascus",
    "iso:country":"SY",
    "name:ara_x_preferred":[
        "\u0628\u0644\u0648\u0632\u0629"
    ],
    "name:und_x_variant":[
        "Belouz\u00e9",
        "Belouzi",
        "Bl\u016bzah"
    ],
    "wof:name":"Bluzah",
    "wof:placetype":"locality"
},
  "geometry": {"coordinates":[36.42567,34.53657],"type":"Point"}
}