{
  "type": "Feature",
  "properties": {
    "gn:admin1_code":"4.0",
    "gn:asciiname":"Jamus",
    "gn:country_code":"SY",
    "gn:dem":370,
    "gn:feature_class":"P",
    "gn:feature_code":"PPL",
    "gn:name":"J\u0101m\u016bs",
    "gn:population":0,
    "gn:timezone":"Asia/Damascus",
    "iso:country":"SY",
    "name:ara_x_preferred":[
        "J\u0101m\u016bs"
    ],
    "name:ara_x_variant":[
        "\u062c\u0627\u0645\u0648\u0633"
    ],
    "name:und_x_variant":[
        "J\u00e2mo\u00fbs"
    ],
    "wof:name":"Jamus",
    "wof:placetype":"locality"
},
  "geometry": {"coordinates":[39.27899,36.59758],"type":"Point"}
}