{
  "type": "Feature",
  "properties": {
    "gn:admin1_code":"8.0",
    "gn:asciiname":"As Surah",
    "gn:country_code":"SY",
    "gn:dem":1433,
    "gn:feature_class":"P",
    "gn:feature_code":"PPL",
    "gn:name":"As S\u016brah",
    "gn:population":0,
    "gn:timezone":"Asia/Damascus",
    "iso:country":"SY",
    "name:ara_x_preferred":[
        "\u0627\u0644\u0633\u0648\u0631\u0629"
    ],
    "name:und_x_variant":[
        "As S\u016brah"
    ],
    "wof:name":"As Surah",
    "wof:placetype":"locality"
},
  "geometry": {"coordinates":[36.66024,34.02348],"type":"Point"}
}