{
  "type": "Feature",
  "properties": {
    "gn:admin1_code":"9.0",
    "gn:asciiname":"Tall ar Rafi`",
    "gn:country_code":"SY",
    "gn:dem":422,
    "gn:feature_class":"P",
    "gn:feature_code":"PPL",
    "gn:name":"Tall ar Raf\u012b\u2018",
    "gn:population":0,
    "gn:timezone":"Asia/Damascus",
    "iso:country":"SY",
    "name:ara_x_preferred":[
        "\u062a\u0644 \u0627\u0644\u0631\u0641\u064a\u0639"
    ],
    "name:und_x_variant":[
        "Tell er Rafia",
        "Tall ar Raf\u012b\u2018"
    ],
    "wof:name":"Tall ar Rafi`",
    "wof:placetype":"locality"
},
  "geometry": {"coordinates":[37.99523,36.57981],"type":"Point"}
}