{
  "type": "Feature",
  "properties": {
    "gn:admin1_code":"12.0",
    "gn:asciiname":"Sabilah",
    "gn:country_code":"SY",
    "gn:dem":495,
    "gn:feature_class":"P",
    "gn:feature_code":"PPL",
    "gn:name":"Sab\u012blah",
    "gn:population":0,
    "gn:timezone":"Asia/Damascus",
    "iso:country":"SY",
    "name:ara_x_preferred":[
        "\u0633\u0628\u064a\u0644\u0629"
    ],
    "name:und_x_variant":[
        "Sab\u012blah"
    ],
    "wof:name":"Sabilah",
    "wof:placetype":"locality"
},
  "geometry": {"coordinates":[36.41584,35.87580999999999],"type":"Point"}
}