{
  "type": "Feature",
  "properties": {
    "gn:admin1_code":"1.0",
    "gn:asciiname":"Damir Qabu",
    "gn:country_code":"SY",
    "gn:dem":412,
    "gn:feature_class":"P",
    "gn:feature_code":"PPL",
    "gn:name":"Dam\u012br Q\u0101b\u016b",
    "gn:population":0,
    "gn:timezone":"Asia/Damascus",
    "iso:country":"SY",
    "name:ara_x_preferred":[
        "\u062f\u0645\u064a\u0631 \u0642\u0627\u0628\u0648"
    ],
    "name:und_x_variant":[
        "Dam\u012br K\u0101b\u016b",
        "D\u00e9mir Qapou",
        "Demir Kapou",
        "Dam\u012br Q\u0101b\u016b"
    ],
    "wof:name":"Damir Qabu",
    "wof:placetype":"locality"
},
  "geometry": {"coordinates":[41.84651,36.96848],"type":"Point"}
}