{
  "type": "Feature",
  "properties": {
    "gn:admin1_code":"12.0",
    "gn:asciiname":"Isqat",
    "gn:country_code":"SY",
    "gn:dem":447,
    "gn:feature_class":"P",
    "gn:feature_code":"PPL",
    "gn:name":"Isq\u0101\u0163",
    "gn:population":0,
    "gn:timezone":"Asia/Damascus",
    "iso:country":"SY",
    "name:ara_x_preferred":[
        "Isq\u0101\u0163"
    ],
    "name:ara_x_variant":[
        "\u0625\u0633\u0642\u0627\u0637"
    ],
    "name:fas_x_preferred":[
        "\u0627\u0633\u0642\u0627\u0637"
    ],
    "name:pol_x_preferred":[
        "Iskat"
    ],
    "name:vie_x_preferred":[
        "Isqat"
    ],
    "wof:name":"Isqat",
    "wof:placetype":"locality"
},
  "geometry": {"coordinates":[36.47369000000001,36.15153],"type":"Point"}
}