{
  "type": "Feature",
  "properties": {
    "gn:admin1_code":"9.0",
    "gn:asciiname":"Qarassi",
    "gn:country_code":"SY",
    "gn:dem":325,
    "gn:feature_class":"P",
    "gn:feature_code":"PPL",
    "gn:name":"Qarassi",
    "gn:population":0,
    "gn:timezone":"Asia/Damascus",
    "iso:country":"SY",
    "name:ara_x_preferred":[
        "\u0642\u0631\u0627\u0635\u064a"
    ],
    "name:ara_x_variant":[
        "\u0642\u0631\u0627\u0637\u0628\u064a"
    ],
    "name:und_x_variant":[
        "Qr\u00e2ssi",
        "Qarassi",
        "Qarassiy\u00e9",
        "Qar\u0101\u015f\u012b",
        "Qar\u0101\u0163b\u012b"
    ],
    "wof:name":"Qarassi",
    "wof:placetype":"locality"
},
  "geometry": {"coordinates":[37.08148,36.0951],"type":"Point"}
}