{
  "type": "Feature",
  "properties": {
    "gn:admin1_code":"8.0",
    "gn:asciiname":"Khan al `Asafir",
    "gn:country_code":"SY",
    "gn:dem":820,
    "gn:feature_class":"P",
    "gn:feature_code":"PPL",
    "gn:name":"Kh\u0101n al \u2018A\u015f\u0101f\u012br",
    "gn:population":0,
    "gn:timezone":"Asia/Damascus",
    "iso:country":"SY",
    "name:und_x_variant":[
        "Kh\u0101n al \u2018A\u015f\u0101f\u012br"
    ],
    "wof:name":"Khan al `Asafir",
    "wof:placetype":"locality"
},
  "geometry": {"coordinates":[36.71667,33.81667],"type":"Point"}
}