{
  "type": "Feature",
  "properties": {
    "gn:admin1_code":"11.0",
    "gn:asciiname":"Ard Tariq Tarabulus",
    "gn:country_code":"SY",
    "gn:dem":495,
    "gn:feature_class":"P",
    "gn:feature_code":"PPLL",
    "gn:name":"Ar\u1e11 \u0162ar\u012bq \u0162ar\u0101bulus",
    "gn:population":0,
    "gn:timezone":"Asia/Damascus",
    "iso:country":"SY",
    "name:ara_x_preferred":[
        "\u0623\u0631\u0636 \u0637\u0631\u064a\u0642 \u0637\u0631\u0627\u0628\u0644\u0633"
    ],
    "name:und_x_variant":[
        "Ar\u1e11 \u0162ar\u012bq \u0162ar\u0101bulus"
    ],
    "wof:name":"Ard Tariq Tarabulus",
    "wof:placetype":"locality"
},
  "geometry": {"coordinates":[36.68749,34.72393],"type":"Point"}
}