{
  "type": "Feature",
  "properties": {
    "gn:admin1_code":"8.0",
    "gn:asciiname":"`Ali Abu Jasim",
    "gn:country_code":"SY",
    "gn:dem":601,
    "gn:feature_class":"P",
    "gn:feature_code":"PPL",
    "gn:name":"\u2018Al\u012b Ab\u016b J\u0101sim",
    "gn:population":0,
    "gn:timezone":"Asia/Damascus",
    "iso:country":"SY",
    "name:ara_x_preferred":[
        "\u0639\u0644\u064a \u0623\u0628\u0648 \u062c\u0627\u0633\u0645"
    ],
    "name:und_x_variant":[
        "\u2018Al\u012b Ab\u016b J\u0101sim"
    ],
    "wof:name":"`Ali Abu Jasim",
    "wof:placetype":"locality"
},
  "geometry": {"coordinates":[36.67897,33.4483],"type":"Point"}
}