{
  "type": "Feature",
  "properties": {
    "gn:admin1_code":"9.0",
    "gn:asciiname":"Abu Maqbarah Saghir",
    "gn:country_code":"SY",
    "gn:dem":339,
    "gn:feature_class":"P",
    "gn:feature_code":"PPL",
    "gn:name":"Ab\u016b Maqbarah Sagh\u012br",
    "gn:population":0,
    "gn:timezone":"Asia/Damascus",
    "iso:country":"SY",
    "name:ara_x_preferred":[
        "\u0623\u0628\u0648 \u0645\u0642\u0628\u0631\u0629 \u0635\u063a\u064a\u0631"
    ],
    "name:und_x_variant":[
        "Abou Moqbara Sghir",
        "Abou Maqbara S\u00e9rh\u00eer\u00e9",
        "Ab\u016b Maqbarah a\u015f \u015eagh\u012brah",
        "Ab\u016b Maqbarah Sagh\u012br"
    ],
    "wof:name":"Abu Maqbarah Saghir",
    "wof:placetype":"locality"
},
  "geometry": {"coordinates":[37.79929,36.1131],"type":"Point"}
}