{
  "type": "Feature",
  "properties": {
    "gn:admin1_code":"8.0",
    "gn:asciiname":"Al Qadi`",
    "gn:country_code":"SY",
    "gn:dem":702,
    "gn:feature_class":"P",
    "gn:feature_code":"PPLL",
    "gn:name":"Al Q\u0101di\u2018",
    "gn:population":0,
    "gn:timezone":"Asia/Damascus",
    "iso:country":"SY",
    "name:ara_x_preferred":[
        "Al Q\u0101di\u2018"
    ],
    "name:ara_x_variant":[
        "\u0627\u0644\u0642\u0627\u062f\u0639"
    ],
    "wof:name":"Al Qadi`",
    "wof:placetype":"locality"
},
  "geometry": {"coordinates":[36.2321,33.42305],"type":"Point"}
}