{
  "type": "Feature",
  "properties": {
    "gn:admin1_code":"10.0",
    "gn:asciiname":"Aq Duqarah",
    "gn:country_code":"SY",
    "gn:dem":404,
    "gn:feature_class":"P",
    "gn:feature_code":"PPL",
    "gn:name":"\u0100q D\u016bq\u0101rah",
    "gn:population":0,
    "gn:timezone":"Asia/Damascus",
    "iso:country":"SY",
    "name:ara_x_preferred":[
        "\u0100q D\u016bq\u0101r"
    ],
    "name:ara_x_variant":[
        "\u0627\u0642 \u062f\u0642\u0627\u0631\u0629",
        "\u0622\u0642 \u062f\u0642\u0627\u0631",
        "\u0628\u064a\u0636\u0627\u0621"
    ],
    "name:und_x_variant":[
        "Aq Douqar",
        "\u0100q D\u016bq\u0101rah",
        "\u0100q D\u016bq\u0101r",
        "Bay\u1e11\u0101\u2019"
    ],
    "wof:name":"Aq Duqarah",
    "wof:placetype":"locality"
},
  "geometry": {"coordinates":[36.37248,34.97302],"type":"Point"}
}