{
  "type": "Feature",
  "properties": {
    "gn:admin1_code":"9.0",
    "gn:asciiname":"An Nayrabiyah",
    "gn:country_code":"SY",
    "gn:dem":538,
    "gn:feature_class":"P",
    "gn:feature_code":"PPL",
    "gn:name":"An Nayrab\u012byah",
    "gn:population":0,
    "gn:timezone":"Asia/Damascus",
    "iso:country":"SY",
    "name:ara_x_preferred":[
        "\u0627\u0644\u0646\u064a\u0631\u0628\u064a\u0629"
    ],
    "name:ara_x_variant":[
        "\u0646\u064a\u0631\u0628\u064a\u0629"
    ],
    "name:und_x_variant":[
        "Ne\u00efrab\u00eey\u00e9",
        "Neirby\u00e9",
        "Nayrab\u012byah",
        "An Nayrab\u012byah"
    ],
    "wof:name":"An Nayrabiyah",
    "wof:placetype":"locality"
},
  "geometry": {"coordinates":[37.38022,36.37443],"type":"Point"}
}