{
  "type": "Feature",
  "properties": {
    "gn:admin1_code":"12.0",
    "gn:asciiname":"Balmis",
    "gn:country_code":"SY",
    "gn:dem":231,
    "gn:feature_class":"P",
    "gn:feature_code":"PPL",
    "gn:name":"Balm\u012bs",
    "gn:population":0,
    "gn:timezone":"Asia/Damascus",
    "iso:country":"SY",
    "name:ara_x_preferred":[
        "\u0628\u0644\u0645\u064a\u0633"
    ],
    "name:fas_x_preferred":[
        "\u0628\u0644\u0645\u06cc\u0633"
    ],
    "name:pol_x_preferred":[
        "Balmis"
    ],
    "name:und_x_variant":[
        "Balm\u012bs"
    ],
    "name:vie_x_preferred":[
        "Balmis"
    ],
    "wof:name":"Balmis",
    "wof:placetype":"locality"
},
  "geometry": {"coordinates":[36.37063,35.88689],"type":"Point"}
}