{
  "type": "Feature",
  "properties": {
    "gn:admin1_code":"7.0",
    "gn:asciiname":"Al Khan",
    "gn:country_code":"SY",
    "gn:dem":209,
    "gn:feature_class":"P",
    "gn:feature_code":"PPL",
    "gn:name":"Al Kh\u0101n",
    "gn:population":0,
    "gn:timezone":"Asia/Damascus",
    "iso:country":"SY",
    "name:ara_x_preferred":[
        "Al Kh\u0101n"
    ],
    "name:ara_x_variant":[
        "\u0627\u0644\u062e\u0627\u0646"
    ],
    "wof:name":"Al Khan",
    "wof:placetype":"locality"
},
  "geometry": {"coordinates":[40.47716,35.21483],"type":"Point"}
}