{
  "type": "Feature",
  "properties": {
    "gn:admin1_code":"7.0",
    "gn:asciiname":"Diban",
    "gn:cc2":"SY",
    "gn:country_code":"SY",
    "gn:dem":189,
    "gn:feature_class":"P",
    "gn:feature_code":"PPL",
    "gn:name":"D\u012bb\u0101n",
    "gn:population":0,
    "gn:timezone":"Asia/Damascus",
    "iso:country":"SY",
    "name:ara_x_preferred":[
        "D\u012bb\u0101n"
    ],
    "name:ara_x_variant":[
        "\u062f\u064a\u0628\u0627\u0646"
    ],
    "name:und_x_variant":[
        "Dabyan",
        "D\u00eeb\u00e2ne"
    ],
    "wof:name":"Diban",
    "wof:placetype":"locality"
},
  "geometry": {"coordinates":[40.51194,34.99528],"type":"Point"}
}