{
  "type": "Feature",
  "properties": {
    "gn:admin1_code":"1.0",
    "gn:asciiname":"`Ayn al Baz",
    "gn:country_code":"SY",
    "gn:dem":424,
    "gn:feature_class":"P",
    "gn:feature_code":"PPL",
    "gn:name":"\u2018Ayn al B\u0101z",
    "gn:population":0,
    "gn:timezone":"Asia/Damascus",
    "iso:country":"SY",
    "name:ara_x_preferred":[
        "\u0639\u064a\u0646 \u0627\u0644\u0628\u0627\u0632"
    ],
    "name:und_x_variant":[
        "A\u00efn B\u00e2zo\u00fbq",
        "\u2018Ayn B\u0101z\u016bt",
        "A\u00efn B\u00e2zo\u00fba",
        "\u2018Ayn B\u0101z\u016bq",
        "\u2018Ayn al B\u0101z"
    ],
    "wof:name":"`Ayn al Baz",
    "wof:placetype":"locality"
},
  "geometry": {"coordinates":[42.18806,37.22257000000001],"type":"Point"}
}