{
  "type": "Feature",
  "properties": {
    "gn:admin1_code":"14.0",
    "gn:asciiname":"Bayt as Sakhi",
    "gn:country_code":"SY",
    "gn:dem":216,
    "gn:feature_class":"P",
    "gn:feature_code":"PPL",
    "gn:name":"Bayt as Sakh\u012b",
    "gn:population":0,
    "gn:timezone":"Asia/Damascus",
    "iso:country":"SY",
    "name:ara_x_preferred":[
        "\u0628\u064a\u062a \u0627\u0644\u0633\u062e\u064a"
    ],
    "name:und_x_variant":[
        "Be\u00eft es Sakhi",
        "Bayt as Sakh\u012b"
    ],
    "wof:name":"Bayt as Sakhi",
    "wof:placetype":"locality"
},
  "geometry": {"coordinates":[35.98101,34.85313],"type":"Point"}
}