{
  "type": "Feature",
  "properties": {
    "gn:admin1_code":"11.0",
    "gn:asciiname":"Hasw Jihar",
    "gn:country_code":"SY",
    "gn:dem":647,
    "gn:feature_class":"P",
    "gn:feature_code":"PPL",
    "gn:name":"\u1e28asw Jih\u0101r",
    "gn:population":0,
    "gn:timezone":"Asia/Damascus",
    "iso:country":"SY",
    "name:ara_x_preferred":[
        "\u062d\u0633\u0648 \u062c\u0647\u0627\u0631"
    ],
    "name:und_x_variant":[
        "\u1e28asw Jih\u0101r"
    ],
    "wof:name":"Hasw Jihar",
    "wof:placetype":"locality"
},
  "geometry": {"coordinates":[37.8291,34.65124],"type":"Point"}
}