{
  "type": "Feature",
  "properties": {
    "gn:admin1_code":"9.0",
    "gn:asciiname":"Burj as Sama",
    "gn:country_code":"SY",
    "gn:dem":582,
    "gn:feature_class":"P",
    "gn:feature_code":"PPL",
    "gn:name":"Burj as Sam\u0101",
    "gn:population":0,
    "gn:timezone":"Asia/Damascus",
    "iso:country":"SY",
    "name:ara_x_preferred":[
        "\u0628\u0631\u062c \u0627\u0644\u0633\u0645\u0627"
    ],
    "name:und_x_variant":[
        "Borj Ahs\u00e2ne ed D\u00e2her",
        "Burj I\u1e29s\u0101n a\u1e11 \u1e10\u0101hir",
        "Burj as Sam\u0101"
    ],
    "wof:name":"Burj as Sama",
    "wof:placetype":"locality"
},
  "geometry": {"coordinates":[37.43482,35.91792],"type":"Point"}
}