{
  "type": "Feature",
  "properties": {
    "gn:admin1_code":"1.0",
    "gn:asciiname":"Ar Rimiyah",
    "gn:country_code":"SY",
    "gn:dem":294,
    "gn:feature_class":"P",
    "gn:feature_code":"PPL",
    "gn:name":"Ar R\u012bm\u012byah",
    "gn:population":0,
    "gn:timezone":"Asia/Damascus",
    "iso:country":"SY",
    "name:ara_x_preferred":[
        "\u0627\u0644\u0631\u064a\u0645\u064a\u0629"
    ],
    "name:und_x_variant":[
        "Ar R\u012bm\u012byah"
    ],
    "wof:name":"Ar Rimiyah",
    "wof:placetype":"locality"
},
  "geometry": {"coordinates":[40.89834000000001,36.07746],"type":"Point"}
}