{
  "type": "Feature",
  "properties": {
    "gn:admin1_code":"2.0",
    "gn:asciiname":"Qabuh",
    "gn:country_code":"SY",
    "gn:dem":453,
    "gn:feature_class":"P",
    "gn:feature_code":"PPL",
    "gn:name":"Qab\u016b\u1e29",
    "gn:population":0,
    "gn:timezone":"Asia/Damascus",
    "iso:country":"SY",
    "name:ara_x_preferred":[
        "Q\u0101b\u016b\u1e29"
    ],
    "name:ara_x_variant":[
        "\u0642\u0628\u0648\u062d"
    ],
    "name:und_x_variant":[
        "Q\u00e2bo\u00fbh",
        "Qab\u016b\u1e29"
    ],
    "wof:name":"Qabuh",
    "wof:placetype":"locality"
},
  "geometry": {"coordinates":[36.14034,35.75588],"type":"Point"}
}