{
  "type": "Feature",
  "properties": {
    "gn:admin1_code":"10.0",
    "gn:asciiname":"At Ta`unah",
    "gn:country_code":"SY",
    "gn:dem":413,
    "gn:feature_class":"P",
    "gn:feature_code":"PPL",
    "gn:name":"At T\u0101\u2018\u016bnah",
    "gn:population":0,
    "gn:timezone":"Asia/Damascus",
    "iso:country":"SY",
    "name:ara_x_preferred":[
        "\u0627\u0644\u062a\u0627\u0639\u0648\u0646\u0629"
    ],
    "name:und_x_variant":[
        "T\u00e2o\u00fbn\u00e9",
        "At T\u0101\u2018\u016bnah",
        "T\u00e2oun\u00e9"
    ],
    "wof:name":"At Ta`unah",
    "wof:placetype":"locality"
},
  "geometry": {"coordinates":[36.43215,34.93046],"type":"Point"}
}