{
  "type": "Feature",
  "properties": {
    "gn:admin1_code":"14.0",
    "gn:asciiname":"Matn as Safsafah",
    "gn:country_code":"SY",
    "gn:dem":196,
    "gn:feature_class":"P",
    "gn:feature_code":"PPL",
    "gn:name":"Matn a\u015f \u015eaf\u015f\u0101fah",
    "gn:population":0,
    "gn:timezone":"Asia/Damascus",
    "iso:country":"SY",
    "name:ara_x_preferred":[
        "\u0645\u062a\u0646 \u0627\u0644\u0635\u0641\u0635\u0627\u0641\u0629"
    ],
    "name:und_x_variant":[
        "Mtene Safsafe",
        "M\u00e9t\u00e8ne Safs\u00e2f\u00e9",
        "Matn a\u015f \u015eaf\u015f\u0101fah"
    ],
    "wof:name":"Matn as Safsafah",
    "wof:placetype":"locality"
},
  "geometry": {"coordinates":[36.06066,34.73138],"type":"Point"}
}