{
  "type": "Feature",
  "properties": {
    "gn:admin1_code":"9.0",
    "gn:asciiname":"Hawr",
    "gn:country_code":"SY",
    "gn:dem":454,
    "gn:feature_class":"P",
    "gn:feature_code":"PPL",
    "gn:name":"\u1e28awr",
    "gn:population":0,
    "gn:timezone":"Asia/Damascus",
    "iso:country":"SY",
    "name:ara_x_preferred":[
        "\u062d\u0648\u0627\u0631"
    ],
    "name:ara_x_variant":[
        "\u062d\u0648\u0631"
    ],
    "name:und_x_variant":[
        "Hou\u00e2r",
        "\u1e28aw\u0101r",
        "\u1e28awr"
    ],
    "wof:name":"Hawr",
    "wof:placetype":"locality"
},
  "geometry": {"coordinates":[36.97595,36.22961],"type":"Point"}
}