{
  "type": "Feature",
  "properties": {
    "gn:admin1_code":"2.0",
    "gn:asciiname":"Budaymu",
    "gn:country_code":"SY",
    "gn:dem":180,
    "gn:feature_class":"P",
    "gn:feature_code":"PPL",
    "gn:name":"Budaym\u016b",
    "gn:population":0,
    "gn:timezone":"Asia/Damascus",
    "iso:country":"SY",
    "name:ara_x_preferred":[
        "\u0628\u062f\u064a\u0645\u0648"
    ],
    "name:und_x_variant":[
        "Budaym\u016b"
    ],
    "wof:name":"Budaymu",
    "wof:placetype":"locality"
},
  "geometry": {"coordinates":[35.97887,35.49733],"type":"Point"}
}