{
  "type": "Feature",
  "properties": {
    "gn:admin1_code":"4.0",
    "gn:asciiname":"Jurn",
    "gn:country_code":"SY",
    "gn:dem":348,
    "gn:feature_class":"P",
    "gn:feature_code":"PPL",
    "gn:name":"Jurn",
    "gn:population":0,
    "gn:timezone":"Asia/Damascus",
    "iso:country":"SY",
    "name:ara_x_preferred":[
        "\u062c\u0631\u0646"
    ],
    "name:und_x_variant":[
        "Journ el Assouad",
        "Journ Assouad",
        "Jurn al Aswad",
        "Jurn"
    ],
    "wof:name":"Jurn",
    "wof:placetype":"locality"
},
  "geometry": {"coordinates":[38.80277,36.55063],"type":"Point"}
}