{
  "type": "Feature",
  "properties": {
    "gn:admin1_code":"9.0",
    "gn:asciiname":"Mazra`at as Sulaymaniyah",
    "gn:country_code":"SY",
    "gn:dem":569,
    "gn:feature_class":"P",
    "gn:feature_code":"PPL",
    "gn:name":"Mazra\u2018at as Sulaym\u0101n\u012byah",
    "gn:population":0,
    "gn:timezone":"Asia/Damascus",
    "iso:country":"SY",
    "name:ara_x_preferred":[
        "\u0645\u0632\u0631\u0639\u0629 \u0627\u0644\u0633\u0644\u064a\u0645\u0627\u0646\u064a\u0629"
    ],
    "name:und_x_variant":[
        "Mazra\u2018at as Sulaym\u0101n\u012byah"
    ],
    "wof:name":"Mazra`at as Sulaymaniyah",
    "wof:placetype":"locality"
},
  "geometry": {"coordinates":[36.69971,36.56526],"type":"Point"}
}