{
  "type": "Feature",
  "properties": {
    "gn:admin1_code":"4.0",
    "gn:asciiname":"Sabkhawi",
    "gn:country_code":"SY",
    "gn:dem":310,
    "gn:feature_class":"P",
    "gn:feature_code":"PPL",
    "gn:name":"Sabkh\u0101w\u012b",
    "gn:population":0,
    "gn:timezone":"Asia/Damascus",
    "iso:country":"SY",
    "name:ara_x_preferred":[
        "\u0633\u0628\u062e\u0627\u0648\u064a"
    ],
    "name:und_x_variant":[
        "Sabkh\u0101w\u012b"
    ],
    "wof:name":"Sabkhawi",
    "wof:placetype":"locality"
},
  "geometry": {"coordinates":[39.23674000000001,35.695],"type":"Point"}
}