{
  "type": "Feature",
  "properties": {
    "gn:admin1_code":"7.0",
    "gn:asciiname":"An Nab`ah",
    "gn:country_code":"SY",
    "gn:dem":193,
    "gn:feature_class":"P",
    "gn:feature_code":"PPL",
    "gn:name":"An Nab\u2018ah",
    "gn:population":0,
    "gn:timezone":"Asia/Damascus",
    "iso:country":"SY",
    "name:ara_x_preferred":[
        "\u0627\u0644\u0646\u0628\u0639\u0629"
    ],
    "name:und_x_variant":[
        "An Nab\u2018ah",
        "An Nab\u1e29ah"
    ],
    "wof:name":"An Nab`ah",
    "wof:placetype":"locality"
},
  "geometry": {"coordinates":[40.46498,35.13692],"type":"Point"}
}