{
  "type": "Feature",
  "properties": {
    "gn:admin1_code":"9.0",
    "gn:asciiname":"Kafr Dali Tahtani",
    "gn:country_code":"SY",
    "gn:dem":390,
    "gn:feature_class":"P",
    "gn:feature_code":"PPL",
    "gn:name":"Kafr Dal\u012b Ta\u1e29t\u0101n\u012b",
    "gn:population":0,
    "gn:timezone":"Asia/Damascus",
    "iso:country":"SY",
    "name:ara_x_preferred":[
        "\u0643\u0641\u0631 \u062f\u0644\u064a \u062a\u062d\u062a\u0627\u0646\u064a"
    ],
    "name:und_x_variant":[
        "Kafer D\u00e9li Taht\u00e2ni",
        "Kafr Dal et Tahtani",
        "Kafr Dal\u012b at Ta\u1e29t\u0101n\u012b",
        "Kafr Dal\u012b Ta\u1e29t\u0101n\u012b"
    ],
    "wof:name":"Kafr Dali Tahtani",
    "wof:placetype":"locality"
},
  "geometry": {"coordinates":[36.77813,36.47738],"type":"Point"}
}