{
  "type": "Feature",
  "properties": {
    "gn:admin1_code":"12.0",
    "gn:asciiname":"Mushayrifah Qibliyah",
    "gn:country_code":"SY",
    "gn:dem":420,
    "gn:feature_class":"P",
    "gn:feature_code":"PPL",
    "gn:name":"Mushayrifah Qibl\u012byah",
    "gn:population":0,
    "gn:timezone":"Asia/Damascus",
    "iso:country":"SY",
    "name:ara_x_preferred":[
        "\u0645\u0634\u064a\u0631\u0641\u0629 \u0642\u0628\u0644\u064a\u0629"
    ],
    "name:und_x_variant":[
        "Mushayrifah Qibl\u012byah"
    ],
    "wof:name":"Mushayrifah Qibliyah",
    "wof:placetype":"locality"
},
  "geometry": {"coordinates":[36.93676,35.42213],"type":"Point"}
}