{
  "type": "Feature",
  "properties": {
    "gn:admin1_code":"9.0",
    "gn:asciiname":"Al Ayyubiyah",
    "gn:country_code":"SY",
    "gn:dem":541,
    "gn:feature_class":"P",
    "gn:feature_code":"PPL",
    "gn:name":"Al Ayy\u016bb\u012byah",
    "gn:population":0,
    "gn:timezone":"Asia/Damascus",
    "iso:country":"SY",
    "name:ara_x_preferred":[
        "\u0627\u0644\u0623\u064a\u0648\u0628\u064a\u0629"
    ],
    "name:ara_x_variant":[
        "\u0639\u0631\u0628 \u062c\u0648\u0631\u062f\u0643"
    ],
    "name:und_x_variant":[
        "Aarab Tcheurdouk",
        "Arab Tcheurdouk",
        "Aarab Tchourdek",
        "\u2018Arab Tashurduk",
        "\u2018Arab J\u016brduk",
        "Al Ayy\u016bb\u012byah"
    ],
    "wof:name":"Al Ayyubiyah",
    "wof:placetype":"locality"
},
  "geometry": {"coordinates":[37.55178,36.57838],"type":"Point"}
}