{
  "type": "Feature",
  "properties": {
    "gn:admin1_code":"12.0",
    "gn:asciiname":"Haysh",
    "gn:country_code":"SY",
    "gn:dem":456,
    "gn:feature_class":"P",
    "gn:feature_code":"PPL",
    "gn:name":"\u1e28aysh",
    "gn:population":0,
    "gn:timezone":"Asia/Damascus",
    "iso:country":"SY",
    "name:und_x_variant":[
        "\u1e28aysh"
    ],
    "wof:name":"Haysh",
    "wof:placetype":"locality"
},
  "geometry": {"coordinates":[36.65,35.54167],"type":"Point"}
}