{
  "type": "Feature",
  "properties": {
    "gn:admin1_code":"6.0",
    "gn:asciiname":"Khirbat al Bu'ayr",
    "gn:country_code":"SY",
    "gn:dem":586,
    "gn:feature_class":"P",
    "gn:feature_code":"PPL",
    "gn:name":"Khirbat al Bu\u2019ayr",
    "gn:population":0,
    "gn:timezone":"Asia/Damascus",
    "iso:country":"SY",
    "name:und_x_variant":[
        "Kheurbet el B\u00f3ua\u00efr",
        "Khirbat al Bu\u2019ayr"
    ],
    "wof:name":"Khirbat al Bu'ayr",
    "wof:placetype":"locality"
},
  "geometry": {"coordinates":[36.28333,32.93391],"type":"Point"}
}