{
  "type": "Feature",
  "properties": {
    "gn:admin1_code":"1.0",
    "gn:asciiname":"Kundak",
    "gn:country_code":"SY",
    "gn:dem":437,
    "gn:feature_class":"P",
    "gn:feature_code":"PPL",
    "gn:name":"Kundak",
    "gn:population":0,
    "gn:timezone":"Asia/Damascus",
    "iso:country":"SY",
    "name:ara_x_preferred":[
        "\u0643\u0646\u062f\u0643"
    ],
    "name:tur_x_preferred":[
        "Kundak"
    ],
    "name:und_x_variant":[
        "Goundek",
        "Kundak"
    ],
    "wof:name":"Kundak",
    "wof:placetype":"locality"
},
  "geometry": {"coordinates":[40.64354,36.9645],"type":"Point"}
}