{
  "type": "Feature",
  "properties": {
    "gn:admin1_code":"14.0",
    "gn:asciiname":"Bayt Zaynah",
    "gn:country_code":"SY",
    "gn:dem":501,
    "gn:feature_class":"P",
    "gn:feature_code":"PPL",
    "gn:name":"Bayt Zaynah",
    "gn:population":0,
    "gn:timezone":"Asia/Damascus",
    "iso:country":"SY",
    "name:ara_x_preferred":[
        "\u0628\u064a\u062a \u0632\u064a\u0646\u0629"
    ],
    "name:und_x_variant":[
        "Be\u00eft Za\u00efna",
        "Bayt Zaynah"
    ],
    "wof:name":"Bayt Zaynah",
    "wof:placetype":"locality"
},
  "geometry": {"coordinates":[36.14336,34.90884],"type":"Point"}
}