{
  "type": "Feature",
  "properties": {
    "gn:admin1_code":"11.0",
    "gn:asciiname":"Al `Aliyat",
    "gn:country_code":"SY",
    "gn:dem":764,
    "gn:feature_class":"P",
    "gn:feature_code":"PPL",
    "gn:name":"Al \u2018\u0100liy\u0101t",
    "gn:population":0,
    "gn:timezone":"Asia/Damascus",
    "iso:country":"SY",
    "name:ara_x_preferred":[
        "\u2018\u0100liy\u0101t"
    ],
    "name:ara_x_variant":[
        "Al \u2018\u0100liy\u0101t",
        "\u0627\u0644\u0639\u0627\u0644\u064a\u0627\u062a"
    ],
    "name:und_x_variant":[
        "Aaliy\u00e2te"
    ],
    "wof:name":"Al `Aliyat",
    "wof:placetype":"locality"
},
  "geometry": {"coordinates":[36.83058,34.5418],"type":"Point"}
}