{
  "type": "Feature",
  "properties": {
    "gn:admin1_code":"5.0",
    "gn:asciiname":"Sa`na",
    "gn:country_code":"SY",
    "gn:dem":1370,
    "gn:feature_class":"P",
    "gn:feature_code":"PPL",
    "gn:name":"Sa\u2018n\u0101",
    "gn:population":0,
    "gn:timezone":"Asia/Damascus",
    "iso:country":"SY",
    "name:ara_x_preferred":[
        "\u0633\u0639\u0646\u0627"
    ],
    "name:und_x_variant":[
        "As Sa\u2018nah",
        "Sa\u2018ne",
        "Sa\u2018nah",
        "Saana",
        "Sa\u2018n\u0101"
    ],
    "wof:name":"Sa`na",
    "wof:placetype":"locality"
},
  "geometry": {"coordinates":[36.84246,32.68994],"type":"Point"}
}