{
  "type": "Feature",
  "properties": {
    "gn:admin1_code":"14.0",
    "gn:asciiname":"`Annazah",
    "gn:country_code":"SY",
    "gn:dem":250,
    "gn:feature_class":"P",
    "gn:feature_code":"PPL",
    "gn:name":"\u2018Ann\u0101zah",
    "gn:population":0,
    "gn:timezone":"Asia/Damascus",
    "iso:country":"SY",
    "name:ara_x_preferred":[
        "\u0639\u0646\u0627\u0632\u0629"
    ],
    "name:und_x_variant":[
        "Aann\u00e2z\u00e9",
        "Al \u2018Ann\u0101zah",
        "\u2018Ann\u0101zah"
    ],
    "wof:name":"`Annazah",
    "wof:placetype":"locality"
},
  "geometry": {"coordinates":[35.96597,35.00219],"type":"Point"}
}