{
  "type": "Feature",
  "properties": {
    "gn:admin1_code":"11.0",
    "gn:asciiname":"Az Zara",
    "gn:country_code":"SY",
    "gn:dem":290,
    "gn:feature_class":"P",
    "gn:feature_code":"PPL",
    "gn:name":"Az Z\u0101r\u0101",
    "gn:population":0,
    "gn:timezone":"Asia/Damascus",
    "iso:country":"SY",
    "name:ara_x_preferred":[
        "Az Z\u0101r\u0101"
    ],
    "name:ara_x_variant":[
        "\u0627\u0644\u0632\u0627\u0631\u0627"
    ],
    "name:und_x_variant":[
        "Z\u00e2ra",
        "Az Z\u0101rah"
    ],
    "wof:name":"Az Zara",
    "wof:placetype":"locality"
},
  "geometry": {"coordinates":[36.25507,34.71585],"type":"Point"}
}