{
  "type": "Feature",
  "properties": {
    "gn:admin1_code":"11.0",
    "gn:asciiname":"Bir ar Rahawi",
    "gn:country_code":"SY",
    "gn:dem":782,
    "gn:feature_class":"P",
    "gn:feature_code":"PPL",
    "gn:name":"B\u012br ar Ra\u1e29\u0101w\u012b",
    "gn:population":0,
    "gn:timezone":"Asia/Damascus",
    "iso:country":"SY",
    "name:ara_x_preferred":[
        "\u0628\u064a\u0631 \u0627\u0644\u0631\u062d\u0627\u0648\u064a"
    ],
    "name:und_x_variant":[
        "B\u012br ar Ra\u1e29\u0101w\u012b"
    ],
    "wof:name":"Bir ar Rahawi",
    "wof:placetype":"locality"
},
  "geometry": {"coordinates":[38.16036,35.00349],"type":"Point"}
}