{
  "type": "Feature",
  "properties": {
    "gn:admin1_code":"9.0",
    "gn:asciiname":"Kharab Nas",
    "gn:country_code":"SY",
    "gn:dem":478,
    "gn:feature_class":"P",
    "gn:feature_code":"PPL",
    "gn:name":"Khar\u0101b N\u0101s",
    "gn:population":0,
    "gn:timezone":"Asia/Damascus",
    "iso:country":"SY",
    "name:ara_x_preferred":[
        "\u062e\u0631\u0627\u0628 \u0646\u0627\u0633"
    ],
    "name:und_x_variant":[
        "Kharab Nias",
        "Khar\u00e2b-N\u00e2ss",
        "Khar\u0101b N\u0101s"
    ],
    "wof:name":"Kharab Nas",
    "wof:placetype":"locality"
},
  "geometry": {"coordinates":[38.55207,36.83025],"type":"Point"}
}