{
  "type": "Feature",
  "properties": {
    "gn:admin1_code":"9.0",
    "gn:asciiname":"Ra's al Aswad",
    "gn:country_code":"SY",
    "gn:dem":414,
    "gn:feature_class":"P",
    "gn:feature_code":"PPL",
    "gn:name":"Ra\u2019s al Aswad",
    "gn:population":0,
    "gn:timezone":"Asia/Damascus",
    "iso:country":"SY",
    "name:ara_x_preferred":[
        "\u0642\u0631\u0647 \u0628\u0627\u0634"
    ],
    "name:ara_x_variant":[
        "\u0631\u0623\u0633 \u0627\u0644\u0623\u0633\u0648\u062f"
    ],
    "name:und_x_variant":[
        "Karabache",
        "Qara B\u00e2ch",
        "Qarah B\u0101sh",
        "Ra\u2019s al Aswad"
    ],
    "wof:name":"Ra's al Aswad",
    "wof:placetype":"locality"
},
  "geometry": {"coordinates":[36.76132,36.47184],"type":"Point"}
}