{
  "type": "Feature",
  "properties": {
    "gn:admin1_code":"9.0",
    "gn:asciiname":"Al Buraykat",
    "gn:country_code":"SY",
    "gn:dem":374,
    "gn:feature_class":"P",
    "gn:feature_code":"PPL",
    "gn:name":"Al Burayk\u0101t",
    "gn:population":0,
    "gn:timezone":"Asia/Damascus",
    "iso:country":"SY",
    "name:ara_x_preferred":[
        "\u0627\u0644\u0628\u0631\u064a\u0643\u0627\u062a"
    ],
    "name:und_x_variant":[
        "Al Burayk\u0101t"
    ],
    "wof:name":"Al Buraykat",
    "wof:placetype":"locality"
},
  "geometry": {"coordinates":[37.03769000000001,36.20223],"type":"Point"}
}