{
  "type": "Feature",
  "properties": {
    "gn:admin1_code":"1.0",
    "gn:asciiname":"Faydah",
    "gn:country_code":"SY",
    "gn:dem":377,
    "gn:feature_class":"P",
    "gn:feature_code":"PPL",
    "gn:name":"Fay\u1e11ah",
    "gn:population":0,
    "gn:timezone":"Asia/Damascus",
    "iso:country":"SY",
    "name:ara_x_preferred":[
        "\u0641\u064a\u0636\u0629"
    ],
    "name:tur_x_preferred":[
        "F\u0101\u2019idah"
    ],
    "name:und_x_variant":[
        "F\u00e2\u00efda",
        "Fay\u1e11ah"
    ],
    "wof:name":"Faydah",
    "wof:placetype":"locality"
},
  "geometry": {"coordinates":[40.44454,36.82648],"type":"Point"}
}