{
  "type": "Feature",
  "properties": {
    "gn:admin1_code":"6.0",
    "gn:asciiname":"Marahat al Manqar ash Shamali",
    "gn:country_code":"SY",
    "gn:dem":602,
    "gn:feature_class":"P",
    "gn:feature_code":"PPL",
    "gn:name":"Mar\u0101\u1e29\u0101t al Manqar ash Sham\u0101l\u012b",
    "gn:population":0,
    "gn:timezone":"Asia/Damascus",
    "iso:country":"SY",
    "name:ara_x_preferred":[
        "\u0645\u0631\u0627\u062d\u0627\u062a \u0627\u0644\u0645\u0646\u0642\u0631 \u0627\u0644\u0634\u0645\u0627\u0644\u064a"
    ],
    "name:und_x_variant":[
        "Mar\u0101\u1e29\u0101t al Manqar ash Sham\u0101l\u012b"
    ],
    "wof:name":"Marahat al Manqar ash Shamali",
    "wof:placetype":"locality"
},
  "geometry": {"coordinates":[36.43055,33.18118],"type":"Point"}
}