{
  "type": "Feature",
  "properties": {
    "gn:country":"SY",
    "gn:fcode":"PPLA3",
    "gn:population":34231,
    "iso:country":"SY",
    "name:ara_x_preferred":[
        "\u0633\u0631\u0627\u0642\u0628"
    ],
    "name:arz_x_preferred":[
        "\u0633\u0631\u0627\u0642\u0628"
    ],
    "name:ast_x_preferred":[
        "Saraqib"
    ],
    "name:ceb_x_preferred":[
        "Sar\u0101qib"
    ],
    "name:ces_x_preferred":[
        "Sarak\u00edb"
    ],
    "name:deu_x_preferred":[
        "Sarakeb"
    ],
    "name:eng_x_preferred":[
        "Saraqib"
    ],
    "name:fas_x_preferred":[
        "\u0633\u0631\u0627\u0642\u0628"
    ],
    "name:fra_x_preferred":[
        "Saraqeb"
    ],
    "name:hye_x_preferred":[
        "\u054d\u0561\u0580\u0561\u056f\u056b\u0562"
    ],
    "name:nld_x_preferred":[
        "Saraqib"
    ],
    "name:nno_x_preferred":[
        "Saraqib"
    ],
    "name:nob_x_preferred":[
        "Saraqib"
    ],
    "name:pol_x_preferred":[
        "Sarakib"
    ],
    "name:rus_x_preferred":[
        "\u0421\u0435\u0440\u0430\u043a\u0438\u0431"
    ],
    "name:swe_x_preferred":[
        "Sar\u0101qib"
    ],
    "name:szl_x_preferred":[
        "Sarakib"
    ],
    "name:ukr_x_preferred":[
        "\u0421\u0430\u0440\u0430\u043a\u0456\u0431"
    ],
    "name:und_x_variant":[
        "Seraqib"
    ],
    "name:urd_x_preferred":[
        "\u0633\u0631\u0627\u0642\u0628"
    ],
    "name:vie_x_preferred":[
        "Saraqip"
    ],
    "name:zho_x_preferred":[
        "\u85a9\u62c9\u52ab"
    ],
    "qs:name":"Sar\u0101qib",
    "qs:photos_9r":0,
    "qs:photos_sr":0,
    "qs:pop_sr":"7",
    "wof:name":"Sar\u0101qib",
    "wof:placetype":"locality",
    "wof:population":34231
},
  "geometry": {"coordinates":[36.80591,35.86447],"type":"Point"}
}