{
  "type": "Feature",
  "properties": {
    "gn:admin1_code":"9.0",
    "gn:asciiname":"Jummiq",
    "gn:country_code":"SY",
    "gn:dem":397,
    "gn:feature_class":"P",
    "gn:feature_code":"PPL",
    "gn:name":"J\u016bmm\u012bq",
    "gn:population":0,
    "gn:timezone":"Asia/Damascus",
    "iso:country":"SY",
    "name:ara_x_preferred":[
        "\u062c\u0648\u0645\u064a\u0642"
    ],
    "name:ara_x_variant":[
        "J\u016bmm\u012bq"
    ],
    "name:und_x_variant":[
        "Jawm\u012bq"
    ],
    "wof:name":"Jummiq",
    "wof:placetype":"locality"
},
  "geometry": {"coordinates":[38.22342,36.71259000000001],"type":"Point"}
}