{
  "type": "Feature",
  "properties": {
    "gn:admin1_code":"8.0",
    "gn:asciiname":"Hawsh Balas",
    "gn:country_code":"SY",
    "gn:dem":682,
    "gn:feature_class":"P",
    "gn:feature_code":"PPLL",
    "gn:name":"\u1e28awsh Bal\u0101s",
    "gn:population":0,
    "gn:timezone":"Asia/Damascus",
    "iso:country":"SY",
    "name:ara_x_preferred":[
        "\u062d\u0648\u0634 \u0628\u0644\u0627\u0633"
    ],
    "name:und_x_variant":[
        "Haouch Blass",
        "Haouch el Bl\u00e2s",
        "\u1e28awsh al Bal\u0101s",
        "\u1e28awsh Bal\u0101s"
    ],
    "wof:name":"Hawsh Balas",
    "wof:placetype":"locality"
},
  "geometry": {"coordinates":[36.26198,33.43993],"type":"Point"}
}