{
  "type": "Feature",
  "properties": {
    "gn:admin1_code":"9.0",
    "gn:asciiname":"Qilji Qiran Fawqani",
    "gn:country_code":"SY",
    "gn:dem":417,
    "gn:feature_class":"P",
    "gn:feature_code":"PPL",
    "gn:name":"Qilj\u012b Q\u012br\u0101n Fawq\u0101n\u012b",
    "gn:population":0,
    "gn:timezone":"Asia/Damascus",
    "iso:country":"SY",
    "name:ara_x_preferred":[
        "\u0642\u0644\u062c\u064a \u0642\u064a\u0631\u0627\u0646 \u0641\u0648\u0642\u0627\u0646\u064a"
    ],
    "name:und_x_variant":[
        "Qilj\u012b Q\u012br\u0101n Fawq\u0101n\u012b",
        "Qalj\u012b Q\u012br\u0101n Fawq\u0101n\u012b"
    ],
    "wof:name":"Qilji Qiran Fawqani",
    "wof:placetype":"locality"
},
  "geometry": {"coordinates":[38.66233,36.55255],"type":"Point"}
}