{
  "type": "Feature",
  "properties": {
    "gn:admin1_code":"9.0",
    "gn:asciiname":"Al Qulay`ah",
    "gn:country_code":"SY",
    "gn:dem":409,
    "gn:feature_class":"P",
    "gn:feature_code":"PPL",
    "gn:name":"Al Qulay\u2018ah",
    "gn:population":0,
    "gn:timezone":"Asia/Damascus",
    "iso:country":"SY",
    "name:ara_x_preferred":[
        "\u0627\u0644\u0642\u0644\u064a\u0639\u0629"
    ],
    "name:und_x_variant":[
        "Qla\u00efa\u00e2",
        "Al Qulay\u2018ah"
    ],
    "wof:name":"Al Qulay`ah",
    "wof:placetype":"locality"
},
  "geometry": {"coordinates":[37.62452,35.78518],"type":"Point"}
}