{
  "type": "Feature",
  "properties": {
    "gn:admin1_code":"9.0",
    "gn:asciiname":"Qantarah",
    "gn:country_code":"SY",
    "gn:dem":495,
    "gn:feature_class":"P",
    "gn:feature_code":"PPL",
    "gn:name":"Qan\u0163arah",
    "gn:population":0,
    "gn:timezone":"Asia/Damascus",
    "iso:country":"SY",
    "name:ara_x_preferred":[
        "\u0642\u0646\u0637\u0631\u0629"
    ],
    "name:ara_x_variant":[
        "\u0642\u0646\u0637\u0631\u0629 \u0643\u0628\u064a\u0631\u0629"
    ],
    "name:und_x_variant":[
        "Qanatara",
        "Qantara",
        "Qanntara",
        "Qan\u0163arah",
        "Qan\u0163arah Kab\u012brah"
    ],
    "wof:name":"Qantarah",
    "wof:placetype":"locality"
},
  "geometry": {"coordinates":[37.72277,36.64402000000001],"type":"Point"}
}