{
  "type": "Feature",
  "properties": {
    "gn:admin1_code":"9.0",
    "gn:asciiname":"Al Mushayrifah",
    "gn:country_code":"SY",
    "gn:dem":380,
    "gn:feature_class":"P",
    "gn:feature_code":"PPL",
    "gn:name":"Al Mushayrifah",
    "gn:population":0,
    "gn:timezone":"Asia/Damascus",
    "iso:country":"SY",
    "name:ara_x_preferred":[
        "\u0627\u0644\u0645\u0634\u064a\u0631\u0641\u0629"
    ],
    "name:ceb_x_preferred":[
        "Al Mushayrifah"
    ],
    "name:swe_x_preferred":[
        "Al Mushayrifah"
    ],
    "wof:name":"Al Mushayrifah",
    "wof:placetype":"locality"
},
  "geometry": {"coordinates":[37.8708,35.64625],"type":"Point"}
}