{
  "type": "Feature",
  "properties": {
    "gn:admin1_code":"4.0",
    "gn:asciiname":"Mustajid Naqib",
    "gn:country_code":"SY",
    "gn:dem":245,
    "gn:feature_class":"P",
    "gn:feature_code":"PPL",
    "gn:name":"Mustaj\u012bd Naq\u012bb",
    "gn:population":0,
    "gn:timezone":"Asia/Damascus",
    "iso:country":"SY",
    "name:ara_x_preferred":[
        "\u0645\u0633\u062a\u062c\u064a\u062f \u0646\u0642\u064a\u0628"
    ],
    "name:und_x_variant":[
        "Naq\u012bb Mustajidd",
        "Mustaj\u012bd Naq\u012bb"
    ],
    "wof:name":"Mustajid Naqib",
    "wof:placetype":"locality"
},
  "geometry": {"coordinates":[39.05283,35.95584],"type":"Point"}
}