{
  "type": "Feature",
  "properties": {
    "gn:admin1_code":"6.0",
    "gn:asciiname":"Qal`at Asma",
    "gn:country_code":"SY",
    "gn:dem":624,
    "gn:feature_class":"P",
    "gn:feature_code":"PPL",
    "gn:name":"Qal\u2018at Asm\u0101",
    "gn:population":0,
    "gn:timezone":"Asia/Damascus",
    "iso:country":"SY",
    "name:ara_x_preferred":[
        "\u0642\u0644\u0639\u0629 \u0627\u0644\u0627\u0633\u0645\u0627"
    ],
    "name:ara_x_variant":[
        "\u0642\u0644\u0639\u0629 \u0623\u0633\u0645\u0627"
    ],
    "name:und_x_variant":[
        "Qalaat es Samak",
        "Qal\u2018at as Samak",
        "Qal\u2018at al Asm\u0101",
        "Qal\u2018at Asm\u0101"
    ],
    "wof:name":"Qal`at Asma",
    "wof:placetype":"locality"
},
  "geometry": {"coordinates":[36.33612,33.09545],"type":"Point"}
}