{
  "type": "Feature",
  "properties": {
    "gn:admin1_code":"1.0",
    "gn:asciiname":"`Ayn Qarah",
    "gn:country_code":"SY",
    "gn:dem":487,
    "gn:feature_class":"P",
    "gn:feature_code":"PPL",
    "gn:name":"\u2018Ayn Qarah",
    "gn:population":0,
    "gn:timezone":"Asia/Damascus",
    "iso:country":"SY",
    "name:ara_x_preferred":[
        "\u0639\u064a\u0646 \u0642\u0631\u0647"
    ],
    "name:tur_x_preferred":[
        "\u2018Ayn al Qird"
    ],
    "name:und_x_variant":[
        "A\u00efn el Qerd",
        "\u2018Ayn Qarah"
    ],
    "wof:name":"`Ayn Qarah",
    "wof:placetype":"locality"
},
  "geometry": {"coordinates":[40.77605,37.10215],"type":"Point"}
}