{
  "type": "Feature",
  "properties": {
    "gn:admin1_code":"10.0",
    "gn:asciiname":"Tall Abwiyah",
    "gn:country_code":"SY",
    "gn:dem":374,
    "gn:feature_class":"P",
    "gn:feature_code":"PPL",
    "gn:name":"Tall Abw\u012byah",
    "gn:population":0,
    "gn:timezone":"Asia/Damascus",
    "iso:country":"SY",
    "name:ara_x_preferred":[
        "\u062a\u0644 \u0623\u0628\u0648\u064a\u0629"
    ],
    "name:und_x_variant":[
        "Abou Hay\u00e9",
        "Ab\u016b \u1e28ayyah",
        "Tall Abw\u012byah"
    ],
    "wof:name":"Tall Abwiyah",
    "wof:placetype":"locality"
},
  "geometry": {"coordinates":[37.12542,35.38253],"type":"Point"}
}