{
  "type": "Feature",
  "properties": {
    "gn:admin1_code":"1.0",
    "gn:asciiname":"Safa",
    "gn:country_code":"SY",
    "gn:dem":343,
    "gn:feature_class":"P",
    "gn:feature_code":"PPL",
    "gn:name":"Safa",
    "gn:population":0,
    "gn:timezone":"Asia/Damascus",
    "iso:country":"SY",
    "name:ara_x_preferred":[
        "A\u015f \u015e\u0101fi\u1e29"
    ],
    "name:ara_x_variant":[
        "\u0627\u0644\u0635\u0627\u0641\u062d"
    ],
    "name:und_x_variant":[
        "Es S\u00e2feh",
        "Safa",
        "\u015e\u0101fi\u1e29",
        "S\u00e2feh"
    ],
    "wof:name":"Safa",
    "wof:placetype":"locality"
},
  "geometry": {"coordinates":[40.15621,36.73524000000001],"type":"Point"}
}