{
  "type": "Feature",
  "properties": {
    "gn:admin1_code":"11.0",
    "gn:asciiname":"Umm Tinah",
    "gn:country_code":"SY",
    "gn:dem":710,
    "gn:feature_class":"P",
    "gn:feature_code":"PPL",
    "gn:name":"Umm T\u012bnah",
    "gn:population":0,
    "gn:timezone":"Asia/Damascus",
    "iso:country":"SY",
    "name:ara_x_preferred":[
        "\u0623\u0645 \u0627\u0644\u062a\u064a\u0646\u0629"
    ],
    "name:ara_x_variant":[
        "\u0623\u0645 \u062a\u064a\u0646\u0629"
    ],
    "name:und_x_variant":[
        "Oum ett T\u00een\u00e9",
        "Umm at T\u012bn",
        "Umm at T\u012bnah",
        "Umm T\u012bnah"
    ],
    "wof:name":"Umm Tinah",
    "wof:placetype":"locality"
},
  "geometry": {"coordinates":[37.19182,34.59733],"type":"Point"}
}