{
  "type": "Feature",
  "properties": {
    "gn:admin1_code":"2.0",
    "gn:asciiname":"Babinna",
    "gn:country_code":"SY",
    "gn:dem":411,
    "gn:feature_class":"P",
    "gn:feature_code":"PPL",
    "gn:name":"B\u0101binn\u0101",
    "gn:population":0,
    "gn:timezone":"Asia/Damascus",
    "iso:country":"SY",
    "name:ara_x_preferred":[
        "\u0628\u0627\u0628\u0646\u0627"
    ],
    "name:und_x_variant":[
        "Mamera",
        "B\u0101binn\u0101",
        "B\u0101binan\u0101",
        "Babenna",
        "B\u0101bann\u0101"
    ],
    "wof:name":"Babinna",
    "wof:placetype":"locality"
},
  "geometry": {"coordinates":[36.04602,35.622],"type":"Point"}
}