{
  "type": "Feature",
  "properties": {
    "gn:admin1_code":"9.0",
    "gn:asciiname":"Mahattah",
    "gn:country_code":"SY",
    "gn:dem":415,
    "gn:feature_class":"P",
    "gn:feature_code":"PPL",
    "gn:name":"Ma\u1e29a\u0163\u0163ah",
    "gn:population":0,
    "gn:timezone":"Asia/Damascus",
    "iso:country":"SY",
    "name:ara_x_preferred":[
        "\u0645\u062d\u0637\u0629"
    ],
    "name:und_x_variant":[
        "Ma\u1e29a\u0163\u0163ah"
    ],
    "wof:name":"Mahattah",
    "wof:placetype":"locality"
},
  "geometry": {"coordinates":[37.21203,36.32371],"type":"Point"}
}