{
  "type": "Feature",
  "properties": {
    "gn:admin1_code":"2.0",
    "gn:asciiname":"Ard Bayt ash Shamlan",
    "gn:country_code":"SY",
    "gn:dem":27,
    "gn:feature_class":"P",
    "gn:feature_code":"PPLL",
    "gn:name":"Ar\u1e11 Bayt ash Shaml\u0101n",
    "gn:population":0,
    "gn:timezone":"Asia/Damascus",
    "iso:country":"SY",
    "name:ara_x_preferred":[
        "\u0623\u0631\u0636 \u0628\u064a\u062a \u0627\u0644\u0634\u0645\u0644\u0627\u0646"
    ],
    "name:und_x_variant":[
        "Ar\u1e11 Bayt ash Shaml\u0101n"
    ],
    "wof:name":"Ard Bayt ash Shamlan",
    "wof:placetype":"locality"
},
  "geometry": {"coordinates":[35.79338,35.56494],"type":"Point"}
}