{
  "type": "Feature",
  "properties": {
    "gn:admin1_code":"8.0",
    "gn:asciiname":"Haqlat as Safrah",
    "gn:country_code":"SY",
    "gn:dem":890,
    "gn:feature_class":"P",
    "gn:feature_code":"PPLL",
    "gn:name":"\u1e28aqlat a\u015f \u015eafrah",
    "gn:population":0,
    "gn:timezone":"Asia/Damascus",
    "iso:country":"SY",
    "name:ara_x_preferred":[
        "\u062d\u0642\u0644\u0629 \u0627\u0644\u0635\u0641\u0631\u0629"
    ],
    "name:und_x_variant":[
        "\u1e28aqlat a\u015f \u015eafrah"
    ],
    "wof:name":"Haqlat as Safrah",
    "wof:placetype":"locality"
},
  "geometry": {"coordinates":[36.15528,33.47332],"type":"Point"}
}