{
  "type": "Feature",
  "properties": {
    "gn:admin1_code":"2.0",
    "gn:asciiname":"Faqih Hasan",
    "gn:country_code":"SY",
    "gn:dem":57,
    "gn:feature_class":"P",
    "gn:feature_code":"PPL",
    "gn:name":"F\u0101q\u012bh \u1e28asan",
    "gn:population":0,
    "gn:timezone":"Asia/Damascus",
    "iso:country":"SY",
    "name:ara_x_preferred":[
        "\u0641\u0642\u064a\u0647 \u062d\u0633\u0646"
    ],
    "name:ara_x_variant":[
        "\u0641\u0627\u0642\u064a \u062d\u0633\u0646",
        "\u0627\u0644\u0634\u064a\u062e \u062d\u0633\u0646"
    ],
    "name:und_x_variant":[
        "F\u00e2qi Hass\u00e2ne",
        "F\u0101q\u012b \u1e28asan",
        "F\u0101q\u012bh \u1e28asan",
        "Ash Shaykh \u1e28asan"
    ],
    "wof:name":"Faqih Hasan",
    "wof:placetype":"locality"
},
  "geometry": {"coordinates":[35.90192000000001,35.86869],"type":"Point"}
}