{
  "type": "Feature",
  "properties": {
    "gn:admin1_code":"11.0",
    "gn:asciiname":"Dabbusiyah",
    "gn:country_code":"SY",
    "gn:dem":28,
    "gn:feature_class":"P",
    "gn:feature_code":"PPL",
    "gn:name":"Dabb\u016bs\u012byah",
    "gn:population":0,
    "gn:timezone":"Asia/Beirut",
    "iso:country":"SY",
    "name:ara_x_preferred":[
        "\u062f\u0628\u0648\u0633\u064a\u0629"
    ],
    "name:ara_x_variant":[
        "\u0627\u0644\u062f\u0628\u0648\u0633\u064a\u0629"
    ],
    "name:und_x_variant":[
        "Dabboussiye",
        "Dabb\u016bs\u012byah",
        "Ad Dabb\u016bs\u012byah"
    ],
    "wof:name":"Dabbusiyah",
    "wof:placetype":"locality"
},
  "geometry": {"coordinates":[36.1196,34.64117],"type":"Point"}
}