{
  "type": "Feature",
  "properties": {
    "gn:admin1_code":"8.0",
    "gn:asciiname":"Al Qusaytil",
    "gn:country_code":"SY",
    "gn:dem":697,
    "gn:feature_class":"P",
    "gn:feature_code":"PPLL",
    "gn:name":"Al Qu\u015fay\u0163il",
    "gn:population":0,
    "gn:timezone":"Asia/Damascus",
    "iso:country":"SY",
    "name:ara_x_preferred":[
        "\u0627\u0644\u0642\u0635\u064a\u0637\u0644"
    ],
    "name:und_x_variant":[
        "Al Qu\u015fay\u0163il"
    ],
    "wof:name":"Al Qusaytil",
    "wof:placetype":"locality"
},
  "geometry": {"coordinates":[36.23884,33.42443],"type":"Point"}
}