{
  "type": "Feature",
  "properties": {
    "gn:admin1_code":"9.0",
    "gn:asciiname":"At Tunbur",
    "gn:country_code":"SY",
    "gn:dem":458,
    "gn:feature_class":"P",
    "gn:feature_code":"PPL",
    "gn:name":"A\u0163 \u0162unbur",
    "gn:population":0,
    "gn:timezone":"Asia/Damascus",
    "iso:country":"SY",
    "name:ara_x_preferred":[
        "\u0162unb\u016br"
    ],
    "name:ara_x_variant":[
        "A\u0163 \u0162unbur",
        "\u0627\u0644\u0637\u0646\u0628\u0631",
        "\u0162umb\u016br",
        "\u0637\u0645\u0628\u0648\u0631"
    ],
    "name:und_x_variant":[
        "Toumbour",
        "Tomebour"
    ],
    "wof:name":"At Tunbur",
    "wof:placetype":"locality"
},
  "geometry": {"coordinates":[37.38014,36.27423],"type":"Point"}
}