{
  "type": "Feature",
  "properties": {
    "gn:admin1_code":"7.0",
    "gn:asciiname":"Al Hawi",
    "gn:country_code":"SY",
    "gn:dem":212,
    "gn:feature_class":"P",
    "gn:feature_code":"PPL",
    "gn:name":"Al \u1e28\u0101w\u012b",
    "gn:population":0,
    "gn:timezone":"Asia/Damascus",
    "iso:country":"SY",
    "name:ara_x_preferred":[
        "Al \u1e28\u0101w\u012b"
    ],
    "name:ara_x_variant":[
        "\u0627\u0644\u062d\u0627\u0648\u064a"
    ],
    "wof:name":"Al Hawi",
    "wof:placetype":"locality"
},
  "geometry": {"coordinates":[39.95822,35.48494],"type":"Point"}
}