{
  "type": "Feature",
  "properties": {
    "gn:admin1_code":"1.0",
    "gn:asciiname":"Khirbat Musaylah",
    "gn:country_code":"SY",
    "gn:dem":364,
    "gn:feature_class":"P",
    "gn:feature_code":"PPL",
    "gn:name":"Khirbat Musaylah",
    "gn:population":0,
    "gn:timezone":"Asia/Damascus",
    "iso:country":"SY",
    "name:ara_x_preferred":[
        "\u062e\u0631\u0628\u0629 \u0645\u0633\u064a\u0644\u0629"
    ],
    "name:tur_x_preferred":[
        "Khirbat Musaylah"
    ],
    "wof:name":"Khirbat Musaylah",
    "wof:placetype":"locality"
},
  "geometry": {"coordinates":[41.00469,36.78564],"type":"Point"}
}