{
  "type": "Feature",
  "properties": {
    "gn:admin1_code":"2.0",
    "gn:asciiname":"Ard Abu Qulaydah",
    "gn:country_code":"SY",
    "gn:dem":26,
    "gn:feature_class":"P",
    "gn:feature_code":"PPLL",
    "gn:name":"Ar\u1e11 Ab\u016b Qulaydah",
    "gn:population":0,
    "gn:timezone":"Asia/Damascus",
    "iso:country":"SY",
    "name:ara_x_preferred":[
        "\u0623\u0631\u0636 \u0623\u0628\u0648 \u0642\u0644\u064a\u062f\u0629"
    ],
    "name:und_x_variant":[
        "Ar\u1e11 Ab\u016b Qulaydah"
    ],
    "wof:name":"Ard Abu Qulaydah",
    "wof:placetype":"locality"
},
  "geometry": {"coordinates":[35.95903,35.29355],"type":"Point"}
}