{
  "type": "Feature",
  "properties": {
    "gn:admin1_code":"1.0",
    "gn:asciiname":"Ghadir an Nusus",
    "gn:country_code":"SY",
    "gn:dem":285,
    "gn:feature_class":"P",
    "gn:feature_code":"PPL",
    "gn:name":"Ghad\u012br an Nus\u016bs",
    "gn:population":0,
    "gn:timezone":"Asia/Damascus",
    "iso:country":"SY",
    "name:ara_x_preferred":[
        "\u063a\u062f\u064a\u0631 \u0627\u0644\u0646\u0633\u0648\u0633"
    ],
    "name:und_x_variant":[
        "Ghad\u012br an Nus\u016bs"
    ],
    "wof:name":"Ghadir an Nusus",
    "wof:placetype":"locality"
},
  "geometry": {"coordinates":[40.81178,36.21167],"type":"Point"}
}