{
  "type": "Feature",
  "properties": {
    "gn:admin1_code":"9.0",
    "gn:asciiname":"Kujik",
    "gn:country_code":"SY",
    "gn:dem":481,
    "gn:feature_class":"P",
    "gn:feature_code":"PPL",
    "gn:name":"K\u016bjik",
    "gn:population":0,
    "gn:timezone":"Asia/Damascus",
    "iso:country":"SY",
    "name:ara_x_preferred":[
        "K\u016bjik"
    ],
    "name:ara_x_variant":[
        "\u0643\u0648\u062c\u0643"
    ],
    "name:und_x_variant":[
        "Kawjak",
        "Qotchek"
    ],
    "wof:name":"Kujik",
    "wof:placetype":"locality"
},
  "geometry": {"coordinates":[38.55686,36.70979000000001],"type":"Point"}
}