{
  "type": "Feature",
  "properties": {
    "gn:admin1_code":"10.0",
    "gn:asciiname":"Salba",
    "gn:country_code":"SY",
    "gn:dem":236,
    "gn:feature_class":"P",
    "gn:feature_code":"PPL",
    "gn:name":"\u015ealb\u0101",
    "gn:population":0,
    "gn:timezone":"Asia/Damascus",
    "iso:country":"SY",
    "name:ara_x_preferred":[
        "\u0635\u0644\u0628\u0627"
    ],
    "name:und_x_variant":[
        "\u015ealb\u0101"
    ],
    "wof:name":"Salba",
    "wof:placetype":"locality"
},
  "geometry": {"coordinates":[36.44426,35.33407000000001],"type":"Point"}
}