{
  "type": "Feature",
  "properties": {
    "gn:admin1_code":"9.0",
    "gn:asciiname":"Kharab Sakk",
    "gn:country_code":"SY",
    "gn:dem":428,
    "gn:feature_class":"P",
    "gn:feature_code":"PPL",
    "gn:name":"Khar\u0101b Sakk",
    "gn:population":0,
    "gn:timezone":"Asia/Damascus",
    "iso:country":"SY",
    "name:und_x_variant":[
        "Khar\u0101b Sakk"
    ],
    "wof:name":"Kharab Sakk",
    "wof:placetype":"locality"
},
  "geometry": {"coordinates":[38.59444000000001,36.54583],"type":"Point"}
}