{
  "type": "Feature",
  "properties": {
    "gn:admin1_code":"4.0",
    "gn:asciiname":"Abu Husayn",
    "gn:country_code":"SY",
    "gn:dem":316,
    "gn:feature_class":"P",
    "gn:feature_code":"PPL",
    "gn:name":"Ab\u016b \u1e28usayn",
    "gn:population":0,
    "gn:timezone":"Asia/Damascus",
    "iso:country":"SY",
    "name:ara_x_preferred":[
        "\u0623\u0628\u0648 \u062d\u0633\u064a\u0646"
    ],
    "name:und_x_variant":[
        "Ab\u016b \u1e28usayn"
    ],
    "wof:name":"Abu Husayn",
    "wof:placetype":"locality"
},
  "geometry": {"coordinates":[39.31586,36.11178],"type":"Point"}
}