{
  "type": "Feature",
  "properties": {
    "gn:admin1_code":"1.0",
    "gn:asciiname":"Awkir Tahtani",
    "gn:country_code":"SY",
    "gn:dem":363,
    "gn:feature_class":"P",
    "gn:feature_code":"PPL",
    "gn:name":"Awk\u012br Ta\u1e29t\u0101n\u012b",
    "gn:population":0,
    "gn:timezone":"Asia/Damascus",
    "iso:country":"SY",
    "name:ara_x_preferred":[
        "\u0623\u0648\u0643\u064a\u0631 \u062a\u062d\u062a\u0627\u0646\u064a"
    ],
    "name:tur_x_preferred":[
        "Awk\u012br Ta\u1e29t\u0101n\u012b"
    ],
    "wof:name":"Awkir Tahtani",
    "wof:placetype":"locality"
},
  "geometry": {"coordinates":[40.84522,36.76608],"type":"Point"}
}