{
  "type": "Feature",
  "properties": {
    "gn:admin1_code":"9.0",
    "gn:asciiname":"Kirsanlah",
    "gn:country_code":"SY",
    "gn:dem":549,
    "gn:feature_class":"P",
    "gn:feature_code":"PPL",
    "gn:name":"Kirsanlah",
    "gn:population":0,
    "gn:timezone":"Asia/Damascus",
    "iso:country":"SY",
    "name:ara_x_preferred":[
        "\u0643\u0631\u0633\u0646\u0644\u064a"
    ],
    "name:ara_x_variant":[
        "\u0643\u0631\u0633\u0646\u0644\u0629"
    ],
    "name:und_x_variant":[
        "Qirsanall\u012b",
        "Kersenti",
        "Kersannli",
        "Kirs\u0101nall\u012b",
        "Kirsanl\u012b",
        "Kirsanlah",
        "Qar\u015fanl\u012b"
    ],
    "wof:name":"Kirsanlah",
    "wof:placetype":"locality"
},
  "geometry": {"coordinates":[37.53648,36.66099000000001],"type":"Point"}
}