{
  "type": "Feature",
  "properties": {
    "iso:country":"SY",
    "name:ara_x_preferred":[
        "\u0645\u064f\u062d\u0627\u0641\u0638\u0629 \u0637\u0631\u0637\u0648\u0633"
    ],
    "name:eng_x_preferred":[
        "Tartus Governorate"
    ],
    "qs:gn_pop":0,
    "qs:name":"\u0645\u064f\u062d\u0627\u0641\u0638\u0629 \u0637\u0631\u0637\u0648\u0633",
    "qs:name_adm0":"\u0633\u0648\u0631\u064a\u0627",
    "qs:name_adm1":"\u0645\u064f\u062d\u0627\u0641\u0638\u0629 \u0637\u0631\u0637\u0648\u0633",
    "qs:photos":664,
    "qs:photos_1k":135,
    "qs:photos_9k":3,
    "qs:photos_9r":5,
    "qs:photos_all":664,
    "qs:photos_sr":8,
    "qs:placetype":"Town",
    "qs:pop_sr":"0",
    "qs:woe_adm0":23424956,
    "wof:name":"Tartus Governorate",
    "wof:placetype":"locality"
},
  "geometry": {"coordinates":[35.8889,34.900738],"type":"Point"}
}