{
  "type": "Feature",
  "properties": {
    "gn:admin1_code":"12.0",
    "gn:asciiname":"Sarfud",
    "gn:country_code":"SY",
    "gn:dem":447,
    "gn:feature_class":"P",
    "gn:feature_code":"PPLL",
    "gn:name":"\u015earf\u016bd",
    "gn:population":0,
    "gn:timezone":"Asia/Damascus",
    "iso:country":"SY",
    "name:ara_x_preferred":[
        "\u0635\u0631\u0641\u0648\u062f"
    ],
    "name:und_x_variant":[
        "Serfo\u00fbd",
        "\u015earf\u016bd"
    ],
    "wof:name":"Sarfud",
    "wof:placetype":"locality"
},
  "geometry": {"coordinates":[36.68936,36.18517],"type":"Point"}
}