{
  "type": "Feature",
  "properties": {
    "gn:admin1_code":"11.0",
    "gn:asciiname":"Ghuzayliyah",
    "gn:country_code":"SY",
    "gn:dem":940,
    "gn:feature_class":"P",
    "gn:feature_code":"PPL",
    "gn:name":"Ghuzayl\u012byah",
    "gn:population":0,
    "gn:timezone":"Asia/Damascus",
    "iso:country":"SY",
    "name:ara_x_preferred":[
        "\u063a\u0632\u064a\u0644\u064a\u0629"
    ],
    "name:und_x_variant":[
        "Rhaz\u00e2l\u00e9",
        "Ghaz\u0101lah",
        "Ghuzayl\u012byah"
    ],
    "wof:name":"Ghuzayliyah",
    "wof:placetype":"locality"
},
  "geometry": {"coordinates":[37.46867,34.84171],"type":"Point"}
}