{
  "type": "Feature",
  "properties": {
    "gn:admin1_code":"14.0",
    "gn:asciiname":"Khirbat al Qatt",
    "gn:country_code":"SY",
    "gn:dem":35,
    "gn:feature_class":"P",
    "gn:feature_code":"PPL",
    "gn:name":"Khirbat al Qa\u0163\u0163",
    "gn:population":0,
    "gn:timezone":"Asia/Damascus",
    "iso:country":"SY",
    "name:ara_x_preferred":[
        "\u062e\u0631\u0628\u0629 \u0627\u0644\u0642\u0637"
    ],
    "name:und_x_variant":[
        "Khirbat al Qa\u0163\u0163"
    ],
    "wof:name":"Khirbat al Qatt",
    "wof:placetype":"locality"
},
  "geometry": {"coordinates":[35.97014,34.75758],"type":"Point"}
}