{
  "type": "Feature",
  "properties": {
    "gn:admin1_code":"2.0",
    "gn:asciiname":"Al Karamat",
    "gn:country_code":"SY",
    "gn:dem":105,
    "gn:feature_class":"P",
    "gn:feature_code":"PPL",
    "gn:name":"Al Kar\u0101m\u0101t",
    "gn:population":0,
    "gn:timezone":"Asia/Damascus",
    "iso:country":"SY",
    "name:ara_x_preferred":[
        "\u0627\u0644\u0643\u0631\u0627\u0645\u0627\u062a"
    ],
    "name:und_x_variant":[
        "Al Kar\u0101m\u0101t"
    ],
    "wof:name":"Al Karamat",
    "wof:placetype":"locality"
},
  "geometry": {"coordinates":[35.98585999999999,35.66655],"type":"Point"}
}