{
  "type": "Feature",
  "properties": {
    "gn:admin1_code":"2.0",
    "gn:asciiname":"`Uwaynat Wasil",
    "gn:country_code":"SY",
    "gn:dem":37,
    "gn:feature_class":"P",
    "gn:feature_code":"PPLL",
    "gn:name":"\u2018Uwayn\u0101t W\u0101\u015fil",
    "gn:population":0,
    "gn:timezone":"Asia/Damascus",
    "iso:country":"SY",
    "name:ara_x_preferred":[
        "\u0639\u0648\u064a\u0646\u0627\u062a \u0648\u0627\u0635\u0644"
    ],
    "name:und_x_variant":[
        "\u2018Uwayn\u0101t W\u0101\u015fil"
    ],
    "wof:name":"`Uwaynat Wasil",
    "wof:placetype":"locality"
},
  "geometry": {"coordinates":[35.88827,35.4856],"type":"Point"}
}