{
  "type": "Feature",
  "properties": {
    "gn:admin1_code":"9.0",
    "gn:asciiname":"`Uwayd",
    "gn:country_code":"SY",
    "gn:dem":334,
    "gn:feature_class":"P",
    "gn:feature_code":"PPL",
    "gn:name":"\u2018Uwayd",
    "gn:population":0,
    "gn:timezone":"Asia/Damascus",
    "iso:country":"SY",
    "name:ara_x_preferred":[
        "\u0639\u0648\u064a\u062f"
    ],
    "name:und_x_variant":[
        "\u2018Uwayd"
    ],
    "wof:name":"`Uwayd",
    "wof:placetype":"locality"
},
  "geometry": {"coordinates":[37.26404,35.78681],"type":"Point"}
}