{
  "type": "Feature",
  "properties": {
    "gn:admin1_code":"9.0",
    "gn:asciiname":"Arsalan Tash",
    "gn:country_code":"SY",
    "gn:dem":482,
    "gn:feature_class":"P",
    "gn:feature_code":"PPL",
    "gn:name":"Arsal\u0101n \u0162\u0101sh",
    "gn:population":0,
    "gn:timezone":"Asia/Damascus",
    "iso:country":"SY",
    "name:ara_x_preferred":[
        "\u0627\u0631\u0633\u0644\u0627\u0646 \u0637\u0627\u0634"
    ],
    "name:ara_x_variant":[
        "\u0634\u064a\u0631\u0627\u0646 \u0643\u0628\u064a\u0631",
        "\u0627\u0644\u0641\u0631\u0632\u062f\u0642",
        "\u062d\u062f\u0627\u062a\u0648"
    ],
    "name:deu_x_preferred":[
        "Arslan Tash"
    ],
    "name:fas_x_preferred":[
        "\u062d\u062f\u0627\u062a\u0648"
    ],
    "name:fra_x_preferred":[
        "Arslan Tash"
    ],
    "name:heb_x_preferred":[
        "\u05d0\u05e8\u05e1\u05dc\u05d0\u05df \u05d8\u05d0\u05e9"
    ],
    "name:ita_x_preferred":[
        "Arslan Tash"
    ],
    "name:kur_x_preferred":[
        "Sh\u00earan"
    ],
    "name:kur_x_variant":[
        "Firidiq",
        "Sheran",
        "\u0634\u06ce\u0631\u0627\u0646",
        "\u0641\u0631\u0632\u062f\u0642",
        "\u0634\u06d5\u0631\u0627\u0646",
        "Ferezideq",
        "\u0641\u06d5\u0631\u06d5\u0632\u062f\u06d5\u0642"
    ],
    "name:pol_x_preferred":[
        "Arslan Tash"
    ],
    "name:spa_x_preferred":[
        "Arslan Tash"
    ],
    "name:und_x_variant":[
        "Arsl\u00e2ne T\u00e2ch",
        "Arsal\u0101n \u0162\u0101sh",
        "Arsil\u0101n \u0162\u0101sh",
        "\u0162\u0101sh",
        "Sh\u012br\u0101n Kab\u012br",
        "Arsalan Tash",
        "Hadatu",
        "Al Farazdaq",
        "Shiran",
        "\u015e\u00earan",
        "Ferezdeq",
        "El Firezdeq"
    ],
    "wof:name":"Arsalan Tash",
    "wof:placetype":"locality"
},
  "geometry": {"coordinates":[38.40808,36.84889],"type":"Point"}
}