{
  "type": "Feature",
  "properties": {
    "gn:admin1_code":"1.0",
    "gn:asciiname":"Al Qamishli",
    "gn:country_code":"SY",
    "gn:dem":454,
    "gn:feature_class":"P",
    "gn:feature_code":"PPLA2",
    "gn:name":"Al Q\u0101mishl\u012b",
    "gn:population":0,
    "gn:timezone":"Asia/Damascus",
    "iso:country":"SY",
    "name:ara_x_preferred":[
        "\u0627\u0644\u0642\u0627\u0645\u0634\u0644\u064a"
    ],
    "name:deu_x_preferred":[
        "Qamischli"
    ],
    "name:eng_x_preferred":[
        "Al-Qamishli"
    ],
    "name:fas_x_preferred":[
        "\u0642\u0627\u0645\u0634\u0644\u06cc"
    ],
    "name:fin_x_preferred":[
        "Kamishli"
    ],
    "name:ita_x_preferred":[
        "Kamishli\u00e9"
    ],
    "name:kur_x_preferred":[
        "Qami\u015flo"
    ],
    "name:rus_x_preferred":[
        "\u042d\u043b\u044c-\u041a\u0430\u043c\u044b\u0448\u043b\u044b"
    ],
    "name:swe_x_preferred":[
        "Al-Qamishli"
    ],
    "name:tur_x_preferred":[
        "Al Q\u0101mishl\u012b"
    ],
    "name:und_x_variant":[
        "Q\u0101meshli",
        "Al-Kamishly",
        "Kamechlie",
        "Qamichl\u00eey\u00e9",
        "El Qamishliye",
        "Q\u0101mishl\u012byah",
        "Kamichlieh",
        "Qamichl\u012byah",
        "Kamishli"
    ],
    "wof:name":"Al Qamishli",
    "wof:placetype":"locality"
},
  "geometry": {"coordinates":[41.23142,37.05215],"type":"Point"}
}