{
  "type": "Feature",
  "properties": {
    "gn:admin1_code":"1.0",
    "gn:asciiname":"Al Mu`abbadah",
    "gn:country_code":"SY",
    "gn:dem":470,
    "gn:feature_class":"P",
    "gn:feature_code":"PPL",
    "gn:name":"Al Mu\u2018abbadah",
    "gn:population":0,
    "gn:timezone":"Asia/Damascus",
    "iso:country":"SY",
    "name:ara_x_preferred":[
        "\u0627\u0644\u0645\u0639\u0628\u062f\u0629"
    ],
    "name:kur_x_preferred":[
        "\u06af\u0631\u0643\u06ce \u0644\u06d5\u06af\u06ce"
    ],
    "name:und_x_variant":[
        "Al Mu\u2018abbadah",
        "Girk\u00ea Leg\u00ea",
        "\u0643\u0631\u0643\u064a \u0644\u0637\u064a"
    ],
    "wof:name":"Al Mu`abbadah",
    "wof:placetype":"locality"
},
  "geometry": {"coordinates":[41.96092,37.0214],"type":"Point"}
}