{
  "type": "Feature",
  "properties": {
    "gn:admin1_code":"14.0",
    "gn:asciiname":"Blimmanah",
    "gn:country_code":"SY",
    "gn:dem":102,
    "gn:feature_class":"P",
    "gn:feature_code":"PPL",
    "gn:name":"Blimm\u0101nah",
    "gn:population":0,
    "gn:timezone":"Asia/Damascus",
    "iso:country":"SY",
    "name:und_x_variant":[
        "Bl\u00e9mm\u00e2ne",
        "Blemm\u00e2na",
        "Blimm\u0101nah"
    ],
    "wof:name":"Blimmanah",
    "wof:placetype":"locality"
},
  "geometry": {"coordinates":[35.92732,35.08707],"type":"Point"}
}