{
  "type": "Feature",
  "properties": {
    "gn:admin1_code":"14.0",
    "gn:asciiname":"`Ayn Dabish",
    "gn:country_code":"SY",
    "gn:dem":292,
    "gn:feature_class":"P",
    "gn:feature_code":"PPL",
    "gn:name":"\u2018Ayn D\u0101bish",
    "gn:population":0,
    "gn:timezone":"Asia/Damascus",
    "iso:country":"SY",
    "name:ara_x_preferred":[
        "\u0639\u064a\u0646 \u062f\u0627\u0628\u0634"
    ],
    "name:und_x_variant":[
        "\u2018Ayn D\u0101bish"
    ],
    "wof:name":"`Ayn Dabish",
    "wof:placetype":"locality"
},
  "geometry": {"coordinates":[36.16178,34.77685],"type":"Point"}
}