{
  "type": "Feature",
  "properties": {
    "gn:admin1_code":"10.0",
    "gn:asciiname":"Ar Rasiyah",
    "gn:country_code":"SY",
    "gn:dem":415,
    "gn:feature_class":"P",
    "gn:feature_code":"PPL",
    "gn:name":"Ar R\u0101s\u012byah",
    "gn:population":0,
    "gn:timezone":"Asia/Damascus",
    "iso:country":"SY",
    "name:ara_x_preferred":[
        "\u0627\u0644\u0631\u0627\u0633\u064a\u0629"
    ],
    "name:und_x_variant":[
        "Ar R\u0101s\u012byah"
    ],
    "wof:name":"Ar Rasiyah",
    "wof:placetype":"locality"
},
  "geometry": {"coordinates":[36.72318,34.95228],"type":"Point"}
}