{
  "type": "Feature",
  "properties": {
    "gn:admin1_code":"9.0",
    "gn:asciiname":"Dunghuz",
    "gn:country_code":"SY",
    "gn:dem":483,
    "gn:feature_class":"P",
    "gn:feature_code":"PPL",
    "gn:name":"D\u016bngh\u016bz",
    "gn:population":0,
    "gn:timezone":"Asia/Damascus",
    "iso:country":"SY",
    "name:ara_x_preferred":[
        "D\u016bngh\u016bz"
    ],
    "name:ara_x_variant":[
        "\u062f\u0646\u063a\u0648\u0632",
        "\u0633\u0644\u0627\u0645\u0629 \u0635\u063a\u064a\u0631\u0629",
        "\u0633\u0644\u0627\u0645\u0629 \u0635\u063a\u064a\u0631"
    ],
    "name:kur_x_preferred":[
        "Dunqiza Bicuk"
    ],
    "name:kur_x_variant":[
        "Donqiza Bicuk",
        "Donqiza Bich\u00fbk",
        "Donqiza Bichuk",
        "\u062f\u0648\u0646\u0642\u0632\u0627 \u0628\u062c\u0648\u0643",
        "\u062f\u06c6\u0646\u0642\u0632\u0627 \u0628\u062c\u0648\u0643",
        "\u062f\u06c6\u0646\u0642\u0632\u0627 \u0628\u0686\u0648\u0648\u0643",
        "\u062f\u06c6\u0646\u0642\u0632\u0627 \u0628\u0686\u0648\u0643"
    ],
    "name:und_x_variant":[
        "Donnrho\u00fbz",
        "Donnrho\u00fbz S\u00e9rh\u00eer",
        "Donrhoz",
        "Dungh\u016bz a\u015f \u015eagh\u012br",
        "Dunghiz Saghir",
        "Sal\u0101mah \u015eagh\u012brah",
        "Donqiza Bi\u00e7\u00fbk",
        "Selama Sex\u00eera",
        "Selama Segh\u00eera",
        "Sal\u0101ma \u015eagh\u012bra",
        "Salama Saghira",
        "Zerav\u00eek",
        "Z\u0101rw\u012bk",
        "Sal\u0101mah \u015eagh\u012br"
    ],
    "wof:name":"Dunghuz",
    "wof:placetype":"locality"
},
  "geometry": {"coordinates":[38.25551,36.7631],"type":"Point"}
}