{
  "type": "Feature",
  "properties": {
    "gn:admin1_code":"9.0",
    "gn:asciiname":"Buban Kabir",
    "gn:country_code":"SY",
    "gn:dem":548,
    "gn:feature_class":"P",
    "gn:feature_code":"PPL",
    "gn:name":"B\u016bb\u0101n Kab\u012br",
    "gn:population":0,
    "gn:timezone":"Asia/Damascus",
    "iso:country":"SY",
    "name:ara_x_preferred":[
        "B\u016by\u0101n"
    ],
    "name:ara_x_variant":[
        "\u0628\u0648\u064a\u0627\u0646",
        "\u0628\u0648\u0628\u0627\u0646",
        "\u0628\u0627\u0628\u0627\u0646",
        "\u0628\u0648\u0628\u0627\u0646 \u0643\u0628\u064a\u0631"
    ],
    "name:kur_x_preferred":[
        "Buban"
    ],
    "name:kur_x_variant":[
        "\u0628\u06c6\u0628\u0627\u0646"
    ],
    "name:und_x_variant":[
        "Bon\u00e2ne",
        "Boy\u00e2ne",
        "B\u016bb\u0101n",
        "Boban",
        "B\u0101b\u0101n",
        "Baban",
        "B\u016bb\u0101n Kab\u012br"
    ],
    "wof:name":"Buban Kabir",
    "wof:placetype":"locality"
},
  "geometry": {"coordinates":[38.19626,36.89572],"type":"Point"}
}