{
  "type": "Feature",
  "properties": {
    "gn:admin1_code":"2.0",
    "gn:asciiname":"Ard al Bayad",
    "gn:country_code":"SY",
    "gn:dem":49,
    "gn:feature_class":"P",
    "gn:feature_code":"PPLL",
    "gn:name":"Ar\u1e11 al Bay\u0101\u1e11",
    "gn:population":0,
    "gn:timezone":"Asia/Damascus",
    "iso:country":"SY",
    "name:ara_x_preferred":[
        "\u0623\u0631\u0636 \u0627\u0644\u0628\u064a\u0627\u0636"
    ],
    "name:und_x_variant":[
        "Ar\u1e11 al Bay\u0101\u1e11"
    ],
    "wof:name":"Ard al Bayad",
    "wof:placetype":"locality"
},
  "geometry": {"coordinates":[35.81924,35.62768],"type":"Point"}
}