{
  "type": "Feature",
  "properties": {
    "gn:admin1_code":"2.0",
    "gn:asciiname":"Qarn Halyah",
    "gn:country_code":"SY",
    "gn:dem":676,
    "gn:feature_class":"P",
    "gn:feature_code":"PPL",
    "gn:name":"Qarn \u1e28alyah",
    "gn:population":0,
    "gn:timezone":"Asia/Damascus",
    "iso:country":"SY",
    "name:ara_x_preferred":[
        "\u0642\u0631\u0646 \u062d\u0644\u064a\u0629"
    ],
    "name:und_x_variant":[
        "Qarn \u1e28alyah",
        "Qarn \u1e28al\u012byah"
    ],
    "wof:name":"Qarn Halyah",
    "wof:placetype":"locality"
},
  "geometry": {"coordinates":[36.16285,35.35438],"type":"Point"}
}