{
  "type": "Feature",
  "properties": {
    "gn:admin1_code":"10.0",
    "gn:asciiname":"Dayr Shumayl at Tahtani",
    "gn:country_code":"SY",
    "gn:dem":310,
    "gn:feature_class":"P",
    "gn:feature_code":"PPL",
    "gn:name":"Dayr Shumayl at Ta\u1e29t\u0101n\u012b",
    "gn:population":0,
    "gn:timezone":"Asia/Damascus",
    "iso:country":"SY",
    "name:ara_x_preferred":[
        "\u062f\u064a\u0631 \u0634\u0645\u064a\u0644 \u0627\u0644\u062a\u062d\u062a\u0627\u0646\u064a"
    ],
    "name:und_x_variant":[
        "Hamidiya",
        "Dayr Sham\u012bl",
        "De\u00efr Chma\u00efl Taht\u00e2ni",
        "Deir Shem\u012bl",
        "Dayr Shumayyil",
        "De\u00efr Chma\u00efl",
        "Deir-y- Chemil",
        "Dar Shemail",
        "Dayr Shumayyil at Ta\u1e29t\u0101n\u012b",
        "Dayr Shumayl at Ta\u1e29t\u0101n\u012b"
    ],
    "wof:name":"Dayr Shumayl at Tahtani",
    "wof:placetype":"locality"
},
  "geometry": {"coordinates":[36.34538,35.21125],"type":"Point"}
}