{
  "type": "Feature",
  "properties": {
    "gn:admin1_code":"11.0",
    "gn:asciiname":"Harat Mahfud",
    "gn:country_code":"SY",
    "gn:dem":574,
    "gn:feature_class":"P",
    "gn:feature_code":"PPL",
    "gn:name":"\u1e28\u0101rat Ma\u1e29f\u016b\u1e11",
    "gn:population":0,
    "gn:timezone":"Asia/Damascus",
    "iso:country":"SY",
    "name:ara_x_preferred":[
        "\u062d\u0627\u0631\u0629 \u0645\u062d\u0641\u0648\u0636"
    ],
    "name:und_x_variant":[
        "\u1e28\u0101rat Ma\u1e29f\u016b\u1e11"
    ],
    "wof:name":"Harat Mahfud",
    "wof:placetype":"locality"
},
  "geometry": {"coordinates":[36.33645,34.81625],"type":"Point"}
}