{
  "type": "Feature",
  "properties": {
    "gn:admin1_code":"12.0",
    "gn:asciiname":"Ma`arrata",
    "gn:country_code":"SY",
    "gn:dem":833,
    "gn:feature_class":"P",
    "gn:feature_code":"PPL",
    "gn:name":"Ma\u2018arr\u0101t\u0101",
    "gn:population":0,
    "gn:timezone":"Asia/Damascus",
    "iso:country":"SY",
    "name:ara_x_preferred":[
        "\u0645\u0639\u0631\u0627\u062a\u0627"
    ],
    "name:und_x_variant":[
        "Ma\u2018arr\u0101t\u0101"
    ],
    "wof:name":"Ma`arrata",
    "wof:placetype":"locality"
},
  "geometry": {"coordinates":[36.47804,35.71042],"type":"Point"}
}