{
  "type": "Feature",
  "properties": {
    "gn:admin1_code":"14.0",
    "gn:asciiname":"An Nabi Yunus",
    "gn:cc2":"SY",
    "gn:country_code":"SY",
    "gn:dem":470,
    "gn:feature_class":"P",
    "gn:feature_code":"PPL",
    "gn:name":"An Nab\u012b Y\u016bnus",
    "gn:population":0,
    "gn:timezone":"Asia/Damascus",
    "iso:country":"SY",
    "name:und_x_variant":[
        "Nabi Yo\u00fbn\u00e9s",
        "Nabi Allah Yo\u00fbnes",
        "An Nab\u012b Y\u016bnus"
    ],
    "wof:name":"An Nabi Yunus",
    "wof:placetype":"locality"
},
  "geometry": {"coordinates":[36.08333,35.03333],"type":"Point"}
}