{
  "type": "Feature",
  "properties": {
    "gn:admin1_code":"9.0",
    "gn:asciiname":"Humaymah Kabir",
    "gn:country_code":"SY",
    "gn:dem":359,
    "gn:feature_class":"P",
    "gn:feature_code":"PPL",
    "gn:name":"\u1e28umaymah Kab\u012br",
    "gn:population":0,
    "gn:timezone":"Asia/Damascus",
    "iso:country":"SY",
    "name:ara_x_preferred":[
        "\u062d\u0645\u064a\u0645\u0629 \u0643\u0628\u064a\u0631"
    ],
    "name:und_x_variant":[
        "Hma\u00efm\u00e9 el K\u00e9b\u00eer\u00e9",
        "Hma\u00efme Kbir\u00e9",
        "Hma\u00efme K\u00e9b\u00eer\u00e9",
        "\u1e28umaymah al Kab\u012brah",
        "\u1e28umaymah Kab\u012br"
    ],
    "wof:name":"Humaymah Kabir",
    "wof:placetype":"locality"
},
  "geometry": {"coordinates":[37.6464,36.17291],"type":"Point"}
}