{
  "type": "Feature",
  "properties": {
    "gn:admin1_code":"1.0",
    "gn:asciiname":"Kharab Run",
    "gn:country_code":"SY",
    "gn:dem":421,
    "gn:feature_class":"P",
    "gn:feature_code":"PPL",
    "gn:name":"Khar\u0101b R\u016bn",
    "gn:population":0,
    "gn:timezone":"Asia/Damascus",
    "iso:country":"SY",
    "name:ara_x_preferred":[
        "\u062e\u0631\u0627\u0628 \u0631\u0648\u0646"
    ],
    "name:und_x_variant":[
        "Khar\u00e2b Ro\u00fbn",
        "Khar\u0101b R\u016bn"
    ],
    "wof:name":"Kharab Run",
    "wof:placetype":"locality"
},
  "geometry": {"coordinates":[42.32448,37.10857],"type":"Point"}
}