{
  "type": "Feature",
  "properties": {
    "gn:admin1_code":"2.0",
    "gn:asciiname":"Ard ash Shaykh Jami`",
    "gn:country_code":"SY",
    "gn:dem":29,
    "gn:feature_class":"P",
    "gn:feature_code":"PPLL",
    "gn:name":"Ar\u1e11 ash Shaykh J\u0101mi\u2018",
    "gn:population":0,
    "gn:timezone":"Asia/Damascus",
    "iso:country":"SY",
    "name:ara_x_preferred":[
        "\u0623\u0631\u0636 \u0627\u0644\u0634\u064a\u062e \u062c\u0627\u0645\u0639"
    ],
    "name:und_x_variant":[
        "Ar\u1e11 ash Shaykh J\u0101mi\u2018"
    ],
    "wof:name":"Ard ash Shaykh Jami`",
    "wof:placetype":"locality"
},
  "geometry": {"coordinates":[35.94831,35.35877],"type":"Point"}
}