{
  "type": "Feature",
  "properties": {
    "gn:admin1_code":"9.0",
    "gn:asciiname":"`Arab Hasan Kabir",
    "gn:country_code":"SY",
    "gn:dem":431,
    "gn:feature_class":"P",
    "gn:feature_code":"PPL",
    "gn:name":"\u2018Arab \u1e28asan Kab\u012br",
    "gn:population":0,
    "gn:timezone":"Asia/Damascus",
    "iso:country":"SY",
    "name:ara_x_preferred":[
        "\u0639\u0631\u0628 \u062d\u0633\u0646 \u0643\u0628\u064a\u0631"
    ],
    "name:und_x_variant":[
        "Aarab Hassan Keb\u00eer",
        "Aarab Hassane K\u00e9b\u00eer",
        "\u2018Arab \u1e28asan al Kab\u012br",
        "\u2018Arab \u1e28asan Kab\u012br"
    ],
    "wof:name":"`Arab Hasan Kabir",
    "wof:placetype":"locality"
},
  "geometry": {"coordinates":[37.84806,36.64984000000001],"type":"Point"}
}