{
  "type": "Feature",
  "properties": {
    "gn:admin1_code":"1.0",
    "gn:asciiname":"Hannawiyah Hadariyah",
    "gn:country_code":"SY",
    "gn:dem":352,
    "gn:feature_class":"P",
    "gn:feature_code":"PPL",
    "gn:name":"\u1e28ann\u0101w\u012byah \u1e28a\u1e11ar\u012byah",
    "gn:population":0,
    "gn:timezone":"Asia/Damascus",
    "iso:country":"SY",
    "name:ara_x_preferred":[
        "\u062d\u0646\u0627\u0648\u064a\u0629 \u062d\u0636\u0631\u064a\u0629"
    ],
    "name:tur_x_preferred":[
        "\u1e28ann\u0101w\u012byah \u1e28a\u1e11ar\u012byah"
    ],
    "name:und_x_variant":[
        "Hann\u00e2ou\u00eey\u00e9 Hadr\u00eey\u00e9"
    ],
    "wof:name":"Hannawiyah Hadariyah",
    "wof:placetype":"locality"
},
  "geometry": {"coordinates":[41.43386,36.78442],"type":"Point"}
}