{
  "type": "Feature",
  "properties": {
    "gn:admin1_code":"12.0",
    "gn:asciiname":"Kuku",
    "gn:country_code":"SY",
    "gn:dem":697,
    "gn:feature_class":"P",
    "gn:feature_code":"PPL",
    "gn:name":"K\u016bk\u016b",
    "gn:population":0,
    "gn:timezone":"Asia/Damascus",
    "iso:country":"SY",
    "name:ara_x_preferred":[
        "K\u016bk\u016b"
    ],
    "name:ara_x_variant":[
        "\u0643\u0648\u0643\u0648"
    ],
    "name:aze_x_preferred":[
        "K\u00fck\u00fc"
    ],
    "name:ceb_x_preferred":[
        "Kuku"
    ],
    "name:deu_x_preferred":[
        "Kuku"
    ],
    "name:eus_x_preferred":[
        "Kuku"
    ],
    "name:fra_x_preferred":[
        "Kuku"
    ],
    "name:pol_x_preferred":[
        "Kuku"
    ],
    "name:sco_x_preferred":[
        "Kuku"
    ],
    "name:swa_x_preferred":[
        "Mto Kuku"
    ],
    "name:swe_x_preferred":[
        "Kuku"
    ],
    "name:und_x_variant":[
        "Ko\u00fbkou"
    ],
    "wof:name":"Kuku",
    "wof:placetype":"locality"
},
  "geometry": {"coordinates":[36.55581,36.07921],"type":"Point"}
}