{
  "type": "Feature",
  "properties": {
    "gn:admin1_code":"2.0",
    "gn:asciiname":"Majdal Salih",
    "gn:country_code":"SY",
    "gn:dem":890,
    "gn:feature_class":"P",
    "gn:feature_code":"PPL",
    "gn:name":"Majdal \u015e\u0101li\u1e29",
    "gn:population":0,
    "gn:timezone":"Asia/Damascus",
    "iso:country":"SY",
    "name:ara_x_preferred":[
        "\u0645\u062c\u062f\u0644 \u0635\u0627\u0644\u062d"
    ],
    "name:und_x_variant":[
        "Majdel S\u00e2leh",
        "Majdal \u015e\u0101li\u1e29"
    ],
    "wof:name":"Majdal Salih",
    "wof:placetype":"locality"
},
  "geometry": {"coordinates":[36.13985,35.61259000000001],"type":"Point"}
}