{
  "type": "Feature",
  "properties": {
    "gn:admin1_code":"9.0",
    "gn:asciiname":"Tall `Anbar",
    "gn:country_code":"SY",
    "gn:dem":576,
    "gn:feature_class":"P",
    "gn:feature_code":"PPL",
    "gn:name":"Tall \u2018Anbar",
    "gn:population":0,
    "gn:timezone":"Asia/Damascus",
    "iso:country":"SY",
    "name:ara_x_preferred":[
        "\u062a\u0644 \u0639\u0646\u0628\u0631"
    ],
    "name:und_x_variant":[
        "Tell Aambar",
        "Tall \u2018Anbar"
    ],
    "wof:name":"Tall `Anbar",
    "wof:placetype":"locality"
},
  "geometry": {"coordinates":[37.41563,35.92367],"type":"Point"}
}