{
  "type": "Feature",
  "properties": {
    "gn:admin1_code":"9.0",
    "gn:asciiname":"Zu`rurah",
    "gn:country_code":"SY",
    "gn:dem":484,
    "gn:feature_class":"P",
    "gn:feature_code":"PPL",
    "gn:name":"Zu\u2018r\u016brah",
    "gn:population":0,
    "gn:timezone":"Asia/Damascus",
    "iso:country":"SY",
    "name:ara_x_preferred":[
        "\u0632\u0639\u0631\u0648\u0631\u0629"
    ],
    "name:und_x_variant":[
        "Sidjane",
        "Zaaro\u00fbra",
        "Za\u2018r\u016brah",
        "Zu\u2018r\u016brah"
    ],
    "wof:name":"Zu`rurah",
    "wof:placetype":"locality"
},
  "geometry": {"coordinates":[37.75059,36.38137],"type":"Point"}
}