{
  "type": "Feature",
  "properties": {
    "gn:admin1_code":"1.0",
    "gn:asciiname":"Haram Hasan",
    "gn:country_code":"SY",
    "gn:dem":390,
    "gn:feature_class":"P",
    "gn:feature_code":"PPL",
    "gn:name":"Haram \u1e28asan",
    "gn:population":0,
    "gn:timezone":"Asia/Damascus",
    "iso:country":"SY",
    "name:ara_x_preferred":[
        "\u0647\u0631\u0645 \u062d\u0633\u0646"
    ],
    "name:tur_x_preferred":[
        "Haram \u1e28asan"
    ],
    "name:und_x_variant":[
        "\u1e28aram \u1e28asan",
        "Haram Hassane"
    ],
    "wof:name":"Haram Hasan",
    "wof:placetype":"locality"
},
  "geometry": {"coordinates":[41.09439,36.89669],"type":"Point"}
}