{
  "type": "Feature",
  "properties": {
    "gn:admin1_code":"12.0",
    "gn:asciiname":"Khirbat ash Shawish",
    "gn:country_code":"SY",
    "gn:dem":179,
    "gn:feature_class":"P",
    "gn:feature_code":"PPL",
    "gn:name":"Khirbat ash Sh\u0101w\u012bsh",
    "gn:population":0,
    "gn:timezone":"Asia/Damascus",
    "iso:country":"SY",
    "name:ara_x_preferred":[
        "\u062e\u0631\u0628\u0629 \u0627\u0644\u0634\u0627\u0648\u064a\u0634"
    ],
    "name:und_x_variant":[
        "Kheurbet ech Ch\u00e2ou\u00eech",
        "Khirbat ash Sh\u0101w\u012bsh"
    ],
    "wof:name":"Khirbat ash Shawish",
    "wof:placetype":"locality"
},
  "geometry": {"coordinates":[36.52856,36.2235],"type":"Point"}
}