{
  "type": "Feature",
  "properties": {
    "gn:admin1_code":"7.0",
    "gn:asciiname":"Sillu",
    "gn:country_code":"SY",
    "gn:dem":196,
    "gn:feature_class":"P",
    "gn:feature_code":"PPL",
    "gn:name":"Sill\u016b",
    "gn:population":0,
    "gn:timezone":"Asia/Damascus",
    "iso:country":"SY",
    "name:ara_x_preferred":[
        "Sill\u016b"
    ],
    "name:ara_x_variant":[
        "\u0633\u0644\u0648"
    ],
    "name:und_x_variant":[
        "Sillo"
    ],
    "wof:name":"Sillu",
    "wof:placetype":"locality"
},
  "geometry": {"coordinates":[40.35778,35.1434],"type":"Point"}
}