{
  "type": "Feature",
  "properties": {
    "gn:admin1_code":"9.0",
    "gn:asciiname":"Ad Dara`iyah Umm `Adas",
    "gn:country_code":"SY",
    "gn:dem":498,
    "gn:feature_class":"P",
    "gn:feature_code":"PPL",
    "gn:name":"Ad Dara\u2018\u012byah Umm \u2018Adas",
    "gn:population":0,
    "gn:timezone":"Asia/Damascus",
    "iso:country":"SY",
    "name:ara_x_preferred":[
        "\u0627\u0644\u062f\u0631\u0639\u064a\u0629 \u0627\u0645 \u0639\u062f\u0633"
    ],
    "name:ara_x_variant":[
        "\u0623\u0645 \u0639\u062f\u064a\u0633\u0629"
    ],
    "name:und_x_variant":[
        "Oum Aadass\u00e9",
        "Umm \u2018Adasah",
        "Ad Dara\u2018\u012byah Umm \u2018Adas",
        "Umm \u2018Adas\u012byah"
    ],
    "wof:name":"Ad Dara`iyah Umm `Adas",
    "wof:placetype":"locality"
},
  "geometry": {"coordinates":[37.34391,36.28804],"type":"Point"}
}