{
  "type": "Feature",
  "properties": {
    "gn:admin1_code":"10.0",
    "gn:asciiname":"Rasm at Tinah",
    "gn:country_code":"SY",
    "gn:dem":363,
    "gn:feature_class":"P",
    "gn:feature_code":"PPL",
    "gn:name":"Rasm at T\u012bnah",
    "gn:population":0,
    "gn:timezone":"Asia/Damascus",
    "iso:country":"SY",
    "name:ara_x_preferred":[
        "\u0631\u0633\u0645 \u0627\u0644\u062a\u064a\u0646\u0629"
    ],
    "name:und_x_variant":[
        "Rasm at T\u012bnah"
    ],
    "wof:name":"Rasm at Tinah",
    "wof:placetype":"locality"
},
  "geometry": {"coordinates":[37.25542,35.41335],"type":"Point"}
}