{
  "type": "Feature",
  "properties": {
    "gn:admin1_code":"9.0",
    "gn:asciiname":"Mamayd",
    "gn:country_code":"SY",
    "gn:dem":546,
    "gn:feature_class":"P",
    "gn:feature_code":"PPL",
    "gn:name":"M\u0101mayd",
    "gn:population":0,
    "gn:timezone":"Asia/Damascus",
    "iso:country":"SY",
    "name:ara_x_preferred":[
        "M\u0101m\u012bd"
    ],
    "name:ara_x_variant":[
        "\u0645\u0627\u0645\u064a\u062f",
        "\u0645\u0627\u0645\u064a\u062a",
        "\u0627\u0644\u062d\u0645\u0627\u0645\u0627",
        "\u062d\u0645\u0627\u0645\u0627"
    ],
    "name:kur_x_preferred":[
        "Himam\u00eek"
    ],
    "name:kur_x_variant":[
        "Himamik",
        "\u0647\u0645\u0627\u0645\u064a\u0643",
        "\u0647\u0645\u0627\u0645\u0643"
    ],
    "name:und_x_variant":[
        "M\u00e2me\u00eft",
        "M\u00e2meite",
        "M\u0101mayt",
        "M\u0101mayd",
        "Mamayt",
        "Al \u1e28am\u0101m\u0101",
        "Elhemama",
        "\u1e28am\u0101m\u0101",
        "Hamama"
    ],
    "wof:name":"Mamayd",
    "wof:placetype":"locality"
},
  "geometry": {"coordinates":[38.32634,36.86961],"type":"Point"}
}