{
  "type": "Feature",
  "properties": {
    "gn:admin1_code":"1.0",
    "gn:asciiname":"Kari Barri",
    "gn:country_code":"SY",
    "gn:dem":412,
    "gn:feature_class":"P",
    "gn:feature_code":"PPL",
    "gn:name":"Kar\u012b Barr\u012b",
    "gn:population":0,
    "gn:timezone":"Asia/Damascus",
    "iso:country":"SY",
    "name:ara_x_preferred":[
        "\u0643\u0631\u064a \u0628\u0631\u064a"
    ],
    "name:tur_x_preferred":[
        "Kar\u012b Barr\u012b"
    ],
    "wof:name":"Kari Barri",
    "wof:placetype":"locality"
},
  "geometry": {"coordinates":[41.60295,37.0033],"type":"Point"}
}