{
  "type": "Feature",
  "properties": {
    "gn:admin1_code":"10.0",
    "gn:asciiname":"Sawma`ah",
    "gn:country_code":"SY",
    "gn:dem":467,
    "gn:feature_class":"P",
    "gn:feature_code":"PPL",
    "gn:name":"\u015eawma\u2018ah",
    "gn:population":0,
    "gn:timezone":"Asia/Damascus",
    "iso:country":"SY",
    "name:ara_x_preferred":[
        "\u0635\u0648\u0645\u0639\u0629"
    ],
    "name:ara_x_variant":[
        "\u0635\u0648\u0645\u0639\u0627"
    ],
    "name:und_x_variant":[
        "Saouma\u00e2",
        "\u015eawma\u2018ah",
        "\u015eawma\u2018\u0101"
    ],
    "wof:name":"Sawma`ah",
    "wof:placetype":"locality"
},
  "geometry": {"coordinates":[36.47217,35.0495],"type":"Point"}
}