{
  "type": "Feature",
  "properties": {
    "gn:admin1_code":"14.0",
    "gn:asciiname":"Majdalun al Bahr",
    "gn:country_code":"SY",
    "gn:dem":83,
    "gn:feature_class":"P",
    "gn:feature_code":"PPL",
    "gn:name":"Majdal\u016bn al Ba\u1e29r",
    "gn:population":0,
    "gn:timezone":"Asia/Damascus",
    "iso:country":"SY",
    "name:ara_x_preferred":[
        "\u0645\u062c\u062f\u0644\u0648\u0646 \u0627\u0644\u0628\u062d\u0631"
    ],
    "name:und_x_variant":[
        "Majdel el Bahr",
        "Majdalo\u00fbn el Boust\u00e2ne",
        "Majdalo\u00fbn el Bahr",
        "Majdal\u016bn al Bust\u0101n",
        "Majdal\u016bn al Ba\u1e29r"
    ],
    "wof:name":"Majdalun al Bahr",
    "wof:placetype":"locality"
},
  "geometry": {"coordinates":[35.95581,34.82915],"type":"Point"}
}