{
  "type": "Feature",
  "properties": {
    "gn:admin1_code":"2.0",
    "gn:asciiname":"`Ayn al `Asharah",
    "gn:country_code":"SY",
    "gn:dem":431,
    "gn:feature_class":"P",
    "gn:feature_code":"PPL",
    "gn:name":"\u2018Ayn al \u2018Asharah",
    "gn:population":0,
    "gn:timezone":"Asia/Damascus",
    "iso:country":"SY",
    "name:ara_x_preferred":[
        "\u0639\u064a\u0646 \u0627\u0644\u0639\u0634\u0631\u0629"
    ],
    "name:und_x_variant":[
        "A\u00efn el Achra",
        "A\u00efn el Aachra",
        "\u2018Ayn al \u2018Asharah"
    ],
    "wof:name":"`Ayn al `Asharah",
    "wof:placetype":"locality"
},
  "geometry": {"coordinates":[36.1428,35.77624],"type":"Point"}
}