{
  "type": "Feature",
  "properties": {
    "gn:admin1_code":"11.0",
    "gn:asciiname":"Al Fitaya",
    "gn:country_code":"SY",
    "gn:dem":516,
    "gn:feature_class":"P",
    "gn:feature_code":"PPL",
    "gn:name":"Al Fit\u0101y\u0101",
    "gn:population":0,
    "gn:timezone":"Asia/Damascus",
    "iso:country":"SY",
    "name:ara_x_preferred":[
        "Lift\u0101y\u0101"
    ],
    "name:ara_x_variant":[
        "Al Fit\u0101y\u0101",
        "\u0627\u0644\u0641\u062a\u0627\u064a\u0627",
        "\u0644\u0641\u062a\u0627\u064a\u0627"
    ],
    "name:ceb_x_preferred":[
        "Al Fit\u0101y\u0101"
    ],
    "name:fas_x_preferred":[
        "\u0644\u0641\u062a\u0627\u06cc\u0627"
    ],
    "name:pol_x_preferred":[
        "Liftaja"
    ],
    "name:und_x_variant":[
        "Leftaya"
    ],
    "name:vie_x_preferred":[
        "Liftaya"
    ],
    "wof:name":"Al Fitaya",
    "wof:placetype":"locality"
},
  "geometry": {"coordinates":[36.46191,34.65635],"type":"Point"}
}