{
  "type": "Feature",
  "properties": {
    "gn:admin1_code":"10.0",
    "gn:asciiname":"Jurin",
    "gn:country_code":"SY",
    "gn:dem":591,
    "gn:feature_class":"P",
    "gn:feature_code":"PPL",
    "gn:name":"J\u016br\u012bn",
    "gn:population":0,
    "gn:timezone":"Asia/Damascus",
    "iso:country":"SY",
    "name:ara_x_preferred":[
        "J\u016br\u012bn"
    ],
    "name:ara_x_variant":[
        "\u062c\u0648\u0631\u064a\u0646",
        "\u0639\u064a\u0646 \u062c\u0648\u0631\u064a\u0646"
    ],
    "name:fas_x_preferred":[
        "\u062c\u0648\u0631\u06cc\u0646"
    ],
    "name:nep_x_preferred":[
        "\u091c\u094b\u0930\u093f\u0928"
    ],
    "name:pol_x_preferred":[
        "D\u017curin"
    ],
    "name:und_x_variant":[
        "Jo\u00fbr\u00eene",
        "\u2018Ayn J\u016br\u012bn"
    ],
    "name:vie_x_preferred":[
        "Jurin"
    ],
    "wof:name":"Jurin",
    "wof:placetype":"locality"
},
  "geometry": {"coordinates":[36.23974000000001,35.61982000000001],"type":"Point"}
}