{
  "type": "Feature",
  "properties": {
    "gn:admin1_code":"14.0",
    "gn:asciiname":"Mi`ar Shakir",
    "gn:country_code":"SY",
    "gn:dem":128,
    "gn:feature_class":"P",
    "gn:feature_code":"PPL",
    "gn:name":"M\u012b\u2018\u0101r Sh\u0101kir",
    "gn:population":0,
    "gn:timezone":"Asia/Damascus",
    "iso:country":"SY",
    "name:ara_x_preferred":[
        "\u0645\u0639\u064a\u0627\u0631 \u0627\u0644\u0645\u0634\u062f"
    ],
    "name:ara_x_variant":[
        "M\u012b\u2018\u0101r Sh\u0101kir",
        "\u0645\u064a\u0639\u0627\u0631 \u0634\u0627\u0643\u0631"
    ],
    "name:und_x_variant":[
        "M\u00eea\u00e2r el Mchadd",
        "M\u00eea\u00e2r",
        "M\u012b\u2018\u0101r al Mchadd",
        "Mi\u2018y\u0101r al Mashadd"
    ],
    "wof:name":"Mi`ar Shakir",
    "wof:placetype":"locality"
},
  "geometry": {"coordinates":[35.99983,34.79620999999999],"type":"Point"}
}