{
  "type": "Feature",
  "properties": {
    "gn:admin1_code":"1.0",
    "gn:asciiname":"Al Badi`",
    "gn:country_code":"SY",
    "gn:dem":283,
    "gn:feature_class":"P",
    "gn:feature_code":"PPL",
    "gn:name":"Al Bad\u012b\u2018",
    "gn:population":0,
    "gn:timezone":"Asia/Damascus",
    "iso:country":"SY",
    "name:ara_x_preferred":[
        "\u0627\u0644\u0628\u062f\u064a\u0639"
    ],
    "name:und_x_variant":[
        "Al Bad\u012b\u2018"
    ],
    "wof:name":"Al Badi`",
    "wof:placetype":"locality"
},
  "geometry": {"coordinates":[40.60493,35.96798],"type":"Point"}
}