{
  "type": "Feature",
  "properties": {
    "gn:admin1_code":"10.0",
    "gn:asciiname":"Rasm al Ahmar",
    "gn:country_code":"SY",
    "gn:dem":394,
    "gn:feature_class":"P",
    "gn:feature_code":"PPL",
    "gn:name":"Rasm al A\u1e29mar",
    "gn:population":0,
    "gn:timezone":"Asia/Damascus",
    "iso:country":"SY",
    "name:ara_x_preferred":[
        "\u0631\u0633\u0645 \u0627\u0644\u0623\u062d\u0645\u0631"
    ],
    "name:und_x_variant":[
        "Rasm al A\u1e29mar"
    ],
    "wof:name":"Rasm al Ahmar",
    "wof:placetype":"locality"
},
  "geometry": {"coordinates":[37.48906,35.32165999999999],"type":"Point"}
}