{
  "type": "Feature",
  "properties": {
    "gn:admin1_code":"4.0",
    "gn:asciiname":"`Abatayn",
    "gn:country_code":"SY",
    "gn:dem":355,
    "gn:feature_class":"P",
    "gn:feature_code":"PPL",
    "gn:name":"\u2018Ab\u0101tayn",
    "gn:population":0,
    "gn:timezone":"Asia/Damascus",
    "iso:country":"SY",
    "name:ara_x_preferred":[
        "\u0639\u0628\u0627\u062a\u064a\u0646"
    ],
    "name:und_x_variant":[
        "Aab\u00e2te\u00efne",
        "\u2018Ab\u0101tayn"
    ],
    "wof:name":"`Abatayn",
    "wof:placetype":"locality"
},
  "geometry": {"coordinates":[39.00989000000001,36.6633],"type":"Point"}
}