{
  "type": "Feature",
  "properties": {
    "gn:admin1_code":"11.0",
    "gn:asciiname":"Akkum",
    "gn:country_code":"SY",
    "gn:dem":1047,
    "gn:feature_class":"P",
    "gn:feature_code":"PPL",
    "gn:name":"Akk\u016bm",
    "gn:population":0,
    "gn:timezone":"Asia/Damascus",
    "iso:country":"SY",
    "name:ara_x_preferred":[
        "Akk\u016bm"
    ],
    "name:ara_x_variant":[
        "\u0623\u0643\u0648\u0645"
    ],
    "name:und_x_variant":[
        "Akam",
        "Akoum",
        "Akko\u00fbm"
    ],
    "wof:name":"Akkum",
    "wof:placetype":"locality"
},
  "geometry": {"coordinates":[36.36994,34.51851],"type":"Point"}
}