{
  "type": "Feature",
  "properties": {
    "gn:admin1_code":"2.0",
    "gn:asciiname":"Bayt Luqman",
    "gn:country_code":"SY",
    "gn:dem":196,
    "gn:feature_class":"P",
    "gn:feature_code":"PPL",
    "gn:name":"Bayt Luqm\u0101n",
    "gn:population":0,
    "gn:timezone":"Asia/Damascus",
    "iso:country":"SY",
    "name:ara_x_preferred":[
        "\u0628\u064a\u062a \u0644\u0642\u0645\u0627\u0646"
    ],
    "name:und_x_variant":[
        "Be\u00eft Loukm\u00e2ne",
        "Bayt Luqm\u0101n"
    ],
    "wof:name":"Bayt Luqman",
    "wof:placetype":"locality"
},
  "geometry": {"coordinates":[36.08167,35.80240999999999],"type":"Point"}
}