{
  "type": "Feature",
  "properties": {
    "gn:admin1_code":"4.0",
    "gn:asciiname":"Mu`ayzilah",
    "gn:country_code":"SY",
    "gn:dem":309,
    "gn:feature_class":"P",
    "gn:feature_code":"PPL",
    "gn:name":"Mu\u2018ayz\u012blah",
    "gn:population":0,
    "gn:timezone":"Asia/Damascus",
    "iso:country":"SY",
    "name:ara_x_preferred":[
        "\u0645\u0639\u064a\u0632\u064a\u0644\u0629"
    ],
    "name:und_x_variant":[
        "Ma\u2018\u012bzilah",
        "Mu\u2018ayz\u012blah"
    ],
    "wof:name":"Mu`ayzilah",
    "wof:placetype":"locality"
},
  "geometry": {"coordinates":[39.1811,36.12039],"type":"Point"}
}