{
  "type": "Feature",
  "properties": {
    "gn:admin1_code":"1.0",
    "gn:asciiname":"Shaybaniyah",
    "gn:country_code":"SY",
    "gn:dem":393,
    "gn:feature_class":"P",
    "gn:feature_code":"PPL",
    "gn:name":"Shayb\u0101n\u012byah",
    "gn:population":0,
    "gn:timezone":"Asia/Damascus",
    "iso:country":"SY",
    "name:ara_x_preferred":[
        "\u0634\u064a\u0628\u0627\u0646\u064a\u0629"
    ],
    "name:und_x_variant":[
        "Ch\u00eeb\u00e2n\u00eey\u00e9",
        "Sh\u012bb\u0101n\u012byah",
        "Shayb\u0101n\u012byah"
    ],
    "wof:name":"Shaybaniyah",
    "wof:placetype":"locality"
},
  "geometry": {"coordinates":[42.23737,37.15516],"type":"Point"}
}