{
  "type": "Feature",
  "properties": {
    "gn:admin1_code":"9.0",
    "gn:asciiname":"Umm `Amud",
    "gn:country_code":"SY",
    "gn:dem":331,
    "gn:feature_class":"P",
    "gn:feature_code":"PPL",
    "gn:name":"Umm \u2018\u0100m\u016bd",
    "gn:population":0,
    "gn:timezone":"Asia/Damascus",
    "iso:country":"SY",
    "name:ara_x_preferred":[
        "Umm \u2018\u0100m\u016bd"
    ],
    "name:ara_x_variant":[
        "\u0627\u0645 \u0639\u0627\u0645\u0648\u062f"
    ],
    "name:und_x_variant":[
        "Oum A\u00e2mo\u00fbd"
    ],
    "wof:name":"Umm `Amud",
    "wof:placetype":"locality"
},
  "geometry": {"coordinates":[37.29965,35.7876],"type":"Point"}
}