{
  "type": "Feature",
  "properties": {
    "gn:admin1_code":"9.0",
    "gn:asciiname":"Khatuniyah",
    "gn:country_code":"SY",
    "gn:dem":383,
    "gn:feature_class":"P",
    "gn:feature_code":"PPL",
    "gn:name":"Kh\u0101t\u016bn\u012byah",
    "gn:population":0,
    "gn:timezone":"Asia/Damascus",
    "iso:country":"SY",
    "name:ara_x_preferred":[
        "\u062e\u0627\u062a\u0648\u0646\u064a\u0629"
    ],
    "name:und_x_variant":[
        "Kh\u00e2to\u00fbn\u00eey\u00e9",
        "Kh\u0101t\u016bn\u012byah",
        "Kh\u0101n\u016bn\u012byah"
    ],
    "wof:name":"Khatuniyah",
    "wof:placetype":"locality"
},
  "geometry": {"coordinates":[38.35586,36.46303],"type":"Point"}
}