{
  "type": "Feature",
  "properties": {
    "gn:admin1_code":"9.0",
    "gn:asciiname":"Sidyan",
    "gn:country_code":"SY",
    "gn:dem":358,
    "gn:feature_class":"P",
    "gn:feature_code":"PPLL",
    "gn:name":"Sidy\u0101n",
    "gn:population":0,
    "gn:timezone":"Asia/Damascus",
    "iso:country":"SY",
    "name:ara_x_preferred":[
        "Sidy\u0101n"
    ],
    "name:ara_x_variant":[
        "\u0633\u062f\u064a\u0627\u0646"
    ],
    "wof:name":"Sidyan",
    "wof:placetype":"locality"
},
  "geometry": {"coordinates":[37.70022,35.7633],"type":"Point"}
}