{
  "type": "Feature",
  "properties": {
    "gn:admin1_code":"11.0",
    "gn:asciiname":"Al Husayniyah",
    "gn:country_code":"SY",
    "gn:dem":632,
    "gn:feature_class":"P",
    "gn:feature_code":"PPL",
    "gn:name":"Al \u1e28usayn\u012byah",
    "gn:population":0,
    "gn:timezone":"Asia/Damascus",
    "iso:country":"SY",
    "name:ara_x_preferred":[
        "\u0627\u0644\u062d\u0633\u064a\u0646\u064a\u0629"
    ],
    "name:und_x_variant":[
        "Husse\u00efni\u00e9",
        "Houssa\u00efn\u00eey\u00e9",
        "Al \u1e28usayn\u012byah"
    ],
    "wof:name":"Al Husayniyah",
    "wof:placetype":"locality"
},
  "geometry": {"coordinates":[36.71195,34.57001],"type":"Point"}
}