{
  "type": "Feature",
  "properties": {
    "gn:admin1_code":"12.0",
    "gn:asciiname":"Jad`ayn",
    "gn:country_code":"SY",
    "gn:dem":478,
    "gn:feature_class":"P",
    "gn:feature_code":"PPL",
    "gn:name":"Jad\u2018ayn",
    "gn:population":0,
    "gn:timezone":"Asia/Damascus",
    "iso:country":"SY",
    "name:ara_x_preferred":[
        "\u062c\u062f\u0639\u064a\u0646"
    ],
    "name:und_x_variant":[
        "Djed A\u00efn",
        "Djedde\u00efne",
        "Jeddaine",
        "Jad\u2018ayn",
        "Jada\u2018ayn"
    ],
    "wof:name":"Jad`ayn",
    "wof:placetype":"locality"
},
  "geometry": {"coordinates":[36.51148,36.14048],"type":"Point"}
}