{
  "type": "Feature",
  "properties": {
    "gn:admin1_code":"12.0",
    "gn:asciiname":"Kharab Sultan",
    "gn:country_code":"SY",
    "gn:dem":466,
    "gn:feature_class":"P",
    "gn:feature_code":"PPL",
    "gn:name":"Khar\u0101b Sul\u0163\u0101n",
    "gn:population":0,
    "gn:timezone":"Asia/Damascus",
    "iso:country":"SY",
    "name:ara_x_preferred":[
        "\u062e\u0631\u0627\u0628 \u0633\u0644\u0637\u0627\u0646"
    ],
    "name:und_x_variant":[
        "Khar\u0101b Sul\u0163\u0101n"
    ],
    "wof:name":"Kharab Sultan",
    "wof:placetype":"locality"
},
  "geometry": {"coordinates":[36.44939,36.00136],"type":"Point"}
}