{
  "type": "Feature",
  "properties": {
    "gn:admin1_code":"6.0",
    "gn:asciiname":"Bustas",
    "gn:cc2":"SY",
    "gn:country_code":"SY",
    "gn:dem":660,
    "gn:feature_class":"P",
    "gn:feature_code":"PPL",
    "gn:name":"Bust\u0101s",
    "gn:population":0,
    "gn:timezone":"Asia/Damascus",
    "iso:country":"SY",
    "name:ara_x_preferred":[
        "Bust\u0101s"
    ],
    "name:und_x_variant":[
        "Bost\u00e2s"
    ],
    "wof:name":"Bustas",
    "wof:placetype":"locality"
},
  "geometry": {"coordinates":[36.01667,32.98333],"type":"Point"}
}