{
  "type": "Feature",
  "properties": {
    "gn:admin1_code":"12.0",
    "gn:asciiname":"Ar Rami",
    "gn:country_code":"SY",
    "gn:dem":714,
    "gn:feature_class":"P",
    "gn:feature_code":"PPL",
    "gn:name":"Ar R\u0101m\u012b",
    "gn:population":0,
    "gn:timezone":"Asia/Damascus",
    "iso:country":"SY",
    "name:ara_x_preferred":[
        "Ar R\u0101m\u012b"
    ],
    "name:ara_x_variant":[
        "R\u0101m\u012b",
        "\u0631\u0627\u0645\u064a",
        "\u0627\u0644\u0631\u0627\u0645\u064a"
    ],
    "name:und_x_variant":[
        "R\u00e2mi"
    ],
    "wof:name":"Ar Rami",
    "wof:placetype":"locality"
},
  "geometry": {"coordinates":[36.56028,35.76306],"type":"Point"}
}