{
  "type": "Feature",
  "properties": {
    "gn:admin1_code":"7.0",
    "gn:asciiname":"Asalah",
    "gn:country_code":"SY",
    "gn:dem":450,
    "gn:feature_class":"P",
    "gn:feature_code":"PPL",
    "gn:name":"A\u015f\u0101lah",
    "gn:population":0,
    "gn:timezone":"Asia/Damascus",
    "iso:country":"SY",
    "name:ara_x_preferred":[
        "\u0627\u0635\u0627\u0644\u0629"
    ],
    "name:und_x_variant":[
        "A\u015f\u0101lah"
    ],
    "wof:name":"Asalah",
    "wof:placetype":"locality"
},
  "geometry": {"coordinates":[39.98402,36.18646],"type":"Point"}
}