{
  "type": "Feature",
  "properties": {
    "gn:admin1_code":"12.0",
    "gn:asciiname":"Khirbat Hannani",
    "gn:country_code":"SY",
    "gn:dem":314,
    "gn:feature_class":"P",
    "gn:feature_code":"PPL",
    "gn:name":"Khirbat \u1e28ann\u0101n\u012b",
    "gn:population":0,
    "gn:timezone":"Asia/Damascus",
    "iso:country":"SY",
    "name:ara_x_preferred":[
        "\u062e\u0631\u0628\u0629 \u062d\u0646\u0627\u0646\u064a"
    ],
    "name:und_x_variant":[
        "Kheurbet Hann\u00e2ni",
        "Khirbat \u1e28ann\u0101n\u012b"
    ],
    "wof:name":"Khirbat Hannani",
    "wof:placetype":"locality"
},
  "geometry": {"coordinates":[36.95928,35.70998],"type":"Point"}
}