{
  "type": "Feature",
  "properties": {
    "gn:admin1_code":"9.0",
    "gn:asciiname":"Tall al Jijan",
    "gn:country_code":"SY",
    "gn:dem":500,
    "gn:feature_class":"P",
    "gn:feature_code":"PPL",
    "gn:name":"Tall al J\u012bj\u0101n",
    "gn:population":0,
    "gn:timezone":"Asia/Damascus",
    "iso:country":"SY",
    "name:ara_x_preferred":[
        "\u062a\u0644 \u062c\u064a\u062c\u0627\u0646"
    ],
    "name:ara_x_variant":[
        "\u062a\u0644 \u0627\u0644\u062c\u064a\u062c\u0627\u0646"
    ],
    "name:und_x_variant":[
        "Tell Jijane",
        "Tell el Jij\u00e2ne",
        "Tell ej Jij\u00e2ne",
        "Tall al J\u012bj\u0101n",
        "Tall J\u012bj\u0101n"
    ],
    "wof:name":"Tall al Jijan",
    "wof:placetype":"locality"
},
  "geometry": {"coordinates":[37.34107,36.41081],"type":"Point"}
}