{
  "type": "Feature",
  "properties": {
    "gn:admin1_code":"9.0",
    "gn:asciiname":"Qutan",
    "gn:country_code":"SY",
    "gn:dem":680,
    "gn:feature_class":"P",
    "gn:feature_code":"PPL",
    "gn:name":"Q\u016b\u0163\u0101n",
    "gn:population":0,
    "gn:timezone":"Asia/Damascus",
    "iso:country":"SY",
    "name:ara_x_preferred":[
        "K\u016bw\u0101nl\u012b"
    ],
    "name:ara_x_variant":[
        "\u0643\u0648\u0648\u0627\u0646\u0644\u064a",
        "\u0642\u0648\u0637\u0627\u0646\u0644\u064a",
        "\u0642\u0648\u0637\u0627\u0646"
    ],
    "name:und_x_variant":[
        "Q\u016b\u0163\u0101nl\u012b",
        "Qaw\u0163\u0101nl\u012b",
        "Q\u016b\u0163\u0101n"
    ],
    "wof:name":"Qutan",
    "wof:placetype":"locality"
},
  "geometry": {"coordinates":[36.80213,36.71105],"type":"Point"}
}