{
  "type": "Feature",
  "properties": {
    "gn:admin1_code":"11.0",
    "gn:asciiname":"`Ayn ar Rahib",
    "gn:country_code":"SY",
    "gn:dem":391,
    "gn:feature_class":"P",
    "gn:feature_code":"PPL",
    "gn:name":"\u2018Ayn ar R\u0101hib",
    "gn:population":0,
    "gn:timezone":"Asia/Damascus",
    "iso:country":"SY",
    "name:ara_x_preferred":[
        "\u0639\u064a\u0646 \u0627\u0644\u0631\u0627\u0647\u0628"
    ],
    "name:und_x_variant":[
        "A\u00efn er R\u00e2heb",
        "\u2018Ayn ar R\u0101hib",
        "A\u00efn er Raheb"
    ],
    "wof:name":"`Ayn ar Rahib",
    "wof:placetype":"locality"
},
  "geometry": {"coordinates":[36.24885,34.76947],"type":"Point"}
}