{
  "type": "Feature",
  "properties": {
    "gn:admin1_code":"11.0",
    "gn:asciiname":"Tiyas",
    "gn:country_code":"SY",
    "gn:dem":569,
    "gn:feature_class":"P",
    "gn:feature_code":"PPL",
    "gn:name":"Tiy\u0101s",
    "gn:population":0,
    "gn:timezone":"Asia/Damascus",
    "iso:country":"SY",
    "name:ara_x_preferred":[
        "Tiy\u0101s"
    ],
    "name:ara_x_variant":[
        "\u062a\u064a\u0627\u0633",
        "\u0627\u0644\u062a\u064a\u0627\u0633"
    ],
    "name:fas_x_preferred":[
        "\u062a\u06cc\u0627\u0633"
    ],
    "name:nor_x_preferred":[
        "Tiyas"
    ],
    "name:pol_x_preferred":[
        "At-Tijas"
    ],
    "name:rus_x_preferred":[
        "\u0422\u0438\u044f\u0441"
    ],
    "name:ukr_x_preferred":[
        "\u0422\u0456\u0430\u0441"
    ],
    "name:und_x_variant":[
        "Ti\u00e2s"
    ],
    "name:vie_x_preferred":[
        "Tiyas"
    ],
    "wof:name":"Tiyas",
    "wof:placetype":"locality"
},
  "geometry": {"coordinates":[37.67515,34.55188],"type":"Point"}
}