{
  "type": "Feature",
  "properties": {
    "gn:admin1_code":"4.0",
    "gn:asciiname":"Aq Kuy",
    "gn:country_code":"SY",
    "gn:dem":360,
    "gn:feature_class":"P",
    "gn:feature_code":"PPL",
    "gn:name":"\u0100q K\u016by",
    "gn:population":0,
    "gn:timezone":"Asia/Damascus",
    "iso:country":"SY",
    "name:ara_x_preferred":[
        "Aq K\u016by"
    ],
    "name:ara_x_variant":[
        "\u0100q K\u016by",
        "\u0622\u0642 \u0643\u0648\u064a"
    ],
    "name:und_x_variant":[
        "Aq Keuy"
    ],
    "wof:name":"Aq Kuy",
    "wof:placetype":"locality"
},
  "geometry": {"coordinates":[38.84191,36.68116],"type":"Point"}
}