{
  "type": "Feature",
  "properties": {
    "gn:admin1_code":"0.0",
    "gn:asciiname":"Giv'at Yo'av",
    "gn:country_code":"SY",
    "gn:dem":324,
    "gn:feature_class":"P",
    "gn:feature_code":"PPL",
    "gn:name":"Giv\u2018at Yo\u2019av",
    "gn:population":0,
    "gn:timezone":"Asia/Damascus",
    "iso:country":"SY",
    "name:und_x_variant":[
        "Giv\u2018at Yo\u2019av"
    ],
    "wof:name":"Giv'at Yo'av",
    "wof:placetype":"locality"
},
  "geometry": {"coordinates":[35.68147000000001,32.79872],"type":"Point"}
}