{
  "type": "Feature",
  "properties": {
    "gn:admin1_code":"9.0",
    "gn:asciiname":"Ar Ramadiyah",
    "gn:country_code":"SY",
    "gn:dem":197,
    "gn:feature_class":"P",
    "gn:feature_code":"PPL",
    "gn:name":"Ar Ram\u0101d\u012byah",
    "gn:population":0,
    "gn:timezone":"Asia/Damascus",
    "iso:country":"SY",
    "name:ara_x_preferred":[
        "\u0631\u0645\u0627\u062f\u064a\u0629"
    ],
    "name:ara_x_variant":[
        "\u0627\u0644\u0631\u0645\u0627\u062f\u064a\u0629"
    ],
    "name:und_x_variant":[
        "Ram\u00e2d\u00eeye",
        "Ramadia",
        "Ram\u0101d\u012byah",
        "Ar Ram\u0101d\u012byah"
    ],
    "wof:name":"Ar Ramadiyah",
    "wof:placetype":"locality"
},
  "geometry": {"coordinates":[36.74613,36.40031],"type":"Point"}
}