{
  "type": "Feature",
  "properties": {
    "gn:admin1_code":"10.0",
    "gn:asciiname":"Az Zarah",
    "gn:country_code":"SY",
    "gn:dem":393,
    "gn:feature_class":"P",
    "gn:feature_code":"PPL",
    "gn:name":"Az Z\u0101rah",
    "gn:population":0,
    "gn:timezone":"Asia/Damascus",
    "iso:country":"SY",
    "name:ara_x_preferred":[
        "Z\u0101ri\u2018"
    ],
    "name:ara_x_variant":[
        "\u0627\u0644\u0632\u0627\u0631\u0629",
        "\u0632\u0631\u0639\u0629"
    ],
    "name:und_x_variant":[
        "Z\u00e2ra",
        "Z\u00e2raa",
        "Az Z\u0101rah",
        "Z\u0101ri\u2018",
        "Zar\u2018ah",
        "Zaraa"
    ],
    "wof:name":"Az Zarah",
    "wof:placetype":"locality"
},
  "geometry": {"coordinates":[36.65981,34.91994],"type":"Point"}
}