{
  "type": "Feature",
  "properties": {
    "gn:admin1_code":"1.0",
    "gn:asciiname":"Turumbah",
    "gn:country_code":"SY",
    "gn:dem":336,
    "gn:feature_class":"P",
    "gn:feature_code":"PPL",
    "gn:name":"\u0162urumbah",
    "gn:population":0,
    "gn:timezone":"Asia/Damascus",
    "iso:country":"SY",
    "name:ara_x_preferred":[
        "\u0637\u0631\u0645\u0628\u0629"
    ],
    "name:und_x_variant":[
        "\u0162urumbah"
    ],
    "wof:name":"Turumbah",
    "wof:placetype":"locality"
},
  "geometry": {"coordinates":[40.41916,36.09368],"type":"Point"}
}