{
  "type": "Feature",
  "properties": {
    "gn:admin1_code":"1.0",
    "gn:asciiname":"Kharrarah",
    "gn:country_code":"SY",
    "gn:dem":434,
    "gn:feature_class":"P",
    "gn:feature_code":"PPL",
    "gn:name":"Kharr\u0101rah",
    "gn:population":0,
    "gn:timezone":"Asia/Damascus",
    "iso:country":"SY",
    "name:ara_x_preferred":[
        "\u062e\u0631\u0627\u0631\u0629"
    ],
    "name:tur_x_preferred":[
        "Kharr\u0101rah"
    ],
    "name:und_x_variant":[
        "Kharr\u00e2ra"
    ],
    "wof:name":"Kharrarah",
    "wof:placetype":"locality"
},
  "geometry": {"coordinates":[40.69704,36.92295],"type":"Point"}
}