{
  "type": "Feature",
  "properties": {
    "gn:admin1_code":"9.0",
    "gn:asciiname":"Kawjuk Ghazi Khan",
    "gn:country_code":"SY",
    "gn:dem":475,
    "gn:feature_class":"P",
    "gn:feature_code":"PPL",
    "gn:name":"Kawj\u016bk Gh\u0101z\u012b Kh\u0101n",
    "gn:population":0,
    "gn:timezone":"Asia/Damascus",
    "iso:country":"SY",
    "name:ara_x_preferred":[
        "\u0643\u0648\u062c\u0648\u0643 \u063a\u0627\u0632\u064a \u062e\u0627\u0646"
    ],
    "name:ara_x_variant":[
        "\u0643\u0623\u0633"
    ],
    "name:kur_x_preferred":[
        "Kasikan"
    ],
    "name:kur_x_variant":[
        "\u0643\u0627\u0633\u0643\u0627\u0646"
    ],
    "name:und_x_variant":[
        "Kawj\u016bk Gh\u0101z\u012b Kh\u0101n",
        "Kaskan",
        "Kazikan",
        "Kazkan",
        "Ka\u2019is",
        "Ka\u2019es"
    ],
    "wof:name":"Kawjuk Ghazi Khan",
    "wof:placetype":"locality"
},
  "geometry": {"coordinates":[38.43091,36.88347],"type":"Point"}
}