{
  "type": "Feature",
  "properties": {
    "gn:admin1_code":"1.0",
    "gn:asciiname":"Mashraq",
    "gn:country_code":"SY",
    "gn:dem":414,
    "gn:feature_class":"P",
    "gn:feature_code":"PPL",
    "gn:name":"Mashr\u0101q",
    "gn:population":0,
    "gn:timezone":"Asia/Damascus",
    "iso:country":"SY",
    "name:ara_x_preferred":[
        "\u0645\u0634\u0631\u0627\u0642"
    ],
    "name:tur_x_preferred":[
        "Mushraq"
    ],
    "name:und_x_variant":[
        "Mouchraq",
        "Mashr\u0101q"
    ],
    "wof:name":"Mashraq",
    "wof:placetype":"locality"
},
  "geometry": {"coordinates":[40.52739,36.81893],"type":"Point"}
}