{
  "type": "Feature",
  "properties": {
    "gn:admin1_code":"11.0",
    "gn:asciiname":"Abu al Masha`ib",
    "gn:country_code":"SY",
    "gn:dem":255,
    "gn:feature_class":"P",
    "gn:feature_code":"PPL",
    "gn:name":"Ab\u016b al Mash\u0101\u2018\u012bb",
    "gn:population":0,
    "gn:timezone":"Asia/Damascus",
    "iso:country":"SY",
    "name:ara_x_preferred":[
        "Ab\u016b M\u012bkh\u0101\u2019\u012bl"
    ],
    "name:ara_x_variant":[
        "\u0623\u0628\u0648 \u0627\u0644\u0645\u0634\u0627\u0639\u064a\u0628"
    ],
    "name:und_x_variant":[
        "Boumechael",
        "Abou Mikh\u00e2yel",
        "Ab\u016b al Mash\u0101\u2018\u012bb"
    ],
    "wof:name":"Abu al Masha`ib",
    "wof:placetype":"locality"
},
  "geometry": {"coordinates":[36.18254,34.65132],"type":"Point"}
}