{
  "type": "Feature",
  "properties": {
    "gn:admin1_code":"7.0",
    "gn:asciiname":"Zu`ayr",
    "gn:country_code":"SY",
    "gn:dem":208,
    "gn:feature_class":"P",
    "gn:feature_code":"PPL",
    "gn:name":"Zu\u2018ayr",
    "gn:population":0,
    "gn:timezone":"Asia/Damascus",
    "iso:country":"SY",
    "name:ara_x_preferred":[
        "\u0632\u0639\u064a\u0631"
    ],
    "name:und_x_variant":[
        "Zu\u2018ayr"
    ],
    "wof:name":"Zu`ayr",
    "wof:placetype":"locality"
},
  "geometry": {"coordinates":[39.98897,35.47113],"type":"Point"}
}