{
  "type": "Feature",
  "properties": {
    "gn:admin1_code":"11.0",
    "gn:asciiname":"Adlin",
    "gn:country_code":"SY",
    "gn:dem":175,
    "gn:feature_class":"P",
    "gn:feature_code":"PPL",
    "gn:name":"Adl\u012bn",
    "gn:population":0,
    "gn:timezone":"Asia/Damascus",
    "iso:country":"SY",
    "name:ara_x_preferred":[
        "Adl\u012bn"
    ],
    "name:ara_x_variant":[
        "\u0627\u062f\u0644\u064a\u0646"
    ],
    "name:und_x_variant":[
        "Edl\u00eene",
        "Adl\u00eene"
    ],
    "wof:name":"Adlin",
    "wof:placetype":"locality"
},
  "geometry": {"coordinates":[36.17376,34.63513],"type":"Point"}
}