{
  "type": "Feature",
  "properties": {
    "gn:admin1_code":"1.0",
    "gn:asciiname":"Dibat Tall Ahmad",
    "gn:country_code":"SY",
    "gn:dem":368,
    "gn:feature_class":"P",
    "gn:feature_code":"PPL",
    "gn:name":"D\u012bbat Tall A\u1e29mad",
    "gn:population":0,
    "gn:timezone":"Asia/Damascus",
    "iso:country":"SY",
    "name:ara_x_preferred":[
        "\u062f\u064a\u0628\u0629 \u062a\u0644 \u0623\u062d\u0645\u062f"
    ],
    "name:tur_x_preferred":[
        "D\u012bbat Tall A\u1e29mad"
    ],
    "name:und_x_variant":[
        "Dhi\u2019bat Tall A\u1e29mad",
        "D\u00eebet Tell Ahmed"
    ],
    "wof:name":"Dibat Tall Ahmad",
    "wof:placetype":"locality"
},
  "geometry": {"coordinates":[41.35111,36.85122],"type":"Point"}
}