{
  "type": "Feature",
  "properties": {
    "gn:admin1_code":"14.0",
    "gn:asciiname":"Dakar",
    "gn:country_code":"SY",
    "gn:dem":25,
    "gn:feature_class":"P",
    "gn:feature_code":"PPL",
    "gn:name":"Dakar",
    "gn:population":0,
    "gn:timezone":"Asia/Damascus",
    "iso:country":"SY",
    "name:ara_x_preferred":[
        "\u062f\u0643\u0631"
    ],
    "wof:name":"Dakar",
    "wof:placetype":"locality"
},
  "geometry": {"coordinates":[36.08502,34.66094],"type":"Point"}
}