{
  "type": "Feature",
  "properties": {
    "gn:admin1_code":"10.0",
    "gn:asciiname":"Fan ash Shamali",
    "gn:country_code":"SY",
    "gn:dem":416,
    "gn:feature_class":"P",
    "gn:feature_code":"PPL",
    "gn:name":"F\u0101n ash Sham\u0101l\u012b",
    "gn:population":0,
    "gn:timezone":"Asia/Damascus",
    "iso:country":"SY",
    "name:ara_x_preferred":[
        "\u0641\u0627\u0646 \u0627\u0644\u0634\u0645\u0627\u0644\u064a"
    ],
    "name:und_x_variant":[
        "F\u0101n ash Shim\u0101l\u012b",
        "F\u00e2ne ech Chim\u00e2li",
        "F\u00e2ne ech Ch\u00e9m\u00e2li",
        "F\u0101n ash Sham\u0101l\u012b"
    ],
    "wof:name":"Fan ash Shamali",
    "wof:placetype":"locality"
},
  "geometry": {"coordinates":[36.91771,35.31028],"type":"Point"}
}