{
  "type": "Feature",
  "properties": {
    "gn:admin1_code":"10.0",
    "gn:asciiname":"Al Jayliyah",
    "gn:country_code":"SY",
    "gn:dem":388,
    "gn:feature_class":"P",
    "gn:feature_code":"PPL",
    "gn:name":"Al Jayl\u012byah",
    "gn:population":0,
    "gn:timezone":"Asia/Damascus",
    "iso:country":"SY",
    "name:ara_x_preferred":[
        "\u0627\u0644\u062c\u064a\u0644\u064a\u0629"
    ],
    "name:und_x_variant":[
        "Al Jayl\u012byah"
    ],
    "wof:name":"Al Jayliyah",
    "wof:placetype":"locality"
},
  "geometry": {"coordinates":[37.07883,35.33134000000001],"type":"Point"}
}