{
  "type": "Feature",
  "properties": {
    "gn:admin1_code":"9.0",
    "gn:asciiname":"Khirbat al Ghudraf",
    "gn:country_code":"SY",
    "gn:dem":364,
    "gn:feature_class":"P",
    "gn:feature_code":"PPL",
    "gn:name":"Khirbat al Ghudr\u0101f",
    "gn:population":0,
    "gn:timezone":"Asia/Damascus",
    "iso:country":"SY",
    "name:ara_x_preferred":[
        "\u062e\u0631\u0628\u0629 \u0627\u0644\u063a\u062f\u0631\u0627\u0641"
    ],
    "name:und_x_variant":[
        "Khirbat al Ghudr\u0101f"
    ],
    "wof:name":"Khirbat al Ghudraf",
    "wof:placetype":"locality"
},
  "geometry": {"coordinates":[37.94258,35.96325],"type":"Point"}
}