{
  "type": "Feature",
  "properties": {
    "gn:admin1_code":"9.0",
    "gn:asciiname":"Daliyanli",
    "gn:country_code":"SY",
    "gn:dem":524,
    "gn:feature_class":"P",
    "gn:feature_code":"PPL",
    "gn:name":"D\u0101liy\u0101nl\u012b",
    "gn:population":0,
    "gn:timezone":"Asia/Damascus",
    "iso:country":"SY",
    "name:ara_x_preferred":[
        "D\u0101liy\u0101nl\u012b"
    ],
    "name:ara_x_variant":[
        "\u062f\u0627\u0644\u064a\u0627\u0646\u0644\u064a",
        "\u0627\u0644\u062f\u0627\u0644\u064a\u0629"
    ],
    "name:und_x_variant":[
        "Ad D\u0101liyah"
    ],
    "wof:name":"Daliyanli",
    "wof:placetype":"locality"
},
  "geometry": {"coordinates":[36.66205,36.50576],"type":"Point"}
}