{
  "type": "Feature",
  "properties": {
    "gn:admin1_code":"12.0",
    "gn:asciiname":"Inkizik",
    "gn:country_code":"SY",
    "gn:dem":605,
    "gn:feature_class":"P",
    "gn:feature_code":"PPL",
    "gn:name":"Inkiz\u012bk",
    "gn:population":0,
    "gn:timezone":"Asia/Damascus",
    "iso:country":"SY",
    "name:ara_x_preferred":[
        "Inkiz\u012bk"
    ],
    "name:ara_x_variant":[
        "\u0627\u0646\u0643\u0632\u064a\u0643"
    ],
    "name:und_x_variant":[
        "Innguizik",
        "Innkz\u00eek"
    ],
    "wof:name":"Inkizik",
    "wof:placetype":"locality"
},
  "geometry": {"coordinates":[36.26172,35.81491],"type":"Point"}
}