{
  "type": "Feature",
  "properties": {
    "gn:admin1_code":"1.0",
    "gn:asciiname":"Khirbat Qadi",
    "gn:country_code":"SY",
    "gn:dem":377,
    "gn:feature_class":"P",
    "gn:feature_code":"PPL",
    "gn:name":"Khirbat Q\u0101\u1e11\u012b",
    "gn:population":0,
    "gn:timezone":"Asia/Damascus",
    "iso:country":"SY",
    "name:ara_x_preferred":[
        "\u062e\u0631\u0628\u0629 \u0642\u0627\u0636\u064a"
    ],
    "name:tur_x_preferred":[
        "Khirbat Q\u0101\u1e11\u012b"
    ],
    "name:und_x_variant":[
        "Kheurbet Q\u00e2di",
        "Khirbat al Q\u0101\u1e11\u012b"
    ],
    "wof:name":"Khirbat Qadi",
    "wof:placetype":"locality"
},
  "geometry": {"coordinates":[41.11534,36.85078],"type":"Point"}
}