{
  "type": "Feature",
  "properties": {
    "gn:admin1_code":"14.0",
    "gn:asciiname":"Ransiyah",
    "gn:country_code":"SY",
    "gn:dem":16,
    "gn:feature_class":"P",
    "gn:feature_code":"PPL",
    "gn:name":"Rans\u012byah",
    "gn:population":0,
    "gn:timezone":"Asia/Damascus",
    "iso:country":"SY",
    "name:ara_x_preferred":[
        "\u0631\u0646\u0633\u064a\u0629"
    ],
    "name:und_x_variant":[
        "Ranns\u00eey\u00e9",
        "Ar Rans\u012byah",
        "Rans\u012byah"
    ],
    "wof:name":"Ransiyah",
    "wof:placetype":"locality"
},
  "geometry": {"coordinates":[36.03835,34.64857],"type":"Point"}
}