{
  "type": "Feature",
  "properties": {
    "gn:admin1_code":"11.0",
    "gn:asciiname":"As Sa`diyah",
    "gn:country_code":"SY",
    "gn:dem":675,
    "gn:feature_class":"P",
    "gn:feature_code":"PPL",
    "gn:name":"As Sa\u2018d\u012byah",
    "gn:population":0,
    "gn:timezone":"Asia/Damascus",
    "iso:country":"SY",
    "name:ara_x_preferred":[
        "\u0627\u0644\u0633\u0639\u062f\u064a\u0629"
    ],
    "name:und_x_variant":[
        "As Sa\u2018d\u012byah"
    ],
    "wof:name":"As Sa`diyah",
    "wof:placetype":"locality"
},
  "geometry": {"coordinates":[37.13499,34.85177],"type":"Point"}
}