{
  "type": "Feature",
  "properties": {
    "gn:admin1_code":"6.0",
    "gn:asciiname":"`Adwan",
    "gn:country_code":"SY",
    "gn:dem":496,
    "gn:feature_class":"P",
    "gn:feature_code":"PPL",
    "gn:name":"\u2018Adw\u0101n",
    "gn:population":0,
    "gn:timezone":"Asia/Damascus",
    "iso:country":"SY",
    "name:ara_x_preferred":[
        "\u2018Adw\u0101n"
    ],
    "name:ara_x_variant":[
        "\u0639\u062f\u0648\u0627\u0646"
    ],
    "name:und_x_variant":[
        "Aadou\u00e2ne",
        "Adaou\u00e2ne",
        "Aadaou\u00e2ne"
    ],
    "wof:name":"`Adwan",
    "wof:placetype":"locality"
},
  "geometry": {"coordinates":[35.99505999999999,32.82119],"type":"Point"}
}