{
  "type": "Feature",
  "properties": {
    "gn:admin1_code":"11.0",
    "gn:asciiname":"Al Muzayyanah",
    "gn:country_code":"SY",
    "gn:dem":372,
    "gn:feature_class":"P",
    "gn:feature_code":"PPL",
    "gn:name":"Al Muzayyanah",
    "gn:population":0,
    "gn:timezone":"Asia/Damascus",
    "iso:country":"SY",
    "name:ara_x_preferred":[
        "\u0627\u0644\u0645\u0632\u064a\u0646\u0629"
    ],
    "name:ara_x_variant":[
        "\u0645\u0632\u064a\u0628\u0644\u0629"
    ],
    "name:und_x_variant":[
        "Mza\u00efbl\u00e9",
        "Al Muzaybilah",
        "Al Muzayyanah",
        "Muzaybilah"
    ],
    "wof:name":"Al Muzayyanah",
    "wof:placetype":"locality"
},
  "geometry": {"coordinates":[36.34053,34.77024],"type":"Point"}
}