{
  "type": "Feature",
  "properties": {
    "gn:admin1_code":"12.0",
    "gn:asciiname":"Shaykh `Abd",
    "gn:country_code":"SY",
    "gn:dem":108,
    "gn:feature_class":"P",
    "gn:feature_code":"PPL",
    "gn:name":"Shaykh \u2018Abd",
    "gn:population":0,
    "gn:timezone":"Asia/Damascus",
    "iso:country":"SY",
    "name:ara_x_preferred":[
        "\u0634\u064a\u062e \u0639\u0628\u062f"
    ],
    "name:und_x_variant":[
        "Che\u00efkh Abid",
        "Che\u00efkh Aabed",
        "Che\u00efkh Abed",
        "Ash Shaykh \u2018\u0100bid",
        "Shaykh \u2018Abd"
    ],
    "wof:name":"Shaykh `Abd",
    "wof:placetype":"locality"
},
  "geometry": {"coordinates":[36.50363,36.23007],"type":"Point"}
}