{
  "type": "Feature",
  "properties": {
    "gn:admin1_code":"4.0",
    "gn:asciiname":"Mashrafah al Fawqaniyah",
    "gn:country_code":"SY",
    "gn:dem":371,
    "gn:feature_class":"P",
    "gn:feature_code":"PPL",
    "gn:name":"Mashrafah al Fawq\u0101n\u012byah",
    "gn:population":0,
    "gn:timezone":"Asia/Damascus",
    "iso:country":"SY",
    "name:ara_x_preferred":[
        "\u0645\u0634\u0631\u0641\u0629 \u0627\u0644\u0641\u0648\u0642\u0627\u0646\u064a\u0629"
    ],
    "name:und_x_variant":[
        "M\u00e9cherfet el Faouq\u00e2n\u00eey\u00e9",
        "Mashrafat al Fawq\u0101n\u012byah",
        "Mashrafah al Fawq\u0101n\u012byah"
    ],
    "wof:name":"Mashrafah al Fawqaniyah",
    "wof:placetype":"locality"
},
  "geometry": {"coordinates":[38.76419,36.59229000000001],"type":"Point"}
}