{
  "type": "Feature",
  "properties": {
    "gn:admin1_code":"10.0",
    "gn:asciiname":"`Ali Kasun",
    "gn:country_code":"SY",
    "gn:dem":576,
    "gn:feature_class":"P",
    "gn:feature_code":"PPL",
    "gn:name":"\u2018Al\u012b K\u0101s\u016bn",
    "gn:population":0,
    "gn:timezone":"Asia/Damascus",
    "iso:country":"SY",
    "name:ara_x_preferred":[
        "\u0627\u0644\u0634\u064a\u062e \u0639\u0644\u064a \u0643\u0627\u0633\u0648\u0646"
    ],
    "name:ara_x_variant":[
        "\u0639\u0644\u064a \u0643\u0627\u0633\u0648\u0646"
    ],
    "name:und_x_variant":[
        "Sheik \u2018Ali Keyesun",
        "Che\u00efkh A\u00e4li K\u00e2sso\u00fbn",
        "Shaykh \u2018Al\u012b K\u0101s\u016bn",
        "Che\u00efkh Aali K\u00e2sso\u00fbm",
        "Ash Shaykh \u2018Al\u012b K\u0101s\u016bn",
        "\u2018Al\u012b K\u0101s\u016bn"
    ],
    "wof:name":"`Ali Kasun",
    "wof:placetype":"locality"
},
  "geometry": {"coordinates":[36.98389,35.17653],"type":"Point"}
}