{
  "type": "Feature",
  "properties": {
    "gn:admin1_code":"7.0",
    "gn:asciiname":"Hawi Khuraytah",
    "gn:country_code":"SY",
    "gn:dem":235,
    "gn:feature_class":"P",
    "gn:feature_code":"PPL",
    "gn:name":"\u1e28\u0101w\u012b Khuray\u0163ah",
    "gn:population":0,
    "gn:timezone":"Asia/Damascus",
    "iso:country":"SY",
    "name:ara_x_preferred":[
        "\u062d\u0627\u0648\u064a \u062e\u0631\u064a\u0637\u0629"
    ],
    "name:und_x_variant":[
        "\u1e28\u0101w\u012b Khuray\u0163ah"
    ],
    "wof:name":"Hawi Khuraytah",
    "wof:placetype":"locality"
},
  "geometry": {"coordinates":[39.98503,35.4534],"type":"Point"}
}