{
  "type": "Feature",
  "properties": {
    "gn:admin1_code":"1.0",
    "gn:asciiname":"Bab ar Rakha",
    "gn:country_code":"SY",
    "gn:dem":322,
    "gn:feature_class":"P",
    "gn:feature_code":"PPL",
    "gn:name":"B\u0101b ar Rakh\u0101",
    "gn:population":0,
    "gn:timezone":"Asia/Damascus",
    "iso:country":"SY",
    "name:ara_x_preferred":[
        "\u0628\u0627\u0628 \u0627\u0644\u0631\u062e\u0627"
    ],
    "name:und_x_variant":[
        "B\u0101b ar Rakh\u0101"
    ],
    "wof:name":"Bab ar Rakha",
    "wof:placetype":"locality"
},
  "geometry": {"coordinates":[40.30662,36.02132],"type":"Point"}
}