{
  "type": "Feature",
  "properties": {
    "gn:admin1_code":"10.0",
    "gn:asciiname":"Qanas",
    "gn:country_code":"SY",
    "gn:dem":529,
    "gn:feature_class":"P",
    "gn:feature_code":"PPL",
    "gn:name":"Qana\u015f",
    "gn:population":0,
    "gn:timezone":"Asia/Damascus",
    "iso:country":"SY",
    "name:ara_x_preferred":[
        "\u062c\u0646\u0633"
    ],
    "name:ara_x_variant":[
        "\u0642\u0646\u0635"
    ],
    "name:und_x_variant":[
        "Junas",
        "Qana\u015f"
    ],
    "wof:name":"Qanas",
    "wof:placetype":"locality"
},
  "geometry": {"coordinates":[36.90003,35.22624000000001],"type":"Point"}
}