{
  "type": "Feature",
  "properties": {
    "gn:admin1_code":"9.0",
    "gn:asciiname":"Bayt Mar`i al Hasan as Safrani",
    "gn:country_code":"SY",
    "gn:dem":453,
    "gn:feature_class":"P",
    "gn:feature_code":"PPL",
    "gn:name":"Bayt Mar\u2018\u012b al \u1e28asan as Safr\u0101n\u012b",
    "gn:population":0,
    "gn:timezone":"Asia/Damascus",
    "iso:country":"SY",
    "name:ara_x_preferred":[
        "\u0628\u064a\u062a \u0645\u0631\u0639\u064a \u0627\u0644\u062d\u0633\u0646 \u0627\u0644\u0633\u0641\u0631\u0627\u0646\u064a"
    ],
    "name:und_x_variant":[
        "Bayt Mar\u2018\u012b al \u1e28asan as Safr\u0101n\u012b"
    ],
    "wof:name":"Bayt Mar`i al Hasan as Safrani",
    "wof:placetype":"locality"
},
  "geometry": {"coordinates":[37.27743,36.47816],"type":"Point"}
}