{
  "type": "Feature",
  "properties": {
    "gn:admin1_code":"1.0",
    "gn:asciiname":"Al Faydah",
    "gn:country_code":"SY",
    "gn:dem":364,
    "gn:feature_class":"P",
    "gn:feature_code":"PPL",
    "gn:name":"Al Fay\u1e11ah",
    "gn:population":0,
    "gn:timezone":"Asia/Damascus",
    "iso:country":"SY",
    "name:ara_x_preferred":[
        "\u0627\u0644\u0641\u0648\u0636\u0629"
    ],
    "name:fas_x_preferred":[
        "\u0627\u0644\u0641\u0627\u06cc\u062f\u0647"
    ],
    "name:nno_x_preferred":[
        "Al Faydah"
    ],
    "name:und_x_variant":[
        "Al Fay\u1e11ah"
    ],
    "wof:name":"Al Faydah",
    "wof:placetype":"locality"
},
  "geometry": {"coordinates":[41.08656,36.23597],"type":"Point"}
}