{
  "type": "Feature",
  "properties": {
    "gn:admin1_code":"12.0",
    "gn:asciiname":"`Ayn Shib",
    "gn:country_code":"SY",
    "gn:dem":566,
    "gn:feature_class":"P",
    "gn:feature_code":"PPL",
    "gn:name":"\u2018Ayn Sh\u012bb",
    "gn:population":0,
    "gn:timezone":"Asia/Damascus",
    "iso:country":"SY",
    "name:ara_x_preferred":[
        "\u2018Ayn Sh\u012bb"
    ],
    "name:ara_x_variant":[
        "\u0639\u064a\u0646 \u0634\u064a\u0628"
    ],
    "name:und_x_variant":[
        "A\u00efn Ch\u00eeb"
    ],
    "wof:name":"`Ayn Shib",
    "wof:placetype":"locality"
},
  "geometry": {"coordinates":[36.53761,35.90507],"type":"Point"}
}