{
  "type": "Feature",
  "properties": {
    "gn:admin1_code":"9.0",
    "gn:asciiname":"Hawzan",
    "gn:country_code":"SY",
    "gn:dem":642,
    "gn:feature_class":"P",
    "gn:feature_code":"PPL",
    "gn:name":"Hawz\u0101n",
    "gn:population":0,
    "gn:timezone":"Asia/Damascus",
    "iso:country":"SY",
    "name:ara_x_preferred":[
        "Ruww\u0101d \u016ash\u0101gh\u012b"
    ],
    "name:ara_x_variant":[
        "\u0631\u0648\u0627\u062f \u0627\u0648\u0634\u0627\u063a\u064a",
        "\u0647\u0648\u0632\u0627\u0646"
    ],
    "name:und_x_variant":[
        "Hawz\u0101n"
    ],
    "wof:name":"Hawzan",
    "wof:placetype":"locality"
},
  "geometry": {"coordinates":[36.84783,36.71933],"type":"Point"}
}