{
  "type": "Feature",
  "properties": {
    "gn:admin1_code":"1.0",
    "gn:asciiname":"Qarah Hasan",
    "gn:country_code":"SY",
    "gn:dem":447,
    "gn:feature_class":"P",
    "gn:feature_code":"PPL",
    "gn:name":"Qarah \u1e28asan",
    "gn:population":0,
    "gn:timezone":"Asia/Damascus",
    "iso:country":"SY",
    "name:ara_x_preferred":[
        "\u0642\u0631\u0647 \u062d\u0633\u0646"
    ],
    "name:ceb_x_preferred":[
        "Qarah \u1e28asan"
    ],
    "name:fas_x_preferred":[
        "\u0642\u0631\u0647\u200c\u062d\u0633\u0646"
    ],
    "name:pol_x_preferred":[
        "Gharehasan"
    ],
    "name:swe_x_preferred":[
        "Qarah \u1e28asan"
    ],
    "name:tur_x_preferred":[
        "Qarah \u1e28asan"
    ],
    "name:und_x_variant":[
        "Kara Hassane",
        "Qara Hassane"
    ],
    "wof:name":"Qarah Hasan",
    "wof:placetype":"locality"
},
  "geometry": {"coordinates":[41.3383,37.07247],"type":"Point"}
}