{
  "type": "Feature",
  "properties": {
    "gn:admin1_code":"12.0",
    "gn:asciiname":"Farwan",
    "gn:country_code":"SY",
    "gn:dem":387,
    "gn:feature_class":"P",
    "gn:feature_code":"PPL",
    "gn:name":"Farw\u0101n",
    "gn:population":0,
    "gn:timezone":"Asia/Damascus",
    "iso:country":"SY",
    "name:ara_x_preferred":[
        "\u0641\u0631\u0648\u0627\u0646"
    ],
    "name:und_x_variant":[
        "Farou\u00e2ne",
        "Farw\u0101n"
    ],
    "wof:name":"Farwan",
    "wof:placetype":"locality"
},
  "geometry": {"coordinates":[36.88321,35.67746],"type":"Point"}
}