{
  "type": "Feature",
  "properties": {
    "gn:admin1_code":"14.0",
    "gn:asciiname":"Al Mastabah",
    "gn:country_code":"SY",
    "gn:dem":338,
    "gn:feature_class":"P",
    "gn:feature_code":"PPL",
    "gn:name":"Al Ma\u015f\u0163abah",
    "gn:population":0,
    "gn:timezone":"Asia/Damascus",
    "iso:country":"SY",
    "name:ara_x_preferred":[
        "\u0627\u0644\u0645\u0635\u0637\u0628\u0629"
    ],
    "name:und_x_variant":[
        "Al Ma\u015f\u0163abah"
    ],
    "wof:name":"Al Mastabah",
    "wof:placetype":"locality"
},
  "geometry": {"coordinates":[36.01821,34.8921],"type":"Point"}
}