{
  "type": "Feature",
  "properties": {
    "gn:admin1_code":"9.0",
    "gn:asciiname":"Kuljibrin",
    "gn:country_code":"SY",
    "gn:dem":493,
    "gn:feature_class":"P",
    "gn:feature_code":"PPL",
    "gn:name":"Kuljibr\u012bn",
    "gn:population":0,
    "gn:timezone":"Asia/Damascus",
    "iso:country":"SY",
    "name:ara_x_preferred":[
        "Jibr\u012bn"
    ],
    "name:ara_x_variant":[
        "\u062c\u0628\u0631\u064a\u0646",
        "Kuljibr\u012bn",
        "\u0643\u0644\u062c\u0628\u0631\u064a\u0646"
    ],
    "name:und_x_variant":[
        "K\u016bl Jibr\u012bn",
        "Cueul J\u00e9bra\u00efne",
        "Gueul J\u00e9bra\u00efne",
        "Jibr\u00eene",
        "Gul Djebre\u00efne"
    ],
    "wof:name":"Kuljibrin",
    "wof:placetype":"locality"
},
  "geometry": {"coordinates":[37.11708,36.53676],"type":"Point"}
}