{
  "type": "Feature",
  "properties": {
    "gn:country":"SY",
    "gn:fcode":"PPLA3",
    "gn:pop":21481,
    "iso:country":"SY",
    "name:ara_x_preferred":[
        "\u0627\u0644\u062f\u0631\u0628\u0627\u0633\u064a\u0629"
    ],
    "name:ara_x_variant":[
        "\u062f\u0631\u0628\u0627\u0633\u064a\u0629"
    ],
    "name:arm_x_preferred":[
        "\u0531\u056c-\u0534\u0561\u0580\u0562\u0561\u057d\u056b\u0561"
    ],
    "name:chi_x_preferred":[
        "\u4ee3\u723e\u5df4\u897f\u8036"
    ],
    "name:diq_x_preferred":[
        "El Derbesiya"
    ],
    "name:dut_x_preferred":[
        "Ad-Darbasiyah"
    ],
    "name:eng_x_preferred":[
        "Al-Darbasiyah"
    ],
    "name:fre_x_preferred":[
        "Al-Darbasiyah"
    ],
    "name:kur_x_preferred":[
        "Dirb\u00eas\u00ee"
    ],
    "name:nno_x_preferred":[
        "Al-Darbasiyah"
    ],
    "name:per_x_preferred":[
        "\u0627\u0644\u062f\u0631\u0628\u0627\u0633\u06cc\u0629"
    ],
    "name:pol_x_preferred":[
        "Ad-Dirbasijja"
    ],
    "name:tur_x_preferred":[
        "Darb\u0101s\u012byah"
    ],
    "name:unk_x_variant":[
        "Dirbassiyeh"
    ],
    "name:urd_x_preferred":[
        "\u0627\u0644\u062f\u0631\u0628\u0627\u0633\u06cc\u06c1"
    ],
    "qs:name":"Ad Darb\u0101s\u012byah",
    "qs:photos_9r":0,
    "qs:photos_sr":0,
    "qs:pop_sr":"7",
    "wof:name":"Ad Darb\u0101s\u012byah",
    "wof:placetype":"locality",
    "wof:population":21481
},
  "geometry": {"coordinates":[40.65199,37.07279],"type":"Point"}
}