{
  "type": "Feature",
  "properties": {
    "gn:country":"SY",
    "gn:fcode":"PPLA3",
    "gn:population":21481,
    "iso:country":"SY",
    "name:ara_x_preferred":[
        "\u0627\u0644\u062f\u0631\u0628\u0627\u0633\u064a\u0629"
    ],
    "name:ara_x_variant":[
        "\u062f\u0631\u0628\u0627\u0633\u064a\u0629"
    ],
    "name:arz_x_preferred":[
        "\u0627\u0644\u062f\u0631\u0628\u0627\u0633\u064a\u0647"
    ],
    "name:ast_x_preferred":[
        "Al-Darbasiyah"
    ],
    "name:ceb_x_preferred":[
        "Ad Darb\u0101s\u012byah"
    ],
    "name:deu_x_preferred":[
        "Ad-Dirbasiyya"
    ],
    "name:diq_x_preferred":[
        "El Derbesiya"
    ],
    "name:eng_x_preferred":[
        "Al-Darbasiyah"
    ],
    "name:fas_x_preferred":[
        "\u0627\u0644\u062f\u0631\u0628\u0627\u0633\u06cc\u0629"
    ],
    "name:fra_x_preferred":[
        "Al-Darbasiyah"
    ],
    "name:hrv_x_preferred":[
        "Al-Darbasiyah"
    ],
    "name:hye_x_preferred":[
        "\u0531\u056c-\u0534\u0561\u0580\u0562\u0561\u057d\u056b\u0561"
    ],
    "name:kur_x_preferred":[
        "Dirb\u00eas\u00ee"
    ],
    "name:nld_x_preferred":[
        "Ad-Darbasiyah"
    ],
    "name:nno_x_preferred":[
        "Al-Darbasiyah"
    ],
    "name:pol_x_preferred":[
        "Ad-Dirbasijja"
    ],
    "name:rus_x_preferred":[
        "\u0414\u0435\u0440\u0431\u0438\u0441\u0438\u044f"
    ],
    "name:spa_x_preferred":[
        "Al Darbasiyah"
    ],
    "name:swe_x_preferred":[
        "Ad Darb\u0101s\u012byah"
    ],
    "name:tur_x_preferred":[
        "Darb\u0101s\u012byah"
    ],
    "name:tur_x_variant":[
        "Ed-Derbesiye"
    ],
    "name:und_x_variant":[
        "Dirbassiyeh"
    ],
    "name:urd_x_preferred":[
        "\u0627\u0644\u062f\u0631\u0628\u0627\u0633\u06cc\u06c1"
    ],
    "name:vie_x_preferred":[
        "Al-Darbasiyah"
    ],
    "name:zho_x_preferred":[
        "\u4ee3\u723e\u5df4\u897f\u8036"
    ],
    "qs:name":"Ad Darb\u0101s\u012byah",
    "qs:photos_9r":0,
    "qs:photos_sr":0,
    "qs:pop_sr":"7",
    "wof:name":"Ad Darb\u0101s\u012byah",
    "wof:placetype":"locality",
    "wof:population":21481
},
  "geometry": {"coordinates":[40.65199,37.07279],"type":"Point"}
}