{
  "type": "Feature",
  "properties": {
    "gn:admin1_code":"10.0",
    "gn:asciiname":"Al Marami",
    "gn:country_code":"SY",
    "gn:dem":673,
    "gn:feature_class":"P",
    "gn:feature_code":"PPL",
    "gn:name":"Al Mar\u0101m\u012b",
    "gn:population":0,
    "gn:timezone":"Asia/Damascus",
    "iso:country":"SY",
    "name:ara_x_preferred":[
        "\u0627\u0644\u0645\u0631\u0627\u0645\u064a"
    ],
    "name:und_x_variant":[
        "El Mar\u00e2mi",
        "Al Mar\u0101m\u012b"
    ],
    "wof:name":"Al Marami",
    "wof:placetype":"locality"
},
  "geometry": {"coordinates":[37.44177,35.05553],"type":"Point"}
}