{
  "type": "Feature",
  "properties": {
    "gn:admin1_code":"11.0",
    "gn:asciiname":"Umm Jurayn al Qibli",
    "gn:country_code":"SY",
    "gn:dem":709,
    "gn:feature_class":"P",
    "gn:feature_code":"PPL",
    "gn:name":"Umm Jurayn al Qibl\u012b",
    "gn:population":0,
    "gn:timezone":"Asia/Damascus",
    "iso:country":"SY",
    "name:ara_x_preferred":[
        "\u0623\u0645 \u062c\u0631\u064a\u0646 \u0627\u0644\u0642\u0628\u0644\u064a"
    ],
    "name:ara_x_variant":[
        "\u0623\u0645 \u062c\u0631\u064a\u0646"
    ],
    "name:und_x_variant":[
        "Oum Journ",
        "Umm Jurn",
        "Umm Jurayn al Qibl\u012b",
        "Umm Jurayn"
    ],
    "wof:name":"Umm Jurayn al Qibli",
    "wof:placetype":"locality"
},
  "geometry": {"coordinates":[37.07868,34.65561],"type":"Point"}
}