{
  "type": "Feature",
  "properties": {
    "gn:admin1_code":"12.0",
    "gn:asciiname":"Qurtah",
    "gn:country_code":"SY",
    "gn:dem":349,
    "gn:feature_class":"P",
    "gn:feature_code":"PPL",
    "gn:name":"Qur\u0163ah",
    "gn:population":0,
    "gn:timezone":"Asia/Damascus",
    "iso:country":"SY",
    "name:ara_x_preferred":[
        "Qur\u0163"
    ],
    "name:ara_x_variant":[
        "\u0642\u0631\u0637",
        "\u0642\u0631\u0637\u0629"
    ],
    "name:und_x_variant":[
        "Qourte",
        "Qur\u0163ah"
    ],
    "wof:name":"Qurtah",
    "wof:placetype":"locality"
},
  "geometry": {"coordinates":[36.46979,35.7805],"type":"Point"}
}