{
  "type": "Feature",
  "properties": {
    "gn:admin1_code":"8.0",
    "gn:asciiname":"Mu`addamiyat ash Shih",
    "gn:country_code":"SY",
    "gn:dem":740,
    "gn:feature_class":"P",
    "gn:feature_code":"PPL",
    "gn:name":"Mu\u2018a\u1e11\u1e11am\u012byat ash Sh\u012b\u1e29",
    "gn:population":0,
    "gn:timezone":"Asia/Damascus",
    "iso:country":"SY",
    "name:ara_x_preferred":[
        "\u0645\u0639\u0636\u0645\u064a\u0629"
    ],
    "name:ara_x_variant":[
        "\u0645\u0639\u0636\u0645\u064a\u0629 \u0627\u0644\u0634\u064a\u062e",
        "\u0645\u0639\u0636\u0645\u064a\u0629 \u0627\u0644\u0634\u064a\u062d",
        "\u0645\u0639\u0636\u0645\u064a\u0629 \u0627\u0644\u0634\u0627\u0645"
    ],
    "name:und_x_variant":[
        "Al Mu\u2018a\u1e11\u1e11am\u012byah",
        "Ma\u2019adamiet Shih",
        "Moaddamy\u00e9",
        "Ma\u2018ddam\u012byah",
        "Mu\u2018az\u0327z\u0327am\u012byat ash Sh\u012b\u1e29",
        "Mu\u2018a\u1e11\u1e11am\u012byat ash Shaykh",
        "Mu\u2018a\u1e11\u1e11am\u012byah",
        "Mu\u2018a\u1e11\u1e11am\u012byat ash Sh\u012b\u1e29",
        "Mu\u2018a\u1e11\u1e11am\u012byat ash Sh\u0101m",
        "Moadamiyeh",
        "Modamiyeh",
        "Muadamia"
    ],
    "wof:name":"Mu`addamiyat ash Shih",
    "wof:placetype":"locality"
},
  "geometry": {"coordinates":[36.20175,33.46465999999999],"type":"Point"}
}