{
  "type": "Feature",
  "properties": {
    "gn:admin1_code":"14.0",
    "gn:asciiname":"Shindakhah",
    "gn:country_code":"SY",
    "gn:dem":779,
    "gn:feature_class":"P",
    "gn:feature_code":"PPL",
    "gn:name":"Shindakhah",
    "gn:population":0,
    "gn:timezone":"Asia/Damascus",
    "iso:country":"SY",
    "name:ara_x_preferred":[
        "\u0634\u0646\u062f\u062e\u0629"
    ],
    "name:und_x_variant":[
        "Shandakhah",
        "Chinndakha",
        "Ash Shindakhah",
        "Shindakhah"
    ],
    "wof:name":"Shindakhah",
    "wof:placetype":"locality"
},
  "geometry": {"coordinates":[36.1812,35.21745],"type":"Point"}
}