{
  "type": "Feature",
  "properties": {
    "gn:admin1_code":"9.0",
    "gn:asciiname":"Bizzah",
    "gn:country_code":"SY",
    "gn:dem":512,
    "gn:feature_class":"P",
    "gn:feature_code":"PPL",
    "gn:name":"Bizzah",
    "gn:population":0,
    "gn:timezone":"Asia/Damascus",
    "iso:country":"SY",
    "name:ara_x_preferred":[
        "\u0628\u0632\u0629"
    ],
    "name:und_x_variant":[
        "B\u00e9zz\u00e9",
        "B\u00e9z\u00e9",
        "Bizzah"
    ],
    "wof:name":"Bizzah",
    "wof:placetype":"locality"
},
  "geometry": {"coordinates":[37.78698,36.41675],"type":"Point"}
}