{
  "type": "Feature",
  "properties": {
    "gn:admin1_code":"2.0",
    "gn:asciiname":"Bayt Samandar",
    "gn:country_code":"SY",
    "gn:dem":317,
    "gn:feature_class":"P",
    "gn:feature_code":"PPL",
    "gn:name":"Bayt Samandar",
    "gn:population":0,
    "gn:timezone":"Asia/Damascus",
    "iso:country":"SY",
    "name:ara_x_preferred":[
        "\u0628\u064a\u062a \u0633\u0645\u0646\u062f\u0631"
    ],
    "wof:name":"Bayt Samandar",
    "wof:placetype":"locality"
},
  "geometry": {"coordinates":[35.98298,35.70217],"type":"Point"}
}