{
  "type": "Feature",
  "properties": {
    "gn:admin1_code":"9.0",
    "gn:asciiname":"Bulbul",
    "gn:country_code":"SY",
    "gn:dem":690,
    "gn:feature_class":"P",
    "gn:feature_code":"PPLA3",
    "gn:name":"Bulbul",
    "gn:population":0,
    "gn:timezone":"Asia/Damascus",
    "iso:country":"SY",
    "name:ara_x_preferred":[
        "\u0628\u0644\u0628\u0644"
    ],
    "name:fas_x_preferred":[
        "\u0628\u0644\u0628\u0644"
    ],
    "name:nld_x_preferred":[
        "Bulbul"
    ],
    "name:pol_x_preferred":[
        "Bulbul"
    ],
    "name:ron_x_preferred":[
        "Bulbul"
    ],
    "name:rus_x_preferred":[
        "\u0411\u044e\u043b\u044c\u0431\u044e\u043b\u044c"
    ],
    "name:tur_x_preferred":[
        "B\u00fclb\u00fcl"
    ],
    "name:vie_x_preferred":[
        "Bulbul"
    ],
    "wof:name":"Bulbul",
    "wof:placetype":"locality"
},
  "geometry": {"coordinates":[36.81969,36.76947],"type":"Point"}
}