{
  "type": "Feature",
  "properties": {
    "gn:admin1_code":"12.0",
    "gn:asciiname":"Al Maydan",
    "gn:country_code":"SY",
    "gn:dem":346,
    "gn:feature_class":"P",
    "gn:feature_code":"PPL",
    "gn:name":"Al Mayd\u0101n",
    "gn:population":0,
    "gn:timezone":"Asia/Damascus",
    "iso:country":"SY",
    "name:ara_x_preferred":[
        "\u0627\u0644\u0645\u064a\u062f\u0627\u0646"
    ],
    "name:und_x_variant":[
        "Al Mayd\u0101n"
    ],
    "wof:name":"Al Maydan",
    "wof:placetype":"locality"
},
  "geometry": {"coordinates":[36.70578,36.1366],"type":"Point"}
}