{
  "type": "Feature",
  "properties": {
    "gn:admin1_code":"14.0",
    "gn:asciiname":"Kafr Tallash",
    "gn:country_code":"SY",
    "gn:dem":398,
    "gn:feature_class":"P",
    "gn:feature_code":"PPL",
    "gn:name":"Kafr \u0162allash",
    "gn:population":0,
    "gn:timezone":"Asia/Damascus",
    "iso:country":"SY",
    "name:ara_x_preferred":[
        "\u0643\u0641\u0631 \u0637\u0644\u0634"
    ],
    "name:und_x_variant":[
        "Kafer Tallech",
        "Kafer Tellech",
        "Kafr \u0162allash"
    ],
    "wof:name":"Kafr Tallash",
    "wof:placetype":"locality"
},
  "geometry": {"coordinates":[36.11286,34.93495],"type":"Point"}
}