{
  "type": "Feature",
  "properties": {
    "gn:admin1_code":"5.0",
    "gn:admin2_code":"172409.0",
    "gn:asciiname":"Sahwat al Khidr",
    "gn:country_code":"SY",
    "gn:dem":1430,
    "gn:feature_class":"P",
    "gn:feature_code":"PPL",
    "gn:name":"Sahwat al Khi\u1e11r",
    "gn:population":0,
    "gn:timezone":"Asia/Damascus",
    "iso:country":"SY",
    "name:ara_x_preferred":[
        "\u0633\u0647\u0648\u0629 \u0627\u0644\u062e\u0636\u0631"
    ],
    "name:rus_x_preferred":[
        "\u0421\u0430\u0445\u0432\u0430\u0442-\u044d\u043b\u044c-\u0425\u0438\u0434\u0440"
    ],
    "name:und_x_variant":[
        "Sahouet el Khodor",
        "Sahwat al Khud\u016br",
        "Sahwat al Khu\u1e11r",
        "Sahwat al Khi\u1e11r"
    ],
    "wof:name":"Sahwat al Khidr",
    "wof:placetype":"locality"
},
  "geometry": {"coordinates":[36.70752,32.60104],"type":"Point"}
}