{
  "type": "Feature",
  "properties": {
    "gn:admin1_code":"6.0",
    "gn:asciiname":"Tall Karim",
    "gn:cc2":"SY",
    "gn:country_code":"SY",
    "gn:dem":726,
    "gn:feature_class":"P",
    "gn:feature_code":"PPL",
    "gn:name":"Tall Kar\u012bm",
    "gn:population":0,
    "gn:timezone":"Asia/Damascus",
    "iso:country":"SY",
    "name:und_x_variant":[
        "Tell Kar\u00eem",
        "Tall Kar\u012bm"
    ],
    "wof:name":"Tall Karim",
    "wof:placetype":"locality"
},
  "geometry": {"coordinates":[36.13333,33.16667],"type":"Point"}
}