{
  "type": "Feature",
  "properties": {
    "gn:admin1_code":"8.0",
    "gn:asciiname":"Sahnaiya",
    "gn:country_code":"SY",
    "gn:dem":705,
    "gn:feature_class":"P",
    "gn:feature_code":"PPLA3",
    "gn:name":"Sahnaiya",
    "gn:population":0,
    "gn:timezone":"Asia/Damascus",
    "iso:country":"SY",
    "name:ara_x_preferred":[
        "\u0635\u062d\u0646\u0627\u064a\u0627"
    ],
    "name:ceb_x_preferred":[
        "Sahnaiya"
    ],
    "name:epo_x_preferred":[
        "Sahnaja"
    ],
    "name:fas_x_preferred":[
        "\u0635\u062d\u0646\u0627\u06cc\u0627"
    ],
    "name:nno_x_preferred":[
        "Sahnaya"
    ],
    "name:pol_x_preferred":[
        "Sahnaja"
    ],
    "name:und_x_variant":[
        "\u015ea\u1e29n\u0101y\u0101"
    ],
    "name:urd_x_preferred":[
        "\u0633\u06c1\u0646\u0627\u06cc\u0627"
    ],
    "name:vie_x_preferred":[
        "Sahnaya"
    ],
    "wof:name":"Sahnaiya",
    "wof:placetype":"locality"
},
  "geometry": {"coordinates":[36.22552,33.42531],"type":"Point"}
}