{
  "type": "Feature",
  "properties": {
    "gn:admin1_code":"12.0",
    "gn:asciiname":"Al Jubaylah",
    "gn:country_code":"SY",
    "gn:dem":127,
    "gn:feature_class":"P",
    "gn:feature_code":"PPL",
    "gn:name":"Al Jubaylah",
    "gn:population":0,
    "gn:timezone":"Asia/Damascus",
    "iso:country":"SY",
    "name:ara_x_preferred":[
        "\u0627\u0644\u062c\u0628\u064a\u0644\u0629"
    ],
    "wof:name":"Al Jubaylah",
    "wof:placetype":"locality"
},
  "geometry": {"coordinates":[36.38512,36.16107],"type":"Point"}
}