{
  "type": "Feature",
  "properties": {
    "gn:admin1_code":"9.0",
    "gn:asciiname":"Rasm ad Damlakh",
    "gn:country_code":"SY",
    "gn:dem":271,
    "gn:feature_class":"P",
    "gn:feature_code":"PPL",
    "gn:name":"Rasm ad Damlakh",
    "gn:population":0,
    "gn:timezone":"Asia/Damascus",
    "iso:country":"SY",
    "name:ara_x_preferred":[
        "\u0631\u0633\u0645 \u0627\u0644\u062f\u0645\u0644\u062e"
    ],
    "wof:name":"Rasm ad Damlakh",
    "wof:placetype":"locality"
},
  "geometry": {"coordinates":[37.17769000000001,35.70614000000001],"type":"Point"}
}