{
  "type": "Feature",
  "properties": {
    "gn:admin1_code":"9.0",
    "gn:asciiname":"Darwish Ubasi",
    "gn:country_code":"SY",
    "gn:dem":942,
    "gn:feature_class":"P",
    "gn:feature_code":"PPL",
    "gn:name":"Darw\u012bsh \u016ab\u0101s\u012b",
    "gn:population":0,
    "gn:timezone":"Asia/Damascus",
    "iso:country":"SY",
    "name:ara_x_preferred":[
        "\u062f\u0631\u0648\u064a\u0634 \u0627\u0648\u0628\u0647 \u0633\u064a"
    ],
    "name:ara_x_variant":[
        "\u062f\u0631\u0648\u064a\u0634 \u0627\u0648\u0628\u0627\u0633\u064a",
        "\u0627\u0644\u062f\u0631\u0648\u064a\u0634\u064a\u0629"
    ],
    "name:und_x_variant":[
        "Derouiche Ovassi",
        "Darou\u00eech Ob\u00e2ssi",
        "Darw\u012bsh \u016ab\u0101s\u012b",
        "Darw\u012bsh \u016abah S\u012b",
        "Ad Darw\u012bsh\u012byah"
    ],
    "wof:name":"Darwish Ubasi",
    "wof:placetype":"locality"
},
  "geometry": {"coordinates":[36.66914000000001,36.6357],"type":"Point"}
}