{
  "type": "Feature",
  "properties": {
    "gn:admin1_code":"12.0",
    "gn:asciiname":"Bayatis",
    "gn:country_code":"SY",
    "gn:dem":342,
    "gn:feature_class":"P",
    "gn:feature_code":"PPL",
    "gn:name":"Bay\u0101\u0163is",
    "gn:population":0,
    "gn:timezone":"Asia/Damascus",
    "iso:country":"SY",
    "name:ara_x_preferred":[
        "Biy\u0101tis"
    ],
    "name:ara_x_variant":[
        "\u0628\u064a\u0627\u062a\u0633",
        "\u0628\u064a\u0627\u0637\u0633"
    ],
    "name:und_x_variant":[
        "Bi\u00e2tess",
        "Biates",
        "Bay\u0101tis",
        "Bay\u0101\u0163is"
    ],
    "wof:name":"Bayatis",
    "wof:placetype":"locality"
},
  "geometry": {"coordinates":[36.47196,36.08176],"type":"Point"}
}