{
  "type": "Feature",
  "properties": {
    "gn:admin1_code":"14.0",
    "gn:asciiname":"Harat Bayt Dayyub",
    "gn:country_code":"SY",
    "gn:dem":150,
    "gn:feature_class":"P",
    "gn:feature_code":"PPL",
    "gn:name":"\u1e28\u0101rat Bayt Dayy\u016bb",
    "gn:population":0,
    "gn:timezone":"Asia/Damascus",
    "iso:country":"SY",
    "name:ara_x_preferred":[
        "\u062d\u0627\u0631\u0629 \u0628\u064a\u062a \u062f\u064a\u0648\u0628"
    ],
    "name:und_x_variant":[
        "\u1e28\u0101rat Bayt Dayy\u016bb"
    ],
    "wof:name":"Harat Bayt Dayyub",
    "wof:placetype":"locality"
},
  "geometry": {"coordinates":[35.99165,34.87384],"type":"Point"}
}