{
  "type": "Feature",
  "properties": {
    "gn:admin1_code":"8.0",
    "gn:asciiname":"Az Za`rurah",
    "gn:country_code":"SY",
    "gn:dem":776,
    "gn:feature_class":"P",
    "gn:feature_code":"PPLL",
    "gn:name":"Az Za\u2018r\u016brah",
    "gn:population":0,
    "gn:timezone":"Asia/Damascus",
    "iso:country":"SY",
    "name:ara_x_preferred":[
        "\u0627\u0644\u0632\u0639\u0631\u0648\u0631\u0629"
    ],
    "name:und_x_variant":[
        "Az Za\u2018r\u016brah"
    ],
    "wof:name":"Az Za`rurah",
    "wof:placetype":"locality"
},
  "geometry": {"coordinates":[36.1264,33.35989],"type":"Point"}
}