{
  "type": "Feature",
  "properties": {
    "gn:admin1_code":"6.0",
    "gn:asciiname":"Qasr as Sulaytah",
    "gn:country_code":"SY",
    "gn:dem":635,
    "gn:feature_class":"P",
    "gn:feature_code":"PPL",
    "gn:name":"Qa\u015fr as Sulaytah",
    "gn:population":0,
    "gn:timezone":"Asia/Damascus",
    "iso:country":"SY",
    "name:ara_x_preferred":[
        "\u0642\u0635\u0631 \u0627\u0644\u0633\u0644\u064a\u062a\u0629"
    ],
    "name:und_x_variant":[
        "Qa\u015fr as Sulaytah"
    ],
    "wof:name":"Qasr as Sulaytah",
    "wof:placetype":"locality"
},
  "geometry": {"coordinates":[36.49115,33.15022],"type":"Point"}
}