{
  "type": "Feature",
  "properties": {
    "gn:admin1_code":"4.0",
    "gn:asciiname":"Hajj `Aqab",
    "gn:country_code":"SY",
    "gn:dem":341,
    "gn:feature_class":"P",
    "gn:feature_code":"PPL",
    "gn:name":"\u1e28\u0101jj \u2018Aqab",
    "gn:population":0,
    "gn:timezone":"Asia/Damascus",
    "iso:country":"SY",
    "name:ara_x_preferred":[
        "\u062d\u0627\u062c \u0639\u0642\u0628"
    ],
    "name:und_x_variant":[
        "\u1e28\u0101jj \u2018Aqab"
    ],
    "wof:name":"Hajj `Aqab",
    "wof:placetype":"locality"
},
  "geometry": {"coordinates":[39.31336,36.16407],"type":"Point"}
}