{
  "type": "Feature",
  "properties": {
    "gn:admin1_code":"1.0",
    "gn:asciiname":"Khaznah Jadidah",
    "gn:country_code":"SY",
    "gn:dem":390,
    "gn:feature_class":"P",
    "gn:feature_code":"PPL",
    "gn:name":"Khaznah Jad\u012bdah",
    "gn:population":0,
    "gn:timezone":"Asia/Damascus",
    "iso:country":"SY",
    "name:ara_x_preferred":[
        "\u062e\u0632\u0646\u0629 \u062c\u062f\u064a\u062f\u0629"
    ],
    "name:tur_x_preferred":[
        "Khaznah Jad\u012bdah"
    ],
    "name:und_x_variant":[
        "Khaznah al Jad\u012bdah",
        "Khazn\u00e9 Jd\u00eed\u00e9"
    ],
    "wof:name":"Khaznah Jadidah",
    "wof:placetype":"locality"
},
  "geometry": {"coordinates":[41.17361,36.92884],"type":"Point"}
}