{
  "type": "Feature",
  "properties": {
    "gn:admin1_code":"8.0",
    "gn:asciiname":"Hasan Ghanim",
    "gn:country_code":"SY",
    "gn:dem":615,
    "gn:feature_class":"P",
    "gn:feature_code":"PPLL",
    "gn:name":"\u1e28asan Ghan\u012bm",
    "gn:population":0,
    "gn:timezone":"Asia/Damascus",
    "iso:country":"SY",
    "name:ara_x_preferred":[
        "\u062d\u0633\u0646 \u063a\u0646\u064a\u0645"
    ],
    "name:und_x_variant":[
        "\u1e28asan Ghan\u012bm"
    ],
    "wof:name":"Hasan Ghanim",
    "wof:placetype":"locality"
},
  "geometry": {"coordinates":[36.57237,33.63547],"type":"Point"}
}