{
  "type": "Feature",
  "properties": {
    "gn:admin1_code":"9.0",
    "gn:asciiname":"Mubasratun",
    "gn:country_code":"SY",
    "gn:dem":448,
    "gn:feature_class":"P",
    "gn:feature_code":"PPL",
    "gn:name":"Mubasr\u0101\u0163\u016bn",
    "gn:population":0,
    "gn:timezone":"Asia/Damascus",
    "iso:country":"SY",
    "name:ara_x_preferred":[
        "\u0645\u0628\u0633\u0631\u0627\u0637\u0648\u0646"
    ],
    "name:ara_x_variant":[
        "\u0628\u0635\u0631\u0627\u062a\u0648\u0646",
        "\u0628\u0635\u0631\u0627\u0637\u0648\u0646"
    ],
    "name:und_x_variant":[
        "Basr\u00e2to\u00fbn",
        "Besratoun",
        "Bezratoum",
        "Basra\u0163\u016bn",
        "Mubasr\u0101\u0163\u016bn",
        "Ba\u015fr\u0101t\u016bn",
        "Ba\u015fr\u0101\u0163\u016bn"
    ],
    "wof:name":"Mubasratun",
    "wof:placetype":"locality"
},
  "geometry": {"coordinates":[36.9114,36.20332],"type":"Point"}
}