{
  "type": "Feature",
  "properties": {
    "gn:admin1_code":"1.0",
    "gn:asciiname":"Khuzaym",
    "gn:country_code":"SY",
    "gn:dem":272,
    "gn:feature_class":"P",
    "gn:feature_code":"PPL",
    "gn:name":"Khuzaym",
    "gn:population":0,
    "gn:timezone":"Asia/Damascus",
    "iso:country":"SY",
    "name:ara_x_preferred":[
        "\u062e\u0632\u064a\u0645"
    ],
    "wof:name":"Khuzaym",
    "wof:placetype":"locality"
},
  "geometry": {"coordinates":[40.90252,35.97618],"type":"Point"}
}