{
  "type": "Feature",
  "properties": {
    "gn:admin1_code":"6.0",
    "gn:asciiname":"Al Kuwayyah",
    "gn:country_code":"SY",
    "gn:dem":188,
    "gn:feature_class":"P",
    "gn:feature_code":"PPL",
    "gn:name":"Al Kuwayyah",
    "gn:population":0,
    "gn:timezone":"Asia/Damascus",
    "iso:country":"SY",
    "name:ara_x_preferred":[
        "\u0627\u0644\u0643\u0648\u064a\u0629"
    ],
    "name:ara_x_variant":[
        "\u0643\u0648\u064a\u0627"
    ],
    "name:und_x_variant":[
        "El Kouaiye",
        "Al Kuwayyah",
        "Kuwayy\u0101",
        "Koya"
    ],
    "wof:name":"Al Kuwayyah",
    "wof:placetype":"locality"
},
  "geometry": {"coordinates":[35.81119,32.74616],"type":"Point"}
}