{
  "type": "Feature",
  "properties": {
    "gn:admin1_code":"11.0",
    "gn:asciiname":"Kawm az Zahrawi",
    "gn:country_code":"SY",
    "gn:dem":517,
    "gn:feature_class":"P",
    "gn:feature_code":"PPLL",
    "gn:name":"Kawm az Zahr\u0101w\u012b",
    "gn:population":0,
    "gn:timezone":"Asia/Damascus",
    "iso:country":"SY",
    "name:ara_x_preferred":[
        "\u0643\u0648\u0645 \u0627\u0644\u0632\u0647\u0631\u0627\u0648\u064a"
    ],
    "name:und_x_variant":[
        "Kawm az Zahr\u0101w\u012b"
    ],
    "wof:name":"Kawm az Zahrawi",
    "wof:placetype":"locality"
},
  "geometry": {"coordinates":[36.73781,34.73911],"type":"Point"}
}