{
  "type": "Feature",
  "properties": {
    "gn:admin1_code":"9.0",
    "gn:asciiname":"Milqafah",
    "gn:country_code":"SY",
    "gn:dem":333,
    "gn:feature_class":"P",
    "gn:feature_code":"PPL",
    "gn:name":"Milq\u0101fah",
    "gn:population":0,
    "gn:timezone":"Asia/Damascus",
    "iso:country":"SY",
    "name:ara_x_preferred":[
        "\u0645\u0644\u0642\u0627\u0641\u0629"
    ],
    "name:und_x_variant":[
        "Ou\u00e2di el Malq\u00e2f\u00e9",
        "Ou\u00e2di Milqaf",
        "W\u0101d\u012b al Malq\u0101fah",
        "Milq\u0101fah",
        "Malq\u0101fah"
    ],
    "wof:name":"Milqafah",
    "wof:placetype":"locality"
},
  "geometry": {"coordinates":[38.03258,36.18447000000001],"type":"Point"}
}