{
  "type": "Feature",
  "properties": {
    "gn:admin1_code":"9.0",
    "gn:asciiname":"Ad Dana",
    "gn:country_code":"SY",
    "gn:dem":489,
    "gn:feature_class":"P",
    "gn:feature_code":"PPL",
    "gn:name":"Ad D\u0101n\u0101",
    "gn:population":0,
    "gn:timezone":"Asia/Damascus",
    "iso:country":"SY",
    "name:ara_x_preferred":[
        "D\u0101n\u0101"
    ],
    "name:ara_x_variant":[
        "\u062f\u0627\u0646\u0627",
        "\u0627\u0644\u062f\u0627\u0646\u0627"
    ],
    "name:und_x_variant":[
        "D\u0101nah",
        "Ad D\u0101n\u0101"
    ],
    "wof:name":"Ad Dana",
    "wof:placetype":"locality"
},
  "geometry": {"coordinates":[37.4662,36.39727],"type":"Point"}
}