{
  "type": "Feature",
  "properties": {
    "gn:admin1_code":"11.0",
    "gn:asciiname":"Utan",
    "gn:country_code":"SY",
    "gn:dem":791,
    "gn:feature_class":"P",
    "gn:feature_code":"PPL",
    "gn:name":"\u016at\u0101n",
    "gn:population":0,
    "gn:timezone":"Asia/Damascus",
    "iso:country":"SY",
    "name:ara_x_preferred":[
        "\u016at\u0101n"
    ],
    "name:ara_x_variant":[
        "\u0627\u0648\u062a\u0627\u0646",
        "\u0623\u0648\u062a\u0627\u0646"
    ],
    "name:fas_x_preferred":[
        "\u0627\u0648\u062a\u0627\u0646"
    ],
    "name:pol_x_preferred":[
        "Utan"
    ],
    "name:und_x_variant":[
        "Out\u00e2ne"
    ],
    "name:vie_x_preferred":[
        "Autan"
    ],
    "wof:name":"Utan",
    "wof:placetype":"locality"
},
  "geometry": {"coordinates":[36.42142,34.81892],"type":"Point"}
}