{
  "type": "Feature",
  "properties": {
    "gn:admin1_code":"14.0",
    "gn:asciiname":"Khirbat Abu Hamdan",
    "gn:country_code":"SY",
    "gn:dem":233,
    "gn:feature_class":"P",
    "gn:feature_code":"PPL",
    "gn:name":"Khirbat Ab\u016b \u1e28amd\u0101n",
    "gn:population":0,
    "gn:timezone":"Asia/Damascus",
    "iso:country":"SY",
    "name:ara_x_preferred":[
        "\u062e\u0631\u0628\u0629 \u0623\u0628\u0648 \u062d\u0645\u062f\u0627\u0646"
    ],
    "name:und_x_variant":[
        "Khirbat Ab\u016b \u1e28amd\u0101n"
    ],
    "wof:name":"Khirbat Abu Hamdan",
    "wof:placetype":"locality"
},
  "geometry": {"coordinates":[36.09275,34.78903],"type":"Point"}
}