{
  "type": "Feature",
  "properties": {
    "gn:admin1_code":"9.0",
    "gn:asciiname":"Ar Rubayl",
    "gn:cc2":"SY",
    "gn:country_code":"SY",
    "gn:dem":296,
    "gn:feature_class":"P",
    "gn:feature_code":"PPL",
    "gn:name":"Ar Rubayl",
    "gn:population":0,
    "gn:timezone":"Asia/Damascus",
    "iso:country":"SY",
    "name:und_x_variant":[
        "Al Rbeil",
        "Ar Rubayl"
    ],
    "wof:name":"Ar Rubayl",
    "wof:placetype":"locality"
},
  "geometry": {"coordinates":[37.46667,35.71667],"type":"Point"}
}