{
  "type": "Feature",
  "properties": {
    "gn:admin1_code":"10.0",
    "gn:asciiname":"Jadwa`iyah Qibliyah",
    "gn:country_code":"SY",
    "gn:dem":285,
    "gn:feature_class":"P",
    "gn:feature_code":"PPL",
    "gn:name":"Jadwa\u2018\u012byah Qibl\u012byah",
    "gn:population":0,
    "gn:timezone":"Asia/Damascus",
    "iso:country":"SY",
    "name:ara_x_preferred":[
        "\u062c\u062f\u0648\u0639\u064a\u0629 \u0642\u0628\u0644\u064a\u0629"
    ],
    "name:und_x_variant":[
        "Jadwa\u2018\u012byah Qibl\u012byah"
    ],
    "wof:name":"Jadwa`iyah Qibliyah",
    "wof:placetype":"locality"
},
  "geometry": {"coordinates":[37.23336,35.54644000000001],"type":"Point"}
}