{
  "type": "Feature",
  "properties": {
    "gn:admin1_code":"2.0",
    "gn:asciiname":"Kibarah",
    "gn:country_code":"SY",
    "gn:dem":601,
    "gn:feature_class":"P",
    "gn:feature_code":"PPL",
    "gn:name":"Kib\u0101rah",
    "gn:population":0,
    "gn:timezone":"Asia/Damascus",
    "iso:country":"SY",
    "name:ara_x_preferred":[
        "\u0643\u0628\u0627\u0631\u0629"
    ],
    "name:und_x_variant":[
        "Kib\u0101rah",
        "Geubara"
    ],
    "wof:name":"Kibarah",
    "wof:placetype":"locality"
},
  "geometry": {"coordinates":[36.03945,35.79599],"type":"Point"}
}