{
  "type": "Feature",
  "properties": {
    "gn:admin1_code":"10.0",
    "gn:asciiname":"Huways ash Shamali",
    "gn:country_code":"SY",
    "gn:dem":351,
    "gn:feature_class":"P",
    "gn:feature_code":"PPL",
    "gn:name":"\u1e28uways ash Sham\u0101l\u012b",
    "gn:population":0,
    "gn:timezone":"Asia/Damascus",
    "iso:country":"SY",
    "name:ara_x_preferred":[
        "\u062d\u0648\u064a\u0633 \u0627\u0644\u0634\u0645\u0627\u0644\u064a"
    ],
    "name:und_x_variant":[
        "Houa\u00efss\u00e9 el Faouq\u00e2ni",
        "\u1e28uway\u015fah al Fawq\u0101n\u012b",
        "\u1e28uways ash Sham\u0101l\u012b"
    ],
    "wof:name":"Huways ash Shamali",
    "wof:placetype":"locality"
},
  "geometry": {"coordinates":[37.12471,35.42652000000001],"type":"Point"}
}