{
  "type": "Feature",
  "properties": {
    "gn:admin1_code":"9.0",
    "gn:asciiname":"Kafr Ta`al",
    "gn:country_code":"SY",
    "gn:dem":407,
    "gn:feature_class":"P",
    "gn:feature_code":"PPL",
    "gn:name":"Kafr Ta\u2018\u0101l",
    "gn:population":0,
    "gn:timezone":"Asia/Damascus",
    "iso:country":"SY",
    "name:ara_x_preferred":[
        "\u0643\u0641\u0631 \u062a\u0639\u0644\u0629"
    ],
    "name:ara_x_variant":[
        "\u0643\u0641\u0631 \u062a\u0639\u0627\u0644"
    ],
    "name:und_x_variant":[
        "Kafer Taal",
        "Kafer Taal\u00e9",
        "Kafr Taal\u00e9",
        "Kafr Ta\u2018lah",
        "Kafr Ta\u2018\u0101l"
    ],
    "wof:name":"Kafr Ta`al",
    "wof:placetype":"locality"
},
  "geometry": {"coordinates":[36.89346,36.15423],"type":"Point"}
}