{
  "type": "Feature",
  "properties": {
    "gn:admin1_code":"14.0",
    "gn:asciiname":"Al Huwayliyat",
    "gn:country_code":"SY",
    "gn:dem":51,
    "gn:feature_class":"P",
    "gn:feature_code":"PPL",
    "gn:name":"Al Huwayl\u012by\u0101t",
    "gn:population":0,
    "gn:timezone":"Asia/Damascus",
    "iso:country":"SY",
    "name:ara_x_preferred":[
        "\u0627\u0644\u0647\u0648\u064a\u0644\u064a\u0627\u062a"
    ],
    "name:und_x_variant":[
        "Al Huwayl\u012by\u0101t"
    ],
    "wof:name":"Al Huwayliyat",
    "wof:placetype":"locality"
},
  "geometry": {"coordinates":[35.91361,34.94905],"type":"Point"}
}