{
  "type": "Feature",
  "properties": {
    "gn:admin1_code":"7.0",
    "gn:asciiname":"Marba`iyah",
    "gn:country_code":"SY",
    "gn:dem":202,
    "gn:feature_class":"P",
    "gn:feature_code":"PPL",
    "gn:name":"Marba\u2018\u012byah",
    "gn:population":0,
    "gn:timezone":"Asia/Damascus",
    "iso:country":"SY",
    "name:ara_x_preferred":[
        "\u0645\u0631\u0628\u0639\u064a\u0629"
    ],
    "name:und_x_variant":[
        "Marba\u2018\u012byah",
        "Murabba\u2018\u012byah"
    ],
    "wof:name":"Marba`iyah",
    "wof:placetype":"locality"
},
  "geometry": {"coordinates":[40.20952,35.29954],"type":"Point"}
}