{
  "type": "Feature",
  "properties": {
    "gn:admin1_code":"7.0",
    "gn:asciiname":"Tashshah",
    "gn:country_code":"SY",
    "gn:dem":706,
    "gn:feature_class":"P",
    "gn:feature_code":"PPL",
    "gn:name":"\u0162ashshah",
    "gn:population":0,
    "gn:timezone":"Asia/Damascus",
    "iso:country":"SY",
    "name:ara_x_preferred":[
        "\u0637\u0634\u0629"
    ],
    "name:und_x_variant":[
        "\u0162ashshah"
    ],
    "wof:name":"Tashshah",
    "wof:placetype":"locality"
},
  "geometry": {"coordinates":[39.31418,35.29316],"type":"Point"}
}