{
  "type": "Feature",
  "properties": {
    "gn:admin1_code":"12.0",
    "gn:asciiname":"Tall Maraq",
    "gn:country_code":"SY",
    "gn:dem":365,
    "gn:feature_class":"P",
    "gn:feature_code":"PPL",
    "gn:name":"Tall Maraq",
    "gn:population":0,
    "gn:timezone":"Asia/Damascus",
    "iso:country":"SY",
    "name:ara_x_preferred":[
        "\u062a\u0644 \u0645\u0631\u0642"
    ],
    "name:und_x_variant":[
        "Tell Maraq",
        "Tall Maraq"
    ],
    "wof:name":"Tall Maraq",
    "wof:placetype":"locality"
},
  "geometry": {"coordinates":[36.84407,35.44141],"type":"Point"}
}