{
  "type": "Feature",
  "properties": {
    "gn:admin1_code":"1.0",
    "gn:asciiname":"Na`matli",
    "gn:country_code":"SY",
    "gn:dem":425,
    "gn:feature_class":"P",
    "gn:feature_code":"PPL",
    "gn:name":"Na\u2018matl\u012b",
    "gn:population":0,
    "gn:timezone":"Asia/Damascus",
    "iso:country":"SY",
    "name:ara_x_preferred":[
        "\u0646\u0639\u0645\u062a\u0644\u064a"
    ],
    "name:tur_x_preferred":[
        "Na\u2018matl\u012b"
    ],
    "name:und_x_variant":[
        "Naamatle",
        "Naamatli"
    ],
    "wof:name":"Na`matli",
    "wof:placetype":"locality"
},
  "geometry": {"coordinates":[41.32100000000001,37.05014],"type":"Point"}
}