{
  "type": "Feature",
  "properties": {
    "gn:admin1_code":"9.0",
    "gn:asciiname":"Za`rah",
    "gn:country_code":"SY",
    "gn:dem":889,
    "gn:feature_class":"P",
    "gn:feature_code":"PPL",
    "gn:name":"Za\u2018rah",
    "gn:population":0,
    "gn:timezone":"Asia/Damascus",
    "iso:country":"SY",
    "name:ara_x_preferred":[
        "\u0632\u0647\u0631\u0627\u0646"
    ],
    "name:ara_x_variant":[
        "\u0632\u0639\u0631\u0629"
    ],
    "name:und_x_variant":[
        "Zahr\u0101n",
        "Za\u2018rah"
    ],
    "wof:name":"Za`rah",
    "wof:placetype":"locality"
},
  "geometry": {"coordinates":[36.80286,36.78531],"type":"Point"}
}