{
  "type": "Feature",
  "properties": {
    "gn:admin1_code":"1.0",
    "gn:asciiname":"Karbala'",
    "gn:country_code":"SY",
    "gn:dem":404,
    "gn:feature_class":"P",
    "gn:feature_code":"PPL",
    "gn:name":"Karbal\u0101\u2019",
    "gn:population":0,
    "gn:timezone":"Asia/Damascus",
    "iso:country":"SY",
    "name:ara_x_preferred":[
        "\u0643\u0631\u0628\u0644\u0627\u0621"
    ],
    "name:kur_x_preferred":[
        "Pil\u00easy\u00ea"
    ],
    "name:kur_x_variant":[
        "\u067e\u0644\u06ce\u0633\u064a\u06ce"
    ],
    "name:und_x_variant":[
        "Karbal\u0101\u2019",
        "Pil\u00easiy\u00ea",
        "\u0628\u0644\u064a\u0633\u0629",
        "Bilaysah"
    ],
    "wof:name":"Karbala'",
    "wof:placetype":"locality"
},
  "geometry": {"coordinates":[42.31434,37.12094],"type":"Point"}
}