{
  "type": "Feature",
  "properties": {
    "gn:admin1_code":"1.0",
    "gn:asciiname":"Majlub",
    "gn:country_code":"SY",
    "gn:dem":263,
    "gn:feature_class":"P",
    "gn:feature_code":"PPL",
    "gn:name":"Majl\u016bb",
    "gn:population":0,
    "gn:timezone":"Asia/Damascus",
    "iso:country":"SY",
    "name:ara_x_preferred":[
        "\u0645\u062c\u0644\u0648\u0628"
    ],
    "name:und_x_variant":[
        "Majl\u016bb"
    ],
    "wof:name":"Majlub",
    "wof:placetype":"locality"
},
  "geometry": {"coordinates":[40.78821,36.01883],"type":"Point"}
}