{
  "type": "Feature",
  "properties": {
    "gn:admin1_code":"7.0",
    "gn:asciiname":"Shumaytah",
    "gn:country_code":"SY",
    "gn:dem":234,
    "gn:feature_class":"P",
    "gn:feature_code":"PPL",
    "gn:name":"Shumaytah",
    "gn:population":0,
    "gn:timezone":"Asia/Damascus",
    "iso:country":"SY",
    "name:ara_x_preferred":[
        "\u0634\u0645\u064a\u062a\u0629"
    ],
    "name:und_x_variant":[
        "Chma\u00eft\u00eey\u00e9",
        "Shumay\u0163\u012byah",
        "Shumaytah",
        "Mashmay\u0163\u012byah Fay\u1e11\u0101t",
        "Chma\u00eftiy\u00e9",
        "Chm\u00e9teiy\u00e9"
    ],
    "wof:name":"Shumaytah",
    "wof:placetype":"locality"
},
  "geometry": {"coordinates":[39.93722,35.47033],"type":"Point"}
}