{
  "type": "Feature",
  "properties": {
    "gn:admin1_code":"12.0",
    "gn:asciiname":"Umm ar Rajim",
    "gn:country_code":"SY",
    "gn:dem":471,
    "gn:feature_class":"P",
    "gn:feature_code":"PPL",
    "gn:name":"Umm ar Raj\u012bm",
    "gn:population":0,
    "gn:timezone":"Asia/Damascus",
    "iso:country":"SY",
    "name:ara_x_preferred":[
        "\u0623\u0645 \u0627\u0644\u0631\u062c\u064a\u0645"
    ],
    "name:und_x_variant":[
        "Oum er Rj\u00eem",
        "Umm ar Rujm",
        "Oumm er Rj\u00eem",
        "Umm ar Raj\u012bm"
    ],
    "wof:name":"Umm ar Rajim",
    "wof:placetype":"locality"
},
  "geometry": {"coordinates":[36.94715,35.5509],"type":"Point"}
}