{
  "type": "Feature",
  "properties": {
    "gn:admin1_code":"2.0",
    "gn:asciiname":"Bayt Ablaq",
    "gn:country_code":"SY",
    "gn:dem":478,
    "gn:feature_class":"P",
    "gn:feature_code":"PPL",
    "gn:name":"Bayt Ablaq",
    "gn:population":0,
    "gn:timezone":"Asia/Damascus",
    "iso:country":"SY",
    "name:ara_x_preferred":[
        "\u064a\u064a\u062a \u0627\u0628\u0644\u0642"
    ],
    "name:und_x_variant":[
        "Be\u00eft Ablaq",
        "Bayt Ablaq"
    ],
    "wof:name":"Bayt Ablaq",
    "wof:placetype":"locality"
},
  "geometry": {"coordinates":[36.02251,35.80272],"type":"Point"}
}