{
  "type": "Feature",
  "properties": {
    "gn:admin1_code":"3.0",
    "gn:asciiname":"Al Munaytihat",
    "gn:country_code":"SY",
    "gn:dem":836,
    "gn:feature_class":"P",
    "gn:feature_code":"PPL",
    "gn:name":"Al Munay\u0163i\u1e29\u0101t",
    "gn:population":0,
    "gn:timezone":"Asia/Damascus",
    "iso:country":"SY",
    "name:ara_x_preferred":[
        "\u0645\u0646\u0627\u0637\u062d\u0627\u062a"
    ],
    "name:ara_x_variant":[
        "\u0627\u0644\u0645\u0646\u064a\u0637\u062d\u0627\u062a"
    ],
    "name:und_x_variant":[
        "Man\u0101\u0163i\u1e29\u0101t",
        "Al Munay\u0163i\u1e29\u0101t",
        "Mun\u0101\u0163a\u1e29\u0101t"
    ],
    "wof:name":"Al Munaytihat",
    "wof:placetype":"locality"
},
  "geometry": {"coordinates":[35.93704,33.08589],"type":"Point"}
}