{
  "type": "Feature",
  "properties": {
    "gn:admin1_code":"12.0",
    "gn:asciiname":"Al Qudayriyat",
    "gn:country_code":"SY",
    "gn:dem":389,
    "gn:feature_class":"P",
    "gn:feature_code":"PPL",
    "gn:name":"Al Qudayr\u012by\u0101t",
    "gn:population":0,
    "gn:timezone":"Asia/Damascus",
    "iso:country":"SY",
    "name:ara_x_preferred":[
        "\u0627\u0644\u0642\u062f\u064a\u0631\u064a\u0627\u062a"
    ],
    "name:und_x_variant":[
        "Al Qudayr\u012by\u0101t"
    ],
    "wof:name":"Al Qudayriyat",
    "wof:placetype":"locality"
},
  "geometry": {"coordinates":[36.77183,36.20344],"type":"Point"}
}