{
  "type": "Feature",
  "properties": {
    "gn:admin1_code":"1.0",
    "gn:asciiname":"Subayh",
    "gn:country_code":"SY",
    "gn:dem":248,
    "gn:feature_class":"P",
    "gn:feature_code":"PPL",
    "gn:name":"\u015eubay\u1e29",
    "gn:population":0,
    "gn:timezone":"Asia/Damascus",
    "iso:country":"SY",
    "name:ara_x_preferred":[
        "\u0635\u0628\u064a\u062d"
    ],
    "name:und_x_variant":[
        "\u015eubay\u1e29",
        "\u015eab\u012b\u1e29"
    ],
    "wof:name":"Subayh",
    "wof:placetype":"locality"
},
  "geometry": {"coordinates":[40.88242,35.78546],"type":"Point"}
}