{
  "type": "Feature",
  "properties": {
    "gn:admin1_code":"9.0",
    "gn:asciiname":"Kurtuk",
    "gn:country_code":"SY",
    "gn:dem":390,
    "gn:feature_class":"P",
    "gn:feature_code":"PPL",
    "gn:name":"K\u016brtuk",
    "gn:population":0,
    "gn:timezone":"Asia/Damascus",
    "iso:country":"SY",
    "name:ara_x_preferred":[
        "K\u016brtuk"
    ],
    "name:ara_x_variant":[
        "\u0643\u0648\u0631\u062a\u0643"
    ],
    "name:und_x_variant":[
        "Guerrik",
        "Gue\u00fbrtik",
        "Kirtik",
        "K\u016brtik"
    ],
    "wof:name":"Kurtuk",
    "wof:placetype":"locality"
},
  "geometry": {"coordinates":[38.66494,36.58284],"type":"Point"}
}