{
  "type": "Feature",
  "properties": {
    "gn:admin1_code":"1.0",
    "gn:asciiname":"Tall Dabash",
    "gn:country_code":"SY",
    "gn:dem":422,
    "gn:feature_class":"P",
    "gn:feature_code":"PPL",
    "gn:name":"Tall D\u0101bash",
    "gn:population":0,
    "gn:timezone":"Asia/Damascus",
    "iso:country":"SY",
    "name:ara_x_preferred":[
        "\u062a\u0644 \u062f\u0627\u0628\u0634"
    ],
    "name:tur_x_preferred":[
        "Tall Dabash"
    ],
    "name:und_x_variant":[
        "Tell D\u00e2bech",
        "Tall D\u0101bash"
    ],
    "wof:name":"Tall Dabash",
    "wof:placetype":"locality"
},
  "geometry": {"coordinates":[40.4629,36.9365],"type":"Point"}
}