{
  "type": "Feature",
  "properties": {
    "gn:admin1_code":"4.0",
    "gn:asciiname":"Kul Kilinjah",
    "gn:country_code":"SY",
    "gn:dem":392,
    "gn:feature_class":"P",
    "gn:feature_code":"PPL",
    "gn:name":"Kul Kilinjah",
    "gn:population":0,
    "gn:timezone":"Asia/Damascus",
    "iso:country":"SY",
    "name:ara_x_preferred":[
        "\u0643\u0644 \u0643\u0644\u0646\u062c\u0629"
    ],
    "name:und_x_variant":[
        "Gul Kilindja",
        "K\u016bl\u016bn",
        "Gul Kilinndja",
        "K\u012bl K\u012blindijah",
        "Koloung",
        "K\u012bl Kilinjah",
        "Kul Kilinjah"
    ],
    "wof:name":"Kul Kilinjah",
    "wof:placetype":"locality"
},
  "geometry": {"coordinates":[38.70144000000001,36.5381],"type":"Point"}
}