{
  "type": "Feature",
  "properties": {
    "gn:admin1_code":"4.0",
    "gn:asciiname":"West Jabar",
    "gn:country_code":"SY",
    "gn:dem":352,
    "gn:feature_class":"P",
    "gn:feature_code":"PPL",
    "gn:name":"West Jabar",
    "gn:population":0,
    "gn:timezone":"Asia/Damascus",
    "iso:country":"SY",
    "wof:name":"West Jabar",
    "wof:placetype":"locality"
},
  "geometry": {"coordinates":[38.49481,35.92825999999999],"type":"Point"}
}