{
  "type": "Feature",
  "properties": {
    "gn:admin1_code":"1.0",
    "gn:asciiname":"Tarzi",
    "gn:country_code":"SY",
    "gn:dem":398,
    "gn:feature_class":"P",
    "gn:feature_code":"PPL",
    "gn:name":"\u0162arz\u012b",
    "gn:population":0,
    "gn:timezone":"Asia/Damascus",
    "iso:country":"SY",
    "name:ara_x_preferred":[
        "\u0637\u0631\u0632\u064a"
    ],
    "name:tur_x_preferred":[
        "Tarz\u012b"
    ],
    "name:und_x_variant":[
        "\u0162arz\u012b"
    ],
    "wof:name":"Tarzi",
    "wof:placetype":"locality"
},
  "geometry": {"coordinates":[40.80202,36.91922],"type":"Point"}
}