{
  "type": "Feature",
  "properties": {
    "gn:admin1_code":"4.0",
    "gn:asciiname":"Jadla'",
    "gn:country_code":"SY",
    "gn:dem":345,
    "gn:feature_class":"P",
    "gn:feature_code":"PPL",
    "gn:name":"Jadl\u0101\u2019",
    "gn:population":0,
    "gn:timezone":"Asia/Damascus",
    "iso:country":"SY",
    "name:ara_x_preferred":[
        "\u062c\u062f\u0644\u0627"
    ],
    "name:und_x_variant":[
        "Jadl\u0101\u2019"
    ],
    "wof:name":"Jadla'",
    "wof:placetype":"locality"
},
  "geometry": {"coordinates":[38.94703,36.65715],"type":"Point"}
}