{
  "type": "Feature",
  "properties": {
    "gn:admin1_code":"10.0",
    "gn:asciiname":"Luwaybidah",
    "gn:country_code":"SY",
    "gn:dem":760,
    "gn:feature_class":"P",
    "gn:feature_code":"PPL",
    "gn:name":"Luwaybidah",
    "gn:population":0,
    "gn:timezone":"Asia/Damascus",
    "iso:country":"SY",
    "name:ara_x_preferred":[
        "\u0644\u0648\u064a\u0628\u062f\u0629"
    ],
    "wof:name":"Luwaybidah",
    "wof:placetype":"locality"
},
  "geometry": {"coordinates":[37.55031,34.98688],"type":"Point"}
}