{
  "type": "Feature",
  "properties": {
    "gn:admin1_code":"9.0",
    "gn:asciiname":"Ash Shaykh `Ali",
    "gn:country_code":"SY",
    "gn:dem":336,
    "gn:feature_class":"P",
    "gn:feature_code":"PPL",
    "gn:name":"Ash Shaykh \u2018Al\u012b",
    "gn:population":0,
    "gn:timezone":"Asia/Damascus",
    "iso:country":"SY",
    "name:ara_x_preferred":[
        "\u0627\u0644\u0634\u064a\u062e \u0639\u0644\u064a"
    ],
    "name:ara_x_variant":[
        "\u0634\u064a\u062e \u0639\u0644\u064a"
    ],
    "name:und_x_variant":[
        "Che\u00efkh Ali",
        "Che\u00efkh Aali",
        "Ash Shaykh \u2018Al\u012b",
        "Shaykh \u2018Al\u012b"
    ],
    "wof:name":"Ash Shaykh `Ali",
    "wof:placetype":"locality"
},
  "geometry": {"coordinates":[36.91402,36.09815],"type":"Point"}
}