{
  "type": "Feature",
  "properties": {
    "gn:admin1_code":"9.0",
    "gn:asciiname":"Rahmaniyah",
    "gn:country_code":"SY",
    "gn:dem":639,
    "gn:feature_class":"P",
    "gn:feature_code":"PPL",
    "gn:name":"Ra\u1e29m\u0101n\u012byah",
    "gn:population":0,
    "gn:timezone":"Asia/Damascus",
    "iso:country":"SY",
    "name:ara_x_preferred":[
        "\u0631\u062d\u0645\u0646\u0644\u064a"
    ],
    "name:ara_x_variant":[
        "\u0631\u062d\u0645\u0627\u0646\u0644\u064a",
        "\u0631\u062d\u0645\u0627\u0646\u064a\u0629"
    ],
    "name:und_x_variant":[
        "Ra\u1e29manl\u012b",
        "Ra\u1e29m\u0101nl\u012b",
        "Ra\u1e29m\u0101n\u012byah",
        "Seytana"
    ],
    "wof:name":"Rahmaniyah",
    "wof:placetype":"locality"
},
  "geometry": {"coordinates":[36.67643,36.58948],"type":"Point"}
}