{
  "type": "Feature",
  "properties": {
    "gn:admin1_code":"1.0",
    "gn:asciiname":"Ramlan Sharqi",
    "gn:country_code":"SY",
    "gn:dem":286,
    "gn:feature_class":"P",
    "gn:feature_code":"PPL",
    "gn:name":"Raml\u0101n Sharq\u012b",
    "gn:population":0,
    "gn:timezone":"Asia/Damascus",
    "iso:country":"SY",
    "name:ara_x_preferred":[
        "\u0631\u0645\u0644\u0627\u0646 \u0634\u0631\u0642\u064a"
    ],
    "name:und_x_variant":[
        "Raml\u0101n Sharq\u012b"
    ],
    "wof:name":"Ramlan Sharqi",
    "wof:placetype":"locality"
},
  "geometry": {"coordinates":[40.62635,36.09528],"type":"Point"}
}