{
  "type": "Feature",
  "properties": {
    "gn:admin1_code":"9.0",
    "gn:asciiname":"Sarijah",
    "gn:country_code":"SY",
    "gn:dem":330,
    "gn:feature_class":"P",
    "gn:feature_code":"PPL",
    "gn:name":"S\u0101rijah",
    "gn:population":0,
    "gn:timezone":"Asia/Damascus",
    "iso:country":"SY",
    "name:ara_x_preferred":[
        "\u0633\u0627\u0631\u062c\u0629"
    ],
    "name:und_x_variant":[
        "Sarj\u00e9",
        "Sarjah",
        "S\u0101rijah"
    ],
    "wof:name":"Sarijah",
    "wof:placetype":"locality"
},
  "geometry": {"coordinates":[37.25609,35.89198],"type":"Point"}
}