{
  "type": "Feature",
  "properties": {
    "gn:admin1_code":"9.0",
    "gn:asciiname":"Ad Dara`i",
    "gn:country_code":"SY",
    "gn:dem":492,
    "gn:feature_class":"P",
    "gn:feature_code":"PPL",
    "gn:name":"Ad Dara\u2018\u012b",
    "gn:population":0,
    "gn:timezone":"Asia/Damascus",
    "iso:country":"SY",
    "name:ara_x_preferred":[
        "\u0627\u0644\u062f\u0631\u0639\u064a"
    ],
    "name:und_x_variant":[
        "Ad Dara\u2018\u012b"
    ],
    "wof:name":"Ad Dara`i",
    "wof:placetype":"locality"
},
  "geometry": {"coordinates":[37.34882,36.29289],"type":"Point"}
}