{
  "type": "Feature",
  "properties": {
    "gn:admin1_code":"14.0",
    "gn:asciiname":"Al Burayj",
    "gn:country_code":"SY",
    "gn:dem":277,
    "gn:feature_class":"P",
    "gn:feature_code":"PPL",
    "gn:name":"Al Burayj",
    "gn:population":0,
    "gn:timezone":"Asia/Damascus",
    "iso:country":"SY",
    "name:ara_x_preferred":[
        "\u0628\u0631\u064a\u062c"
    ],
    "name:ara_x_variant":[
        "\u0627\u0644\u0628\u0631\u064a\u062c"
    ],
    "name:und_x_variant":[
        "Bra\u00efj",
        "Al Burayj",
        "Burayj"
    ],
    "wof:name":"Al Burayj",
    "wof:placetype":"locality"
},
  "geometry": {"coordinates":[35.92803,34.9702],"type":"Point"}
}