{
  "type": "Feature",
  "properties": {
    "gn:admin1_code":"12.0",
    "gn:asciiname":"Ma'arr Baliyah",
    "gn:country_code":"SY",
    "gn:dem":535,
    "gn:feature_class":"P",
    "gn:feature_code":"PPL",
    "gn:name":"Ma\u2019arr Bal\u012byah",
    "gn:population":0,
    "gn:timezone":"Asia/Damascus",
    "iso:country":"SY",
    "name:ara_x_preferred":[
        "\u0645\u0639\u0631 \u0628\u0644\u064a\u062a"
    ],
    "name:ara_x_variant":[
        "\u0645\u0639\u0631 \u0628\u0644\u064a\u0629"
    ],
    "name:und_x_variant":[
        "Maar Ballite",
        "Ma\u2018arr Ball\u012b\u0163",
        "Ma\u2018arr Ball\u012bt",
        "Ma\u2019arr Bal\u012byah"
    ],
    "wof:name":"Ma'arr Baliyah",
    "wof:placetype":"locality"
},
  "geometry": {"coordinates":[36.6626,35.80754],"type":"Point"}
}