{
  "type": "Feature",
  "properties": {
    "gn:admin1_code":"2.0",
    "gn:asciiname":"Bruma",
    "gn:country_code":"SY",
    "gn:dem":735,
    "gn:feature_class":"P",
    "gn:feature_code":"PPL",
    "gn:name":"Br\u016bm\u0101",
    "gn:population":0,
    "gn:timezone":"Asia/Damascus",
    "iso:country":"SY",
    "name:ara_x_preferred":[
        "Br\u016bm\u0101"
    ],
    "name:ara_x_variant":[
        "\u0628\u0631\u0648\u0645\u0627"
    ],
    "name:und_x_variant":[
        "Bro\u00fbma"
    ],
    "wof:name":"Bruma",
    "wof:placetype":"locality"
},
  "geometry": {"coordinates":[36.15464,35.72108],"type":"Point"}
}