{
  "type": "Feature",
  "properties": {
    "gn:admin1_code":"11.0",
    "gn:asciiname":"Al Mukarram",
    "gn:country_code":"SY",
    "gn:dem":977,
    "gn:feature_class":"P",
    "gn:feature_code":"PPL",
    "gn:name":"Al Mukarram",
    "gn:population":0,
    "gn:timezone":"Asia/Damascus",
    "iso:country":"SY",
    "name:ara_x_preferred":[
        "\u0627\u0644\u0645\u0643\u0631\u0645"
    ],
    "wof:name":"Al Mukarram",
    "wof:placetype":"locality"
},
  "geometry": {"coordinates":[37.4773,34.81265],"type":"Point"}
}