{
  "type": "Feature",
  "properties": {
    "gn:admin1_code":"5.0",
    "gn:asciiname":"Miyas",
    "gn:country_code":"SY",
    "gn:dem":1429,
    "gn:feature_class":"P",
    "gn:feature_code":"PPL",
    "gn:name":"Miy\u0101s",
    "gn:population":0,
    "gn:timezone":"Asia/Damascus",
    "iso:country":"SY",
    "name:ara_x_preferred":[
        "Miy\u0101s"
    ],
    "name:ara_x_variant":[
        "\u0645\u064a\u0627\u0633"
    ],
    "wof:name":"Miyas",
    "wof:placetype":"locality"
},
  "geometry": {"coordinates":[36.68866,32.61594],"type":"Point"}
}