{
  "type": "Feature",
  "properties": {
    "gn:admin1_code":"9.0",
    "gn:asciiname":"Kharab Suluk",
    "gn:country_code":"SY",
    "gn:dem":440,
    "gn:feature_class":"P",
    "gn:feature_code":"PPL",
    "gn:name":"Khar\u0101b Sul\u016bk",
    "gn:population":0,
    "gn:timezone":"Asia/Damascus",
    "iso:country":"SY",
    "name:ara_x_preferred":[
        "\u062e\u0631\u0627\u0628 \u0635\u0644\u0648\u0642"
    ],
    "name:ara_x_variant":[
        "\u062e\u0631\u0627\u0628 \u0633\u0644\u0648\u0643"
    ],
    "name:und_x_variant":[
        "Khar\u0101b \u015eul\u016bq",
        "Khar\u0101b Sul\u016bk"
    ],
    "wof:name":"Kharab Suluk",
    "wof:placetype":"locality"
},
  "geometry": {"coordinates":[36.65257,36.74018],"type":"Point"}
}