{
  "type": "Feature",
  "properties": {
    "gn:admin1_code":"1.0",
    "gn:asciiname":"Rayhaniyah",
    "gn:country_code":"SY",
    "gn:dem":360,
    "gn:feature_class":"P",
    "gn:feature_code":"PPL",
    "gn:name":"Ray\u1e29\u0101n\u012byah",
    "gn:population":0,
    "gn:timezone":"Asia/Damascus",
    "iso:country":"SY",
    "name:ara_x_preferred":[
        "\u0631\u064a\u062d\u0627\u0646\u064a\u0629"
    ],
    "name:tur_x_preferred":[
        "Ray\u1e29\u0101n\u012byah"
    ],
    "name:und_x_variant":[
        "R\u00eeh\u00e2n\u00eeye"
    ],
    "wof:name":"Rayhaniyah",
    "wof:placetype":"locality"
},
  "geometry": {"coordinates":[41.56653,36.82339],"type":"Point"}
}