{
  "type": "Feature",
  "properties": {
    "gn:admin1_code":"9.0",
    "gn:asciiname":"Al Judaydah",
    "gn:country_code":"SY",
    "gn:dem":478,
    "gn:feature_class":"P",
    "gn:feature_code":"PPL",
    "gn:name":"Al Judaydah",
    "gn:population":0,
    "gn:timezone":"Asia/Damascus",
    "iso:country":"SY",
    "name:ara_x_preferred":[
        "\u064a\u0646\u064a \u064a\u0627\u0628\u0627\u0646"
    ],
    "name:ara_x_variant":[
        "\u0627\u0644\u062c\u062f\u064a\u062f\u0629"
    ],
    "name:und_x_variant":[
        "Y\u00e9ni Yap\u00e2ne",
        "Yan\u012b Yab\u0101n",
        "Yan\u012b Y\u0101b\u0101n",
        "Al Judaydah"
    ],
    "wof:name":"Al Judaydah",
    "wof:placetype":"locality"
},
  "geometry": {"coordinates":[37.2663,36.61776],"type":"Point"}
}