{
  "type": "Feature",
  "properties": {
    "gn:admin1_code":"1.0",
    "gn:asciiname":"Qusaybah",
    "gn:country_code":"SY",
    "gn:dem":298,
    "gn:feature_class":"P",
    "gn:feature_code":"PPL",
    "gn:name":"Qu\u015faybah",
    "gn:population":0,
    "gn:timezone":"Asia/Damascus",
    "iso:country":"SY",
    "name:ara_x_preferred":[
        "\u0642\u0635\u064a\u0628\u0629"
    ],
    "name:und_x_variant":[
        "Qu\u015faybah"
    ],
    "wof:name":"Qusaybah",
    "wof:placetype":"locality"
},
  "geometry": {"coordinates":[40.64641,36.22244],"type":"Point"}
}