{
  "type": "Feature",
  "properties": {
    "gn:admin1_code":"6.0",
    "gn:asciiname":"Al Masharif",
    "gn:country_code":"SY",
    "gn:dem":652,
    "gn:feature_class":"P",
    "gn:feature_code":"PPL",
    "gn:name":"Al Mash\u0101rif",
    "gn:population":0,
    "gn:timezone":"Asia/Damascus",
    "iso:country":"SY",
    "name:ara_x_preferred":[
        "\u0627\u0644\u0645\u0634\u0627\u0631\u0641"
    ],
    "name:und_x_variant":[
        "Al Mash\u0101rif"
    ],
    "wof:name":"Al Masharif",
    "wof:placetype":"locality"
},
  "geometry": {"coordinates":[36.3812,33.05319],"type":"Point"}
}