{
  "type": "Feature",
  "properties": {
    "gn:admin1_code":"8.0",
    "gn:asciiname":"Ard al Mutlaqah",
    "gn:country_code":"SY",
    "gn:dem":601,
    "gn:feature_class":"P",
    "gn:feature_code":"PPLL",
    "gn:name":"Ar\u1e11 al Mu\u0163laqah",
    "gn:population":0,
    "gn:timezone":"Asia/Damascus",
    "iso:country":"SY",
    "name:ara_x_preferred":[
        "\u0623\u0631\u0636 \u0627\u0644\u0645\u0637\u0644\u0642\u0629"
    ],
    "name:und_x_variant":[
        "Ar\u1e11 al Mu\u0163laqah"
    ],
    "wof:name":"Ard al Mutlaqah",
    "wof:placetype":"locality"
},
  "geometry": {"coordinates":[36.61984,33.48449],"type":"Point"}
}