{
  "type": "Feature",
  "properties": {
    "gn:admin1_code":"9.0",
    "gn:asciiname":"Bayt Rujm al Faraj",
    "gn:country_code":"SY",
    "gn:dem":355,
    "gn:feature_class":"P",
    "gn:feature_code":"PPLL",
    "gn:name":"Bayt Rujm al Faraj",
    "gn:population":0,
    "gn:timezone":"Asia/Damascus",
    "iso:country":"SY",
    "name:ara_x_preferred":[
        "\u0628\u064a\u062a \u0631\u062c\u0645 \u0627\u0644\u0641\u0631\u062c"
    ],
    "name:und_x_variant":[
        "Bayt Rajam al Faraj",
        "Bayt Rujm al Faraj"
    ],
    "wof:name":"Bayt Rujm al Faraj",
    "wof:placetype":"locality"
},
  "geometry": {"coordinates":[37.34224,36.14676],"type":"Point"}
}