{
  "type": "Feature",
  "properties": {
    "gn:admin1_code":"3.0",
    "gn:asciiname":"Aradi ash Shakarah",
    "gn:country_code":"SY",
    "gn:dem":965,
    "gn:feature_class":"P",
    "gn:feature_code":"PPLL",
    "gn:name":"Ar\u0101\u1e11\u012b ash Shak\u0101rah",
    "gn:population":0,
    "gn:timezone":"Asia/Damascus",
    "iso:country":"SY",
    "name:ara_x_preferred":[
        "\u0623\u0631\u0627\u0636\u064a \u0627\u0644\u0634\u0643\u0627\u0631\u0629"
    ],
    "name:und_x_variant":[
        "Ar\u0101\u1e11\u012b ash Shak\u0101rah",
        "Ar\u0101\u1e11\u012b ash Shakk\u0101rah"
    ],
    "wof:name":"Aradi ash Shakarah",
    "wof:placetype":"locality"
},
  "geometry": {"coordinates":[35.93771,33.19234],"type":"Point"}
}