{
  "type": "Feature",
  "properties": {
    "gn:admin1_code":"7.0",
    "gn:asciiname":"As Safiyah",
    "gn:country_code":"SY",
    "gn:dem":223,
    "gn:feature_class":"P",
    "gn:feature_code":"PPL",
    "gn:name":"A\u015f \u015eaf\u012byah",
    "gn:population":0,
    "gn:timezone":"Asia/Damascus",
    "iso:country":"SY",
    "name:ara_x_preferred":[
        "\u0627\u0644\u0635\u0641\u064a\u0629"
    ],
    "name:und_x_variant":[
        "A\u015f \u015eaf\u012byah"
    ],
    "wof:name":"As Safiyah",
    "wof:placetype":"locality"
},
  "geometry": {"coordinates":[40.65043,35.49896],"type":"Point"}
}