{
  "type": "Feature",
  "properties": {
    "iso:country":"SY",
    "name:ara_x_preferred":[
        "\u0645\u064f\u062d\u0627\u0641\u0638\u0629 \u0627\u0644\u0644\u0627\u0630\u0642\u064a\u0629"
    ],
    "name:eng_x_preferred":[
        "Latakia"
    ],
    "name:eng_x_variant":[
        "Latakia Governate"
    ],
    "qs:gn_pop":0,
    "qs:name":"\u0645\u064f\u062d\u0627\u0641\u0638\u0629 \u0627\u0644\u0644\u0627\u0630\u0642\u064a\u0629",
    "qs:name_adm0":"\u0633\u0648\u0631\u064a\u0627",
    "qs:name_adm1":"\u0645\u064f\u062d\u0627\u0641\u0638\u0629 \u0627\u0644\u0644\u0627\u0630\u0642\u064a\u0629",
    "qs:photos":1097,
    "qs:photos_1k":222,
    "qs:photos_9k":5,
    "qs:photos_9r":7,
    "qs:photos_all":1097,
    "qs:photos_sr":11,
    "qs:placetype":"Town",
    "qs:pop_sr":"0",
    "qs:woe_adm0":23424956,
    "wof:name":"Latakia",
    "wof:placetype":"locality"
},
  "geometry": {"coordinates":[35.786075,35.52538],"type":"Point"}
}