{
  "type": "Feature",
  "properties": {
    "gn:admin1_code":"14.0",
    "gn:asciiname":"Hammam Wasil",
    "gn:country_code":"SY",
    "gn:dem":583,
    "gn:feature_class":"P",
    "gn:feature_code":"PPLA3",
    "gn:name":"\u1e28amm\u0101m W\u0101\u015fil",
    "gn:population":0,
    "gn:timezone":"Asia/Damascus",
    "iso:country":"SY",
    "name:ara_x_preferred":[
        "\u062d\u0645\u0627\u0645 \u0648\u0627\u0635\u0644"
    ],
    "name:und_x_variant":[
        "Hamm\u00e2m Ou\u00e2ssel",
        "\u1e28amm\u0101m W\u0101\u015fil"
    ],
    "wof:name":"Hammam Wasil",
    "wof:placetype":"locality"
},
  "geometry": {"coordinates":[36.08677,35.07437],"type":"Point"}
}