{
  "type": "Feature",
  "properties": {
    "gn:admin1_code":"0.0",
    "gn:asciiname":"Khirbat Duwayzin",
    "gn:country_code":"SY",
    "gn:dem":915,
    "gn:feature_class":"P",
    "gn:feature_code":"PPL",
    "gn:name":"Khirbat Duwayz\u012bn",
    "gn:population":0,
    "gn:timezone":"Asia/Damascus",
    "iso:country":"SY",
    "name:ara_x_preferred":[
        "\u062e\u0631\u0628\u0629 \u062f\u0648\u064a\u0632\u064a\u0646"
    ],
    "name:und_x_variant":[
        "Khirbat Duwayz\u012bn"
    ],
    "wof:name":"Khirbat Duwayzin",
    "wof:placetype":"locality"
},
  "geometry": {"coordinates":[37.86703,34.98701],"type":"Point"}
}