{
  "type": "Feature",
  "properties": {
    "gn:admin1_code":"3.0",
    "gn:asciiname":"Rasm Fatimah",
    "gn:country_code":"SY",
    "gn:dem":791,
    "gn:feature_class":"P",
    "gn:feature_code":"PPL",
    "gn:name":"Rasm F\u0101\u0163imah",
    "gn:population":0,
    "gn:timezone":"Asia/Damascus",
    "iso:country":"SY",
    "name:ara_x_preferred":[
        "\u0631\u0633\u0645 \u0641\u0627\u0637\u0645\u0629"
    ],
    "name:und_x_variant":[
        "Rasm F\u0101\u0163imah"
    ],
    "wof:name":"Rasm Fatimah",
    "wof:placetype":"locality"
},
  "geometry": {"coordinates":[35.7943,33.03315],"type":"Point"}
}