{
  "type": "Feature",
  "properties": {
    "gn:admin1_code":"11.0",
    "gn:asciiname":"Umm at Tababir",
    "gn:country_code":"SY",
    "gn:dem":690,
    "gn:feature_class":"P",
    "gn:feature_code":"PPL",
    "gn:name":"Umm a\u0163 \u0162ab\u0101b\u012br",
    "gn:population":0,
    "gn:timezone":"Asia/Damascus",
    "iso:country":"SY",
    "name:ara_x_preferred":[
        "\u0623\u0645 \u0627\u0644\u0637\u0628\u0627\u0628\u064a\u0631"
    ],
    "name:und_x_variant":[
        "Oum ett Tab\u00e2b\u00eer",
        "Umm a\u0163 \u0162ab\u0101b\u012br"
    ],
    "wof:name":"Umm at Tababir",
    "wof:placetype":"locality"
},
  "geometry": {"coordinates":[37.2795,34.58263],"type":"Point"}
}