{
  "type": "Feature",
  "properties": {
    "gn:admin1_code":"14.0",
    "gn:asciiname":"Al Futasiyah",
    "gn:country_code":"SY",
    "gn:dem":71,
    "gn:feature_class":"P",
    "gn:feature_code":"PPL",
    "gn:name":"Al Fu\u0163\u0101s\u012byah",
    "gn:population":0,
    "gn:timezone":"Asia/Damascus",
    "iso:country":"SY",
    "name:ara_x_preferred":[
        "\u0627\u0644\u0641\u0637\u0627\u0633\u064a\u0629"
    ],
    "name:und_x_variant":[
        "Louft\u00e2ss\u00eey\u00e9",
        "El Ft\u00e2ss\u00eey\u00e9",
        "Al Fu\u0163\u0101s\u012byah"
    ],
    "wof:name":"Al Futasiyah",
    "wof:placetype":"locality"
},
  "geometry": {"coordinates":[35.97108,34.81587],"type":"Point"}
}