{
  "type": "Feature",
  "properties": {
    "gn:admin1_code":"11.0",
    "gn:asciiname":"Zawr al `Ibarah",
    "gn:country_code":"SY",
    "gn:dem":483,
    "gn:feature_class":"P",
    "gn:feature_code":"PPLL",
    "gn:name":"Zawr al \u2018Ib\u0101rah",
    "gn:population":0,
    "gn:timezone":"Asia/Damascus",
    "iso:country":"SY",
    "name:ara_x_preferred":[
        "\u0632\u0648\u0631 \u0627\u0644\u0639\u0628\u0627\u0631\u0629"
    ],
    "name:und_x_variant":[
        "Zawr al \u2018Ib\u0101rah"
    ],
    "wof:name":"Zawr al `Ibarah",
    "wof:placetype":"locality"
},
  "geometry": {"coordinates":[36.70066,34.73993],"type":"Point"}
}