{
  "type": "Feature",
  "properties": {
    "gn:admin1_code":"10.0",
    "gn:asciiname":"Shalahmi",
    "gn:country_code":"SY",
    "gn:dem":611,
    "gn:feature_class":"P",
    "gn:feature_code":"PPL",
    "gn:name":"Shala\u1e29m\u012b",
    "gn:population":0,
    "gn:timezone":"Asia/Damascus",
    "iso:country":"SY",
    "name:ara_x_preferred":[
        "\u0634\u0644\u062d\u0645\u064a"
    ],
    "name:ara_x_variant":[
        "\u0645\u0634\u062a\u0649 \u0627\u0644\u0634\u0644\u0627\u0647\u0645\u0629"
    ],
    "name:und_x_variant":[
        "A\u00efn el Kro\u00fbm",
        "Chal\u00e2hmi",
        "Shala\u1e29m\u012b",
        "Shal\u1e29am\u00e1",
        "Masht\u00e1 ash Shal\u0101himah"
    ],
    "wof:name":"Shalahmi",
    "wof:placetype":"locality"
},
  "geometry": {"coordinates":[36.25493,35.34737],"type":"Point"}
}