{
  "type": "Feature",
  "properties": {
    "gn:admin1_code":"1.0",
    "gn:asciiname":"Khirbat Khurayjat",
    "gn:country_code":"SY",
    "gn:dem":344,
    "gn:feature_class":"P",
    "gn:feature_code":"PPL",
    "gn:name":"Khirbat Khurayj\u0101t",
    "gn:population":0,
    "gn:timezone":"Asia/Damascus",
    "iso:country":"SY",
    "name:ara_x_preferred":[
        "\u062e\u0631\u0628\u0629 \u062e\u0631\u064a\u062c\u0627\u062a"
    ],
    "name:tur_x_preferred":[
        "Khirbat Khurayj\u0101t"
    ],
    "name:und_x_variant":[
        "Kheurbet Khare\u00efj\u00e2te"
    ],
    "wof:name":"Khirbat Khurayjat",
    "wof:placetype":"locality"
},
  "geometry": {"coordinates":[41.27,36.77896],"type":"Point"}
}