{
  "type": "Feature",
  "properties": {
    "gn:admin1_code":"7.0",
    "gn:asciiname":"Mazlum",
    "gn:country_code":"SY",
    "gn:dem":200,
    "gn:feature_class":"P",
    "gn:feature_code":"PPL",
    "gn:name":"Maz\u0327l\u016bm",
    "gn:population":0,
    "gn:timezone":"Asia/Damascus",
    "iso:country":"SY",
    "name:ara_x_preferred":[
        "\u0645\u0638\u0644\u0648\u0645"
    ],
    "name:bos_x_preferred":[
        "Mazlum"
    ],
    "name:und_x_variant":[
        "Mazlo\u00fbm",
        "Maz\u0327l\u016bm"
    ],
    "wof:name":"Mazlum",
    "wof:placetype":"locality"
},
  "geometry": {"coordinates":[40.25908,35.30839],"type":"Point"}
}