{
  "type": "Feature",
  "properties": {
    "gn:admin1_code":"12.0",
    "gn:asciiname":"Tall Mahush",
    "gn:country_code":"SY",
    "gn:dem":382,
    "gn:feature_class":"P",
    "gn:feature_code":"PPL",
    "gn:name":"Tall M\u0101h\u016bsh",
    "gn:population":0,
    "gn:timezone":"Asia/Damascus",
    "iso:country":"SY",
    "name:ara_x_preferred":[
        "\u062a\u0644 \u0645\u0627\u0647\u0648\u0634"
    ],
    "name:und_x_variant":[
        "Tall M\u0101h\u016bsh"
    ],
    "wof:name":"Tall Mahush",
    "wof:placetype":"locality"
},
  "geometry": {"coordinates":[36.74519,36.19764],"type":"Point"}
}