{
  "type": "Feature",
  "properties": {
    "gn:admin1_code":"6.0",
    "gn:asciiname":"Hawsh Sharid",
    "gn:country_code":"SY",
    "gn:dem":646,
    "gn:feature_class":"P",
    "gn:feature_code":"PPL",
    "gn:name":"\u1e28awsh Shar\u012bd",
    "gn:population":0,
    "gn:timezone":"Asia/Damascus",
    "iso:country":"SY",
    "name:ara_x_preferred":[
        "\u062d\u0648\u0634 \u0634\u0631\u064a\u062f"
    ],
    "name:und_x_variant":[
        "\u1e28awsh Shar\u012bd"
    ],
    "wof:name":"Hawsh Sharid",
    "wof:placetype":"locality"
},
  "geometry": {"coordinates":[36.45103,33.12114],"type":"Point"}
}