{
  "type": "Feature",
  "properties": {
    "gn:admin1_code":"11.0",
    "gn:asciiname":"Huwayk",
    "gn:country_code":"SY",
    "gn:dem":626,
    "gn:feature_class":"P",
    "gn:feature_code":"PPL",
    "gn:name":"\u1e28uwayk",
    "gn:population":0,
    "gn:timezone":"Asia/Damascus",
    "iso:country":"SY",
    "name:ara_x_preferred":[
        "\u062d\u0648\u064a\u0643"
    ],
    "name:ara_x_variant":[
        "\u0627\u0644\u062d\u0627\u0648\u064a"
    ],
    "name:und_x_variant":[
        "\u1e28uwayk",
        "Al \u1e28\u0101w\u012b"
    ],
    "wof:name":"Huwayk",
    "wof:placetype":"locality"
},
  "geometry": {"coordinates":[36.42271,34.54737],"type":"Point"}
}