{
  "type": "Feature",
  "properties": {
    "gn:admin1_code":"1.0",
    "gn:asciiname":"Khirbat Tiflah",
    "gn:country_code":"SY",
    "gn:dem":345,
    "gn:feature_class":"P",
    "gn:feature_code":"PPL",
    "gn:name":"Khirbat Tiflah",
    "gn:population":0,
    "gn:timezone":"Asia/Damascus",
    "iso:country":"SY",
    "name:ara_x_preferred":[
        "\u062e\u0631\u0628\u0629 \u062a\u0641\u0644\u0629"
    ],
    "name:und_x_variant":[
        "Kheurbet Tofl\u00e9",
        "Khirbat Tofl\u00e9",
        "Khirbat Tiflah"
    ],
    "wof:name":"Khirbat Tiflah",
    "wof:placetype":"locality"
},
  "geometry": {"coordinates":[41.17384000000001,36.73634000000001],"type":"Point"}
}