{
  "type": "Feature",
  "properties": {
    "gn:admin1_code":"14.0",
    "gn:asciiname":"Jurat Shatbush",
    "gn:country_code":"SY",
    "gn:dem":527,
    "gn:feature_class":"P",
    "gn:feature_code":"PPL",
    "gn:name":"J\u016brat Sha\u0163b\u016bsh",
    "gn:population":0,
    "gn:timezone":"Asia/Damascus",
    "iso:country":"SY",
    "name:ara_x_preferred":[
        "\u062c\u0648\u0631\u0629"
    ],
    "name:ara_x_variant":[
        "\u062c\u0648\u0631\u0629 \u0634\u0637\u0628\u0648\u0634"
    ],
    "name:und_x_variant":[
        "Jo\u00fbret Chattbo\u00fbch",
        "Jo\u00fbret Chatbo\u00fbch",
        "J\u016brat Sha\u0163b\u016bsh",
        "J\u016brah",
        "Jouret Chatbo\u00fbch"
    ],
    "wof:name":"Jurat Shatbush",
    "wof:placetype":"locality"
},
  "geometry": {"coordinates":[36.20633,34.90107],"type":"Point"}
}