{
  "type": "Feature",
  "properties": {
    "gn:admin1_code":"2.0",
    "gn:asciiname":"Daghdaghan",
    "gn:country_code":"SY",
    "gn:dem":447,
    "gn:feature_class":"P",
    "gn:feature_code":"PPL",
    "gn:name":"Daghdagh\u0101n",
    "gn:population":0,
    "gn:timezone":"Asia/Damascus",
    "iso:country":"SY",
    "name:ara_x_preferred":[
        "\u062f\u063a\u062f\u063a\u0627\u0646"
    ],
    "name:und_x_variant":[
        "Darhdarh\u00e2ne",
        "Daghdagh\u0101n"
    ],
    "wof:name":"Daghdaghan",
    "wof:placetype":"locality"
},
  "geometry": {"coordinates":[36.04018,35.82848],"type":"Point"}
}