{
  "type": "Feature",
  "properties": {
    "gn:admin1_code":"10.0",
    "gn:asciiname":"Sufaynah",
    "gn:country_code":"SY",
    "gn:dem":432,
    "gn:feature_class":"P",
    "gn:feature_code":"PPL",
    "gn:name":"\u015eufaynah",
    "gn:population":0,
    "gn:timezone":"Asia/Damascus",
    "iso:country":"SY",
    "name:ara_x_preferred":[
        "\u0635\u0641\u064a\u0646\u0629"
    ],
    "name:und_x_variant":[
        "\u015eufaynah"
    ],
    "wof:name":"Sufaynah",
    "wof:placetype":"locality"
},
  "geometry": {"coordinates":[36.90383,35.14104],"type":"Point"}
}