{
  "type": "Feature",
  "properties": {
    "gn:admin1_code":"1.0",
    "gn:asciiname":"Khaybak",
    "gn:country_code":"SY",
    "gn:dem":427,
    "gn:feature_class":"P",
    "gn:feature_code":"PPL",
    "gn:name":"Khaybak",
    "gn:population":0,
    "gn:timezone":"Asia/Damascus",
    "iso:country":"SY",
    "name:ara_x_preferred":[
        "\u062e\u064a\u0628\u0643"
    ],
    "name:tur_x_preferred":[
        "Khaybak"
    ],
    "name:und_x_variant":[
        "Khaib\u00e9k"
    ],
    "wof:name":"Khaybak",
    "wof:placetype":"locality"
},
  "geometry": {"coordinates":[41.33745,37.05447],"type":"Point"}
}