{
  "type": "Feature",
  "properties": {
    "gn:admin1_code":"14.0",
    "gn:asciiname":"Khirbat al Faras",
    "gn:country_code":"SY",
    "gn:dem":362,
    "gn:feature_class":"P",
    "gn:feature_code":"PPL",
    "gn:name":"Khirbat al Faras",
    "gn:population":0,
    "gn:timezone":"Asia/Damascus",
    "iso:country":"SY",
    "name:ara_x_preferred":[
        "\u062e\u0631\u0628\u0629 \u0627\u0644\u0641\u0631\u0633"
    ],
    "name:und_x_variant":[
        "Kheurbet el Farass",
        "Khirbat al Faras",
        "Kh. el Farass"
    ],
    "wof:name":"Khirbat al Faras",
    "wof:placetype":"locality"
},
  "geometry": {"coordinates":[36.0135,34.95097],"type":"Point"}
}