{
  "type": "Feature",
  "properties": {
    "gn:admin1_code":"1.0",
    "gn:asciiname":"Tall Habbu",
    "gn:country_code":"SY",
    "gn:dem":412,
    "gn:feature_class":"P",
    "gn:feature_code":"PPL",
    "gn:name":"Tall \u1e28abb\u016b",
    "gn:population":0,
    "gn:timezone":"Asia/Damascus",
    "iso:country":"SY",
    "name:ara_x_preferred":[
        "\u062a\u0644 \u062d\u0628\u0648"
    ],
    "name:tur_x_preferred":[
        "Tall \u1e28abb\u016b"
    ],
    "name:und_x_variant":[
        "Tell Habbou"
    ],
    "wof:name":"Tall Habbu",
    "wof:placetype":"locality"
},
  "geometry": {"coordinates":[40.53857,36.86863],"type":"Point"}
}