{
  "type": "Feature",
  "properties": {
    "gn:admin1_code":"9.0",
    "gn:asciiname":"Hajjan",
    "gn:country_code":"SY",
    "gn:dem":578,
    "gn:feature_class":"P",
    "gn:feature_code":"PPL",
    "gn:name":"\u1e28ajj\u0101n",
    "gn:population":0,
    "gn:timezone":"Asia/Damascus",
    "iso:country":"SY",
    "name:ara_x_preferred":[
        "\u062c\u0645\u0627\u0646\u0644\u064a"
    ],
    "name:ara_x_variant":[
        "\u062d\u062c\u0627\u0646",
        "\u062c\u0645\u0627\u0646"
    ],
    "name:und_x_variant":[
        "Tchemanli",
        "Tchamannli",
        "Tch\u00e9mannli",
        "Shamanl\u012b",
        "Jam\u0101nl\u012b",
        "\u1e28ajj\u0101n",
        "Jam\u0101n"
    ],
    "wof:name":"Hajjan",
    "wof:placetype":"locality"
},
  "geometry": {"coordinates":[36.93935,36.64718],"type":"Point"}
}