{
  "type": "Feature",
  "properties": {
    "gn:admin1_code":"4.0",
    "gn:asciiname":"Bandar Khan",
    "gn:country_code":"SY",
    "gn:dem":387,
    "gn:feature_class":"P",
    "gn:feature_code":"PPL",
    "gn:name":"Bandar Kh\u0101n",
    "gn:population":0,
    "gn:timezone":"Asia/Damascus",
    "iso:country":"SY",
    "name:ara_x_preferred":[
        "\u0628\u0646\u062f\u0631 \u062e\u0627\u0646"
    ],
    "name:und_x_variant":[
        "Banndar Kh\u00e2ne",
        "Bandar Kh\u0101n"
    ],
    "wof:name":"Bandar Khan",
    "wof:placetype":"locality"
},
  "geometry": {"coordinates":[38.69621,36.70922],"type":"Point"}
}