{
  "type": "Feature",
  "properties": {
    "gn:admin1_code":"1.0",
    "gn:asciiname":"Ghadrafa",
    "gn:country_code":"SY",
    "gn:dem":384,
    "gn:feature_class":"P",
    "gn:feature_code":"PPL",
    "gn:name":"Gha\u1e11r\u0101f\u0101",
    "gn:population":0,
    "gn:timezone":"Asia/Damascus",
    "iso:country":"SY",
    "name:ara_x_preferred":[
        "\u063a\u0636\u0631\u0627\u0641\u0627"
    ],
    "name:und_x_variant":[
        "Gha\u1e11r\u0101f\u0101"
    ],
    "wof:name":"Ghadrafa",
    "wof:placetype":"locality"
},
  "geometry": {"coordinates":[40.40892,36.17281],"type":"Point"}
}