{
  "type": "Feature",
  "properties": {
    "gn:admin1_code":"14.0",
    "gn:asciiname":"Sabbuniyah",
    "gn:country_code":"SY",
    "gn:dem":100,
    "gn:feature_class":"P",
    "gn:feature_code":"PPL",
    "gn:name":"\u015e\u0101bb\u016bn\u012byah",
    "gn:population":0,
    "gn:timezone":"Asia/Damascus",
    "iso:country":"SY",
    "name:ara_x_preferred":[
        "\u0635\u0627\u0628\u0648\u0646\u064a\u0629"
    ],
    "name:und_x_variant":[
        "Sabbouhiy\u00e9",
        "A\u015f \u015eabb\u016b\u1e29\u012byah",
        "\u015e\u0101bb\u016bn\u012byah"
    ],
    "wof:name":"Sabbuniyah",
    "wof:placetype":"locality"
},
  "geometry": {"coordinates":[36.06589,34.71307],"type":"Point"}
}