{
  "type": "Feature",
  "properties": {
    "gn:admin1_code":"11.0",
    "gn:asciiname":"Buwaydat al Salamiyah",
    "gn:country_code":"SY",
    "gn:dem":573,
    "gn:feature_class":"P",
    "gn:feature_code":"PPL",
    "gn:name":"Buway\u1e11at al Salam\u012byah",
    "gn:population":0,
    "gn:timezone":"Asia/Damascus",
    "iso:country":"SY",
    "name:ara_x_preferred":[
        "\u0628\u0648\u064a\u0636\u0629 \u0627\u0644\u0633\u0644\u0645\u064a\u0629"
    ],
    "name:und_x_variant":[
        "Boua\u00efdet S\u00e9l\u00e9m\u00eey\u00e9",
        "Buway\u1e11at Salam\u012byah",
        "Buway\u1e11at al Salam\u012byah"
    ],
    "wof:name":"Buwaydat al Salamiyah",
    "wof:placetype":"locality"
},
  "geometry": {"coordinates":[37.01351,34.83926],"type":"Point"}
}