{
  "type": "Feature",
  "properties": {
    "gn:admin1_code":"9.0",
    "gn:asciiname":"Mazra`at as Sayyadah al Kabirah",
    "gn:country_code":"SY",
    "gn:dem":512,
    "gn:feature_class":"P",
    "gn:feature_code":"PPL",
    "gn:name":"Mazra\u2018at a\u015f \u015eayy\u0101dah al Kab\u012brah",
    "gn:population":0,
    "gn:timezone":"Asia/Damascus",
    "iso:country":"SY",
    "name:ara_x_preferred":[
        "\u0645\u0632\u0631\u0639\u0629 \u0627\u0644\u0635\u064a\u0627\u062f\u0629 \u0627\u0644\u0643\u0628\u064a\u0631\u0629"
    ],
    "name:und_x_variant":[
        "Mazra\u2018at a\u015f \u015eayy\u0101dah al Kab\u012brah"
    ],
    "wof:name":"Mazra`at as Sayyadah al Kabirah",
    "wof:placetype":"locality"
},
  "geometry": {"coordinates":[37.73718,36.55062],"type":"Point"}
}