{
  "type": "Feature",
  "properties": {
    "gn:admin1_code":"9.0",
    "gn:asciiname":"Jubb Sultan",
    "gn:country_code":"SY",
    "gn:dem":371,
    "gn:feature_class":"P",
    "gn:feature_code":"PPL",
    "gn:name":"Jubb Sul\u0163\u0101n",
    "gn:population":0,
    "gn:timezone":"Asia/Damascus",
    "iso:country":"SY",
    "name:ara_x_preferred":[
        "Jubb Sul\u0163\u0101n"
    ],
    "name:ara_x_variant":[
        "\u062c\u0628 \u0633\u0644\u0637\u0627\u0646"
    ],
    "wof:name":"Jubb Sultan",
    "wof:placetype":"locality"
},
  "geometry": {"coordinates":[37.854,35.69793],"type":"Point"}
}