{
  "type": "Feature",
  "properties": {
    "gn:admin1_code":"11.0",
    "gn:asciiname":"Al Mihnayah",
    "gn:country_code":"SY",
    "gn:dem":451,
    "gn:feature_class":"P",
    "gn:feature_code":"PPL",
    "gn:name":"Al Mi\u1e29n\u0101yah",
    "gn:population":0,
    "gn:timezone":"Asia/Damascus",
    "iso:country":"SY",
    "name:ara_x_preferred":[
        "\u0627\u0644\u0645\u062d\u0646\u0627\u064a\u0629"
    ],
    "name:und_x_variant":[
        "Al Mi\u1e29n\u0101yah"
    ],
    "wof:name":"Al Mihnayah",
    "wof:placetype":"locality"
},
  "geometry": {"coordinates":[36.59515,34.80025],"type":"Point"}
}