{
  "type": "Feature",
  "properties": {
    "gn:admin1_code":"7.0",
    "gn:asciiname":"Al Matha",
    "gn:country_code":"SY",
    "gn:dem":233,
    "gn:feature_class":"P",
    "gn:feature_code":"PPL",
    "gn:name":"Al Mat\u1e29\u0101",
    "gn:population":0,
    "gn:timezone":"Asia/Damascus",
    "iso:country":"SY",
    "name:ara_x_preferred":[
        "\u0627\u0644\u0645\u062a\u062d\u0627"
    ],
    "name:und_x_variant":[
        "Al Mat\u1e29\u0101"
    ],
    "wof:name":"Al Matha",
    "wof:placetype":"locality"
},
  "geometry": {"coordinates":[39.66797,35.73957],"type":"Point"}
}