{
  "type": "Feature",
  "properties": {
    "gn:admin1_code":"6.0",
    "gn:asciiname":"Raqqat Jum`ah",
    "gn:country_code":"SY",
    "gn:dem":634,
    "gn:feature_class":"P",
    "gn:feature_code":"PPL",
    "gn:name":"Raqqat Jum\u2018ah",
    "gn:population":0,
    "gn:timezone":"Asia/Damascus",
    "iso:country":"SY",
    "name:ara_x_preferred":[
        "\u0631\u0642\u0629 \u062c\u0645\u0639\u0629"
    ],
    "name:und_x_variant":[
        "Raqqat Jum\u2018ah"
    ],
    "wof:name":"Raqqat Jum`ah",
    "wof:placetype":"locality"
},
  "geometry": {"coordinates":[36.25532000000001,33.08322],"type":"Point"}
}