{
  "type": "Feature",
  "properties": {
    "gn:admin1_code":"2.0",
    "gn:asciiname":"Ard ad Dawrat",
    "gn:country_code":"SY",
    "gn:dem":10,
    "gn:feature_class":"P",
    "gn:feature_code":"PPLL",
    "gn:name":"Ar\u1e11 ad Dawr\u0101t",
    "gn:population":0,
    "gn:timezone":"Asia/Damascus",
    "iso:country":"SY",
    "name:ara_x_preferred":[
        "\u0623\u0631\u0636 \u0627\u0644\u062f\u0648\u0631\u0627\u062a"
    ],
    "name:und_x_variant":[
        "Ar\u1e11 ad Dawr\u0101t"
    ],
    "wof:name":"Ard ad Dawrat",
    "wof:placetype":"locality"
},
  "geometry": {"coordinates":[35.83077,35.52225],"type":"Point"}
}