{
  "type": "Feature",
  "properties": {
    "gn:admin1_code":"6.0",
    "gn:asciiname":"Sath al Ju`",
    "gn:country_code":"SY",
    "gn:dem":621,
    "gn:feature_class":"P",
    "gn:feature_code":"PPL",
    "gn:name":"Sa\u0163\u1e29 al J\u016b\u2018",
    "gn:population":0,
    "gn:timezone":"Asia/Damascus",
    "iso:country":"SY",
    "name:ara_x_preferred":[
        "\u0633\u0637\u062d \u0627\u0644\u062c\u0648\u0639"
    ],
    "name:und_x_variant":[
        "Sa\u0163\u1e29 al J\u016b\u2018"
    ],
    "wof:name":"Sath al Ju`",
    "wof:placetype":"locality"
},
  "geometry": {"coordinates":[36.33368,33.08689],"type":"Point"}
}