{
  "type": "Feature",
  "properties": {
    "gn:admin1_code":"11.0",
    "gn:asciiname":"Mujaydil",
    "gn:country_code":"SY",
    "gn:dem":518,
    "gn:feature_class":"P",
    "gn:feature_code":"PPL",
    "gn:name":"Mujaydil",
    "gn:population":0,
    "gn:timezone":"Asia/Damascus",
    "iso:country":"SY",
    "name:ara_x_preferred":[
        "\u0645\u062c\u064a\u062f\u0644"
    ],
    "name:und_x_variant":[
        "Mja\u00efdel",
        "Mujaydil"
    ],
    "wof:name":"Mujaydil",
    "wof:placetype":"locality"
},
  "geometry": {"coordinates":[36.49956,34.7977],"type":"Point"}
}