{
  "type": "Feature",
  "properties": {
    "gn:admin1_code":"10.0",
    "gn:asciiname":"Mas`adah",
    "gn:country_code":"SY",
    "gn:dem":598,
    "gn:feature_class":"P",
    "gn:feature_code":"PPL",
    "gn:name":"Mas\u2018adah",
    "gn:population":0,
    "gn:timezone":"Asia/Damascus",
    "iso:country":"SY",
    "name:ara_x_preferred":[
        "\u0645\u0633\u0639\u062f\u0629"
    ],
    "name:und_x_variant":[
        "Massaad\u00e9",
        "Mas\u2018adah"
    ],
    "wof:name":"Mas`adah",
    "wof:placetype":"locality"
},
  "geometry": {"coordinates":[37.37944,35.10979],"type":"Point"}
}