{
  "type": "Feature",
  "properties": {
    "gn:admin1_code":"10.0",
    "gn:asciiname":"`Aliyat al Qastal",
    "gn:country_code":"SY",
    "gn:dem":627,
    "gn:feature_class":"P",
    "gn:feature_code":"PPL",
    "gn:name":"\u2018Al\u012byat al Qas\u0163al",
    "gn:population":0,
    "gn:timezone":"Asia/Damascus",
    "iso:country":"SY",
    "name:ara_x_preferred":[
        "\u0639\u0644\u064a\u0629 \u0627\u0644\u0642\u0633\u0637\u0644"
    ],
    "name:und_x_variant":[
        "\u2018Al\u012byat al Qas\u0163al"
    ],
    "wof:name":"`Aliyat al Qastal",
    "wof:placetype":"locality"
},
  "geometry": {"coordinates":[37.59418,35.07393],"type":"Point"}
}