{
  "type": "Feature",
  "properties": {
    "gn:admin1_code":"6.0",
    "gn:asciiname":"Ma`raba",
    "gn:country_code":"SY",
    "gn:dem":773,
    "gn:feature_class":"P",
    "gn:feature_code":"PPL",
    "gn:name":"Ma\u2018rab\u0101",
    "gn:population":0,
    "gn:timezone":"Asia/Damascus",
    "iso:country":"SY",
    "name:ara_x_preferred":[
        "\u0645\u0639\u0631\u0628\u0627"
    ],
    "name:ara_x_variant":[
        "\u0645\u0639\u0631\u0628\u0629"
    ],
    "name:und_x_variant":[
        "Maaraba",
        "Ma\u2018rab\u0101",
        "Mu\u2018arrabah"
    ],
    "wof:name":"Ma`raba",
    "wof:placetype":"locality"
},
  "geometry": {"coordinates":[36.42609,32.54640999999999],"type":"Point"}
}