{
  "type": "Feature",
  "properties": {
    "gn:admin1_code":"3.0",
    "gn:asciiname":"`Umrat al Fawwar",
    "gn:country_code":"SY",
    "gn:dem":956,
    "gn:feature_class":"P",
    "gn:feature_code":"PPL",
    "gn:name":"\u2018Umrat al Faww\u0101r",
    "gn:population":0,
    "gn:timezone":"Asia/Damascus",
    "iso:country":"SY",
    "name:ara_x_preferred":[
        "\u0639\u0645\u0631\u0629 \u0627\u0644\u0641\u0648\u0651\u0627\u0631"
    ],
    "name:und_x_variant":[
        "\u2018Umrat al Faww\u0101r"
    ],
    "wof:name":"`Umrat al Fawwar",
    "wof:placetype":"locality"
},
  "geometry": {"coordinates":[35.92144000000001,33.23513],"type":"Point"}
}