{
  "type": "Feature",
  "properties": {
    "gn:admin1_code":"11.0",
    "gn:asciiname":"Tall Jirdawn",
    "gn:country_code":"SY",
    "gn:dem":438,
    "gn:feature_class":"P",
    "gn:feature_code":"PPL",
    "gn:name":"Tall Jirdawn",
    "gn:population":0,
    "gn:timezone":"Asia/Damascus",
    "iso:country":"SY",
    "name:ara_x_preferred":[
        "\u062a\u0644 \u062c\u0631\u062f\u0648\u0646"
    ],
    "name:und_x_variant":[
        "Tell Jardon",
        "Tell Jardoun",
        "Tall Jirdawn"
    ],
    "wof:name":"Tall Jirdawn",
    "wof:placetype":"locality"
},
  "geometry": {"coordinates":[36.39173,34.72098],"type":"Point"}
}