{
  "type": "Feature",
  "properties": {
    "gn:admin1_code":"9.0",
    "gn:asciiname":"Umm Hawsh",
    "gn:country_code":"SY",
    "gn:dem":463,
    "gn:feature_class":"P",
    "gn:feature_code":"PPL",
    "gn:name":"Umm \u1e28awsh",
    "gn:population":0,
    "gn:timezone":"Asia/Damascus",
    "iso:country":"SY",
    "name:ara_x_preferred":[
        "\u0645\u0639\u0631\u0627\u062a \u0623\u0645 \u062d\u0648\u0634"
    ],
    "name:ara_x_variant":[
        "\u0623\u0645 \u062d\u0648\u0634",
        "\u0645\u0639\u0631\u0627\u062a\u0629 \u0623\u0645 \u062d\u0648\u0634"
    ],
    "name:und_x_variant":[
        "Maarta Oum el Hoch",
        "Maarret oum Haouch",
        "Ma\u2018arrat Umm al \u1e28awsh",
        "Ma\u2018arr\u0101t Umm \u1e28awsh",
        "Umm \u1e28awsh",
        "Ma\u2018arr\u0101tat Umm \u1e28awsh",
        "Ma\u2018r\u0101tat Umm \u1e28awsh"
    ],
    "wof:name":"Umm Hawsh",
    "wof:placetype":"locality"
},
  "geometry": {"coordinates":[37.21252,36.41168],"type":"Point"}
}