{
  "type": "Feature",
  "properties": {
    "gn:admin1_code":"11.0",
    "gn:asciiname":"Hisya",
    "gn:country_code":"SY",
    "gn:dem":780,
    "gn:feature_class":"P",
    "gn:feature_code":"PPLA3",
    "gn:name":"Hisya",
    "gn:population":0,
    "gn:timezone":"Asia/Damascus",
    "iso:country":"SY",
    "name:ara_x_preferred":[
        "\u062d\u0633\u064a\u0629"
    ],
    "name:ara_x_variant":[
        "\u1e28isy\u0101",
        "\u062d\u0633\u064a\u0627",
        "\u1e28isy\u0101\u2019",
        "\u062d\u0633\u064a\u0627\u0621"
    ],
    "name:ceb_x_preferred":[
        "Hisya"
    ],
    "name:fas_x_preferred":[
        "\u062d\u0633\u06cc\u0627\u0621"
    ],
    "name:fra_x_preferred":[
        "Hisyah"
    ],
    "name:nno_x_preferred":[
        "Hisyah"
    ],
    "name:pol_x_preferred":[
        "Hisja"
    ],
    "name:rus_x_preferred":[
        "\u0425\u0438\u0441\u044c\u044f"
    ],
    "name:und_x_variant":[
        "Hassy\u00e9",
        "Hisya",
        "Hasiya",
        "\u1e28is\u012byah",
        "Hassi\u00e9",
        "\u1e28asyah",
        "\u1e28isyah"
    ],
    "name:vie_x_preferred":[
        "Hisyah"
    ],
    "wof:name":"Hisya",
    "wof:placetype":"locality"
},
  "geometry": {"coordinates":[36.75867,34.41197],"type":"Point"}
}