{
  "type": "Feature",
  "properties": {
    "gn:admin1_code":"12.0",
    "gn:asciiname":"Shaykh Barakah",
    "gn:country_code":"SY",
    "gn:dem":421,
    "gn:feature_class":"P",
    "gn:feature_code":"PPL",
    "gn:name":"Shaykh Barakah",
    "gn:population":0,
    "gn:timezone":"Asia/Damascus",
    "iso:country":"SY",
    "name:ara_x_preferred":[
        "\u0634\u064a\u062e \u0628\u0631\u0643\u0629"
    ],
    "name:und_x_variant":[
        "Che\u00efkh Barak\u00e9",
        "Ash Shaykh Barakah",
        "Shaykh Barakah",
        "Sheikh Barakeh"
    ],
    "wof:name":"Shaykh Barakah",
    "wof:placetype":"locality"
},
  "geometry": {"coordinates":[36.97974,35.55970999999999],"type":"Point"}
}