{
  "type": "Feature",
  "properties": {
    "gn:admin1_code":"1.0",
    "gn:asciiname":"Khirbat Hamma",
    "gn:country_code":"SY",
    "gn:dem":340,
    "gn:feature_class":"P",
    "gn:feature_code":"PPL",
    "gn:name":"Khirbat \u1e28amm\u00e1",
    "gn:population":0,
    "gn:timezone":"Asia/Damascus",
    "iso:country":"SY",
    "name:ara_x_preferred":[
        "\u062e\u0631\u0628\u0629 \u062d\u0645\u0649"
    ],
    "name:und_x_variant":[
        "Kheurbet Hamma",
        "Khirbat \u1e28ammah",
        "Khirbat \u1e28amm\u00e1"
    ],
    "wof:name":"Khirbat Hamma",
    "wof:placetype":"locality"
},
  "geometry": {"coordinates":[40.70586,36.55964],"type":"Point"}
}