{
  "type": "Feature",
  "properties": {
    "gn:admin1_code":"4.0",
    "gn:asciiname":"At Tabaqah",
    "gn:country_code":"SY",
    "gn:dem":342,
    "gn:feature_class":"P",
    "gn:feature_code":"PPL",
    "gn:name":"A\u0163 \u0162abaqah",
    "gn:population":0,
    "gn:timezone":"Asia/Damascus",
    "iso:country":"SY",
    "name:ara_x_preferred":[
        "\u0627\u0644\u0637\u0628\u0642\u0629"
    ],
    "name:und_x_variant":[
        "A\u0163 \u0162abaqah"
    ],
    "wof:name":"At Tabaqah",
    "wof:placetype":"locality"
},
  "geometry": {"coordinates":[38.54811,35.8373],"type":"Point"}
}