{
  "type": "Feature",
  "properties": {
    "gn:admin1_code":"7.0",
    "gn:asciiname":"Tabarayya",
    "gn:country_code":"SY",
    "gn:dem":227,
    "gn:feature_class":"P",
    "gn:feature_code":"PPL",
    "gn:name":"\u0162abarayy\u0101",
    "gn:population":0,
    "gn:timezone":"Asia/Damascus",
    "iso:country":"SY",
    "name:ara_x_preferred":[
        "\u0637\u0628\u0631\u064a\u0627"
    ],
    "name:und_x_variant":[
        "\u0162abarayy\u0101",
        "\u0162abriy\u0101"
    ],
    "wof:name":"Tabarayya",
    "wof:placetype":"locality"
},
  "geometry": {"coordinates":[40.68048,35.57791],"type":"Point"}
}