{
  "type": "Feature",
  "properties": {
    "gn:admin1_code":"10.0",
    "gn:asciiname":"Shaykh Hadid",
    "gn:country_code":"SY",
    "gn:dem":202,
    "gn:feature_class":"P",
    "gn:feature_code":"PPL",
    "gn:name":"Shaykh \u1e28ad\u012bd",
    "gn:population":0,
    "gn:timezone":"Asia/Damascus",
    "iso:country":"SY",
    "name:ara_x_preferred":[
        "\u0634\u064a\u062e \u062d\u062f\u064a\u062f"
    ],
    "name:ara_x_variant":[
        "\u0627\u0644\u0634\u064a\u062e \u062d\u062f\u064a\u062f"
    ],
    "name:fas_x_preferred":[
        "\u0627\u0644\u0634\u06cc\u062e \u062d\u062f\u06cc\u062f"
    ],
    "name:pol_x_preferred":[
        "Szajch Hadid"
    ],
    "name:und_x_variant":[
        "Shaykh \u1e28ad\u012bd",
        "Che\u012bkh Had\u00eed",
        "Ash Shaykh \u1e28ad\u012bd"
    ],
    "name:vie_x_preferred":[
        "Shaykh Hadid"
    ],
    "wof:name":"Shaykh Hadid",
    "wof:placetype":"locality"
},
  "geometry": {"coordinates":[36.48286,35.35242],"type":"Point"}
}