{
  "type": "Feature",
  "properties": {
    "gn:admin1_code":"11.0",
    "gn:asciiname":"Dalfin",
    "gn:country_code":"SY",
    "gn:dem":378,
    "gn:feature_class":"P",
    "gn:feature_code":"PPL",
    "gn:name":"Dalf\u012bn",
    "gn:population":0,
    "gn:timezone":"Asia/Damascus",
    "iso:country":"SY",
    "name:ara_x_preferred":[
        "\u062f\u0644\u0641\u064a\u0646"
    ],
    "name:und_x_variant":[
        "Dalf\u012bn"
    ],
    "wof:name":"Dalfin",
    "wof:placetype":"locality"
},
  "geometry": {"coordinates":[36.89368,34.96875],"type":"Point"}
}