{
  "type": "Feature",
  "properties": {
    "gn:admin1_code":"2.0",
    "gn:asciiname":"Bayt Tawuj",
    "gn:country_code":"SY",
    "gn:dem":143,
    "gn:feature_class":"P",
    "gn:feature_code":"PPL",
    "gn:name":"Bayt T\u0101w\u016bj",
    "gn:population":0,
    "gn:timezone":"Asia/Damascus",
    "iso:country":"SY",
    "name:ara_x_preferred":[
        "\u0628\u064a\u062a \u062a\u0627\u0648\u0648\u062c"
    ],
    "name:ara_x_variant":[
        "\u0628\u064a\u062a \u0646\u0648\u0627\u062c\u0629"
    ],
    "name:und_x_variant":[
        "Be\u00eft T\u00e2o\u00fbj",
        "Bayt T\u0101w\u016bj",
        "Be\u00eft Nou\u00e2ji",
        "Be\u00eft Nou\u00e2j\u00e9",
        "Bayt Nu\u2019\u0101jah",
        "Bayt Naww\u0101jah",
        "Bayt Nuw\u0101jah"
    ],
    "wof:name":"Bayt Tawuj",
    "wof:placetype":"locality"
},
  "geometry": {"coordinates":[35.93058,35.72552],"type":"Point"}
}