{
  "type": "Feature",
  "properties": {
    "gn:admin1_code":"1.0",
    "gn:asciiname":"Shurak",
    "gn:cc2":"SY",
    "gn:country_code":"SY",
    "gn:dem":424,
    "gn:feature_class":"P",
    "gn:feature_code":"PPL",
    "gn:name":"Sh\u016brak",
    "gn:population":0,
    "gn:timezone":"Asia/Damascus",
    "iso:country":"SY",
    "name:tur_x_preferred":[
        "Sh\u016brak"
    ],
    "name:und_x_variant":[
        "Cho\u00fbrek"
    ],
    "wof:name":"Shurak",
    "wof:placetype":"locality"
},
  "geometry": {"coordinates":[41.35,37.05],"type":"Point"}
}