{
  "type": "Feature",
  "properties": {
    "gn:admin1_code":"10.0",
    "gn:asciiname":"Shathah",
    "gn:country_code":"SY",
    "gn:dem":207,
    "gn:feature_class":"P",
    "gn:feature_code":"PPLA3",
    "gn:name":"Sha\u0163\u1e29ah",
    "gn:population":0,
    "gn:timezone":"Asia/Damascus",
    "iso:country":"SY",
    "name:ara_x_preferred":[
        "\u0634\u0637\u062d\u0629 \u0627\u0644\u062a\u062d\u062a\u0627"
    ],
    "name:ara_x_variant":[
        "\u0634\u0637\u062d\u0629"
    ],
    "name:ceb_x_preferred":[
        "Sha\u0163\u1e29ah"
    ],
    "name:fas_x_preferred":[
        "\u0634\u0637\u062d\u0647"
    ],
    "name:hye_x_preferred":[
        "\u0547\u0561\u057f\u0570\u0561"
    ],
    "name:nno_x_preferred":[
        "Shathah"
    ],
    "name:pol_x_preferred":[
        "Szatha at-Tahta"
    ],
    "name:rus_x_preferred":[
        "\u0428\u0430\u0442\u0445\u0430"
    ],
    "name:sco_x_preferred":[
        "Shathah"
    ],
    "name:und_x_variant":[
        "Chat\u2019 ha ett Tahta",
        "Sha\u0163\u1e29ah at Ta\u1e29t\u0101\u2019",
        "Sha\u0163\u1e29ah at Ta\u1e29t\u0101",
        "Sha\u0163\u1e29at at Ta\u1e29t\u0101"
    ],
    "name:vie_x_preferred":[
        "Shathah"
    ],
    "wof:name":"Shathah",
    "wof:placetype":"locality"
},
  "geometry": {"coordinates":[36.24377,35.50509],"type":"Point"}
}