{
  "type": "Feature",
  "properties": {
    "gn:admin1_code":"10.0",
    "gn:asciiname":"`Abd Allah al Kilani",
    "gn:country_code":"SY",
    "gn:dem":397,
    "gn:feature_class":"P",
    "gn:feature_code":"PPL",
    "gn:name":"\u2018Abd All\u0101h al K\u012bl\u0101n\u012b",
    "gn:population":0,
    "gn:timezone":"Asia/Damascus",
    "iso:country":"SY",
    "name:ara_x_preferred":[
        "\u0639\u0628\u062f \u0627\u0644\u0644\u0647 \u0627\u0644\u0643\u064a\u0644\u0627\u0646\u064a"
    ],
    "name:und_x_variant":[
        "\u2018Abd All\u0101h al K\u012bl\u0101n\u012b"
    ],
    "wof:name":"`Abd Allah al Kilani",
    "wof:placetype":"locality"
},
  "geometry": {"coordinates":[36.82462,35.18705999999999],"type":"Point"}
}