{
  "type": "Feature",
  "properties": {
    "gn:admin1_code":"10.0",
    "gn:asciiname":"Kawkab",
    "gn:country_code":"SY",
    "gn:dem":373,
    "gn:feature_class":"P",
    "gn:feature_code":"PPL",
    "gn:name":"Kawkab",
    "gn:population":0,
    "gn:timezone":"Asia/Damascus",
    "iso:country":"SY",
    "name:ara_x_preferred":[
        "\u0643\u0648\u0643\u0628"
    ],
    "name:und_x_variant":[
        "Kaukab",
        "Keukeb",
        "Kukeb",
        "Kaoukab",
        "Kawkab"
    ],
    "wof:name":"Kawkab",
    "wof:placetype":"locality"
},
  "geometry": {"coordinates":[36.8029,35.29973],"type":"Point"}
}