{
  "type": "Feature",
  "properties": {
    "gn:admin1_code":"8.0",
    "gn:asciiname":"Buzaynah",
    "gn:country_code":"SY",
    "gn:dem":632,
    "gn:feature_class":"P",
    "gn:feature_code":"PPL",
    "gn:name":"Buzaynah",
    "gn:population":0,
    "gn:timezone":"Asia/Damascus",
    "iso:country":"SY",
    "name:ara_x_preferred":[
        "\u0628\u0632\u064a\u0646\u0629"
    ],
    "name:und_x_variant":[
        "Bz\u00e9n\u00e9",
        "Bza\u00efn\u00e9",
        "Buzaynah"
    ],
    "wof:name":"Buzaynah",
    "wof:placetype":"locality"
},
  "geometry": {"coordinates":[36.44022,33.48288],"type":"Point"}
}