{
  "type": "Feature",
  "properties": {
    "gn:admin1_code":"4.0",
    "gn:asciiname":"Fatsat `Abd Isma`il",
    "gn:country_code":"SY",
    "gn:dem":236,
    "gn:feature_class":"P",
    "gn:feature_code":"PPL",
    "gn:name":"Fa\u0163sat \u2018Abd Ism\u0101\u2018\u012bl",
    "gn:population":0,
    "gn:timezone":"Asia/Damascus",
    "iso:country":"SY",
    "name:ara_x_preferred":[
        "\u0641\u0637\u0633\u0629 \u0639\u0628\u062f \u0627\u0633\u0645\u0627\u0639\u064a\u0644"
    ],
    "name:und_x_variant":[
        "Fa\u0163sat \u2018Abd Ism\u0101\u2018\u012bl"
    ],
    "wof:name":"Fatsat `Abd Isma`il",
    "wof:placetype":"locality"
},
  "geometry": {"coordinates":[39.32761,35.85408],"type":"Point"}
}