{
  "type": "Feature",
  "properties": {
    "gn:admin1_code":"14.0",
    "gn:asciiname":"Dahr Bashir",
    "gn:country_code":"SY",
    "gn:dem":254,
    "gn:feature_class":"P",
    "gn:feature_code":"PPL",
    "gn:name":"\u1e10ahr Bash\u012br",
    "gn:population":0,
    "gn:timezone":"Asia/Damascus",
    "iso:country":"SY",
    "name:ara_x_preferred":[
        "\u0636\u0647\u0631 \u0628\u0634\u064a\u0631"
    ],
    "name:und_x_variant":[
        "Dahr Bch\u00eer",
        "\u1e10ahr Bash\u012br"
    ],
    "wof:name":"Dahr Bashir",
    "wof:placetype":"locality"
},
  "geometry": {"coordinates":[36.07986,34.74588],"type":"Point"}
}