{
  "type": "Feature",
  "properties": {
    "gn:admin1_code":"10.0",
    "gn:asciiname":"Tarfawi",
    "gn:country_code":"SY",
    "gn:dem":285,
    "gn:feature_class":"P",
    "gn:feature_code":"PPL",
    "gn:name":"\u0162arf\u0101w\u012b",
    "gn:population":0,
    "gn:timezone":"Asia/Damascus",
    "iso:country":"SY",
    "name:ara_x_preferred":[
        "\u0637\u0631\u0641\u0627\u0648\u064a"
    ],
    "name:ara_x_variant":[
        "\u0627\u0644\u0637\u0631\u0641\u0627\u0648\u064a"
    ],
    "name:fas_x_preferred":[
        "\u0627\u0644\u0637\u0631\u0641\u0627\u0648\u06cc"
    ],
    "name:pol_x_preferred":[
        "At-Tarfawi"
    ],
    "name:und_x_variant":[
        "Terf\u00e2oui",
        "\u0162arf\u0101w\u012b"
    ],
    "name:vie_x_preferred":[
        "Tarfawi"
    ],
    "wof:name":"Tarfawi",
    "wof:placetype":"locality"
},
  "geometry": {"coordinates":[37.20419,35.53426],"type":"Point"}
}