{
  "type": "Feature",
  "properties": {
    "gn:admin1_code":"1.0",
    "gn:asciiname":"Umm al Masamir",
    "gn:country_code":"SY",
    "gn:dem":368,
    "gn:feature_class":"P",
    "gn:feature_code":"PPL",
    "gn:name":"Umm al Mas\u0101m\u012br",
    "gn:population":0,
    "gn:timezone":"Asia/Damascus",
    "iso:country":"SY",
    "name:ara_x_preferred":[
        "\u0627\u0645 \u0627\u0644\u0645\u0633\u0627\u0645\u064a\u0631"
    ],
    "name:und_x_variant":[
        "Oum el Mass\u00e2m\u00eer",
        "Umm al Mas\u0101m\u012br"
    ],
    "wof:name":"Umm al Masamir",
    "wof:placetype":"locality"
},
  "geometry": {"coordinates":[40.58175,36.66395],"type":"Point"}
}