{
  "type": "Feature",
  "properties": {
    "gn:admin1_code":"14.0",
    "gn:asciiname":"Al Mubarakah",
    "gn:country_code":"SY",
    "gn:dem":156,
    "gn:feature_class":"P",
    "gn:feature_code":"PPL",
    "gn:name":"Al Mub\u0101rakah",
    "gn:population":0,
    "gn:timezone":"Asia/Damascus",
    "iso:country":"SY",
    "name:ara_x_preferred":[
        "\u0627\u0644\u0645\u0628\u0627\u0631\u0643\u0629"
    ],
    "name:und_x_variant":[
        "Al Mub\u0101rakah"
    ],
    "wof:name":"Al Mubarakah",
    "wof:placetype":"locality"
},
  "geometry": {"coordinates":[35.99094,34.87934],"type":"Point"}
}