{
  "type": "Feature",
  "properties": {
    "gn:admin1_code":"7.0",
    "gn:asciiname":"As Safafinah",
    "gn:country_code":"SY",
    "gn:dem":173,
    "gn:feature_class":"P",
    "gn:feature_code":"PPL",
    "gn:name":"A\u015f \u015eaf\u0101finah",
    "gn:population":0,
    "gn:timezone":"Asia/Damascus",
    "iso:country":"SY",
    "name:ara_x_preferred":[
        "\u0627\u0644\u0635\u0641\u0627\u0641\u0646\u0629"
    ],
    "name:und_x_variant":[
        "A\u015f \u015eaf\u0101qinah",
        "A\u015f \u015eaf\u0101finah"
    ],
    "wof:name":"As Safafinah",
    "wof:placetype":"locality"
},
  "geometry": {"coordinates":[40.945,34.49472],"type":"Point"}
}