{
  "type": "Feature",
  "properties": {
    "gn:admin1_code":"2.0",
    "gn:asciiname":"Jibul",
    "gn:country_code":"SY",
    "gn:dem":568,
    "gn:feature_class":"P",
    "gn:feature_code":"PPL",
    "gn:name":"J\u012bb\u016bl",
    "gn:population":0,
    "gn:timezone":"Asia/Damascus",
    "iso:country":"SY",
    "name:ara_x_preferred":[
        "J\u012bb\u016bl"
    ],
    "name:ara_x_variant":[
        "\u062c\u064a\u0628\u0648\u0644"
    ],
    "name:und_x_variant":[
        "Jibail",
        "J\u00eebo\u00fbl"
    ],
    "wof:name":"Jibul",
    "wof:placetype":"locality"
},
  "geometry": {"coordinates":[36.08732,35.2824],"type":"Point"}
}