{
  "type": "Feature",
  "properties": {
    "gn:admin1_code":"1.0",
    "gn:asciiname":"Tall Jammal",
    "gn:country_code":"SY",
    "gn:dem":479,
    "gn:feature_class":"P",
    "gn:feature_code":"PPL",
    "gn:name":"Tall Jamm\u0101l",
    "gn:population":0,
    "gn:timezone":"Asia/Damascus",
    "iso:country":"SY",
    "name:ara_x_preferred":[
        "\u062a\u0644 \u062c\u0645\u0627\u0644"
    ],
    "name:und_x_variant":[
        "Tell Jamm\u00e2l",
        "Tall Jamm\u0101l"
    ],
    "wof:name":"Tall Jammal",
    "wof:placetype":"locality"
},
  "geometry": {"coordinates":[41.99521,37.04825],"type":"Point"}
}