{
  "type": "Feature",
  "properties": {
    "gn:admin1_code":"1.0",
    "gn:asciiname":"Naf Kur",
    "gn:country_code":"SY",
    "gn:dem":455,
    "gn:feature_class":"P",
    "gn:feature_code":"PPL",
    "gn:name":"N\u0101f K\u016br",
    "gn:population":0,
    "gn:timezone":"Asia/Damascus",
    "iso:country":"SY",
    "name:ara_x_preferred":[
        "\u0646\u0627\u0641 \u0643\u0648\u0631"
    ],
    "name:tur_x_preferred":[
        "N\u0101f K\u016br"
    ],
    "name:und_x_variant":[
        "N\u00e2f Kour"
    ],
    "wof:name":"Naf Kur",
    "wof:placetype":"locality"
},
  "geometry": {"coordinates":[41.1567,37.05367],"type":"Point"}
}