{
  "type": "Feature",
  "properties": {
    "gn:admin1_code":"9.0",
    "gn:asciiname":"Jamus Wiran",
    "gn:cc2":"SY",
    "gn:country_code":"SY",
    "gn:dem":484,
    "gn:feature_class":"P",
    "gn:feature_code":"PPL",
    "gn:name":"J\u0101m\u016bs W\u012br\u0101n",
    "gn:population":0,
    "gn:timezone":"Asia/Damascus",
    "iso:country":"SY",
    "name:ara_x_preferred":[
        "J\u0101m\u016bs W\u012br\u0101n"
    ],
    "name:und_x_variant":[
        "Djamous Virane",
        "J\u00e2mo\u00fbs V\u00eer\u00e2ne"
    ],
    "wof:name":"Jamus Wiran",
    "wof:placetype":"locality"
},
  "geometry": {"coordinates":[37.78333,36.56667],"type":"Point"}
}