{
  "type": "Feature",
  "properties": {
    "gn:admin1_code":"9.0",
    "gn:asciiname":"Shaykh Bilal",
    "gn:country_code":"SY",
    "gn:dem":680,
    "gn:feature_class":"P",
    "gn:feature_code":"PPL",
    "gn:name":"Shaykh Bil\u0101l",
    "gn:population":0,
    "gn:timezone":"Asia/Damascus",
    "iso:country":"SY",
    "name:ara_x_preferred":[
        "\u0634\u064a\u062e \u0628\u0644\u0627\u0644"
    ],
    "name:und_x_variant":[
        "Shaykh Bil\u0101l"
    ],
    "wof:name":"Shaykh Bilal",
    "wof:placetype":"locality"
},
  "geometry": {"coordinates":[36.71773,36.66014000000001],"type":"Point"}
}