{
  "type": "Feature",
  "properties": {
    "gn:admin1_code":"1.0",
    "gn:asciiname":"Awkir Fawqani",
    "gn:country_code":"SY",
    "gn:dem":373,
    "gn:feature_class":"P",
    "gn:feature_code":"PPL",
    "gn:name":"Awk\u012br Fawq\u0101n\u012b",
    "gn:population":0,
    "gn:timezone":"Asia/Damascus",
    "iso:country":"SY",
    "name:ara_x_preferred":[
        "\u0623\u0648\u0643\u064a\u0631 \u0641\u0648\u0642\u0627\u0646\u064a"
    ],
    "name:tur_x_preferred":[
        "Awk\u012br Fawq\u0101n\u012b"
    ],
    "name:und_x_variant":[
        "Awk\u012br Fawq\u0101n\u012b"
    ],
    "wof:name":"Awkir Fawqani",
    "wof:placetype":"locality"
},
  "geometry": {"coordinates":[40.825,36.78056],"type":"Point"}
}