{
  "type": "Feature",
  "properties": {
    "gn:admin1_code":"1.0",
    "gn:asciiname":"Tall Rajab",
    "gn:country_code":"SY",
    "gn:dem":359,
    "gn:feature_class":"P",
    "gn:feature_code":"PPL",
    "gn:name":"Tall Rajab",
    "gn:population":0,
    "gn:timezone":"Asia/Damascus",
    "iso:country":"SY",
    "name:ara_x_preferred":[
        "\u062a\u0644 \u0631\u062c\u0628"
    ],
    "name:und_x_variant":[
        "Tell Rajab",
        "Tall Rajab"
    ],
    "wof:name":"Tall Rajab",
    "wof:placetype":"locality"
},
  "geometry": {"coordinates":[40.5974,36.71053],"type":"Point"}
}