{
  "type": "Feature",
  "properties": {
    "gn:admin1_code":"2.0",
    "gn:asciiname":"Ad Da`thur",
    "gn:country_code":"SY",
    "gn:dem":75,
    "gn:feature_class":"P",
    "gn:feature_code":"PPL",
    "gn:name":"Ad Da\u2018th\u016br",
    "gn:population":0,
    "gn:timezone":"Asia/Damascus",
    "iso:country":"SY",
    "name:ara_x_preferred":[
        "\u0627\u0644\u062f\u0639\u062b\u0648\u0631"
    ],
    "name:und_x_variant":[
        "Ad Da\u2018th\u016br"
    ],
    "wof:name":"Ad Da`thur",
    "wof:placetype":"locality"
},
  "geometry": {"coordinates":[35.94726,35.61378],"type":"Point"}
}