{
  "type": "Feature",
  "properties": {
    "gn:admin1_code":"11.0",
    "gn:asciiname":"Al Khulaylah",
    "gn:country_code":"SY",
    "gn:dem":839,
    "gn:feature_class":"P",
    "gn:feature_code":"PPL",
    "gn:name":"Al Khulaylah",
    "gn:population":0,
    "gn:timezone":"Asia/Damascus",
    "iso:country":"SY",
    "name:ara_x_preferred":[
        "\u0627\u0644\u062e\u0644\u064a\u0644\u0629"
    ],
    "wof:name":"Al Khulaylah",
    "wof:placetype":"locality"
},
  "geometry": {"coordinates":[37.23185,34.6632],"type":"Point"}
}