{
  "type": "Feature",
  "properties": {
    "gn:admin1_code":"9.0",
    "gn:asciiname":"Khirbat Hawish",
    "gn:country_code":"SY",
    "gn:dem":276,
    "gn:feature_class":"P",
    "gn:feature_code":"PPL",
    "gn:name":"Khirbat \u1e28aw\u012bsh",
    "gn:population":0,
    "gn:timezone":"Asia/Damascus",
    "iso:country":"SY",
    "name:ara_x_preferred":[
        "\u062e\u0631\u0628\u0629 \u062d\u0648\u064a\u0634"
    ],
    "name:und_x_variant":[
        "Khirbat \u1e28aw\u012bsh"
    ],
    "wof:name":"Khirbat Hawish",
    "wof:placetype":"locality"
},
  "geometry": {"coordinates":[37.45935,35.68129000000001],"type":"Point"}
}