{
  "type": "Feature",
  "properties": {
    "gn:admin1_code":"7.0",
    "gn:asciiname":"An Namliyah",
    "gn:country_code":"SY",
    "gn:dem":221,
    "gn:feature_class":"P",
    "gn:feature_code":"PPL",
    "gn:name":"An Naml\u012byah",
    "gn:population":0,
    "gn:timezone":"Asia/Damascus",
    "iso:country":"SY",
    "name:ara_x_preferred":[
        "\u0627\u0644\u0646\u0645\u0644\u064a\u0629"
    ],
    "name:und_x_variant":[
        "An Naml\u012byah"
    ],
    "wof:name":"An Namliyah",
    "wof:placetype":"locality"
},
  "geometry": {"coordinates":[40.65606,35.45002],"type":"Point"}
}