{
  "type": "Feature",
  "properties": {
    "gn:admin1_code":"1.0",
    "gn:asciiname":"Kur Suwar",
    "gn:country_code":"SY",
    "gn:dem":395,
    "gn:feature_class":"P",
    "gn:feature_code":"PPL",
    "gn:name":"K\u016br Suw\u0101r",
    "gn:population":0,
    "gn:timezone":"Asia/Damascus",
    "iso:country":"SY",
    "name:ara_x_preferred":[
        "\u0643\u0648\u0631 \u0633\u0648\u0627\u0631"
    ],
    "name:tur_x_preferred":[
        "K\u012br\u012b Suw\u0101r"
    ],
    "name:und_x_variant":[
        "Guir So\u00fbar",
        "K\u016br Suw\u0101r",
        "Guiri Sou\u00e2r",
        "K\u012br Suw\u0101r"
    ],
    "wof:name":"Kur Suwar",
    "wof:placetype":"locality"
},
  "geometry": {"coordinates":[41.44262,36.99515],"type":"Point"}
}