{
  "type": "Feature",
  "properties": {
    "gn:admin1_code":"8.0",
    "gn:asciiname":"Ibrahim Zayn ad Din",
    "gn:country_code":"SY",
    "gn:dem":631,
    "gn:feature_class":"P",
    "gn:feature_code":"PPLL",
    "gn:name":"Ibr\u0101h\u012bm Zayn ad D\u012bn",
    "gn:population":0,
    "gn:timezone":"Asia/Damascus",
    "iso:country":"SY",
    "name:ara_x_preferred":[
        "\u0627\u0628\u0631\u0627\u0647\u064a\u0645 \u0632\u064a\u0646 \u0627\u0644\u062f\u064a\u0646"
    ],
    "name:und_x_variant":[
        "Ibr\u0101h\u012bm Zayn ad D\u012bn"
    ],
    "wof:name":"Ibrahim Zayn ad Din",
    "wof:placetype":"locality"
},
  "geometry": {"coordinates":[36.57924000000001,33.64226],"type":"Point"}
}