{
  "type": "Feature",
  "properties": {
    "gn:admin1_code":"9.0",
    "gn:asciiname":"Sukkariyah Kabirah",
    "gn:country_code":"SY",
    "gn:dem":470,
    "gn:feature_class":"P",
    "gn:feature_code":"PPL",
    "gn:name":"Sukkar\u012byah Kab\u012brah",
    "gn:population":0,
    "gn:timezone":"Asia/Damascus",
    "iso:country":"SY",
    "name:ara_x_preferred":[
        "\u0633\u0643\u0631\u064a\u0629 \u0643\u0628\u064a\u0631\u0629"
    ],
    "name:und_x_variant":[
        "Soukkariy\u00e9 el K\u00e9b\u00eere",
        "Sukkar\u012byah",
        "Sukkar\u012byih al Kab\u012brih",
        "Sukkar\u012byah al Kubr\u00e1",
        "Sukkar\u012byah Kab\u012brah"
    ],
    "wof:name":"Sukkariyah Kabirah",
    "wof:placetype":"locality"
},
  "geometry": {"coordinates":[37.7199,36.3968],"type":"Point"}
}