{
  "type": "Feature",
  "properties": {
    "gn:admin1_code":"1.0",
    "gn:asciiname":"Sanjaq Sa`dun",
    "gn:country_code":"SY",
    "gn:dem":433,
    "gn:feature_class":"P",
    "gn:feature_code":"PPL",
    "gn:name":"Sanjaq Sa\u2018d\u016bn",
    "gn:population":0,
    "gn:timezone":"Asia/Damascus",
    "iso:country":"SY",
    "name:ara_x_preferred":[
        "\u0633\u0646\u062c\u0642 \u0633\u0639\u062f\u0648\u0646"
    ],
    "name:tur_x_preferred":[
        "Sanjaq Sa\u2018d\u016bn"
    ],
    "name:und_x_variant":[
        "Sanndjaq Saado\u00fbn",
        "Sanjaq Sa\u2018d\u016bn"
    ],
    "wof:name":"Sanjaq Sa`dun",
    "wof:placetype":"locality"
},
  "geometry": {"coordinates":[40.93484,37.02083],"type":"Point"}
}