{
  "type": "Feature",
  "properties": {
    "gn:admin1_code":"14.0",
    "gn:asciiname":"Huraysun",
    "gn:country_code":"SY",
    "gn:dem":23,
    "gn:feature_class":"P",
    "gn:feature_code":"PPL",
    "gn:name":"\u1e28uray\u015f\u016bn",
    "gn:population":0,
    "gn:timezone":"Asia/Damascus",
    "iso:country":"SY",
    "name:ara_x_preferred":[
        "\u062d\u0631\u064a\u0635\u0648\u0646"
    ],
    "name:ara_x_variant":[
        "\u062d\u0631\u064a\u0635\u0648\u0646 \u0627\u0644\u0642\u0627\u0645\u0648\u0639"
    ],
    "name:und_x_variant":[
        "Hra\u00efsso\u00fbn",
        "\u1e28uray\u015f\u016bn",
        "\u1e28uray\u015f\u016bn al Q\u0101m\u016b\u2018",
        "Harisun Qamue"
    ],
    "wof:name":"Huraysun",
    "wof:placetype":"locality"
},
  "geometry": {"coordinates":[35.96673,35.23645],"type":"Point"}
}