{
  "type": "Feature",
  "properties": {
    "gn:admin1_code":"2.0",
    "gn:asciiname":"Kafr `Ajuz",
    "gn:country_code":"SY",
    "gn:dem":813,
    "gn:feature_class":"P",
    "gn:feature_code":"PPL",
    "gn:name":"Kafr \u2018Aj\u016bz",
    "gn:population":0,
    "gn:timezone":"Asia/Damascus",
    "iso:country":"SY",
    "name:ara_x_preferred":[
        "\u0643\u0641\u0631 \u0639\u062c\u0648\u0632"
    ],
    "name:und_x_variant":[
        "Kafer Aajo\u00fbz",
        "Kafr Aajo\u00fbz",
        "Kafr \u2018Aj\u016bz"
    ],
    "wof:name":"Kafr `Ajuz",
    "wof:placetype":"locality"
},
  "geometry": {"coordinates":[36.15102,35.66835],"type":"Point"}
}