{
  "type": "Feature",
  "properties": {
    "gn:admin1_code":"14.0",
    "gn:asciiname":"Az Zarqat",
    "gn:country_code":"SY",
    "gn:dem":91,
    "gn:feature_class":"P",
    "gn:feature_code":"PPL",
    "gn:name":"Az Zarq\u0101t",
    "gn:population":0,
    "gn:timezone":"Asia/Damascus",
    "iso:country":"SY",
    "name:ara_x_preferred":[
        "\u0627\u0644\u0632\u0631\u0642\u0627\u062a"
    ],
    "name:und_x_variant":[
        "Zarq\u00e2te",
        "Az Zarq\u0101t"
    ],
    "wof:name":"Az Zarqat",
    "wof:placetype":"locality"
},
  "geometry": {"coordinates":[35.97091,34.82023],"type":"Point"}
}