{
  "type": "Feature",
  "properties": {
    "gn:admin1_code":"2.0",
    "gn:asciiname":"Khadlu",
    "gn:country_code":"SY",
    "gn:dem":533,
    "gn:feature_class":"P",
    "gn:feature_code":"PPL",
    "gn:name":"Khadl\u016b",
    "gn:population":0,
    "gn:timezone":"Asia/Damascus",
    "iso:country":"SY",
    "name:und_x_variant":[
        "Khadl\u016b"
    ],
    "wof:name":"Khadlu",
    "wof:placetype":"locality"
},
  "geometry": {"coordinates":[36.075,35.575],"type":"Point"}
}