{
  "type": "Feature",
  "properties": {
    "gn:admin1_code":"9.0",
    "gn:asciiname":"Shash",
    "gn:country_code":"SY",
    "gn:dem":389,
    "gn:feature_class":"P",
    "gn:feature_code":"PPL",
    "gn:name":"Sh\u0101sh",
    "gn:population":0,
    "gn:timezone":"Asia/Damascus",
    "iso:country":"SY",
    "name:ara_x_preferred":[
        "Sh\u0101sh"
    ],
    "name:ara_x_variant":[
        "\u0634\u0627\u0634"
    ],
    "name:und_x_variant":[
        "Ech Ch\u00e2ch",
        "Ch\u00e2ch"
    ],
    "wof:name":"Shash",
    "wof:placetype":"locality"
},
  "geometry": {"coordinates":[38.66785,36.59576],"type":"Point"}
}