{
  "type": "Feature",
  "properties": {
    "gn:admin1_code":"11.0",
    "gn:asciiname":"Nasriyat ar Ruwayhaniyah",
    "gn:country_code":"SY",
    "gn:dem":584,
    "gn:feature_class":"P",
    "gn:feature_code":"PPL",
    "gn:name":"Na\u015fr\u012byat ar Ruway\u1e29\u0101n\u012byah",
    "gn:population":0,
    "gn:timezone":"Asia/Damascus",
    "iso:country":"SY",
    "name:ara_x_preferred":[
        "\u0646\u0635\u0631\u064a\u0629 \u0627\u0644\u0631\u0648\u064a\u062d\u0627\u0646\u064a\u0629"
    ],
    "name:und_x_variant":[
        "Na\u015fr\u012byat ar Ruway\u1e29\u0101n\u012byah"
    ],
    "wof:name":"Nasriyat ar Ruwayhaniyah",
    "wof:placetype":"locality"
},
  "geometry": {"coordinates":[37.09071,34.86436],"type":"Point"}
}