{
  "type": "Feature",
  "properties": {
    "gn:admin1_code":"11.0",
    "gn:asciiname":"Hawalik",
    "gn:country_code":"SY",
    "gn:dem":465,
    "gn:feature_class":"P",
    "gn:feature_code":"PPL",
    "gn:name":"\u1e28aw\u0101lik",
    "gn:population":0,
    "gn:timezone":"Asia/Damascus",
    "iso:country":"SY",
    "name:ara_x_preferred":[
        "\u062d\u0648\u0627\u0644\u0643"
    ],
    "name:und_x_variant":[
        "\u1e28aw\u0101lik"
    ],
    "wof:name":"Hawalik",
    "wof:placetype":"locality"
},
  "geometry": {"coordinates":[36.64068,34.80472],"type":"Point"}
}