{
  "type": "Feature",
  "properties": {
    "gn:admin1_code":"9.0",
    "gn:asciiname":"Duwayr az Zaytun",
    "gn:country_code":"SY",
    "gn:dem":494,
    "gn:feature_class":"P",
    "gn:feature_code":"PPL",
    "gn:name":"Duwayr az Zayt\u016bn",
    "gn:population":0,
    "gn:timezone":"Asia/Damascus",
    "iso:country":"SY",
    "name:ara_x_preferred":[
        "\u062f\u0648\u064a\u0631 \u0627\u0644\u0632\u064a\u062a\u0648\u0646"
    ],
    "name:und_x_variant":[
        "Douer Zeitoune",
        "Douair Za\u00eftoun",
        "Doua\u00efr ez Za\u00efto\u00fbn",
        "Duwayr az Zayt\u016bn"
    ],
    "wof:name":"Duwayr az Zaytun",
    "wof:placetype":"locality"
},
  "geometry": {"coordinates":[37.15795,36.33343],"type":"Point"}
}