{
  "type": "Feature",
  "properties": {
    "gn:admin1_code":"1.0",
    "gn:asciiname":"Ash Shamsiyah",
    "gn:country_code":"SY",
    "gn:dem":404,
    "gn:feature_class":"P",
    "gn:feature_code":"PPL",
    "gn:name":"Ash Shams\u012byah",
    "gn:population":0,
    "gn:timezone":"Asia/Damascus",
    "iso:country":"SY",
    "name:ara_x_preferred":[
        "\u0627\u0644\u0634\u0645\u0633\u064a\u0629"
    ],
    "name:kur_x_preferred":[
        "Gir D\u00eamy\u00ea"
    ],
    "name:kur_x_variant":[
        "\u06af\u0631 \u062f\u06ce\u0645\u064a\u06ce"
    ],
    "name:und_x_variant":[
        "Ash Shams\u012byah",
        "Gir D\u00eamiy\u00ea",
        "\u0643\u0631 \u062f\u064a\u0645\u064a\u0629"
    ],
    "wof:name":"Ash Shamsiyah",
    "wof:placetype":"locality"
},
  "geometry": {"coordinates":[41.76034,36.95234],"type":"Point"}
}