{
  "type": "Feature",
  "properties": {
    "gn:admin1_code":"7.0",
    "gn:asciiname":"Al Jad`an",
    "gn:country_code":"SY",
    "gn:dem":216,
    "gn:feature_class":"P",
    "gn:feature_code":"PPL",
    "gn:name":"Al Jad\u2018\u0101n",
    "gn:population":0,
    "gn:timezone":"Asia/Damascus",
    "iso:country":"SY",
    "name:ara_x_preferred":[
        "\u0627\u0644\u062c\u062f\u0639\u0627\u0646"
    ],
    "name:und_x_variant":[
        "Al Jad\u2018\u0101n"
    ],
    "wof:name":"Al Jad`an",
    "wof:placetype":"locality"
},
  "geometry": {"coordinates":[40.59353,35.43103],"type":"Point"}
}