{
  "type": "Feature",
  "properties": {
    "gn:admin1_code":"1.0",
    "gn:asciiname":"Surka",
    "gn:country_code":"SY",
    "gn:dem":465,
    "gn:feature_class":"P",
    "gn:feature_code":"PPL",
    "gn:name":"S\u016brk\u0101",
    "gn:population":0,
    "gn:timezone":"Asia/Damascus",
    "iso:country":"SY",
    "name:ara_x_preferred":[
        "S\u016brk\u0101"
    ],
    "name:ara_x_variant":[
        "\u0633\u0648\u0631\u0643\u0627"
    ],
    "name:tur_x_preferred":[
        "\u015e\u016brkhah"
    ],
    "name:und_x_variant":[
        "Sourka"
    ],
    "wof:name":"Surka",
    "wof:placetype":"locality"
},
  "geometry": {"coordinates":[41.00155,37.09287],"type":"Point"}
}