{
  "type": "Feature",
  "properties": {
    "gn:admin1_code":"8.0",
    "gn:asciiname":"Ard Ra's Ghanim",
    "gn:country_code":"SY",
    "gn:dem":823,
    "gn:feature_class":"P",
    "gn:feature_code":"PPLL",
    "gn:name":"Ar\u1e11 Ra\u2019s Ghan\u012bm",
    "gn:population":0,
    "gn:timezone":"Asia/Damascus",
    "iso:country":"SY",
    "name:ara_x_preferred":[
        "\u0623\u0631\u0636 \u0631\u0623\u0633 \u063a\u0646\u064a\u0645"
    ],
    "name:und_x_variant":[
        "Ar\u1e11 Ra\u2019s Ghan\u012bm"
    ],
    "wof:name":"Ard Ra's Ghanim",
    "wof:placetype":"locality"
},
  "geometry": {"coordinates":[36.26131,33.55105],"type":"Point"}
}