{
  "type": "Feature",
  "properties": {
    "gn:admin1_code":"6.0",
    "gn:asciiname":"Ghariyah ash Sharqiyah",
    "gn:country_code":"SY",
    "gn:dem":595,
    "gn:feature_class":"P",
    "gn:feature_code":"PPL",
    "gn:name":"Gh\u0101riyah ash Sharq\u012byah",
    "gn:population":0,
    "gn:timezone":"Asia/Damascus",
    "iso:country":"SY",
    "name:ara_x_preferred":[
        "\u063a\u0627\u0631\u064a\u0629 \u0627\u0644\u0634\u0631\u0642\u064a\u0629"
    ],
    "name:ara_x_variant":[
        "\u063a\u0631\u064a\u0629 \u0627\u0644\u0634\u0631\u0642\u064a\u0629"
    ],
    "name:und_x_variant":[
        "Rh\u00e2riet ech Charqiye",
        "Gh\u0101riyat Sharq\u012byah",
        "Rhariye Charaiy\u00e9",
        "Es Ghariye esh Sherkiye",
        "Gh\u0101r\u012byat ash Sharq\u012byah",
        "Gh\u0101riyah ash Sharq\u012byah",
        "Ghariyah ash Sharq\u012byah"
    ],
    "wof:name":"Ghariyah ash Sharqiyah",
    "wof:placetype":"locality"
},
  "geometry": {"coordinates":[36.25809,32.67824],"type":"Point"}
}