{
  "type": "Feature",
  "properties": {
    "gn:admin1_code":"14.0",
    "gn:asciiname":"`Abd Allah `Abd ar Razzaq",
    "gn:country_code":"SY",
    "gn:dem":52,
    "gn:feature_class":"P",
    "gn:feature_code":"PPLL",
    "gn:name":"\u2018Abd All\u0101h \u2018Abd ar Razz\u0101q",
    "gn:population":0,
    "gn:timezone":"Asia/Damascus",
    "iso:country":"SY",
    "name:ara_x_preferred":[
        "\u0639\u0628\u062f \u0627\u0644\u0644\u0647 \u0639\u0628\u062f \u0627\u0644\u0631\u0632\u0627\u0642"
    ],
    "name:und_x_variant":[
        "\u2018Abd All\u0101h \u2018Abd ar Razz\u0101q"
    ],
    "wof:name":"`Abd Allah `Abd ar Razzaq",
    "wof:placetype":"locality"
},
  "geometry": {"coordinates":[35.90665999999999,34.88447],"type":"Point"}
}