{
  "type": "Feature",
  "properties": {
    "gn:admin1_code":"9.0",
    "gn:asciiname":"Judaydah",
    "gn:country_code":"SY",
    "gn:dem":326,
    "gn:feature_class":"P",
    "gn:feature_code":"PPL",
    "gn:name":"Judaydah",
    "gn:population":0,
    "gn:timezone":"Asia/Damascus",
    "iso:country":"SY",
    "name:ara_x_preferred":[
        "\u062c\u062f\u064a\u062f\u0629"
    ],
    "name:und_x_variant":[
        "Djede\u00efd\u00e9",
        "Jda\u00efd\u00e9",
        "Judaydah"
    ],
    "wof:name":"Judaydah",
    "wof:placetype":"locality"
},
  "geometry": {"coordinates":[37.51117,36.10736],"type":"Point"}
}