{
  "type": "Feature",
  "properties": {
    "gn:admin1_code":"10.0",
    "gn:asciiname":"Furaytan",
    "gn:country_code":"SY",
    "gn:dem":586,
    "gn:feature_class":"P",
    "gn:feature_code":"PPL",
    "gn:name":"Furayt\u0101n",
    "gn:population":0,
    "gn:timezone":"Asia/Damascus",
    "iso:country":"SY",
    "name:ara_x_preferred":[
        "\u0641\u0631\u064a\u062a\u0627\u0646"
    ],
    "name:fas_x_preferred":[
        "\u0641\u0631\u06cc\u062a\u0627\u0646"
    ],
    "name:pol_x_preferred":[
        "Furajtan"
    ],
    "name:und_x_variant":[
        "Furayt\u0101n"
    ],
    "name:vie_x_preferred":[
        "Furaytan"
    ],
    "wof:name":"Furaytan",
    "wof:placetype":"locality"
},
  "geometry": {"coordinates":[37.24167,34.95833],"type":"Point"}
}