{
  "type": "Feature",
  "properties": {
    "gn:admin1_code":"11.0",
    "gn:asciiname":"Batish",
    "gn:country_code":"SY",
    "gn:dem":637,
    "gn:feature_class":"P",
    "gn:feature_code":"PPL",
    "gn:name":"B\u0101\u0163\u012bsh",
    "gn:population":0,
    "gn:timezone":"Asia/Damascus",
    "iso:country":"SY",
    "name:ara_x_preferred":[
        "B\u00e2tech"
    ],
    "name:ara_x_variant":[
        "B\u0101\u0163\u012bsh",
        "\u0628\u0627\u0637\u064a\u0634"
    ],
    "name:und_x_variant":[
        "B\u00e2tich"
    ],
    "wof:name":"Batish",
    "wof:placetype":"locality"
},
  "geometry": {"coordinates":[36.43062000000001,34.51687],"type":"Point"}
}