{
  "type": "Feature",
  "properties": {
    "gn:admin1_code":"9.0",
    "gn:asciiname":"Hawdanah",
    "gn:country_code":"SY",
    "gn:dem":595,
    "gn:feature_class":"P",
    "gn:feature_code":"PPL",
    "gn:name":"\u1e28awd\u0101nah",
    "gn:population":0,
    "gn:timezone":"Asia/Damascus",
    "iso:country":"SY",
    "name:ara_x_preferred":[
        "\u062d\u0648\u062f\u0627\u0646\u0629"
    ],
    "name:und_x_variant":[
        "\u1e28awd\u0101nah"
    ],
    "wof:name":"Hawdanah",
    "wof:placetype":"locality"
},
  "geometry": {"coordinates":[37.47216,35.8819],"type":"Point"}
}