{
  "type": "Feature",
  "properties": {
    "gn:admin1_code":"4.0",
    "gn:asciiname":"Mutahayyir",
    "gn:country_code":"SY",
    "gn:dem":342,
    "gn:feature_class":"P",
    "gn:feature_code":"PPL",
    "gn:name":"Muta\u1e29ayyir",
    "gn:population":0,
    "gn:timezone":"Asia/Damascus",
    "iso:country":"SY",
    "name:ara_x_preferred":[
        "\u0645\u062a\u062d\u064a\u0631"
    ],
    "name:und_x_variant":[
        "Muta\u1e29ayyir"
    ],
    "wof:name":"Mutahayyir",
    "wof:placetype":"locality"
},
  "geometry": {"coordinates":[38.23479,35.80876],"type":"Point"}
}