{
  "type": "Feature",
  "properties": {
    "gn:admin1_code":"9.0",
    "gn:asciiname":"Bayt Muslim Muslim",
    "gn:country_code":"SY",
    "gn:dem":435,
    "gn:feature_class":"P",
    "gn:feature_code":"PPL",
    "gn:name":"Bayt Muslim Muslim",
    "gn:population":0,
    "gn:timezone":"Asia/Damascus",
    "iso:country":"SY",
    "name:ara_x_preferred":[
        "\u0628\u064a\u062a \u0645\u0633\u0644\u0645 \u0645\u0633\u0644\u0645"
    ],
    "wof:name":"Bayt Muslim Muslim",
    "wof:placetype":"locality"
},
  "geometry": {"coordinates":[38.14891,36.8199],"type":"Point"}
}