{
  "type": "Feature",
  "properties": {
    "gn:admin1_code":"2.0",
    "gn:asciiname":"Shaykh al Hami",
    "gn:country_code":"SY",
    "gn:dem":26,
    "gn:feature_class":"P",
    "gn:feature_code":"PPL",
    "gn:name":"Shaykh al \u1e28am\u012b",
    "gn:population":0,
    "gn:timezone":"Asia/Damascus",
    "iso:country":"SY",
    "name:ara_x_preferred":[
        "\u0634\u064a\u062e \u0627\u0644\u062d\u0645\u064a"
    ],
    "name:und_x_variant":[
        "Che\u00efkh el Hami",
        "Che\u00efkh el H\u00e9m\u00e9",
        "Ash Shaykh al \u1e28am\u012b",
        "Ash Shaykh al \u1e28im\u00e1",
        "Shaykh al \u1e28im\u00e1",
        "Shaykh al \u1e28am\u012b",
        "Sheikh Elhamah"
    ],
    "wof:name":"Shaykh al Hami",
    "wof:placetype":"locality"
},
  "geometry": {"coordinates":[35.84674000000001,35.49910999999999],"type":"Point"}
}