{
  "type": "Feature",
  "properties": {
    "gn:admin1_code":"1.0",
    "gn:asciiname":"Hurayshiyah",
    "gn:country_code":"SY",
    "gn:dem":245,
    "gn:feature_class":"P",
    "gn:feature_code":"PPL",
    "gn:name":"\u1e28uraysh\u012byah",
    "gn:population":0,
    "gn:timezone":"Asia/Damascus",
    "iso:country":"SY",
    "name:ara_x_preferred":[
        "\u062d\u0631\u064a\u0634\u064a\u0629"
    ],
    "name:und_x_variant":[
        "\u1e28uraysh\u012byah"
    ],
    "wof:name":"Hurayshiyah",
    "wof:placetype":"locality"
},
  "geometry": {"coordinates":[40.80665,35.74563],"type":"Point"}
}