{
  "type": "Feature",
  "properties": {
    "gn:admin1_code":"12.0",
    "gn:asciiname":"Zifr Kabir",
    "gn:country_code":"SY",
    "gn:dem":323,
    "gn:feature_class":"P",
    "gn:feature_code":"PPL",
    "gn:name":"Z\u0327ifr Kab\u012br",
    "gn:population":0,
    "gn:timezone":"Asia/Damascus",
    "iso:country":"SY",
    "name:ara_x_preferred":[
        "\u0632\u0641\u0631 \u0643\u0628\u064a\u0631"
    ],
    "name:ara_x_variant":[
        "\u0632\u0641\u0631 \u0627\u0644\u0643\u0628\u064a\u0631"
    ],
    "name:und_x_variant":[
        "Zafr K\u00e9b\u00eer",
        "Z\u0327ifr Kab\u012br",
        "Zifr al Kab\u012br"
    ],
    "wof:name":"Zifr Kabir",
    "wof:placetype":"locality"
},
  "geometry": {"coordinates":[36.99282,35.70115],"type":"Point"}
}