{
  "type": "Feature",
  "properties": {
    "gn:admin1_code":"11.0",
    "gn:asciiname":"Abu Tababir",
    "gn:country_code":"SY",
    "gn:dem":682,
    "gn:feature_class":"P",
    "gn:feature_code":"PPL",
    "gn:name":"Ab\u016b \u0162ab\u0101b\u012br",
    "gn:population":0,
    "gn:timezone":"Asia/Damascus",
    "iso:country":"SY",
    "name:und_x_variant":[
        "Abou Tab\u00e2b\u00eer",
        "Ab\u016b \u0162ab\u0101b\u012br"
    ],
    "wof:name":"Abu Tababir",
    "wof:placetype":"locality"
},
  "geometry": {"coordinates":[37.31667,34.91667],"type":"Point"}
}