{
  "type": "Feature",
  "properties": {
    "gn:admin1_code":"9.0",
    "gn:asciiname":"Rashadiyah",
    "gn:country_code":"SY",
    "gn:dem":317,
    "gn:feature_class":"P",
    "gn:feature_code":"PPL",
    "gn:name":"Rash\u0101d\u012byah",
    "gn:population":0,
    "gn:timezone":"Asia/Damascus",
    "iso:country":"SY",
    "name:ara_x_preferred":[
        "\u0631\u0634\u0627\u062f\u064a\u0629"
    ],
    "name:und_x_variant":[
        "Rach\u00e2diy\u00e9",
        "Rash\u0101d\u012byah"
    ],
    "wof:name":"Rashadiyah",
    "wof:placetype":"locality"
},
  "geometry": {"coordinates":[37.47104,35.72837],"type":"Point"}
}