{
  "type": "Feature",
  "properties": {
    "gn:admin1_code":"10.0",
    "gn:asciiname":"Luwaybidah",
    "gn:cc2":"SY",
    "gn:country_code":"SY",
    "gn:dem":312,
    "gn:feature_class":"P",
    "gn:feature_code":"PPL",
    "gn:name":"Luwaybidah",
    "gn:population":0,
    "gn:timezone":"Asia/Damascus",
    "iso:country":"SY",
    "name:und_x_variant":[
        "Loua\u00efb\u00e9",
        "Luwaybidah"
    ],
    "wof:name":"Luwaybidah",
    "wof:placetype":"locality"
},
  "geometry": {"coordinates":[37.26667,35.48333],"type":"Point"}
}