{
  "type": "Feature",
  "properties": {
    "gn:admin1_code":"9.0",
    "gn:asciiname":"Hayrut",
    "gn:country_code":"SY",
    "gn:dem":356,
    "gn:feature_class":"P",
    "gn:feature_code":"PPLL",
    "gn:name":"\u1e28ayr\u016bt",
    "gn:population":0,
    "gn:timezone":"Asia/Damascus",
    "iso:country":"SY",
    "name:ara_x_preferred":[
        "\u062d\u064a\u0631\u0648\u062a"
    ],
    "name:und_x_variant":[
        "\u1e28ayr\u016bt"
    ],
    "wof:name":"Hayrut",
    "wof:placetype":"locality"
},
  "geometry": {"coordinates":[37.33539,36.14644000000001],"type":"Point"}
}