{
  "type": "Feature",
  "properties": {
    "gn:admin1_code":"7.0",
    "gn:asciiname":"Muhammad ad Dandal",
    "gn:country_code":"SY",
    "gn:dem":764,
    "gn:feature_class":"P",
    "gn:feature_code":"PPL",
    "gn:name":"Mu\u1e29ammad ad Dandal",
    "gn:population":0,
    "gn:timezone":"Asia/Damascus",
    "iso:country":"SY",
    "name:ara_x_preferred":[
        "\u0645\u062d\u0645\u062f \u0627\u0644\u062f\u0646\u062f\u0644"
    ],
    "name:und_x_variant":[
        "Mu\u1e29ammad ad Dandal"
    ],
    "wof:name":"Muhammad ad Dandal",
    "wof:placetype":"locality"
},
  "geometry": {"coordinates":[39.44694000000001,35.39927],"type":"Point"}
}