{
  "type": "Feature",
  "properties": {
    "gn:admin1_code":"1.0",
    "gn:asciiname":"Faq`at Wadi ad Dab`ah",
    "gn:country_code":"SY",
    "gn:dem":316,
    "gn:feature_class":"P",
    "gn:feature_code":"PPL",
    "gn:name":"Faq\u2018at W\u0101d\u012b a\u1e11 \u1e10ab\u2018ah",
    "gn:population":0,
    "gn:timezone":"Asia/Damascus",
    "iso:country":"SY",
    "name:ara_x_preferred":[
        "\u0641\u0642\u0639\u0629 \u0648\u0627\u062f\u064a \u0627\u0644\u0636\u0628\u0639\u0629"
    ],
    "name:und_x_variant":[
        "Faq\u2018at W\u0101d\u012b a\u1e11 \u1e10ab\u2018ah"
    ],
    "wof:name":"Faq`at Wadi ad Dab`ah",
    "wof:placetype":"locality"
},
  "geometry": {"coordinates":[40.99327,36.06178],"type":"Point"}
}