{
  "type": "Feature",
  "properties": {
    "gn:admin1_code":"8.0",
    "gn:asciiname":"Bayt Hamdan",
    "gn:country_code":"SY",
    "gn:dem":710,
    "gn:feature_class":"P",
    "gn:feature_code":"PPL",
    "gn:name":"Bayt \u1e28amd\u0101n",
    "gn:population":0,
    "gn:timezone":"Asia/Damascus",
    "iso:country":"SY",
    "name:ara_x_preferred":[
        "\u0628\u064a\u062a \u062d\u0645\u062f\u0627\u0646"
    ],
    "name:und_x_variant":[
        "Bayt \u1e28amd\u0101n"
    ],
    "wof:name":"Bayt Hamdan",
    "wof:placetype":"locality"
},
  "geometry": {"coordinates":[36.93822,33.61516],"type":"Point"}
}