{
  "type": "Feature",
  "properties": {
    "gn:admin1_code":"14.0",
    "gn:asciiname":"Al `Annabiyah",
    "gn:country_code":"SY",
    "gn:dem":58,
    "gn:feature_class":"P",
    "gn:feature_code":"PPL",
    "gn:name":"Al \u2018Ann\u0101b\u012byah",
    "gn:population":0,
    "gn:timezone":"Asia/Damascus",
    "iso:country":"SY",
    "name:ara_x_preferred":[
        "\u0627\u0644\u0639\u0646\u0627\u0628\u064a\u0629"
    ],
    "name:und_x_variant":[
        "Aann\u00e2b\u00eey\u00e9",
        "Al \u2018Unn\u0101b\u012byah",
        "Al \u2018Ann\u0101b\u012byah",
        "Al \u2018Un\u0101b\u012byah"
    ],
    "wof:name":"Al `Annabiyah",
    "wof:placetype":"locality"
},
  "geometry": {"coordinates":[35.93129000000001,34.84985],"type":"Point"}
}