{
  "type": "Feature",
  "properties": {
    "gn:admin1_code":"10.0",
    "gn:asciiname":"Abu Mansaf",
    "gn:country_code":"SY",
    "gn:dem":411,
    "gn:feature_class":"P",
    "gn:feature_code":"PPL",
    "gn:name":"Ab\u016b Mansaf",
    "gn:population":0,
    "gn:timezone":"Asia/Damascus",
    "iso:country":"SY",
    "name:ara_x_preferred":[
        "\u0623\u0628\u0648 \u0645\u0646\u0633\u0641"
    ],
    "name:fas_x_preferred":[
        "\u0627\u0628\u0648 \u0645\u0646\u0633\u0641"
    ],
    "name:pol_x_preferred":[
        "Abu Mansaf"
    ],
    "name:und_x_variant":[
        "Abou Mannsaf",
        "Ab\u016b Mannsaf",
        "Ab\u016b Mansaf"
    ],
    "name:vie_x_preferred":[
        "Abu Mansaf"
    ],
    "wof:name":"Abu Mansaf",
    "wof:placetype":"locality"
},
  "geometry": {"coordinates":[36.87212,35.26537000000001],"type":"Point"}
}