{
  "type": "Feature",
  "properties": {
    "gn:admin1_code":"7.0",
    "gn:asciiname":"Rumayl",
    "gn:country_code":"SY",
    "gn:dem":205,
    "gn:feature_class":"P",
    "gn:feature_code":"PPL",
    "gn:name":"Rumayl",
    "gn:population":0,
    "gn:timezone":"Asia/Damascus",
    "iso:country":"SY",
    "name:ara_x_preferred":[
        "\u0631\u0645\u064a\u0644"
    ],
    "name:und_x_variant":[
        "Raml",
        "Rumayl"
    ],
    "wof:name":"Rumayl",
    "wof:placetype":"locality"
},
  "geometry": {"coordinates":[40.49075,35.21213],"type":"Point"}
}