{
  "type": "Feature",
  "properties": {
    "gn:admin1_code":"9.0",
    "gn:asciiname":"Rasm as Sayalah",
    "gn:country_code":"SY",
    "gn:dem":330,
    "gn:feature_class":"P",
    "gn:feature_code":"PPL",
    "gn:name":"Rasm as Say\u0101lah",
    "gn:population":0,
    "gn:timezone":"Asia/Damascus",
    "iso:country":"SY",
    "name:ara_x_preferred":[
        "\u0631\u0633\u0645 \u0627\u0644\u0633\u064a\u0627\u0644\u0629"
    ],
    "name:und_x_variant":[
        "Si\u00e2l\u00e9",
        "Siy\u00e2l\u00e9",
        "Rasm Sa\u00efy\u00e2l\u00e9",
        "Sa\u00efy\u00e2l\u00e9",
        "Siy\u0101lah",
        "Rasm Sayy\u0101lah",
        "Rasm as Say\u0101lah"
    ],
    "wof:name":"Rasm as Sayalah",
    "wof:placetype":"locality"
},
  "geometry": {"coordinates":[37.4159,35.75635],"type":"Point"}
}