{
  "type": "Feature",
  "properties": {
    "gn:admin1_code":"5.0",
    "gn:asciiname":"Kusayb",
    "gn:country_code":"SY",
    "gn:dem":1412,
    "gn:feature_class":"P",
    "gn:feature_code":"PPL",
    "gn:name":"Kusayb",
    "gn:population":0,
    "gn:timezone":"Asia/Damascus",
    "iso:country":"SY",
    "name:ara_x_preferred":[
        "\u0643\u0633\u064a\u0628"
    ],
    "name:und_x_variant":[
        "El Kse\u00efb",
        "Kusayb"
    ],
    "wof:name":"Kusayb",
    "wof:placetype":"locality"
},
  "geometry": {"coordinates":[36.78663,32.80123],"type":"Point"}
}