{
  "type": "Feature",
  "properties": {
    "gn:admin1_code":"2.0",
    "gn:asciiname":"Mamuhiyah",
    "gn:country_code":"SY",
    "gn:dem":1049,
    "gn:feature_class":"P",
    "gn:feature_code":"PPL",
    "gn:name":"M\u0101m\u016bh\u012byah",
    "gn:population":0,
    "gn:timezone":"Asia/Damascus",
    "iso:country":"SY",
    "name:und_x_variant":[
        "M\u00e2mo\u00fbh\u00eey\u00e9",
        "M\u0101m\u016bh\u012byah"
    ],
    "wof:name":"Mamuhiyah",
    "wof:placetype":"locality"
},
  "geometry": {"coordinates":[36.23029,35.68543],"type":"Point"}
}