{
  "type": "Feature",
  "properties": {
    "gn:admin1_code":"4.0",
    "gn:asciiname":"`Ayn `Isa",
    "gn:country_code":"SY",
    "gn:dem":340,
    "gn:feature_class":"P",
    "gn:feature_code":"PPLA3",
    "gn:name":"\u2018Ayn \u2018\u012as\u00e1",
    "gn:population":0,
    "gn:timezone":"Asia/Damascus",
    "iso:country":"SY",
    "name:ara_x_preferred":[
        "\u2018Ayn \u2018\u012as\u00e1"
    ],
    "name:ara_x_variant":[
        "\u0639\u064a\u0646 \u0639\u064a\u0633\u0649"
    ],
    "name:und_x_variant":[
        "A\u00efn A\u00efssa"
    ],
    "wof:name":"`Ayn `Isa",
    "wof:placetype":"locality"
},
  "geometry": {"coordinates":[38.86228,36.3855],"type":"Point"}
}