{
  "type": "Feature",
  "properties": {
    "gn:admin1_code":"10.0",
    "gn:asciiname":"Nawa",
    "gn:country_code":"SY",
    "gn:dem":555,
    "gn:feature_class":"P",
    "gn:feature_code":"PPL",
    "gn:name":"Naw\u0101",
    "gn:population":0,
    "gn:timezone":"Asia/Damascus",
    "iso:country":"SY",
    "name:ara_x_preferred":[
        "\u0646\u0648\u0627"
    ],
    "name:ceb_x_preferred":[
        "Nawa"
    ],
    "name:deu_x_preferred":[
        "Nawa"
    ],
    "name:ita_x_preferred":[
        "Nawa"
    ],
    "name:pol_x_preferred":[
        "Nawa"
    ],
    "name:rus_x_preferred":[
        "\u041d\u0430\u0432\u0430"
    ],
    "name:swe_x_preferred":[
        "Nawa"
    ],
    "name:ukr_x_preferred":[
        "\u041d\u0430\u0432\u0430"
    ],
    "name:und_x_variant":[
        "Naoua",
        "Naw\u00e1",
        "Naw\u0101"
    ],
    "wof:name":"Nawa",
    "wof:placetype":"locality"
},
  "geometry": {"coordinates":[37.0579,35.19771],"type":"Point"}
}