{
  "type": "Feature",
  "properties": {
    "gn:admin1_code":"10.0",
    "gn:asciiname":"Qanbar",
    "gn:country_code":"SY",
    "gn:dem":663,
    "gn:feature_class":"P",
    "gn:feature_code":"PPL",
    "gn:name":"Qanbar",
    "gn:population":0,
    "gn:timezone":"Asia/Damascus",
    "iso:country":"SY",
    "name:ara_x_preferred":[
        "\u0642\u0646\u0628\u0631"
    ],
    "wof:name":"Qanbar",
    "wof:placetype":"locality"
},
  "geometry": {"coordinates":[37.45297,35.07230999999999],"type":"Point"}
}