{
  "type": "Feature",
  "properties": {
    "gn:admin1_code":"2.0",
    "gn:asciiname":"Ruwaysah",
    "gn:country_code":"SY",
    "gn:dem":290,
    "gn:feature_class":"P",
    "gn:feature_code":"PPL",
    "gn:name":"Ruwaysah",
    "gn:population":0,
    "gn:timezone":"Asia/Damascus",
    "iso:country":"SY",
    "name:ara_x_preferred":[
        "\u0631\u0648\u064a\u0633\u0629"
    ],
    "name:und_x_variant":[
        "Roua\u00efss\u00e9",
        "Ru\u2019aysah"
    ],
    "wof:name":"Ruwaysah",
    "wof:placetype":"locality"
},
  "geometry": {"coordinates":[36.03093,35.6133],"type":"Point"}
}