{
  "type": "Feature",
  "properties": {
    "gn:admin1_code":"9.0",
    "gn:asciiname":"Al Haradat",
    "gn:country_code":"SY",
    "gn:dem":467,
    "gn:feature_class":"P",
    "gn:feature_code":"PPL",
    "gn:name":"Al \u1e28arad\u0101t",
    "gn:population":0,
    "gn:timezone":"Asia/Damascus",
    "iso:country":"SY",
    "name:ara_x_preferred":[
        "\u0627\u0644\u062d\u0631\u062f\u0627\u062a"
    ],
    "name:und_x_variant":[
        "Al \u1e28arad\u0101t"
    ],
    "wof:name":"Al Haradat",
    "wof:placetype":"locality"
},
  "geometry": {"coordinates":[37.33814,36.54479],"type":"Point"}
}