{
  "type": "Feature",
  "properties": {
    "gn:admin1_code":"14.0",
    "gn:asciiname":"Duwayr al `Uwayniyah",
    "gn:country_code":"SY",
    "gn:dem":589,
    "gn:feature_class":"P",
    "gn:feature_code":"PPL",
    "gn:name":"Duwayr al \u2018Uwayn\u012byah",
    "gn:population":0,
    "gn:timezone":"Asia/Damascus",
    "iso:country":"SY",
    "name:ara_x_preferred":[
        "\u062f\u0648\u064a\u0631 \u0627\u0644\u0639\u0648\u064a\u0646\u064a\u0629"
    ],
    "name:und_x_variant":[
        "Doua\u00efr el Aaoua\u00efn\u00eey\u00e9",
        "Duwayr al \u2018Uwayn\u012byah",
        "Doua\u00efr el Aaoua\u00efniy\u00e9"
    ],
    "wof:name":"Duwayr al `Uwayniyah",
    "wof:placetype":"locality"
},
  "geometry": {"coordinates":[36.18565,34.91706],"type":"Point"}
}