{
  "type": "Feature",
  "properties": {
    "gn:admin1_code":"10.0",
    "gn:asciiname":"Abu Hakfa",
    "gn:country_code":"SY",
    "gn:dem":570,
    "gn:feature_class":"P",
    "gn:feature_code":"PPL",
    "gn:name":"Ab\u016b \u1e28akf\u0101",
    "gn:population":0,
    "gn:timezone":"Asia/Damascus",
    "iso:country":"SY",
    "name:ara_x_preferred":[
        "\u0623\u0628\u0648 \u062d\u0643\u0641\u0627"
    ],
    "name:ara_x_variant":[
        "\u0623\u0628\u0648 \u062d\u0643\u0641\u0629"
    ],
    "name:fas_x_preferred":[
        "\u0627\u0628\u0648 \u062d\u06a9\u0641\u0647"
    ],
    "name:pol_x_preferred":[
        "Abu Hakfa"
    ],
    "name:und_x_variant":[
        "Ab\u016b \u1e28akf\u0101"
    ],
    "name:vie_x_preferred":[
        "Abu Hakfa"
    ],
    "wof:name":"Abu Hakfa",
    "wof:placetype":"locality"
},
  "geometry": {"coordinates":[37.52719,35.15876],"type":"Point"}
}