{
  "type": "Feature",
  "properties": {
    "gn:admin1_code":"11.0",
    "gn:asciiname":"Al `Ajami",
    "gn:country_code":"SY",
    "gn:dem":524,
    "gn:feature_class":"P",
    "gn:feature_code":"PPL",
    "gn:name":"Al \u2018Ajam\u012b",
    "gn:population":0,
    "gn:timezone":"Asia/Damascus",
    "iso:country":"SY",
    "name:ara_x_preferred":[
        "\u0627\u0644\u0639\u062c\u0645\u064a"
    ],
    "name:und_x_variant":[
        "Al \u2018Ajam\u012b"
    ],
    "wof:name":"Al `Ajami",
    "wof:placetype":"locality"
},
  "geometry": {"coordinates":[36.46453,34.57439],"type":"Point"}
}