{
  "type": "Feature",
  "properties": {
    "gn:admin1_code":"11.0",
    "gn:asciiname":"Abu Hamamah",
    "gn:country_code":"SY",
    "gn:dem":381,
    "gn:feature_class":"P",
    "gn:feature_code":"PPL",
    "gn:name":"Ab\u016b Ham\u0101mah",
    "gn:population":0,
    "gn:timezone":"Asia/Damascus",
    "iso:country":"SY",
    "name:ara_x_preferred":[
        "\u0623\u0628\u0648 \u0647\u0645\u0627\u0645\u0629"
    ],
    "name:fas_x_preferred":[
        "\u0627\u0628\u0648 \u0647\u0645\u0627\u0645\u0647"
    ],
    "name:pol_x_preferred":[
        "Abu Hamama"
    ],
    "name:und_x_variant":[
        "Abou Ham\u00e2mi",
        "Abou Hamam",
        "Ab\u016b \u1e28am\u0101m",
        "Ab\u016b Ham\u0101mah"
    ],
    "wof:name":"Abu Hamamah",
    "wof:placetype":"locality"
},
  "geometry": {"coordinates":[36.87746,34.95396],"type":"Point"}
}