{
  "type": "Feature",
  "properties": {
    "gn:admin1_code":"14.0",
    "gn:asciiname":"Habbah",
    "gn:country_code":"SY",
    "gn:dem":191,
    "gn:feature_class":"P",
    "gn:feature_code":"PPL",
    "gn:name":"\u1e28abbah",
    "gn:population":0,
    "gn:timezone":"Asia/Damascus",
    "iso:country":"SY",
    "name:ara_x_preferred":[
        "H\u00e9bo"
    ],
    "name:ara_x_variant":[
        "\u062d\u0628\u0629"
    ],
    "name:und_x_variant":[
        "\u1e28abbah",
        "Khubbah"
    ],
    "wof:name":"Habbah",
    "wof:placetype":"locality"
},
  "geometry": {"coordinates":[35.96594,35.09358],"type":"Point"}
}