{
  "type": "Feature",
  "properties": {
    "gn:admin1_code":"4.0",
    "gn:asciiname":"Big Suwaydiya",
    "gn:country_code":"SY",
    "gn:dem":314,
    "gn:feature_class":"P",
    "gn:feature_code":"PPL",
    "gn:name":"Big Suwaydiya",
    "gn:population":0,
    "gn:timezone":"Asia/Damascus",
    "iso:country":"SY",
    "wof:name":"Big Suwaydiya",
    "wof:placetype":"locality"
},
  "geometry": {"coordinates":[38.61712,35.89656],"type":"Point"}
}