{
  "type": "Feature",
  "properties": {
    "gn:admin1_code":"1.0",
    "gn:asciiname":"Ad Duwaym",
    "gn:country_code":"SY",
    "gn:dem":389,
    "gn:feature_class":"P",
    "gn:feature_code":"PPL",
    "gn:name":"Ad Duwaym",
    "gn:population":0,
    "gn:timezone":"Asia/Damascus",
    "iso:country":"SY",
    "name:ara_x_preferred":[
        "\u0627\u0644\u062f\u0648\u064a\u0645"
    ],
    "wof:name":"Ad Duwaym",
    "wof:placetype":"locality"
},
  "geometry": {"coordinates":[41.9529,36.84767],"type":"Point"}
}