{
  "type": "Feature",
  "properties": {
    "gn:admin1_code":"11.0",
    "gn:asciiname":"Al Halbah",
    "gn:country_code":"SY",
    "gn:dem":543,
    "gn:feature_class":"P",
    "gn:feature_code":"PPL",
    "gn:name":"Al \u1e28albah",
    "gn:population":0,
    "gn:timezone":"Asia/Damascus",
    "iso:country":"SY",
    "name:ara_x_preferred":[
        "\u0627\u0644\u062d\u0644\u0628\u0629"
    ],
    "name:und_x_variant":[
        "Al Halba",
        "Al \u1e28albah"
    ],
    "wof:name":"Al Halbah",
    "wof:placetype":"locality"
},
  "geometry": {"coordinates":[38.4323,34.07937],"type":"Point"}
}