{
  "type": "Feature",
  "properties": {
    "gn:admin1_code":"9.0",
    "gn:asciiname":"Ath Thawrah",
    "gn:country_code":"SY",
    "gn:dem":540,
    "gn:feature_class":"P",
    "gn:feature_code":"PPL",
    "gn:name":"Ath Thawrah",
    "gn:population":0,
    "gn:timezone":"Asia/Damascus",
    "iso:country":"SY",
    "name:ara_x_preferred":[
        "\u0627\u0644\u062b\u0648\u0631\u0629"
    ],
    "wof:name":"Ath Thawrah",
    "wof:placetype":"locality"
},
  "geometry": {"coordinates":[37.57474000000001,36.56072],"type":"Point"}
}