{
  "type": "Feature",
  "properties": {
    "gn:admin1_code":"7.0",
    "gn:asciiname":"Al Jurdi ash Sharqi",
    "gn:country_code":"SY",
    "gn:dem":187,
    "gn:feature_class":"P",
    "gn:feature_code":"PPL",
    "gn:name":"Al Jurd\u012b ash Sharq\u012b",
    "gn:population":0,
    "gn:timezone":"Asia/Damascus",
    "iso:country":"SY",
    "name:ara_x_preferred":[
        "\u0627\u0644\u062c\u0631\u062f\u064a \u0627\u0644\u0634\u0631\u0642\u064a"
    ],
    "name:ara_x_variant":[
        "\u0627\u0644\u062c\u0631\u0630\u0649 \u0627\u0644\u0634\u0631\u0642\u064a"
    ],
    "name:und_x_variant":[
        "Al Jurd\u012b Sharq\u012b",
        "Al Jurd\u012b ash Sharq\u012b",
        "Al Jurdh\u012b ash Sharq\u012b"
    ],
    "wof:name":"Al Jurdi ash Sharqi",
    "wof:placetype":"locality"
},
  "geometry": {"coordinates":[40.63895,34.87203],"type":"Point"}
}