{
  "type": "Feature",
  "properties": {
    "gn:admin1_code":"10.0",
    "gn:asciiname":"Huwayr at Turkuman",
    "gn:country_code":"SY",
    "gn:dem":680,
    "gn:feature_class":"P",
    "gn:feature_code":"PPL",
    "gn:name":"\u1e28uwayr at Turkum\u0101n",
    "gn:population":0,
    "gn:timezone":"Asia/Damascus",
    "iso:country":"SY",
    "name:ara_x_preferred":[
        "\u062d\u0648\u064a\u0631 \u0627\u0644\u062a\u0631\u0643\u0645\u0627\u0646"
    ],
    "name:und_x_variant":[
        "Houa\u00efr ett Tourkm\u00e2ne",
        "Houa\u00efr ett Toukm\u00e2ne",
        "\u1e28uwayr at Turkum\u0101n"
    ],
    "wof:name":"Huwayr at Turkuman",
    "wof:placetype":"locality"
},
  "geometry": {"coordinates":[36.35168,34.92608],"type":"Point"}
}