{
  "type": "Feature",
  "properties": {
    "gn:admin1_code":"8.0",
    "gn:asciiname":"Bustan Ba`lah",
    "gn:country_code":"SY",
    "gn:dem":1050,
    "gn:feature_class":"P",
    "gn:feature_code":"PPL",
    "gn:name":"Bust\u0101n Ba\u2018lah",
    "gn:population":0,
    "gn:timezone":"Asia/Damascus",
    "iso:country":"SY",
    "name:ara_x_preferred":[
        "\u0628\u0633\u062a\u0627\u0646 \u0628\u0639\u0644\u0629"
    ],
    "name:und_x_variant":[
        "Bust\u0101n Ba\u2018lah"
    ],
    "wof:name":"Bustan Ba`lah",
    "wof:placetype":"locality"
},
  "geometry": {"coordinates":[36.00169,33.38113],"type":"Point"}
}