{
  "type": "Feature",
  "properties": {
    "gn:admin1_code":"9.0",
    "gn:asciiname":"Tash Qabu",
    "gn:cc2":"SY",
    "gn:country_code":"SY",
    "gn:dem":586,
    "gn:feature_class":"P",
    "gn:feature_code":"PPL",
    "gn:name":"\u0162\u0101sh Qab\u016b",
    "gn:population":0,
    "gn:timezone":"Asia/Damascus",
    "iso:country":"SY",
    "name:und_x_variant":[
        "Tache Kapou",
        "\u0162\u0101sh Aqb\u016b",
        "T\u00e2ch Qapou",
        "\u0162\u0101sh Qab\u016b"
    ],
    "wof:name":"Tash Qabu",
    "wof:placetype":"locality"
},
  "geometry": {"coordinates":[37.58333,36.65],"type":"Point"}
}