{
  "type": "Feature",
  "properties": {
    "gn:admin1_code":"7.0",
    "gn:asciiname":"Jizra",
    "gn:country_code":"SY",
    "gn:dem":222,
    "gn:feature_class":"P",
    "gn:feature_code":"PPL",
    "gn:name":"Jizr\u0101",
    "gn:population":0,
    "gn:timezone":"Asia/Damascus",
    "iso:country":"SY",
    "name:ara_x_preferred":[
        "Jizr\u0101"
    ],
    "name:ara_x_variant":[
        "\u062c\u0632\u0631\u0627"
    ],
    "wof:name":"Jizra",
    "wof:placetype":"locality"
},
  "geometry": {"coordinates":[39.72259,35.75437],"type":"Point"}
}