{
  "type": "Feature",
  "properties": {
    "gn:admin1_code":"9.0",
    "gn:asciiname":"Khirbat ad Dib",
    "gn:country_code":"SY",
    "gn:dem":469,
    "gn:feature_class":"P",
    "gn:feature_code":"PPL",
    "gn:name":"Khirbat ad D\u012bb",
    "gn:population":0,
    "gn:timezone":"Asia/Damascus",
    "iso:country":"SY",
    "name:ara_x_preferred":[
        "\u062e\u0631\u0628\u0629 \u0627\u0644\u062f\u064a\u0628"
    ],
    "name:und_x_variant":[
        "Khirbat ad D\u012bb",
        "Kheurbet ed Dib",
        "Khirbat D\u012bb",
        "Khirbat adh Dhi\u2019b"
    ],
    "wof:name":"Khirbat ad Dib",
    "wof:placetype":"locality"
},
  "geometry": {"coordinates":[37.73974000000001,36.34666],"type":"Point"}
}