{
  "type": "Feature",
  "properties": {
    "gn:admin1_code":"2.0",
    "gn:asciiname":"Tilal",
    "gn:country_code":"SY",
    "gn:dem":612,
    "gn:feature_class":"P",
    "gn:feature_code":"PPL",
    "gn:name":"\u0162il\u0101l",
    "gn:population":0,
    "gn:timezone":"Asia/Damascus",
    "iso:country":"SY",
    "name:ara_x_preferred":[
        "Ask\u016br\u0101n"
    ],
    "name:ara_x_variant":[
        "\u0627\u0633\u0643\u0648\u0631\u0627\u0646",
        "\u0637\u0644\u0627\u0644"
    ],
    "name:und_x_variant":[
        "Ask\u00f4r\u00e2ne",
        "\u0162il\u0101l"
    ],
    "wof:name":"Tilal",
    "wof:placetype":"locality"
},
  "geometry": {"coordinates":[36.00184,35.92129],"type":"Point"}
}