{
  "type": "Feature",
  "properties": {
    "gn:admin1_code":"4.0",
    "gn:asciiname":"Bir Abu Qattash",
    "gn:country_code":"SY",
    "gn:dem":321,
    "gn:feature_class":"P",
    "gn:feature_code":"PPL",
    "gn:name":"B\u012br Ab\u016b Qa\u0163\u0163\u0101sh",
    "gn:population":0,
    "gn:timezone":"Asia/Damascus",
    "iso:country":"SY",
    "name:ara_x_preferred":[
        "\u0628\u064a\u0631 \u0623\u0628\u0648 \u0642\u0637\u0627\u0634"
    ],
    "name:und_x_variant":[
        "B\u012br Ab\u016b Qa\u0163\u0163\u0101sh"
    ],
    "wof:name":"Bir Abu Qattash",
    "wof:placetype":"locality"
},
  "geometry": {"coordinates":[38.80636,35.61019],"type":"Point"}
}