{
  "type": "Feature",
  "properties": {
    "gn:admin1_code":"9.0",
    "gn:asciiname":"Mazra`at Saqlaya",
    "gn:country_code":"SY",
    "gn:dem":389,
    "gn:feature_class":"P",
    "gn:feature_code":"PPL",
    "gn:name":"Mazra\u2018at \u015eaql\u0101y\u0101",
    "gn:population":0,
    "gn:timezone":"Asia/Damascus",
    "iso:country":"SY",
    "name:ara_x_preferred":[
        "\u0645\u0628\u062f\u0631\u062d"
    ],
    "name:ara_x_variant":[
        "\u0645\u0632\u0631\u0639\u0629 \u0635\u0642\u0644\u0627\u064a\u0627"
    ],
    "name:und_x_variant":[
        "Mubadra\u1e29",
        "Midra\u1e29",
        "Mazra\u2018at \u015eaql\u0101y\u0101"
    ],
    "wof:name":"Mazra`at Saqlaya",
    "wof:placetype":"locality"
},
  "geometry": {"coordinates":[37.18748,36.13574000000001],"type":"Point"}
}