{
  "type": "Feature",
  "properties": {
    "gn:admin1_code":"9.0",
    "gn:asciiname":"Jalamah",
    "gn:country_code":"SY",
    "gn:dem":216,
    "gn:feature_class":"P",
    "gn:feature_code":"PPL",
    "gn:name":"Jalamah",
    "gn:population":0,
    "gn:timezone":"Asia/Damascus",
    "iso:country":"SY",
    "name:ara_x_preferred":[
        "\u062c\u0644\u0645\u0629"
    ],
    "name:cat_x_preferred":[
        "Jalamah"
    ],
    "name:ceb_x_preferred":[
        "Al Jalamah"
    ],
    "name:heb_x_preferred":[
        "\u05d2'\u05dc\u05de\u05d4"
    ],
    "name:nno_x_preferred":[
        "Jalamah"
    ],
    "name:pol_x_preferred":[
        "D\u017calama"
    ],
    "name:und_x_variant":[
        "Dj\u00e9l\u00e9m\u00e9",
        "Jalm\u00e9",
        "Jalamah"
    ],
    "wof:name":"Jalamah",
    "wof:placetype":"locality"
},
  "geometry": {"coordinates":[36.77036,36.35735],"type":"Point"}
}