{
  "type": "Feature",
  "properties": {
    "gn:admin1_code":"9.0",
    "gn:asciiname":"Baraghidah",
    "gn:country_code":"SY",
    "gn:dem":491,
    "gn:feature_class":"P",
    "gn:feature_code":"PPL",
    "gn:name":"Bar\u0101gh\u012bdah",
    "gn:population":0,
    "gn:timezone":"Asia/Damascus",
    "iso:country":"SY",
    "name:ara_x_preferred":[
        "\u0628\u0631\u0627\u063a\u064a\u062f\u0629"
    ],
    "name:ara_x_variant":[
        "\u0628\u0631\u0627\u063a\u064a\u062a\u0629"
    ],
    "name:und_x_variant":[
        "Bar\u0101gh\u012btih",
        "Bar\u00e2rh\u00eete",
        "Barguita",
        "Bar\u0101gh\u012bthah",
        "Bar\u0101gh\u012btah",
        "Bar\u0101gh\u012bdah"
    ],
    "wof:name":"Baraghidah",
    "wof:placetype":"locality"
},
  "geometry": {"coordinates":[37.21351,36.63321],"type":"Point"}
}