{
  "type": "Feature",
  "properties": {
    "gn:admin1_code":"9.0",
    "gn:asciiname":"Kharfan",
    "gn:country_code":"SY",
    "gn:dem":434,
    "gn:feature_class":"P",
    "gn:feature_code":"PPL",
    "gn:name":"Kharf\u0101n",
    "gn:population":0,
    "gn:timezone":"Asia/Damascus",
    "iso:country":"SY",
    "name:ara_x_preferred":[
        "\u062e\u0631\u0641\u0627\u0646"
    ],
    "name:und_x_variant":[
        "\u1e28afr",
        "Harfar",
        "Kharf\u00e2ne",
        "Kharf\u0101n"
    ],
    "wof:name":"Kharfan",
    "wof:placetype":"locality"
},
  "geometry": {"coordinates":[38.15637,36.5902],"type":"Point"}
}