{
  "type": "Feature",
  "properties": {
    "gn:admin1_code":"9.0",
    "gn:asciiname":"Kuran",
    "gn:country_code":"SY",
    "gn:dem":395,
    "gn:feature_class":"P",
    "gn:feature_code":"PPL",
    "gn:name":"K\u016br\u0101n",
    "gn:population":0,
    "gn:timezone":"Asia/Damascus",
    "iso:country":"SY",
    "name:ara_x_preferred":[
        "K\u016br\u0101n"
    ],
    "name:ara_x_variant":[
        "\u0643\u0648\u0631\u0627\u0646"
    ],
    "name:ceb_x_preferred":[
        "Kuran"
    ],
    "name:fas_x_preferred":[
        "\u06a9\u0648\u0631\u0646"
    ],
    "name:swe_x_preferred":[
        "Kuran"
    ],
    "name:und_x_variant":[
        "Ko\u00fbr\u00e2ne",
        "Kourane"
    ],
    "wof:name":"Kuran",
    "wof:placetype":"locality"
},
  "geometry": {"coordinates":[36.67432,36.43969],"type":"Point"}
}