{
  "type": "Feature",
  "properties": {
    "gn:admin1_code":"1.0",
    "gn:asciiname":"Hulwah",
    "gn:country_code":"SY",
    "gn:dem":409,
    "gn:feature_class":"P",
    "gn:feature_code":"PPL",
    "gn:name":"\u1e28ulwah",
    "gn:population":0,
    "gn:timezone":"Asia/Damascus",
    "iso:country":"SY",
    "name:ara_x_preferred":[
        "\u062d\u0644\u0648\u0629"
    ],
    "name:tur_x_preferred":[
        "\u1e28ulwah"
    ],
    "name:und_x_variant":[
        "H\u00e9loua"
    ],
    "wof:name":"Hulwah",
    "wof:placetype":"locality"
},
  "geometry": {"coordinates":[40.39959,36.98854],"type":"Point"}
}