{
  "type": "Feature",
  "properties": {
    "gn:admin1_code":"9.0",
    "gn:asciiname":"Qibab Bayniyah",
    "gn:country_code":"SY",
    "gn:dem":405,
    "gn:feature_class":"P",
    "gn:feature_code":"PPL",
    "gn:name":"Qib\u0101b Bayn\u012byah",
    "gn:population":0,
    "gn:timezone":"Asia/Damascus",
    "iso:country":"SY",
    "name:ara_x_preferred":[
        "\u0642\u0628\u0627\u0628 \u0628\u064a\u0646\u064a\u0629"
    ],
    "name:und_x_variant":[
        "B\u00e9ni\u00e9",
        "Qubab Ban\u012byah",
        "Qoubba",
        "Qubbah",
        "Qoub\u00e2b Be\u00efn\u00eey\u00e9",
        "Qib\u0101b Bayn\u012byah"
    ],
    "wof:name":"Qibab Bayniyah",
    "wof:placetype":"locality"
},
  "geometry": {"coordinates":[38.02293,36.59087],"type":"Point"}
}