{
  "type": "Feature",
  "properties": {
    "gn:admin1_code":"8.0",
    "gn:asciiname":"Ard al `Ubb",
    "gn:country_code":"SY",
    "gn:dem":638,
    "gn:feature_class":"P",
    "gn:feature_code":"PPLL",
    "gn:name":"Ar\u1e11 al \u2018Ubb",
    "gn:population":0,
    "gn:timezone":"Asia/Damascus",
    "iso:country":"SY",
    "name:ara_x_preferred":[
        "\u0623\u0631\u0636 \u0627\u0644\u0639\u0628"
    ],
    "name:und_x_variant":[
        "Ar\u1e11 al \u2018Ubb"
    ],
    "wof:name":"Ard al `Ubb",
    "wof:placetype":"locality"
},
  "geometry": {"coordinates":[36.42585,33.55212],"type":"Point"}
}