{
  "type": "Feature",
  "properties": {
    "gn:admin1_code":"1.0",
    "gn:asciiname":"Mas`ura",
    "gn:country_code":"SY",
    "gn:dem":289,
    "gn:feature_class":"P",
    "gn:feature_code":"PPL",
    "gn:name":"Mas\u2018\u016br\u0101",
    "gn:population":0,
    "gn:timezone":"Asia/Damascus",
    "iso:country":"SY",
    "name:ara_x_preferred":[
        "\u0645\u0633\u0639\u0648\u0631\u0627"
    ],
    "name:und_x_variant":[
        "Mas\u2018\u016br\u0101"
    ],
    "wof:name":"Mas`ura",
    "wof:placetype":"locality"
},
  "geometry": {"coordinates":[40.6544,36.11842],"type":"Point"}
}