{
  "type": "Feature",
  "properties": {
    "gn:admin1_code":"11.0",
    "gn:asciiname":"Jankamrah",
    "gn:country_code":"SY",
    "gn:dem":662,
    "gn:feature_class":"P",
    "gn:feature_code":"PPL",
    "gn:name":"Jankamrah",
    "gn:population":0,
    "gn:timezone":"Asia/Damascus",
    "iso:country":"SY",
    "name:ara_x_preferred":[
        "\u062c\u0646\u0643\u0645\u0631\u0629"
    ],
    "name:pol_x_preferred":[
        "D\u017cankamra"
    ],
    "name:und_x_variant":[
        "Jennkamra",
        "Jankamrah"
    ],
    "name:vie_x_preferred":[
        "Jankamrah"
    ],
    "wof:name":"Jankamrah",
    "wof:placetype":"locality"
},
  "geometry": {"coordinates":[36.31649,34.83843],"type":"Point"}
}