{
  "type": "Feature",
  "properties": {
    "gn:admin1_code":"10.0",
    "gn:asciiname":"Jubb al Magharah",
    "gn:country_code":"SY",
    "gn:dem":549,
    "gn:feature_class":"P",
    "gn:feature_code":"PPL",
    "gn:name":"Jubb al Magh\u0101rah",
    "gn:population":0,
    "gn:timezone":"Asia/Damascus",
    "iso:country":"SY",
    "name:ara_x_preferred":[
        "\u062c\u0628 \u0627\u0644\u0645\u063a\u0627\u0631\u0629"
    ],
    "name:und_x_variant":[
        "Joubb el Mrh\u00e2ra",
        "Jubb al Magh\u0101rah"
    ],
    "wof:name":"Jubb al Magharah",
    "wof:placetype":"locality"
},
  "geometry": {"coordinates":[36.26269,35.68465],"type":"Point"}
}