{
  "type": "Feature",
  "properties": {
    "gn:admin1_code":"3.0",
    "gn:asciiname":"Rasm ad Dawwayah as Saghirah",
    "gn:country_code":"SY",
    "gn:dem":752,
    "gn:feature_class":"P",
    "gn:feature_code":"PPL",
    "gn:name":"Rasm ad Daww\u0101yah a\u015f \u015eagh\u012brah",
    "gn:population":0,
    "gn:timezone":"Asia/Damascus",
    "iso:country":"SY",
    "name:ara_x_preferred":[
        "\u0631\u0633\u0645 \u0627\u0644\u062f\u0648\u0651\u0627\u064a\u0629 \u0627\u0644\u0635\u063a\u064a\u0631\u0629"
    ],
    "name:und_x_variant":[
        "Rasm ad Daww\u0101yah a\u015f \u015eagh\u012brah"
    ],
    "wof:name":"Rasm ad Dawwayah as Saghirah",
    "wof:placetype":"locality"
},
  "geometry": {"coordinates":[35.93617000000001,33.0257],"type":"Point"}
}