{
  "type": "Feature",
  "properties": {
    "gn:admin1_code":"7.0",
    "gn:asciiname":"Kuwaytar",
    "gn:country_code":"SY",
    "gn:dem":340,
    "gn:feature_class":"P",
    "gn:feature_code":"PPL",
    "gn:name":"Kuwayt\u0101r",
    "gn:population":0,
    "gn:timezone":"Asia/Damascus",
    "iso:country":"SY",
    "name:ara_x_preferred":[
        "\u0643\u0648\u064a\u062a\u0627\u0631"
    ],
    "name:und_x_variant":[
        "Kuwayt\u0101r"
    ],
    "wof:name":"Kuwaytar",
    "wof:placetype":"locality"
},
  "geometry": {"coordinates":[39.78694,36.04028],"type":"Point"}
}