{
  "type": "Feature",
  "properties": {
    "gn:admin1_code":"4.0",
    "gn:asciiname":"At Tinah",
    "gn:country_code":"SY",
    "gn:dem":348,
    "gn:feature_class":"P",
    "gn:feature_code":"PPL",
    "gn:name":"At T\u012bnah",
    "gn:population":0,
    "gn:timezone":"Asia/Damascus",
    "iso:country":"SY",
    "name:ara_x_preferred":[
        "\u0627\u0644\u062a\u064a\u0646\u0629"
    ],
    "name:und_x_variant":[
        "T\u00een\u00e9",
        "Tiyne",
        "T\u00eer\u00e9",
        "T\u012bnah",
        "At T\u012bnah"
    ],
    "wof:name":"At Tinah",
    "wof:placetype":"locality"
},
  "geometry": {"coordinates":[38.83788,36.44343],"type":"Point"}
}