{
  "type": "Feature",
  "properties": {
    "gn:admin1_code":"9.0",
    "gn:asciiname":"Madrasah",
    "gn:country_code":"SY",
    "gn:dem":580,
    "gn:feature_class":"P",
    "gn:feature_code":"PPL",
    "gn:name":"Madrasah",
    "gn:population":0,
    "gn:timezone":"Asia/Damascus",
    "iso:country":"SY",
    "name:ara_x_preferred":[
        "\u0645\u062f\u0631\u0633\u0629"
    ],
    "name:und_x_variant":[
        "Madrass\u00e9",
        "Madrasah"
    ],
    "wof:name":"Madrasah",
    "wof:placetype":"locality"
},
  "geometry": {"coordinates":[37.39618,35.90631],"type":"Point"}
}