{
  "type": "Feature",
  "properties": {
    "gn:admin1_code":"2.0",
    "gn:asciiname":"Ard ad Dis",
    "gn:country_code":"SY",
    "gn:dem":4,
    "gn:feature_class":"P",
    "gn:feature_code":"PPLL",
    "gn:name":"Ar\u1e11 ad D\u012bs",
    "gn:population":0,
    "gn:timezone":"Asia/Damascus",
    "iso:country":"SY",
    "name:ara_x_preferred":[
        "\u0623\u0631\u0636 \u0627\u0644\u062f\u064a\u0633"
    ],
    "name:und_x_variant":[
        "Ar\u1e11 ad D\u012bs"
    ],
    "wof:name":"Ard ad Dis",
    "wof:placetype":"locality"
},
  "geometry": {"coordinates":[35.75305,35.58642000000001],"type":"Point"}
}