{
  "type": "Feature",
  "properties": {
    "gn:admin1_code":"1.0",
    "gn:asciiname":"Al Hurriyah",
    "gn:country_code":"SY",
    "gn:dem":388,
    "gn:feature_class":"P",
    "gn:feature_code":"PPL",
    "gn:name":"Al \u1e28urr\u012byah",
    "gn:population":0,
    "gn:timezone":"Asia/Damascus",
    "iso:country":"SY",
    "name:ara_x_preferred":[
        "\u0627\u0644\u062d\u0631\u064a\u0629"
    ],
    "name:und_x_variant":[
        "Al \u1e28urr\u012byah"
    ],
    "wof:name":"Al Hurriyah",
    "wof:placetype":"locality"
},
  "geometry": {"coordinates":[41.95651,36.81241],"type":"Point"}
}