{
  "type": "Feature",
  "properties": {
    "gn:admin1_code":"9.0",
    "gn:asciiname":"Jat",
    "gn:country_code":"SY",
    "gn:dem":364,
    "gn:feature_class":"P",
    "gn:feature_code":"PPL",
    "gn:name":"J\u0101t",
    "gn:population":0,
    "gn:timezone":"Asia/Damascus",
    "iso:country":"SY",
    "name:ara_x_preferred":[
        "J\u0101t"
    ],
    "name:ara_x_variant":[
        "\u062c\u0627\u062a"
    ],
    "wof:name":"Jat",
    "wof:placetype":"locality"
},
  "geometry": {"coordinates":[38.03299000000001,36.63725],"type":"Point"}
}