{
  "type": "Feature",
  "properties": {
    "gn:admin1_code":"1.0",
    "gn:asciiname":"`Alawi al As`ad",
    "gn:country_code":"SY",
    "gn:dem":300,
    "gn:feature_class":"P",
    "gn:feature_code":"PPL",
    "gn:name":"\u2018Al\u0101w\u012b al As\u2018ad",
    "gn:population":0,
    "gn:timezone":"Asia/Damascus",
    "iso:country":"SY",
    "name:ara_x_preferred":[
        "\u0639\u0644\u0627\u0648\u064a \u0627\u0644\u0623\u0633\u0639\u062f"
    ],
    "name:und_x_variant":[
        "\u2018Al\u0101w\u012b al As\u2018ad"
    ],
    "wof:name":"`Alawi al As`ad",
    "wof:placetype":"locality"
},
  "geometry": {"coordinates":[41.14325,36.00152],"type":"Point"}
}