{
  "type": "Feature",
  "properties": {
    "gn:admin1_code":"11.0",
    "gn:asciiname":"Al Yamamah",
    "gn:country_code":"SY",
    "gn:dem":481,
    "gn:feature_class":"P",
    "gn:feature_code":"PPL",
    "gn:name":"Al Yam\u0101mah",
    "gn:population":0,
    "gn:timezone":"Asia/Damascus",
    "iso:country":"SY",
    "name:ara_x_preferred":[
        "\u0627\u0644\u064a\u0645\u0627\u0645\u0629"
    ],
    "name:und_x_variant":[
        "Al Yam\u0101mah"
    ],
    "wof:name":"Al Yamamah",
    "wof:placetype":"locality"
},
  "geometry": {"coordinates":[36.86818,34.86048],"type":"Point"}
}