{
  "type": "Feature",
  "properties": {
    "gn:admin1_code":"8.0",
    "gn:asciiname":"Ard al Khammashah",
    "gn:country_code":"SY",
    "gn:dem":607,
    "gn:feature_class":"P",
    "gn:feature_code":"PPLL",
    "gn:name":"Ar\u1e11 al Khamm\u0101shah",
    "gn:population":0,
    "gn:timezone":"Asia/Damascus",
    "iso:country":"SY",
    "name:ara_x_preferred":[
        "\u0623\u0631\u0636 \u0627\u0644\u062e\u0645\u0627\u0634\u0629"
    ],
    "name:und_x_variant":[
        "Ar\u1e11 al Khamm\u0101shah"
    ],
    "wof:name":"Ard al Khammashah",
    "wof:placetype":"locality"
},
  "geometry": {"coordinates":[36.56905,33.50849],"type":"Point"}
}