{
  "type": "Feature",
  "properties": {
    "gn:admin1_code":"9.0",
    "gn:asciiname":"Rasm al Khashuf",
    "gn:country_code":"SY",
    "gn:dem":335,
    "gn:feature_class":"P",
    "gn:feature_code":"PPL",
    "gn:name":"Rasm al Khash\u016bf",
    "gn:population":0,
    "gn:timezone":"Asia/Damascus",
    "iso:country":"SY",
    "name:ara_x_preferred":[
        "\u0631\u0633\u0645 \u0627\u0644\u062e\u0634\u0648\u0641"
    ],
    "name:und_x_variant":[
        "Rasm al Khash\u016bf"
    ],
    "wof:name":"Rasm al Khashuf",
    "wof:placetype":"locality"
},
  "geometry": {"coordinates":[37.13235,35.59248],"type":"Point"}
}