{
  "type": "Feature",
  "properties": {
    "gn:admin1_code":"3.0",
    "gn:asciiname":"Dur `Ayn `Alqah",
    "gn:country_code":"SY",
    "gn:dem":940,
    "gn:feature_class":"P",
    "gn:feature_code":"PPL",
    "gn:name":"D\u016br \u2018Ayn \u2018Alqah",
    "gn:population":0,
    "gn:timezone":"Asia/Damascus",
    "iso:country":"SY",
    "name:ara_x_preferred":[
        "\u062f\u0648\u0631 \u0639\u064a\u0646 \u0639\u0644\u0642\u0629"
    ],
    "name:und_x_variant":[
        "D\u016br \u2018Ayn \u2018Alqah"
    ],
    "wof:name":"Dur `Ayn `Alqah",
    "wof:placetype":"locality"
},
  "geometry": {"coordinates":[35.93523,33.22849],"type":"Point"}
}