{
  "type": "Feature",
  "properties": {
    "gn:admin1_code":"7.0",
    "gn:asciiname":"Bir ash Sham",
    "gn:country_code":"SY",
    "gn:dem":210,
    "gn:feature_class":"P",
    "gn:feature_code":"PPL",
    "gn:name":"Bir ash Sh\u0101m",
    "gn:population":0,
    "gn:timezone":"Asia/Damascus",
    "iso:country":"SY",
    "name:ara_x_preferred":[
        "\u0628\u0631 \u0627\u0644\u0634\u0627\u0645"
    ],
    "name:und_x_variant":[
        "Bir ash Sh\u0101m"
    ],
    "wof:name":"Bir ash Sham",
    "wof:placetype":"locality"
},
  "geometry": {"coordinates":[40.4945,35.21844],"type":"Point"}
}