{
  "type": "Feature",
  "properties": {
    "gn:admin1_code":"9.0",
    "gn:asciiname":"Sawwan Kabir",
    "gn:country_code":"SY",
    "gn:dem":811,
    "gn:feature_class":"P",
    "gn:feature_code":"PPL",
    "gn:name":"\u015eaww\u0101n Kab\u012br",
    "gn:population":0,
    "gn:timezone":"Asia/Damascus",
    "iso:country":"SY",
    "name:ara_x_preferred":[
        "\u062c\u0642\u0645\u0642 \u0643\u0628\u064a\u0631"
    ],
    "name:ara_x_variant":[
        "\u0635\u0648\u0627\u0646 \u0643\u0628\u064a\u0631"
    ],
    "name:und_x_variant":[
        "Jaqmaq Kab\u012br",
        "Buyuk Tchaqmaq",
        "Buy\u016bk J\u0101qmaq",
        "\u015eaww\u0101n Kab\u012br"
    ],
    "wof:name":"Sawwan Kabir",
    "wof:placetype":"locality"
},
  "geometry": {"coordinates":[36.6978,36.71517],"type":"Point"}
}