{
  "type": "Feature",
  "properties": {
    "gn:admin1_code":"9.0",
    "gn:asciiname":"Nuwajat Mahmud Bak",
    "gn:country_code":"SY",
    "gn:dem":484,
    "gn:feature_class":"P",
    "gn:feature_code":"PPL",
    "gn:name":"Nuw\u0101jat Ma\u1e29m\u016bd Bak",
    "gn:population":0,
    "gn:timezone":"Asia/Damascus",
    "iso:country":"SY",
    "name:ara_x_preferred":[
        "\u0646\u0648\u0627\u062c\u0629 \u0645\u062d\u0645\u0648\u062f \u0628\u0643"
    ],
    "name:und_x_variant":[
        "Naou\u00e2jet Mahmo\u00fbd Bey",
        "Nu\u2019\u0101jat Ma\u1e29m\u016bd Bayk",
        "Nuw\u0101jat Ma\u1e29m\u016bd Bak"
    ],
    "wof:name":"Nuwajat Mahmud Bak",
    "wof:placetype":"locality"
},
  "geometry": {"coordinates":[38.02014000000001,36.51034],"type":"Point"}
}