{
  "type": "Feature",
  "properties": {
    "gn:admin1_code":"4.0",
    "gn:asciiname":"Shuray`an",
    "gn:country_code":"SY",
    "gn:dem":337,
    "gn:feature_class":"P",
    "gn:feature_code":"PPL",
    "gn:name":"Shuray\u2018\u0101n",
    "gn:population":0,
    "gn:timezone":"Asia/Damascus",
    "iso:country":"SY",
    "name:ara_x_preferred":[
        "\u0634\u0631\u064a\u0639\u0627\u0646"
    ],
    "name:und_x_variant":[
        "Chre\u00efa\u00e2ne",
        "Shuray\u2018\u0101n"
    ],
    "wof:name":"Shuray`an",
    "wof:placetype":"locality"
},
  "geometry": {"coordinates":[38.97692,36.61687],"type":"Point"}
}