{
  "type": "Feature",
  "properties": {
    "gn:admin1_code":"11.0",
    "gn:asciiname":"Rasm at Tuwayliyah",
    "gn:country_code":"SY",
    "gn:dem":631,
    "gn:feature_class":"P",
    "gn:feature_code":"PPL",
    "gn:name":"Rasm a\u0163 \u0162uwayl\u012byah",
    "gn:population":0,
    "gn:timezone":"Asia/Damascus",
    "iso:country":"SY",
    "name:ara_x_preferred":[
        "\u0631\u0633\u0645 \u0627\u0644\u0637\u0648\u064a\u0644\u064a\u0629"
    ],
    "name:und_x_variant":[
        "Tell ett Taou\u00eel\u00e9",
        "Tall a\u0163 \u0162aw\u012blah",
        "Rasm a\u0163 \u0162uwayl\u012byah"
    ],
    "wof:name":"Rasm at Tuwayliyah",
    "wof:placetype":"locality"
},
  "geometry": {"coordinates":[37.09222000000001,34.8449],"type":"Point"}
}