{
  "type": "Feature",
  "properties": {
    "gn:admin1_code":"11.0",
    "gn:asciiname":"Burj al Maksur",
    "gn:country_code":"SY",
    "gn:dem":144,
    "gn:feature_class":"P",
    "gn:feature_code":"PPL",
    "gn:name":"Burj al Maks\u016br",
    "gn:population":0,
    "gn:timezone":"Asia/Damascus",
    "iso:country":"SY",
    "name:ara_x_preferred":[
        "\u0628\u0631\u062c \u0627\u0644\u0645\u0643\u0633\u0648\u0631"
    ],
    "name:und_x_variant":[
        "Borj el Makso\u00fbr",
        "Burj al Maks\u016br"
    ],
    "wof:name":"Burj al Maksur",
    "wof:placetype":"locality"
},
  "geometry": {"coordinates":[36.17635,34.69528],"type":"Point"}
}