{
  "type": "Feature",
  "properties": {
    "gn:admin1_code":"9.0",
    "gn:asciiname":"Tuwayran",
    "gn:country_code":"SY",
    "gn:dem":498,
    "gn:feature_class":"P",
    "gn:feature_code":"PPL",
    "gn:name":"Tuwayr\u0101n",
    "gn:population":0,
    "gn:timezone":"Asia/Damascus",
    "iso:country":"SY",
    "name:ara_x_preferred":[
        "\u0637\u0648\u064a\u0631\u0627\u0646"
    ],
    "name:und_x_variant":[
        "Toua\u00efr\u00e2ne",
        "Tuwayr\u0101n"
    ],
    "wof:name":"Tuwayran",
    "wof:placetype":"locality"
},
  "geometry": {"coordinates":[37.45348,36.58671],"type":"Point"}
}