{
  "type": "Feature",
  "properties": {
    "gn:admin1_code":"9.0",
    "gn:asciiname":"Hayr Karim",
    "gn:country_code":"SY",
    "gn:dem":479,
    "gn:feature_class":"P",
    "gn:feature_code":"PPL",
    "gn:name":"\u1e28ayr Kar\u012bm",
    "gn:population":0,
    "gn:timezone":"Asia/Damascus",
    "iso:country":"SY",
    "name:ara_x_preferred":[
        "\u062d\u064a\u0631 \u0643\u0631\u064a\u0645"
    ],
    "name:und_x_variant":[
        "\u1e28ayr Kar\u012bm"
    ],
    "wof:name":"Hayr Karim",
    "wof:placetype":"locality"
},
  "geometry": {"coordinates":[36.87076,36.20349],"type":"Point"}
}