{
  "type": "Feature",
  "properties": {
    "gn:admin1_code":"9.0",
    "gn:asciiname":"Udani Jubb",
    "gn:country_code":"SY",
    "gn:dem":499,
    "gn:feature_class":"P",
    "gn:feature_code":"PPL",
    "gn:name":"\u016a\u1e11\u0101n\u012b Jubb",
    "gn:population":0,
    "gn:timezone":"Asia/Damascus",
    "iso:country":"SY",
    "name:ara_x_preferred":[
        "\u016a\u1e11\u0101n\u012b Jubb"
    ],
    "name:ara_x_variant":[
        "\u0627\u0648\u0636\u0627\u0646\u064a \u062c\u0628"
    ],
    "name:und_x_variant":[
        "El Q\u00fbdanni",
        "O\u00fbdannli Jobb",
        "O\u00fbdannli Joubb",
        "\u016adanl\u012b Jubb"
    ],
    "wof:name":"Udani Jubb",
    "wof:placetype":"locality"
},
  "geometry": {"coordinates":[38.36899,36.31697],"type":"Point"}
}