{
  "type": "Feature",
  "properties": {
    "gn:admin1_code":"2.0",
    "gn:asciiname":"Mayzah",
    "gn:country_code":"SY",
    "gn:dem":431,
    "gn:feature_class":"P",
    "gn:feature_code":"PPL",
    "gn:name":"Mayzah",
    "gn:population":0,
    "gn:timezone":"Asia/Damascus",
    "iso:country":"SY",
    "name:und_x_variant":[
        "Meiz\u00e9",
        "Mayzah"
    ],
    "wof:name":"Mayzah",
    "wof:placetype":"locality"
},
  "geometry": {"coordinates":[36.05959,35.57564],"type":"Point"}
}