{
  "type": "Feature",
  "properties": {
    "gn:admin1_code":"1.0",
    "gn:asciiname":"Farrujah",
    "gn:country_code":"SY",
    "gn:dem":356,
    "gn:feature_class":"P",
    "gn:feature_code":"PPL",
    "gn:name":"Farr\u016bjah",
    "gn:population":0,
    "gn:timezone":"Asia/Damascus",
    "iso:country":"SY",
    "name:ara_x_preferred":[
        "\u0641\u0631\u0648\u062c\u0629"
    ],
    "name:tur_x_preferred":[
        "Farr\u016bjah"
    ],
    "name:und_x_variant":[
        "Farro\u00fbj\u00e9"
    ],
    "wof:name":"Farrujah",
    "wof:placetype":"locality"
},
  "geometry": {"coordinates":[41.31536,36.794],"type":"Point"}
}