{
  "type": "Feature",
  "properties": {
    "gn:admin1_code":"1.0",
    "gn:asciiname":"Abu Gharbah",
    "gn:country_code":"SY",
    "gn:dem":281,
    "gn:feature_class":"P",
    "gn:feature_code":"PPL",
    "gn:name":"Ab\u016b Gharbah",
    "gn:population":0,
    "gn:timezone":"Asia/Damascus",
    "iso:country":"SY",
    "name:ara_x_preferred":[
        "\u0623\u0628\u0648 \u063a\u0631\u0628\u0629"
    ],
    "name:und_x_variant":[
        "Ab\u016b Gharbah",
        "Ab\u016b Ghurbah"
    ],
    "wof:name":"Abu Gharbah",
    "wof:placetype":"locality"
},
  "geometry": {"coordinates":[40.63208,35.99674],"type":"Point"}
}