{
  "type": "Feature",
  "properties": {
    "gn:admin1_code":"2.0",
    "gn:asciiname":"Farqalu",
    "gn:country_code":"SY",
    "gn:dem":206,
    "gn:feature_class":"P",
    "gn:feature_code":"PPL",
    "gn:name":"Farqal\u016b",
    "gn:population":0,
    "gn:timezone":"Asia/Damascus",
    "iso:country":"SY",
    "name:ara_x_preferred":[
        "\u0641\u0631\u0642\u0644\u0648"
    ],
    "name:und_x_variant":[
        "Farqal\u016b"
    ],
    "wof:name":"Farqalu",
    "wof:placetype":"locality"
},
  "geometry": {"coordinates":[36.00874,35.53661],"type":"Point"}
}