{
  "type": "Feature",
  "properties": {
    "gn:admin1_code":"9.0",
    "gn:asciiname":"Umm al Julud",
    "gn:country_code":"SY",
    "gn:dem":467,
    "gn:feature_class":"P",
    "gn:feature_code":"PPL",
    "gn:name":"Umm al Jul\u016bd",
    "gn:population":0,
    "gn:timezone":"Asia/Damascus",
    "iso:country":"SY",
    "name:ara_x_preferred":[
        "\u0623\u0645 \u062c\u0644\u0648\u062f"
    ],
    "name:und_x_variant":[
        "Oum ej Jlo\u00fbd",
        "Umm Jul\u016bd",
        "Oumm ej Jloud",
        "Oum ed Djouloud",
        "Umm al Jul\u016bd"
    ],
    "wof:name":"Umm al Julud",
    "wof:placetype":"locality"
},
  "geometry": {"coordinates":[37.78978,36.62079],"type":"Point"}
}