{
  "type": "Feature",
  "properties": {
    "gn:admin1_code":"6.0",
    "gn:asciiname":"Umm al Mayadin",
    "gn:country_code":"SY",
    "gn:dem":557,
    "gn:feature_class":"P",
    "gn:feature_code":"PPL",
    "gn:name":"Umm al May\u0101din",
    "gn:population":0,
    "gn:timezone":"Asia/Damascus",
    "iso:country":"SY",
    "name:ara_x_preferred":[
        "\u0623\u0645 \u0627\u0644\u0645\u064a\u0627\u062f\u0646"
    ],
    "name:ara_x_variant":[
        "\u0627\u0645 \u0627\u0644\u0645\u064a\u0627\u0630\u0646"
    ],
    "name:und_x_variant":[
        "Oum el May\u00e2de\u00efne",
        "Oum el May\u00e2d\u00eene",
        "Oumm el Mayadine",
        "Umm al May\u0101d\u012bn",
        "Umm al May\u0101din",
        "Umm al May\u0101dhin"
    ],
    "wof:name":"Umm al Mayadin",
    "wof:placetype":"locality"
},
  "geometry": {"coordinates":[36.18975,32.58501],"type":"Point"}
}