{
  "type": "Feature",
  "properties": {
    "gn:admin1_code":"9.0",
    "gn:asciiname":"Al Malikiyah",
    "gn:country_code":"SY",
    "gn:dem":405,
    "gn:feature_class":"P",
    "gn:feature_code":"PPL",
    "gn:name":"Al Malik\u012byah",
    "gn:population":0,
    "gn:timezone":"Asia/Damascus",
    "iso:country":"SY",
    "name:ara_x_preferred":[
        "\u0627\u0644\u0645\u0644\u0643\u064a\u0629"
    ],
    "name:und_x_variant":[
        "Al Malik\u012byah"
    ],
    "wof:name":"Al Malikiyah",
    "wof:placetype":"locality"
},
  "geometry": {"coordinates":[37.27927,36.09204],"type":"Point"}
}