{
  "type": "Feature",
  "properties": {
    "gn:admin1_code":"14.0",
    "gn:asciiname":"Qubayrin",
    "gn:country_code":"SY",
    "gn:dem":291,
    "gn:feature_class":"P",
    "gn:feature_code":"PPL",
    "gn:name":"Qubayr\u012bn",
    "gn:population":0,
    "gn:timezone":"Asia/Damascus",
    "iso:country":"SY",
    "name:ara_x_preferred":[
        "\u0642\u0628\u064a\u0631\u064a\u0646"
    ],
    "name:und_x_variant":[
        "Qubayr\u012bn"
    ],
    "wof:name":"Qubayrin",
    "wof:placetype":"locality"
},
  "geometry": {"coordinates":[35.9391,34.99345],"type":"Point"}
}