{
  "type": "Feature",
  "properties": {
    "gn:admin1_code":"12.0",
    "gn:asciiname":"Mugharat al Khasiki",
    "gn:country_code":"SY",
    "gn:dem":355,
    "gn:feature_class":"P",
    "gn:feature_code":"PPL",
    "gn:name":"Mugh\u0101rat al Kh\u0101sik\u012b",
    "gn:population":0,
    "gn:timezone":"Asia/Damascus",
    "iso:country":"SY",
    "name:ara_x_preferred":[
        "\u0645\u0639\u0631\u0629"
    ],
    "name:ara_x_variant":[
        "\u0645\u063a\u0627\u0631\u0629 \u0627\u0644\u062e\u0627\u0633\u0643\u064a"
    ],
    "name:und_x_variant":[
        "Ma\u2018arrat al Khasakah",
        "Maara",
        "Maarra",
        "Ma\u00e2ret el Kh\u00e2sk\u00e9",
        "Maarat",
        "Ma\u2018\u0101rat al Kh\u0101sikah",
        "Ma\u2018arrah",
        "Mugh\u0101rat al Kh\u0101sik\u012b"
    ],
    "wof:name":"Mugharat al Khasiki",
    "wof:placetype":"locality"
},
  "geometry": {"coordinates":[36.83728,36.03518],"type":"Point"}
}