{
  "type": "Feature",
  "properties": {
    "gn:admin1_code":"12.0",
    "gn:asciiname":"Muqah",
    "gn:country_code":"SY",
    "gn:dem":446,
    "gn:feature_class":"P",
    "gn:feature_code":"PPL",
    "gn:name":"M\u016bqah",
    "gn:population":0,
    "gn:timezone":"Asia/Damascus",
    "iso:country":"SY",
    "name:ara_x_preferred":[
        "\u0645\u0648\u0642\u0629"
    ],
    "name:und_x_variant":[
        "Mouqa",
        "Mo\u00fbka",
        "M\u016bqah"
    ],
    "wof:name":"Muqah",
    "wof:placetype":"locality"
},
  "geometry": {"coordinates":[36.6399,35.49898],"type":"Point"}
}