{
  "type": "Feature",
  "properties": {
    "gn:admin1_code":"7.0",
    "gn:asciiname":"Kubar",
    "gn:country_code":"SY",
    "gn:dem":217,
    "gn:feature_class":"P",
    "gn:feature_code":"PPL",
    "gn:name":"Kub\u0101r",
    "gn:population":0,
    "gn:timezone":"Asia/Damascus",
    "iso:country":"SY",
    "name:ara_x_preferred":[
        "Kub\u0101r"
    ],
    "name:ara_x_variant":[
        "\u0643\u0628\u0627\u0631"
    ],
    "name:und_x_variant":[
        "El Ko\u00fbb\u00e2r",
        "Koubar"
    ],
    "wof:name":"Kubar",
    "wof:placetype":"locality"
},
  "geometry": {"coordinates":[39.85384000000001,35.61912],"type":"Point"}
}