{
  "type": "Feature",
  "properties": {
    "gn:admin1_code":"2.0",
    "gn:asciiname":"Al Muruj",
    "gn:country_code":"SY",
    "gn:dem":5,
    "gn:feature_class":"P",
    "gn:feature_code":"PPLL",
    "gn:name":"Al Mur\u016bj",
    "gn:population":0,
    "gn:timezone":"Asia/Damascus",
    "iso:country":"SY",
    "name:ara_x_preferred":[
        "Al Mur\u016bj"
    ],
    "name:ara_x_variant":[
        "\u0627\u0644\u0645\u0631\u0648\u062c"
    ],
    "name:und_x_variant":[
        "El Mro\u00fbj",
        "El Merouj"
    ],
    "wof:name":"Al Muruj",
    "wof:placetype":"locality"
},
  "geometry": {"coordinates":[35.75103,35.57724],"type":"Point"}
}