{
  "type": "Feature",
  "properties": {
    "gn:admin1_code":"10.0",
    "gn:asciiname":"`Unq al Jarrah",
    "gn:country_code":"SY",
    "gn:dem":448,
    "gn:feature_class":"P",
    "gn:feature_code":"PPL",
    "gn:name":"\u2018Unq al Jarrah",
    "gn:population":0,
    "gn:timezone":"Asia/Damascus",
    "iso:country":"SY",
    "name:ara_x_preferred":[
        "\u0639\u0646\u0642 \u0627\u0644\u062c\u0631\u0629"
    ],
    "name:und_x_variant":[
        "\u2018Unq al Jarrah"
    ],
    "wof:name":"`Unq al Jarrah",
    "wof:placetype":"locality"
},
  "geometry": {"coordinates":[37.28498,35.2903],"type":"Point"}
}