{
  "type": "Feature",
  "properties": {
    "gn:admin1_code":"9.0",
    "gn:asciiname":"Ashkan Gharbi",
    "gn:country_code":"SY",
    "gn:dem":297,
    "gn:feature_class":"P",
    "gn:feature_code":"PPL",
    "gn:name":"Ashk\u0101n Gharb\u012b",
    "gn:population":0,
    "gn:timezone":"Asia/Damascus",
    "iso:country":"SY",
    "name:ara_x_preferred":[
        "\u0623\u0634\u0643\u0627\u0646 \u063a\u0631\u0628\u064a"
    ],
    "name:und_x_variant":[
        "Ashk\u0101n Gharb\u012b",
        "Achk\u00e2ne Rharbi"
    ],
    "wof:name":"Ashkan Gharbi",
    "wof:placetype":"locality"
},
  "geometry": {"coordinates":[36.63507,36.39977],"type":"Point"}
}