{
  "type": "Feature",
  "properties": {
    "gn:admin1_code":"9.0",
    "gn:asciiname":"Al `Alqanah",
    "gn:country_code":"SY",
    "gn:dem":371,
    "gn:feature_class":"P",
    "gn:feature_code":"PPL",
    "gn:name":"Al \u2018Alq\u0101nah",
    "gn:population":0,
    "gn:timezone":"Asia/Damascus",
    "iso:country":"SY",
    "name:ara_x_preferred":[
        "\u0627\u0644\u0639\u0644\u0642\u0627\u0646\u0629"
    ],
    "name:und_x_variant":[
        "Al \u2018Alq\u0101nah"
    ],
    "wof:name":"Al `Alqanah",
    "wof:placetype":"locality"
},
  "geometry": {"coordinates":[37.79643,35.62914],"type":"Point"}
}