{
  "type": "Feature",
  "properties": {
    "gn:admin1_code":"1.0",
    "gn:asciiname":"Husayn al Hajalah",
    "gn:country_code":"SY",
    "gn:dem":297,
    "gn:feature_class":"P",
    "gn:feature_code":"PPL",
    "gn:name":"\u1e28usayn al \u1e28ajalah",
    "gn:population":0,
    "gn:timezone":"Asia/Damascus",
    "iso:country":"SY",
    "name:ara_x_preferred":[
        "\u062d\u0633\u064a\u0646 \u0627\u0644\u062d\u062c\u0644\u0629"
    ],
    "name:und_x_variant":[
        "\u1e28usayn al \u1e28ajalah"
    ],
    "wof:name":"Husayn al Hajalah",
    "wof:placetype":"locality"
},
  "geometry": {"coordinates":[40.90823,36.04355],"type":"Point"}
}