{
  "type": "Feature",
  "properties": {
    "gn:admin1_code":"11.0",
    "gn:asciiname":"Al Qulaybah",
    "gn:country_code":"SY",
    "gn:dem":470,
    "gn:feature_class":"P",
    "gn:feature_code":"PPL",
    "gn:name":"Al Qulaybah",
    "gn:population":0,
    "gn:timezone":"Asia/Damascus",
    "iso:country":"SY",
    "name:ara_x_preferred":[
        "\u0627\u0644\u0642\u0644\u064a\u0628\u0629"
    ],
    "name:und_x_variant":[
        "Al Qalb\u012byah",
        "Al Qulaybah",
        "Al Kulaybah"
    ],
    "wof:name":"Al Qulaybah",
    "wof:placetype":"locality"
},
  "geometry": {"coordinates":[37.98357,34.53258],"type":"Point"}
}