{
  "type": "Feature",
  "properties": {
    "gn:admin1_code":"11.0",
    "gn:asciiname":"Rasm Humaydah",
    "gn:country_code":"SY",
    "gn:dem":914,
    "gn:feature_class":"P",
    "gn:feature_code":"PPL",
    "gn:name":"Rasm \u1e28umaydah",
    "gn:population":0,
    "gn:timezone":"Asia/Damascus",
    "iso:country":"SY",
    "name:ara_x_preferred":[
        "\u0631\u0633\u0645 \u062d\u0645\u064a\u062f\u0629"
    ],
    "name:und_x_variant":[
        "Rasm Hme\u00efd\u00e9",
        "Rasm \u1e28umaydah"
    ],
    "wof:name":"Rasm Humaydah",
    "wof:placetype":"locality"
},
  "geometry": {"coordinates":[37.28086,34.70534],"type":"Point"}
}