{
  "type": "Feature",
  "properties": {
    "gn:admin1_code":"10.0",
    "gn:asciiname":"As Sayyadah",
    "gn:country_code":"SY",
    "gn:dem":456,
    "gn:feature_class":"P",
    "gn:feature_code":"PPL",
    "gn:name":"A\u015f \u015eayy\u0101dah",
    "gn:population":0,
    "gn:timezone":"Asia/Damascus",
    "iso:country":"SY",
    "name:ara_x_preferred":[
        "\u0627\u0644\u0635\u064a\u0627\u062f\u0629"
    ],
    "name:und_x_variant":[
        "Tell es Say\u00e2d\u00e9",
        "Tall a\u015f \u015eayy\u0101dah",
        "A\u015f \u015eayy\u0101dah"
    ],
    "wof:name":"As Sayyadah",
    "wof:placetype":"locality"
},
  "geometry": {"coordinates":[37.07327,35.05925],"type":"Point"}
}