{
  "type": "Feature",
  "properties": {
    "gn:admin1_code":"9.0",
    "gn:asciiname":"`Ayn az Zarqa'",
    "gn:country_code":"SY",
    "gn:dem":356,
    "gn:feature_class":"P",
    "gn:feature_code":"PPL",
    "gn:name":"\u2018Ayn az Zarq\u0101\u2019",
    "gn:population":0,
    "gn:timezone":"Asia/Damascus",
    "iso:country":"SY",
    "name:ara_x_preferred":[
        "\u0639\u064a\u0646 \u0627\u0644\u0632\u0631\u0642\u0627\u0621"
    ],
    "name:und_x_variant":[
        "\u2018Ayn az Zarq\u0101\u2019"
    ],
    "wof:name":"`Ayn az Zarqa'",
    "wof:placetype":"locality"
},
  "geometry": {"coordinates":[37.59438,35.52881],"type":"Point"}
}