{
  "type": "Feature",
  "properties": {
    "gn:admin1_code":"1.0",
    "gn:asciiname":"Chulamah Fawqani",
    "gn:country_code":"SY",
    "gn:dem":421,
    "gn:feature_class":"P",
    "gn:feature_code":"PPL",
    "gn:name":"Ch\u016bl\u0101mah Fawq\u0101n\u012b",
    "gn:population":0,
    "gn:timezone":"Asia/Damascus",
    "iso:country":"SY",
    "name:ara_x_preferred":[
        "\u0686\u0648\u0644\u0627\u0645\u0629 \u0641\u0648\u0642\u0627\u0646\u064a"
    ],
    "name:tur_x_preferred":[
        "Sh\u016blm\u0101 al Fawq\u0101n\u012b"
    ],
    "name:und_x_variant":[
        "Tchol\u00e2ma Faouq\u00e2ni",
        "Ch\u016bl\u0101mah Fawq\u0101n\u012b",
        "Chawl\u0101mah Fawq\u0101n\u012b"
    ],
    "wof:name":"Chulamah Fawqani",
    "wof:placetype":"locality"
},
  "geometry": {"coordinates":[40.73715,36.86821],"type":"Point"}
}