{
  "type": "Feature",
  "properties": {
    "gn:admin1_code":"1.0",
    "gn:asciiname":"Chul Bustan",
    "gn:country_code":"SY",
    "gn:dem":375,
    "gn:feature_class":"P",
    "gn:feature_code":"PPL",
    "gn:name":"Ch\u016bl Bust\u0101n",
    "gn:population":0,
    "gn:timezone":"Asia/Damascus",
    "iso:country":"SY",
    "name:ara_x_preferred":[
        "Ch\u016bl Bust\u0101n"
    ],
    "name:ara_x_variant":[
        "\u0686\u0648\u0644 \u0628\u0633\u062a\u0627\u0646"
    ],
    "name:tur_x_preferred":[
        "J\u016bl Bust\u0101n"
    ],
    "wof:name":"Chul Bustan",
    "wof:placetype":"locality"
},
  "geometry": {"coordinates":[40.94947,36.83115],"type":"Point"}
}