{
  "type": "Feature",
  "properties": {
    "gn:admin1_code":"8.0",
    "gn:asciiname":"Al `Awasij",
    "gn:country_code":"SY",
    "gn:dem":998,
    "gn:feature_class":"P",
    "gn:feature_code":"PPL",
    "gn:name":"Al \u2018Aw\u0101sij",
    "gn:population":0,
    "gn:timezone":"Asia/Damascus",
    "iso:country":"SY",
    "name:ara_x_preferred":[
        "\u062e\u0646\u064a\u0641\u0633\u0629"
    ],
    "name:ara_x_variant":[
        "\u0627\u0644\u0639\u0648\u0627\u0633\u062c"
    ],
    "name:und_x_variant":[
        "Khna\u00effs\u00e9",
        "Khunayfisah",
        "Al \u2018Aw\u0101sij"
    ],
    "wof:name":"Al `Awasij",
    "wof:placetype":"locality"
},
  "geometry": {"coordinates":[36.08507,33.4795],"type":"Point"}
}