{
  "type": "Feature",
  "properties": {
    "gn:admin1_code":"14.0",
    "gn:asciiname":"Jawbat Mujbir",
    "gn:country_code":"SY",
    "gn:dem":654,
    "gn:feature_class":"P",
    "gn:feature_code":"PPL",
    "gn:name":"Jawbat Mujbir",
    "gn:population":0,
    "gn:timezone":"Asia/Damascus",
    "iso:country":"SY",
    "name:ara_x_preferred":[
        "\u062c\u0648\u0628\u0629 \u0645\u062c\u0628\u0631"
    ],
    "name:und_x_variant":[
        "Jaoubet Moujber",
        "Jawbat Mujbir"
    ],
    "wof:name":"Jawbat Mujbir",
    "wof:placetype":"locality"
},
  "geometry": {"coordinates":[36.16504000000001,35.02997],"type":"Point"}
}