{
  "type": "Feature",
  "properties": {
    "gn:admin1_code":"1.0",
    "gn:asciiname":"Shamma",
    "gn:country_code":"SY",
    "gn:dem":324,
    "gn:feature_class":"P",
    "gn:feature_code":"PPL",
    "gn:name":"Shamm\u0101",
    "gn:population":0,
    "gn:timezone":"Asia/Damascus",
    "iso:country":"SY",
    "name:ara_x_preferred":[
        "\u0634\u0645\u0627"
    ],
    "name:und_x_variant":[
        "Shamm\u0101"
    ],
    "wof:name":"Shamma",
    "wof:placetype":"locality"
},
  "geometry": {"coordinates":[40.51417,36.11385],"type":"Point"}
}