{
  "type": "Feature",
  "properties": {
    "gn:admin1_code":"11.0",
    "gn:asciiname":"Khirbat al Hayik",
    "gn:country_code":"SY",
    "gn:dem":502,
    "gn:feature_class":"P",
    "gn:feature_code":"PPL",
    "gn:name":"Khirbat al \u1e28\u0101yik",
    "gn:population":0,
    "gn:timezone":"Asia/Damascus",
    "iso:country":"SY",
    "name:ara_x_preferred":[
        "\u1e28\u0101yik"
    ],
    "name:ara_x_variant":[
        "\u062d\u0627\u064a\u0643",
        "\u062e\u0631\u0628\u0629 \u0627\u0644\u062d\u0627\u064a\u0643"
    ],
    "name:und_x_variant":[
        "Kheurbet el Hayeck",
        "Kheurbet el H\u00e2yek",
        "Khirbat al \u1e28\u0101\u2019ik",
        "Khirbat al \u1e28\u0101yik"
    ],
    "wof:name":"Khirbat al Hayik",
    "wof:placetype":"locality"
},
  "geometry": {"coordinates":[36.60861,34.70585],"type":"Point"}
}