{
  "type": "Feature",
  "properties": {
    "gn:admin1_code":"6.0",
    "gn:asciiname":"Al Bakkar",
    "gn:country_code":"SY",
    "gn:dem":532,
    "gn:feature_class":"P",
    "gn:feature_code":"PPL",
    "gn:name":"Al Bakk\u0101r",
    "gn:population":0,
    "gn:timezone":"Asia/Damascus",
    "iso:country":"SY",
    "name:ara_x_preferred":[
        "\u0627\u0644\u0628\u0643\u0627\u0631"
    ],
    "name:und_x_variant":[
        "Al Bakk\u0101r"
    ],
    "wof:name":"Al Bakkar",
    "wof:placetype":"locality"
},
  "geometry": {"coordinates":[35.92916,32.88117],"type":"Point"}
}