{
  "type": "Feature",
  "properties": {
    "gn:admin1_code":"8.0",
    "gn:asciiname":"Mudayra",
    "gn:country_code":"SY",
    "gn:dem":665,
    "gn:feature_class":"P",
    "gn:feature_code":"PPL",
    "gn:name":"Mudayr\u0101",
    "gn:population":0,
    "gn:timezone":"Asia/Damascus",
    "iso:country":"SY",
    "name:ara_x_preferred":[
        "\u0645\u062f\u064a\u0631\u0629"
    ],
    "name:ara_x_variant":[
        "\u0645\u062f\u064a\u0631\u0627"
    ],
    "name:und_x_variant":[
        "Mudayrah",
        "Mudayr\u0101"
    ],
    "wof:name":"Mudayra",
    "wof:placetype":"locality"
},
  "geometry": {"coordinates":[36.38615,33.54539],"type":"Point"}
}