{
  "type": "Feature",
  "properties": {
    "gn:admin1_code":"10.0",
    "gn:asciiname":"Mu`addamiyah",
    "gn:country_code":"SY",
    "gn:dem":742,
    "gn:feature_class":"P",
    "gn:feature_code":"PPL",
    "gn:name":"Mu\u2018a\u1e11\u1e11am\u012byah",
    "gn:population":0,
    "gn:timezone":"Asia/Damascus",
    "iso:country":"SY",
    "name:ara_x_preferred":[
        "\u0645\u0639\u0636\u0645\u064a\u0629"
    ],
    "name:und_x_variant":[
        "Mu\u2018a\u1e11\u1e11am\u012byah",
        "Ma\u2018\u1e11am\u012byah"
    ],
    "wof:name":"Mu`addamiyah",
    "wof:placetype":"locality"
},
  "geometry": {"coordinates":[37.51654,34.99643],"type":"Point"}
}