{
  "type": "Feature",
  "properties": {
    "gn:admin1_code":"1.0",
    "gn:asciiname":"Al `Asi",
    "gn:country_code":"SY",
    "gn:dem":291,
    "gn:feature_class":"P",
    "gn:feature_code":"PPL",
    "gn:name":"Al \u2018\u0100\u015f\u012b",
    "gn:population":0,
    "gn:timezone":"Asia/Damascus",
    "iso:country":"SY",
    "name:ara_x_preferred":[
        "\u0627\u0644\u0639\u0627\u0635\u064a"
    ],
    "name:und_x_variant":[
        "Al \u2018\u0100\u015f\u012b"
    ],
    "wof:name":"Al `Asi",
    "wof:placetype":"locality"
},
  "geometry": {"coordinates":[40.50062,35.95672000000001],"type":"Point"}
}