{
  "type": "Feature",
  "properties": {
    "gn:admin1_code":"4.0",
    "gn:asciiname":"As Suwayda",
    "gn:country_code":"SY",
    "gn:dem":224,
    "gn:feature_class":"P",
    "gn:feature_code":"PPL",
    "gn:name":"As Suwayd\u0101",
    "gn:population":0,
    "gn:timezone":"Asia/Damascus",
    "iso:country":"SY",
    "name:ara_x_preferred":[
        "\u0627\u0644\u0633\u0648\u064a\u062f\u0627"
    ],
    "name:und_x_variant":[
        "As Suwayd\u0101\u2019",
        "As Suwayd\u0101"
    ],
    "wof:name":"As Suwayda",
    "wof:placetype":"locality"
},
  "geometry": {"coordinates":[39.64005,35.77745],"type":"Point"}
}