{
  "type": "Feature",
  "properties": {
    "gn:admin1_code":"10.0",
    "gn:asciiname":"Al Madba`ah",
    "gn:country_code":"SY",
    "gn:dem":470,
    "gn:feature_class":"P",
    "gn:feature_code":"PPL",
    "gn:name":"Al Ma\u1e11ba\u2018ah",
    "gn:population":0,
    "gn:timezone":"Asia/Damascus",
    "iso:country":"SY",
    "name:ara_x_preferred":[
        "\u0645\u0636\u0628\u0639\u0629"
    ],
    "name:ara_x_variant":[
        "\u0627\u0644\u0645\u0636\u0628\u0639\u0629"
    ],
    "name:und_x_variant":[
        "Madba\u00e2",
        "Ma\u1e11ba\u2018ah",
        "Al Ma\u1e11ba\u2018ah"
    ],
    "wof:name":"Al Madba`ah",
    "wof:placetype":"locality"
},
  "geometry": {"coordinates":[36.8708,35.23891],"type":"Point"}
}