{
  "type": "Feature",
  "properties": {
    "gn:country":"SY",
    "gn:fcode":"PPLA2",
    "gn:population":66138,
    "iso:country":"SY",
    "name:ara_x_preferred":[
        "A\u2018z\u0101z"
    ],
    "name:ara_x_variant":[
        "\u0625\u0639\u0632\u0627\u0632",
        "I\u2018z\u0101z",
        "\u0623\u0639\u0632\u0627\u0632"
    ],
    "name:arz_x_preferred":[
        "\u0627\u0639\u0632\u0627\u0632"
    ],
    "name:ast_x_preferred":[
        "Azaz"
    ],
    "name:aze_x_preferred":[
        "Az\u0259z"
    ],
    "name:bel_x_preferred":[
        "\u0410\u0430\u0437\u0430\u0437"
    ],
    "name:cat_x_preferred":[
        "Azaz"
    ],
    "name:ceb_x_preferred":[
        "I\u2018z\u0101z"
    ],
    "name:ces_x_preferred":[
        "Azaz"
    ],
    "name:ces_x_variant":[
        "Az\u00e1z"
    ],
    "name:ckb_x_preferred":[
        "\u0626\u06d5\u0639\u0632\u0627\u0632"
    ],
    "name:deu_x_preferred":[
        "A\u02bfz\u0101z"
    ],
    "name:diq_x_preferred":[
        "Ezaz"
    ],
    "name:ell_x_preferred":[
        "\u0391\u03b6\u03ac\u03b6\u03b9\u03bf"
    ],
    "name:eng_x_preferred":[
        "Azaz"
    ],
    "name:fas_x_preferred":[
        "\u0627\u0639\u0632\u0627\u0632"
    ],
    "name:fin_x_preferred":[
        "Azaz"
    ],
    "name:fra_x_preferred":[
        "Azaz"
    ],
    "name:heb_x_preferred":[
        "\u05e2\u05d6\u05d0\u05d6"
    ],
    "name:hye_x_preferred":[
        "\u0531\u0566\u0561\u0566"
    ],
    "name:ita_x_preferred":[
        "Azaz"
    ],
    "name:jpn_x_preferred":[
        "\u30a2\u30a2\u30b6\u30fc\u30ba"
    ],
    "name:kat_x_preferred":[
        "\u10d0\u10d6\u10d0\u10d6\u10d8"
    ],
    "name:kur_x_preferred":[
        "Ezaz"
    ],
    "name:lit_x_preferred":[
        "Azazas"
    ],
    "name:mzn_x_preferred":[
        "\u0627\u0639\u0632\u0627\u0632"
    ],
    "name:nld_x_preferred":[
        "A'zaz"
    ],
    "name:nno_x_preferred":[
        "Azaz"
    ],
    "name:nob_x_preferred":[
        "Azaz"
    ],
    "name:pol_x_preferred":[
        "Azaz"
    ],
    "name:ron_x_preferred":[
        "Azaz"
    ],
    "name:rus_x_preferred":[
        "\u0410\u0437\u0430\u0437"
    ],
    "name:rus_x_variant":[
        "\u0410\u0430\u0437\u0430\u0437"
    ],
    "name:spa_x_preferred":[
        "Azaz"
    ],
    "name:sqi_x_preferred":[
        "Azaz"
    ],
    "name:srp_x_preferred":[
        "\u0410\u0437\u0430\u0437"
    ],
    "name:swe_x_preferred":[
        "I\u2018z\u0101z"
    ],
    "name:tur_x_preferred":[
        "A'z\u00e2z"
    ],
    "name:tur_x_variant":[
        "Az'ez"
    ],
    "name:ukr_x_preferred":[
        "\u0410\u0430\u0437\u0430\u0437"
    ],
    "name:und_x_variant":[
        "Aaz\u00e2z"
    ],
    "name:urd_x_preferred":[
        "\u0627\u0639\u0632\u0627\u0632"
    ],
    "name:vie_x_preferred":[
        "Azaz"
    ],
    "name:zho_x_preferred":[
        "\u963f\u624e\u8332"
    ],
    "qs:name":"I\u2018z\u0101z",
    "qs:photos_9r":0,
    "qs:photos_sr":0,
    "qs:pop_sr":"8",
    "wof:name":"I\u2018z\u0101z",
    "wof:placetype":"locality",
    "wof:population":66138
},
  "geometry": {"coordinates":[37.04628,36.58662],"type":"Point"}
}