{
  "type": "Feature",
  "properties": {
    "gn:admin1_code":"10.0",
    "gn:asciiname":"Hamadah ash Shaykhan",
    "gn:country_code":"SY",
    "gn:dem":488,
    "gn:feature_class":"P",
    "gn:feature_code":"PPL",
    "gn:name":"\u1e28am\u0101dah ash Shaykh\u0101n",
    "gn:population":0,
    "gn:timezone":"Asia/Damascus",
    "iso:country":"SY",
    "name:ara_x_preferred":[
        "\u062d\u0645\u0627\u062f\u0629 \u0627\u0644\u0634\u064a\u062e\u0627\u0646"
    ],
    "name:und_x_variant":[
        "\u1e28am\u0101dah ash Shaykh\u0101n"
    ],
    "wof:name":"Hamadah ash Shaykhan",
    "wof:placetype":"locality"
},
  "geometry": {"coordinates":[36.83336,35.16142],"type":"Point"}
}