{
  "type": "Feature",
  "properties": {
    "gn:admin1_code":"12.0",
    "gn:asciiname":"Basatin al Karkh",
    "gn:country_code":"SY",
    "gn:dem":226,
    "gn:feature_class":"P",
    "gn:feature_code":"PPL",
    "gn:name":"Bas\u0101t\u012bn al Karkh",
    "gn:population":0,
    "gn:timezone":"Asia/Damascus",
    "iso:country":"SY",
    "name:ara_x_preferred":[
        "\u0628\u0633\u0627\u062a\u064a\u0646 \u0627\u0644\u0643\u0631\u062e"
    ],
    "name:und_x_variant":[
        "Bas\u0101t\u012bn al Karkh"
    ],
    "wof:name":"Basatin al Karkh",
    "wof:placetype":"locality"
},
  "geometry": {"coordinates":[36.46063,35.81933],"type":"Point"}
}