{
  "type": "Feature",
  "properties": {
    "gn:admin1_code":"14.0",
    "gn:asciiname":"Bayt ash Shaykh `Ali",
    "gn:country_code":"SY",
    "gn:dem":356,
    "gn:feature_class":"P",
    "gn:feature_code":"PPL",
    "gn:name":"Bayt ash Shaykh \u2018Al\u012b",
    "gn:population":0,
    "gn:timezone":"Asia/Damascus",
    "iso:country":"SY",
    "name:ara_x_preferred":[
        "\u0628\u064a\u062a \u0627\u0644\u0634\u064a\u062e \u0639\u0644\u064a"
    ],
    "name:und_x_variant":[
        "Be\u00eft ech Che\u00efkh Aali",
        "Bayt ash Shaykh \u2018Al\u012b"
    ],
    "wof:name":"Bayt ash Shaykh `Ali",
    "wof:placetype":"locality"
},
  "geometry": {"coordinates":[35.95817,35.09902],"type":"Point"}
}