{
  "type": "Feature",
  "properties": {
    "gn:admin1_code":"1.0",
    "gn:asciiname":"Al Ghafiqiyah",
    "gn:country_code":"SY",
    "gn:dem":528,
    "gn:feature_class":"P",
    "gn:feature_code":"PPL",
    "gn:name":"Al Gh\u0101fiq\u012byah",
    "gn:population":0,
    "gn:timezone":"Asia/Damascus",
    "iso:country":"SY",
    "name:ara_x_preferred":[
        "\u0627\u0644\u063a\u0627\u0641\u0642\u064a\u0629"
    ],
    "name:kur_x_preferred":[
        "Badiyan"
    ],
    "name:und_x_variant":[
        "Bady\u0101n",
        "Badi\u00e2ne",
        "Al Gh\u0101fuq\u012byah",
        "Al Gh\u0101fiq\u012byah",
        "Badyan",
        "\u0628\u0627\u062f\u064a\u0627\u0646"
    ],
    "wof:name":"Al Ghafiqiyah",
    "wof:placetype":"locality"
},
  "geometry": {"coordinates":[41.84127,37.09457],"type":"Point"}
}