{
  "type": "Feature",
  "properties": {
    "gn:admin1_code":"9.0",
    "gn:asciiname":"Jindayris",
    "gn:country_code":"SY",
    "gn:dem":237,
    "gn:feature_class":"P",
    "gn:feature_code":"PPLA3",
    "gn:name":"Jindayris",
    "gn:population":0,
    "gn:timezone":"Asia/Damascus",
    "iso:country":"SY",
    "name:ara_x_preferred":[
        "\u062c\u0646\u062f\u064a\u0631\u0633"
    ],
    "name:ara_x_variant":[
        "\u062f\u064a\u0646\u062f\u0631\u0633"
    ],
    "name:und_x_variant":[
        "Djennd\u00e9ress",
        "Genderesse",
        "Djinnd\u00e9ress",
        "Jend\u00e9ress",
        "Jindaras",
        "Jandar\u012bs",
        "Jindayris",
        "D\u012bndaris",
        "Jandayris",
        "Jundayris"
    ],
    "wof:name":"Jindayris",
    "wof:placetype":"locality"
},
  "geometry": {"coordinates":[36.6889,36.39496],"type":"Point"}
}