{
  "type": "Feature",
  "properties": {
    "gn:admin1_code":"12.0",
    "gn:asciiname":"Al Ghadfah",
    "gn:country_code":"SY",
    "gn:dem":476,
    "gn:feature_class":"P",
    "gn:feature_code":"PPL",
    "gn:name":"Al Ghadfah",
    "gn:population":0,
    "gn:timezone":"Asia/Damascus",
    "iso:country":"SY",
    "name:ara_x_preferred":[
        "\u0627\u0644\u063a\u062f\u0641\u0629"
    ],
    "name:und_x_variant":[
        "Rhadfa",
        "Al Ghadfah",
        "Al \u2018Adfah"
    ],
    "wof:name":"Al Ghadfah",
    "wof:placetype":"locality"
},
  "geometry": {"coordinates":[36.79058,35.6742],"type":"Point"}
}