{
  "type": "Feature",
  "properties": {
    "gn:admin1_code":"2.0",
    "gn:asciiname":"Bayt Qanuta",
    "gn:country_code":"SY",
    "gn:dem":40,
    "gn:feature_class":"P",
    "gn:feature_code":"PPL",
    "gn:name":"Bayt Q\u0101n\u016b\u0163\u0101",
    "gn:population":0,
    "gn:timezone":"Asia/Damascus",
    "iso:country":"SY",
    "name:und_x_variant":[
        "Bayt Q\u0101n\u016b\u0163\u0101"
    ],
    "wof:name":"Bayt Qanuta",
    "wof:placetype":"locality"
},
  "geometry": {"coordinates":[35.97917,35.28333],"type":"Point"}
}