{
  "type": "Feature",
  "properties": {
    "gn:admin1_code":"1.0",
    "gn:asciiname":"Khass",
    "gn:country_code":"SY",
    "gn:dem":430,
    "gn:feature_class":"P",
    "gn:feature_code":"PPL",
    "gn:name":"Khass",
    "gn:population":0,
    "gn:timezone":"Asia/Damascus",
    "iso:country":"SY",
    "name:ara_x_preferred":[
        "\u062e\u0633"
    ],
    "name:tur_x_preferred":[
        "Khass"
    ],
    "wof:name":"Khass",
    "wof:placetype":"locality"
},
  "geometry": {"coordinates":[40.62164,36.96437],"type":"Point"}
}