{
  "type": "Feature",
  "properties": {
    "gn:admin1_code":"4.0",
    "gn:asciiname":"`Abd Allah al `Isa",
    "gn:country_code":"SY",
    "gn:dem":354,
    "gn:feature_class":"P",
    "gn:feature_code":"PPL",
    "gn:name":"\u2018Abd All\u0101h al \u2018\u012as\u00e1",
    "gn:population":0,
    "gn:timezone":"Asia/Damascus",
    "iso:country":"SY",
    "name:ara_x_preferred":[
        "\u0639\u0628\u062f \u0627\u0644\u0644\u0647 \u0627\u0644\u0639\u064a\u0633\u0649"
    ],
    "name:und_x_variant":[
        "\u2018Abd All\u0101h al \u2018\u012as\u00e1"
    ],
    "wof:name":"`Abd Allah al `Isa",
    "wof:placetype":"locality"
},
  "geometry": {"coordinates":[38.14283,35.83558],"type":"Point"}
}