{
  "type": "Feature",
  "properties": {
    "gn:admin1_code":"10.0",
    "gn:asciiname":"Al Mubarakat",
    "gn:country_code":"SY",
    "gn:dem":360,
    "gn:feature_class":"P",
    "gn:feature_code":"PPL",
    "gn:name":"Al Mub\u0101rak\u0101t",
    "gn:population":0,
    "gn:timezone":"Asia/Damascus",
    "iso:country":"SY",
    "name:ara_x_preferred":[
        "\u0627\u0644\u0645\u0628\u0627\u0631\u0643\u0627\u062a"
    ],
    "name:ara_x_variant":[
        "\u0645\u0628\u0627\u0631\u0643\u0627\u062a"
    ],
    "name:fas_x_preferred":[
        "\u0627\u0644\u0645\u0628\u0627\u0631\u06a9\u0627\u062a"
    ],
    "name:pol_x_preferred":[
        "Al-Mubarakat"
    ],
    "name:und_x_variant":[
        "Mb\u00e2rak\u00e2te",
        "Mb\u0101rak\u0101t",
        "Mub\u0101rak\u0101t",
        "Al Mub\u0101rak\u0101t"
    ],
    "name:vie_x_preferred":[
        "Mubarakat"
    ],
    "wof:name":"Al Mubarakat",
    "wof:placetype":"locality"
},
  "geometry": {"coordinates":[36.86175,35.12213],"type":"Point"}
}