{
  "type": "Feature",
  "properties": {
    "gn:admin1_code":"9.0",
    "gn:asciiname":"Qusayr al Ward",
    "gn:country_code":"SY",
    "gn:dem":330,
    "gn:feature_class":"P",
    "gn:feature_code":"PPL",
    "gn:name":"Qu\u015fayr al Ward",
    "gn:population":0,
    "gn:timezone":"Asia/Damascus",
    "iso:country":"SY",
    "name:ara_x_preferred":[
        "\u0642\u0635\u0631 \u0627\u0644\u0648\u0631\u062f"
    ],
    "name:ara_x_variant":[
        "\u0642\u0635\u064a\u0631 \u0627\u0644\u0648\u0631\u062f"
    ],
    "name:und_x_variant":[
        "Kse\u00efr el Ouard",
        "Qoussa\u00efr el Ouard",
        "Qasr el Ouard",
        "Qa\u015fr al Ward",
        "Qu\u015fayr al Ward"
    ],
    "wof:name":"Qusayr al Ward",
    "wof:placetype":"locality"
},
  "geometry": {"coordinates":[37.45535,36.11644],"type":"Point"}
}