{
  "type": "Feature",
  "properties": {
    "gn:admin1_code":"2.0",
    "gn:asciiname":"As Samiyah",
    "gn:country_code":"SY",
    "gn:dem":66,
    "gn:feature_class":"P",
    "gn:feature_code":"PPL",
    "gn:name":"As S\u0101m\u012byah",
    "gn:population":0,
    "gn:timezone":"Asia/Damascus",
    "iso:country":"SY",
    "name:ara_x_preferred":[
        "\u0633\u0627\u0645\u064a\u0629"
    ],
    "name:ara_x_variant":[
        "\u0627\u0644\u0633\u0627\u0645\u064a\u0629"
    ],
    "name:und_x_variant":[
        "S\u0101miyah",
        "As S\u0101m\u012byah",
        "S\u0101m\u012byah",
        "Samiya"
    ],
    "wof:name":"As Samiyah",
    "wof:placetype":"locality"
},
  "geometry": {"coordinates":[35.96162,35.56142],"type":"Point"}
}