{
  "type": "Feature",
  "properties": {
    "gn:admin1_code":"14.0",
    "gn:asciiname":"Bishra'il",
    "gn:country_code":"SY",
    "gn:dem":483,
    "gn:feature_class":"P",
    "gn:feature_code":"PPL",
    "gn:name":"Bishr\u0101\u2019\u012bl",
    "gn:population":0,
    "gn:timezone":"Asia/Damascus",
    "iso:country":"SY",
    "name:ara_x_preferred":[
        "Bishr\u0101\u2019\u012bl"
    ],
    "name:ara_x_variant":[
        "\u0628\u0634\u0631\u0627\u0626\u064a\u0644"
    ],
    "name:und_x_variant":[
        "Bichr\u00e2yel"
    ],
    "wof:name":"Bishra'il",
    "wof:placetype":"locality"
},
  "geometry": {"coordinates":[36.19758,34.85442],"type":"Point"}
}