{
  "type": "Feature",
  "properties": {
    "gn:admin1_code":"9.0",
    "gn:asciiname":"Jaban",
    "gn:country_code":"SY",
    "gn:dem":489,
    "gn:feature_class":"P",
    "gn:feature_code":"PPL",
    "gn:name":"J\u0101b\u0101n",
    "gn:population":0,
    "gn:timezone":"Asia/Damascus",
    "iso:country":"SY",
    "name:ara_x_preferred":[
        "J\u0101b\u0101n"
    ],
    "name:ara_x_variant":[
        "\u062c\u0627\u0628\u0627\u0646"
    ],
    "name:fas_x_preferred":[
        "\u062c\u0627\u0628\u0627\u0646"
    ],
    "name:und_x_variant":[
        "Tchap\u00e2ne",
        "Shab\u0101n"
    ],
    "wof:name":"Jaban",
    "wof:placetype":"locality"
},
  "geometry": {"coordinates":[38.5394,36.54157],"type":"Point"}
}