{
  "type": "Feature",
  "properties": {
    "gn:admin1_code":"9.0",
    "gn:asciiname":"Tahtik Fawqani",
    "gn:country_code":"SY",
    "gn:dem":491,
    "gn:feature_class":"P",
    "gn:feature_code":"PPL",
    "gn:name":"Ta\u1e29t\u012bk Fawq\u0101n\u012b",
    "gn:population":0,
    "gn:timezone":"Asia/Damascus",
    "iso:country":"SY",
    "name:ara_x_preferred":[
        "\u062a\u062d\u062a\u064a\u0643 \u0641\u0648\u0642\u0627\u0646\u064a"
    ],
    "name:und_x_variant":[
        "Ta\u1e29t\u012bk Fawq\u0101n\u012b"
    ],
    "wof:name":"Tahtik Fawqani",
    "wof:placetype":"locality"
},
  "geometry": {"coordinates":[38.52952,36.7327],"type":"Point"}
}