{
  "type": "Feature",
  "properties": {
    "gn:admin1_code":"10.0",
    "gn:asciiname":"Abu Hubaylat",
    "gn:country_code":"SY",
    "gn:dem":607,
    "gn:feature_class":"P",
    "gn:feature_code":"PPL",
    "gn:name":"Ab\u016b \u1e28ubayl\u0101t",
    "gn:population":0,
    "gn:timezone":"Asia/Damascus",
    "iso:country":"SY",
    "name:ara_x_preferred":[
        "\u0623\u0628\u0648 \u062d\u0628\u064a\u0644\u0627\u062a"
    ],
    "name:und_x_variant":[
        "Abou Hbe\u00efl\u00e2te",
        "Ab\u016b Hbayl\u0101t",
        "Ab\u016b \u1e28ubayl\u0101t"
    ],
    "wof:name":"Abu Hubaylat",
    "wof:placetype":"locality"
},
  "geometry": {"coordinates":[37.31146,35.03120999999999],"type":"Point"}
}