{
  "type": "Feature",
  "properties": {
    "gn:admin1_code":"0.0",
    "gn:asciiname":"Geshur",
    "gn:country_code":"SY",
    "gn:dem":349,
    "gn:feature_class":"P",
    "gn:feature_code":"STLMT",
    "gn:name":"Geshur",
    "gn:population":0,
    "gn:timezone":"Asia/Damascus",
    "iso:country":"SY",
    "name:ces_x_preferred":[
        "Ge\u0161ur"
    ],
    "name:heb_x_preferred":[
        "\u05d2\u05e9\u05d5\u05e8"
    ],
    "name:pol_x_preferred":[
        "Geszur"
    ],
    "name:vie_x_preferred":[
        "Geshur"
    ],
    "wof:name":"Geshur",
    "wof:placetype":"locality"
},
  "geometry": {"coordinates":[35.71808,32.81873],"type":"Point"}
}