{
  "type": "Feature",
  "properties": {
    "gn:admin1_code":"10.0",
    "gn:asciiname":"Jubb Razaq",
    "gn:country_code":"SY",
    "gn:dem":465,
    "gn:feature_class":"P",
    "gn:feature_code":"PPL",
    "gn:name":"Jubb Razaq",
    "gn:population":0,
    "gn:timezone":"Asia/Damascus",
    "iso:country":"SY",
    "name:ara_x_preferred":[
        "\u062c\u0628 \u0631\u0632\u0642"
    ],
    "name:und_x_variant":[
        "Arze\u00efj\u00e9",
        "Joubb Rze\u00efq",
        "Jubb Ruzayq",
        "Jubb Razaq"
    ],
    "wof:name":"Jubb Razaq",
    "wof:placetype":"locality"
},
  "geometry": {"coordinates":[37.21998,35.26392],"type":"Point"}
}