{
  "type": "Feature",
  "properties": {
    "gn:admin1_code":"9.0",
    "gn:asciiname":"Sijju Salamah",
    "gn:country_code":"SY",
    "gn:dem":569,
    "gn:feature_class":"P",
    "gn:feature_code":"PPL",
    "gn:name":"Sijj\u016b Sal\u0101mah",
    "gn:population":0,
    "gn:timezone":"Asia/Damascus",
    "iso:country":"SY",
    "name:ara_x_preferred":[
        "\u015e\u016bdj\u012b"
    ],
    "name:ara_x_variant":[
        "\u0635\u0648\u062f\u062c\u064a",
        "\u0633\u062c\u0648 \u0633\u0644\u0627\u0645\u0629"
    ],
    "name:und_x_variant":[
        "S\u016bj\u012b",
        "Soudji",
        "Sijj\u016b Sal\u0101mah"
    ],
    "wof:name":"Sijju Salamah",
    "wof:placetype":"locality"
},
  "geometry": {"coordinates":[37.07767,36.61777],"type":"Point"}
}