{
  "type": "Feature",
  "properties": {
    "gn:admin1_code":"2.0",
    "gn:asciiname":"Kurt Fawqani",
    "gn:country_code":"SY",
    "gn:dem":508,
    "gn:feature_class":"P",
    "gn:feature_code":"PPL",
    "gn:name":"Kurt Fawq\u0101n\u012b",
    "gn:population":0,
    "gn:timezone":"Asia/Damascus",
    "iso:country":"SY",
    "name:ara_x_preferred":[
        "\u0643\u0631\u062a \u0641\u0648\u0642\u0627\u0646\u064a"
    ],
    "name:und_x_variant":[
        "Kert Fawq\u0101n\u012b",
        "Kurt Fawq\u0101n\u012b"
    ],
    "wof:name":"Kurt Fawqani",
    "wof:placetype":"locality"
},
  "geometry": {"coordinates":[36.10996,35.69747],"type":"Point"}
}