{
  "type": "Feature",
  "properties": {
    "gn:admin1_code":"1.0",
    "gn:asciiname":"Khirbat `Aridah",
    "gn:country_code":"SY",
    "gn:dem":371,
    "gn:feature_class":"P",
    "gn:feature_code":"PPL",
    "gn:name":"Khirbat \u2018Ar\u012b\u1e11ah",
    "gn:population":0,
    "gn:timezone":"Asia/Damascus",
    "iso:country":"SY",
    "name:ara_x_preferred":[
        "\u062e\u0631\u0628\u0629 \u0639\u0631\u064a\u0636\u0629"
    ],
    "name:tur_x_preferred":[
        "Khirbat \u2018Ar\u012b\u1e11ah"
    ],
    "name:und_x_variant":[
        "Kheurbet Aar\u00eeda"
    ],
    "wof:name":"Khirbat `Aridah",
    "wof:placetype":"locality"
},
  "geometry": {"coordinates":[41.44568,36.90282],"type":"Point"}
}