{
  "type": "Feature",
  "properties": {
    "gn:admin1_code":"9.0",
    "gn:asciiname":"Khirbat Tuwayni",
    "gn:country_code":"SY",
    "gn:dem":381,
    "gn:feature_class":"P",
    "gn:feature_code":"PPL",
    "gn:name":"Khirbat Tuwayn\u012b",
    "gn:population":0,
    "gn:timezone":"Asia/Damascus",
    "iso:country":"SY",
    "name:ara_x_preferred":[
        "\u062e\u0631\u0628\u0629 \u062a\u0648\u064a\u0646\u064a"
    ],
    "name:und_x_variant":[
        "Kheurbet Toua\u00efni",
        "Kheurbet ett Toue\u00efni",
        "Khirbat Tuwayn\u012b"
    ],
    "wof:name":"Khirbat Tuwayni",
    "wof:placetype":"locality"
},
  "geometry": {"coordinates":[38.13708,36.38613],"type":"Point"}
}