{
  "type": "Feature",
  "properties": {
    "gn:admin1_code":"1.0",
    "gn:asciiname":"Khalid",
    "gn:country_code":"SY",
    "gn:dem":344,
    "gn:feature_class":"P",
    "gn:feature_code":"PPL",
    "gn:name":"Kh\u0101lid",
    "gn:population":0,
    "gn:timezone":"Asia/Damascus",
    "iso:country":"SY",
    "name:ara_x_preferred":[
        "Kh\u0101n\u012bk"
    ],
    "name:ara_x_variant":[
        "Ch\u0101m Kh\u0101n\u012bk",
        "\u0686\u0627\u0645 \u062e\u0627\u0646\u064a\u0643",
        "\u062e\u0627\u0646\u064a\u0643",
        "Kh\u0101lid",
        "\u062e\u0627\u0644\u062f"
    ],
    "name:kur_x_preferred":[
        "Xan\u00eek"
    ],
    "name:und_x_variant":[
        "Xanik",
        "\u062e\u0627\u0646\u0643"
    ],
    "wof:name":"Khalid",
    "wof:placetype":"locality"
},
  "geometry": {"coordinates":[42.371,37.074],"type":"Point"}
}