{
  "type": "Feature",
  "properties": {
    "gn:admin1_code":"10.0",
    "gn:asciiname":"Tall an Nahr",
    "gn:country_code":"SY",
    "gn:dem":281,
    "gn:feature_class":"P",
    "gn:feature_code":"PPL",
    "gn:name":"Tall an Nahr",
    "gn:population":0,
    "gn:timezone":"Asia/Damascus",
    "iso:country":"SY",
    "name:ara_x_preferred":[
        "\u062a\u0644 \u0627\u0644\u0646\u0647\u0631"
    ],
    "name:ara_x_variant":[
        "\u062a\u0644 \u0633\u0643\u064a\u0646",
        "\u062a\u0644 \u0633\u0643\u064a\u0646 \u0633\u0627\u0631\u0648\u062a"
    ],
    "name:und_x_variant":[
        "Tell Skine es Saroute",
        "Tell Sikk\u00eene S\u00e2ro\u00fbte",
        "Tall Sikk\u00eene S\u00e2ro\u00fbte",
        "Tall an Nahr",
        "Tall Sikk\u012bn",
        "Tall Sikk\u012bn S\u0101r\u016bt"
    ],
    "wof:name":"Tall an Nahr",
    "wof:placetype":"locality"
},
  "geometry": {"coordinates":[36.58207,35.15972],"type":"Point"}
}