{
  "type": "Feature",
  "properties": {
    "gn:admin1_code":"9.0",
    "gn:asciiname":"Abu Hayj",
    "gn:country_code":"SY",
    "gn:dem":504,
    "gn:feature_class":"P",
    "gn:feature_code":"PPL",
    "gn:name":"Ab\u016b Hayj",
    "gn:population":0,
    "gn:timezone":"Asia/Damascus",
    "iso:country":"SY",
    "name:ara_x_preferred":[
        "\u0623\u0628\u0648 \u0647\u064a\u062c"
    ],
    "name:und_x_variant":[
        "Abou He\u00efj",
        "Abou Heidj",
        "Ab\u016b Hayj"
    ],
    "wof:name":"Abu Hayj",
    "wof:placetype":"locality"
},
  "geometry": {"coordinates":[37.67185,36.44915],"type":"Point"}
}