{
  "type": "Feature",
  "properties": {
    "gn:admin1_code":"11.0",
    "gn:asciiname":"Ar Riqama",
    "gn:country_code":"SY",
    "gn:dem":784,
    "gn:feature_class":"P",
    "gn:feature_code":"PPLA3",
    "gn:name":"Ar Riq\u0101m\u0101",
    "gn:population":0,
    "gn:timezone":"Asia/Damascus",
    "iso:country":"SY",
    "name:ara_x_preferred":[
        "\u0627\u0644\u0631\u0642\u0627\u0645\u0629"
    ],
    "name:ara_x_variant":[
        "Ar Riq\u0101m\u0101",
        "\u0627\u0644\u0631\u0642\u0627\u0645\u0627"
    ],
    "name:und_x_variant":[
        "Irg\u0101ma",
        "Arq\u0101mah",
        "Irghama",
        "Raq\u0101mah",
        "Irq\u0101ma",
        "Riq\u00e2ma",
        "Riq\u0101mah",
        "Ar Riq\u0101mah"
    ],
    "wof:name":"Ar Riqama",
    "wof:placetype":"locality"
},
  "geometry": {"coordinates":[36.91909,34.53879000000001],"type":"Point"}
}