{
  "type": "Feature",
  "properties": {
    "gn:admin1_code":"9.0",
    "gn:asciiname":"`Uwaynah",
    "gn:country_code":"SY",
    "gn:dem":364,
    "gn:feature_class":"P",
    "gn:feature_code":"PPL",
    "gn:name":"\u2018Uwaynah",
    "gn:population":0,
    "gn:timezone":"Asia/Damascus",
    "iso:country":"SY",
    "name:ara_x_preferred":[
        "\u0639\u0648\u064a\u0646\u0629"
    ],
    "name:und_x_variant":[
        "Aaoue\u00efn\u00e9",
        "Aaoue\u00efni",
        "\u2018Uwaynah"
    ],
    "wof:name":"`Uwaynah",
    "wof:placetype":"locality"
},
  "geometry": {"coordinates":[38.21212,36.68229],"type":"Point"}
}