{
  "type": "Feature",
  "properties": {
    "gn:admin1_code":"2.0",
    "gn:asciiname":"Rayyanah",
    "gn:country_code":"SY",
    "gn:dem":191,
    "gn:feature_class":"P",
    "gn:feature_code":"PPL",
    "gn:name":"Rayy\u0101nah",
    "gn:population":0,
    "gn:timezone":"Asia/Damascus",
    "iso:country":"SY",
    "name:ara_x_preferred":[
        "\u0631\u064a\u0627\u0646\u0629"
    ],
    "name:ara_x_variant":[
        "\u0627\u0644\u0631\u064a\u0627\u0646\u0629"
    ],
    "name:und_x_variant":[
        "Rayy\u0101nah",
        "Rayyana",
        "Ar Rayy\u0101nah",
        "Yakhmur"
    ],
    "wof:name":"Rayyanah",
    "wof:placetype":"locality"
},
  "geometry": {"coordinates":[35.94592,35.78487],"type":"Point"}
}