{
  "type": "Feature",
  "properties": {
    "gn:admin1_code":"9.0",
    "gn:asciiname":"Wudeihi",
    "gn:country_code":"SY",
    "gn:dem":350,
    "gn:feature_class":"P",
    "gn:feature_code":"PPL",
    "gn:name":"Wudeihi",
    "gn:population":0,
    "gn:timezone":"Asia/Damascus",
    "iso:country":"SY",
    "name:ara_x_preferred":[
        "\u0627\u0644\u0648\u0636\u064a\u062d\u064a"
    ],
    "name:ara_x_variant":[
        "\u0648\u0636\u064a\u062d\u064a"
    ],
    "name:und_x_variant":[
        "Al Wa\u1e11\u012b\u1e29\u012b",
        "Wa\u1e11\u012b\u1e29\u012b",
        "Wa\u1e11\u1e29\u012b",
        "Wudeihi",
        "Oud\u00e9h",
        "O\u00fbd\u00e9hi",
        "Wu\u1e11ay\u1e29\u012b"
    ],
    "wof:name":"Wudeihi",
    "wof:placetype":"locality"
},
  "geometry": {"coordinates":[37.12878,36.10183],"type":"Point"}
}