{
  "type": "Feature",
  "properties": {
    "gn:admin1_code":"9.0",
    "gn:asciiname":"Kurdala Wastani",
    "gn:country_code":"SY",
    "gn:dem":464,
    "gn:feature_class":"P",
    "gn:feature_code":"PPL",
    "gn:name":"Kurdal\u0101 Was\u0163\u0101n\u012b",
    "gn:population":0,
    "gn:timezone":"Asia/Damascus",
    "iso:country":"SY",
    "name:ara_x_preferred":[
        "\u0643\u0631\u062f\u0644\u0627 \u0648\u0633\u0637\u0627\u0646\u064a"
    ],
    "name:und_x_variant":[
        "Qourdala Ouast\u00e2ni",
        "Qurdal\u0101 al Was\u0163\u0101n\u012b",
        "Kurdal\u0101 Was\u0163\u0101n\u012b"
    ],
    "wof:name":"Kurdala Wastani",
    "wof:placetype":"locality"
},
  "geometry": {"coordinates":[37.92571,36.59047],"type":"Point"}
}