{
  "type": "Feature",
  "properties": {
    "gn:admin1_code":"4.0",
    "gn:asciiname":"Shatnah",
    "gn:country_code":"SY",
    "gn:dem":338,
    "gn:feature_class":"P",
    "gn:feature_code":"PPL",
    "gn:name":"Shatnah",
    "gn:population":0,
    "gn:timezone":"Asia/Damascus",
    "iso:country":"SY",
    "name:ara_x_preferred":[
        "\u0634\u062a\u0646\u0629"
    ],
    "wof:name":"Shatnah",
    "wof:placetype":"locality"
},
  "geometry": {"coordinates":[38.27717,35.80777],"type":"Point"}
}