{
  "type": "Feature",
  "properties": {
    "gn:admin1_code":"8.0",
    "gn:asciiname":"Ard al Habbasat",
    "gn:country_code":"SY",
    "gn:dem":605,
    "gn:feature_class":"P",
    "gn:feature_code":"PPLL",
    "gn:name":"Ar\u1e11 al \u1e28abb\u0101s\u0101t",
    "gn:population":0,
    "gn:timezone":"Asia/Damascus",
    "iso:country":"SY",
    "name:ara_x_preferred":[
        "\u0627\u0631\u0636 \u0627\u0644\u062d\u0628\u0627\u0633\u0627\u062a"
    ],
    "name:und_x_variant":[
        "Ar\u1e11 al \u1e28abb\u0101s\u0101t"
    ],
    "wof:name":"Ard al Habbasat",
    "wof:placetype":"locality"
},
  "geometry": {"coordinates":[36.54306,33.55465],"type":"Point"}
}