{
  "type": "Feature",
  "properties": {
    "gn:admin1_code":"2.0",
    "gn:asciiname":"Harat Wadi Jahannam",
    "gn:country_code":"SY",
    "gn:dem":30,
    "gn:feature_class":"P",
    "gn:feature_code":"PPL",
    "gn:name":"\u1e28\u0101rat W\u0101d\u012b Jahannam",
    "gn:population":0,
    "gn:timezone":"Asia/Damascus",
    "iso:country":"SY",
    "name:ara_x_preferred":[
        "\u062d\u0627\u0631\u0629 \u0648\u0627\u062f\u064a \u062c\u0647\u0646\u0645"
    ],
    "name:und_x_variant":[
        "\u1e28\u0101rat W\u0101d\u012b Jahannam"
    ],
    "wof:name":"Harat Wadi Jahannam",
    "wof:placetype":"locality"
},
  "geometry": {"coordinates":[35.78915999999999,35.62842],"type":"Point"}
}