{
  "type": "Feature",
  "properties": {
    "gn:admin1_code":"7.0",
    "gn:asciiname":"Sahran",
    "gn:country_code":"SY",
    "gn:dem":324,
    "gn:feature_class":"P",
    "gn:feature_code":"PPL",
    "gn:name":"Sahr\u0101n",
    "gn:population":0,
    "gn:timezone":"Asia/Damascus",
    "iso:country":"SY",
    "name:ara_x_preferred":[
        "\u0633\u0647\u0631\u0627\u0646"
    ],
    "name:und_x_variant":[
        "Sahr\u0101n"
    ],
    "wof:name":"Sahran",
    "wof:placetype":"locality"
},
  "geometry": {"coordinates":[39.76792,35.96908],"type":"Point"}
}