{
  "type": "Feature",
  "properties": {
    "gn:admin1_code":"8.0",
    "gn:asciiname":"Hawsh Sahya",
    "gn:country_code":"SY",
    "gn:dem":656,
    "gn:feature_class":"P",
    "gn:feature_code":"PPL",
    "gn:name":"\u1e28awsh \u015eahy\u0101",
    "gn:population":0,
    "gn:timezone":"Asia/Damascus",
    "iso:country":"SY",
    "name:ara_x_preferred":[
        "\u062d\u0648\u0634 \u0635\u0647\u064a\u0627"
    ],
    "name:und_x_variant":[
        "Haouch S\u00e2ya",
        "Haouch Sayeh",
        "\u1e28awsh \u015e\u0101y\u0101",
        "\u1e28awsh \u015eahy\u0101"
    ],
    "wof:name":"Hawsh Sahya",
    "wof:placetype":"locality"
},
  "geometry": {"coordinates":[36.34605,33.43065],"type":"Point"}
}