{
  "type": "Feature",
  "properties": {
    "gn:admin1_code":"11.0",
    "gn:asciiname":"`Azazat",
    "gn:country_code":"SY",
    "gn:dem":506,
    "gn:feature_class":"P",
    "gn:feature_code":"PPL",
    "gn:name":"\u2018Az\u0101z\u0101t",
    "gn:population":0,
    "gn:timezone":"Asia/Damascus",
    "iso:country":"SY",
    "name:ara_x_preferred":[
        "\u2018Az\u0101z\u0101t"
    ],
    "name:ara_x_variant":[
        "\u0639\u0632\u0627\u0632\u0627\u062a"
    ],
    "wof:name":"`Azazat",
    "wof:placetype":"locality"
},
  "geometry": {"coordinates":[36.4838,34.57039],"type":"Point"}
}