{
  "type": "Feature",
  "properties": {
    "gn:admin1_code":"7.0",
    "gn:asciiname":"At Tabiyah",
    "gn:country_code":"SY",
    "gn:dem":198,
    "gn:feature_class":"P",
    "gn:feature_code":"PPL",
    "gn:name":"A\u0163 \u0162\u0101biyah",
    "gn:population":0,
    "gn:timezone":"Asia/Damascus",
    "iso:country":"SY",
    "name:ara_x_preferred":[
        "\u0627\u0644\u0637\u0627\u0628\u064a\u0629"
    ],
    "name:und_x_variant":[
        "A\u0163 \u0162\u0101biyah",
        "A\u0163 \u0162\u0101b\u012byah"
    ],
    "wof:name":"At Tabiyah",
    "wof:placetype":"locality"
},
  "geometry": {"coordinates":[40.29627,35.25016],"type":"Point"}
}