{
  "type": "Feature",
  "properties": {
    "gn:admin1_code":"1.0",
    "gn:asciiname":"Hanajiya",
    "gn:country_code":"SY",
    "gn:dem":273,
    "gn:feature_class":"P",
    "gn:feature_code":"PPL",
    "gn:name":"Han\u0101jiy\u0101",
    "gn:population":0,
    "gn:timezone":"Asia/Damascus",
    "iso:country":"SY",
    "name:ara_x_preferred":[
        "\u0647\u0646\u0627\u062c\u064a\u0627"
    ],
    "name:und_x_variant":[
        "Han\u0101jiy\u0101"
    ],
    "wof:name":"Hanajiya",
    "wof:placetype":"locality"
},
  "geometry": {"coordinates":[40.77869000000001,36.2213],"type":"Point"}
}