{
  "type": "Feature",
  "properties": {
    "gn:admin1_code":"11.0",
    "gn:asciiname":"Bayt Qurayn",
    "gn:country_code":"SY",
    "gn:dem":137,
    "gn:feature_class":"P",
    "gn:feature_code":"PPL",
    "gn:name":"Bayt Qurayn",
    "gn:population":0,
    "gn:timezone":"Asia/Damascus",
    "iso:country":"SY",
    "name:ara_x_preferred":[
        "\u0628\u064a\u062a \u0642\u0631\u064a\u0646"
    ],
    "name:und_x_variant":[
        "Be\u00eft Qra\u00efne",
        "Bayt Qurayn"
    ],
    "wof:name":"Bayt Qurayn",
    "wof:placetype":"locality"
},
  "geometry": {"coordinates":[36.19645,34.66992],"type":"Point"}
}