{
  "type": "Feature",
  "properties": {
    "gn:admin1_code":"12.0",
    "gn:asciiname":"Mawrantaz",
    "gn:country_code":"SY",
    "gn:dem":391,
    "gn:feature_class":"P",
    "gn:feature_code":"PPL",
    "gn:name":"Mawran\u0163\u0101z",
    "gn:population":0,
    "gn:timezone":"Asia/Damascus",
    "iso:country":"SY",
    "name:ara_x_preferred":[
        "\u0645\u0648\u0631\u0646\u0637\u0627\u0632"
    ],
    "name:und_x_variant":[
        "Mawran\u0163\u0101z",
        "Mourinngaz"
    ],
    "wof:name":"Mawrantaz",
    "wof:placetype":"locality"
},
  "geometry": {"coordinates":[36.21343,35.81944],"type":"Point"}
}