{
  "type": "Feature",
  "properties": {
    "gn:admin1_code":"14.0",
    "gn:asciiname":"Ash Shaybani",
    "gn:country_code":"SY",
    "gn:dem":604,
    "gn:feature_class":"P",
    "gn:feature_code":"PPL",
    "gn:name":"Ash Shayb\u0101n\u012b",
    "gn:population":0,
    "gn:timezone":"Asia/Damascus",
    "iso:country":"SY",
    "name:ara_x_preferred":[
        "\u0627\u0644\u0634\u064a\u0628\u0627\u0646\u064a"
    ],
    "name:und_x_variant":[
        "Ash Shayb\u0101n\u012b"
    ],
    "wof:name":"Ash Shaybani",
    "wof:placetype":"locality"
},
  "geometry": {"coordinates":[36.05152,35.14712],"type":"Point"}
}