{
  "type": "Feature",
  "properties": {
    "gn:admin1_code":"9.0",
    "gn:asciiname":"Darb an Nawb Saghir",
    "gn:country_code":"SY",
    "gn:dem":403,
    "gn:feature_class":"P",
    "gn:feature_code":"PPL",
    "gn:name":"Darb an Nawb Sagh\u012br",
    "gn:population":0,
    "gn:timezone":"Asia/Damascus",
    "iso:country":"SY",
    "name:ara_x_preferred":[
        "\u062f\u0631\u0628 \u0627\u0644\u0646\u0648\u0628"
    ],
    "name:ara_x_variant":[
        "\u062f\u0631\u0628 \u0627\u0644\u0646\u0648\u0628 \u0635\u063a\u064a\u0631"
    ],
    "name:kur_x_preferred":[
        "Derbe Nob\u00ea Mezin"
    ],
    "name:kur_x_variant":[
        "\u062f\u06d5\u0631\u0628\u06d5\u0646\u06c6\u0628\u06ce \u0645\u06d5\u0632\u0646",
        "\u062f\u06d5\u0631\u0628\u06d5 \u0646\u06c6\u0628\u06ce \u0645\u06d5\u0632\u0646"
    ],
    "name:und_x_variant":[
        "Darb an Nawb",
        "Darb enn N\u00f4b",
        "Darb an N\u016bb",
        "Derbenob\u00ea Mezin",
        "Darb an Nawb Sagh\u012br"
    ],
    "wof:name":"Darb an Nawb Saghir",
    "wof:placetype":"locality"
},
  "geometry": {"coordinates":[38.15183,36.78503],"type":"Point"}
}