{
  "type": "Feature",
  "properties": {
    "gn:admin1_code":"14.0",
    "gn:asciiname":"At Tun al Jurd",
    "gn:country_code":"SY",
    "gn:dem":947,
    "gn:feature_class":"P",
    "gn:feature_code":"PPL",
    "gn:name":"At T\u016bn al Jurd",
    "gn:population":0,
    "gn:timezone":"Asia/Damascus",
    "iso:country":"SY",
    "name:ara_x_preferred":[
        "\u0627\u0644\u062a\u0648\u0646 \u0627\u0644\u062c\u0631\u062f"
    ],
    "name:und_x_variant":[
        "To\u00fbn ej Jourd",
        "T\u016bn al Jurd",
        "Alt\u016bn al Jurd",
        "At T\u016bn al Jurd"
    ],
    "wof:name":"At Tun al Jurd",
    "wof:placetype":"locality"
},
  "geometry": {"coordinates":[36.14699,35.19115],"type":"Point"}
}