{
  "type": "Feature",
  "properties": {
    "gn:admin1_code":"1.0",
    "gn:asciiname":"Tall Dahab",
    "gn:country_code":"SY",
    "gn:dem":374,
    "gn:feature_class":"P",
    "gn:feature_code":"PPL",
    "gn:name":"Tall Dahab",
    "gn:population":0,
    "gn:timezone":"Asia/Damascus",
    "iso:country":"SY",
    "name:ara_x_preferred":[
        "\u062a\u0644 \u062f\u0647\u0628"
    ],
    "name:tur_x_preferred":[
        "Tall Dhahab"
    ],
    "name:und_x_variant":[
        "Tell Dahab",
        "Tall Dahab"
    ],
    "wof:name":"Tall Dahab",
    "wof:placetype":"locality"
},
  "geometry": {"coordinates":[41.15229,36.86788],"type":"Point"}
}