{
  "type": "Feature",
  "properties": {
    "gn:admin1_code":"14.0",
    "gn:asciiname":"Khirbat Makkar",
    "gn:country_code":"SY",
    "gn:dem":622,
    "gn:feature_class":"P",
    "gn:feature_code":"PPL",
    "gn:name":"Khirbat Makk\u0101r",
    "gn:population":0,
    "gn:timezone":"Asia/Damascus",
    "iso:country":"SY",
    "name:und_x_variant":[
        "Kheurbet Makk\u00e2r",
        "Khirbat Makk\u0101r"
    ],
    "wof:name":"Khirbat Makkar",
    "wof:placetype":"locality"
},
  "geometry": {"coordinates":[36.11925,35.07882],"type":"Point"}
}