{
  "type": "Feature",
  "properties": {
    "gn:admin1_code":"6.0",
    "gn:asciiname":"Ash Shaqraniyah",
    "gn:country_code":"SY",
    "gn:dem":629,
    "gn:feature_class":"P",
    "gn:feature_code":"PPL",
    "gn:name":"Ash Shaqr\u0101n\u012byah",
    "gn:population":0,
    "gn:timezone":"Asia/Damascus",
    "iso:country":"SY",
    "name:ara_x_preferred":[
        "\u0627\u0644\u0634\u0642\u0631\u0627\u0646\u064a\u0629"
    ],
    "name:und_x_variant":[
        "Ash Shuqr\u0101n\u012byah",
        "Ash Shaqr\u0101n\u012byah"
    ],
    "wof:name":"Ash Shaqraniyah",
    "wof:placetype":"locality"
},
  "geometry": {"coordinates":[36.48704,33.24759],"type":"Point"}
}