{
  "type": "Feature",
  "properties": {
    "gn:admin1_code":"4.0",
    "gn:asciiname":"Abu as Sakhrah",
    "gn:country_code":"SY",
    "gn:dem":334,
    "gn:feature_class":"P",
    "gn:feature_code":"PPL",
    "gn:name":"Ab\u016b a\u015f \u015eakhrah",
    "gn:population":0,
    "gn:timezone":"Asia/Damascus",
    "iso:country":"SY",
    "name:ara_x_preferred":[
        "\u0623\u0628\u0648 \u0627\u0644\u0635\u062e\u0631\u0629"
    ],
    "name:und_x_variant":[
        "Ab\u016b a\u015f \u015eakhrah"
    ],
    "wof:name":"Abu as Sakhrah",
    "wof:placetype":"locality"
},
  "geometry": {"coordinates":[38.44479000000001,35.98488],"type":"Point"}
}