{
  "type": "Feature",
  "properties": {
    "gn:admin1_code":"1.0",
    "gn:asciiname":"Khirbat al Ghazal",
    "gn:country_code":"SY",
    "gn:dem":379,
    "gn:feature_class":"P",
    "gn:feature_code":"PPL",
    "gn:name":"Khirbat al Ghaz\u0101l",
    "gn:population":0,
    "gn:timezone":"Asia/Damascus",
    "iso:country":"SY",
    "name:ara_x_preferred":[
        "\u062d\u0631\u0628\u0629 \u0627\u0644\u063a\u0632\u0627\u0644"
    ],
    "name:tur_x_preferred":[
        "Khirbat al Ghaz\u0101l"
    ],
    "name:und_x_variant":[
        "Kheurbet el Rhaz\u00e2l",
        "Khirbat al Ghaz\u0101l"
    ],
    "wof:name":"Khirbat al Ghazal",
    "wof:placetype":"locality"
},
  "geometry": {"coordinates":[40.98163,36.85141],"type":"Point"}
}