{
  "type": "Feature",
  "properties": {
    "gn:admin1_code":"14.0",
    "gn:asciiname":"Karmaya",
    "gn:country_code":"SY",
    "gn:dem":160,
    "gn:feature_class":"P",
    "gn:feature_code":"PPL",
    "gn:name":"Karm\u0101y\u0101",
    "gn:population":0,
    "gn:timezone":"Asia/Damascus",
    "iso:country":"SY",
    "name:ara_x_preferred":[
        "\u0643\u0631\u0645\u0627\u064a\u0627"
    ],
    "name:und_x_variant":[
        "Karm\u0101y\u0101"
    ],
    "wof:name":"Karmaya",
    "wof:placetype":"locality"
},
  "geometry": {"coordinates":[35.96165,35.08865],"type":"Point"}
}