{
  "type": "Feature",
  "properties": {
    "gn:admin1_code":"1.0",
    "gn:asciiname":"Rayya",
    "gn:country_code":"SY",
    "gn:dem":391,
    "gn:feature_class":"P",
    "gn:feature_code":"PPL",
    "gn:name":"Rayy\u0101",
    "gn:population":0,
    "gn:timezone":"Asia/Damascus",
    "iso:country":"SY",
    "name:ara_x_preferred":[
        "\u0631\u064a\u0627"
    ],
    "name:tur_x_preferred":[
        "Rayy\u0101"
    ],
    "name:und_x_variant":[
        "Ra\u00efya"
    ],
    "wof:name":"Rayya",
    "wof:placetype":"locality"
},
  "geometry": {"coordinates":[41.52097,36.98248],"type":"Point"}
}