{
  "type": "Feature",
  "properties": {
    "gn:admin1_code":"2.0",
    "gn:asciiname":"`Ayn Tantash",
    "gn:country_code":"SY",
    "gn:dem":1142,
    "gn:feature_class":"P",
    "gn:feature_code":"PPL",
    "gn:name":"\u2018Ayn \u0162an\u0163\u0101sh",
    "gn:population":0,
    "gn:timezone":"Asia/Damascus",
    "iso:country":"SY",
    "name:ara_x_preferred":[
        "\u0639\u064a\u0646 \u0637\u0646\u0637\u0627\u0634"
    ],
    "name:und_x_variant":[
        "A\u00efn Tennt\u00e2ch",
        "\u2018Ayn \u0162an\u0163\u0101sh"
    ],
    "wof:name":"`Ayn Tantash",
    "wof:placetype":"locality"
},
  "geometry": {"coordinates":[36.20151,35.60768],"type":"Point"}
}