{
  "type": "Feature",
  "properties": {
    "gn:admin1_code":"10.0",
    "gn:asciiname":"Rasm Hammam",
    "gn:country_code":"SY",
    "gn:dem":410,
    "gn:feature_class":"P",
    "gn:feature_code":"PPL",
    "gn:name":"Rasm \u1e28amm\u0101m",
    "gn:population":0,
    "gn:timezone":"Asia/Damascus",
    "iso:country":"SY",
    "name:ara_x_preferred":[
        "\u0631\u0633\u0645 \u062d\u0645\u0627\u0645"
    ],
    "name:und_x_variant":[
        "Rasm \u1e28amm\u0101m"
    ],
    "wof:name":"Rasm Hammam",
    "wof:placetype":"locality"
},
  "geometry": {"coordinates":[37.15712,35.41304],"type":"Point"}
}