{
  "type": "Feature",
  "properties": {
    "gn:admin1_code":"9.0",
    "gn:asciiname":"Sharabati",
    "gn:country_code":"SY",
    "gn:dem":602,
    "gn:feature_class":"P",
    "gn:feature_code":"PPL",
    "gn:name":"Shar\u0101b\u0101t\u012b",
    "gn:population":0,
    "gn:timezone":"Asia/Damascus",
    "iso:country":"SY",
    "name:ara_x_preferred":[
        "\u0634\u0631\u0627\u0628\u0627\u062a\u064a"
    ],
    "name:und_x_variant":[
        "Char\u00e2b\u00e2ti",
        "Shar\u0101b\u0101t\u012b"
    ],
    "wof:name":"Sharabati",
    "wof:placetype":"locality"
},
  "geometry": {"coordinates":[38.4482,36.73128],"type":"Point"}
}