{
  "type": "Feature",
  "properties": {
    "gn:admin1_code":"11.0",
    "gn:asciiname":"Ash Shanyah",
    "gn:country_code":"SY",
    "gn:dem":486,
    "gn:feature_class":"P",
    "gn:feature_code":"PPL",
    "gn:name":"Ash Shanyah",
    "gn:population":0,
    "gn:timezone":"Asia/Damascus",
    "iso:country":"SY",
    "name:ara_x_preferred":[
        "\u0627\u0644\u0634\u0646\u064a\u0629"
    ],
    "name:ara_x_variant":[
        "\u0634\u0646\u064a\u0629"
    ],
    "name:und_x_variant":[
        "Ch\u00e9ni\u00e9",
        "Shanyah",
        "Ash Shanyah"
    ],
    "wof:name":"Ash Shanyah",
    "wof:placetype":"locality"
},
  "geometry": {"coordinates":[36.45262,34.85975999999999],"type":"Point"}
}