{
  "type": "Feature",
  "properties": {
    "gn:admin1_code":"2.0",
    "gn:asciiname":"An Nawaqir",
    "gn:cc2":"SY",
    "gn:country_code":"SY",
    "gn:dem":721,
    "gn:feature_class":"P",
    "gn:feature_code":"PPL",
    "gn:name":"An Naw\u0101q\u012br",
    "gn:population":0,
    "gn:timezone":"Asia/Damascus",
    "iso:country":"SY",
    "name:und_x_variant":[
        "Nou\u00e2q\u00eer",
        "An Naw\u0101q\u012br"
    ],
    "wof:name":"An Nawaqir",
    "wof:placetype":"locality"
},
  "geometry": {"coordinates":[36.11667,35.23333],"type":"Point"}
}