{
  "type": "Feature",
  "properties": {
    "gn:admin1_code":"1.0",
    "gn:asciiname":"Mawrik Tahtani",
    "gn:country_code":"SY",
    "gn:dem":333,
    "gn:feature_class":"P",
    "gn:feature_code":"PPL",
    "gn:name":"Mawr\u012bk Ta\u1e29t\u0101n\u012b",
    "gn:population":0,
    "gn:timezone":"Asia/Damascus",
    "iso:country":"SY",
    "name:ara_x_preferred":[
        "\u0645\u0648\u0631\u064a\u0643 \u062a\u062d\u062a\u0627\u0646\u064a"
    ],
    "name:und_x_variant":[
        "Mo\u00fbrek Taht\u00e2ni",
        "M\u016brak at Ta\u1e29t\u0101n\u012b",
        "Mawr\u012bk Ta\u1e29t\u0101n\u012b"
    ],
    "wof:name":"Mawrik Tahtani",
    "wof:placetype":"locality"
},
  "geometry": {"coordinates":[40.77423,36.67538],"type":"Point"}
}