{
  "type": "Feature",
  "properties": {
    "gn:admin1_code":"6.0",
    "gn:asciiname":"An Nafi`ah",
    "gn:country_code":"SY",
    "gn:dem":453,
    "gn:feature_class":"P",
    "gn:feature_code":"PPL",
    "gn:name":"An N\u0101fi\u2018ah",
    "gn:population":0,
    "gn:timezone":"Asia/Damascus",
    "iso:country":"SY",
    "name:ara_x_preferred":[
        "\u0646\u0627\u0641\u0639\u0629"
    ],
    "name:ara_x_variant":[
        "\u0627\u0644\u0646\u0627\u0641\u0639\u0629"
    ],
    "name:und_x_variant":[
        "N\u00e2fa\u00e2",
        "Nafia\u00e2",
        "N\u0101fi\u2018ah",
        "An N\u0101fi\u2018ah"
    ],
    "wof:name":"An Nafi`ah",
    "wof:placetype":"locality"
},
  "geometry": {"coordinates":[35.89491,32.80954000000001],"type":"Point"}
}