{
  "type": "Feature",
  "properties": {
    "gn:admin1_code":"11.0",
    "gn:asciiname":"As Sikafiyah",
    "gn:country_code":"SY",
    "gn:dem":527,
    "gn:feature_class":"P",
    "gn:feature_code":"PPL",
    "gn:name":"As Sik\u0101f\u012byah",
    "gn:population":0,
    "gn:timezone":"Asia/Damascus",
    "iso:country":"SY",
    "name:ara_x_preferred":[
        "\u0627\u0644\u0633\u0643\u0627\u0641\u064a\u0629"
    ],
    "name:und_x_variant":[
        "As Sik\u0101f\u012byah"
    ],
    "wof:name":"As Sikafiyah",
    "wof:placetype":"locality"
},
  "geometry": {"coordinates":[36.52854,34.47176],"type":"Point"}
}