{
  "type": "Feature",
  "properties": {
    "gn:admin1_code":"9.0",
    "gn:asciiname":"Tall Sha`ir",
    "gn:country_code":"SY",
    "gn:dem":481,
    "gn:feature_class":"P",
    "gn:feature_code":"PPL",
    "gn:name":"Tall Sha\u2018\u012br",
    "gn:population":0,
    "gn:timezone":"Asia/Damascus",
    "iso:country":"SY",
    "name:ara_x_preferred":[
        "\u062a\u0644 \u0634\u0639\u064a\u0631"
    ],
    "name:und_x_variant":[
        "Tell Cha\u00efr",
        "Tall Sha\u2018\u012br"
    ],
    "wof:name":"Tall Sha`ir",
    "wof:placetype":"locality"
},
  "geometry": {"coordinates":[37.34352,36.61462],"type":"Point"}
}