{
  "type": "Feature",
  "properties": {
    "gn:admin1_code":"10.0",
    "gn:asciiname":"Shaqqat an Nuhaylah",
    "gn:country_code":"SY",
    "gn:dem":180,
    "gn:feature_class":"P",
    "gn:feature_code":"PPL",
    "gn:name":"Shaqqat an Nu\u1e29aylah",
    "gn:population":0,
    "gn:timezone":"Asia/Damascus",
    "iso:country":"SY",
    "name:ara_x_preferred":[
        "\u0634\u0642\u0629 \u0627\u0644\u0646\u062d\u064a\u0644\u0629"
    ],
    "name:und_x_variant":[
        "Chaqqet enn Nha\u00efl\u00e9",
        "Shaqqat an Nu\u1e29aylah"
    ],
    "wof:name":"Shaqqat an Nuhaylah",
    "wof:placetype":"locality"
},
  "geometry": {"coordinates":[36.24771,35.48837],"type":"Point"}
}