{
  "type": "Feature",
  "properties": {
    "gn:admin1_code":"14.0",
    "gn:asciiname":"`Ayn al Jawz",
    "gn:country_code":"SY",
    "gn:dem":462,
    "gn:feature_class":"P",
    "gn:feature_code":"PPL",
    "gn:name":"\u2018Ayn al Jawz",
    "gn:population":0,
    "gn:timezone":"Asia/Damascus",
    "iso:country":"SY",
    "name:ara_x_preferred":[
        "\u0639\u064a\u0646 \u0627\u0644\u062c\u0648\u0632"
    ],
    "name:und_x_variant":[
        "\u2018Ain ej Jaouz",
        "\u2018Ayn al Jawz",
        "A\u00efn ej Jaouz"
    ],
    "wof:name":"`Ayn al Jawz",
    "wof:placetype":"locality"
},
  "geometry": {"coordinates":[36.15026,34.87546],"type":"Point"}
}