{
  "type": "Feature",
  "properties": {
    "gn:admin1_code":"8.0",
    "gn:asciiname":"Muhammad Rifa`i",
    "gn:country_code":"SY",
    "gn:dem":601,
    "gn:feature_class":"P",
    "gn:feature_code":"PPL",
    "gn:name":"Mu\u1e29ammad Rif\u0101\u2018\u012b",
    "gn:population":0,
    "gn:timezone":"Asia/Damascus",
    "iso:country":"SY",
    "name:ara_x_preferred":[
        "\u0645\u062d\u0645\u062f \u0631\u0641\u0627\u0639\u064a"
    ],
    "name:und_x_variant":[
        "Mu\u1e29ammad Rif\u0101\u2018\u012b"
    ],
    "wof:name":"Muhammad Rifa`i",
    "wof:placetype":"locality"
},
  "geometry": {"coordinates":[36.63143,33.48232],"type":"Point"}
}