{
  "type": "Feature",
  "properties": {
    "gn:admin1_code":"9.0",
    "gn:asciiname":"Tuba",
    "gn:country_code":"SY",
    "gn:dem":433,
    "gn:feature_class":"P",
    "gn:feature_code":"PPL",
    "gn:name":"T\u016bb\u0101",
    "gn:population":0,
    "gn:timezone":"Asia/Damascus",
    "iso:country":"SY",
    "name:ara_x_preferred":[
        "T\u016bb\u0101"
    ],
    "name:ara_x_variant":[
        "\u062a\u0648\u0628\u0627"
    ],
    "name:und_x_variant":[
        "Sahr\u00eej",
        "\u015eah\u0101r\u012bj"
    ],
    "wof:name":"Tuba",
    "wof:placetype":"locality"
},
  "geometry": {"coordinates":[38.36202,36.51667],"type":"Point"}
}