{
  "type": "Feature",
  "properties": {
    "gn:admin1_code":"12.0",
    "gn:asciiname":"Al Judaydah",
    "gn:country_code":"SY",
    "gn:dem":166,
    "gn:feature_class":"P",
    "gn:feature_code":"PPL",
    "gn:name":"Al Judaydah",
    "gn:population":0,
    "gn:timezone":"Asia/Damascus",
    "iso:country":"SY",
    "wof:name":"Al Judaydah",
    "wof:placetype":"locality"
},
  "geometry": {"coordinates":[36.31667,35.55417],"type":"Point"}
}