{
  "type": "Feature",
  "properties": {
    "gn:admin1_code":"1.0",
    "gn:asciiname":"Hajji Baqqari",
    "gn:country_code":"SY",
    "gn:dem":372,
    "gn:feature_class":"P",
    "gn:feature_code":"PPL",
    "gn:name":"\u1e28ajj\u012b Baqq\u0101r\u012b",
    "gn:population":0,
    "gn:timezone":"Asia/Damascus",
    "iso:country":"SY",
    "name:ara_x_preferred":[
        "\u062d\u062c\u064a \u0628\u0642\u0627\u0631\u064a"
    ],
    "name:tur_x_preferred":[
        "\u1e28\u0101jj\u012b Baqq\u0101r\u012b"
    ],
    "name:und_x_variant":[
        "\u1e28ajj\u012b Baqq\u0101r\u012b"
    ],
    "wof:name":"Hajji Baqqari",
    "wof:placetype":"locality"
},
  "geometry": {"coordinates":[41.0004,36.80054000000001],"type":"Point"}
}