{
  "type": "Feature",
  "properties": {
    "gn:admin1_code":"11.0",
    "gn:asciiname":"Ard Bahtar",
    "gn:country_code":"SY",
    "gn:dem":529,
    "gn:feature_class":"P",
    "gn:feature_code":"PPLL",
    "gn:name":"Ar\u1e11 Ba\u1e29tar",
    "gn:population":0,
    "gn:timezone":"Asia/Damascus",
    "iso:country":"SY",
    "name:ara_x_preferred":[
        "\u0623\u0631\u0636 \u0628\u062d\u062a\u0631"
    ],
    "name:und_x_variant":[
        "Ar\u1e11 Ba\u1e29tar"
    ],
    "wof:name":"Ard Bahtar",
    "wof:placetype":"locality"
},
  "geometry": {"coordinates":[36.70366,34.68701],"type":"Point"}
}