{
  "type": "Feature",
  "properties": {
    "gn:admin1_code":"9.0",
    "gn:asciiname":"Jasim Wasmi",
    "gn:country_code":"SY",
    "gn:dem":370,
    "gn:feature_class":"P",
    "gn:feature_code":"PPL",
    "gn:name":"J\u0101sim Wasm\u012b",
    "gn:population":0,
    "gn:timezone":"Asia/Damascus",
    "iso:country":"SY",
    "name:ara_x_preferred":[
        "\u062c\u0627\u0633\u0645 \u0648\u0633\u0645\u064a"
    ],
    "name:und_x_variant":[
        "J\u0101sim Wasm\u012b"
    ],
    "wof:name":"Jasim Wasmi",
    "wof:placetype":"locality"
},
  "geometry": {"coordinates":[37.92324,35.68778],"type":"Point"}
}