{
  "type": "Feature",
  "properties": {
    "gn:admin1_code":"9.0",
    "gn:asciiname":"Jattalah",
    "gn:country_code":"SY",
    "gn:dem":323,
    "gn:feature_class":"P",
    "gn:feature_code":"PPL",
    "gn:name":"Jatt\u0101lah",
    "gn:population":0,
    "gn:timezone":"Asia/Damascus",
    "iso:country":"SY",
    "name:ara_x_preferred":[
        "\u062c\u062a\u0627\u0644\u0629"
    ],
    "name:und_x_variant":[
        "Jatt\u00e2l\u00e9",
        "Jatt\u0101lah"
    ],
    "wof:name":"Jattalah",
    "wof:placetype":"locality"
},
  "geometry": {"coordinates":[37.99896,36.11434000000001],"type":"Point"}
}