{
  "type": "Feature",
  "properties": {
    "gn:admin1_code":"2.0",
    "gn:asciiname":"Khashkhashah",
    "gn:country_code":"SY",
    "gn:dem":396,
    "gn:feature_class":"P",
    "gn:feature_code":"PPL",
    "gn:name":"Khashkh\u0101shah",
    "gn:population":0,
    "gn:timezone":"Asia/Damascus",
    "iso:country":"SY",
    "name:ara_x_preferred":[
        "\u062e\u0634\u062e\u0627\u0634\u0629"
    ],
    "name:und_x_variant":[
        "Khachkh\u00e2ch\u00e9",
        "Khashkh\u0101shah"
    ],
    "wof:name":"Khashkhashah",
    "wof:placetype":"locality"
},
  "geometry": {"coordinates":[36.03352,35.49832],"type":"Point"}
}