{
  "type": "Feature",
  "properties": {
    "gn:admin1_code":"14.0",
    "gn:asciiname":"Ma`ti",
    "gn:country_code":"SY",
    "gn:dem":274,
    "gn:feature_class":"P",
    "gn:feature_code":"PPL",
    "gn:name":"Ma\u2018t\u012b",
    "gn:population":0,
    "gn:timezone":"Asia/Damascus",
    "iso:country":"SY",
    "name:ara_x_preferred":[
        "\u0645\u0639\u062a\u064a"
    ],
    "name:und_x_variant":[
        "Maati",
        "Ma\u2018t\u012b"
    ],
    "wof:name":"Ma`ti",
    "wof:placetype":"locality"
},
  "geometry": {"coordinates":[35.97327999999999,35.04429],"type":"Point"}
}