{
  "type": "Feature",
  "properties": {
    "gn:admin1_code":"12.0",
    "gn:asciiname":"Abu Dali",
    "gn:country_code":"SY",
    "gn:dem":401,
    "gn:feature_class":"P",
    "gn:feature_code":"PPL",
    "gn:name":"Ab\u016b D\u0101l\u012b",
    "gn:population":0,
    "gn:timezone":"Asia/Damascus",
    "iso:country":"SY",
    "name:ara_x_preferred":[
        "\u0623\u0628\u0648 \u062f\u0627\u0644\u064a"
    ],
    "name:pol_x_preferred":[
        "Abu Dali"
    ],
    "name:und_x_variant":[
        "Ab\u016b D\u0101l\u012b"
    ],
    "wof:name":"Abu Dali",
    "wof:placetype":"locality"
},
  "geometry": {"coordinates":[36.90358,35.45056],"type":"Point"}
}