{
  "type": "Feature",
  "properties": {
    "gn:admin1_code":"4.0",
    "gn:asciiname":"Mulayhan",
    "gn:country_code":"SY",
    "gn:dem":306,
    "gn:feature_class":"P",
    "gn:feature_code":"PPLL",
    "gn:name":"Mulay\u1e29\u0101n",
    "gn:population":0,
    "gn:timezone":"Asia/Damascus",
    "iso:country":"SY",
    "name:ara_x_preferred":[
        "\u0645\u0644\u064a\u062d\u0627\u0646"
    ],
    "name:und_x_variant":[
        "Mla\u00efh\u00e2ne",
        "Mulay\u1e29\u0101n"
    ],
    "wof:name":"Mulayhan",
    "wof:placetype":"locality"
},
  "geometry": {"coordinates":[38.97839000000001,36.3559],"type":"Point"}
}