{
  "type": "Feature",
  "properties": {
    "gn:admin1_code":"3.0",
    "gn:asciiname":"Al Hamidiyah",
    "gn:country_code":"SY",
    "gn:dem":947,
    "gn:feature_class":"P",
    "gn:feature_code":"PPL",
    "gn:name":"Al \u1e28am\u012bd\u012byah",
    "gn:population":0,
    "gn:timezone":"Asia/Damascus",
    "iso:country":"SY",
    "name:ara_x_preferred":[
        "\u0627\u0644\u062d\u0645\u064a\u062f\u064a\u0629"
    ],
    "name:und_x_variant":[
        "Ahm\u00e9d\u00eey\u00e9",
        "A\u1e29mad\u012byah",
        "Al \u1e28am\u012bd\u012byah"
    ],
    "wof:name":"Al Hamidiyah",
    "wof:placetype":"locality"
},
  "geometry": {"coordinates":[35.84812,33.15646],"type":"Point"}
}