{
  "type": "Feature",
  "properties": {
    "gn:admin1_code":"12.0",
    "gn:asciiname":"Haymat ad Dayir",
    "gn:country_code":"SY",
    "gn:dem":250,
    "gn:feature_class":"P",
    "gn:feature_code":"PPL",
    "gn:name":"Haym\u0101t ad D\u0101yir",
    "gn:population":0,
    "gn:timezone":"Asia/Damascus",
    "iso:country":"SY",
    "name:ara_x_preferred":[
        "\u062d\u064a\u0645\u0627\u062a \u0627\u0644\u062f\u0627\u064a\u0631"
    ],
    "name:und_x_variant":[
        "Hma\u00efm\u00e2te ed D\u00e2er",
        "\u1e28umaym\u0101t ad D\u0101\u2019ir",
        "Haym\u0101t ad D\u0101yir"
    ],
    "wof:name":"Haymat ad Dayir",
    "wof:placetype":"locality"
},
  "geometry": {"coordinates":[37.10164,35.79175],"type":"Point"}
}