{
  "type": "Feature",
  "properties": {
    "gn:admin1_code":"9.0",
    "gn:asciiname":"Al Qatar",
    "gn:country_code":"SY",
    "gn:dem":400,
    "gn:feature_class":"P",
    "gn:feature_code":"PPL",
    "gn:name":"Al Qa\u0163ar",
    "gn:population":0,
    "gn:timezone":"Asia/Damascus",
    "iso:country":"SY",
    "name:ara_x_preferred":[
        "\u0642\u0637\u0631"
    ],
    "name:ara_x_variant":[
        "\u0627\u0644\u0642\u0637\u0631"
    ],
    "name:und_x_variant":[
        "Qatar",
        "El Katar",
        "El Qatar",
        "Al Qa\u0163ar",
        "Qa\u0163ar"
    ],
    "wof:name":"Al Qatar",
    "wof:placetype":"locality"
},
  "geometry": {"coordinates":[37.49852,36.24518],"type":"Point"}
}