{
  "type": "Feature",
  "properties": {
    "gn:admin1_code":"1.0",
    "gn:asciiname":"Tall Ghazal at Tahtani",
    "gn:country_code":"SY",
    "gn:dem":380,
    "gn:feature_class":"P",
    "gn:feature_code":"PPL",
    "gn:name":"Tall Ghaz\u0101l at Ta\u1e29t\u0101n\u012b",
    "gn:population":0,
    "gn:timezone":"Asia/Damascus",
    "iso:country":"SY",
    "name:ara_x_preferred":[
        "\u062a\u0644 \u063a\u0632\u0627\u0644 \u062a\u062d\u062a\u0627\u0646\u064a"
    ],
    "name:tur_x_preferred":[
        "Tall Ghaz\u0101l at Ta\u1e29t\u0101n\u012b"
    ],
    "name:und_x_variant":[
        "Tell Rhaz\u00e2l Taht\u00e2ni",
        "Tall Ghaz\u0101l at Ta\u1e29t\u0101n\u012b"
    ],
    "wof:name":"Tall Ghazal at Tahtani",
    "wof:placetype":"locality"
},
  "geometry": {"coordinates":[40.49219,36.7653],"type":"Point"}
}