{
  "type": "Feature",
  "properties": {
    "gn:admin1_code":"9.0",
    "gn:asciiname":"Abu Zannah",
    "gn:country_code":"SY",
    "gn:dem":363,
    "gn:feature_class":"P",
    "gn:feature_code":"PPL",
    "gn:name":"Ab\u016b Z\u0327annah",
    "gn:population":0,
    "gn:timezone":"Asia/Damascus",
    "iso:country":"SY",
    "name:ara_x_preferred":[
        "Ab\u016b D\u0101n\u0101"
    ],
    "name:ara_x_variant":[
        "\u0623\u0628\u0648 \u062f\u0627\u0646\u0627",
        "\u0623\u0628\u0648 \u0638\u0646\u0629"
    ],
    "name:und_x_variant":[
        "Abou Danna",
        "Ab\u016b Dannah",
        "Ab\u016b Z\u0327annah"
    ],
    "wof:name":"Abu Zannah",
    "wof:placetype":"locality"
},
  "geometry": {"coordinates":[37.45152,36.1843],"type":"Point"}
}