{
  "type": "Feature",
  "properties": {
    "gn:admin1_code":"1.0",
    "gn:asciiname":"Ghunah",
    "gn:country_code":"SY",
    "gn:dem":373,
    "gn:feature_class":"P",
    "gn:feature_code":"PPL",
    "gn:name":"Gh\u016bnah",
    "gn:population":0,
    "gn:timezone":"Asia/Damascus",
    "iso:country":"SY",
    "name:ara_x_preferred":[
        "\u063a\u0648\u0646\u0629"
    ],
    "name:und_x_variant":[
        "Gh\u016bnah"
    ],
    "wof:name":"Ghunah",
    "wof:placetype":"locality"
},
  "geometry": {"coordinates":[41.07003,36.17824],"type":"Point"}
}