{
  "type": "Feature",
  "properties": {
    "gn:admin1_code":"14.0",
    "gn:asciiname":"As Sawdah",
    "gn:country_code":"SY",
    "gn:dem":44,
    "gn:feature_class":"P",
    "gn:feature_code":"PPL",
    "gn:name":"As Sawdah",
    "gn:population":0,
    "gn:timezone":"Asia/Damascus",
    "iso:country":"SY",
    "name:ara_x_preferred":[
        "\u0627\u0644\u0633\u0648\u062f\u0629"
    ],
    "name:und_x_variant":[
        "Saouda",
        "As Sawd\u0101\u2019",
        "As Sawdah"
    ],
    "wof:name":"As Sawdah",
    "wof:placetype":"locality"
},
  "geometry": {"coordinates":[36.05231,34.67186],"type":"Point"}
}