{
  "type": "Feature",
  "properties": {
    "gn:admin1_code":"11.0",
    "gn:asciiname":"Al Khalidiyah",
    "gn:country_code":"SY",
    "gn:dem":480,
    "gn:feature_class":"P",
    "gn:feature_code":"PPL",
    "gn:name":"Al Kh\u0101lid\u012byah",
    "gn:population":0,
    "gn:timezone":"Asia/Damascus",
    "iso:country":"SY",
    "name:ara_x_preferred":[
        "\u0627\u0644\u062e\u0627\u0644\u062f\u064a\u0629"
    ],
    "name:und_x_variant":[
        "Al Kh\u0101lid\u012byah"
    ],
    "wof:name":"Al Khalidiyah",
    "wof:placetype":"locality"
},
  "geometry": {"coordinates":[36.76791,34.86762],"type":"Point"}
}