{
  "type": "Feature",
  "properties": {
    "gn:admin1_code":"3.0",
    "gn:asciiname":"Khirbat al Julaybinah",
    "gn:country_code":"SY",
    "gn:dem":157,
    "gn:feature_class":"P",
    "gn:feature_code":"PPL",
    "gn:name":"Khirbat al Julayb\u012bnah",
    "gn:population":0,
    "gn:timezone":"Asia/Damascus",
    "iso:country":"SY",
    "name:ara_x_preferred":[
        "\u062e\u0631\u0628\u0629 \u0627\u0644\u062c\u0644\u064a\u0628\u064a\u0646\u0629"
    ],
    "name:und_x_variant":[
        "Kheurbet ej Jalabina",
        "Kheurbet ej J\u00e9l\u00e9b\u00een\u00e9",
        "Khirbat al Julayb\u012bnah"
    ],
    "wof:name":"Khirbat al Julaybinah",
    "wof:placetype":"locality"
},
  "geometry": {"coordinates":[35.64369,33.03442],"type":"Point"}
}