{
  "type": "Feature",
  "properties": {
    "gn:admin1_code":"10.0",
    "gn:asciiname":"`Aqarib as Safi",
    "gn:country_code":"SY",
    "gn:dem":522,
    "gn:feature_class":"P",
    "gn:feature_code":"PPL",
    "gn:name":"\u2018Aq\u0101rib a\u015f \u015e\u0101f\u012b",
    "gn:population":0,
    "gn:timezone":"Asia/Damascus",
    "iso:country":"SY",
    "name:ara_x_preferred":[
        "\u0639\u0642\u0627\u0631\u0628 \u0627\u0644\u0635\u0627\u0641\u064a"
    ],
    "name:und_x_variant":[
        "Aaq\u00e2reb es S\u00e2fi",
        "\u2018Aq\u0101rib",
        "Aaq\u00e2rib es S\u00e2fi",
        "Aqareb es S\u00e2fi",
        "\u2018Aq\u0101rib a\u015f \u015e\u0101f\u012b"
    ],
    "wof:name":"`Aqarib as Safi",
    "wof:placetype":"locality"
},
  "geometry": {"coordinates":[37.21004,35.10575],"type":"Point"}
}