{
  "type": "Feature",
  "properties": {
    "gn:admin1_code":"1.0",
    "gn:asciiname":"Shamsani ash Sharqi",
    "gn:country_code":"SY",
    "gn:dem":248,
    "gn:feature_class":"P",
    "gn:feature_code":"PPL",
    "gn:name":"Shams\u0101n\u012b ash Sharq\u012b",
    "gn:population":0,
    "gn:timezone":"Asia/Damascus",
    "iso:country":"SY",
    "name:ara_x_preferred":[
        "\u0634\u0645\u0633\u0627\u0646\u064a \u0627\u0644\u0634\u0631\u0642\u064a"
    ],
    "name:und_x_variant":[
        "Chams\u00e2ni",
        "Shams\u0101n\u012byah",
        "Chamsaniy\u00e9",
        "Shams\u0101n\u012b",
        "Shams\u0101n\u012b ash Sharq\u012b"
    ],
    "wof:name":"Shamsani ash Sharqi",
    "wof:placetype":"locality"
},
  "geometry": {"coordinates":[40.88433,35.86327],"type":"Point"}
}