{
  "type": "Feature",
  "properties": {
    "gn:admin1_code":"10.0",
    "gn:asciiname":"Sarha al Qibliyah",
    "gn:country_code":"SY",
    "gn:dem":375,
    "gn:feature_class":"P",
    "gn:feature_code":"PPL",
    "gn:name":"Sar\u1e29\u0101 al Qibl\u012byah",
    "gn:population":0,
    "gn:timezone":"Asia/Damascus",
    "iso:country":"SY",
    "name:ara_x_preferred":[
        "\u0633\u0631\u062d\u0627 \u0627\u0644\u0642\u0628\u0644\u064a\u0629"
    ],
    "name:und_x_variant":[
        "Sar\u1e29\u0101 al Qibl\u012byah"
    ],
    "wof:name":"Sarha al Qibliyah",
    "wof:placetype":"locality"
},
  "geometry": {"coordinates":[37.42551,35.34199],"type":"Point"}
}