{
  "type": "Feature",
  "properties": {
    "gn:admin1_code":"2.0",
    "gn:asciiname":"Al Bahsat",
    "gn:country_code":"SY",
    "gn:dem":19,
    "gn:feature_class":"P",
    "gn:feature_code":"PPLL",
    "gn:name":"Al Ba\u1e29\u015f\u0101t",
    "gn:population":0,
    "gn:timezone":"Asia/Damascus",
    "iso:country":"SY",
    "name:ara_x_preferred":[
        "\u0627\u0644\u0628\u062d\u0635\u0627\u062a"
    ],
    "name:und_x_variant":[
        "Al Ba\u1e29\u015f\u0101t"
    ],
    "wof:name":"Al Bahsat",
    "wof:placetype":"locality"
},
  "geometry": {"coordinates":[35.88329,35.57462],"type":"Point"}
}