{
  "type": "Feature",
  "properties": {
    "gn:admin1_code":"12.0",
    "gn:asciiname":"Sukayk",
    "gn:country_code":"SY",
    "gn:dem":346,
    "gn:feature_class":"P",
    "gn:feature_code":"PPL",
    "gn:name":"Sukayk",
    "gn:population":0,
    "gn:timezone":"Asia/Damascus",
    "iso:country":"SY",
    "name:ara_x_preferred":[
        "\u0633\u0643\u064a\u0643"
    ],
    "name:fas_x_preferred":[
        "\u0633\u06a9\u06cc\u06a9"
    ],
    "name:pol_x_preferred":[
        "Sukajk"
    ],
    "name:und_x_variant":[
        "Souka\u00efk",
        "Sukayk"
    ],
    "name:vie_x_preferred":[
        "Sukayk"
    ],
    "wof:name":"Sukayk",
    "wof:placetype":"locality"
},
  "geometry": {"coordinates":[36.77053,35.42892],"type":"Point"}
}