{
  "type": "Feature",
  "properties": {
    "gn:admin1_code":"1.0",
    "gn:asciiname":"Huqul ar Rumaylan",
    "gn:country_code":"SY",
    "gn:dem":454,
    "gn:feature_class":"P",
    "gn:feature_code":"PPL",
    "gn:name":"\u1e28uq\u016bl ar Rumayl\u0101n",
    "gn:population":0,
    "gn:timezone":"Asia/Damascus",
    "iso:country":"SY",
    "name:ara_x_preferred":[
        "\u062d\u0642\u0648\u0644 \u0627\u0644\u0631\u0645\u064a\u0644\u0627\u0646"
    ],
    "name:und_x_variant":[
        "\u1e28uq\u016bl ar Rumayl\u0101n"
    ],
    "wof:name":"Huqul ar Rumaylan",
    "wof:placetype":"locality"
},
  "geometry": {"coordinates":[41.95047,37.00658],"type":"Point"}
}