{
  "type": "Feature",
  "properties": {
    "gn:admin1_code":"1.0",
    "gn:asciiname":"Lazzakah",
    "gn:country_code":"SY",
    "gn:dem":318,
    "gn:feature_class":"P",
    "gn:feature_code":"PPL",
    "gn:name":"Lazz\u0101kah",
    "gn:population":0,
    "gn:timezone":"Asia/Damascus",
    "iso:country":"SY",
    "name:ara_x_preferred":[
        "\u0644\u0632\u0627\u0643\u0629"
    ],
    "name:und_x_variant":[
        "Lazz\u0101kah",
        "Laz\u0101kah"
    ],
    "wof:name":"Lazzakah",
    "wof:placetype":"locality"
},
  "geometry": {"coordinates":[40.67362,35.91495],"type":"Point"}
}