{
  "type": "Feature",
  "properties": {
    "gn:admin1_code":"14.0",
    "gn:asciiname":"Bnimrah",
    "gn:country_code":"SY",
    "gn:dem":665,
    "gn:feature_class":"P",
    "gn:feature_code":"PPL",
    "gn:name":"Bnimrah",
    "gn:population":0,
    "gn:timezone":"Asia/Damascus",
    "iso:country":"SY",
    "name:ara_x_preferred":[
        "\u0628\u0646\u0645\u0631\u0629"
    ],
    "name:und_x_variant":[
        "Binimrah"
    ],
    "wof:name":"Bnimrah",
    "wof:placetype":"locality"
},
  "geometry": {"coordinates":[36.2199,34.95239],"type":"Point"}
}