{
  "type": "Feature",
  "properties": {
    "gn:admin1_code":"8.0",
    "gn:asciiname":"Ard ash Shawk",
    "gn:country_code":"SY",
    "gn:dem":608,
    "gn:feature_class":"P",
    "gn:feature_code":"PPLL",
    "gn:name":"Ar\u1e11 ash Shawk",
    "gn:population":0,
    "gn:timezone":"Asia/Damascus",
    "iso:country":"SY",
    "name:ara_x_preferred":[
        "\u0623\u0631\u0636 \u0627\u0644\u0634\u0648\u0643"
    ],
    "name:und_x_variant":[
        "Ar\u1e11 ash Shawk"
    ],
    "wof:name":"Ard ash Shawk",
    "wof:placetype":"locality"
},
  "geometry": {"coordinates":[36.50443,33.60413],"type":"Point"}
}