{
  "type": "Feature",
  "properties": {
    "gn:admin1_code":"8.0",
    "gn:asciiname":"Jaramana",
    "gn:country_code":"SY",
    "gn:dem":670,
    "gn:feature_class":"P",
    "gn:feature_code":"PPLA3",
    "gn:name":"Jaram\u0101n\u0101",
    "gn:population":0,
    "gn:timezone":"Asia/Damascus",
    "iso:country":"SY",
    "name:ara_x_preferred":[
        "\u062c\u0631\u0645\u0627\u0646\u0627"
    ],
    "name:ceb_x_preferred":[
        "Jaram\u0101n\u0101"
    ],
    "name:deu_x_preferred":[
        "Dscharamana"
    ],
    "name:epo_x_preferred":[
        "\u011caramana"
    ],
    "name:fas_x_preferred":[
        "\u062c\u0631\u0645\u0627\u0646\u0627"
    ],
    "name:fin_x_preferred":[
        "Jaramana"
    ],
    "name:fra_x_preferred":[
        "Jaramana"
    ],
    "name:ind_x_preferred":[
        "Jaramana"
    ],
    "name:nld_x_preferred":[
        "Jaramanah"
    ],
    "name:nno_x_preferred":[
        "Jaramana"
    ],
    "name:pol_x_preferred":[
        "D\u017caramana"
    ],
    "name:por_x_preferred":[
        "Jaramana"
    ],
    "name:sco_x_preferred":[
        "Jaramana"
    ],
    "name:tur_x_preferred":[
        "Ceramana"
    ],
    "name:ukr_x_preferred":[
        "\u0414\u0436\u0435\u0440\u0430\u043c\u0430\u043d\u0430"
    ],
    "name:und_x_variant":[
        "Djaram\u0101n\u0101",
        "J\u00e9ram\u00e2na",
        "Jaram\u0101n\u0101",
        "Jaram\u0101nah",
        "Jurm\u0101n\u0101"
    ],
    "name:urd_x_preferred":[
        "\u062c\u0631\u0645\u0627\u0646\u0627"
    ],
    "name:vie_x_preferred":[
        "Jaramana"
    ],
    "wof:name":"Jaramana",
    "wof:placetype":"locality"
},
  "geometry": {"coordinates":[36.34614000000001,33.4862],"type":"Point"}
}