{
  "type": "Feature",
  "properties": {
    "gn:admin1_code":"8.0",
    "gn:asciiname":"Jaramana",
    "gn:country_code":"SY",
    "gn:dem":670,
    "gn:feature_class":"P",
    "gn:feature_code":"PPLA3",
    "gn:name":"Jaram\u0101n\u0101",
    "gn:population":0,
    "gn:timezone":"Asia/Damascus",
    "iso:country":"SY",
    "name:ara_x_preferred":[
        "\u062c\u0631\u0645\u0627\u0646\u0627"
    ],
    "name:und_x_variant":[
        "Djaram\u0101n\u0101",
        "J\u00e9ram\u00e2na",
        "Jaram\u0101n\u0101",
        "Jaram\u0101nah",
        "Jurm\u0101n\u0101"
    ],
    "wof:name":"Jaramana",
    "wof:placetype":"locality"
},
  "geometry": {"coordinates":[36.34614000000001,33.4862],"type":"Point"}
}