{
  "type": "Feature",
  "properties": {
    "gn:admin1_code":"4.0",
    "gn:asciiname":"Qaltah",
    "gn:country_code":"SY",
    "gn:dem":286,
    "gn:feature_class":"P",
    "gn:feature_code":"PPL",
    "gn:name":"Qal\u0163ah",
    "gn:population":0,
    "gn:timezone":"Asia/Damascus",
    "iso:country":"SY",
    "name:ara_x_preferred":[
        "\u0642\u0644\u0637\u0629"
    ],
    "name:und_x_variant":[
        "Qal\u0163ah"
    ],
    "wof:name":"Qaltah",
    "wof:placetype":"locality"
},
  "geometry": {"coordinates":[39.01298,36.17681],"type":"Point"}
}