{
  "type": "Feature",
  "properties": {
    "gn:admin1_code":"6.0",
    "gn:asciiname":"Shajarat at Tayihah",
    "gn:country_code":"SY",
    "gn:dem":675,
    "gn:feature_class":"P",
    "gn:feature_code":"PPL",
    "gn:name":"Shajarat a\u0163 \u0162\u0101yi\u1e29ah",
    "gn:population":0,
    "gn:timezone":"Asia/Damascus",
    "iso:country":"SY",
    "name:ara_x_preferred":[
        "\u0634\u062c\u0631\u0629 \u0627\u0644\u0637\u0627\u064a\u062d\u0629"
    ],
    "name:und_x_variant":[
        "Shajarat a\u0163 \u0162\u0101yi\u1e29ah",
        "Shajarat al \u0162\u0101ya\u1e29ah"
    ],
    "wof:name":"Shajarat at Tayihah",
    "wof:placetype":"locality"
},
  "geometry": {"coordinates":[36.3359,32.45605],"type":"Point"}
}