{
  "type": "Feature",
  "properties": {
    "gn:admin1_code":"9.0",
    "gn:asciiname":"Jubb Mahli",
    "gn:country_code":"SY",
    "gn:dem":446,
    "gn:feature_class":"P",
    "gn:feature_code":"PPL",
    "gn:name":"Jubb Ma\u1e29l\u012b",
    "gn:population":0,
    "gn:timezone":"Asia/Damascus",
    "iso:country":"SY",
    "name:und_x_variant":[
        "Joubb Mahli",
        "Jubb Ma\u1e29l\u012b"
    ],
    "wof:name":"Jubb Mahli",
    "wof:placetype":"locality"
},
  "geometry": {"coordinates":[38.41445,36.56121],"type":"Point"}
}