{
  "type": "Feature",
  "properties": {
    "gn:admin1_code":"6.0",
    "gn:asciiname":"Al Qunayyah",
    "gn:country_code":"SY",
    "gn:dem":606,
    "gn:feature_class":"P",
    "gn:feature_code":"PPL",
    "gn:name":"Al Qunayyah",
    "gn:population":0,
    "gn:timezone":"Asia/Damascus",
    "iso:country":"SY",
    "name:ara_x_preferred":[
        "\u0642\u0646\u064a\u0629"
    ],
    "name:ara_x_variant":[
        "\u0627\u0644\u0642\u0646\u064a\u0651\u0629"
    ],
    "name:und_x_variant":[
        "Qunn\u012byah",
        "Kan\u00e2y\u00e9",
        "Qan\u00e2y\u00e9",
        "Qan\u00e2ya",
        "Qan\u0101yah",
        "Qunayyah",
        "Al Qunayyah"
    ],
    "wof:name":"Al Qunayyah",
    "wof:placetype":"locality"
},
  "geometry": {"coordinates":[36.18449,33.01175],"type":"Point"}
}