{
  "type": "Feature",
  "properties": {
    "gn:admin1_code":"9.0",
    "gn:asciiname":"Hamlurak",
    "gn:country_code":"SY",
    "gn:dem":710,
    "gn:feature_class":"P",
    "gn:feature_code":"PPL",
    "gn:name":"\u1e28aml\u016brak",
    "gn:population":0,
    "gn:timezone":"Asia/Damascus",
    "iso:country":"SY",
    "name:ara_x_preferred":[
        "\u062d\u0645\u0644\u0648\u0631\u0643"
    ],
    "name:ara_x_variant":[
        "\u0627\u0644\u062f\u0641\u0644\u0629"
    ],
    "name:und_x_variant":[
        "Djoum Koufar",
        "Hamlo\u00fbr\u00e2k",
        "\u1e28aml\u016br\u0101k",
        "\u1e28aml\u016brak",
        "Ad Daflah"
    ],
    "wof:name":"Hamlurak",
    "wof:placetype":"locality"
},
  "geometry": {"coordinates":[36.66496,36.58584000000001],"type":"Point"}
}