{
  "type": "Feature",
  "properties": {
    "gn:admin1_code":"9.0",
    "gn:asciiname":"As Sayyadah al Kabirah",
    "gn:country_code":"SY",
    "gn:dem":507,
    "gn:feature_class":"P",
    "gn:feature_code":"PPL",
    "gn:name":"A\u015f \u015eayy\u0101dah al Kab\u012brah",
    "gn:population":0,
    "gn:timezone":"Asia/Damascus",
    "iso:country":"SY",
    "name:ara_x_preferred":[
        "\u0633\u0639\u064a\u062f\u064a\u0629"
    ],
    "name:ara_x_variant":[
        "\u0627\u0644\u0635\u064a\u0627\u062f\u0629 \u0627\u0644\u0643\u0628\u064a\u0631\u0629",
        "\u0635\u064a\u0627\u062f\u0629"
    ],
    "name:und_x_variant":[
        "Sa\u00efd\u00eey\u00e9",
        "\u015eayd\u012byah",
        "Sa\u2018\u012bd\u012byah",
        "A\u015f \u015eayy\u0101dah al Kab\u012brah",
        "\u015eayy\u0101dah"
    ],
    "wof:name":"As Sayyadah al Kabirah",
    "wof:placetype":"locality"
},
  "geometry": {"coordinates":[37.7514,36.55478],"type":"Point"}
}