{
  "type": "Feature",
  "properties": {
    "gn:admin1_code":"1.0",
    "gn:asciiname":"As Sayibah",
    "gn:country_code":"SY",
    "gn:dem":316,
    "gn:feature_class":"P",
    "gn:feature_code":"PPL",
    "gn:name":"As S\u0101yibah",
    "gn:population":0,
    "gn:timezone":"Asia/Damascus",
    "iso:country":"SY",
    "name:ara_x_preferred":[
        "\u0627\u0644\u0633\u0627\u064a\u0628\u0629"
    ],
    "name:und_x_variant":[
        "As S\u0101ybah",
        "As S\u0101yibah"
    ],
    "wof:name":"As Sayibah",
    "wof:placetype":"locality"
},
  "geometry": {"coordinates":[41.20545,36.05438],"type":"Point"}
}