{
  "type": "Feature",
  "properties": {
    "gn:admin1_code":"1.0",
    "gn:asciiname":"Junaydiyah",
    "gn:country_code":"SY",
    "gn:dem":417,
    "gn:feature_class":"P",
    "gn:feature_code":"PPL",
    "gn:name":"Junayd\u012byah",
    "gn:population":0,
    "gn:timezone":"Asia/Damascus",
    "iso:country":"SY",
    "name:ara_x_preferred":[
        "\u062c\u0646\u064a\u062f\u064a\u0629"
    ],
    "name:tur_x_preferred":[
        "Junayd\u012byah"
    ],
    "name:und_x_variant":[
        "J\u00e9n\u00e9d\u00eey\u00e9"
    ],
    "wof:name":"Junaydiyah",
    "wof:placetype":"locality"
},
  "geometry": {"coordinates":[41.28068,36.99031],"type":"Point"}
}