{
  "type": "Feature",
  "properties": {
    "gn:admin1_code":"4.0",
    "gn:asciiname":"Shams ad Din al Wastani",
    "gn:country_code":"SY",
    "gn:dem":321,
    "gn:feature_class":"P",
    "gn:feature_code":"PPL",
    "gn:name":"Shams ad D\u012bn al Was\u0163\u0101n\u012b",
    "gn:population":0,
    "gn:timezone":"Asia/Damascus",
    "iso:country":"SY",
    "name:ara_x_preferred":[
        "\u0634\u0645\u0633 \u0627\u0644\u062f\u064a\u0646 \u0627\u0644\u0648\u0633\u0637\u0627\u0646\u064a"
    ],
    "name:und_x_variant":[
        "Chams ed D\u00eene Ouast\u00e2ni",
        "Shams ad D\u012bn al Was\u0163\u0101n\u012b"
    ],
    "wof:name":"Shams ad Din al Wastani",
    "wof:placetype":"locality"
},
  "geometry": {"coordinates":[38.19359,36.23847],"type":"Point"}
}