{
  "type": "Feature",
  "properties": {
    "gn:admin1_code":"10.0",
    "gn:asciiname":"Houla",
    "gn:country_code":"SY",
    "gn:dem":375,
    "gn:feature_class":"P",
    "gn:feature_code":"PPLS",
    "gn:name":"Houla",
    "gn:population":0,
    "gn:timezone":"Asia/Damascus",
    "iso:country":"SY",
    "name:ara_x_preferred":[
        "\u0627\u0644\u062d\u0648\u0644\u0629\u200e\u200e"
    ],
    "name:ara_x_variant":[
        "\u0627\u0644\u062d\u0648\u0644\u0629"
    ],
    "name:aze_x_preferred":[
        "Hula"
    ],
    "name:deu_x_preferred":[
        "Hula"
    ],
    "name:fas_x_preferred":[
        "\u0645\u0646\u0637\u0642\u0647 \u062d\u0648\u0644\u0647"
    ],
    "name:fra_x_preferred":[
        "Houla"
    ],
    "name:ita_x_preferred":[
        "Houla"
    ],
    "name:jpn_x_preferred":[
        "\u30db\u30a6\u30e9"
    ],
    "name:nno_x_preferred":[
        "Houla"
    ],
    "name:spa_x_preferred":[
        "Hula"
    ],
    "name:und_x_variant":[
        "Hula",
        "al-Houlah"
    ],
    "name:zho_x_preferred":[
        "\u4faf\u62c9\u9547"
    ],
    "wof:name":"Houla",
    "wof:placetype":"locality"
},
  "geometry": {"coordinates":[36.50027,34.89368],"type":"Point"}
}