{
  "type": "Feature",
  "properties": {
    "gn:admin1_code":"9.0",
    "gn:asciiname":"Khirbat al Bighal",
    "gn:country_code":"SY",
    "gn:dem":412,
    "gn:feature_class":"P",
    "gn:feature_code":"PPL",
    "gn:name":"Khirbat al Bigh\u0101l",
    "gn:population":0,
    "gn:timezone":"Asia/Damascus",
    "iso:country":"SY",
    "name:ara_x_preferred":[
        "\u062e\u0631\u0628\u0629 \u0627\u0644\u0628\u063a\u0627\u0644"
    ],
    "name:und_x_variant":[
        "Kheurbet el Brh\u00e2l",
        "Khirbat Bigh\u0101l",
        "Khirbat al Bigh\u0101l"
    ],
    "wof:name":"Khirbat al Bighal",
    "wof:placetype":"locality"
},
  "geometry": {"coordinates":[38.19715,36.49273],"type":"Point"}
}