{
  "type": "Feature",
  "properties": {
    "gn:admin1_code":"2.0",
    "gn:asciiname":"Balluta",
    "gn:country_code":"SY",
    "gn:dem":756,
    "gn:feature_class":"P",
    "gn:feature_code":"PPL",
    "gn:name":"Ball\u016b\u0163\u0101",
    "gn:population":0,
    "gn:timezone":"Asia/Damascus",
    "iso:country":"SY",
    "name:ara_x_preferred":[
        "\u0628\u0644\u0648\u0637\u0627"
    ],
    "name:und_x_variant":[
        "Blo\u00fbta",
        "Ball\u016b\u0163ah",
        "Ball\u016b\u0163\u0101"
    ],
    "wof:name":"Balluta",
    "wof:placetype":"locality"
},
  "geometry": {"coordinates":[36.12123,35.65411],"type":"Point"}
}