{
  "type": "Feature",
  "properties": {
    "gn:admin1_code":"12.0",
    "gn:asciiname":"Abu al Khassah",
    "gn:country_code":"SY",
    "gn:dem":329,
    "gn:feature_class":"P",
    "gn:feature_code":"PPL",
    "gn:name":"Ab\u016b al Khassah",
    "gn:population":0,
    "gn:timezone":"Asia/Damascus",
    "iso:country":"SY",
    "name:und_x_variant":[
        "Ab\u016b al Khassah"
    ],
    "wof:name":"Abu al Khassah",
    "wof:placetype":"locality"
},
  "geometry": {"coordinates":[36.90417,35.83333],"type":"Point"}
}