{
  "type": "Feature",
  "properties": {
    "gn:admin1_code":"2.0",
    "gn:asciiname":"Marran",
    "gn:country_code":"SY",
    "gn:dem":704,
    "gn:feature_class":"P",
    "gn:feature_code":"PPL",
    "gn:name":"Marr\u0101n",
    "gn:population":0,
    "gn:timezone":"Asia/Damascus",
    "iso:country":"SY",
    "name:ara_x_preferred":[
        "\u0645\u0631\u0627\u0646"
    ],
    "name:und_x_variant":[
        "Merr\u00e2n\u00e9",
        "Marr\u0101nah",
        "Marr\u0101n",
        "Merr\u00e2ne"
    ],
    "wof:name":"Marran",
    "wof:placetype":"locality"
},
  "geometry": {"coordinates":[36.11773,35.45152],"type":"Point"}
}