{
  "type": "Feature",
  "properties": {
    "gn:admin1_code":"4.0",
    "gn:asciiname":"Al Huzaymah",
    "gn:country_code":"SY",
    "gn:dem":281,
    "gn:feature_class":"P",
    "gn:feature_code":"PPL",
    "gn:name":"Al Huzaymah",
    "gn:population":0,
    "gn:timezone":"Asia/Damascus",
    "iso:country":"SY",
    "name:ara_x_preferred":[
        "\u0627\u0644\u0647\u0632\u064a\u0645\u0629"
    ],
    "name:und_x_variant":[
        "\u1e28az\u012bmah",
        "Haz\u012bm\u00e9",
        "Al \u1e28az\u012bmah",
        "Al Huzaymah"
    ],
    "wof:name":"Al Huzaymah",
    "wof:placetype":"locality"
},
  "geometry": {"coordinates":[38.96442,36.13317],"type":"Point"}
}