{
  "type": "Feature",
  "properties": {
    "gn:admin1_code":"12.0",
    "gn:asciiname":"Birat Armanaz",
    "gn:country_code":"SY",
    "gn:dem":262,
    "gn:feature_class":"P",
    "gn:feature_code":"PPL",
    "gn:name":"B\u012brat Arman\u0101z",
    "gn:population":0,
    "gn:timezone":"Asia/Damascus",
    "iso:country":"SY",
    "name:ara_x_preferred":[
        "\u0628\u064a\u0631\u0629 \u0623\u0631\u0645\u0646\u0627\u0632"
    ],
    "name:und_x_variant":[
        "B\u00eeret Arman\u00e2z",
        "B\u00eeret Armen\u00e2z",
        "B\u012brat Arman\u0101z"
    ],
    "wof:name":"Birat Armanaz",
    "wof:placetype":"locality"
},
  "geometry": {"coordinates":[36.4875,36.03393],"type":"Point"}
}