{
  "type": "Feature",
  "properties": {
    "gn:admin1_code":"2.0",
    "gn:asciiname":"Dayr Hanna",
    "gn:country_code":"SY",
    "gn:dem":272,
    "gn:feature_class":"P",
    "gn:feature_code":"PPL",
    "gn:name":"Dayr \u1e28ann\u0101",
    "gn:population":0,
    "gn:timezone":"Asia/Damascus",
    "iso:country":"SY",
    "name:ara_x_preferred":[
        "\u062f\u064a\u0631 \u062d\u0646\u0627"
    ],
    "name:und_x_variant":[
        "De\u00efr Hanna",
        "Dayr \u1e28ann\u0101"
    ],
    "wof:name":"Dayr Hanna",
    "wof:placetype":"locality"
},
  "geometry": {"coordinates":[36.01929000000001,35.70618],"type":"Point"}
}