{
  "type": "Feature",
  "properties": {
    "gn:admin1_code":"8.0",
    "gn:asciiname":"Qabr as Sitt",
    "gn:country_code":"SY",
    "gn:dem":660,
    "gn:feature_class":"P",
    "gn:feature_code":"PPL",
    "gn:name":"Qabr as Sitt",
    "gn:population":0,
    "gn:timezone":"Asia/Damascus",
    "iso:country":"SY",
    "name:ara_x_preferred":[
        "\u0642\u0628\u0631 \u0627\u0644\u0633\u062a"
    ],
    "name:ara_x_variant":[
        "\u0627\u0644\u0633\u064a\u062f\u0629 \u0632\u064a\u0646\u0628"
    ],
    "name:fas_x_preferred":[
        "\u0633\u06cc\u062f\u0647 \u0632\u06cc\u0646\u0628"
    ],
    "name:fin_x_preferred":[
        "Sayyidah Zaynab"
    ],
    "name:fra_x_preferred":[
        "Sayyida Zeinab"
    ],
    "name:nno_x_preferred":[
        "Sayyidah Zaynab"
    ],
    "name:pnb_x_preferred":[
        "\u0633\u06cc\u062f\u06c1 \u0632\u06cc\u0646\u0628"
    ],
    "name:pol_x_preferred":[
        "As-Sajjida Zajnab"
    ],
    "name:por_x_preferred":[
        "Sayyidah Zaynab"
    ],
    "name:sco_x_preferred":[
        "Sayyidah Zaynab"
    ],
    "name:und_x_variant":[
        "Qabr es Sett",
        "Qabr es Sitt",
        "Qabr as Sitt",
        "As Sayyidah Zaynab",
        "Set Zaynab",
        "Sayeda Zainab"
    ],
    "name:urd_x_preferred":[
        "\u0633\u06cc\u062f\u06c1 \u0632\u06cc\u0646\u0628"
    ],
    "name:vie_x_preferred":[
        "Sayyidah Zaynab"
    ],
    "wof:name":"Qabr as Sitt",
    "wof:placetype":"locality"
},
  "geometry": {"coordinates":[36.33641,33.4466],"type":"Point"}
}