{
  "type": "Feature",
  "properties": {
    "gn:country":"SY",
    "gn:fcode":"PPLA3",
    "gn:population":21987,
    "iso:country":"SY",
    "name:ara_x_preferred":[
        "Ad D\u0101n\u0101"
    ],
    "name:ara_x_variant":[
        "\u0627\u0644\u062f\u0627\u0646\u0627"
    ],
    "name:und_x_variant":[
        "Ed D\u00e2na"
    ],
    "qs_pg:aaroncc":"SY",
    "qs_pg:gn_country":"SY",
    "qs_pg:gn_fcode":"PPLA3",
    "qs_pg:gn_pop":21987,
    "qs_pg:name":"Ad D\u0101n\u0101",
    "qs_pg:photos_9r":0,
    "qs_pg:photos_sr":0,
    "qs_pg:pop_sr":7,
    "qs_pg:qs_pg_placetype":"locality",
    "wof:name":"Ad D\u0101n\u0101",
    "wof:placetype":"locality",
    "wof:population":21987
},
  "geometry": {"coordinates":[36.76978,36.21252],"type":"Point"}
}