{
  "type": "Feature",
  "properties": {
    "gn:admin1_code":"3.0",
    "gn:asciiname":"Mazra`at Qafwah",
    "gn:country_code":"SY",
    "gn:dem":821,
    "gn:feature_class":"P",
    "gn:feature_code":"PPL",
    "gn:name":"Mazra\u2018at Qafwah",
    "gn:population":0,
    "gn:timezone":"Asia/Damascus",
    "iso:country":"SY",
    "name:ara_x_preferred":[
        "\u0645\u0632\u0631\u0639\u0629 \u0642\u0641\u0648\u0629"
    ],
    "name:und_x_variant":[
        "Mazraat Qafoua",
        "Mazra\u2018at Qafwah"
    ],
    "wof:name":"Mazra`at Qafwah",
    "wof:placetype":"locality"
},
  "geometry": {"coordinates":[35.68074,33.28302],"type":"Point"}
}