{
  "type": "Feature",
  "properties": {
    "gn:admin1_code":"10.0",
    "gn:asciiname":"Duwayr al Akrad",
    "gn:country_code":"SY",
    "gn:dem":721,
    "gn:feature_class":"P",
    "gn:feature_code":"PPL",
    "gn:name":"Duwayr al Akr\u0101d",
    "gn:population":0,
    "gn:timezone":"Asia/Damascus",
    "iso:country":"SY",
    "name:ara_x_preferred":[
        "\u062f\u0648\u064a\u0631 \u0627\u0644\u0627\u0643\u0631\u0627\u062f"
    ],
    "name:und_x_variant":[
        "Doua\u00efr el Akr\u00e2d",
        "Duwayr al Akr\u0101d",
        "Al Akr\u0101d"
    ],
    "wof:name":"Duwayr al Akrad",
    "wof:placetype":"locality"
},
  "geometry": {"coordinates":[36.26163,35.72116],"type":"Point"}
}