{
  "type": "Feature",
  "properties": {
    "gn:admin1_code":"12.0",
    "gn:asciiname":"Buzayt",
    "gn:country_code":"SY",
    "gn:dem":496,
    "gn:feature_class":"P",
    "gn:feature_code":"PPL",
    "gn:name":"Buzayt",
    "gn:population":0,
    "gn:timezone":"Asia/Damascus",
    "iso:country":"SY",
    "name:ara_x_preferred":[
        "\u0628\u0632\u064a\u062a"
    ],
    "name:und_x_variant":[
        "Bza\u00efte",
        "Bze\u00efte",
        "Bzaytah",
        "Buzayt"
    ],
    "wof:name":"Buzayt",
    "wof:placetype":"locality"
},
  "geometry": {"coordinates":[36.39974,35.78887],"type":"Point"}
}