{
  "type": "Feature",
  "properties": {
    "gn:admin1_code":"9.0",
    "gn:asciiname":"Umm Ghubar",
    "gn:country_code":"SY",
    "gn:dem":294,
    "gn:feature_class":"P",
    "gn:feature_code":"PPL",
    "gn:name":"Umm Ghub\u0101r",
    "gn:population":0,
    "gn:timezone":"Asia/Damascus",
    "iso:country":"SY",
    "name:ara_x_preferred":[
        "Umm Ghub\u0101r"
    ],
    "name:ara_x_variant":[
        "\u0627\u0645 \u063a\u0628\u0627\u0631"
    ],
    "name:und_x_variant":[
        "Oum Rhb\u00e2r"
    ],
    "wof:name":"Umm Ghubar",
    "wof:placetype":"locality"
},
  "geometry": {"coordinates":[37.29275,35.73518],"type":"Point"}
}