{
  "type": "Feature",
  "properties": {
    "gn:admin1_code":"9.0",
    "gn:asciiname":"Tall `Abur",
    "gn:country_code":"SY",
    "gn:dem":369,
    "gn:feature_class":"P",
    "gn:feature_code":"PPL",
    "gn:name":"Tall \u2018\u0100b\u016br",
    "gn:population":0,
    "gn:timezone":"Asia/Damascus",
    "iso:country":"SY",
    "name:ara_x_preferred":[
        "\u062a\u0644 \u0639\u0627\u0628\u0648\u0631"
    ],
    "name:und_x_variant":[
        "Tell A\u00e2bo\u00fbr",
        "Tell Abbas",
        "Tall \u2018\u0100b\u016br"
    ],
    "wof:name":"Tall `Abur",
    "wof:placetype":"locality"
},
  "geometry": {"coordinates":[37.29646,36.099],"type":"Point"}
}