{
  "type": "Feature",
  "properties": {
    "gn:admin1_code":"2.0",
    "gn:asciiname":"`Annaqiyat Jiftlik",
    "gn:country_code":"SY",
    "gn:dem":136,
    "gn:feature_class":"P",
    "gn:feature_code":"PPL",
    "gn:name":"\u2018Ann\u0101q\u012byat Jiftlik",
    "gn:population":0,
    "gn:timezone":"Asia/Damascus",
    "iso:country":"SY",
    "name:ara_x_preferred":[
        "\u0639\u0646\u0627\u0642\u064a\u0629 \u062c\u0641\u062a\u0644\u0643"
    ],
    "name:ara_x_variant":[
        "\u0627\u0644\u0639\u0646\u0627\u0642\u064a\u0629 \u062c\u0641\u062a\u0644\u0643"
    ],
    "name:und_x_variant":[
        "Aann\u00e2q\u00eeyet Tchiftlik",
        "\u2018Ann\u0101q\u012byat Jiftlik",
        "Al \u2018Ann\u0101q\u012byat Jiftlik"
    ],
    "wof:name":"`Annaqiyat Jiftlik",
    "wof:placetype":"locality"
},
  "geometry": {"coordinates":[35.98333,35.55],"type":"Point"}
}