{
  "type": "Feature",
  "properties": {
    "gn:admin1_code":"9.0",
    "gn:asciiname":"Karak Mawla",
    "gn:country_code":"SY",
    "gn:dem":431,
    "gn:feature_class":"P",
    "gn:feature_code":"PPL",
    "gn:name":"Karak Mawl\u00e1",
    "gn:population":0,
    "gn:timezone":"Asia/Damascus",
    "iso:country":"SY",
    "name:ara_x_preferred":[
        "\u0643\u0631\u0643 \u0645\u0648\u0644\u0649"
    ],
    "name:und_x_variant":[
        "Guirek Mo\u00fbla",
        "K\u012brk M\u016bl\u0101",
        "Guirk",
        "K\u012brak M\u016bl\u0101",
        "Karak Mawl\u00e1"
    ],
    "wof:name":"Karak Mawla",
    "wof:placetype":"locality"
},
  "geometry": {"coordinates":[38.39667,36.61232],"type":"Point"}
}