{
  "type": "Feature",
  "properties": {
    "gn:admin1_code":"1.0",
    "gn:asciiname":"Al Hilaliyah",
    "gn:country_code":"SY",
    "gn:dem":367,
    "gn:feature_class":"P",
    "gn:feature_code":"PPL",
    "gn:name":"Al Hil\u0101l\u012byah",
    "gn:population":0,
    "gn:timezone":"Asia/Damascus",
    "iso:country":"SY",
    "name:ara_x_preferred":[
        "\u0627\u0644\u0647\u0644\u0627\u0644\u064a\u0629"
    ],
    "name:und_x_variant":[
        "El H\u00e9l\u00e2l\u00eey\u00e9",
        "Al Hil\u0101l\u012byah"
    ],
    "wof:name":"Al Hilaliyah",
    "wof:placetype":"locality"
},
  "geometry": {"coordinates":[40.58769,36.64565],"type":"Point"}
}