{
  "type": "Feature",
  "properties": {
    "gn:admin1_code":"10.0",
    "gn:asciiname":"Al Muradiyah",
    "gn:country_code":"SY",
    "gn:dem":289,
    "gn:feature_class":"P",
    "gn:feature_code":"PPL",
    "gn:name":"Al Mur\u0101d\u012byah",
    "gn:population":0,
    "gn:timezone":"Asia/Damascus",
    "iso:country":"SY",
    "name:ara_x_preferred":[
        "\u0645\u0631\u0627\u062f\u064a\u0629"
    ],
    "name:ara_x_variant":[
        "\u0627\u0644\u0645\u0631\u0627\u062f\u064a\u0629"
    ],
    "name:und_x_variant":[
        "Mr\u00e2d\u00eey\u00e9",
        "Mur\u0101d\u012byah",
        "Mr\u00e2diye",
        "Al Mur\u0101d\u012byah"
    ],
    "wof:name":"Al Muradiyah",
    "wof:placetype":"locality"
},
  "geometry": {"coordinates":[36.83244000000001,35.08354],"type":"Point"}
}