{
  "type": "Feature",
  "properties": {
    "gn:admin1_code":"9.0",
    "gn:asciiname":"Kayariyah",
    "gn:country_code":"SY",
    "gn:dem":358,
    "gn:feature_class":"P",
    "gn:feature_code":"PPL",
    "gn:name":"Kay\u0101r\u012byah",
    "gn:population":0,
    "gn:timezone":"Asia/Damascus",
    "iso:country":"SY",
    "name:ara_x_preferred":[
        "\u0643\u064a\u0627\u0631\u064a\u0629"
    ],
    "name:und_x_variant":[
        "Gayariy\u00e9",
        "Kay\u00e2r\u00eey\u00e9",
        "Kay\u0101r\u012byah"
    ],
    "wof:name":"Kayariyah",
    "wof:placetype":"locality"
},
  "geometry": {"coordinates":[37.70761,36.19308],"type":"Point"}
}