{
  "type": "Feature",
  "properties": {
    "gn:admin1_code":"4.0",
    "gn:asciiname":"Kur Hasan",
    "gn:country_code":"SY",
    "gn:dem":362,
    "gn:feature_class":"P",
    "gn:feature_code":"PPL",
    "gn:name":"K\u016br \u1e28asan",
    "gn:population":0,
    "gn:timezone":"Asia/Damascus",
    "iso:country":"SY",
    "name:ara_x_preferred":[
        "\u0643\u0648\u0631 \u062d\u0633\u0646"
    ],
    "name:und_x_variant":[
        "Ko\u00fbr Hassane",
        "K\u016br \u1e28asan"
    ],
    "wof:name":"Kur Hasan",
    "wof:placetype":"locality"
},
  "geometry": {"coordinates":[38.75751,36.57615],"type":"Point"}
}