{
  "type": "Feature",
  "properties": {
    "gn:admin1_code":"5.0",
    "gn:asciiname":"`Ariqah",
    "gn:country_code":"SY",
    "gn:dem":804,
    "gn:feature_class":"P",
    "gn:feature_code":"PPLA3",
    "gn:name":"\u2018Ar\u012bqah",
    "gn:population":0,
    "gn:timezone":"Asia/Damascus",
    "iso:country":"SY",
    "name:ara_x_preferred":[
        "\u062a\u0644 \u0639\u0645\u0627\u0631"
    ],
    "name:ara_x_variant":[
        "\u0639\u0631\u064a\u0642\u0629"
    ],
    "name:rus_x_preferred":[
        "\u0410\u0440\u0438\u043a\u0430"
    ],
    "name:und_x_variant":[
        "\u2018Ar\u012bqah"
    ],
    "wof:name":"`Ariqah",
    "wof:placetype":"locality"
},
  "geometry": {"coordinates":[36.48336,32.88981],"type":"Point"}
}