{
  "type": "Feature",
  "properties": {
    "gn:admin1_code":"9.0",
    "gn:asciiname":"Wadi`ah",
    "gn:country_code":"SY",
    "gn:dem":370,
    "gn:feature_class":"P",
    "gn:feature_code":"PPL",
    "gn:name":"Wad\u012b\u2018ah",
    "gn:population":0,
    "gn:timezone":"Asia/Damascus",
    "iso:country":"SY",
    "name:ara_x_preferred":[
        "\u0648\u062f\u064a\u0639\u0629"
    ],
    "name:und_x_variant":[
        "Ouad\u00eea\u00e2",
        "Oudiah",
        "Oud\u00e9ah",
        "Wad\u012b\u2018ah"
    ],
    "wof:name":"Wadi`ah",
    "wof:placetype":"locality"
},
  "geometry": {"coordinates":[37.48425,36.19335],"type":"Point"}
}