{
  "type": "Feature",
  "properties": {
    "gn:admin1_code":"9.0",
    "gn:asciiname":"Tall Hasan",
    "gn:country_code":"SY",
    "gn:dem":342,
    "gn:feature_class":"P",
    "gn:feature_code":"PPL",
    "gn:name":"Tall \u1e28asan",
    "gn:population":0,
    "gn:timezone":"Asia/Damascus",
    "iso:country":"SY",
    "name:ara_x_preferred":[
        "\u062a\u0644 \u062d\u0633\u0646"
    ],
    "name:und_x_variant":[
        "Tell Hassane",
        "Tall \u1e28asan"
    ],
    "wof:name":"Tall Hasan",
    "wof:placetype":"locality"
},
  "geometry": {"coordinates":[37.851,36.06056],"type":"Point"}
}