{
  "type": "Feature",
  "properties": {
    "gn:admin1_code":"9.0",
    "gn:asciiname":"Mi`sarat Juqq",
    "gn:country_code":"SY",
    "gn:dem":714,
    "gn:feature_class":"P",
    "gn:feature_code":"PPL",
    "gn:name":"Mi\u2018\u015farat Juqq",
    "gn:population":0,
    "gn:timezone":"Asia/Damascus",
    "iso:country":"SY",
    "name:ara_x_preferred":[
        "\u0645\u0639\u0635\u0631\u0629 \u062c\u0642"
    ],
    "name:ara_x_variant":[
        "\u0627\u0644\u0645\u0639\u0635\u0631\u0629"
    ],
    "name:und_x_variant":[
        "Maassaradjiq",
        "Massaradjik",
        "Ma\u2018\u015far Juqq",
        "Mi\u2018\u015farat Juqq",
        "Ma\u2018\u015farat Juqq",
        "Al Mi\u2018\u015farah"
    ],
    "wof:name":"Mi`sarat Juqq",
    "wof:placetype":"locality"
},
  "geometry": {"coordinates":[36.66565,36.54814],"type":"Point"}
}