{
  "type": "Feature",
  "properties": {
    "gn:admin1_code":"1.0",
    "gn:asciiname":"Kawlah",
    "gn:country_code":"SY",
    "gn:dem":409,
    "gn:feature_class":"P",
    "gn:feature_code":"PPL",
    "gn:name":"Kawlah",
    "gn:population":0,
    "gn:timezone":"Asia/Damascus",
    "iso:country":"SY",
    "name:ara_x_preferred":[
        "\u0643\u0648\u0644\u0629"
    ],
    "wof:name":"Kawlah",
    "wof:placetype":"locality"
},
  "geometry": {"coordinates":[40.68785,36.86704],"type":"Point"}
}