{
  "type": "Feature",
  "properties": {
    "gn:admin1_code":"7.0",
    "gn:asciiname":"Shujayri",
    "gn:country_code":"SY",
    "gn:dem":786,
    "gn:feature_class":"P",
    "gn:feature_code":"PPL",
    "gn:name":"Shujayr\u012b",
    "gn:population":0,
    "gn:timezone":"Asia/Damascus",
    "iso:country":"SY",
    "name:ara_x_preferred":[
        "\u0634\u062c\u064a\u0631\u064a"
    ],
    "name:und_x_variant":[
        "Shujayr\u012b"
    ],
    "wof:name":"Shujayri",
    "wof:placetype":"locality"
},
  "geometry": {"coordinates":[39.41926,35.4186],"type":"Point"}
}