{
  "type": "Feature",
  "properties": {
    "gn:admin1_code":"2.0",
    "gn:asciiname":"`Ayn Jandal",
    "gn:country_code":"SY",
    "gn:dem":623,
    "gn:feature_class":"P",
    "gn:feature_code":"PPL",
    "gn:name":"\u2018Ayn Jandal",
    "gn:population":0,
    "gn:timezone":"Asia/Damascus",
    "iso:country":"SY",
    "name:und_x_variant":[
        "A\u00efn Jannal",
        "\u2018Ayn Jandal"
    ],
    "wof:name":"`Ayn Jandal",
    "wof:placetype":"locality"
},
  "geometry": {"coordinates":[36.08813,35.51317],"type":"Point"}
}