{
  "type": "Feature",
  "properties": {
    "gn:admin1_code":"2.0",
    "gn:asciiname":"Al Qafr al Fawqani",
    "gn:country_code":"SY",
    "gn:dem":56,
    "gn:feature_class":"P",
    "gn:feature_code":"PPL",
    "gn:name":"Al Qafr al Fawq\u0101n\u012b",
    "gn:population":0,
    "gn:timezone":"Asia/Damascus",
    "iso:country":"SY",
    "name:ara_x_preferred":[
        "\u0627\u0644\u0642\u0641\u0631 \u0627\u0644\u0641\u0648\u0642\u0627\u0646\u064a"
    ],
    "name:und_x_variant":[
        "Al Qafr al Fawq\u0101n\u012b"
    ],
    "wof:name":"Al Qafr al Fawqani",
    "wof:placetype":"locality"
},
  "geometry": {"coordinates":[35.86312,35.71926],"type":"Point"}
}