{
  "type": "Feature",
  "properties": {
    "gn:admin1_code":"9.0",
    "gn:asciiname":"Qarah Mazra`ah",
    "gn:country_code":"SY",
    "gn:dem":482,
    "gn:feature_class":"P",
    "gn:feature_code":"PPL",
    "gn:name":"Qarah Mazra\u2018ah",
    "gn:population":0,
    "gn:timezone":"Asia/Damascus",
    "iso:country":"SY",
    "name:ara_x_preferred":[
        "\u0642\u0631\u0647 \u0645\u0632\u0631\u0639\u0629"
    ],
    "name:und_x_variant":[
        "Kara Mezraa",
        "Q\u0101rat Mazra\u2018ah",
        "Qara Mazraa",
        "Qarah Mazra\u2018ah"
    ],
    "wof:name":"Qarah Mazra`ah",
    "wof:placetype":"locality"
},
  "geometry": {"coordinates":[37.28105,36.65187],"type":"Point"}
}