{
  "type": "Feature",
  "properties": {
    "gn:admin1_code":"9.0",
    "gn:asciiname":"Bir Abu al `Allaj",
    "gn:country_code":"SY",
    "gn:dem":398,
    "gn:feature_class":"P",
    "gn:feature_code":"PPL",
    "gn:name":"B\u012br Ab\u016b al \u2018All\u0101j",
    "gn:population":0,
    "gn:timezone":"Asia/Damascus",
    "iso:country":"SY",
    "name:ara_x_preferred":[
        "\u0628\u064a\u0631 \u0623\u0628\u0648 \u0627\u0644\u0639\u0644\u0627\u062c"
    ],
    "name:und_x_variant":[
        "B\u012br Ab\u016b al \u2018All\u0101j"
    ],
    "wof:name":"Bir Abu al `Allaj",
    "wof:placetype":"locality"
},
  "geometry": {"coordinates":[38.1773,35.49022],"type":"Point"}
}