{
  "type": "Feature",
  "properties": {
    "gn:admin1_code":"11.0",
    "gn:asciiname":"`Ayn Subaykhah",
    "gn:country_code":"SY",
    "gn:dem":470,
    "gn:feature_class":"P",
    "gn:feature_code":"PPL",
    "gn:name":"\u2018Ayn Subaykhah",
    "gn:population":0,
    "gn:timezone":"Asia/Damascus",
    "iso:country":"SY",
    "name:ara_x_preferred":[
        "\u0639\u064a\u0646 \u0633\u0628\u064a\u062e\u0629"
    ],
    "name:und_x_variant":[
        "\u2018Ayn Subaykhah"
    ],
    "wof:name":"`Ayn Subaykhah",
    "wof:placetype":"locality"
},
  "geometry": {"coordinates":[38.8231,35.20255],"type":"Point"}
}