{
  "type": "Feature",
  "properties": {
    "gn:admin1_code":"3.0",
    "gn:asciiname":"Al Asbah",
    "gn:country_code":"SY",
    "gn:dem":775,
    "gn:feature_class":"P",
    "gn:feature_code":"PPL",
    "gn:name":"Al A\u015fba\u1e29",
    "gn:population":0,
    "gn:timezone":"Asia/Damascus",
    "iso:country":"SY",
    "name:ara_x_preferred":[
        "\u0627\u0644\u0623\u0635\u0628\u062d"
    ],
    "name:und_x_variant":[
        "Es Sb\u00e2h",
        "Es Sh\u00e2h",
        "A\u015f \u015eab\u0101\u1e29",
        "Al A\u015fba\u1e29",
        "Asbah"
    ],
    "wof:name":"Al Asbah",
    "wof:placetype":"locality"
},
  "geometry": {"coordinates":[35.88552,32.97987],"type":"Point"}
}