{
  "type": "Feature",
  "properties": {
    "gn:admin1_code":"1.0",
    "gn:asciiname":"Saraqasha",
    "gn:country_code":"SY",
    "gn:dem":323,
    "gn:feature_class":"P",
    "gn:feature_code":"PPL",
    "gn:name":"Sar\u0101qash\u0101",
    "gn:population":0,
    "gn:timezone":"Asia/Damascus",
    "iso:country":"SY",
    "name:ara_x_preferred":[
        "\u0633\u0631\u0627\u0642\u0634\u0627"
    ],
    "name:und_x_variant":[
        "Sarr\u0101q\u0101",
        "Sar\u0101qash\u0101"
    ],
    "wof:name":"Saraqasha",
    "wof:placetype":"locality"
},
  "geometry": {"coordinates":[40.37734,36.03796],"type":"Point"}
}