{
  "type": "Feature",
  "properties": {
    "gn:admin1_code":"9.0",
    "gn:asciiname":"Dawli Daq",
    "gn:country_code":"SY",
    "gn:dem":581,
    "gn:feature_class":"P",
    "gn:feature_code":"PPL",
    "gn:name":"Dawl\u012b D\u0101q",
    "gn:population":0,
    "gn:timezone":"Asia/Damascus",
    "iso:country":"SY",
    "name:ara_x_preferred":[
        "\u062f\u0648\u0644\u064a \u062f\u0627\u063a"
    ],
    "name:ara_x_variant":[
        "\u0627\u0644\u0627\u0645\u064a\u0631\u064a\u0629",
        "\u062f\u0648\u0646\u064a \u062f\u0627\u063a",
        "\u062f\u0648\u0644\u064a \u062f\u0627\u0642"
    ],
    "name:kur_x_preferred":[
        "Don\u00ea Dagh"
    ],
    "name:kur_x_variant":[
        "Don\u00ee Dagh",
        "\u062f\u06c6\u0646\u06ce \u062f\u0627\u063a",
        "\u062f\u06c6\u0646\u0649 \u062f\u0627\u063a"
    ],
    "name:und_x_variant":[
        "D\u00f4l\u00ee D\u00e2rh",
        "Dawh L\u012b \u0162\u0101gh",
        "Dawl\u012b \u0162\u0101gh",
        "Dawl\u012b D\u0101gh",
        "Al Am\u012br\u012byah",
        "D\u016bn\u012b D\u0101gh",
        "El Am\u00eeriy\u00ea",
        "Don\u00ea Dax",
        "Dawl\u012b D\u0101q"
    ],
    "wof:name":"Dawli Daq",
    "wof:placetype":"locality"
},
  "geometry": {"coordinates":[38.24491,36.86397],"type":"Point"}
}