{
  "type": "Feature",
  "properties": {
    "gn:admin1_code":"9.0",
    "gn:asciiname":"Khirbat al Jahash",
    "gn:country_code":"SY",
    "gn:dem":401,
    "gn:feature_class":"P",
    "gn:feature_code":"PPL",
    "gn:name":"Khirbat al Ja\u1e29ash",
    "gn:population":0,
    "gn:timezone":"Asia/Damascus",
    "iso:country":"SY",
    "name:ara_x_preferred":[
        "\u062e\u0631\u0628\u0629 \u0627\u0644\u062c\u062d\u0634"
    ],
    "name:und_x_variant":[
        "Kheurbet el Hadjiche",
        "Kheurbet ej Jh\u00e2ch",
        "Khirbat al Ji\u1e29\u0101sh",
        "Khirbat al Ja\u1e29ash"
    ],
    "wof:name":"Khirbat al Jahash",
    "wof:placetype":"locality"
},
  "geometry": {"coordinates":[37.62332,36.27197],"type":"Point"}
}