{
  "type": "Feature",
  "properties": {
    "gn:admin1_code":"12.0",
    "gn:asciiname":"Al Khafiyah",
    "gn:country_code":"SY",
    "gn:dem":300,
    "gn:feature_class":"P",
    "gn:feature_code":"PPL",
    "gn:name":"Al Khaf\u012byah",
    "gn:population":0,
    "gn:timezone":"Asia/Damascus",
    "iso:country":"SY",
    "name:ara_x_preferred":[
        "\u0627\u0644\u062e\u0641\u064a\u0629"
    ],
    "name:und_x_variant":[
        "Kh\u00e2f\u00eey\u00e9",
        "Kh\u0101f\u012byah",
        "Al Khaf\u012byah"
    ],
    "wof:name":"Al Khafiyah",
    "wof:placetype":"locality"
},
  "geometry": {"coordinates":[36.99699,35.73478],"type":"Point"}
}