{
  "type": "Feature",
  "properties": {
    "gn:admin1_code":"1.0",
    "gn:asciiname":"Aradah",
    "gn:country_code":"SY",
    "gn:dem":366,
    "gn:feature_class":"P",
    "gn:feature_code":"PPL",
    "gn:name":"Ar\u0101\u1e11ah",
    "gn:population":0,
    "gn:timezone":"Asia/Damascus",
    "iso:country":"SY",
    "name:ara_x_preferred":[
        "\u0623\u0631\u0627\u0636\u0629"
    ],
    "name:und_x_variant":[
        "Ar\u0101\u1e11ah"
    ],
    "wof:name":"Aradah",
    "wof:placetype":"locality"
},
  "geometry": {"coordinates":[41.0506,36.16034000000001],"type":"Point"}
}