{
  "type": "Feature",
  "properties": {
    "gn:admin1_code":"8.0",
    "gn:asciiname":"Ard az Za`tarah",
    "gn:country_code":"SY",
    "gn:dem":1105,
    "gn:feature_class":"P",
    "gn:feature_code":"PPLL",
    "gn:name":"Ar\u1e11 az Za\u2018tarah",
    "gn:population":0,
    "gn:timezone":"Asia/Damascus",
    "iso:country":"SY",
    "name:ara_x_preferred":[
        "\u0623\u0631\u0636 \u0627\u0644\u0632\u0639\u062a\u0631\u0629"
    ],
    "name:und_x_variant":[
        "Ar\u1e11 az Za\u2018tarah"
    ],
    "wof:name":"Ard az Za`tarah",
    "wof:placetype":"locality"
},
  "geometry": {"coordinates":[36.52782,33.70326],"type":"Point"}
}