{
  "type": "Feature",
  "properties": {
    "gn:admin1_code":"7.0",
    "gn:asciiname":"Hawayij Diyab",
    "gn:country_code":"SY",
    "gn:dem":211,
    "gn:feature_class":"P",
    "gn:feature_code":"PPL",
    "gn:name":"\u1e28aw\u0101yij Diy\u0101b",
    "gn:population":0,
    "gn:timezone":"Asia/Damascus",
    "iso:country":"SY",
    "name:ara_x_preferred":[
        "\u062d\u0648\u0627\u064a\u062c \u062f\u064a\u0627\u0628"
    ],
    "name:und_x_variant":[
        "\u1e28aw\u0101yij Diy\u0101b",
        "\u1e28aw\u0101\u2019ij Dhi\u2019\u0101b"
    ],
    "wof:name":"Hawayij Diyab",
    "wof:placetype":"locality"
},
  "geometry": {"coordinates":[40.06217,35.47752],"type":"Point"}
}