{
  "type": "Feature",
  "properties": {
    "gn:admin1_code":"9.0",
    "gn:asciiname":"Adh Dhahabiyah",
    "gn:country_code":"SY",
    "gn:dem":401,
    "gn:feature_class":"P",
    "gn:feature_code":"PPL",
    "gn:name":"Adh Dhahab\u012byah",
    "gn:population":0,
    "gn:timezone":"Asia/Damascus",
    "iso:country":"SY",
    "name:ara_x_preferred":[
        "\u0627\u0644\u0630\u0647\u0628\u064a\u0629"
    ],
    "name:ara_x_variant":[
        "\u0630\u0647\u0628\u064a\u0629"
    ],
    "name:und_x_variant":[
        "Dahab\u00eey\u00e9",
        "Adh Dhahab\u012byah",
        "Dhahab\u012byah"
    ],
    "wof:name":"Adh Dhahabiyah",
    "wof:placetype":"locality"
},
  "geometry": {"coordinates":[37.20164000000001,36.13625],"type":"Point"}
}