{
  "type": "Feature",
  "properties": {
    "gn:admin1_code":"2.0",
    "gn:asciiname":"Masit",
    "gn:country_code":"SY",
    "gn:dem":584,
    "gn:feature_class":"P",
    "gn:feature_code":"PPL",
    "gn:name":"Mas\u012bt",
    "gn:population":0,
    "gn:timezone":"Asia/Damascus",
    "iso:country":"SY",
    "name:ara_x_preferred":[
        "Ms\u012bt"
    ],
    "name:ara_x_variant":[
        "\u0645\u0633\u064a\u062a"
    ],
    "name:und_x_variant":[
        "Ms\u00eete",
        "Mas\u012bt"
    ],
    "wof:name":"Masit",
    "wof:placetype":"locality"
},
  "geometry": {"coordinates":[36.12851,35.47969000000001],"type":"Point"}
}