{
  "type": "Feature",
  "properties": {
    "gn:admin1_code":"9.0",
    "gn:asciiname":"Qurayriyah",
    "gn:country_code":"SY",
    "gn:dem":197,
    "gn:feature_class":"P",
    "gn:feature_code":"PPL",
    "gn:name":"Qurayr\u012byah",
    "gn:population":0,
    "gn:timezone":"Asia/Damascus",
    "iso:country":"SY",
    "name:ara_x_preferred":[
        "\u0642\u0631\u064a\u0631\u064a\u0651\u0629"
    ],
    "name:und_x_variant":[
        "Fre\u00efri\u00e9",
        "Qra\u00efr\u00eey\u00e9",
        "Frer\u00efy\u00e9",
        "Qurayr\u012byah"
    ],
    "wof:name":"Qurayriyah",
    "wof:placetype":"locality"
},
  "geometry": {"coordinates":[36.7709,36.39959],"type":"Point"}
}