{
  "type": "Feature",
  "properties": {
    "gn:admin1_code":"1.0",
    "gn:asciiname":"Umm `Ayyash Fawqani",
    "gn:country_code":"SY",
    "gn:dem":399,
    "gn:feature_class":"P",
    "gn:feature_code":"PPL",
    "gn:name":"Umm \u2018Ayy\u0101sh Fawq\u0101n\u012b",
    "gn:population":0,
    "gn:timezone":"Asia/Damascus",
    "iso:country":"SY",
    "name:ara_x_preferred":[
        "\u0623\u0645 \u0639\u064a\u0627\u0634 \u0641\u0648\u0642\u0627\u0646\u064a"
    ],
    "name:und_x_variant":[
        "Oum A\u00efyach Faouq\u00e2ni",
        "Umm \u2018Ayy\u0101sh Fawq\u0101n\u012b"
    ],
    "wof:name":"Umm `Ayyash Fawqani",
    "wof:placetype":"locality"
},
  "geometry": {"coordinates":[40.42938,36.87128],"type":"Point"}
}