{
  "type": "Feature",
  "properties": {
    "gn:admin1_code":"4.0",
    "gn:asciiname":"Al Jabir",
    "gn:country_code":"SY",
    "gn:dem":226,
    "gn:feature_class":"P",
    "gn:feature_code":"PPL",
    "gn:name":"Al J\u0101bir",
    "gn:population":0,
    "gn:timezone":"Asia/Damascus",
    "iso:country":"SY",
    "name:ara_x_preferred":[
        "Al J\u0101bir"
    ],
    "name:ara_x_variant":[
        "\u0627\u0644\u062c\u0627\u0628\u0631"
    ],
    "wof:name":"Al Jabir",
    "wof:placetype":"locality"
},
  "geometry": {"coordinates":[39.54421,35.77797],"type":"Point"}
}