{
  "type": "Feature",
  "properties": {
    "gn:admin1_code":"9.0",
    "gn:asciiname":"Muman `Azu",
    "gn:country_code":"SY",
    "gn:dem":561,
    "gn:feature_class":"P",
    "gn:feature_code":"PPL",
    "gn:name":"M\u016bm\u0101n \u2018Az\u016b",
    "gn:population":0,
    "gn:timezone":"Asia/Damascus",
    "iso:country":"SY",
    "name:ara_x_preferred":[
        "M\u016bm\u0101n \u2018Az\u016b"
    ],
    "name:ara_x_variant":[
        "\u0645\u0648\u0645\u0627\u0646 \u0639\u0632\u0648",
        "\u0639\u0632\u064a\u0632\u064a\u0629",
        "\u0627\u0644\u0639\u0632\u064a\u0632\u064a\u0629"
    ],
    "name:kur_x_preferred":[
        "Moman\u00ea Xezo"
    ],
    "name:kur_x_variant":[
        "Muman\u00ee Xizu",
        "Muman\u00ee Xezu",
        "\u0645\u06c6\u0645\u0627\u0646\u06ce \u062e\u06d5\u0632\u06c6",
        "\u0645\u0648\u0645\u0627\u0646\u064a \u062e\u0632\u0648",
        "\u0645\u0648\u0645\u0627\u0646\u0649 \u062e\u06d5\u0632\u0648"
    ],
    "name:und_x_variant":[
        "Mo\u00fbm\u00e2ne Aazo",
        "Moum\u00e2ne Aaza",
        "Muman \u2018Azo",
        "\u2018Az\u012bz\u012byah",
        "Momani Khazo",
        "Ez\u00eeziya",
        "\u2018Az\u012bz\u012bya",
        "Al \u2018Az\u012bz\u012byah",
        "Aziza",
        "Azizia",
        "Aziziyeh",
        "Aziziah",
        "Azizeih"
    ],
    "wof:name":"Muman `Azu",
    "wof:placetype":"locality"
},
  "geometry": {"coordinates":[38.29114000000001,36.87125],"type":"Point"}
}