{
  "type": "Feature",
  "properties": {
    "gn:admin1_code":"9.0",
    "gn:asciiname":"Al Mashrafah",
    "gn:country_code":"SY",
    "gn:dem":495,
    "gn:feature_class":"P",
    "gn:feature_code":"PPL",
    "gn:name":"Al Mashrafah",
    "gn:population":0,
    "gn:timezone":"Asia/Damascus",
    "iso:country":"SY",
    "name:ara_x_preferred":[
        "\u0627\u0644\u0645\u0634\u0631\u0641\u0629"
    ],
    "wof:name":"Al Mashrafah",
    "wof:placetype":"locality"
},
  "geometry": {"coordinates":[37.1255,36.37761],"type":"Point"}
}