{
  "type": "Feature",
  "properties": {
    "gn:admin1_code":"9.0",
    "gn:asciiname":"Khirbat Zarbah",
    "gn:country_code":"SY",
    "gn:dem":451,
    "gn:feature_class":"P",
    "gn:feature_code":"PPL",
    "gn:name":"Khirbat Zarbah",
    "gn:population":0,
    "gn:timezone":"Asia/Damascus",
    "iso:country":"SY",
    "name:ara_x_preferred":[
        "\u062e\u0631\u0628\u0629 \u0632\u0631\u0628\u0629"
    ],
    "name:und_x_variant":[
        "Kheurbet Zerb\u00e9",
        "Khirbat Zarbah"
    ],
    "wof:name":"Khirbat Zarbah",
    "wof:placetype":"locality"
},
  "geometry": {"coordinates":[38.4103,36.48495],"type":"Point"}
}