{
  "type": "Feature",
  "properties": {
    "gn:admin1_code":"2.0",
    "gn:asciiname":"Jahruqah",
    "gn:cc2":"SY",
    "gn:country_code":"SY",
    "gn:dem":148,
    "gn:feature_class":"P",
    "gn:feature_code":"PPL",
    "gn:name":"Ja\u1e29r\u016bqah",
    "gn:population":0,
    "gn:timezone":"Asia/Damascus",
    "iso:country":"SY",
    "name:und_x_variant":[
        "Mahro\u00fbqa",
        "Ja\u1e29r\u016bqah"
    ],
    "wof:name":"Jahruqah",
    "wof:placetype":"locality"
},
  "geometry": {"coordinates":[36.06667,35.73333],"type":"Point"}
}