{
  "type": "Feature",
  "properties": {
    "gn:admin1_code":"2.0",
    "gn:asciiname":"Kafr Dulbah",
    "gn:country_code":"SY",
    "gn:dem":896,
    "gn:feature_class":"P",
    "gn:feature_code":"PPL",
    "gn:name":"Kafr Dulbah",
    "gn:population":0,
    "gn:timezone":"Asia/Damascus",
    "iso:country":"SY",
    "name:ara_x_preferred":[
        "\u0643\u0641\u0631 \u062f\u0644\u0628\u0629"
    ],
    "name:und_x_variant":[
        "Kafer Delb\u00e9",
        "Kafr Delb\u00e9",
        "Kafr Dulbah"
    ],
    "wof:name":"Kafr Dulbah",
    "wof:placetype":"locality"
},
  "geometry": {"coordinates":[36.15911,35.67017],"type":"Point"}
}