{
  "type": "Feature",
  "properties": {
    "gn:admin1_code":"2.0",
    "gn:asciiname":"Mashqita",
    "gn:country_code":"SY",
    "gn:dem":251,
    "gn:feature_class":"P",
    "gn:feature_code":"PPL",
    "gn:name":"Mashq\u012bt\u0101",
    "gn:population":0,
    "gn:timezone":"Asia/Damascus",
    "iso:country":"SY",
    "name:ara_x_preferred":[
        "\u0645\u0634\u0642\u064a\u062a\u0627"
    ],
    "name:und_x_variant":[
        "Machkita",
        "Mashk\u012bt\u0101",
        "Mechqita",
        "Machqita",
        "Mashq\u012btah",
        "Mashq\u012bt\u0101",
        "Mashqita"
    ],
    "wof:name":"Mashqita",
    "wof:placetype":"locality"
},
  "geometry": {"coordinates":[35.90297,35.66823],"type":"Point"}
}