{
  "type": "Feature",
  "properties": {
    "gn:admin1_code":"14.0",
    "gn:asciiname":"Sa`in al Gharbiyah",
    "gn:country_code":"SY",
    "gn:dem":151,
    "gn:feature_class":"P",
    "gn:feature_code":"PPL",
    "gn:name":"S\u0101\u2018\u012bn al Gharb\u012byah",
    "gn:population":0,
    "gn:timezone":"Asia/Damascus",
    "iso:country":"SY",
    "name:ara_x_preferred":[
        "\u0633\u0627\u0639\u064a\u0646 \u0627\u0644\u063a\u0631\u0628\u064a\u0629"
    ],
    "name:und_x_variant":[
        "S\u00e2a\u00efn\u00e9 el Rharb\u00eey\u00e9",
        "S\u0101\u2018\u012bn al Gharb\u012byah",
        "S\u00e2a\u00efne el Rharb\u00eey\u00e9"
    ],
    "wof:name":"Sa`in al Gharbiyah",
    "wof:placetype":"locality"
},
  "geometry": {"coordinates":[36.00729000000001,34.80068],"type":"Point"}
}