{
  "type": "Feature",
  "properties": {
    "gn:admin1_code":"14.0",
    "gn:asciiname":"Sa`in ash Sharqiyah",
    "gn:country_code":"SY",
    "gn:dem":246,
    "gn:feature_class":"P",
    "gn:feature_code":"PPL",
    "gn:name":"S\u0101\u2018\u012bn ash Sharq\u012byah",
    "gn:population":0,
    "gn:timezone":"Asia/Damascus",
    "iso:country":"SY",
    "name:ara_x_preferred":[
        "\u0633\u0627\u0639\u064a\u0646 \u0627\u0644\u0634\u0631\u0642\u064a\u0629"
    ],
    "name:ara_x_variant":[
        "\u0628\u064a\u062a \u0628\u0627\u0633\u0637"
    ],
    "name:und_x_variant":[
        "S\u00e2a\u00efne ech Charq\u00eey\u00e9",
        "S\u0101\u2018\u012bn ash Sharq\u012byah",
        "S\u00e2a\u00efne ech Charq\u00eeye",
        "Bayt B\u0101si\u0163"
    ],
    "wof:name":"Sa`in ash Sharqiyah",
    "wof:placetype":"locality"
},
  "geometry": {"coordinates":[36.04585,34.92861],"type":"Point"}
}