{
  "type": "Feature",
  "properties": {
    "gn:admin1_code":"12.0",
    "gn:asciiname":"Zurzur",
    "gn:country_code":"SY",
    "gn:dem":377,
    "gn:feature_class":"P",
    "gn:feature_code":"PPL",
    "gn:name":"Zurz\u016br",
    "gn:population":0,
    "gn:timezone":"Asia/Damascus",
    "iso:country":"SY",
    "name:ara_x_preferred":[
        "Zurz\u016br"
    ],
    "name:ara_x_variant":[
        "\u0632\u0631\u0632\u0648\u0631"
    ],
    "name:und_x_variant":[
        "Zarz\u016br",
        "Zarzo\u00fbr"
    ],
    "wof:name":"Zurzur",
    "wof:placetype":"locality"
},
  "geometry": {"coordinates":[36.34011,35.95480999999999],"type":"Point"}
}