{
  "type": "Feature",
  "properties": {
    "gn:admin1_code":"12.0",
    "gn:asciiname":"Killi",
    "gn:country_code":"SY",
    "gn:dem":336,
    "gn:feature_class":"P",
    "gn:feature_code":"PPL",
    "gn:name":"Kill\u012b",
    "gn:population":0,
    "gn:timezone":"Asia/Damascus",
    "iso:country":"SY",
    "name:ara_x_preferred":[
        "Kill\u012b"
    ],
    "name:ara_x_variant":[
        "\u0643\u0644\u064a",
        "\u0643\u0644\u0644\u064a"
    ],
    "name:fas_x_preferred":[
        "\u06a9\u0644\u0644\u06cc"
    ],
    "name:pol_x_preferred":[
        "Killi"
    ],
    "name:und_x_variant":[
        "Kelli",
        "Kilal\u012b"
    ],
    "name:vie_x_preferred":[
        "Killi"
    ],
    "wof:name":"Killi",
    "wof:placetype":"locality"
},
  "geometry": {"coordinates":[36.69428,36.11089000000001],"type":"Point"}
}