{
  "type": "Feature",
  "properties": {
    "gn:admin1_code":"12.0",
    "gn:asciiname":"Dadikhin",
    "gn:country_code":"SY",
    "gn:dem":252,
    "gn:feature_class":"P",
    "gn:feature_code":"PPL",
    "gn:name":"D\u0101dikh\u012bn",
    "gn:population":0,
    "gn:timezone":"Asia/Damascus",
    "iso:country":"SY",
    "name:ara_x_preferred":[
        "\u062f\u0627\u062f\u062e\u064a\u0646"
    ],
    "name:ara_x_variant":[
        "\u062a\u0627\u062f\u062e\u064a\u0646"
    ],
    "name:und_x_variant":[
        "D\u0101dikh\u012bn",
        "T\u0101dikh\u012bn"
    ],
    "wof:name":"Dadikhin",
    "wof:placetype":"locality"
},
  "geometry": {"coordinates":[36.34094,35.87469],"type":"Point"}
}