{
  "type": "Feature",
  "properties": {
    "gn:admin1_code":"12.0",
    "gn:asciiname":"Ad Dana",
    "gn:country_code":"SY",
    "gn:dem":524,
    "gn:feature_class":"P",
    "gn:feature_code":"PPL",
    "gn:name":"Ad D\u0101n\u0101",
    "gn:population":0,
    "gn:timezone":"Asia/Damascus",
    "iso:country":"SY",
    "name:ara_x_preferred":[
        "Ad D\u0101n\u0101"
    ],
    "name:ara_x_variant":[
        "\u0627\u0644\u062f\u0627\u0646\u0627"
    ],
    "name:und_x_variant":[
        "Ed D\u00e2na",
        "D\u0101na",
        "Dana K\u00f6i"
    ],
    "wof:name":"Ad Dana",
    "wof:placetype":"locality"
},
  "geometry": {"coordinates":[36.68736,35.6997],"type":"Point"}
}