{
  "type": "Feature",
  "properties": {
    "gn:admin1_code":"5.0",
    "gn:asciiname":"`Awas",
    "gn:country_code":"SY",
    "gn:dem":1295,
    "gn:feature_class":"P",
    "gn:feature_code":"PPL",
    "gn:name":"\u2018Aw\u0101s",
    "gn:population":0,
    "gn:timezone":"Asia/Damascus",
    "iso:country":"SY",
    "name:ara_x_preferred":[
        "\u2018Aw\u0101s"
    ],
    "name:ara_x_variant":[
        "\u0639\u0648\u0627\u0633"
    ],
    "name:und_x_variant":[
        "Aaouas",
        "\u2018Awas"
    ],
    "wof:name":"`Awas",
    "wof:placetype":"locality"
},
  "geometry": {"coordinates":[36.77176,32.46992],"type":"Point"}
}