{
  "type": "Feature",
  "properties": {
    "gn:admin1_code":"6.0",
    "gn:asciiname":"Khirbat Junf",
    "gn:country_code":"SY",
    "gn:dem":639,
    "gn:feature_class":"P",
    "gn:feature_code":"PPL",
    "gn:name":"Khirbat Junf",
    "gn:population":0,
    "gn:timezone":"Asia/Damascus",
    "iso:country":"SY",
    "name:ara_x_preferred":[
        "\u062e\u0631\u0628\u0629 \u062c\u0646\u0641"
    ],
    "wof:name":"Khirbat Junf",
    "wof:placetype":"locality"
},
  "geometry": {"coordinates":[36.27876,32.48309],"type":"Point"}
}