{
  "type": "Feature",
  "properties": {
    "gn:admin1_code":"9.0",
    "gn:asciiname":"Mazra`at ar Rahib",
    "gn:country_code":"SY",
    "gn:dem":349,
    "gn:feature_class":"P",
    "gn:feature_code":"PPL",
    "gn:name":"Mazra\u2018at ar R\u0101hib",
    "gn:population":0,
    "gn:timezone":"Asia/Damascus",
    "iso:country":"SY",
    "name:ara_x_preferred":[
        "\u0645\u0632\u0631\u0639\u0629 \u0627\u0644\u0631\u0627\u0647\u0628"
    ],
    "name:und_x_variant":[
        "Mazra\u00e2t er Roua\u00efheb",
        "Mazra\u2018at ar Ruwayhib",
        "Mazra\u2018at ar R\u0101hib"
    ],
    "wof:name":"Mazra`at ar Rahib",
    "wof:placetype":"locality"
},
  "geometry": {"coordinates":[37.54139,35.82753],"type":"Point"}
}