{
  "type": "Feature",
  "properties": {
    "gn:admin1_code":"9.0",
    "gn:asciiname":"Qilah",
    "gn:country_code":"SY",
    "gn:dem":277,
    "gn:feature_class":"P",
    "gn:feature_code":"PPL",
    "gn:name":"Q\u012blah",
    "gn:population":0,
    "gn:timezone":"Asia/Damascus",
    "iso:country":"SY",
    "name:ara_x_preferred":[
        "\u0642\u064a\u0644\u0629"
    ],
    "name:und_x_variant":[
        "Kila",
        "Q\u00eel\u00e9",
        "Q\u012blah"
    ],
    "wof:name":"Qilah",
    "wof:placetype":"locality"
},
  "geometry": {"coordinates":[36.71642,36.41799],"type":"Point"}
}