{
  "type": "Feature",
  "properties": {
    "gn:admin1_code":"11.0",
    "gn:asciiname":"As Sarayim",
    "gn:country_code":"SY",
    "gn:dem":349,
    "gn:feature_class":"P",
    "gn:feature_code":"PPL",
    "gn:name":"A\u015f \u015ear\u0101yim",
    "gn:population":0,
    "gn:timezone":"Asia/Damascus",
    "iso:country":"SY",
    "name:ara_x_preferred":[
        "\u0627\u0644\u0635\u0631\u0627\u064a\u0645"
    ],
    "name:und_x_variant":[
        "A\u015f \u015ear\u0101yim"
    ],
    "wof:name":"As Sarayim",
    "wof:placetype":"locality"
},
  "geometry": {"coordinates":[39.53137,34.59744],"type":"Point"}
}