{
  "type": "Feature",
  "properties": {
    "gn:admin1_code":"4.0",
    "gn:asciiname":"Jubb al Jahlan",
    "gn:country_code":"SY",
    "gn:dem":345,
    "gn:feature_class":"P",
    "gn:feature_code":"PPL",
    "gn:name":"Jubb al Ja\u1e29l\u0101n",
    "gn:population":0,
    "gn:timezone":"Asia/Damascus",
    "iso:country":"SY",
    "name:ara_x_preferred":[
        "\u062c\u0628 \u0627\u0644\u062c\u062d\u0644\u0627\u0646"
    ],
    "name:und_x_variant":[
        "Jubb al Ja\u1e29l\u0101n"
    ],
    "wof:name":"Jubb al Jahlan",
    "wof:placetype":"locality"
},
  "geometry": {"coordinates":[38.42017,35.6784],"type":"Point"}
}