{
  "type": "Feature",
  "properties": {
    "gn:admin1_code":"4.0",
    "gn:asciiname":"Huwayjat Faraj",
    "gn:country_code":"SY",
    "gn:dem":254,
    "gn:feature_class":"P",
    "gn:feature_code":"PPL",
    "gn:name":"\u1e28uwayjat Faraj",
    "gn:population":0,
    "gn:timezone":"Asia/Damascus",
    "iso:country":"SY",
    "name:ara_x_preferred":[
        "\u062d\u0648\u064a\u062c\u0629 \u0641\u0631\u062c"
    ],
    "name:und_x_variant":[
        "\u1e28uwayjat Faraj"
    ],
    "wof:name":"Huwayjat Faraj",
    "wof:placetype":"locality"
},
  "geometry": {"coordinates":[38.7563,35.91099000000001],"type":"Point"}
}