{
  "type": "Feature",
  "properties": {
    "gn:admin1_code":"14.0",
    "gn:asciiname":"Murayjah",
    "gn:country_code":"SY",
    "gn:dem":522,
    "gn:feature_class":"P",
    "gn:feature_code":"PPL",
    "gn:name":"Murayjah",
    "gn:population":0,
    "gn:timezone":"Asia/Damascus",
    "iso:country":"SY",
    "name:ara_x_preferred":[
        "\u0645\u0631\u064a\u062c\u0629"
    ],
    "name:und_x_variant":[
        "Mra\u00efj\u00e9",
        "Murayjah"
    ],
    "wof:name":"Murayjah",
    "wof:placetype":"locality"
},
  "geometry": {"coordinates":[36.08399,35.02828],"type":"Point"}
}