{
  "type": "Feature",
  "properties": {
    "gn:admin1_code":"4.0",
    "gn:asciiname":"Mat`ab",
    "gn:country_code":"SY",
    "gn:dem":227,
    "gn:feature_class":"P",
    "gn:feature_code":"PPL",
    "gn:name":"Mat\u2018ab",
    "gn:population":0,
    "gn:timezone":"Asia/Damascus",
    "iso:country":"SY",
    "name:ara_x_preferred":[
        "\u0645\u062a\u0639\u0628"
    ],
    "name:und_x_variant":[
        "Mat\u2018ab"
    ],
    "wof:name":"Mat`ab",
    "wof:placetype":"locality"
},
  "geometry": {"coordinates":[39.66462,35.79296],"type":"Point"}
}