{
  "type": "Feature",
  "properties": {
    "gn:admin1_code":"9.0",
    "gn:asciiname":"Quru`ah Kabirah",
    "gn:country_code":"SY",
    "gn:dem":531,
    "gn:feature_class":"P",
    "gn:feature_code":"PPL",
    "gn:name":"Qur\u016b\u2018ah Kab\u012brah",
    "gn:population":0,
    "gn:timezone":"Asia/Damascus",
    "iso:country":"SY",
    "name:ara_x_preferred":[
        "\u0642\u0631\u0639\u0629 \u0643\u0628\u064a\u0631\u0629"
    ],
    "name:und_x_variant":[
        "Qoura Kbire",
        "Qoura\u00e2 K\u00e9b\u00eere",
        "Qur\u016b\u2018ah Kab\u012brah",
        "Qur\u2018at al Kab\u012brah",
        "Qur\u2018ah al Kab\u012brah"
    ],
    "wof:name":"Quru`ah Kabirah",
    "wof:placetype":"locality"
},
  "geometry": {"coordinates":[37.94166,36.43081],"type":"Point"}
}