{
  "type": "Feature",
  "properties": {
    "gn:admin1_code":"9.0",
    "gn:asciiname":"Bayt Isma`il",
    "gn:country_code":"SY",
    "gn:dem":354,
    "gn:feature_class":"P",
    "gn:feature_code":"PPLL",
    "gn:name":"Bayt Ism\u0101\u2018\u012bl",
    "gn:population":0,
    "gn:timezone":"Asia/Damascus",
    "iso:country":"SY",
    "name:ara_x_preferred":[
        "\u0628\u064a\u062a \u0627\u0633\u0645\u0627\u0639\u064a\u0644"
    ],
    "name:und_x_variant":[
        "Bayt Ism\u0101\u2018\u012bl"
    ],
    "wof:name":"Bayt Isma`il",
    "wof:placetype":"locality"
},
  "geometry": {"coordinates":[37.35875,36.14219],"type":"Point"}
}