{
  "type": "Feature",
  "properties": {
    "gn:admin1_code":"1.0",
    "gn:asciiname":"Tall az Ziyarat",
    "gn:country_code":"SY",
    "gn:dem":497,
    "gn:feature_class":"P",
    "gn:feature_code":"PPL",
    "gn:name":"Tall az Ziy\u0101r\u0101t",
    "gn:population":0,
    "gn:timezone":"Asia/Damascus",
    "iso:country":"SY",
    "name:ara_x_preferred":[
        "\u062a\u0644 \u0627\u0644\u0632\u064a\u0627\u0631\u0627\u062a"
    ],
    "name:und_x_variant":[
        "Kir\u012b Zil\u0101rah",
        "Guiri Zi\u00e2ra",
        "Kir\u012b Ziy\u0101rah",
        "Guira Ziara",
        "K\u012br Ziy\u0101r\u0101",
        "Gir Ziyara",
        "Guir Zi\u00e2ra",
        "Tall az Ziy\u0101r\u0101t"
    ],
    "wof:name":"Tall az Ziyarat",
    "wof:placetype":"locality"
},
  "geometry": {"coordinates":[42.05347,37.05798],"type":"Point"}
}