{
  "type": "Feature",
  "properties": {
    "gn:admin1_code":"12.0",
    "gn:asciiname":"Hukrat al Bayda'",
    "gn:country_code":"SY",
    "gn:dem":494,
    "gn:feature_class":"P",
    "gn:feature_code":"PPL",
    "gn:name":"\u1e28ukrat al Bayd\u0101\u2019",
    "gn:population":0,
    "gn:timezone":"Asia/Damascus",
    "iso:country":"SY",
    "name:ara_x_preferred":[
        "\u062d\u0643\u0631\u0629 \u0627\u0644\u0628\u064a\u0636\u0627\u0621"
    ],
    "name:und_x_variant":[
        "\u1e28ukrat al Bayd\u0101\u2019",
        "\u1e28akirat al Bayd\u0101\u2019"
    ],
    "wof:name":"Hukrat al Bayda'",
    "wof:placetype":"locality"
},
  "geometry": {"coordinates":[36.51683,36.04962],"type":"Point"}
}