{
  "type": "Feature",
  "properties": {
    "gn:admin1_code":"9.0",
    "gn:asciiname":"Ta`anah",
    "gn:country_code":"SY",
    "gn:dem":475,
    "gn:feature_class":"P",
    "gn:feature_code":"PPL",
    "gn:name":"\u0162a\u2018\u0101nah",
    "gn:population":0,
    "gn:timezone":"Asia/Damascus",
    "iso:country":"SY",
    "name:ara_x_preferred":[
        "\u0637\u0639\u0627\u0646\u0629"
    ],
    "name:und_x_variant":[
        "\u0162a\u2018\u0101nah"
    ],
    "wof:name":"Ta`anah",
    "wof:placetype":"locality"
},
  "geometry": {"coordinates":[37.31128,36.24981],"type":"Point"}
}