{
  "type": "Feature",
  "properties": {
    "gn:admin1_code":"12.0",
    "gn:asciiname":"Tall as Sahn",
    "gn:country_code":"SY",
    "gn:dem":283,
    "gn:feature_class":"P",
    "gn:feature_code":"PPL",
    "gn:name":"Tall a\u015f \u015ea\u1e29n",
    "gn:population":0,
    "gn:timezone":"Asia/Damascus",
    "iso:country":"SY",
    "name:ara_x_preferred":[
        "\u062a\u0644 \u0627\u0644\u0635\u062d\u0646"
    ],
    "name:und_x_variant":[
        "Tell es Sahn",
        "Tall a\u015f \u015ea\u1e29n"
    ],
    "wof:name":"Tall as Sahn",
    "wof:placetype":"locality"
},
  "geometry": {"coordinates":[36.40051,35.72400000000001],"type":"Point"}
}