{
  "type": "Feature",
  "properties": {
    "gn:admin1_code":"5.0",
    "gn:asciiname":"Khirbat Turayfah",
    "gn:country_code":"SY",
    "gn:dem":900,
    "gn:feature_class":"P",
    "gn:feature_code":"PPL",
    "gn:name":"Khirbat \u0162urayfah",
    "gn:population":0,
    "gn:timezone":"Asia/Damascus",
    "iso:country":"SY",
    "name:ara_x_preferred":[
        "\u062e\u0631\u0628\u0629 \u0637\u0631\u064a\u0641\u0629"
    ],
    "name:und_x_variant":[
        "Khirbat \u0162urayfah"
    ],
    "wof:name":"Khirbat Turayfah",
    "wof:placetype":"locality"
},
  "geometry": {"coordinates":[36.51954,32.66967],"type":"Point"}
}