{
  "type": "Feature",
  "properties": {
    "gn:admin1_code":"1.0",
    "gn:asciiname":"Na`am al `Ulwi",
    "gn:country_code":"SY",
    "gn:dem":261,
    "gn:feature_class":"P",
    "gn:feature_code":"PPL",
    "gn:name":"Na\u2018am al \u2018Ulw\u012b",
    "gn:population":0,
    "gn:timezone":"Asia/Damascus",
    "iso:country":"SY",
    "name:ara_x_preferred":[
        "\u0646\u0639\u0645 \u0627\u0644\u0639\u0644\u0648\u064a"
    ],
    "name:und_x_variant":[
        "Na\u2018am al \u2018Ulw\u012b",
        "Na\u2018am al \u2018Ilw\u012b"
    ],
    "wof:name":"Na`am al `Ulwi",
    "wof:placetype":"locality"
},
  "geometry": {"coordinates":[40.79987,35.96574000000001],"type":"Point"}
}