{
  "type": "Feature",
  "properties": {
    "gn:admin1_code":"2.0",
    "gn:asciiname":"Al Baqruqah",
    "gn:country_code":"SY",
    "gn:dem":1187,
    "gn:feature_class":"P",
    "gn:feature_code":"PPL",
    "gn:name":"Al Baqr\u016bqah",
    "gn:population":0,
    "gn:timezone":"Asia/Damascus",
    "iso:country":"SY",
    "name:und_x_variant":[
        "Bakro\u00fbq",
        "Al Baqr\u016bqah"
    ],
    "wof:name":"Al Baqruqah",
    "wof:placetype":"locality"
},
  "geometry": {"coordinates":[36.18661,35.63065],"type":"Point"}
}