{
  "type": "Feature",
  "properties": {
    "gn:admin1_code":"14.0",
    "gn:asciiname":"Harat at Tulay`i",
    "gn:country_code":"SY",
    "gn:dem":87,
    "gn:feature_class":"P",
    "gn:feature_code":"PPL",
    "gn:name":"\u1e28\u0101rat a\u0163 \u0162ulay\u2018\u012b",
    "gn:population":0,
    "gn:timezone":"Asia/Damascus",
    "iso:country":"SY",
    "name:ara_x_preferred":[
        "\u062d\u0627\u0631\u0629 \u0627\u0644\u0637\u0644\u064a\u0639\u064a"
    ],
    "name:und_x_variant":[
        "El H\u00e2ra",
        "H\u00e2ret ett Tla\u00efa\u00ef",
        "\u1e28\u0101rat a\u0163 \u0162ulay\u2018\u012b"
    ],
    "wof:name":"Harat at Tulay`i",
    "wof:placetype":"locality"
},
  "geometry": {"coordinates":[36.1264,34.72548],"type":"Point"}
}