{
  "type": "Feature",
  "properties": {
    "gn:admin1_code":"5.0",
    "gn:asciiname":"Junaynah",
    "gn:country_code":"SY",
    "gn:dem":1133,
    "gn:feature_class":"P",
    "gn:feature_code":"PPL",
    "gn:name":"Junaynah",
    "gn:population":0,
    "gn:timezone":"Asia/Damascus",
    "iso:country":"SY",
    "name:ara_x_preferred":[
        "\u062c\u0646\u064a\u0646\u0629"
    ],
    "name:fas_x_preferred":[
        "\u062c\u0646\u06cc\u0646\u0647"
    ],
    "name:pol_x_preferred":[
        "D\u017cunajna"
    ],
    "name:und_x_variant":[
        "Ej Jna\u00efn\u00e9",
        "Al Jnaynih",
        "Al Jan\u0101\u2019\u012bnah"
    ],
    "name:vie_x_preferred":[
        "Junaynah"
    ],
    "wof:name":"Junaynah",
    "wof:placetype":"locality"
},
  "geometry": {"coordinates":[36.73976,32.90257],"type":"Point"}
}