{
  "type": "Feature",
  "properties": {
    "gn:admin1_code":"9.0",
    "gn:asciiname":"Tatiyah",
    "gn:country_code":"SY",
    "gn:dem":537,
    "gn:feature_class":"P",
    "gn:feature_code":"PPL",
    "gn:name":"\u0162\u0101\u0163\u012byah",
    "gn:population":0,
    "gn:timezone":"Asia/Damascus",
    "iso:country":"SY",
    "name:ara_x_preferred":[
        "\u0637\u0627\u0637\u064a\u0629"
    ],
    "name:und_x_variant":[
        "T\u00e2tiy\u00e9",
        "\u0162\u0101\u0163\u012byah"
    ],
    "wof:name":"Tatiyah",
    "wof:placetype":"locality"
},
  "geometry": {"coordinates":[37.1159,36.62136],"type":"Point"}
}