{
  "type": "Feature",
  "properties": {
    "gn:admin1_code":"9.0",
    "gn:asciiname":"Khanasir",
    "gn:country_code":"SY",
    "gn:dem":353,
    "gn:feature_class":"P",
    "gn:feature_code":"PPLA3",
    "gn:name":"Khan\u0101\u015fir",
    "gn:population":0,
    "gn:timezone":"Asia/Damascus",
    "iso:country":"SY",
    "name:ara_x_preferred":[
        "\u062e\u0646\u0627\u0635\u0631"
    ],
    "name:ceb_x_preferred":[
        "Khan\u0101\u015fir"
    ],
    "name:fas_x_preferred":[
        "\u062e\u0646\u0627\u0635\u0631"
    ],
    "name:fra_x_preferred":[
        "Khanasser"
    ],
    "name:nno_x_preferred":[
        "Khanasir"
    ],
    "name:pol_x_preferred":[
        "Chanasir"
    ],
    "name:rus_x_preferred":[
        "\u0425\u0430\u043d\u0430\u0441\u0441\u0435\u0440"
    ],
    "name:und_x_variant":[
        "Qun\u0101sira",
        "Khamassir",
        "Khan\u00e2sser"
    ],
    "name:vie_x_preferred":[
        "Khanasir"
    ],
    "wof:name":"Khanasir",
    "wof:placetype":"locality"
},
  "geometry": {"coordinates":[37.49919000000001,35.78159],"type":"Point"}
}