{
  "type": "Feature",
  "properties": {
    "gn:admin1_code":"1.0",
    "gn:asciiname":"Kildanin",
    "gn:country_code":"SY",
    "gn:dem":330,
    "gn:feature_class":"P",
    "gn:feature_code":"PPL",
    "gn:name":"Kild\u0101n\u012bn",
    "gn:population":0,
    "gn:timezone":"Asia/Damascus",
    "iso:country":"SY",
    "name:ara_x_preferred":[
        "Kild\u0101n\u012bn"
    ],
    "name:ara_x_variant":[
        "\u0643\u0644\u062f\u0627\u0646\u064a\u0646"
    ],
    "wof:name":"Kildanin",
    "wof:placetype":"locality"
},
  "geometry": {"coordinates":[40.38611,36.67222],"type":"Point"}
}