{
  "type": "Feature",
  "properties": {
    "gn:admin1_code":"2.0",
    "gn:asciiname":"Al Buraykah",
    "gn:country_code":"SY",
    "gn:dem":112,
    "gn:feature_class":"P",
    "gn:feature_code":"PPL",
    "gn:name":"Al Buraykah",
    "gn:population":0,
    "gn:timezone":"Asia/Damascus",
    "iso:country":"SY",
    "name:ara_x_preferred":[
        "\u0627\u0644\u0628\u0631\u064a\u0643\u0629"
    ],
    "name:fas_x_preferred":[
        "\u0627\u0644\u0628\u0648\u0631\u06cc\u06a9\u0647"
    ],
    "name:nno_x_preferred":[
        "Al Buraykah"
    ],
    "name:und_x_variant":[
        "El Birk\u00e9",
        "Al Birkah",
        "Al Buraykah"
    ],
    "wof:name":"Al Buraykah",
    "wof:placetype":"locality"
},
  "geometry": {"coordinates":[35.93133,35.47568],"type":"Point"}
}