{
  "type": "Feature",
  "properties": {
    "gn:admin1_code":"12.0",
    "gn:asciiname":"Al Jubb ash Shamali",
    "gn:country_code":"SY",
    "gn:dem":247,
    "gn:feature_class":"P",
    "gn:feature_code":"PPL",
    "gn:name":"Al Jubb ash Sham\u0101l\u012b",
    "gn:population":0,
    "gn:timezone":"Asia/Damascus",
    "iso:country":"SY",
    "name:ara_x_preferred":[
        "\u0627\u0644\u062c\u0628 \u0627\u0644\u0634\u0645\u0627\u0644\u064a"
    ],
    "name:und_x_variant":[
        "Al Jubb ash Sham\u0101l\u012b"
    ],
    "wof:name":"Al Jubb ash Shamali",
    "wof:placetype":"locality"
},
  "geometry": {"coordinates":[36.46786,35.98643],"type":"Point"}
}