{
  "type": "Feature",
  "properties": {
    "gn:admin1_code":"2.0",
    "gn:asciiname":"Ad Dahqurah",
    "gn:country_code":"SY",
    "gn:dem":55,
    "gn:feature_class":"P",
    "gn:feature_code":"PPL",
    "gn:name":"Ad Da\u1e29q\u016brah",
    "gn:population":0,
    "gn:timezone":"Asia/Damascus",
    "iso:country":"SY",
    "name:ara_x_preferred":[
        "\u0627\u0644\u062f\u062d\u0642\u0648\u0631\u0629"
    ],
    "name:und_x_variant":[
        "Ad Da\u1e29q\u016brah"
    ],
    "wof:name":"Ad Dahqurah",
    "wof:placetype":"locality"
},
  "geometry": {"coordinates":[35.9765,35.26938],"type":"Point"}
}