{
  "type": "Feature",
  "properties": {
    "gn:admin1_code":"9.0",
    "gn:asciiname":"Bayt Ahmad al Muhammad",
    "gn:country_code":"SY",
    "gn:dem":359,
    "gn:feature_class":"P",
    "gn:feature_code":"PPL",
    "gn:name":"Bayt A\u1e29mad al Mu\u1e29ammad",
    "gn:population":0,
    "gn:timezone":"Asia/Damascus",
    "iso:country":"SY",
    "name:ara_x_preferred":[
        "\u0628\u064a\u062a \u0627\u062d\u0645\u062f \u0627\u0644\u0645\u062d\u0645\u062f"
    ],
    "name:und_x_variant":[
        "Bayt A\u1e29mad al Mu\u1e29ammad"
    ],
    "wof:name":"Bayt Ahmad al Muhammad",
    "wof:placetype":"locality"
},
  "geometry": {"coordinates":[37.36561,36.15554],"type":"Point"}
}