{
  "type": "Feature",
  "properties": {
    "gn:admin1_code":"9.0",
    "gn:asciiname":"Al `Amud",
    "gn:country_code":"SY",
    "gn:dem":681,
    "gn:feature_class":"P",
    "gn:feature_code":"PPL",
    "gn:name":"Al \u2018\u0100m\u016bd",
    "gn:population":0,
    "gn:timezone":"Asia/Damascus",
    "iso:country":"SY",
    "name:ara_x_preferred":[
        "\u062f\u064a\u0643\u0645\u0629 \u0637\u0627\u0634"
    ],
    "name:ara_x_variant":[
        "\u0627\u0644\u0639\u0627\u0645\u0648\u062f"
    ],
    "name:und_x_variant":[
        "D\u012bkmah \u0162\u0101sh",
        "D\u012bkmat \u0162\u0101sh",
        "Al \u2018\u0100m\u016bd"
    ],
    "wof:name":"Al `Amud",
    "wof:placetype":"locality"
},
  "geometry": {"coordinates":[37.01497,36.66296],"type":"Point"}
}