{
  "type": "Feature",
  "properties": {
    "gn:admin1_code":"9.0",
    "gn:asciiname":"Tall at Tawil",
    "gn:country_code":"SY",
    "gn:dem":290,
    "gn:feature_class":"P",
    "gn:feature_code":"PPL",
    "gn:name":"Tall a\u0163 \u0162aw\u012bl",
    "gn:population":0,
    "gn:timezone":"Asia/Damascus",
    "iso:country":"SY",
    "name:ara_x_preferred":[
        "\u062a\u0644 \u0637\u0648\u064a\u0644"
    ],
    "name:ara_x_variant":[
        "\u062a\u0644 \u0627\u0644\u0637\u0648\u064a\u0644"
    ],
    "name:und_x_variant":[
        "Tell Taou\u00eel",
        "Tall \u0162aw\u012bl",
        "Tall a\u0163 \u0162aw\u012bl"
    ],
    "wof:name":"Tall at Tawil",
    "wof:placetype":"locality"
},
  "geometry": {"coordinates":[36.86237,36.52415],"type":"Point"}
}