{
  "type": "Feature",
  "properties": {
    "gn:admin1_code":"14.0",
    "gn:asciiname":"Ubin",
    "gn:country_code":"SY",
    "gn:dem":400,
    "gn:feature_class":"P",
    "gn:feature_code":"PPL",
    "gn:name":"\u016ab\u012bn",
    "gn:population":0,
    "gn:timezone":"Asia/Damascus",
    "iso:country":"SY",
    "name:ara_x_preferred":[
        "\u016ab\u012bn"
    ],
    "name:ara_x_variant":[
        "\u0623\u0648\u0628\u064a\u0646"
    ],
    "name:und_x_variant":[
        "Oub\u00eene"
    ],
    "wof:name":"Ubin",
    "wof:placetype":"locality"
},
  "geometry": {"coordinates":[36.15632,34.84373],"type":"Point"}
}