{
  "type": "Feature",
  "properties": {
    "gn:admin1_code":"8.0",
    "gn:asciiname":"Al Khamisiyah",
    "gn:country_code":"SY",
    "gn:dem":611,
    "gn:feature_class":"P",
    "gn:feature_code":"PPL",
    "gn:name":"Al Kh\u0101mis\u012byah",
    "gn:population":0,
    "gn:timezone":"Asia/Damascus",
    "iso:country":"SY",
    "name:ara_x_preferred":[
        "\u0627\u0644\u062e\u0627\u0645\u0633\u064a\u0629"
    ],
    "name:und_x_variant":[
        "Al Kh\u0101mis\u012byah"
    ],
    "wof:name":"Al Khamisiyah",
    "wof:placetype":"locality"
},
  "geometry": {"coordinates":[36.49712,33.467],"type":"Point"}
}