{
  "type": "Feature",
  "properties": {
    "gn:admin1_code":"8.0",
    "gn:asciiname":"Dayr Khabiyah",
    "gn:country_code":"SY",
    "gn:dem":755,
    "gn:feature_class":"P",
    "gn:feature_code":"PPL",
    "gn:name":"Dayr Khab\u012byah",
    "gn:population":0,
    "gn:timezone":"Asia/Damascus",
    "iso:country":"SY",
    "name:ara_x_preferred":[
        "\u062f\u064a\u0631 \u062e\u0628\u064a\u0629"
    ],
    "name:und_x_variant":[
        "Dayr Gh\u0101biyah",
        "Deir Gh\u0101biye",
        "Dar Khab\u012byah",
        "Deir Khab\u00eey\u00e9",
        "De\u00efr Khaby\u00e9",
        "D\u00e2r Khab\u00eey\u00e9",
        "Dayr Khab\u012byah",
        "Deir Khabiyeh"
    ],
    "wof:name":"Dayr Khabiyah",
    "wof:placetype":"locality"
},
  "geometry": {"coordinates":[36.15975,33.36403],"type":"Point"}
}