{
  "type": "Feature",
  "properties": {
    "gn:admin1_code":"7.0",
    "gn:asciiname":"Al Kashmah",
    "gn:country_code":"SY",
    "gn:dem":176,
    "gn:feature_class":"P",
    "gn:feature_code":"PPL",
    "gn:name":"Al Kashmah",
    "gn:population":0,
    "gn:timezone":"Asia/Damascus",
    "iso:country":"SY",
    "name:ara_x_preferred":[
        "\u0627\u0644\u0643\u0634\u0645\u0629"
    ],
    "name:ara_x_variant":[
        "\u0627\u0644\u0643\u0634\u0643\u064a\u0629"
    ],
    "name:und_x_variant":[
        "Khashm\u0101",
        "Kechm\u00e9",
        "Kashmah",
        "Al Kashmah",
        "Al Kishmah",
        "Al Kishk\u012byah"
    ],
    "wof:name":"Al Kashmah",
    "wof:placetype":"locality"
},
  "geometry": {"coordinates":[40.93754000000001,34.62110999999999],"type":"Point"}
}