{
  "type": "Feature",
  "properties": {
    "gn:admin1_code":"6.0",
    "gn:asciiname":"Rakham",
    "gn:country_code":"SY",
    "gn:dem":673,
    "gn:feature_class":"P",
    "gn:feature_code":"PPL",
    "gn:name":"Rakham",
    "gn:population":0,
    "gn:timezone":"Asia/Damascus",
    "iso:country":"SY",
    "name:ara_x_preferred":[
        "\u0631\u062e\u0645"
    ],
    "wof:name":"Rakham",
    "wof:placetype":"locality"
},
  "geometry": {"coordinates":[36.34379000000001,32.71908],"type":"Point"}
}