{
  "type": "Feature",
  "properties": {
    "gn:admin1_code":"9.0",
    "gn:asciiname":"Umm Rajal",
    "gn:country_code":"SY",
    "gn:dem":354,
    "gn:feature_class":"P",
    "gn:feature_code":"PPL",
    "gn:name":"Umm Rajal",
    "gn:population":0,
    "gn:timezone":"Asia/Damascus",
    "iso:country":"SY",
    "name:ara_x_preferred":[
        "\u0623\u0645 \u0631\u062c\u0644"
    ],
    "wof:name":"Umm Rajal",
    "wof:placetype":"locality"
},
  "geometry": {"coordinates":[37.92738,35.85929],"type":"Point"}
}