{
  "type": "Feature",
  "properties": {
    "gn:admin1_code":"4.0",
    "gn:asciiname":"Salhabiyah",
    "gn:country_code":"SY",
    "gn:dem":248,
    "gn:feature_class":"P",
    "gn:feature_code":"PPL",
    "gn:name":"Sal\u1e29ab\u012byah",
    "gn:population":0,
    "gn:timezone":"Asia/Damascus",
    "iso:country":"SY",
    "name:ara_x_preferred":[
        "\u0633\u0644\u062d\u0628\u064a\u0629"
    ],
    "name:ara_x_variant":[
        "\u0627\u0644\u062e\u064a\u0627\u0644\u0629"
    ],
    "name:eng_x_preferred":[
        "Khayala"
    ],
    "name:und_x_variant":[
        "Salhab\u00eey\u00e9",
        "\u015eal\u1e29ab\u012byah",
        "Sal\u1e29ab\u012byah",
        "Al Khay\u0101lah"
    ],
    "wof:name":"Salhabiyah",
    "wof:placetype":"locality"
},
  "geometry": {"coordinates":[38.79,35.95541],"type":"Point"}
}