{
  "type": "Feature",
  "properties": {
    "gn:admin1_code":"2.0",
    "gn:asciiname":"Bishraghi",
    "gn:country_code":"SY",
    "gn:dem":775,
    "gn:feature_class":"P",
    "gn:feature_code":"PPL",
    "gn:name":"Bishr\u0101gh\u012b",
    "gn:population":0,
    "gn:timezone":"Asia/Damascus",
    "iso:country":"SY",
    "name:ara_x_preferred":[
        "Bishr\u0101gh\u012b"
    ],
    "name:ara_x_variant":[
        "\u0628\u0634\u0631\u0627\u063a\u064a"
    ],
    "name:und_x_variant":[
        "B\u00e9chr\u00e2rhi",
        "Beshr\u2019arhi"
    ],
    "wof:name":"Bishraghi",
    "wof:placetype":"locality"
},
  "geometry": {"coordinates":[36.09997,35.29872],"type":"Point"}
}