{
  "type": "Feature",
  "properties": {
    "gn:admin1_code":"7.0",
    "gn:asciiname":"Al Ba`um",
    "gn:country_code":"SY",
    "gn:dem":191,
    "gn:feature_class":"P",
    "gn:feature_code":"PPL",
    "gn:name":"Al B\u0101\u2018\u016bm",
    "gn:population":0,
    "gn:timezone":"Asia/Damascus",
    "iso:country":"SY",
    "name:ara_x_preferred":[
        "Al B\u0101\u2018\u016bm"
    ],
    "name:ara_x_variant":[
        "\u0627\u0644\u0628\u0627\u0639\u0648\u0645"
    ],
    "name:und_x_variant":[
        "Al Bul\u2018um"
    ],
    "wof:name":"Al Ba`um",
    "wof:placetype":"locality"
},
  "geometry": {"coordinates":[40.42755,35.0338],"type":"Point"}
}