{
  "type": "Feature",
  "properties": {
    "gn:admin1_code":"12.0",
    "gn:asciiname":"Dalluzah",
    "gn:country_code":"SY",
    "gn:dem":704,
    "gn:feature_class":"P",
    "gn:feature_code":"PPL",
    "gn:name":"Dall\u016bzah",
    "gn:population":0,
    "gn:timezone":"Asia/Damascus",
    "iso:country":"SY",
    "name:und_x_variant":[
        "Dalaouza",
        "Dall\u016bzah"
    ],
    "wof:name":"Dalluzah",
    "wof:placetype":"locality"
},
  "geometry": {"coordinates":[36.58217,35.69633],"type":"Point"}
}