{
  "type": "Feature",
  "properties": {
    "gn:admin1_code":"12.0",
    "gn:asciiname":"Al Muntar",
    "gn:country_code":"SY",
    "gn:dem":316,
    "gn:feature_class":"P",
    "gn:feature_code":"PPL",
    "gn:name":"Al Mun\u0163\u0101r",
    "gn:population":0,
    "gn:timezone":"Asia/Damascus",
    "iso:country":"SY",
    "name:ara_x_preferred":[
        "Mun\u0163\u0101r"
    ],
    "name:ara_x_variant":[
        "\u0645\u0646\u0637\u0627\u0631",
        "\u0627\u0644\u0645\u0646\u0637\u0627\u0631"
    ],
    "name:und_x_variant":[
        "Mount\u00e2r",
        "Al Mun\u0163\u0101r"
    ],
    "wof:name":"Al Muntar",
    "wof:placetype":"locality"
},
  "geometry": {"coordinates":[36.37314,35.76574],"type":"Point"}
}