{
  "type": "Feature",
  "properties": {
    "gn:admin1_code":"9.0",
    "gn:asciiname":"Kafr Nabw",
    "gn:country_code":"SY",
    "gn:dem":562,
    "gn:feature_class":"P",
    "gn:feature_code":"PPL",
    "gn:name":"Kafr Nabw",
    "gn:population":0,
    "gn:timezone":"Asia/Damascus",
    "iso:country":"SY",
    "name:ara_x_preferred":[
        "\u0643\u0641\u0631 \u0646\u0628\u0648"
    ],
    "name:und_x_variant":[
        "Kafer Nabou",
        "Kafer N\u00e9bo\u00fb",
        "Kafr Nabw"
    ],
    "wof:name":"Kafr Nabw",
    "wof:placetype":"locality"
},
  "geometry": {"coordinates":[36.90711,36.36055],"type":"Point"}
}