{
  "type": "Feature",
  "properties": {
    "gn:admin1_code":"5.0",
    "gn:asciiname":"Abu Zurayq",
    "gn:country_code":"SY",
    "gn:dem":1499,
    "gn:feature_class":"P",
    "gn:feature_code":"PPL",
    "gn:name":"Ab\u016b Zurayq",
    "gn:population":0,
    "gn:timezone":"Asia/Damascus",
    "iso:country":"SY",
    "name:ara_x_preferred":[
        "\u0623\u0628\u0648 \u0632\u0631\u064a\u0642"
    ],
    "name:heb_x_preferred":[
        "\u05d0\u05d1\u05d5 \u05d6\u05e8\u05d9\u05e7"
    ],
    "name:pol_x_preferred":[
        "Abu Zurajk"
    ],
    "name:und_x_variant":[
        "Abou Zre\u00efg",
        "Ab\u016b Zurayq"
    ],
    "wof:name":"Abu Zurayq",
    "wof:placetype":"locality"
},
  "geometry": {"coordinates":[36.79783,32.5894],"type":"Point"}
}