{
  "type": "Feature",
  "properties": {
    "gn:admin1_code":"0.0",
    "gn:asciiname":"Mevo Hamma",
    "gn:country_code":"SY",
    "gn:dem":348,
    "gn:feature_class":"P",
    "gn:feature_code":"STLMT",
    "gn:name":"Mevo Hamma",
    "gn:population":0,
    "gn:timezone":"Asia/Damascus",
    "iso:country":"SY",
    "wof:name":"Mevo Hamma",
    "wof:placetype":"locality"
},
  "geometry": {"coordinates":[35.65537,32.73710999999999],"type":"Point"}
}