{
  "type": "Feature",
  "properties": {
    "gn:admin1_code":"11.0",
    "gn:asciiname":"Jabburin",
    "gn:country_code":"SY",
    "gn:dem":433,
    "gn:feature_class":"P",
    "gn:feature_code":"PPL",
    "gn:name":"Jabb\u016br\u012bn",
    "gn:population":0,
    "gn:timezone":"Asia/Damascus",
    "iso:country":"SY",
    "name:ara_x_preferred":[
        "\u062c\u0628\u0648\u0631\u064a\u0646"
    ],
    "name:ara_x_variant":[
        "\u062a\u0644 \u062c\u0628\u0648\u0631\u064a\u0646"
    ],
    "name:und_x_variant":[
        "Jabb\u016br\u012bn",
        "Tall Jabb\u016br\u012bn"
    ],
    "wof:name":"Jabburin",
    "wof:placetype":"locality"
},
  "geometry": {"coordinates":[36.67315,34.84812],"type":"Point"}
}