{
  "type": "Feature",
  "properties": {
    "gn:admin1_code":"9.0",
    "gn:asciiname":"Mastur `Ashur",
    "gn:country_code":"SY",
    "gn:dem":609,
    "gn:feature_class":"P",
    "gn:feature_code":"PPL",
    "gn:name":"Mast\u016br \u2018\u0100sh\u016br",
    "gn:population":0,
    "gn:timezone":"Asia/Damascus",
    "iso:country":"SY",
    "name:ara_x_preferred":[
        "\u062d\u062c\u064a \u0642\u0627\u0633\u0645\u0644\u0644\u064a"
    ],
    "name:ara_x_variant":[
        "\u0645\u0633\u062a\u0648\u0631 \u0639\u0627\u0634\u0648\u0631",
        "\u0639\u0627\u0634\u0648\u0631"
    ],
    "name:und_x_variant":[
        "\u1e28ajj\u012b Q\u0101simill\u012b",
        "\u1e28ajj\u012b Q\u0101simlal\u012b",
        "Mast\u016br \u2018\u0100sh\u016br",
        "\u1e28ajj\u012b Q\u0101siml\u012b",
        "\u2018\u0100sh\u016br"
    ],
    "wof:name":"Mastur `Ashur",
    "wof:placetype":"locality"
},
  "geometry": {"coordinates":[36.67683,36.52727],"type":"Point"}
}